Workbook

Sheet UI KPI Map
A1: KPI ID | B1: Measure | C1: Scopes shown in UI | D1: Screens | E1: Group P06 | F1: A1 P06 | G1: A2 P06 | H1: Plant-level? | I1: Source
A2: CMP-005 | B2: Regulatory breaches YTD (same measure as REG-010) | C2: A1,Group | D2: E01 O01 | E2: 0 | F2: 0 | G2: 0 | H2: yes | I2: alias of REG-010
A3: CON-001 | B3: Contracts expiring, next 90 days | C3: A1,Group | D3: E04 E07 G07 O05 | E3: 4 | F3: 2 | G3: 2 | H3: no | I3: source model
A4: CON-002 | B4: Contract-compliance rate | C4: A1,Group | D4: E04 E07 G07 O05 | E4: 95.71 | F4: 95.83 | G4: 95.59 | H4: no | I4: source model
A5: CON-003 | B5: Supplier EHS non-compliance | C5: A1,Group | D5: E04 E07 G05 G07 O05 | E5: 0 | F5: 0 | G5: 0 | H5: no | I5: source model
A6: CPX-001 | B6: Approved capex budget | C6: A1,Group | D6: E06 G06 O04 | E6: 1860 | F6: 1000 | G6: 860 | H6: no | I6: source model
A7: CPX-002 | B7: Committed capex | C7: A1,Group | D7: E06 G06 O04 | E7: 1347.73 | F7: 722.63 | G7: 625.1 | H7: no | I7: source model
A8: CPX-003 | B8: Capex actual spend YTD | C8: A1,Group | D8: E06 G06 O04 | E8: 879.71 | F8: 468.11 | G8: 411.6 | H8: no | I8: source model
A9: CPX-004 | B9: Capex physical progress, weighted | C9: A1,Group | D9: E06 G01 G01b G06 O01 O04 X L | E9: 60.85 | F9: 59 | G9: 63 | H9: no | I9: source model
A10: CSH-001 | B10: Cash position | C10: A1,Group | D10: E05 G04 G08 G08o O03 | E10: 2141.82 | F10: 967.08 | G10: 1174.74 | H10: no | I10: source model
A11: CSH-002 | B11: Cash released YTD | C11: A1,Group | D11: E05 G04 | E11: 22.03 | F11: 4.2 | G11: 17.83 | H11: no | I11: source model
A12: CSH-003 | B12: Daily collections | C12: A1,Group | D12: E01 E05 E08 G04 S11 | E12: 76.77 | F12: 38.6 | G12: 38.17 | H12: no | I12: source model
A13: CSH-004 | B13: Cash-conversion cycle | C13: A1,Group | D13: E05 G04 | E13: 32.59 | F13: 52.3 | G13: 13.42 | H13: no | I13: source model
... A20: CTL-002 | B20: Control failures YTD | C20: A1,Group | D20: E07 G07 O05 | E20: 4 | F20: 2 | G20: 2 | H20: no | I20: source model
A21: CTL-003 | B21: Assurance reviews completed | C21: Group | D21: G07 | E21: 6 of 8 | F21: 2 of 4 | G21: 4 of 4 | H21: no | I21: source model
A22: CTL-004 | B22: High-severity control failures YTD | C22: Group | D22: G07 O05 | E22: 0 | F22: 0 | G22: 0 | H22: no | I22: source model
A23: CTL-005 | B23: Policy exceptions YTD | C23: A1,Group | D23: E07 G07 O05 | E23: 4 | F23: 2 | G23: 2 | H23: no | I23: source model
A24: CTL-006 | B24: Unauthorised-vendor usage YTD | C24: A1,Group | D24: E07 G07 O05 | E24: 0 | F24: 0 | G24: 0 | H24: no | I24: source model
A25: CTL-007 | B25: Segregation-of-duties exceptions YTD | C25: A1,Group | D25: E07 G07 O05 | E25: 1 | F25: 0 | G25: 1 | H25: no | I25: source model
A26: CTL-008 | B26: Unauthorised-access events YTD | C26: A1,Group | D26: E07 G07 O05 | E26: 0 | F26: 0 | G26: 0 | H26: no | I26: source model
A27: CTL-009 | B27: Data-sharing exceptions YTD | C27: A1,Group | D27: E07 G07 O05 | E27: 0 | F27: 0 | G27: 0 | H27: no | I27: source model
A28: CTL-010 | B28: Manual overrides YTD | C28: A1,Group | D28: E07 G07 O05 | E28: 14 | F28: 7 | G28: 7 | H28: no | I28: source model
A29: EFF-002 | B29: Open critical alerts | C29: A1,Group | D29: E01 E09 G01 G01b G02 G07 G09 O01 X L | E29: 1 | F29: 1 | G29: 0 | H29: no | I29: source model
A30: EFF-006 | B30: Alerts without accepted owners | C30: Group | D30: G09 | E30: 1 | F30: 0 | G30: 1 | H30: no | I30: source model
A31: EFF-007 | B31: Overdue actions | C31: A1,Group | D31: E01 E09 G09 | E31: 0 | F31: 0 | G31: 0 | H31: no | I31: source model
A32: EFF-008 | B32: Average resolution time | C32: A1,Group | D32: E09 G09 O06 | E32: 2.45 | F32: 2.78 | G32: 2.06 | H32: no | I32: source model
A33: EFF-009 | B33: Closed escalations, last 30 days | C33: A1,Group | D33: E09 G09 O06 | E33: 11 | F33: 3 | G33: 8 | H33: no | I33: source model
A34: EFF-010 | B34: Repeat issues, last 90 days | C34: A1,Group | D34: E09 G09 O06 | E34: 4 | F34: 3 | G34: 1 | H34: no | I34: source model
A35: EFF-011 | B35: Root causes eliminated YTD | C35: A1,Group | D35: E09 G09 O06 | E35: 8 of 9 | F35: 4 of 4 | G35: 4 of 5 | H35: no | I35: source model
A36: EHS-001 | B36: TRIR | C36: A1,Group | D36: E07 G07 G08 O05 | E36: 0.47 | F36: 0.91 | G36: 0 | H36: yes | I36: source model
A37: EHS-002 | B37: Severity incidents | C37: A1,Group | D37: E07 G01 G01b G07 O01 O05 | E37: 3 | F37: 1 | G37: 2 | H37: yes | I37: source model
A38: EHS-003 | B38: Near misses | C38: A1,Group | D38: E07 G07 O05 | E38: 41 | F38: 20 | G38: 21 | H38: yes | I38: source model
A39: EHS-004 | B39: Critical safety incidents | C39: A1,Group | D39: E07 G07 O05 | E39: 0 | F39: 0 | G39: 0 | H39: yes | I39: source model
A40: EHS-005 | B40: Environmental excursions | C40: A1,Group | D40: E07 G07 O05 | E40: 2 | F40: 1 | G40: 1 | H40: yes | I40: source model
A41: EHS-006 | B41: Open EHS corrective actions | C41: A1,Group | D41: E07 G07 | E41: 45 | F41: 28 | G41: 17 | H41: yes | I41: source model
A42: EHS-007 | B42: Overdue EHS actions | C42: A1,Group | D42: E07 G07 O05 | E42: 9 | F42: 7 | G42: 2 | H42: yes | I42: source model
A43: EHS-008 | B43: EHS escalation clocks running | C43: A1,Group | D43: E07 G07 O05 | E43: 0 | F43: 0 | G43: 0 | H43: yes | I43: source model
A44: EHS-009 | B44: EHS investigation completion | C44: A1,Group | D44: E07 G07 | E44: 75 | F44: 75 | G44: 100 | H44: yes | I44: source model
A45: EHS-010 | B45: EHS investigation completion rate YTD | C45: Group | D45: G07 | E45: 85.42 | F45: 81.82 | G45: 88.46 | H45: yes | I45: source model
A46: FIN-001 | B46: EBITDA YTD | C46: A1,Group | D46: E01 E11 G01 G01b G02 G03 G08 G08o O01 X L | E46: 1760.09 | F46: 890.55 | G46: 869.54 | H46: no | I46: source model
A47: FIN-002 | B47: EBIT YTD | C47: A1,Group | D47: E01 E11 G01 G01b G03 O01 X L | E47: 1228.14 | F47: 610.05 | G47: 618.1 | H47: no | I47: source model
... A78: PRD-003 | B78: Projected EBITDA gap, rest of year | C78: A1,Group | D78: G01 G01b G03 G10 O01 O02 S09 S12 S12e X L | E78: -56.18 | F78: -48.53 | G78: -7.65 | H78: no | I78: source model
A79: PRD-004 | B79: Projected liquidity gap, next 90 days | C79: A1,Group | D79: G01 G01b G04 O02 S12 S12e | E79: None within 90 d | F79: None within 90 d | G79: None within 90 d | H79: no | I79: source model
A80: PRD-005 | B80: Forecast covenant breach | C80: A1,Group | D80: G04 G10 O02 S12 S12e | E80: Not forecast | F80: Not forecast | G80: Not forecast | H80: no | I80: source model
A81: PRD-006 | B81: Production loss from downtime, next month | C81: Group | D81: G05 G10 | E81: 28.01 | F81: 22.3 | G81: 5.71 | H81: yes | I81: source model
A82: PRD-008 | B82: Projected FCF gap, full year | C82: A1 | D82: E11 | E82: -120.09 | F82: -101.29 | G82: -18.8 | H82: no | I82: added (synthetic inputs)
A83: PRD-009 | B83: ROCE at P12 (forecast) | C83: A1 | D83: E11 | E83: 11.26 | F83: 10.48 | G83: 12.12 | H83: no | I83: added (synthetic inputs)
A84: PRD-010 | B84: Revenue per FTE YTD | C84: A1 | D84: E11 | E84: 5.247 | F84: 5.172 | G84: 5.326 | H84: no | I84: added (synthetic inputs)
A85: PRD-011 | B85: Tonnes per FTE | C85: A1 | D85: E11 | E85: 237.7 | F85: 235 | G85: 240.6 | H85: no | I85: added (synthetic inputs)
A86: PRD-012 | B86: Probability of EBITDA plan miss, full year | C86: A1 | D86: E11 | E86: 69.39 | F86: 80.43 | G86: 44.32 | H86: no | I86: added (synthetic inputs)
A87: PRG-001 | B87: Capex project status | C87: Group | D87: G06 | E87: 9 on track · 2 at risk · 0 off track | F87: 5 on track · 1 at risk · 0 off track | G87: 4 on track · 1 at risk · 0 off track | H87: no | I87: source model
A88: PRG-002 | B88: Benefits realisation | C88: A1,Group | D88: E06 G06 O04 | E88: 47.96 | F88: 69.34 | G88: 36.27 | H88: no | I88: source model
A89: PRG-003 | B89: Delayed projects | C89: A1,Group | D89: E06 G06 | E89: 1 | F89: 0 | G89: 1 | H89: no | I89: source model
A90: PRG-004 | B90: Capex / transformation progress (same measure as STR-002) | C90: A1,Group | D90: E01 G01 G01b O01 | E90: 54.03 | F90: 53.33 | G90: 54.69 | H90: no | I90: alias of STR-002
A91: PRG-005 | B91: Transformation initiative status | C91: A1 | D91: E06 | E91: 15 on track · 6 at risk · 3 delayed | F91: 5 on track · 2 at risk · 1 delayed | G91: 10 on track · 4 at risk · 2 delayed | H91: no | I91: source model
A92: REG-001 | B92: Pending filings | C92: A1,Group | D92: E07 G07 | E92: 0 | F92: 0 | G92: 0 | H92: yes | I92: source model
A93: REG-002 | B93: Regulatory deadlines, next 30 days | C93: A1,Group | D93: E07 G07 | E93: 3 | F93: 2 | G93: 1 | H93: yes | I93: source model
A94: REG-003 | B94: Licence expirations, next 12 months | C94: A1,Group | D94: E07 G07 | E94: 1 | F94: 1 | G94: 0 | H94: yes | I94: source model
A95: REG-004 | B95: Regulatory obligations due, next 30 days | C95: A1,Group | D95: E07 G07 | E95: 2 | F95: 1 | G95: 1 | H95: yes | I95: source model
A96: REG-005 | B96: Overdue regulatory obligations | C96: A1,Group | D96: E07 G07 O05 | E96: 0 | F96: 0 | G96: 0 | H96: yes | I96: source model
A97: REG-006 | B97: Licence or permit expiry clock | C97: A1,Group | D97: E07 O05 | E97: 65 | F97: 65 | G97: 102 | H97: yes | I97: source model
A98: REG-007 | B98: Open regulatory actions | C98: A1,Group | D98: E07 G07 | E98: 0 | F98: 0 | G98: 0 | H98: yes | I98: source model
A99: REG-008 | B99: Overdue compliance actions | C99: A1,Group | D99: E07 G07 | E99: 0 | F99: 0 | G99: 0 | H99: yes | I99: source model
A100: REG-009 | B100: Disclosure-clock status | C100: Group | D100: O05 | E100: Not triggered | F100: Not triggered | G100: Not triggered | H100: yes | I100: source model
A101: REG-010 | B101: Regulatory breaches YTD | C101: A1,Group | D101: E07 G01 G01b O05 | E101: 0 | F101: 0 | G101: 0 | H101: yes | I101: source model
A102: REG-011 | B102: Disclosure clock, hours remaining | C102: A1 | D102: E07 | E102: 38 | F102: 38 | G102: 999 | H102: no | I102: added (synthetic inputs)
A103: REL-001 | B103: MTBF | C103: A1,A2,Group | D103: E03 G05 O09 | E103: 269.69 | F103: 165.35 | G103: 687.07 | H103: yes | I103: source model
A104: REL-002 | B104: Mean Time to Repair | C104: A1,A2,Group | D104: E03 G05 O09 | E104: 7.83 | F104: 8.24 | G104: 6.17 | H104: yes | I104: source model
A105: REL-003 | B105: Unplanned downtime | C105: A1,A2,Group | D105: E03 G05 O09 | E105: 154.4 | F105: 120.7 | G105: 33.7 | H105: yes | I105: source model
A106: REL-004 | B106: Production loss from downtime | C106: A1,Group | D106: E03 G05 | E106: 27176 | F106: 21684 | G106: 5492 | H106: yes | I106: source model
A107: REL-005 | B107: Preventive-maintenance compliance | C107: A1,A2 | D107: E03 O09 | E107: 95.62 | F107: 93.43 | G107: 97.81 | H107: yes | I107: source model
A108: RSK-001 | B108: Open critical alerts (same measure as EFF-002) | C108: Group | D108: X L | E108: 1 | F108: 1 | G108: 0 | H108: no | I108: alias of EFF-002
A109: RSK-002 | B109: Severity incidents (same measure as EHS-002) | C109: Group | D109: X L | E109: 3 | F109: 1 | G109: 2 | H109: yes | I109: alias of EHS-002
A110: RSK-003 | B110: Regulatory breaches YTD (same measure as REG-010) | C110: Group | D110: O01 X L | E110: 0 | F110: 0 | G110: 0 | H110: yes | I110: alias of REG-010
A111: SIG-001 | B111: Unplanned downtime (same measure as REL-003) | C111: A1,Group | D111: O02 S12 S12e | E111: 154.4 | F111: 120.7 | G111: 33.7 | H111: yes | I111: alias of REL-003
A112: SIG-002 | B112: Yield (same measure as PLT-005) | C112: A1,Group | D112: E02 S12 S12e | E112: 91.93 | F112: 91.46 | G112: 92.42 | H112: yes | I112: alias of PLT-005
... A115: SIG-005 | B115: Payment delays | C115: A1,Group | D115: E05 G04 S12 S12e | E115: 3 | F115: 2 | G115: 1 | H115: no | I115: source model
A116: SIG-006 | B116: Cash burn signal | C116: Group | D116: S12 | E116: Not triggered | F116: Not triggered | G116: Not triggered | H116: no | I116: source model
A117: SIG-007 | B117: Production at risk | C117: A1,Group,Plant02 | D117: E01 E02 E05 O02 S10 S12 S12e | E117: 36810 | F117: 30930 | G117: 5880 | H117: yes | I117: source model
A118: SIG-008 | B118: Critical plant-state alerts | C118: A1,Group | D118: E03 S12 S12e | E118: 7 | F118: 5 | G118: 2 | H118: yes | I118: source model
A119: SIG-009 | B119: Critical-material shortage risk | C119: A1,Group | D119: E01 E04 O02 S10 S12 S12e | E119: 5 | F119: 4 | G119: 1 | H119: yes | I119: source model
A120: SIG-010 | B120: Single-source supply risk | C120: A1,Group | D120: E01 E04 S12 S12e | E120: 1 | F120: 1 | G120: 0 | H120: no | I120: added (synthetic inputs)
A121: SIG-011 | B121: Capex value at risk | C121: A1,Group | D121: E06 G06 O04 S12 S12e | E121: 148.03 | F121: 20.8 | G121: 127.23 | H121: no | I121: source model
A122: SIG-012 | B122: Dispatch delays | C122: A1,Group | D122: E05 O02 S11 S12 S12e | E122: 8.66 | F122: 10.91 | G122: 6.1 | H122: yes | I122: source model
A123: SIG-013 | B123: Pricing pressure | C123: Group | D123: G03 S12 | E123: Low (-0.4% vs plan price) | F123: Low (-0.9% vs plan price) | G123: Low (0% vs plan price) | H123: yes | I123: source model
A124: SIG-014 | B124: Commodity-price movement (RM-1 index) | C124: Group | D124: G03 O02 S12 | E124: 2.13 | F124: 2.13 | G124: 2.13 | H124: no | I124: added (synthetic inputs)
A125: SIG-015 | B125: FX exposure, unhedged (same measure as TRS-001) | C125: Group | D125: G03 O02 S12 | E125: 221.72 | F125: 123.27 | G125: 98.46 | H125: no | I125: alias of TRS-001
A126: SIG-016 | B126: Freight exposure (lanes disrupted) | C126: A1,Group | D126: G03 O02 S12 S12e | E126: 1 | F126: 1 | G126: 0 | H126: no | I126: added (synthetic inputs)
A127: SIG-017 | B127: Fuel exposure (fuel cost per tonne, MoM) | C127: A1,Group | D127: G03 O02 S12 S12e | E127: -17.66 | F127: -27.67 | G127: -5.67 | H127: yes | I127: added (synthetic inputs)
A128: SIG-018 | B128: Power-cost exposure (power cost per tonne, MoM) | C128: Group | D128: G03 O02 S12 | E128: -7.14 | F128: -10.59 | G128: -3.1 | H128: yes | I128: added (synthetic inputs)
A129: SIG-019 | B129: Regulatory deadlines, next 30 days (same measure as REG-002) | C129: A1,Group | D129: O02 S12 S12e | E129: 3 | F129: 2 | G129: 1 | H129: yes | I129: alias of REG-002
A130: SIG-020 | B130: Licence expirations, next 12 months (same measure as REG-003) | C130: A1,Group | D130: O02 S12 S12e | E130: 1 | F130: 1 | G130: 0 | H130: yes | I130: alias of REG-003
A131: SIG-021 | B131: Environmental violations | C131: A1,Group | D131: E07 O02 S12 S12e | E131: 0 | F131: 0 | G131: 0 | H131: yes | I131: source model
A132: STR-001 | B132: Capex physical progress, weighted (same measure as CPX-004) | C132: Group | D132: X L | E132: 60.85 | F132: 59 | G132: 63 | H132: no | I132: alias of CPX-004
A133: STR-002 | B133: Transformation progress | C133: Group | D133: G06 O01 X L | E133: 54.03 | F133: 53.33 | G133: 54.69 | H133: no | I133: source model
A134: SUP-001 | B134: Supplier on-time delivery | C134: A1,A2,Group | D134: E04 G05 O09 | E134: 91.41 | F134: 90.39 | G134: 92.28 | H134: yes | I134: source model
A135: SUP-002 | B135: Supplier fill rate | C135: A1,A2 | D135: E04 O09 | E135: 96.82 | F135: 97.01 | G135: 96.61 | H135: yes | I135: source model
... A165: WCP-006 | B165: Working-capital days | C165: A1,Group | D165: E05 G04 | E165: 35.72 | F165: 52.23 | G165: 19.54 | H165: no | I165: source model

Sheet Calculated vs Shown
A1: KPI ID | B1: Measure | C1: Unit | D1: Formula | E1: Calculated value, Sep 2026 (P06) | F1: Shown on the mockups (Group) | G1: Same or different | H1: Screens | I1: Where the inputs come from
A2: OPS-001 | B2: Production vs plan | C2: % | D2: Good output ÷ Planned production × 100 | E2: ='Group KPIs'!K2 | F2: 95.5 % of plan | G2: Different | H2: O-01, O-09, E-01, E-02, E-05, G-01, G-02, G-03, G-05, S-03, S-10, STATE GALLERY | I2: Original plant data (plant_base.csv, synthetic)
A3: OPS-003 | B3: Capacity utilization | C3: % | D3: Good output ÷ Installed capacity × 100 | E3: ='Group KPIs'!K3 | F3: 83.4 % | G3: Different | H3: O-01, E-02, G-05, STATE GALLERY | I3: Original plant data (plant_base.csv, synthetic)
A4: PLT-001 | B4: Asset utilization | C4: % | D4: Run hours ÷ Calendar hours × 100 | E4: ='Group KPIs'!K4 | F4: Not shown | G4: Not shown | I4: Original plant data (plant_base.csv, synthetic)
A5: PLT-002 | B5: OEE | C5: % | D5: Availability × Performance × Quality = Good output ÷ Ideal output × 100 | E5: ='Group KPIs'!K5 | F5: 84.1 % | G5: Different | H5: E-02, G-05 | I5: Original plant data (plant_base.csv, synthetic)
A6: PLT-004 | B6: Recovery percentage | C6: % | D6: Valuable content recovered ÷ Valuable content in feed × 100 | E6: ='Group KPIs'!K6 | F6: Not shown | G6: Not shown | I6: Original plant data (plant_base.csv, synthetic)
A7: PLT-005 | B7: Yield | C7: % | D7: Good output ÷ Feed input × 100 | E7: ='Group KPIs'!K7 | F7: Not shown | G7: Not shown | I7: Original plant data (plant_base.csv, synthetic)
A8: REL-001 | B8: MTBF | C8: h | D8: Run hours ÷ Breakdowns | E8: ='Group KPIs'!K8 | F8: 270 h | G8: Different | H8: O-09, E-03, G-05 | I8: Original plant data (plant_base.csv, synthetic)
A9: REL-002 | B9: Mean Time to Repair | C9: h | D9: Repair hours ÷ Breakdowns | E9: ='Group KPIs'!K9 | F9: 7.8 h | G9: Different | H9: E-03, G-05 | I9: Original plant data (plant_base.csv, synthetic)
A10: REL-003 | B10: Unplanned downtime | C10: h | D10: Unplanned downtime | E10: ='Group KPIs'!K10 | F10: 3.1 % of hours | G10: Different | H10: E-03, G-05 | I10: Original plant data (plant_base.csv, synthetic)
A11: REL-004 | B11: Production loss from downtime | C11: t | D11: Production lost to downtime | E11: ='Group KPIs'!K11 | F11: 93% | G11: Different | H11: E-03,G-05 | I11: Original plant data (plant_base.csv, synthetic)
A12: REL-005 | B12: Preventive-maintenance compliance | C12: % | D12: Preventive maintenance completed ÷ Preventive maintenance scheduled × 100 | E12: ='Group KPIs'!K12 | F12: 95.6 % | G12: Different | H12: E-03 | I12: Original plant data (plant_base.csv, synthetic)
A13: CST-001 | B13: Cost per tonne | C13: ₹/t | D13: (Variable cost + Fixed cost) × 1000 ÷ Good output | E13: ='Group KPIs'!K13 | F13: 2,934 ₹/t | G13: Different | H13: O-09, E-02, E-11, G-03, G-05 | I13: Original plant data (plant_base.csv, synthetic)
A14: CST-002 | B14: Variable cost | C14: ₹ thousand | D14: Variable cost | E14: ='Group KPIs'!K14 | F14: ₹214 /t | G14: Different | H14: E-02, E-11, G-03 | I14: Original plant data (plant_base.csv, synthetic)
A15: CST-003 | B15: Fuel cost | C15: ₹ thousand | D15: Fuel cost | E15: ='Group KPIs'!K15 | F15: 9.8 ₹/t | G15: Different | H15: E-02 | I15: Original plant data (plant_base.csv, synthetic)
A16: SUS-001 | B16: Water usage | C16: m3 | D16: Water used | E16: ='Group KPIs'!K16 | F16: 3.1 m³/t | G16: Different | H16: O-05, E-02, E-07, G-05, G-07 | I16: Original plant data (plant_base.csv, synthetic)
A17: SUS-002 | B17: Emissions | C17: tCO2e | D17: Emissions | E17: ='Group KPIs'!K17 | F17: 427.7 kt CO2e | G17: Different | H17: O-05, E-02, E-07, G-05, G-07 | I17: Original plant data (plant_base.csv, synthetic)
A18: SUS-003 | B18: Energy intensity | C18: GJ/t | D18: Energy used ÷ Good output | E18: ='Group KPIs'!K18 | F18: 5.2 GJ/t | G18: Different | H18: O-05, E-02, E-07, G-05, G-07 | I18: Original plant data (plant_base.csv, synthetic)
A19: SIG-007 | B19: Production at risk | C19: t | D19: Production at risk | E19: ='Group KPIs'!K19 | F19: Not shown | G19: Not shown | I19: Original plant data (plant_base.csv, synthetic)
A20: SIG-008 | B20: Critical plant-state alerts | C20: count | D20: Critical plant alerts | E20: ='Group KPIs'!K20 | F20: Not shown | G20: Not shown | I20: Original plant data (plant_base.csv, synthetic)
A21: SIG-009 | B21: Critical-material shortage risk | C21: count | D21: Critical materials at risk | E21: ='Group KPIs'!K21 | F21: 3.5 days of cover | G21: Different | H21: E-01, E-04, S-10, S-12 | I21: Original plant data (plant_base.csv, synthetic)
A22: SIG-012 | B22: Dispatch delays | C22: % | D22: Delayed dispatches ÷ Dispatches × 100 | E22: ='Group KPIs'!K22 | F22: 2–4 days | G22: Different | H22: E-05,S-11,S-12 | I22: Original plant data (plant_base.csv, synthetic)
A23: SIG-021 | B23: Environmental violations | C23: count | D23: Environmental violations | E23: ='Group KPIs'!K23 | F23: Not shown | G23: Not shown | I23: Original plant data (plant_base.csv, synthetic)
A24: EHS-001 | B24: TRIR | C24: per 200,000 h | D24: Recordable injuries × 200,000 ÷ Hours worked | E24: ='Group KPIs'!K24 | F24: 0.42 | G24: Different | H24: E-07,G-07,O-05 | I24: Original plant data (plant_base.csv, synthetic)
A25: EHS-002 | B25: Severity incidents | C25: count | D25: Severity incidents | E25: ='Group KPIs'!K25 | F25: 0 | G25: Different | H25: E-07,G-01,G-07,O-05 | I25: Original plant data (plant_base.csv, synthetic)
A26: EHS-003 | B26: Near misses | C26: count | D26: Near misses | E26: ='Group KPIs'!K26 | F26: 14 | G26: Different | H26: E-07,G-07,O-05 | I26: Original plant data (plant_base.csv, synthetic)
A27: EHS-004 | B27: Critical safety incidents | C27: count | D27: Critical safety incidents | E27: ='Group KPIs'!K27 | F27: 0 | G27: Same | H27: E-07,G-07,O-05 | I27: Original plant data (plant_base.csv, synthetic)
A28: EHS-005 | B28: Environmental excursions | C28: count | D28: Environmental excursions | E28: ='Group KPIs'!K28 | F28: 1 (minor, closed) | G28: Different | H28: E-07,G-07,O-05 | I28: Original plant data (plant_base.csv, synthetic)
A29: EHS-006 | B29: Open EHS corrective actions | C29: count | D29: Open EHS corrective actions | E29: ='Group KPIs'!K29 | F29: 9 | G29: Different | H29: E-07,G-07 | I29: Original plant data (plant_base.csv, synthetic)
A30: EHS-007 | B30: Overdue EHS actions | C30: count | D30: Overdue EHS corrective actions | E30: ='Group KPIs'!K30 | F30: 0 | G30: Different | H30: E-07,G-07,O-05 | I30: Original plant data (plant_base.csv, synthetic)
A31: EHS-009 | B31: EHS investigation completion | C31: % | D31: EHS investigations completed ÷ EHS investigations due × 100 (100 if none due) | E31: ='Group KPIs'!K31 | F31: 100% | G31: Different | H31: E-07,G-07 | I31: Original plant data (plant_base.csv, synthetic)
A32: REG-006 | B32: Licence or permit expiry clock | C32: days | D32: Days to permit expiry (lowest plant) | E32: ='Group KPIs'!K32 | F32: 74 days · Entity C1 | G32: Different | H32: E-07,O-05 | I32: Original plant data (plant_base.csv, synthetic)
A33: OPS-005 | B33: Capacity utilisation (same measure as OPS-003) | C33: % | D33: Good output ÷ Installed capacity × 100 | E33: ='Group KPIs'!K33 | F33: 86% | G33: Different | H33: O-01, E-01, G-01 | I33: Original plant data (plant_base.csv, synthetic)
A34: OPS-006 | B34: OEE · Group weighted (same measure as PLT-002) | C34: % | D34: Good output ÷ Ideal output × 100 (weighted by output, not an average of plants) | E34: ='Group KPIs'!K34 | F34: Not on a screen | G34: — | H34: — | I34: Original plant data (plant_base.csv, synthetic)
A35: OPS-002 | B35: Sales vs plan | C35: % | D35: Sales volume ÷ Planned sales volume × 100 | E35: ='Group KPIs'!K35 | F35: 97.6% | G35: Different | H35: E-01,G-01,G-03,O-01,STATE GALLERY | I35: Synthetic inputs added for this model
... A82: SUP-002 | B82: Supplier fill rate | C82: % | D82: Quantity received ÷ Quantity ordered × 100 | E82: ='Group KPIs'!K82 | F82: Not on a screen | G82: — | H82: — | I82: Synthetic inputs added for this model
A83: SUP-003 | B83: Supplier quality-rejection rate | C83: % | D83: Quantity rejected ÷ Quantity received × 100 | E83: ='Group KPIs'!K83 | F83: Not shown | G83: Not shown | I83: Synthetic inputs added for this model
A84: SUP-004 | B84: Supplier lead-time variance | C84: % | D84: (Actual lead time − Planned lead time) ÷ Planned lead time × 100 | E84: ='Group KPIs'!K84 | F84: 38% | G84: Different | H84: E-04,G-05 | I84: Synthetic inputs added for this model
A85: SUP-005 | B85: Critical supplier exposure | C85: count | D85: Critical single-source suppliers [Month end] | E85: ='Group KPIs'!K85 | F85: 3 single-source (1 elevated: S-07) | G85: Same | H85: E-04,G-05 | I85: Synthetic inputs added for this model
A86: SUP-007 | B86: Single-source spend share | C86: % | D86: Spend with single-source suppliers ÷ Supplier spend × 100 | E86: ='Group KPIs'!K86 | F86: Not on a screen | G86: — | H86: — | I86: Synthetic inputs added for this model
A87: SUP-008 | B87: Supplier EHS incidents YTD | C87: count | D87: Sum of supplier EHS incidents since April [Year to date] | E87: ='Group KPIs'!K87 | F87: Not on a screen | G87: — | H87: — | I87: Synthetic inputs added for this model
A88: CON-001 | B88: Contracts expiring, next 90 days | C88: count | D88: Contracts expiring in next 90 days [Month end] | E88: ='Group KPIs'!K88 | F88: 4 | G88: Same | H88: E-04,E-07,G-07,O-05 | I88: Synthetic inputs added for this model
A89: CON-002 | B89: Contract-compliance rate | C89: % | D89: Contracts fully compliant ÷ Active contracts × 100 [Month end] | E89: ='Group KPIs'!K89 | F89: 96% | G89: Same | H89: E-04,E-07,G-07,O-05 | I89: Synthetic inputs added for this model
A90: CON-003 | B90: Supplier EHS non-compliance | C90: count | D90: Suppliers not meeting EHS requirements [Month end] | E90: ='Group KPIs'!K90 | F90: 1 | G90: Different | H90: E-04,E-07,G-05,G-07,O-05 | I90: Synthetic inputs added for this model
A91: REG-001 | B91: Pending filings | C91: count | D91: Regulatory filings pending [Month end] | E91: ='Group KPIs'!K91 | F91: 3 | G91: Different | H91: E-07,G-07 | I91: Synthetic inputs added for this model
A92: REG-002 | B92: Regulatory deadlines, next 30 days | C92: count | D92: Regulatory deadlines in next 30 days [Month end] | E92: ='Group KPIs'!K92 | F92: 3 | G92: Same | H92: E-07,G-07 | I92: Synthetic inputs added for this model
A93: REG-003 | B93: Licence expirations, next 12 months | C93: count | D93: Licences expiring in next 12 months [Month end] | E93: ='Group KPIs'!K93 | F93: 2 | G93: Different | H93: E-07,G-07 | I93: Synthetic inputs added for this model
A94: REG-004 | B94: Regulatory obligations due, next 30 days | C94: count | D94: Regulatory obligations due in next 30 days [Month end] | E94: ='Group KPIs'!K94 | F94: 5 | G94: Different | H94: E-07,G-07 | I94: Synthetic inputs added for this model
A95: REG-005 | B95: Overdue regulatory obligations | C95: count | D95: Regulatory obligations overdue [Month end] | E95: ='Group KPIs'!K95 | F95: 0 | G95: Same | H95: E-07,G-07,O-05 | I95: Synthetic inputs added for this model
... A150: PRD-007 | B150: Probability OEE below 78%, next month | C150: % | D150: Chance that Forecast good output < 78% × Ideal output next month (same distribution as PRD-002) [Next month] | E150: ='Group KPIs'!K150 | F150: Not on a screen | G150: — | H150: — | I150: Synthetic inputs added for this model

Sheet Group KPIs
A1: KPI ID | B1: Measure | C1: Unit | D1: Time basis | E1: How it is calculated | F1: 2026-04 (P01) | G1: 2026-05 (P02) | H1: 2026-06 (P03) | I1: 2026-07 (P04) | J1: 2026-08 (P05) | K1: 2026-09 (P06) | L1: Shown on the mockups today (Group) | M1: Screens | N1: Inputs used (Group Inputs columns)
A2: OPS-001 | B2: Production vs plan | C2: % | D2: Month | E2: Good output ÷ Planned production × 100 | F2: =ROUND(IFERROR(100*'Group Inputs'!M4/'Group Inputs'!K4,0),2) | G2: =ROUND(IFERROR(100*'Group Inputs'!M5/'Group Inputs'!K5,0),2) | H2: =ROUND(IFERROR(100*'Group Inputs'!M6/'Group Inputs'!K6,0),2) | I2: =ROUND(IFERROR(100*'Group Inputs'!M7/'Group Inputs'!K7,0),2) | J2: =ROUND(IFERROR(100*'Group Inputs'!M8/'Group Inputs'!K8,0),2) | K2: =ROUND(IFERROR(100*'Group Inputs'!M9/'Group Inputs'!K9,0),2) | L2: 98.1%; 95.5 % of plan (O-09) | M2: O-01, O-09, E-01, E-02, E-05, G-01, G-02, G-03, G-05, S-03, S-10, STATE GALLERY | N2: planned_production_t, good_output_t
A3: OPS-003 | B3: Capacity utilization | C3: % | D3: Month | E3: Good output ÷ Installed capacity × 100 | F3: =ROUND(IFERROR(100*'Group Inputs'!M4/'Group Inputs'!J4,0),2) | G3: =ROUND(IFERROR(100*'Group Inputs'!M5/'Group Inputs'!J5,0),2) | H3: =ROUND(IFERROR(100*'Group Inputs'!M6/'Group Inputs'!J6,0),2) | I3: =ROUND(IFERROR(100*'Group Inputs'!M7/'Group Inputs'!J7,0),2) | J3: =ROUND(IFERROR(100*'Group Inputs'!M8/'Group Inputs'!J8,0),2) | K3: =ROUND(IFERROR(100*'Group Inputs'!M9/'Group Inputs'!J9,0),2) | L3: 86% | M3: O-01, E-02, G-05, STATE GALLERY | N3: installed_capacity_t, good_output_t
A4: PLT-001 | B4: Asset utilization | C4: % | D4: Month | E4: Run hours ÷ Calendar hours × 100 | F4: =ROUND(IFERROR(100*'Group Inputs'!G4/'Group Inputs'!E4,0),2) | G4: =ROUND(IFERROR(100*'Group Inputs'!G5/'Group Inputs'!E5,0),2) | H4: =ROUND(IFERROR(100*'Group Inputs'!G6/'Group Inputs'!E6,0),2) | I4: =ROUND(IFERROR(100*'Group Inputs'!G7/'Group Inputs'!E7,0),2) | J4: =ROUND(IFERROR(100*'Group Inputs'!G8/'Group Inputs'!E8,0),2) | K4: =ROUND(IFERROR(100*'Group Inputs'!G9/'Group Inputs'!E9,0),2) | L4: Not shown | N4: calendar_hours, run_hours
A5: PLT-002 | B5: OEE | C5: % | D5: Month | E5: Availability × Performance × Quality = Good output ÷ Ideal output × 100 | F5: =ROUND(IFERROR(100*'Group Inputs'!M4/'Group Inputs'!I4,0),2) | G5: =ROUND(IFERROR(100*'Group Inputs'!M5/'Group Inputs'!I5,0),2) | H5: =ROUND(IFERROR(100*'Group Inputs'!M6/'Group Inputs'!I6,0),2) | I5: =ROUND(IFERROR(100*'Group Inputs'!M7/'Group Inputs'!I7,0),2) | J5: =ROUND(IFERROR(100*'Group Inputs'!M8/'Group Inputs'!I8,0),2) | K5: =ROUND(IFERROR(100*'Group Inputs'!M9/'Group Inputs'!I9,0),2) | L5: 78 % | M5: E-02, G-05 | N5: ideal_output_t, good_output_t
A6: PLT-004 | B6: Recovery percentage | C6: % | D6: Month | E6: Valuable content recovered ÷ Valuable content in feed × 100 | F6: =ROUND(IFERROR(100*'Group Inputs'!P4/'Group Inputs'!O4,0),2) | G6: =ROUND(IFERROR(100*'Group Inputs'!P5/'Group Inputs'!O5,0),2) | H6: =ROUND(IFERROR(100*'Group Inputs'!P6/'Group Inputs'!O6,0),2) | I6: =ROUND(IFERROR(100*'Group Inputs'!P7/'Group Inputs'!O7,0),2) | J6: =ROUND(IFERROR(100*'Group Inputs'!P8/'Group Inputs'!O8,0),2) | K6: =ROUND(IFERROR(100*'Group Inputs'!P9/'Group Inputs'!O9,0),2) | L6: Not shown | N6: feed_contained_t, recovered_contained_t
A7: PLT-005 | B7: Yield | C7: % | D7: Month | E7: Good output ÷ Feed input × 100 | F7: =ROUND(IFERROR(100*'Group Inputs'!M4/'Group Inputs'!N4,0),2) | G7: =ROUND(IFERROR(100*'Group Inputs'!M5/'Group Inputs'!N5,0),2) | H7: =ROUND(IFERROR(100*'Group Inputs'!M6/'Group Inputs'!N6,0),2) | I7: =ROUND(IFERROR(100*'Group Inputs'!M7/'Group Inputs'!N7,0),2) | J7: =ROUND(IFERROR(100*'Group Inputs'!M8/'Group Inputs'!N8,0),2) | K7: =ROUND(IFERROR(100*'Group Inputs'!M9/'Group Inputs'!N9,0),2) | L7: Not shown | N7: good_output_t, feed_input_t
A8: REL-001 | B8: MTBF | C8: h | D8: Month | E8: Run hours ÷ Breakdowns | F8: =ROUND(IFERROR('Group Inputs'!G4/'Group Inputs'!R4,0),2) | G8: =ROUND(IFERROR('Group Inputs'!G5/'Group Inputs'!R5,0),2) | H8: =ROUND(IFERROR('Group Inputs'!G6/'Group Inputs'!R6,0),2) | I8: =ROUND(IFERROR('Group Inputs'!G7/'Group Inputs'!R7,0),2) | J8: =ROUND(IFERROR('Group Inputs'!G8/'Group Inputs'!R8,0),2) | K8: =ROUND(IFERROR('Group Inputs'!G9/'Group Inputs'!R9,0),2) | L8: 205 h; 270 h (O-09) | M8: O-09, E-03, G-05 | N8: run_hours, failures
A9: REL-002 | B9: Mean Time to Repair | C9: h | D9: Month | E9: Repair hours ÷ Breakdowns | F9: =ROUND(IFERROR('Group Inputs'!S4/'Group Inputs'!R4,0),2) | G9: =ROUND(IFERROR('Group Inputs'!S5/'Group Inputs'!R5,0),2) | H9: =ROUND(IFERROR('Group Inputs'!S6/'Group Inputs'!R6,0),2) | I9: =ROUND(IFERROR('Group Inputs'!S7/'Group Inputs'!R7,0),2) | J9: =ROUND(IFERROR('Group Inputs'!S8/'Group Inputs'!R8,0),2) | K9: =ROUND(IFERROR('Group Inputs'!S9/'Group Inputs'!R9,0),2) | L9: 3.6 h | M9: E-03, G-05 | N9: failures, repair_hours
A10: REL-003 | B10: Unplanned downtime | C10: h | D10: Month | E10: Unplanned downtime | F10: =ROUND('Group Inputs'!H4,2) | G10: =ROUND('Group Inputs'!H5,2) | H10: =ROUND('Group Inputs'!H6,2) | I10: =ROUND('Group Inputs'!H7,2) | J10: =ROUND('Group Inputs'!H8,2) | K10: =ROUND('Group Inputs'!H9,2) | L10: 3.1 % of hours | M10: E-03, G-05 | N10: unplanned_downtime_hours
A11: REL-004 | B11: Production loss from downtime | C11: t | D11: Month | E11: Production lost to downtime | F11: =ROUND('Group Inputs'!Q4,2) | G11: =ROUND('Group Inputs'!Q5,2) | H11: =ROUND('Group Inputs'!Q6,2) | I11: =ROUND('Group Inputs'!Q7,2) | J11: =ROUND('Group Inputs'!Q8,2) | K11: =ROUND('Group Inputs'!Q9,2) | L11: 93% | M11: E-03,G-05 | N11: prod_loss_downtime_t
A12: REL-005 | B12: Preventive-maintenance compliance | C12: % | D12: Month | E12: Preventive maintenance completed ÷ Preventive maintenance scheduled × 100 | F12: =ROUND(IFERROR(100*'Group Inputs'!U4/'Group Inputs'!T4,0),2) | G12: =ROUND(IFERROR(100*'Group Inputs'!U5/'Group Inputs'!T5,0),2) | H12: =ROUND(IFERROR(100*'Group Inputs'!U6/'Group Inputs'!T6,0),2) | I12: =ROUND(IFERROR(100*'Group Inputs'!U7/'Group Inputs'!T7,0),2) | J12: =ROUND(IFERROR(100*'Group Inputs'!U8/'Group Inputs'!T8,0),2) | K12: =ROUND(IFERROR(100*'Group Inputs'!U9/'Group Inputs'!T9,0),2) | L12: 93% | M12: E-03 | N12: pm_scheduled, pm_completed
A13: CST-001 | B13: Cost per tonne | C13: ₹/t | D13: Month | E13: (Variable cost + Fixed cost) × 1000 ÷ Good output | F13: =ROUND(IFERROR(1000*('Group Inputs'!V4+'Group Inputs'!X4)/'Group Inputs'!M4,0),2) | G13: =ROUND(IFERROR(1000*('Group Inputs'!V5+'Group Inputs'!X5)/'Group Inputs'!M5,0),2) | H13: =ROUND(IFERROR(1000*('Group Inputs'!V6+'Group Inputs'!X6)/'Group Inputs'!M6,0),2) | I13: =ROUND(IFERROR(1000*('Group Inputs'!V7+'Group Inputs'!X7)/'Group Inputs'!M7,0),2) | J13: =ROUND(IFERROR(1000*('Group Inputs'!V8+'Group Inputs'!X8)/'Group Inputs'!M8,0),2) | K13: =ROUND(IFERROR(1000*('Group Inputs'!V9+'Group Inputs'!X9)/'Group Inputs'!M9,0),2) | L13: ₹412 /t; 2,934 ₹/t (O-09) | M13: O-09, E-02, E-11, G-03, G-05 | N13: good_output_t, variable_cost_k, fixed_cost_k
A14: CST-002 | B14: Variable cost | C14: ₹ thousand | D14: Month | E14: Variable cost | F14: =ROUND('Group Inputs'!V4,2) | G14: =ROUND('Group Inputs'!V5,2) | H14: =ROUND('Group Inputs'!V6,2) | I14: =ROUND('Group Inputs'!V7,2) | J14: =ROUND('Group Inputs'!V8,2) | K14: =ROUND('Group Inputs'!V9,2) | L14: ₹214 /t | M14: E-02, E-11, G-03 | N14: variable_cost_k
A15: CST-003 | B15: Fuel cost | C15: ₹ thousand | D15: Month | E15: Fuel cost | F15: =ROUND('Group Inputs'!W4,2) | G15: =ROUND('Group Inputs'!W5,2) | H15: =ROUND('Group Inputs'!W6,2) | I15: =ROUND('Group Inputs'!W7,2) | J15: =ROUND('Group Inputs'!W8,2) | K15: =ROUND('Group Inputs'!W9,2) | L15: 9.8 ₹/t | M15: E-02 | N15: fuel_cost_k
A16: SUS-001 | B16: Water usage | C16: m3 | D16: Month | E16: Water used | F16: =ROUND('Group Inputs'!Y4,2) | G16: =ROUND('Group Inputs'!Y5,2) | H16: =ROUND('Group Inputs'!Y6,2) | I16: =ROUND('Group Inputs'!Y7,2) | J16: =ROUND('Group Inputs'!Y8,2) | K16: =ROUND('Group Inputs'!Y9,2) | L16: 3.1 m³/t | M16: O-05, E-02, E-07, G-05, G-07 | N16: water_m3
A17: SUS-002 | B17: Emissions | C17: tCO2e | D17: Month | E17: Emissions | F17: =ROUND('Group Inputs'!Z4,2) | G17: =ROUND('Group Inputs'!Z5,2) | H17: =ROUND('Group Inputs'!Z6,2) | I17: =ROUND('Group Inputs'!Z7,2) | J17: =ROUND('Group Inputs'!Z8,2) | K17: =ROUND('Group Inputs'!Z9,2) | L17: 0.82 tCO2e/t | M17: O-05, E-02, E-07, G-05, G-07 | N17: emissions_tco2e
A18: SUS-003 | B18: Energy intensity | C18: GJ/t | D18: Month | E18: Energy used ÷ Good output | F18: =ROUND(IFERROR('Group Inputs'!AA4/'Group Inputs'!M4,0),2) | G18: =ROUND(IFERROR('Group Inputs'!AA5/'Group Inputs'!M5,0),2) | H18: =ROUND(IFERROR('Group Inputs'!AA6/'Group Inputs'!M6,0),2) | I18: =ROUND(IFERROR('Group Inputs'!AA7/'Group Inputs'!M7,0),2) | J18: =ROUND(IFERROR('Group Inputs'!AA8/'Group Inputs'!M8,0),2) | K18: =ROUND(IFERROR('Group Inputs'!AA9/'Group Inputs'!M9,0),2) | L18: 5.2 GJ/t | M18: O-05, E-02, E-07, G-05, G-07 | N18: good_output_t, energy_gj
A19: SIG-007 | B19: Production at risk | C19: t | D19: Month | E19: Production at risk | F19: =ROUND('Group Inputs'!AB4,2) | G19: =ROUND('Group Inputs'!AB5,2) | H19: =ROUND('Group Inputs'!AB6,2) | I19: =ROUND('Group Inputs'!AB7,2) | J19: =ROUND('Group Inputs'!AB8,2) | K19: =ROUND('Group Inputs'!AB9,2) | L19: Not shown | N19: production_at_risk_t
A20: SIG-008 | B20: Critical plant-state alerts | C20: count | D20: Month | E20: Critical plant alerts | F20: =ROUND('Group Inputs'!AC4,2) | G20: =ROUND('Group Inputs'!AC5,2) | H20: =ROUND('Group Inputs'!AC6,2) | I20: =ROUND('Group Inputs'!AC7,2) | J20: =ROUND('Group Inputs'!AC8,2) | K20: =ROUND('Group Inputs'!AC9,2) | L20: Not shown | N20: critical_plant_alerts
A21: SIG-009 | B21: Critical-material shortage risk | C21: count | D21: Month | E21: Critical materials at risk | F21: =ROUND('Group Inputs'!AO4,2) | G21: =ROUND('Group Inputs'!AO5,2) | H21: =ROUND('Group Inputs'!AO6,2) | I21: =ROUND('Group Inputs'!AO7,2) | J21: =ROUND('Group Inputs'!AO8,2) | K21: =ROUND('Group Inputs'!AO9,2) | L21: 3.5 days of cover | M21: E-01, E-04, S-10, S-12 | N21: critical_material_risks
A22: SIG-012 | B22: Dispatch delays | C22: % | D22: Month | E22: Delayed dispatches ÷ Dispatches × 100 | F22: =ROUND(IFERROR(100*'Group Inputs'!AQ4/'Group Inputs'!AP4,0),2) | G22: =ROUND(IFERROR(100*'Group Inputs'!AQ5/'Group Inputs'!AP5,0),2) | H22: =ROUND(IFERROR(100*'Group Inputs'!AQ6/'Group Inputs'!AP6,0),2) | I22: =ROUND(IFERROR(100*'Group Inputs'!AQ7/'Group Inputs'!AP7,0),2) | J22: =ROUND(IFERROR(100*'Group Inputs'!AQ8/'Group Inputs'!AP8,0),2) | K22: =ROUND(IFERROR(100*'Group Inputs'!AQ9/'Group Inputs'!AP9,0),2) | L22: 2–4 days | M22: E-05,S-11,S-12 | N22: dispatches_total, dispatches_delayed
A23: SIG-021 | B23: Environmental violations | C23: count | D23: Month | E23: Environmental violations | F23: =ROUND('Group Inputs'!AJ4,2) | G23: =ROUND('Group Inputs'!AJ5,2) | H23: =ROUND('Group Inputs'!AJ6,2) | I23: =ROUND('Group Inputs'!AJ7,2) | J23: =ROUND('Group Inputs'!AJ8,2) | K23: =ROUND('Group Inputs'!AJ9,2) | L23: Not shown | N23: env_violations
A24: EHS-001 | B24: TRIR | C24: per 200,000 h | D24: Month | E24: Recordable injuries × 200,000 ÷ Hours worked | F24: =ROUND(IFERROR(200000*'Group Inputs'!AE4/'Group Inputs'!AD4,0),2) | G24: =ROUND(IFERROR(200000*'Group Inputs'!AE5/'Group Inputs'!AD5,0),2) | H24: =ROUND(IFERROR(200000*'Group Inputs'!AE6/'Group Inputs'!AD6,0),2) | I24: =ROUND(IFERROR(200000*'Group Inputs'!AE7/'Group Inputs'!AD7,0),2) | J24: =ROUND(IFERROR(200000*'Group Inputs'!AE8/'Group Inputs'!AD8,0),2) | K24: =ROUND(IFERROR(200000*'Group Inputs'!AE9/'Group Inputs'!AD9,0),2) | L24: 0.42 | M24: E-07,G-07,O-05 | N24: hours_worked, recordable_injuries
A25: EHS-002 | B25: Severity incidents | C25: count | D25: Month | E25: Severity incidents | F25: =ROUND('Group Inputs'!AF4,2) | G25: =ROUND('Group Inputs'!AF5,2) | H25: =ROUND('Group Inputs'!AF6,2) | I25: =ROUND('Group Inputs'!AF7,2) | J25: =ROUND('Group Inputs'!AF8,2) | K25: =ROUND('Group Inputs'!AF9,2) | L25: 0 | M25: E-07,G-01,G-07,O-05 | N25: severity_incidents
A26: EHS-003 | B26: Near misses | C26: count | D26: Month | E26: Near misses | F26: =ROUND('Group Inputs'!AG4,2) | G26: =ROUND('Group Inputs'!AG5,2) | H26: =ROUND('Group Inputs'!AG6,2) | I26: =ROUND('Group Inputs'!AG7,2) | J26: =ROUND('Group Inputs'!AG8,2) | K26: =ROUND('Group Inputs'!AG9,2) | L26: 14 | M26: E-07,G-07,O-05 | N26: near_misses
A27: EHS-004 | B27: Critical safety incidents | C27: count | D27: Month | E27: Critical safety incidents | F27: =ROUND('Group Inputs'!AH4,2) | G27: =ROUND('Group Inputs'!AH5,2) | H27: =ROUND('Group Inputs'!AH6,2) | I27: =ROUND('Group Inputs'!AH7,2) | J27: =ROUND('Group Inputs'!AH8,2) | K27: =ROUND('Group Inputs'!AH9,2) | L27: 0 | M27: E-07,G-07,O-05 | N27: critical_safety_incidents
A28: EHS-005 | B28: Environmental excursions | C28: count | D28: Month | E28: Environmental excursions | F28: =ROUND('Group Inputs'!AI4,2) | G28: =ROUND('Group Inputs'!AI5,2) | H28: =ROUND('Group Inputs'!AI6,2) | I28: =ROUND('Group Inputs'!AI7,2) | J28: =ROUND('Group Inputs'!AI8,2) | K28: =ROUND('Group Inputs'!AI9,2) | L28: 1 (minor, closed) | M28: E-07,G-07,O-05 | N28: env_excursions
A29: EHS-006 | B29: Open EHS corrective actions | C29: count | D29: Month | E29: Open EHS corrective actions | F29: =ROUND('Group Inputs'!AK4,2) | G29: =ROUND('Group Inputs'!AK5,2) | H29: =ROUND('Group Inputs'!AK6,2) | I29: =ROUND('Group Inputs'!AK7,2) | J29: =ROUND('Group Inputs'!AK8,2) | K29: =ROUND('Group Inputs'!AK9,2) | L29: 9 | M29: E-07,G-07 | N29: ehs_ca_open
A30: EHS-007 | B30: Overdue EHS actions | C30: count | D30: Month | E30: Overdue EHS corrective actions | F30: =ROUND('Group Inputs'!AL4,2) | G30: =ROUND('Group Inputs'!AL5,2) | H30: =ROUND('Group Inputs'!AL6,2) | I30: =ROUND('Group Inputs'!AL7,2) | J30: =ROUND('Group Inputs'!AL8,2) | K30: =ROUND('Group Inputs'!AL9,2) | L30: 0 | M30: E-07,G-07,O-05 | N30: ehs_ca_overdue
A31: EHS-009 | B31: EHS investigation completion | C31: % | D31: Month | E31: EHS investigations completed ÷ EHS investigations due × 100 (100 if none due) | F31: =ROUND(IF('Group Inputs'!AM4=0,100,100*'Group Inputs'!AN4/'Group Inputs'!AM4),2) | G31: =ROUND(IF('Group Inputs'!AM5=0,100,100*'Group Inputs'!AN5/'Group Inputs'!AM5),2) | H31: =ROUND(IF('Group Inputs'!AM6=0,100,100*'Group Inputs'!AN6/'Group Inputs'!AM6),2) | I31: =ROUND(IF('Group Inputs'!AM7=0,100,100*'Group Inputs'!AN7/'Group Inputs'!AM7),2) | J31: =ROUND(IF('Group Inputs'!AM8=0,100,100*'Group Inputs'!AN8/'Group Inputs'!AM8),2) | K31: =ROUND(IF('Group Inputs'!AM9=0,100,100*'Group Inputs'!AN9/'Group Inputs'!AM9),2) | L31: 100% | M31: E-07,G-07 | N31: investigations_due, investigations_completed
A32: REG-006 | B32: Licence or permit expiry clock | C32: days | D32: Month | E32: Days to permit expiry (lowest plant) | F32: =ROUND('Group Inputs'!AR4,2) | G32: =ROUND('Group Inputs'!AR5,2) | H32: =ROUND('Group Inputs'!AR6,2) | I32: =ROUND('Group Inputs'!AR7,2) | J32: =ROUND('Group Inputs'!AR8,2) | K32: =ROUND('Group Inputs'!AR9,2) | L32: 74 days · Entity C1 | M32: E-07,O-05 | N32: permit_days_to_expiry
A33: OPS-005 | B33: Capacity utilisation (same measure as OPS-003) | C33: % | D33: Month | E33: Good output ÷ Installed capacity × 100 | F33: =ROUND(IFERROR(100*'Group Inputs'!M4/'Group Inputs'!J4,0),2) | G33: =ROUND(IFERROR(100*'Group Inputs'!M5/'Group Inputs'!J5,0),2) | H33: =ROUND(IFERROR(100*'Group Inputs'!M6/'Group Inputs'!J6,0),2) | I33: =ROUND(IFERROR(100*'Group Inputs'!M7/'Group Inputs'!J7,0),2) | J33: =ROUND(IFERROR(100*'Group Inputs'!M8/'Group Inputs'!J8,0),2) | K33: =ROUND(IFERROR(100*'Group Inputs'!M9/'Group Inputs'!J9,0),2) | L33: 86% | M33: O-01, E-01, G-01 | N33: installed_capacity_t, good_output_t
A34: OPS-006 | B34: OEE · Group weighted (same measure as PLT-002) | C34: % | D34: Month | E34: Good output ÷ Ideal output × 100 (weighted by output, not an average of plants) | F34: =ROUND(IFERROR(100*'Group Inputs'!M4/'Group Inputs'!I4,0),2) | G34: =ROUND(IFERROR(100*'Group Inputs'!M5/'Group Inputs'!I5,0),2) | H34: =ROUND(IFERROR(100*'Group Inputs'!M6/'Group Inputs'!I6,0),2) | I34: =ROUND(IFERROR(100*'Group Inputs'!M7/'Group Inputs'!I7,0),2) | J34: =ROUND(IFERROR(100*'Group Inputs'!M8/'Group Inputs'!I8,0),2) | K34: =ROUND(IFERROR(100*'Group Inputs'!M9/'Group Inputs'!I9,0),2) | L34: 78.4 % | M34: — | N34: ideal_output_t, good_output_t
A35: OPS-002 | B35: Sales vs plan | C35: % | D35: Month | E35: Sales volume ÷ Planned sales volume × 100 | F35: =ROUND(IF('Group Inputs'!AT4=0,0,100*'Group Inputs'!AS4/'Group Inputs'!AT4),2) | G35: =ROUND(IF('Group Inputs'!AT5=0,0,100*'Group Inputs'!AS5/'Group Inputs'!AT5),2) | H35: =ROUND(IF('Group Inputs'!AT6=0,0,100*'Group Inputs'!AS6/'Group Inputs'!AT6),2) | I35: =ROUND(IF('Group Inputs'!AT7=0,0,100*'Group Inputs'!AS7/'Group Inputs'!AT7),2) | J35: =ROUND(IF('Group Inputs'!AT8=0,0,100*'Group Inputs'!AS8/'Group Inputs'!AT8),2) | K35: =ROUND(IF('Group Inputs'!AT9=0,0,100*'Group Inputs'!AS9/'Group Inputs'!AT9),2) | L35: 97.6% | M35: E-01,G-01,G-03,O-01,STATE GALLERY | N35: sales_t, planned_sales_t
A36: OPS-004 | B36: Sales vs plan · Group (same measure as OPS-002) | C36: % | D36: Month | E36: Sales volume ÷ Planned sales volume × 100 | F36: =ROUND(IF('Group Inputs'!AT4=0,0,100*'Group Inputs'!AS4/'Group Inputs'!AT4),2) | G36: =ROUND(IF('Group Inputs'!AT5=0,0,100*'Group Inputs'!AS5/'Group Inputs'!AT5),2) | H36: =ROUND(IF('Group Inputs'!AT6=0,0,100*'Group Inputs'!AS6/'Group Inputs'!AT6),2) | I36: =ROUND(IF('Group Inputs'!AT7=0,0,100*'Group Inputs'!AS7/'Group Inputs'!AT7),2) | J36: =ROUND(IF('Group Inputs'!AT8=0,0,100*'Group Inputs'!AS8/'Group Inputs'!AT8),2) | K36: =ROUND(IF('Group Inputs'!AT9=0,0,100*'Group Inputs'!AS9/'Group Inputs'!AT9),2) | L36: 97.6% | M36: O-01 | N36: sales_t, planned_sales_t
A37: CST-004 | B37: Power cost per tonne | C37: ₹/t | D37: Month | E37: Power cost × 1000 ÷ Good output | F37: =ROUND(IF('Group Inputs'!M4=0,0,1000*'Group Inputs'!AW4/'Group Inputs'!M4),2) | G37: =ROUND(IF('Group Inputs'!M5=0,0,1000*'Group Inputs'!AW5/'Group Inputs'!M5),2) | H37: =ROUND(IF('Group Inputs'!M6=0,0,1000*'Group Inputs'!AW6/'Group Inputs'!M6),2) | I37: =ROUND(IF('Group Inputs'!M7=0,0,1000*'Group Inputs'!AW7/'Group Inputs'!M7),2) | J37: =ROUND(IF('Group Inputs'!M8=0,0,1000*'Group Inputs'!AW8/'Group Inputs'!M8),2) | K37: =ROUND(IF('Group Inputs'!M9=0,0,1000*'Group Inputs'!AW9/'Group Inputs'!M9),2) | L37: 6.1 ₹/t; 174 ₹/t (O-09) | M37: O-09 | N37: good_output_t, power_cost_k
A38: FIN-001 | B38: EBITDA YTD | C38: ₹ m | D38: Year to date | E38: Sum of monthly EBITDA since April ÷ 1000 | F38: =ROUND(SUM('Group Inputs'!FV$4:FV4)/1000,2) | G38: =ROUND(SUM('Group Inputs'!FV$4:FV5)/1000,2) | H38: =ROUND(SUM('Group Inputs'!FV$4:FV6)/1000,2) | I38: =ROUND(SUM('Group Inputs'!FV$4:FV7)/1000,2) | J38: =ROUND(SUM('Group Inputs'!FV$4:FV8)/1000,2) | K38: =ROUND(SUM('Group Inputs'!FV$4:FV9)/1000,2) | L38: 361.3 ₹ m | M38: E-01,E-11,G-01,G-02,G-03,O-01,STATE GALLERY | N38: ebitda_k
A39: FIN-002 | B39: EBIT YTD | C39: ₹ m | D39: Year to date | E39: Sum of monthly EBIT since April ÷ 1000 | F39: =ROUND(SUM('Group Inputs'!FW$4:FW4)/1000,2) | G39: =ROUND(SUM('Group Inputs'!FW$4:FW5)/1000,2) | H39: =ROUND(SUM('Group Inputs'!FW$4:FW6)/1000,2) | I39: =ROUND(SUM('Group Inputs'!FW$4:FW7)/1000,2) | J39: =ROUND(SUM('Group Inputs'!FW$4:FW8)/1000,2) | K39: =ROUND(SUM('Group Inputs'!FW$4:FW9)/1000,2) | L39: 238.4 ₹ m | M39: E-01,E-11,G-01,G-03,O-01,STATE GALLERY | N39: ebit_k
A40: FIN-003 | B40: Revenue YTD | C40: ₹ m | D40: Year to date | E40: Sum of monthly Revenue since April ÷ 1000 | F40: =ROUND(SUM('Group Inputs'!AU$4:AU4)/1000,2) | G40: =ROUND(SUM('Group Inputs'!AU$4:AU5)/1000,2) | H40: =ROUND(SUM('Group Inputs'!AU$4:AU6)/1000,2) | I40: =ROUND(SUM('Group Inputs'!AU$4:AU7)/1000,2) | J40: =ROUND(SUM('Group Inputs'!AU$4:AU8)/1000,2) | K40: =ROUND(SUM('Group Inputs'!AU$4:AU9)/1000,2) | L40: 2,410 ₹ m | M40: E-01,E-11,G-01,G-02,G-03,O-01,STATE GALLERY | N40: revenue_k
A41: FIN-004 | B41: Free cash flow YTD | C41: ₹ m | D41: Year to date | E41: Sum of monthly Free cash flow since April ÷ 1000 | F41: =ROUND(SUM('Group Inputs'!GA$4:GA4)/1000,2) | G41: =ROUND(SUM('Group Inputs'!GA$4:GA5)/1000,2) | H41: =ROUND(SUM('Group Inputs'!GA$4:GA6)/1000,2) | I41: =ROUND(SUM('Group Inputs'!GA$4:GA7)/1000,2) | J41: =ROUND(SUM('Group Inputs'!GA$4:GA8)/1000,2) | K41: =ROUND(SUM('Group Inputs'!GA$4:GA9)/1000,2) | L41: 96.4 ₹ m | M41: O-01, E-01, E-11, G-01, G-03, STATE GALLERY | N41: fcf_k
A42: FIN-005 | B42: ROCE, annualised | C42: % | D42: Year to date | E42: EBIT since April × 12 ÷ months elapsed ÷ Capital employed × 100 | F42: =ROUND(IF('Group Inputs'!CA4=0,0,100*SUM('Group Inputs'!FW$4:FW4)*12/'Group Inputs'!D4/'Group Inputs'!CA4),2) | G42: =ROUND(IF('Group Inputs'!CA5=0,0,100*SUM('Group Inputs'!FW$4:FW5)*12/'Group Inputs'!D5/'Group Inputs'!CA5),2) | H42: =ROUND(IF('Group Inputs'!CA6=0,0,100*SUM('Group Inputs'!FW$4:FW6)*12/'Group Inputs'!D6/'Group Inputs'!CA6),2) | I42: =ROUND(IF('Group Inputs'!CA7=0,0,100*SUM('Group Inputs'!FW$4:FW7)*12/'Group Inputs'!D7/'Group Inputs'!CA7),2) | J42: =ROUND(IF('Group Inputs'!CA8=0,0,100*SUM('Group Inputs'!FW$4:FW8)*12/'Group Inputs'!D8/'Group Inputs'!CA8),2) | K42: =ROUND(IF('Group Inputs'!CA9=0,0,100*SUM('Group Inputs'!FW$4:FW9)*12/'Group Inputs'!D9/'Group Inputs'!CA9),2) | L42: 11.8% | M42: E-01,E-11,G-01,G-03,O-01,STATE GALLERY | N42: ytd_months, capital_employed_k, ebit_k
A43: FIN-006 | B43: Net debt | C43: ₹ m | D43: Month end | E43: (Gross debt − Cash) ÷ 1000 | F43: =ROUND('Group Inputs'!GB4/1000,2) | G43: =ROUND('Group Inputs'!GB5/1000,2) | H43: =ROUND('Group Inputs'!GB6/1000,2) | I43: =ROUND('Group Inputs'!GB7/1000,2) | J43: =ROUND('Group Inputs'!GB8/1000,2) | K43: =ROUND('Group Inputs'!GB9/1000,2) | L43: 1,140 ₹ m; 6,650.0 ₹ m (O-03) | M43: O-01, O-03, G-01, G-03, STATE GALLERY | N43: net_debt_k
A44: FIN-007 | B44: Shareholder-value indicator (economic profit YTD) | C44: ₹ m | D44: Year to date | E44: (EBIT since April × (1 − Tax rate) − Capital employed × Cost of capital × months elapsed ÷ 12) ÷ 1000 | F44: =ROUND((SUM('Group Inputs'!FW$4:FW4)*(1-Parameters!$B$2)-'Group Inputs'!CA4*Parameters!$B$3*'Group Inputs'!D4/12)/1000,2) | G44: =ROUND((SUM('Group Inputs'!FW$4:FW5)*(1-Parameters!$B$2)-'Group Inputs'!CA5*Parameters!$B$3*'Group Inputs'!D5/12)/1000,2) | H44: =ROUND((SUM('Group Inputs'!FW$4:FW6)*(1-Parameters!$B$2)-'Group Inputs'!CA6*Parameters!$B$3*'Group Inputs'!D6/12)/1000,2) | I44: =ROUND((SUM('Group Inputs'!FW$4:FW7)*(1-Parameters!$B$2)-'Group Inputs'!CA7*Parameters!$B$3*'Group Inputs'!D7/12)/1000,2) | J44: =ROUND((SUM('Group Inputs'!FW$4:FW8)*(1-Parameters!$B$2)-'Group Inputs'!CA8*Parameters!$B$3*'Group Inputs'!D8/12)/1000,2) | K44: =ROUND((SUM('Group Inputs'!FW$4:FW9)*(1-Parameters!$B$2)-'Group Inputs'!CA9*Parameters!$B$3*'Group Inputs'!D9/12)/1000,2) | L44: [PLACEHOLDER] | M44: G-03,O-01,STATE GALLERY | N44: ytd_months, capital_employed_k, ebit_k
A45: FIN-008 | B45: FCF conversion (FCF ÷ EBITDA) | C45: % | D45: Year to date | E45: Free cash flow since April ÷ EBITDA since April × 100 | F45: =ROUND(IF(SUM('Group Inputs'!FV$4:FV4)=0,0,100*SUM('Group Inputs'!GA$4:GA4)/SUM('Group Inputs'!FV$4:FV4)),2) | G45: =ROUND(IF(SUM('Group Inputs'!FV$4:FV5)=0,0,100*SUM('Group Inputs'!GA$4:GA5)/SUM('Group Inputs'!FV$4:FV5)),2) | H45: =ROUND(IF(SUM('Group Inputs'!FV$4:FV6)=0,0,100*SUM('Group Inputs'!GA$4:GA6)/SUM('Group Inputs'!FV$4:FV6)),2) | I45: =ROUND(IF(SUM('Group Inputs'!FV$4:FV7)=0,0,100*SUM('Group Inputs'!GA$4:GA7)/SUM('Group Inputs'!FV$4:FV7)),2) | J45: =ROUND(IF(SUM('Group Inputs'!FV$4:FV8)=0,0,100*SUM('Group Inputs'!GA$4:GA8)/SUM('Group Inputs'!FV$4:FV8)),2) | K45: =ROUND(IF(SUM('Group Inputs'!FV$4:FV9)=0,0,100*SUM('Group Inputs'!GA$4:GA9)/SUM('Group Inputs'!FV$4:FV9)),2) | L45: 27% | M45: G-03 | N45: ebitda_k, fcf_k
A46: CSH-001 | B46: Cash position | C46: ₹ m | D46: Month end | E46: Cash ÷ 1000 | F46: =ROUND('Group Inputs'!CC4/1000,2) | G46: =ROUND('Group Inputs'!CC5/1000,2) | H46: =ROUND('Group Inputs'!CC6/1000,2) | I46: =ROUND('Group Inputs'!CC7/1000,2) | J46: =ROUND('Group Inputs'!CC8/1000,2) | K46: =ROUND('Group Inputs'!CC9/1000,2) | L46: 384 ₹ m; 2,141.8 ₹ m (O-03) | M46: O-03, E-05, G-04 | N46: cash_k
A47: CSH-002 | B47: Cash released YTD | C47: ₹ m | D47: Year to date | E47: Sum of cash released since April ÷ 1000 | F47: =ROUND(SUM('Group Inputs'!CN$4:CN4)/1000,2) | G47: =ROUND(SUM('Group Inputs'!CN$4:CN5)/1000,2) | H47: =ROUND(SUM('Group Inputs'!CN$4:CN6)/1000,2) | I47: =ROUND(SUM('Group Inputs'!CN$4:CN7)/1000,2) | J47: =ROUND(SUM('Group Inputs'!CN$4:CN8)/1000,2) | K47: =ROUND(SUM('Group Inputs'!CN$4:CN9)/1000,2) | L47: ₹21 m | M47: E-05, G-04 | N47: cash_released_k
A48: CSH-003 | B48: Daily collections | C48: ₹ m per day | D48: Month | E48: Cash collected ÷ Days in month ÷ 1000 | F48: =ROUND('Group Inputs'!CM4/'Group Inputs'!C4/1000,2) | G48: =ROUND('Group Inputs'!CM5/'Group Inputs'!C5/1000,2) | H48: =ROUND('Group Inputs'!CM6/'Group Inputs'!C6/1000,2) | I48: =ROUND('Group Inputs'!CM7/'Group Inputs'!C7/1000,2) | J48: =ROUND('Group Inputs'!CM8/'Group Inputs'!C8/1000,2) | K48: =ROUND('Group Inputs'!CM9/'Group Inputs'!C9/1000,2) | L48: ₹18.6 m | M48: E-01, E-05, G-04, S-11 | N48: days, collections_k
A49: CSH-004 | B49: Cash-conversion cycle | C49: days | D49: Month end | E49: DSO + Inventory days − DPO | F49: =ROUND('Group Inputs'!GD4+'Group Inputs'!GF4-'Group Inputs'!GE4,2) | G49: =ROUND('Group Inputs'!GD5+'Group Inputs'!GF5-'Group Inputs'!GE5,2) | H49: =ROUND('Group Inputs'!GD6+'Group Inputs'!GF6-'Group Inputs'!GE6,2) | I49: =ROUND('Group Inputs'!GD7+'Group Inputs'!GF7-'Group Inputs'!GE7,2) | J49: =ROUND('Group Inputs'!GD8+'Group Inputs'!GF8-'Group Inputs'!GE8,2) | K49: =ROUND('Group Inputs'!GD9+'Group Inputs'!GF9-'Group Inputs'!GE9,2) | L49: 33 d | M49: E-05, G-04 | N49: dso_d, dpo_d, dio_d
A50: CSH-006 | B50: Cash-upstream exposure | C50: ₹ m | D50: Next 30 days | E50: (Cash due to be upstreamed − Amount covered by available cash) ÷ 1000 | F50: =ROUND(('Group Inputs'!CO4-'Group Inputs'!CP4)/1000,2) | G50: =ROUND(('Group Inputs'!CO5-'Group Inputs'!CP5)/1000,2) | H50: =ROUND(('Group Inputs'!CO6-'Group Inputs'!CP6)/1000,2) | I50: =ROUND(('Group Inputs'!CO7-'Group Inputs'!CP7)/1000,2) | J50: =ROUND(('Group Inputs'!CO8-'Group Inputs'!CP8)/1000,2) | K50: =ROUND(('Group Inputs'!CO9-'Group Inputs'!CP9)/1000,2) | L50: 26 ₹ m; 27.2 ₹ m (O-03) | M50: O-03, E-01, E-05, G-04, S-11 | N50: upstream_due_k, upstream_covered_k
A51: WCP-001 | B51: DSO | C51: days | D51: Month end | E51: Trade receivables ÷ Revenue × Days in month | F51: =ROUND('Group Inputs'!GD4,2) | G51: =ROUND('Group Inputs'!GD5,2) | H51: =ROUND('Group Inputs'!GD6,2) | I51: =ROUND('Group Inputs'!GD7,2) | J51: =ROUND('Group Inputs'!GD8,2) | K51: =ROUND('Group Inputs'!GD9,2) | L51: 47 d; 47.0 days (O-03) | M51: O-03, E-01, E-05, G-02, G-04, S-11 | N51: dso_d
A52: WCP-002 | B52: DPO | C52: days | D52: Month end | E52: Trade payables ÷ Variable cost × Days in month | F52: =ROUND('Group Inputs'!GE4,2) | G52: =ROUND('Group Inputs'!GE5,2) | H52: =ROUND('Group Inputs'!GE6,2) | I52: =ROUND('Group Inputs'!GE7,2) | J52: =ROUND('Group Inputs'!GE8,2) | K52: =ROUND('Group Inputs'!GE9,2) | L52: 52 d | M52: E-05, G-04 | N52: dpo_d
A53: WCP-003 | B53: Inventory days | C53: days | D53: Month end | E53: Inventory ÷ Variable cost × Days in month | F53: =ROUND('Group Inputs'!GF4,2) | G53: =ROUND('Group Inputs'!GF5,2) | H53: =ROUND('Group Inputs'!GF6,2) | I53: =ROUND('Group Inputs'!GF7,2) | J53: =ROUND('Group Inputs'!GF8,2) | K53: =ROUND('Group Inputs'!GF9,2) | L53: 38 d | M53: E-05, G-04 | N53: dio_d
A54: WCP-004 | B54: Net working capital | C54: ₹ m | D54: Month end | E54: (Trade receivables + Inventory − Trade payables) ÷ 1000 | F54: =ROUND('Group Inputs'!FX4/1000,2) | G54: =ROUND('Group Inputs'!FX5/1000,2) | H54: =ROUND('Group Inputs'!FX6/1000,2) | I54: =ROUND('Group Inputs'!FX7/1000,2) | J54: =ROUND('Group Inputs'!FX8/1000,2) | K54: =ROUND('Group Inputs'!FX9/1000,2) | L54: 512 ₹ m; 2,781.0 ₹ m (O-03) | M54: O-03, E-05, G-04 | N54: nwc_k
A55: WCP-005 | B55: Working-capital movement | C55: ₹ m | D55: Month | E55: (Net working capital − last month's net working capital) ÷ 1000; positive = cash tied up | F55: =ROUND('Group Inputs'!FY4/1000,2) | G55: =ROUND('Group Inputs'!FY5/1000,2) | H55: =ROUND('Group Inputs'!FY6/1000,2) | I55: =ROUND('Group Inputs'!FY7/1000,2) | J55: =ROUND('Group Inputs'!FY8/1000,2) | K55: =ROUND('Group Inputs'!FY9/1000,2) | L55: +₹14 m | M55: E-05, G-04 | N55: nwc_change_k
A56: WCP-006 | B56: Working-capital days | C56: days | D56: Month end | E56: Net working capital ÷ Revenue × Days in month | F56: =ROUND(IF('Group Inputs'!AU4=0,0,'Group Inputs'!FX4/'Group Inputs'!AU4*'Group Inputs'!C4),2) | G56: =ROUND(IF('Group Inputs'!AU5=0,0,'Group Inputs'!FX5/'Group Inputs'!AU5*'Group Inputs'!C5),2) | H56: =ROUND(IF('Group Inputs'!AU6=0,0,'Group Inputs'!FX6/'Group Inputs'!AU6*'Group Inputs'!C6),2) | I56: =ROUND(IF('Group Inputs'!AU7=0,0,'Group Inputs'!FX7/'Group Inputs'!AU7*'Group Inputs'!C7),2) | J56: =ROUND(IF('Group Inputs'!AU8=0,0,'Group Inputs'!FX8/'Group Inputs'!AU8*'Group Inputs'!C8),2) | K56: =ROUND(IF('Group Inputs'!AU9=0,0,'Group Inputs'!FX9/'Group Inputs'!AU9*'Group Inputs'!C9),2) | L56: 33 | M56: E-05, G-04 | N56: days, revenue_k, nwc_k
A57: LIQ-001 | B57: Liquidity runway | C57: months | D57: Month end | E57: (Cash + Undrawn facilities) ÷ (Fixed cost + Overheads + Debt service) per month | F57: =ROUND(IF(('Group Inputs'!X4+'Group Inputs'!BY4+'Group Inputs'!CE4)=0,0,('Group Inputs'!CC4+'Group Inputs'!CD4)/('Group Inputs'!X4+'Group Inputs'!BY4+'Group Inputs'!CE4)),2) | G57: =ROUND(IF(('Group Inputs'!X5+'Group Inputs'!BY5+'Group Inputs'!CE5)=0,0,('Group Inputs'!CC5+'Group Inputs'!CD5)/('Group Inputs'!X5+'Group Inputs'!BY5+'Group Inputs'!CE5)),2) | H57: =ROUND(IF(('Group Inputs'!X6+'Group Inputs'!BY6+'Group Inputs'!CE6)=0,0,('Group Inputs'!CC6+'Group Inputs'!CD6)/('Group Inputs'!X6+'Group Inputs'!BY6+'Group Inputs'!CE6)),2) | I57: =ROUND(IF(('Group Inputs'!X7+'Group Inputs'!BY7+'Group Inputs'!CE7)=0,0,('Group Inputs'!CC7+'Group Inputs'!CD7)/('Group Inputs'!X7+'Group Inputs'!BY7+'Group Inputs'!CE7)),2) | J57: =ROUND(IF(('Group Inputs'!X8+'Group Inputs'!BY8+'Group Inputs'!CE8)=0,0,('Group Inputs'!CC8+'Group Inputs'!CD8)/('Group Inputs'!X8+'Group Inputs'!BY8+'Group Inputs'!CE8)),2) | K57: =ROUND(IF(('Group Inputs'!X9+'Group Inputs'!BY9+'Group Inputs'!CE9)=0,0,('Group Inputs'!CC9+'Group Inputs'!CD9)/('Group Inputs'!X9+'Group Inputs'!BY9+'Group Inputs'!CE9)),2) | L57: 14.2 months; 16.7 months (O-03) | M57: O-03, E-05, G-04 | N57: fixed_cost_k, overhead_k, cash_k, undrawn_facilities_k, debt_service_k
A58: LIQ-002 | B58: Covenant headroom | C58: % | D58: Month end | E58: (Covenant limit − Net debt ÷ Annualised EBITDA) ÷ Covenant limit × 100 | F58: =ROUND(IF('Group Inputs'!GC4=0,0,100*(Parameters!$B$4-'Group Inputs'!GB4/'Group Inputs'!GC4)/Parameters!$B$4),2) | G58: =ROUND(IF('Group Inputs'!GC5=0,0,100*(Parameters!$B$4-'Group Inputs'!GB5/'Group Inputs'!GC5)/Parameters!$B$4),2) | H58: =ROUND(IF('Group Inputs'!GC6=0,0,100*(Parameters!$B$4-'Group Inputs'!GB6/'Group Inputs'!GC6)/Parameters!$B$4),2) | I58: =ROUND(IF('Group Inputs'!GC7=0,0,100*(Parameters!$B$4-'Group Inputs'!GB7/'Group Inputs'!GC7)/Parameters!$B$4),2) | J58: =ROUND(IF('Group Inputs'!GC8=0,0,100*(Parameters!$B$4-'Group Inputs'!GB8/'Group Inputs'!GC8)/Parameters!$B$4),2) | K58: =ROUND(IF('Group Inputs'!GC9=0,0,100*(Parameters!$B$4-'Group Inputs'!GB9/'Group Inputs'!GC9)/Parameters!$B$4),2) | L58: 22 % [TERMS — PH] | M58: E-05, G-04 | N58: net_debt_k, ebitda_annualised_k
A59: LIQ-003 | B59: Debt-maturity exposure, next 12 months | C59: ₹ m | D59: Month end | E59: Debt maturing in next 12 months ÷ 1000 | F59: =ROUND('Group Inputs'!CF4/1000,2) | G59: =ROUND('Group Inputs'!CF5/1000,2) | H59: =ROUND('Group Inputs'!CF6/1000,2) | I59: =ROUND('Group Inputs'!CF7/1000,2) | J59: =ROUND('Group Inputs'!CF8/1000,2) | K59: =ROUND('Group Inputs'!CF9/1000,2) | L59: ₹120 m; 891.4 ₹ m (O-03) | M59: O-03, E-05, G-04 | N59: debt_maturing_12m_k
A60: LIQ-004 | B60: Financing exposure (floating-rate debt) | C60: ₹ m | D60: Month end | E60: Floating-rate debt ÷ 1000 | F60: =ROUND('Group Inputs'!CG4/1000,2) | G60: =ROUND('Group Inputs'!CG5/1000,2) | H60: =ROUND('Group Inputs'!CG6/1000,2) | I60: =ROUND('Group Inputs'!CG7/1000,2) | J60: =ROUND('Group Inputs'!CG8/1000,2) | K60: =ROUND('Group Inputs'!CG9/1000,2) | L60: ₹310 m; 2,720.8 ₹ m (O-03) | M60: O-03, G-04 | N60: floating_rate_debt_k
A61: TRS-001 | B61: FX exposure, unhedged | C61: ₹ m | D61: Month end | E61: (Foreign-currency exposure − Amount hedged) ÷ 1000 | F61: =ROUND(('Group Inputs'!CZ4-'Group Inputs'!DA4)/1000,2) | G61: =ROUND(('Group Inputs'!CZ5-'Group Inputs'!DA5)/1000,2) | H61: =ROUND(('Group Inputs'!CZ6-'Group Inputs'!DA6)/1000,2) | I61: =ROUND(('Group Inputs'!CZ7-'Group Inputs'!DA7)/1000,2) | J61: =ROUND(('Group Inputs'!CZ8-'Group Inputs'!DA8)/1000,2) | K61: =ROUND(('Group Inputs'!CZ9-'Group Inputs'!DA9)/1000,2) | L61: ₹64 m | M61: E-05, G-04 | N61: fx_exposure_k, fx_hedged_k
A62: TRS-002 | B62: Hedging effectiveness | C62: % | D62: Month | E62: Change in value of hedges ÷ Change in value of hedged items × 100 | F62: =ROUND(IF('Group Inputs'!DE4=0,0,100*'Group Inputs'!DD4/'Group Inputs'!DE4),2) | G62: =ROUND(IF('Group Inputs'!DE5=0,0,100*'Group Inputs'!DD5/'Group Inputs'!DE5),2) | H62: =ROUND(IF('Group Inputs'!DE6=0,0,100*'Group Inputs'!DD6/'Group Inputs'!DE6),2) | I62: =ROUND(IF('Group Inputs'!DE7=0,0,100*'Group Inputs'!DD7/'Group Inputs'!DE7),2) | J62: =ROUND(IF('Group Inputs'!DE8=0,0,100*'Group Inputs'!DD8/'Group Inputs'!DE8),2) | K62: =ROUND(IF('Group Inputs'!DE9=0,0,100*'Group Inputs'!DD9/'Group Inputs'!DE9),2) | L62: 91% | M62: E-05, G-04 | N62: hedge_value_change_k, hedged_item_value_change_k
A63: TRS-003 | B63: USD share of unhedged FX exposure | C63: % | D63: Month end | E63: (USD exposure − USD hedged) ÷ (FX exposure − FX hedged) × 100 | F63: =ROUND(IF(('Group Inputs'!CZ4-'Group Inputs'!DA4)=0,0,100*('Group Inputs'!DB4-'Group Inputs'!DC4)/('Group Inputs'!CZ4-'Group Inputs'!DA4)),2) | G63: =ROUND(IF(('Group Inputs'!CZ5-'Group Inputs'!DA5)=0,0,100*('Group Inputs'!DB5-'Group Inputs'!DC5)/('Group Inputs'!CZ5-'Group Inputs'!DA5)),2) | H63: =ROUND(IF(('Group Inputs'!CZ6-'Group Inputs'!DA6)=0,0,100*('Group Inputs'!DB6-'Group Inputs'!DC6)/('Group Inputs'!CZ6-'Group Inputs'!DA6)),2) | I63: =ROUND(IF(('Group Inputs'!CZ7-'Group Inputs'!DA7)=0,0,100*('Group Inputs'!DB7-'Group Inputs'!DC7)/('Group Inputs'!CZ7-'Group Inputs'!DA7)),2) | J63: =ROUND(IF(('Group Inputs'!CZ8-'Group Inputs'!DA8)=0,0,100*('Group Inputs'!DB8-'Group Inputs'!DC8)/('Group Inputs'!CZ8-'Group Inputs'!DA8)),2) | K63: =ROUND(IF(('Group Inputs'!CZ9-'Group Inputs'!DA9)=0,0,100*('Group Inputs'!DB9-'Group Inputs'!DC9)/('Group Inputs'!CZ9-'Group Inputs'!DA9)),2) | L63: 72% of unhedged | M63: — | N63: fx_exposure_k, fx_hedged_k, usd_exposure_k, usd_hedged_k
A64: TRS-004 | B64: Hedge cover, next 6 months | C64: % | D64: Next 6 months | E64: Foreign-currency flows hedged ÷ Forecast foreign-currency flows, next 6 months × 100 | F64: =ROUND(IF('Group Inputs'!DF4=0,0,100*'Group Inputs'!DG4/'Group Inputs'!DF4),2) | G64: =ROUND(IF('Group Inputs'!DF5=0,0,100*'Group Inputs'!DG5/'Group Inputs'!DF5),2) | H64: =ROUND(IF('Group Inputs'!DF6=0,0,100*'Group Inputs'!DG6/'Group Inputs'!DF6),2) | I64: =ROUND(IF('Group Inputs'!DF7=0,0,100*'Group Inputs'!DG7/'Group Inputs'!DF7),2) | J64: =ROUND(IF('Group Inputs'!DF8=0,0,100*'Group Inputs'!DG8/'Group Inputs'!DF8),2) | K64: =ROUND(IF('Group Inputs'!DF9=0,0,100*'Group Inputs'!DG9/'Group Inputs'!DF9),2) | L64: 68%; 70.7 % (O-03) | M64: O-03, E-05, G-04 | N64: fx_flows_6m_k, fx_hedged_6m_k
A65: TRS-005 | B65: FX sensitivity, 5% USD move | C65: ₹ m | D65: Month end | E65: 5% × (USD exposure − USD hedged) ÷ 1000 | F65: =ROUND(0.05*('Group Inputs'!DB4-'Group Inputs'!DC4)/1000,2) | G65: =ROUND(0.05*('Group Inputs'!DB5-'Group Inputs'!DC5)/1000,2) | H65: =ROUND(0.05*('Group Inputs'!DB6-'Group Inputs'!DC6)/1000,2) | I65: =ROUND(0.05*('Group Inputs'!DB7-'Group Inputs'!DC7)/1000,2) | J65: =ROUND(0.05*('Group Inputs'!DB8-'Group Inputs'!DC8)/1000,2) | K65: =ROUND(0.05*('Group Inputs'!DB9-'Group Inputs'!DC9)/1000,2) | L65: ₹3.2 m EBITDA | M65: — | N65: usd_exposure_k, usd_hedged_k
A66: CPX-001 | B66: Approved capex budget | C66: ₹ m | D66: Full year | E66: Approved capex budget ÷ 1000 | F66: =ROUND('Group Inputs'!DH4/1000,2) | G66: =ROUND('Group Inputs'!DH5/1000,2) | H66: =ROUND('Group Inputs'!DH6/1000,2) | I66: =ROUND('Group Inputs'!DH7/1000,2) | J66: =ROUND('Group Inputs'!DH8/1000,2) | K66: =ROUND('Group Inputs'!DH9/1000,2) | L66: 850 ₹ m | M66: E-06,G-06,O-04 | N66: capex_budget_k
A67: CPX-002 | B67: Committed capex | C67: ₹ m | D67: To date | E67: Capex committed to date ÷ 1000 | F67: =ROUND('Group Inputs'!DI4/1000,2) | G67: =ROUND('Group Inputs'!DI5/1000,2) | H67: =ROUND('Group Inputs'!DI6/1000,2) | I67: =ROUND('Group Inputs'!DI7/1000,2) | J67: =ROUND('Group Inputs'!DI8/1000,2) | K67: =ROUND('Group Inputs'!DI9/1000,2) | L67: 610 ₹ m · 72% | M67: E-06,G-06,O-04 | N67: capex_committed_k
A68: CPX-003 | B68: Capex actual spend YTD | C68: ₹ m | D68: Year to date | E68: Sum of capex spent since April ÷ 1000 | F68: =ROUND(SUM('Group Inputs'!DJ$4:DJ4)/1000,2) | G68: =ROUND(SUM('Group Inputs'!DJ$4:DJ5)/1000,2) | H68: =ROUND(SUM('Group Inputs'!DJ$4:DJ6)/1000,2) | I68: =ROUND(SUM('Group Inputs'!DJ$4:DJ7)/1000,2) | J68: =ROUND(SUM('Group Inputs'!DJ$4:DJ8)/1000,2) | K68: =ROUND(SUM('Group Inputs'!DJ$4:DJ9)/1000,2) | L68: 402 ₹ m · 47% | M68: E-06,G-06,O-04 | N68: capex_spend_k
A69: CPX-004 | B69: Capex physical progress, weighted | C69: % | D69: To date | E69: Work completed valued at budget ÷ Approved budget × 100 (weights each project by its budget) | F69: =ROUND(IF('Group Inputs'!DH4=0,0,100*'Group Inputs'!DK4/'Group Inputs'!DH4),2) | G69: =ROUND(IF('Group Inputs'!DH5=0,0,100*'Group Inputs'!DK5/'Group Inputs'!DH5),2) | H69: =ROUND(IF('Group Inputs'!DH6=0,0,100*'Group Inputs'!DK6/'Group Inputs'!DH6),2) | I69: =ROUND(IF('Group Inputs'!DH7=0,0,100*'Group Inputs'!DK7/'Group Inputs'!DH7),2) | J69: =ROUND(IF('Group Inputs'!DH8=0,0,100*'Group Inputs'!DK8/'Group Inputs'!DH8),2) | K69: =ROUND(IF('Group Inputs'!DH9=0,0,100*'Group Inputs'!DK9/'Group Inputs'!DH9),2) | L69: 61 % weighted | M69: E-06,G-01,G-06,O-01,O-04,STATE GALLERY | N69: capex_budget_k, capex_earned_value_k
A70: SIG-011 | B70: Capex value at risk | C70: ₹ m | D70: Month end | E70: Budget of projects at risk ÷ 1000 | F70: =ROUND('Group Inputs'!DL4/1000,2) | G70: =ROUND('Group Inputs'!DL5/1000,2) | H70: =ROUND('Group Inputs'!DL6/1000,2) | I70: =ROUND('Group Inputs'!DL7/1000,2) | J70: =ROUND('Group Inputs'!DL8/1000,2) | K70: =ROUND('Group Inputs'!DL9/1000,2) | L70: ₹34 m | M70: E-06,G-06,O-04 | N70: capex_at_risk_k
A71: PRG-001 | B71: Capex project status | C71: text | D71: Month end | E71: Count of projects by status | F71: ='Group Inputs'!DM4&" on track · "&'Group Inputs'!DN4&" at risk · "&'Group Inputs'!DO4&" off track" | G71: ='Group Inputs'!DM5&" on track · "&'Group Inputs'!DN5&" at risk · "&'Group Inputs'!DO5&" off track" | H71: ='Group Inputs'!DM6&" on track · "&'Group Inputs'!DN6&" at risk · "&'Group Inputs'!DO6&" off track" | I71: ='Group Inputs'!DM7&" on track · "&'Group Inputs'!DN7&" at risk · "&'Group Inputs'!DO7&" off track" | J71: ='Group Inputs'!DM8&" on track · "&'Group Inputs'!DN8&" at risk · "&'Group Inputs'!DO8&" off track" | K71: ='Group Inputs'!DM9&" on track · "&'Group Inputs'!DN9&" at risk · "&'Group Inputs'!DO9&" off track" | L71: 9 on track · 2 at risk · 0 off track | M71: G-06,O-04 | N71: projects_on_track, projects_at_risk, projects_off_track
A72: PRG-002 | B72: Benefits realisation | C72: % | D72: Year to date | E72: Benefits delivered since April ÷ Benefits planned since April × 100 | F72: =ROUND(IF(SUM('Group Inputs'!DX$4:DX4)=0,0,100*SUM('Group Inputs'!DY$4:DY4)/SUM('Group Inputs'!DX$4:DX4)),2) | G72: =ROUND(IF(SUM('Group Inputs'!DX$4:DX5)=0,0,100*SUM('Group Inputs'!DY$4:DY5)/SUM('Group Inputs'!DX$4:DX5)),2) | H72: =ROUND(IF(SUM('Group Inputs'!DX$4:DX6)=0,0,100*SUM('Group Inputs'!DY$4:DY6)/SUM('Group Inputs'!DX$4:DX6)),2) | I72: =ROUND(IF(SUM('Group Inputs'!DX$4:DX7)=0,0,100*SUM('Group Inputs'!DY$4:DY7)/SUM('Group Inputs'!DX$4:DX7)),2) | J72: =ROUND(IF(SUM('Group Inputs'!DX$4:DX8)=0,0,100*SUM('Group Inputs'!DY$4:DY8)/SUM('Group Inputs'!DX$4:DX8)),2) | K72: =ROUND(IF(SUM('Group Inputs'!DX$4:DX9)=0,0,100*SUM('Group Inputs'!DY$4:DY9)/SUM('Group Inputs'!DX$4:DX9)),2) | L72: 48 % of plan | M72: E-06,G-06,O-04 | N72: benefits_planned_k, benefits_delivered_k
A73: PRG-003 | B73: Delayed projects | C73: count | D73: Month end | E73: Capex projects delayed | F73: =ROUND('Group Inputs'!DP4,2) | G73: =ROUND('Group Inputs'!DP5,2) | H73: =ROUND('Group Inputs'!DP6,2) | I73: =ROUND('Group Inputs'!DP7,2) | J73: =ROUND('Group Inputs'!DP8,2) | K73: =ROUND('Group Inputs'!DP9,2) | L73: 1 | M73: E-06,G-06,O-04 | N73: projects_delayed
A74: PRG-004 | B74: Capex / transformation progress (same measure as STR-002) | C74: % | D74: To date | E74: Transformation milestones completed ÷ Milestones in plan × 100 | F74: =ROUND(IF('Group Inputs'!DV4=0,0,100*'Group Inputs'!DW4/'Group Inputs'!DV4),2) | G74: =ROUND(IF('Group Inputs'!DV5=0,0,100*'Group Inputs'!DW5/'Group Inputs'!DV5),2) | H74: =ROUND(IF('Group Inputs'!DV6=0,0,100*'Group Inputs'!DW6/'Group Inputs'!DV6),2) | I74: =ROUND(IF('Group Inputs'!DV7=0,0,100*'Group Inputs'!DW7/'Group Inputs'!DV7),2) | J74: =ROUND(IF('Group Inputs'!DV8=0,0,100*'Group Inputs'!DW8/'Group Inputs'!DV8),2) | K74: =ROUND(IF('Group Inputs'!DV9=0,0,100*'Group Inputs'!DW9/'Group Inputs'!DV9),2) | L74: 54% | M74: E-01,G-01,O-01,O-04 | N74: milestones_total, milestones_done
A75: STR-002 | B75: Transformation progress | C75: % | D75: To date | E75: Transformation milestones completed ÷ Milestones in plan × 100 | F75: =ROUND(IF('Group Inputs'!DV4=0,0,100*'Group Inputs'!DW4/'Group Inputs'!DV4),2) | G75: =ROUND(IF('Group Inputs'!DV5=0,0,100*'Group Inputs'!DW5/'Group Inputs'!DV5),2) | H75: =ROUND(IF('Group Inputs'!DV6=0,0,100*'Group Inputs'!DW6/'Group Inputs'!DV6),2) | I75: =ROUND(IF('Group Inputs'!DV7=0,0,100*'Group Inputs'!DW7/'Group Inputs'!DV7),2) | J75: =ROUND(IF('Group Inputs'!DV8=0,0,100*'Group Inputs'!DW8/'Group Inputs'!DV8),2) | K75: =ROUND(IF('Group Inputs'!DV9=0,0,100*'Group Inputs'!DW9/'Group Inputs'!DV9),2) | L75: 54% | M75: G-06,O-01,O-04,STATE GALLERY | N75: milestones_total, milestones_done
A76: PRG-005 | B76: Transformation initiative status | C76: text | D76: Month end | E76: Count of transformation initiatives by status | F76: ='Group Inputs'!DS4&" on track · "&'Group Inputs'!DT4&" at risk · "&'Group Inputs'!DU4&" delayed" | G76: ='Group Inputs'!DS5&" on track · "&'Group Inputs'!DT5&" at risk · "&'Group Inputs'!DU5&" delayed" | H76: ='Group Inputs'!DS6&" on track · "&'Group Inputs'!DT6&" at risk · "&'Group Inputs'!DU6&" delayed" | I76: ='Group Inputs'!DS7&" on track · "&'Group Inputs'!DT7&" at risk · "&'Group Inputs'!DU7&" delayed" | J76: ='Group Inputs'!DS8&" on track · "&'Group Inputs'!DT8&" at risk · "&'Group Inputs'!DU8&" delayed" | K76: ='Group Inputs'!DS9&" on track · "&'Group Inputs'!DT9&" at risk · "&'Group Inputs'!DU9&" delayed" | L76: 15 on track · 6 at risk · 3 delayed | M76: E-06,O-04 | N76: initiatives_on_track, initiatives_at_risk, initiatives_delayed
A77: SUP-006 | B77: Contractor slippage | C77: days | D77: Month | E77: Contractor days late ÷ Contractor milestones due (average days late per milestone) | F77: =ROUND(IF('Group Inputs'!DQ4=0,0,'Group Inputs'!DR4/'Group Inputs'!DQ4),2) | G77: =ROUND(IF('Group Inputs'!DQ5=0,0,'Group Inputs'!DR5/'Group Inputs'!DQ5),2) | H77: =ROUND(IF('Group Inputs'!DQ6=0,0,'Group Inputs'!DR6/'Group Inputs'!DQ6),2) | I77: =ROUND(IF('Group Inputs'!DQ7=0,0,'Group Inputs'!DR7/'Group Inputs'!DQ7),2) | J77: =ROUND(IF('Group Inputs'!DQ8=0,0,'Group Inputs'!DR8/'Group Inputs'!DQ8),2) | K77: =ROUND(IF('Group Inputs'!DQ9=0,0,'Group Inputs'!DR9/'Group Inputs'!DQ9),2) | L77: Not shown | M77: E-04,E-06,G-06 | N77: contractor_milestones_due, contractor_days_late
A78: VAL-001 | B78: EBITDA benefit YTD | C78: ₹ m | D78: Year to date | E78: Sum of EBITDA benefit since April ÷ 1000 | F78: =ROUND(SUM('Group Inputs'!DZ$4:DZ4)/1000,2) | G78: =ROUND(SUM('Group Inputs'!DZ$4:DZ5)/1000,2) | H78: =ROUND(SUM('Group Inputs'!DZ$4:DZ6)/1000,2) | I78: =ROUND(SUM('Group Inputs'!DZ$4:DZ7)/1000,2) | J78: =ROUND(SUM('Group Inputs'!DZ$4:DZ8)/1000,2) | K78: =ROUND(SUM('Group Inputs'!DZ$4:DZ9)/1000,2) | L78: ₹14 m | M78: E-06,G-06,O-04 | N78: ebitda_benefit_k
A79: VAL-002 | B79: Cash benefit YTD | C79: ₹ m | D79: Year to date | E79: Sum of cash benefit since April ÷ 1000 | F79: =ROUND(SUM('Group Inputs'!EA$4:EA4)/1000,2) | G79: =ROUND(SUM('Group Inputs'!EA$4:EA5)/1000,2) | H79: =ROUND(SUM('Group Inputs'!EA$4:EA6)/1000,2) | I79: =ROUND(SUM('Group Inputs'!EA$4:EA7)/1000,2) | J79: =ROUND(SUM('Group Inputs'!EA$4:EA8)/1000,2) | K79: =ROUND(SUM('Group Inputs'!EA$4:EA9)/1000,2) | L79: ₹9 m | M79: E-06,G-06,O-04 | N79: cash_benefit_k
A80: VAL-003 | B80: Cost savings delivered YTD | C80: ₹ m | D80: Year to date | E80: Sum of cost savings since April ÷ 1000 | F80: =ROUND(SUM('Group Inputs'!EB$4:EB4)/1000,2) | G80: =ROUND(SUM('Group Inputs'!EB$4:EB5)/1000,2) | H80: =ROUND(SUM('Group Inputs'!EB$4:EB6)/1000,2) | I80: =ROUND(SUM('Group Inputs'!EB$4:EB7)/1000,2) | J80: =ROUND(SUM('Group Inputs'!EB$4:EB8)/1000,2) | K80: =ROUND(SUM('Group Inputs'!EB$4:EB9)/1000,2) | L80: ₹11 m | M80: E-06,G-06,O-04 | N80: cost_savings_k
A81: SUP-001 | B81: Supplier on-time delivery | C81: % | D81: Month | E81: Purchase-order lines on time ÷ Lines due × 100 | F81: =ROUND(IF('Group Inputs'!AY4=0,0,100*'Group Inputs'!AZ4/'Group Inputs'!AY4),2) | G81: =ROUND(IF('Group Inputs'!AY5=0,0,100*'Group Inputs'!AZ5/'Group Inputs'!AY5),2) | H81: =ROUND(IF('Group Inputs'!AY6=0,0,100*'Group Inputs'!AZ6/'Group Inputs'!AY6),2) | I81: =ROUND(IF('Group Inputs'!AY7=0,0,100*'Group Inputs'!AZ7/'Group Inputs'!AY7),2) | J81: =ROUND(IF('Group Inputs'!AY8=0,0,100*'Group Inputs'!AZ8/'Group Inputs'!AY8),2) | K81: =ROUND(IF('Group Inputs'!AY9=0,0,100*'Group Inputs'!AZ9/'Group Inputs'!AY9),2) | L81: 91% | M81: E-04, G-05 | N81: po_lines_due, po_lines_on_time
A82: SUP-002 | B82: Supplier fill rate | C82: % | D82: Month | E82: Quantity received ÷ Quantity ordered × 100 | F82: =ROUND(IF('Group Inputs'!BA4=0,0,100*'Group Inputs'!BB4/'Group Inputs'!BA4),2) | G82: =ROUND(IF('Group Inputs'!BA5=0,0,100*'Group Inputs'!BB5/'Group Inputs'!BA5),2) | H82: =ROUND(IF('Group Inputs'!BA6=0,0,100*'Group Inputs'!BB6/'Group Inputs'!BA6),2) | I82: =ROUND(IF('Group Inputs'!BA7=0,0,100*'Group Inputs'!BB7/'Group Inputs'!BA7),2) | J82: =ROUND(IF('Group Inputs'!BA8=0,0,100*'Group Inputs'!BB8/'Group Inputs'!BA8),2) | K82: =ROUND(IF('Group Inputs'!BA9=0,0,100*'Group Inputs'!BB9/'Group Inputs'!BA9),2) | L82: Not shown | M82: — | N82: qty_ordered_t, qty_received_t
A83: SUP-003 | B83: Supplier quality-rejection rate | C83: % | D83: Month | E83: Quantity rejected ÷ Quantity received × 100 | F83: =ROUND(IF('Group Inputs'!BB4=0,0,100*'Group Inputs'!BC4/'Group Inputs'!BB4),2) | G83: =ROUND(IF('Group Inputs'!BB5=0,0,100*'Group Inputs'!BC5/'Group Inputs'!BB5),2) | H83: =ROUND(IF('Group Inputs'!BB6=0,0,100*'Group Inputs'!BC6/'Group Inputs'!BB6),2) | I83: =ROUND(IF('Group Inputs'!BB7=0,0,100*'Group Inputs'!BC7/'Group Inputs'!BB7),2) | J83: =ROUND(IF('Group Inputs'!BB8=0,0,100*'Group Inputs'!BC8/'Group Inputs'!BB8),2) | K83: =ROUND(IF('Group Inputs'!BB9=0,0,100*'Group Inputs'!BC9/'Group Inputs'!BB9),2) | L83: Not shown | N83: qty_received_t, qty_rejected_t
A84: SUP-004 | B84: Supplier lead-time variance | C84: % | D84: Month | E84: (Actual lead time − Planned lead time) ÷ Planned lead time × 100 | F84: =ROUND(IF('Group Inputs'!BD4=0,0,100*('Group Inputs'!BE4-'Group Inputs'!BD4)/'Group Inputs'!BD4),2) | G84: =ROUND(IF('Group Inputs'!BD5=0,0,100*('Group Inputs'!BE5-'Group Inputs'!BD5)/'Group Inputs'!BD5),2) | H84: =ROUND(IF('Group Inputs'!BD6=0,0,100*('Group Inputs'!BE6-'Group Inputs'!BD6)/'Group Inputs'!BD6),2) | I84: =ROUND(IF('Group Inputs'!BD7=0,0,100*('Group Inputs'!BE7-'Group Inputs'!BD7)/'Group Inputs'!BD7),2) | J84: =ROUND(IF('Group Inputs'!BD8=0,0,100*('Group Inputs'!BE8-'Group Inputs'!BD8)/'Group Inputs'!BD8),2) | K84: =ROUND(IF('Group Inputs'!BD9=0,0,100*('Group Inputs'!BE9-'Group Inputs'!BD9)/'Group Inputs'!BD9),2) | L84: 38% | M84: E-04,G-05 | N84: lead_time_planned_days, lead_time_actual_days
A85: SUP-005 | B85: Critical supplier exposure | C85: count | D85: Month end | E85: Critical single-source suppliers | F85: =ROUND('Group Inputs'!EG4,2) | G85: =ROUND('Group Inputs'!EG5,2) | H85: =ROUND('Group Inputs'!EG6,2) | I85: =ROUND('Group Inputs'!EG7,2) | J85: =ROUND('Group Inputs'!EG8,2) | K85: =ROUND('Group Inputs'!EG9,2) | L85: 3 single-source (1 elevated: S-07) | M85: E-04,G-05 | N85: single_source_suppliers
A86: SUP-007 | B86: Single-source spend share | C86: % | D86: Month | E86: Spend with single-source suppliers ÷ Supplier spend × 100 | F86: =ROUND(IF('Group Inputs'!BF4=0,0,100*'Group Inputs'!BG4/'Group Inputs'!BF4),2) | G86: =ROUND(IF('Group Inputs'!BF5=0,0,100*'Group Inputs'!BG5/'Group Inputs'!BF5),2) | H86: =ROUND(IF('Group Inputs'!BF6=0,0,100*'Group Inputs'!BG6/'Group Inputs'!BF6),2) | I86: =ROUND(IF('Group Inputs'!BF7=0,0,100*'Group Inputs'!BG7/'Group Inputs'!BF7),2) | J86: =ROUND(IF('Group Inputs'!BF8=0,0,100*'Group Inputs'!BG8/'Group Inputs'!BF8),2) | K86: =ROUND(IF('Group Inputs'!BF9=0,0,100*'Group Inputs'!BG9/'Group Inputs'!BF9),2) | L86: 38% | M86: — | N86: supplier_spend_k, single_source_spend_k
A87: SUP-008 | B87: Supplier EHS incidents YTD | C87: count | D87: Year to date | E87: Sum of supplier EHS incidents since April | F87: =ROUND(SUM('Group Inputs'!BH$4:BH4),2) | G87: =ROUND(SUM('Group Inputs'!BH$4:BH5),2) | H87: =ROUND(SUM('Group Inputs'!BH$4:BH6),2) | I87: =ROUND(SUM('Group Inputs'!BH$4:BH7),2) | J87: =ROUND(SUM('Group Inputs'!BH$4:BH8),2) | K87: =ROUND(SUM('Group Inputs'!BH$4:BH9),2) | L87: 0 | M87: — | N87: supplier_ehs_incidents
A88: CON-001 | B88: Contracts expiring, next 90 days | C88: count | D88: Month end | E88: Contracts expiring in next 90 days | F88: =ROUND('Group Inputs'!EE4,2) | G88: =ROUND('Group Inputs'!EE5,2) | H88: =ROUND('Group Inputs'!EE6,2) | I88: =ROUND('Group Inputs'!EE7,2) | J88: =ROUND('Group Inputs'!EE8,2) | K88: =ROUND('Group Inputs'!EE9,2) | L88: 4 | M88: E-04,E-07,G-07,O-05 | N88: contracts_expiring_90d
A89: CON-002 | B89: Contract-compliance rate | C89: % | D89: Month end | E89: Contracts fully compliant ÷ Active contracts × 100 | F89: =ROUND(IF('Group Inputs'!EC4=0,0,100*'Group Inputs'!ED4/'Group Inputs'!EC4),2) | G89: =ROUND(IF('Group Inputs'!EC5=0,0,100*'Group Inputs'!ED5/'Group Inputs'!EC5),2) | H89: =ROUND(IF('Group Inputs'!EC6=0,0,100*'Group Inputs'!ED6/'Group Inputs'!EC6),2) | I89: =ROUND(IF('Group Inputs'!EC7=0,0,100*'Group Inputs'!ED7/'Group Inputs'!EC7),2) | J89: =ROUND(IF('Group Inputs'!EC8=0,0,100*'Group Inputs'!ED8/'Group Inputs'!EC8),2) | K89: =ROUND(IF('Group Inputs'!EC9=0,0,100*'Group Inputs'!ED9/'Group Inputs'!EC9),2) | L89: 96% | M89: E-04,E-07,G-07,O-05 | N89: contracts_total, contracts_compliant
A90: CON-003 | B90: Supplier EHS non-compliance | C90: count | D90: Month end | E90: Suppliers not meeting EHS requirements | F90: =ROUND('Group Inputs'!EF4,2) | G90: =ROUND('Group Inputs'!EF5,2) | H90: =ROUND('Group Inputs'!EF6,2) | I90: =ROUND('Group Inputs'!EF7,2) | J90: =ROUND('Group Inputs'!EF8,2) | K90: =ROUND('Group Inputs'!EF9,2) | L90: 1 | M90: E-04,E-07,G-05,G-07,O-05 | N90: supplier_ehs_noncompliance
A91: REG-001 | B91: Pending filings | C91: count | D91: Month end | E91: Regulatory filings pending | F91: =ROUND('Group Inputs'!BI4,2) | G91: =ROUND('Group Inputs'!BI5,2) | H91: =ROUND('Group Inputs'!BI6,2) | I91: =ROUND('Group Inputs'!BI7,2) | J91: =ROUND('Group Inputs'!BI8,2) | K91: =ROUND('Group Inputs'!BI9,2) | L91: 3 | M91: E-07,G-07 | N91: pending_filings
A92: REG-002 | B92: Regulatory deadlines, next 30 days | C92: count | D92: Month end | E92: Regulatory deadlines in next 30 days | F92: =ROUND('Group Inputs'!BJ4,2) | G92: =ROUND('Group Inputs'!BJ5,2) | H92: =ROUND('Group Inputs'!BJ6,2) | I92: =ROUND('Group Inputs'!BJ7,2) | J92: =ROUND('Group Inputs'!BJ8,2) | K92: =ROUND('Group Inputs'!BJ9,2) | L92: 3 | M92: E-07,G-07 | N92: reg_deadlines_30d
A93: REG-003 | B93: Licence expirations, next 12 months | C93: count | D93: Month end | E93: Licences expiring in next 12 months | F93: =ROUND('Group Inputs'!BK4,2) | G93: =ROUND('Group Inputs'!BK5,2) | H93: =ROUND('Group Inputs'!BK6,2) | I93: =ROUND('Group Inputs'!BK7,2) | J93: =ROUND('Group Inputs'!BK8,2) | K93: =ROUND('Group Inputs'!BK9,2) | L93: 2 | M93: E-07,G-07 | N93: licences_expiring_12m
A94: REG-004 | B94: Regulatory obligations due, next 30 days | C94: count | D94: Month end | E94: Regulatory obligations due in next 30 days | F94: =ROUND('Group Inputs'!BL4,2) | G94: =ROUND('Group Inputs'!BL5,2) | H94: =ROUND('Group Inputs'!BL6,2) | I94: =ROUND('Group Inputs'!BL7,2) | J94: =ROUND('Group Inputs'!BL8,2) | K94: =ROUND('Group Inputs'!BL9,2) | L94: 5 | M94: E-07,G-07 | N94: reg_obligations_due_30d
A95: REG-005 | B95: Overdue regulatory obligations | C95: count | D95: Month end | E95: Regulatory obligations overdue | F95: =ROUND('Group Inputs'!BM4,2) | G95: =ROUND('Group Inputs'!BM5,2) | H95: =ROUND('Group Inputs'!BM6,2) | I95: =ROUND('Group Inputs'!BM7,2) | J95: =ROUND('Group Inputs'!BM8,2) | K95: =ROUND('Group Inputs'!BM9,2) | L95: 0 | M95: E-07,G-07,O-05 | N95: reg_obligations_overdue
A96: REG-007 | B96: Open regulatory actions | C96: count | D96: Month end | E96: Open regulatory actions | F96: =ROUND('Group Inputs'!BN4,2) | G96: =ROUND('Group Inputs'!BN5,2) | H96: =ROUND('Group Inputs'!BN6,2) | I96: =ROUND('Group Inputs'!BN7,2) | J96: =ROUND('Group Inputs'!BN8,2) | K96: =ROUND('Group Inputs'!BN9,2) | L96: 2 | M96: E-07,G-07 | N96: reg_actions_open
A97: REG-008 | B97: Overdue compliance actions | C97: count | D97: Month end | E97: Overdue compliance actions | F97: =ROUND('Group Inputs'!BO4,2) | G97: =ROUND('Group Inputs'!BO5,2) | H97: =ROUND('Group Inputs'!BO6,2) | I97: =ROUND('Group Inputs'!BO7,2) | J97: =ROUND('Group Inputs'!BO8,2) | K97: =ROUND('Group Inputs'!BO9,2) | L97: 0 | M97: E-07,G-07 | N97: compliance_actions_overdue
A98: REG-009 | B98: Disclosure-clock status | C98: text | D98: Month end | E98: Triggered if any event that needs disclosure is open, otherwise Not triggered | F98: =IF('Group Inputs'!BQ4>0,"Triggered","Not triggered") | G98: =IF('Group Inputs'!BQ5>0,"Triggered","Not triggered") | H98: =IF('Group Inputs'!BQ6>0,"Triggered","Not triggered") | I98: =IF('Group Inputs'!BQ7>0,"Triggered","Not triggered") | J98: =IF('Group Inputs'!BQ8>0,"Triggered","Not triggered") | K98: =IF('Group Inputs'!BQ9>0,"Triggered","Not triggered") | L98: Not triggered | M98: O-05 | N98: disclosure_events_open
A99: REG-010 | B99: Regulatory breaches YTD | C99: count | D99: Year to date | E99: Sum of regulatory breaches since April | F99: =ROUND(SUM('Group Inputs'!BP$4:BP4),2) | G99: =ROUND(SUM('Group Inputs'!BP$4:BP5),2) | H99: =ROUND(SUM('Group Inputs'!BP$4:BP6),2) | I99: =ROUND(SUM('Group Inputs'!BP$4:BP7),2) | J99: =ROUND(SUM('Group Inputs'!BP$4:BP8),2) | K99: =ROUND(SUM('Group Inputs'!BP$4:BP9),2) | L99: 0 | M99: E-07,G-01,O-05 | N99: reg_breaches
A100: RSK-003 | B100: Regulatory breaches YTD (same measure as REG-010) | C100: count | D100: Year to date | E100: Sum of regulatory breaches since April | F100: =ROUND(SUM('Group Inputs'!BP$4:BP4),2) | G100: =ROUND(SUM('Group Inputs'!BP$4:BP5),2) | H100: =ROUND(SUM('Group Inputs'!BP$4:BP6),2) | I100: =ROUND(SUM('Group Inputs'!BP$4:BP7),2) | J100: =ROUND(SUM('Group Inputs'!BP$4:BP8),2) | K100: =ROUND(SUM('Group Inputs'!BP$4:BP9),2) | L100: 0 | M100: O-01,STATE GALLERY | N100: reg_breaches
...

Sheet Group Inputs
A1: Group | B1: Month | C1: Days in month | D1: Months since April (YTD) | E1: Calendar hours (h) | F1: Planned operating hours (h) | G1: Run hours (h) | H1: Unplanned downtime (h) | I1: Ideal output (t) | J1: Installed capacity (t) | K1: Planned production (t) | L1: Gross output (t) | M1: Good output (t) | N1: Feed input (t) | O1: Valuable content in feed (t) | P1: Valuable content recovered (t) | Q1: Production lost to downtime (t) | R1: Breakdowns (count) | S1: Repair hours (h) | T1: Preventive maintenance scheduled (count) | U1: Preventive maintenance completed (count) | V1: Variable cost (₹ thousand) | W1: Fuel cost (₹ thousand) | X1: Fixed cost (₹ thousand) | Y1: Water used (m³) | Z1: Emissions (t CO2e) | AA1: Energy used (GJ) | AB1: Production at risk (t) | AC1: Critical plant alerts (count) | AD1: Hours worked (h) | AE1: Recordable injuries (count) | AF1: Severity incidents (count) | AG1: Near misses (count) | AH1: Critical safety incidents (count) | AI1: Environmental excursions (count) | AJ1: Environmental violations (count) | AK1: Open EHS corrective actions (count) | AL1: Overdue EHS corrective actions (count) | AM1: EHS investigations due (count) | AN1: EHS investigations completed (count) | AO1: Critical materials at risk (count) | AP1: Dispatches (count) | AQ1: Delayed dispatches (count) | AR1: Days to permit expiry (days) | AS1: Sales volume (t) | AT1: Planned sales volume (t) | AU1: Revenue (₹ thousand) | AV1: Planned revenue (₹ thousand) | AW1: Power cost, part of variable cost (₹ thousand) | AX1: Depreciation and amortisation (₹ thousand) | AY1: Purchase-order lines due (count) | AZ1: Purchase-order lines delivered on time (count) | BA1: Quantity ordered from suppliers (t) | BB1: Quantity received (t) | BC1: Quantity rejected on quality (t) | BD1: Planned lead time, all deliveries (days) | BE1: Actual lead time, all deliveries (days) | BF1: Supplier spend (₹ thousand) | BG1: Spend with single-source suppliers (₹ thousand) | BH1: Supplier EHS incidents (count) | BI1: Regulatory filings pending (count) | BJ1: Regulatory deadlines in next 30 days (count) | BK1: Licences expiring in next 12 months (count) | BL1: Regulatory obligations due in next 30 days (count) | BM1: Regulatory obligations overdue (count) | BN1: Open regulatory actions (count) | BO1: Overdue compliance actions (count) | BP1: Regulatory breaches in the month (count) | BQ1: Events that trigger a disclosure clock (count) | BR1: EHS escalation clocks running (count) | BS1: Days until production plan is breached, forecast (days; 99 = not expected) | BT1: Planned production next month (t) | BU1: Forecast good output next month (t) | BV1: Forecast uncertainty next month (variance, t²) | BW1: Ideal output next month (t) | BX1: Forecast production lost to downtime next month (t) | BY1: Overheads, SG&A (₹ thousand) | BZ1: Tax paid (₹ thousand) | CA1: Capital employed, month end (₹ thousand) | CB1: Gross debt, month end (₹ thousand) | CC1: Cash, month end (₹ thousand) | CD1: Undrawn committed facilities (₹ thousand) | CE1: Debt service in the month (₹ thousand) | CF1: Debt maturing in next 12 months (₹ thousand) | CG1: Floating-rate debt (₹ thousand) | CH1: EBITDA as reported in the Board pack (₹ thousand) | CI1: Revenue in the flash report (₹ thousand) | CJ1: Trade receivables, month end (₹ thousand) | CK1: Trade payables, month end (₹ thousand) | CL1: Inventory, month end (₹ thousand) | CM1: Cash collected from customers (₹ thousand) | CN1: Cash released by working-capital actions (₹ thousand) | CO1: Cash due to be upstreamed to Group, next 30 days (₹ thousand) | CP1: Of which covered by available cash (₹ thousand) | CQ1: Invoices collected (count) | CR1: Days taken to collect, all invoices (days) | CS1: Agreed payment terms, all invoices (days) | CT1: Customers more than 30 days overdue (count) | CU1: Forecast EBITDA, rest of year (₹ thousand) | CV1: Planned EBITDA, rest of year (₹ thousand) | CW1: Forecast net cash flow, next 90 days (₹ thousand) | CX1: Forecast net debt at quarter end (₹ thousand) | CY1: Forecast EBITDA, 12 months to quarter end (₹ thousand) | CZ1: Foreign-currency exposure, gross (₹ thousand) | DA1: Foreign-currency exposure hedged (₹ thousand) | DB1: USD exposure, gross (₹ thousand) | DC1: USD exposure hedged (₹ thousand) | DD1: Change in value of hedges (₹ thousand) | DE1: Change in value of hedged items (₹ thousand) | DF1: Forecast foreign-currency flows, next 6 months (₹ thousand) | DG1: Of which hedged (₹ thousand) | DH1: Approved capex budget, full year (₹ thousand) | DI1: Capex committed to date (₹ thousand) | DJ1: Capex spent in the month (₹ thousand) | DK1: Capex work completed, valued at budget (₹ thousand) | DL1: Budget of capex projects at risk (₹ thousand) | DM1: Capex projects on track (count) | DN1: Capex projects at risk (count) | DO1: Capex projects off track (count) | DP1: Capex projects delayed (count) | DQ1: Contractor milestones due (count) | DR1: Contractor days late, all milestones (days) | DS1: Transformation initiatives on track (count) | DT1: Transformation initiatives at risk (count) | DU1: Transformation initiatives delayed (count) | DV1: Transformation milestones in plan (count) | DW1: Transformation milestones completed (count) | DX1: Programme benefits planned in the month (₹ thousand) | DY1: Programme benefits delivered in the month (₹ thousand) | DZ1: EBITDA benefit delivered (₹ thousand) | EA1: Cash benefit delivered (₹ thousand) | EB1: Cost savings delivered (₹ thousand) | EC1: Active supply contracts (count) | ED1: Contracts fully compliant (count) | EE1: Contracts expiring in next 90 days (count) | EF1: Suppliers not meeting EHS requirements (count) | EG1: Critical single-source suppliers (count) | EH1: Control failures (count) | EI1: High-severity control failures (count) | EJ1: Assurance reviews planned (count) | EK1: Assurance reviews completed (count) | EL1: Policy exceptions (count) | EM1: Unauthorised vendor uses (count) | EN1: Segregation-of-duties exceptions (count) | EO1: Unauthorised access events (count) | EP1: Data-sharing exceptions (count) | EQ1: Manual operational or system overrides (count) | ER1: Certification approvals past due date (count) | ES1: KPI values overridden (count) | ET1: Recurring data-quality issues (count) | EU1: Open audit findings (count) | EV1: Overdue assurance actions (count) | EW1: Repeat audit findings (count) | EX1: Leadership KPIs affected by open findings (count) | EY1: Evidence items required (count) | EZ1: Evidence items complete (count) | FA1: Audit findings closed in the month (count) | FB1: Days taken to close those findings (days) | FC1: Leadership KPI values reported (count) | FD1: Of which certified (count) | FE1: Of which inside the certification process (count) | FF1: Certifications overdue (count) | FG1: Open reconciliation breaks (count) | FH1: Material reconciliation breaks (count) | FI1: Records loaded to the data lake (count) | FJ1: Records reconciled to source (count) | FK1: Flash report lines (count) | FL1: Flash lines matching MIS (count) | FM1: Open critical alerts (count) | FN1: Alerts with no accepted owner (count) | FO1: Overdue actions (count) | FP1: Alerts resolved in the month (count) | FQ1: Days taken to resolve those alerts (days) | FR1: Escalations closed in the month (count) | FS1: Repeat issues raised in the month (count) | FT1: Root causes identified (count) | FU1: Root causes eliminated (count) | FV1: EBITDA (₹ thousand) | FW1: EBIT (₹ thousand) | FX1: Net working capital (₹ thousand) | FY1: Change in net working capital (₹ thousand) | FZ1: Operating cash flow (₹ thousand) | GA1: Free cash flow (₹ thousand) | GB1: Net debt (₹ thousand) | GC1: EBITDA, annualised (₹ thousand) | GD1: DSO (days) | GE1: DPO (days) | GF1: Inventory days (days) | GG1: Realised price vs plan (%) | GH1: Full-time employees (FTE, count) | GI1: FCF plan, full year (₹ thousand) | GJ1: Forecast FCF, rest of year (₹ thousand) | GK1: Forecast EBIT, rest of year (₹ thousand) | GL1: Forecast capital employed at P12 (₹ thousand) | GM1: EBITDA plan, full year (₹ thousand) | GN1: EBITDA full-year forecast uncertainty, 1σ (₹ thousand) | GO1: Hours to nearest open disclosure deadline (999 = none) | GP1: Single-source suppliers with cover below lead time (count) | GQ1: RM-1 price index (external, same for every entity) | GR1: Supply lanes with a disruption flag (count)
A2: group | B2: period | C2: days | D2: ytd_months | E2: calendar_hours | F2: planned_op_hours | G2: run_hours | H2: unplanned_downtime_hours | I2: ideal_output_t | J2: installed_capacity_t | K2: planned_production_t | L2: gross_output_t | M2: good_output_t | N2: feed_input_t | O2: feed_contained_t | P2: recovered_contained_t | Q2: prod_loss_downtime_t | R2: failures | S2: repair_hours | T2: pm_scheduled | U2: pm_completed | V2: variable_cost_k | W2: fuel_cost_k | X2: fixed_cost_k | Y2: water_m3 | Z2: emissions_tco2e | AA2: energy_gj | AB2: production_at_risk_t | AC2: critical_plant_alerts | AD2: hours_worked | AE2: recordable_injuries | AF2: severity_incidents | AG2: near_misses | AH2: critical_safety_incidents | AI2: env_excursions | AJ2: env_violations | AK2: ehs_ca_open | AL2: ehs_ca_overdue | AM2: investigations_due | AN2: investigations_completed | AO2: critical_material_risks | AP2: dispatches_total | AQ2: dispatches_delayed | AR2: permit_days_to_expiry | AS2: sales_t | AT2: planned_sales_t | AU2: revenue_k | AV2: planned_revenue_k | AW2: power_cost_k | AX2: depreciation_k | AY2: po_lines_due | AZ2: po_lines_on_time | BA2: qty_ordered_t | BB2: qty_received_t | BC2: qty_rejected_t | BD2: lead_time_planned_days | BE2: lead_time_actual_days | BF2: supplier_spend_k | BG2: single_source_spend_k | BH2: supplier_ehs_incidents | BI2: pending_filings | BJ2: reg_deadlines_30d | BK2: licences_expiring_12m | BL2: reg_obligations_due_30d | BM2: reg_obligations_overdue | BN2: reg_actions_open | BO2: compliance_actions_overdue | BP2: reg_breaches | BQ2: disclosure_events_open | BR2: ehs_escalation_clocks | BS2: days_to_breach | BT2: planned_production_next_t | BU2: forecast_good_next_t | BV2: forecast_good_var_next | BW2: ideal_output_next_t | BX2: forecast_downtime_loss_next_t | BY2: overhead_k | BZ2: tax_paid_k | CA2: capital_employed_k | CB2: gross_debt_k | CC2: cash_k | CD2: undrawn_facilities_k | CE2: debt_service_k | CF2: debt_maturing_12m_k | CG2: floating_rate_debt_k | CH2: board_ebitda_k | CI2: flash_revenue_k | CJ2: receivables_k | CK2: payables_k | CL2: inventory_k | CM2: collections_k | CN2: cash_released_k | CO2: upstream_due_k | CP2: upstream_covered_k | CQ2: invoices_collected | CR2: collection_days | CS2: terms_days | CT2: customers_overdue | CU2: forecast_ebitda_rest_k | CV2: planned_ebitda_rest_k | CW2: forecast_net_cash_flow_90d_k | CX2: forecast_net_debt_k | CY2: forecast_ebitda_ltm_k | CZ2: fx_exposure_k | DA2: fx_hedged_k | DB2: usd_exposure_k | DC2: usd_hedged_k | DD2: hedge_value_change_k | DE2: hedged_item_value_change_k | DF2: fx_flows_6m_k | DG2: fx_hedged_6m_k | DH2: capex_budget_k | DI2: capex_committed_k | DJ2: capex_spend_k | DK2: capex_earned_value_k | DL2: capex_at_risk_k | DM2: projects_on_track | DN2: projects_at_risk | DO2: projects_off_track | DP2: projects_delayed | DQ2: contractor_milestones_due | DR2: contractor_days_late | DS2: initiatives_on_track | DT2: initiatives_at_risk | DU2: initiatives_delayed | DV2: milestones_total | DW2: milestones_done | DX2: benefits_planned_k | DY2: benefits_delivered_k | DZ2: ebitda_benefit_k | EA2: cash_benefit_k | EB2: cost_savings_k | EC2: contracts_total | ED2: contracts_compliant | EE2: contracts_expiring_90d | EF2: supplier_ehs_noncompliance | EG2: single_source_suppliers | EH2: control_failures | EI2: control_failures_high | EJ2: assurance_reviews_planned | EK2: assurance_reviews_done | EL2: policy_exceptions | EM2: unauthorized_vendor_uses | EN2: sod_exceptions | EO2: unauthorized_access_events | EP2: data_sharing_exceptions | EQ2: manual_overrides | ER2: cert_approvals_ageing | ES2: kpi_overrides | ET2: dq_issues_recurring | EU2: audit_findings_open | EV2: assurance_actions_overdue | EW2: repeat_findings | EX2: leadership_kpis_affected | EY2: evidence_required | EZ2: evidence_complete | FA2: findings_closed | FB2: finding_closure_days | FC2: kpis_leadership | FD2: kpis_certified | FE2: kpis_in_scope | FF2: certifications_overdue | FG2: recon_breaks_open | FH2: recon_breaks_material | FI2: lake_records_loaded | FJ2: lake_records_reconciled | FK2: mis_lines_total | FL2: mis_lines_matched | FM2: critical_alerts_open | FN2: alerts_unowned | FO2: actions_overdue | FP2: alerts_resolved | FQ2: alert_resolution_days | FR2: escalations_closed | FS2: repeat_issues | FT2: root_causes_identified | FU2: root_causes_eliminated | FV2: ebitda_k | FW2: ebit_k | FX2: nwc_k | FY2: nwc_change_k | FZ2: op_cash_flow_k | GA2: fcf_k | GB2: net_debt_k | GC2: ebitda_annualised_k | GD2: dso_d | GE2: dpo_d | GF2: dio_d | GG2: price_vs_plan_pct | GH2: fte | GI2: fcf_plan_fy_k | GJ2: forecast_fcf_rest_k | GK2: ebit_fcst_rest_k | GL2: capital_employed_p12_k | GM2: ebitda_plan_fy_k | GN2: ebitda_fy_sigma_k | GO2: disclosure_deadline_h | GP2: single_source_elevated | GQ2: rm1_price_index | GR2: freight_lanes_disrupted
E3: Sum of Entity A1 and Entity A2 (Entity Inputs sheet) | F3: Sum of Entity A1 and Entity A2 (Entity Inputs sheet) | G3: Sum of Entity A1 and Entity A2 (Entity Inputs sheet) | H3: Sum of Entity A1 and Entity A2 (Entity Inputs sheet) | I3: Sum of Entity A1 and Entity A2 (Entity Inputs sheet) | J3: Sum of Entity A1 and Entity A2 (Entity Inputs sheet) | K3: Sum of Entity A1 and Entity A2 (Entity Inputs sheet) | L3: Sum of Entity A1 and Entity A2 (Entity Inputs sheet) | M3: Sum of Entity A1 and Entity A2 (Entity Inputs sheet) | N3: Sum of Entity A1 and Entity A2 (Entity Inputs sheet) | O3: Sum of Entity A1 and Entity A2 (Entity Inputs sheet) | P3: Sum of Entity A1 and Entity A2 (Entity Inputs sheet) | Q3: Sum of Entity A1 and Entity A2 (Entity Inputs sheet) | R3: Sum of Entity A1 and Entity A2 (Entity Inputs sheet) | S3: Sum of Entity A1 and Entity A2 (Entity Inputs sheet) | T3: Sum of Entity A1 and Entity A2 (Entity Inputs sheet) | U3: Sum of Entity A1 and Entity A2 (Entity Inputs sheet) | V3: Sum of Entity A1 and Entity A2 (Entity Inputs sheet) | W3: Sum of Entity A1 and Entity A2 (Entity Inputs sheet) | X3: Sum of Entity A1 and Entity A2 (Entity Inputs sheet) | Y3: Sum of Entity A1 and Entity A2 (Entity Inputs sheet) | Z3: Sum of Entity A1 and Entity A2 (Entity Inputs sheet) | AA3: Sum of Entity A1 and Entity A2 (Entity Inputs sheet) | AB3: Sum of Entity A1 and Entity A2 (Entity Inputs sheet) | AC3: Sum of Entity A1 and Entity A2 (Entity Inputs sheet) | AD3: Sum of Entity A1 and Entity A2 (Entity Inputs sheet) | AE3: Sum of Entity A1 and Entity A2 (Entity Inputs sheet) | AF3: Sum of Entity A1 and Entity A2 (Entity Inputs sheet) | AG3: Sum of Entity A1 and Entity A2 (Entity Inputs sheet) | AH3: Sum of Entity A1 and Entity A2 (Entity Inputs sheet) | AI3: Sum of Entity A1 and Entity A2 (Entity Inputs sheet) | AJ3: Sum of Entity A1 and Entity A2 (Entity Inputs sheet) | AK3: Sum of Entity A1 and Entity A2 (Entity Inputs sheet) | AL3: Sum of Entity A1 and Entity A2 (Entity Inputs sheet) | AM3: Sum of Entity A1 and Entity A2 (Entity Inputs sheet) | AN3: Sum of Entity A1 and Entity A2 (Entity Inputs sheet) | AO3: Sum of Entity A1 and Entity A2 (Entity Inputs sheet) | AP3: Sum of Entity A1 and Entity A2 (Entity Inputs sheet) | AQ3: Sum of Entity A1 and Entity A2 (Entity Inputs sheet) | AR3: Lowest of Entity A1 and Entity A2 (Entity Inputs sheet) | AS3: Sum of Entity A1 and Entity A2 (Entity Inputs sheet) | AT3: Sum of Entity A1 and Entity A2 (Entity Inputs sheet) | AU3: Sum of Entity A1 and Entity A2 (Entity Inputs sheet) | AV3: Sum of Entity A1 and Entity A2 (Entity Inputs sheet) | AW3: Sum of Entity A1 and Entity A2 (Entity Inputs sheet) | AX3: Sum of Entity A1 and Entity A2 (Entity Inputs sheet) | AY3: Sum of Entity A1 and Entity A2 (Entity Inputs sheet) | AZ3: Sum of Entity A1 and Entity A2 (Entity Inputs sheet) | BA3: Sum of Entity A1 and Entity A2 (Entity Inputs sheet) | BB3: Sum of Entity A1 and Entity A2 (Entity Inputs sheet) | BC3: Sum of Entity A1 and Entity A2 (Entity Inputs sheet) | BD3: Sum of Entity A1 and Entity A2 (Entity Inputs sheet) | BE3: Sum of Entity A1 and Entity A2 (Entity Inputs sheet) | BF3: Sum of Entity A1 and Entity A2 (Entity Inputs sheet) | BG3: Sum of Entity A1 and Entity A2 (Entity Inputs sheet) | BH3: Sum of Entity A1 and Entity A2 (Entity Inputs sheet) | BI3: Sum of Entity A1 and Entity A2 (Entity Inputs sheet) | BJ3: Sum of Entity A1 and Entity A2 (Entity Inputs sheet) | BK3: Sum of Entity A1 and Entity A2 (Entity Inputs sheet) | BL3: Sum of Entity A1 and Entity A2 (Entity Inputs sheet) | BM3: Sum of Entity A1 and Entity A2 (Entity Inputs sheet) | BN3: Sum of Entity A1 and Entity A2 (Entity Inputs sheet) | BO3: Sum of Entity A1 and Entity A2 (Entity Inputs sheet) | BP3: Sum of Entity A1 and Entity A2 (Entity Inputs sheet) | BQ3: Sum of Entity A1 and Entity A2 (Entity Inputs sheet) | BR3: Sum of Entity A1 and Entity A2 (Entity Inputs sheet) | BS3: Lowest of Entity A1 and Entity A2 (Entity Inputs sheet) | BT3: Sum of Entity A1 and Entity A2 (Entity Inputs sheet) | BU3: Sum of Entity A1 and Entity A2 (Entity Inputs sheet) | BV3: Sum of Entity A1 and Entity A2 (Entity Inputs sheet) | BW3: Sum of Entity A1 and Entity A2 (Entity Inputs sheet) | BX3: Sum of Entity A1 and Entity A2 (Entity Inputs sheet) | BY3: Sum of Entity A1 and Entity A2 (Entity Inputs sheet) | BZ3: Sum of Entity A1 and Entity A2 (Entity Inputs sheet) | CA3: Sum of Entity A1 and Entity A2 (Entity Inputs sheet) | CB3: Sum of Entity A1 and Entity A2 (Entity Inputs sheet) | CC3: Sum of Entity A1 and Entity A2 (Entity Inputs sheet) | CD3: Sum of Entity A1 and Entity A2 (Entity Inputs sheet) | CE3: Sum of Entity A1 and Entity A2 (Entity Inputs sheet) | CF3: Sum of Entity A1 and Entity A2 (Entity Inputs sheet) | CG3: Sum of Entity A1 and Entity A2 (Entity Inputs sheet) | CH3: Sum of Entity A1 and Entity A2 (Entity Inputs sheet) | CI3: Sum of Entity A1 and Entity A2 (Entity Inputs sheet) | CJ3: Sum of Entity A1 and Entity A2 (Entity Inputs sheet) | CK3: Sum of Entity A1 and Entity A2 (Entity Inputs sheet) | CL3: Sum of Entity A1 and Entity A2 (Entity Inputs sheet) | CM3: Sum of Entity A1 and Entity A2 (Entity Inputs sheet) | CN3: Sum of Entity A1 and Entity A2 (Entity Inputs sheet) | CO3: Sum of Entity A1 and Entity A2 (Entity Inputs sheet) | CP3: Sum of Entity A1 and Entity A2 (Entity Inputs sheet) | CQ3: Sum of Entity A1 and Entity A2 (Entity Inputs sheet) | CR3: Sum of Entity A1 and Entity A2 (Entity Inputs sheet) | CS3: Sum of Entity A1 and Entity A2 (Entity Inputs sheet) | CT3: Sum of Entity A1 and Entity A2 (Entity Inputs sheet) | CU3: Sum of Entity A1 and Entity A2 (Entity Inputs sheet) | CV3: Sum of Entity A1 and Entity A2 (Entity Inputs sheet) | CW3: Sum of Entity A1 and Entity A2 (Entity Inputs sheet) | CX3: Sum of Entity A1 and Entity A2 (Entity Inputs sheet) | CY3: Sum of Entity A1 and Entity A2 (Entity Inputs sheet) | CZ3: Sum of Entity A1 and Entity A2 (Entity Inputs sheet) | DA3: Sum of Entity A1 and Entity A2 (Entity Inputs sheet) | DB3: Sum of Entity A1 and Entity A2 (Entity Inputs sheet) | DC3: Sum of Entity A1 and Entity A2 (Entity Inputs sheet) | DD3: Sum of Entity A1 and Entity A2 (Entity Inputs sheet) | DE3: Sum of Entity A1 and Entity A2 (Entity Inputs sheet) | DF3: Sum of Entity A1 and Entity A2 (Entity Inputs sheet) | DG3: Sum of Entity A1 and Entity A2 (Entity Inputs sheet) | DH3: Sum of Entity A1 and Entity A2 (Entity Inputs sheet) | DI3: Sum of Entity A1 and Entity A2 (Entity Inputs sheet) | DJ3: Sum of Entity A1 and Entity A2 (Entity Inputs sheet) | DK3: Sum of Entity A1 and Entity A2 (Entity Inputs sheet) | DL3: Sum of Entity A1 and Entity A2 (Entity Inputs sheet) | DM3: Sum of Entity A1 and Entity A2 (Entity Inputs sheet) | DN3: Sum of Entity A1 and Entity A2 (Entity Inputs sheet) | DO3: Sum of Entity A1 and Entity A2 (Entity Inputs sheet) | DP3: Sum of Entity A1 and Entity A2 (Entity Inputs sheet) | DQ3: Sum of Entity A1 and Entity A2 (Entity Inputs sheet) | DR3: Sum of Entity A1 and Entity A2 (Entity Inputs sheet) | DS3: Sum of Entity A1 and Entity A2 (Entity Inputs sheet) | DT3: Sum of Entity A1 and Entity A2 (Entity Inputs sheet) | DU3: Sum of Entity A1 and Entity A2 (Entity Inputs sheet) | DV3: Sum of Entity A1 and Entity A2 (Entity Inputs sheet) | DW3: Sum of Entity A1 and Entity A2 (Entity Inputs sheet) | DX3: Sum of Entity A1 and Entity A2 (Entity Inputs sheet) | DY3: Sum of Entity A1 and Entity A2 (Entity Inputs sheet) | DZ3: Sum of Entity A1 and Entity A2 (Entity Inputs sheet) | EA3: Sum of Entity A1 and Entity A2 (Entity Inputs sheet) | EB3: Sum of Entity A1 and Entity A2 (Entity Inputs sheet) | EC3: Sum of Entity A1 and Entity A2 (Entity Inputs sheet) | ED3: Sum of Entity A1 and Entity A2 (Entity Inputs sheet) | EE3: Sum of Entity A1 and Entity A2 (Entity Inputs sheet) | EF3: Sum of Entity A1 and Entity A2 (Entity Inputs sheet) | EG3: Sum of Entity A1 and Entity A2 (Entity Inputs sheet) | EH3: Sum of Entity A1 and Entity A2 (Entity Inputs sheet) | EI3: Sum of Entity A1 and Entity A2 (Entity Inputs sheet) | EJ3: Sum of Entity A1 and Entity A2 (Entity Inputs sheet) | EK3: Sum of Entity A1 and Entity A2 (Entity Inputs sheet) | EL3: Sum of Entity A1 and Entity A2 (Entity Inputs sheet) | EM3: Sum of Entity A1 and Entity A2 (Entity Inputs sheet) | EN3: Sum of Entity A1 and Entity A2 (Entity Inputs sheet) | EO3: Sum of Entity A1 and Entity A2 (Entity Inputs sheet) | EP3: Sum of Entity A1 and Entity A2 (Entity Inputs sheet) | EQ3: Sum of Entity A1 and Entity A2 (Entity Inputs sheet) | ER3: Sum of Entity A1 and Entity A2 (Entity Inputs sheet) | ES3: Sum of Entity A1 and Entity A2 (Entity Inputs sheet) | ET3: Sum of Entity A1 and Entity A2 (Entity Inputs sheet) | EU3: Sum of Entity A1 and Entity A2 (Entity Inputs sheet) | EV3: Sum of Entity A1 and Entity A2 (Entity Inputs sheet) | EW3: Sum of Entity A1 and Entity A2 (Entity Inputs sheet) | EX3: Sum of Entity A1 and Entity A2 (Entity Inputs sheet) | EY3: Sum of Entity A1 and Entity A2 (Entity Inputs sheet) | EZ3: Sum of Entity A1 and Entity A2 (Entity Inputs sheet) | FA3: Sum of Entity A1 and Entity A2 (Entity Inputs sheet) | FB3: Sum of Entity A1 and Entity A2 (Entity Inputs sheet) | FC3: Sum of Entity A1 and Entity A2 (Entity Inputs sheet) | FD3: Sum of Entity A1 and Entity A2 (Entity Inputs sheet) | FE3: Sum of Entity A1 and Entity A2 (Entity Inputs sheet) | FF3: Sum of Entity A1 and Entity A2 (Entity Inputs sheet) | FG3: Sum of Entity A1 and Entity A2 (Entity Inputs sheet) | FH3: Sum of Entity A1 and Entity A2 (Entity Inputs sheet) | FI3: Sum of Entity A1 and Entity A2 (Entity Inputs sheet) | FJ3: Sum of Entity A1 and Entity A2 (Entity Inputs sheet) | FK3: Sum of Entity A1 and Entity A2 (Entity Inputs sheet) | FL3: Sum of Entity A1 and Entity A2 (Entity Inputs sheet) | FM3: Sum of Entity A1 and Entity A2 (Entity Inputs sheet) | FN3: Sum of Entity A1 and Entity A2 (Entity Inputs sheet) | FO3: Sum of Entity A1 and Entity A2 (Entity Inputs sheet) | FP3: Sum of Entity A1 and Entity A2 (Entity Inputs sheet) | FQ3: Sum of Entity A1 and Entity A2 (Entity Inputs sheet) | FR3: Sum of Entity A1 and Entity A2 (Entity Inputs sheet) | FS3: Sum of Entity A1 and Entity A2 (Entity Inputs sheet) | FT3: Sum of Entity A1 and Entity A2 (Entity Inputs sheet) | FU3: Sum of Entity A1 and Entity A2 (Entity Inputs sheet) | FV3: Calculated: Revenue − Variable cost − Fixed cost − Overheads | FW3: Calculated: EBITDA − Depreciation and amortisation | FX3: Calculated: Trade receivables + Inventory − Trade payables | FY3: Calculated: Net working capital − last month's net working capital (April uses the 31 March balance on Parameters) | FZ3: Calculated: EBITDA − Tax paid − Change in net working capital | GA3: Calculated: Operating cash flow − Capex spent | GB3: Calculated: Gross debt − Cash | GC3: Calculated: EBITDA since April × 12 ÷ months elapsed | GD3: Calculated: Trade receivables ÷ Revenue × Days in month | GE3: Calculated: Trade payables ÷ Variable cost × Days in month | GF3: Calculated: Inventory ÷ Variable cost × Days in month | GG3: Calculated: (Revenue ÷ Sales volume) ÷ (Planned revenue ÷ Planned sales volume) − 1, as % | GH3: SUM of Entity A1 and Entity A2 (added) | GI3: SUM of Entity A1 and Entity A2 (added) | GJ3: SUM of Entity A1 and Entity A2 (added) | GK3: SUM of Entity A1 and Entity A2 (added) | GL3: SUM of Entity A1 and Entity A2 (added) | GM3: SUM of Entity A1 and Entity A2 (added) | GN3: SQRTSUMSQ of Entity A1 and Entity A2 (added) | GO3: MIN of Entity A1 and Entity A2 (added) | GP3: SUM of Entity A1 and Entity A2 (added) | GQ3: FIRST of Entity A1 and Entity A2 (added) | GR3: SUM of Entity A1 and Entity A2 (added)
A4: Group | B4: 2026-04 | C4: 30 | D4: 1 | E4: =SUM('Entity Inputs'!E4,'Entity Inputs'!E10) | F4: =SUM('Entity Inputs'!F4,'Entity Inputs'!F10) | G4: =SUM('Entity Inputs'!G4,'Entity Inputs'!G10) | H4: =SUM('Entity Inputs'!H4,'Entity Inputs'!H10) | I4: =SUM('Entity Inputs'!I4,'Entity Inputs'!I10) | J4: =SUM('Entity Inputs'!J4,'Entity Inputs'!J10) | K4: =SUM('Entity Inputs'!K4,'Entity Inputs'!K10) | L4: =SUM('Entity Inputs'!L4,'Entity Inputs'!L10) | ... AQ4: =SUM('Entity Inputs'!AQ4,'Entity Inputs'!AQ10) | AR4: =MIN('Entity Inputs'!AR4,'Entity Inputs'!AR10) | AS4: =SUM('Entity Inputs'!AS4,'Entity Inputs'!AS10) | AT4: =SUM('Entity Inputs'!AT4,'Entity Inputs'!AT10) | AU4: =SUM('Entity Inputs'!AU4,'Entity Inputs'!AU10) | AV4: =SUM('Entity Inputs'!AV4,'Entity Inputs'!AV10) | AW4: =SUM('Entity Inputs'!AW4,'Entity Inputs'!AW10) | AX4: =SUM('Entity Inputs'!AX4,'Entity Inputs'!AX10) | AY4: =SUM('Entity Inputs'!AY4,'Entity Inputs'!AY10) | AZ4: =SUM('Entity Inputs'!AZ4,'Entity Inputs'!AZ10) | ... BR4: =SUM('Entity Inputs'!BR4,'Entity Inputs'!BR10) | BS4: =MIN('Entity Inputs'!BS4,'Entity Inputs'!BS10) | BT4: =SUM('Entity Inputs'!BT4,'Entity Inputs'!BT10) | BU4: =SUM('Entity Inputs'!BU4,'Entity Inputs'!BU10) | BV4: =SUM('Entity Inputs'!BV4,'Entity Inputs'!BV10) | BW4: =SUM('Entity Inputs'!BW4,'Entity Inputs'!BW10) | BX4: =SUM('Entity Inputs'!BX4,'Entity Inputs'!BX10) | BY4: =SUM('Entity Inputs'!BY4,'Entity Inputs'!BY10) | BZ4: =SUM('Entity Inputs'!BZ4,'Entity Inputs'!BZ10) | CA4: =SUM('Entity Inputs'!CA4,'Entity Inputs'!CA10) | ... FU4: =SUM('Entity Inputs'!FU4,'Entity Inputs'!FU10) | FV4: =AU4-V4-X4-BY4 | FW4: =FV4-AX4 | FX4: =CJ4+CL4-CK4 | FY4: =FX4-Parameters!$B$7 | FZ4: =FV4-BZ4-FY4 | GA4: =FZ4-DJ4 | GB4: =CB4-CC4 | GC4: =SUM(FV$4:FV4)*12/D4 | GD4: =IF(AU4=0,0,CJ4/AU4*C4) | GE4: =IF(V4=0,0,CK4/V4*C4) | GF4: =IF(V4=0,0,CL4/V4*C4) | GG4: =IF(OR(AS4=0,AT4=0,AV4=0),0,100*((AU4/AS4)/(AV4/AT4)-1)) | GH4: =SUM('Entity Inputs'!FV4,'Entity Inputs'!FV10) | GI4: =SUM('Entity Inputs'!FW4,'Entity Inputs'!FW10) | GJ4: =SUM('Entity Inputs'!FX4,'Entity Inputs'!FX10) | GK4: =SUM('Entity Inputs'!FY4,'Entity Inputs'!FY10) | GL4: =SUM('Entity Inputs'!FZ4,'Entity Inputs'!FZ10) | GM4: =SUM('Entity Inputs'!GA4,'Entity Inputs'!GA10) | GN4: =SQRT('Entity Inputs'!GB4^2+'Entity Inputs'!GB10^2) | GO4: =MIN('Entity Inputs'!GC4,'Entity Inputs'!GC10) | GP4: =SUM('Entity Inputs'!GD4,'Entity Inputs'!GD10) | GQ4: ='Entity Inputs'!GE4 | GR4: =SUM('Entity Inputs'!GF4,'Entity Inputs'!GF10)
A5: Group | B5: 2026-05 | C5: 31 | D5: 2 | E5: =SUM('Entity Inputs'!E5,'Entity Inputs'!E11) | F5: =SUM('Entity Inputs'!F5,'Entity Inputs'!F11) | G5: =SUM('Entity Inputs'!G5,'Entity Inputs'!G11) | H5: =SUM('Entity Inputs'!H5,'Entity Inputs'!H11) | I5: =SUM('Entity Inputs'!I5,'Entity Inputs'!I11) | J5: =SUM('Entity Inputs'!J5,'Entity Inputs'!J11) | K5: =SUM('Entity Inputs'!K5,'Entity Inputs'!K11) | L5: =SUM('Entity Inputs'!L5,'Entity Inputs'!L11) | ... AQ5: =SUM('Entity Inputs'!AQ5,'Entity Inputs'!AQ11) | AR5: =MIN('Entity Inputs'!AR5,'Entity Inputs'!AR11) | AS5: =SUM('Entity Inputs'!AS5,'Entity Inputs'!AS11) | AT5: =SUM('Entity Inputs'!AT5,'Entity Inputs'!AT11) | AU5: =SUM('Entity Inputs'!AU5,'Entity Inputs'!AU11) | AV5: =SUM('Entity Inputs'!AV5,'Entity Inputs'!AV11) | AW5: =SUM('Entity Inputs'!AW5,'Entity Inputs'!AW11) | AX5: =SUM('Entity Inputs'!AX5,'Entity Inputs'!AX11) | AY5: =SUM('Entity Inputs'!AY5,'Entity Inputs'!AY11) | AZ5: =SUM('Entity Inputs'!AZ5,'Entity Inputs'!AZ11) | ... BR5: =SUM('Entity Inputs'!BR5,'Entity Inputs'!BR11) | BS5: =MIN('Entity Inputs'!BS5,'Entity Inputs'!BS11) | BT5: =SUM('Entity Inputs'!BT5,'Entity Inputs'!BT11) | BU5: =SUM('Entity Inputs'!BU5,'Entity Inputs'!BU11) | BV5: =SUM('Entity Inputs'!BV5,'Entity Inputs'!BV11) | BW5: =SUM('Entity Inputs'!BW5,'Entity Inputs'!BW11) | BX5: =SUM('Entity Inputs'!BX5,'Entity Inputs'!BX11) | BY5: =SUM('Entity Inputs'!BY5,'Entity Inputs'!BY11) | BZ5: =SUM('Entity Inputs'!BZ5,'Entity Inputs'!BZ11) | CA5: =SUM('Entity Inputs'!CA5,'Entity Inputs'!CA11) | ... FU5: =SUM('Entity Inputs'!FU5,'Entity Inputs'!FU11) | FV5: =AU5-V5-X5-BY5 | FW5: =FV5-AX5 | FX5: =CJ5+CL5-CK5 | FY5: =FX5-FX4 | FZ5: =FV5-BZ5-FY5 | GA5: =FZ5-DJ5 | GB5: =CB5-CC5 | GC5: =SUM(FV$4:FV5)*12/D5 | GD5: =IF(AU5=0,0,CJ5/AU5*C5) | GE5: =IF(V5=0,0,CK5/V5*C5) | GF5: =IF(V5=0,0,CL5/V5*C5) | GG5: =IF(OR(AS5=0,AT5=0,AV5=0),0,100*((AU5/AS5)/(AV5/AT5)-1)) | GH5: =SUM('Entity Inputs'!FV5,'Entity Inputs'!FV11) | GI5: =SUM('Entity Inputs'!FW5,'Entity Inputs'!FW11) | GJ5: =SUM('Entity Inputs'!FX5,'Entity Inputs'!FX11) | GK5: =SUM('Entity Inputs'!FY5,'Entity Inputs'!FY11) | GL5: =SUM('Entity Inputs'!FZ5,'Entity Inputs'!FZ11) | GM5: =SUM('Entity Inputs'!GA5,'Entity Inputs'!GA11) | GN5: =SQRT('Entity Inputs'!GB5^2+'Entity Inputs'!GB11^2) | GO5: =MIN('Entity Inputs'!GC5,'Entity Inputs'!GC11) | GP5: =SUM('Entity Inputs'!GD5,'Entity Inputs'!GD11) | GQ5: ='Entity Inputs'!GE5 | GR5: =SUM('Entity Inputs'!GF5,'Entity Inputs'!GF11)
A6: Group | B6: 2026-06 | C6: 30 | D6: 3 | E6: =SUM('Entity Inputs'!E6,'Entity Inputs'!E12) | F6: =SUM('Entity Inputs'!F6,'Entity Inputs'!F12) | G6: =SUM('Entity Inputs'!G6,'Entity Inputs'!G12) | H6: =SUM('Entity Inputs'!H6,'Entity Inputs'!H12) | I6: =SUM('Entity Inputs'!I6,'Entity Inputs'!I12) | J6: =SUM('Entity Inputs'!J6,'Entity Inputs'!J12) | K6: =SUM('Entity Inputs'!K6,'Entity Inputs'!K12) | L6: =SUM('Entity Inputs'!L6,'Entity Inputs'!L12) | ... AQ6: =SUM('Entity Inputs'!AQ6,'Entity Inputs'!AQ12) | AR6: =MIN('Entity Inputs'!AR6,'Entity Inputs'!AR12) | AS6: =SUM('Entity Inputs'!AS6,'Entity Inputs'!AS12) | AT6: =SUM('Entity Inputs'!AT6,'Entity Inputs'!AT12) | AU6: =SUM('Entity Inputs'!AU6,'Entity Inputs'!AU12) | AV6: =SUM('Entity Inputs'!AV6,'Entity Inputs'!AV12) | AW6: =SUM('Entity Inputs'!AW6,'Entity Inputs'!AW12) | AX6: =SUM('Entity Inputs'!AX6,'Entity Inputs'!AX12) | AY6: =SUM('Entity Inputs'!AY6,'Entity Inputs'!AY12) | AZ6: =SUM('Entity Inputs'!AZ6,'Entity Inputs'!AZ12) | ... BR6: =SUM('Entity Inputs'!BR6,'Entity Inputs'!BR12) | BS6: =MIN('Entity Inputs'!BS6,'Entity Inputs'!BS12) | BT6: =SUM('Entity Inputs'!BT6,'Entity Inputs'!BT12) | BU6: =SUM('Entity Inputs'!BU6,'Entity Inputs'!BU12) | BV6: =SUM('Entity Inputs'!BV6,'Entity Inputs'!BV12) | BW6: =SUM('Entity Inputs'!BW6,'Entity Inputs'!BW12) | BX6: =SUM('Entity Inputs'!BX6,'Entity Inputs'!BX12) | BY6: =SUM('Entity Inputs'!BY6,'Entity Inputs'!BY12) | BZ6: =SUM('Entity Inputs'!BZ6,'Entity Inputs'!BZ12) | CA6: =SUM('Entity Inputs'!CA6,'Entity Inputs'!CA12) | ... FU6: =SUM('Entity Inputs'!FU6,'Entity Inputs'!FU12) | FV6: =AU6-V6-X6-BY6 | FW6: =FV6-AX6 | FX6: =CJ6+CL6-CK6 | FY6: =FX6-FX5 | FZ6: =FV6-BZ6-FY6 | GA6: =FZ6-DJ6 | GB6: =CB6-CC6 | GC6: =SUM(FV$4:FV6)*12/D6 | GD6: =IF(AU6=0,0,CJ6/AU6*C6) | GE6: =IF(V6=0,0,CK6/V6*C6) | GF6: =IF(V6=0,0,CL6/V6*C6) | GG6: =IF(OR(AS6=0,AT6=0,AV6=0),0,100*((AU6/AS6)/(AV6/AT6)-1)) | GH6: =SUM('Entity Inputs'!FV6,'Entity Inputs'!FV12) | GI6: =SUM('Entity Inputs'!FW6,'Entity Inputs'!FW12) | GJ6: =SUM('Entity Inputs'!FX6,'Entity Inputs'!FX12) | GK6: =SUM('Entity Inputs'!FY6,'Entity Inputs'!FY12) | GL6: =SUM('Entity Inputs'!FZ6,'Entity Inputs'!FZ12) | GM6: =SUM('Entity Inputs'!GA6,'Entity Inputs'!GA12) | GN6: =SQRT('Entity Inputs'!GB6^2+'Entity Inputs'!GB12^2) | GO6: =MIN('Entity Inputs'!GC6,'Entity Inputs'!GC12) | GP6: =SUM('Entity Inputs'!GD6,'Entity Inputs'!GD12) | GQ6: ='Entity Inputs'!GE6 | GR6: =SUM('Entity Inputs'!GF6,'Entity Inputs'!GF12)
A7: Group | B7: 2026-07 | C7: 31 | D7: 4 | E7: =SUM('Entity Inputs'!E7,'Entity Inputs'!E13) | F7: =SUM('Entity Inputs'!F7,'Entity Inputs'!F13) | G7: =SUM('Entity Inputs'!G7,'Entity Inputs'!G13) | H7: =SUM('Entity Inputs'!H7,'Entity Inputs'!H13) | I7: =SUM('Entity Inputs'!I7,'Entity Inputs'!I13) | J7: =SUM('Entity Inputs'!J7,'Entity Inputs'!J13) | K7: =SUM('Entity Inputs'!K7,'Entity Inputs'!K13) | L7: =SUM('Entity Inputs'!L7,'Entity Inputs'!L13) | ... AQ7: =SUM('Entity Inputs'!AQ7,'Entity Inputs'!AQ13) | AR7: =MIN('Entity Inputs'!AR7,'Entity Inputs'!AR13) | AS7: =SUM('Entity Inputs'!AS7,'Entity Inputs'!AS13) | AT7: =SUM('Entity Inputs'!AT7,'Entity Inputs'!AT13) | AU7: =SUM('Entity Inputs'!AU7,'Entity Inputs'!AU13) | AV7: =SUM('Entity Inputs'!AV7,'Entity Inputs'!AV13) | AW7: =SUM('Entity Inputs'!AW7,'Entity Inputs'!AW13) | AX7: =SUM('Entity Inputs'!AX7,'Entity Inputs'!AX13) | AY7: =SUM('Entity Inputs'!AY7,'Entity Inputs'!AY13) | AZ7: =SUM('Entity Inputs'!AZ7,'Entity Inputs'!AZ13) | ... BR7: =SUM('Entity Inputs'!BR7,'Entity Inputs'!BR13) | BS7: =MIN('Entity Inputs'!BS7,'Entity Inputs'!BS13) | BT7: =SUM('Entity Inputs'!BT7,'Entity Inputs'!BT13) | BU7: =SUM('Entity Inputs'!BU7,'Entity Inputs'!BU13) | BV7: =SUM('Entity Inputs'!BV7,'Entity Inputs'!BV13) | BW7: =SUM('Entity Inputs'!BW7,'Entity Inputs'!BW13) | BX7: =SUM('Entity Inputs'!BX7,'Entity Inputs'!BX13) | BY7: =SUM('Entity Inputs'!BY7,'Entity Inputs'!BY13) | BZ7: =SUM('Entity Inputs'!BZ7,'Entity Inputs'!BZ13) | CA7: =SUM('Entity Inputs'!CA7,'Entity Inputs'!CA13) | ... FU7: =SUM('Entity Inputs'!FU7,'Entity Inputs'!FU13) | FV7: =AU7-V7-X7-BY7 | FW7: =FV7-AX7 | FX7: =CJ7+CL7-CK7 | FY7: =FX7-FX6 | FZ7: =FV7-BZ7-FY7 | GA7: =FZ7-DJ7 | GB7: =CB7-CC7 | GC7: =SUM(FV$4:FV7)*12/D7 | GD7: =IF(AU7=0,0,CJ7/AU7*C7) | GE7: =IF(V7=0,0,CK7/V7*C7) | GF7: =IF(V7=0,0,CL7/V7*C7) | GG7: =IF(OR(AS7=0,AT7=0,AV7=0),0,100*((AU7/AS7)/(AV7/AT7)-1)) | GH7: =SUM('Entity Inputs'!FV7,'Entity Inputs'!FV13) | GI7: =SUM('Entity Inputs'!FW7,'Entity Inputs'!FW13) | GJ7: =SUM('Entity Inputs'!FX7,'Entity Inputs'!FX13) | GK7: =SUM('Entity Inputs'!FY7,'Entity Inputs'!FY13) | GL7: =SUM('Entity Inputs'!FZ7,'Entity Inputs'!FZ13) | GM7: =SUM('Entity Inputs'!GA7,'Entity Inputs'!GA13) | GN7: =SQRT('Entity Inputs'!GB7^2+'Entity Inputs'!GB13^2) | GO7: =MIN('Entity Inputs'!GC7,'Entity Inputs'!GC13) | GP7: =SUM('Entity Inputs'!GD7,'Entity Inputs'!GD13) | GQ7: ='Entity Inputs'!GE7 | GR7: =SUM('Entity Inputs'!GF7,'Entity Inputs'!GF13)
A8: Group | B8: 2026-08 | C8: 31 | D8: 5 | E8: =SUM('Entity Inputs'!E8,'Entity Inputs'!E14) | F8: =SUM('Entity Inputs'!F8,'Entity Inputs'!F14) | G8: =SUM('Entity Inputs'!G8,'Entity Inputs'!G14) | H8: =SUM('Entity Inputs'!H8,'Entity Inputs'!H14) | I8: =SUM('Entity Inputs'!I8,'Entity Inputs'!I14) | J8: =SUM('Entity Inputs'!J8,'Entity Inputs'!J14) | K8: =SUM('Entity Inputs'!K8,'Entity Inputs'!K14) | L8: =SUM('Entity Inputs'!L8,'Entity Inputs'!L14) | ... AQ8: =SUM('Entity Inputs'!AQ8,'Entity Inputs'!AQ14) | AR8: =MIN('Entity Inputs'!AR8,'Entity Inputs'!AR14) | AS8: =SUM('Entity Inputs'!AS8,'Entity Inputs'!AS14) | AT8: =SUM('Entity Inputs'!AT8,'Entity Inputs'!AT14) | AU8: =SUM('Entity Inputs'!AU8,'Entity Inputs'!AU14) | AV8: =SUM('Entity Inputs'!AV8,'Entity Inputs'!AV14) | AW8: =SUM('Entity Inputs'!AW8,'Entity Inputs'!AW14) | AX8: =SUM('Entity Inputs'!AX8,'Entity Inputs'!AX14) | AY8: =SUM('Entity Inputs'!AY8,'Entity Inputs'!AY14) | AZ8: =SUM('Entity Inputs'!AZ8,'Entity Inputs'!AZ14) | ... BR8: =SUM('Entity Inputs'!BR8,'Entity Inputs'!BR14) | BS8: =MIN('Entity Inputs'!BS8,'Entity Inputs'!BS14) | BT8: =SUM('Entity Inputs'!BT8,'Entity Inputs'!BT14) | BU8: =SUM('Entity Inputs'!BU8,'Entity Inputs'!BU14) | BV8: =SUM('Entity Inputs'!BV8,'Entity Inputs'!BV14) | BW8: =SUM('Entity Inputs'!BW8,'Entity Inputs'!BW14) | BX8: =SUM('Entity Inputs'!BX8,'Entity Inputs'!BX14) | BY8: =SUM('Entity Inputs'!BY8,'Entity Inputs'!BY14) | BZ8: =SUM('Entity Inputs'!BZ8,'Entity Inputs'!BZ14) | CA8: =SUM('Entity Inputs'!CA8,'Entity Inputs'!CA14) | ... FU8: =SUM('Entity Inputs'!FU8,'Entity Inputs'!FU14) | FV8: =AU8-V8-X8-BY8 | FW8: =FV8-AX8 | FX8: =CJ8+CL8-CK8 | FY8: =FX8-FX7 | FZ8: =FV8-BZ8-FY8 | GA8: =FZ8-DJ8 | GB8: =CB8-CC8 | GC8: =SUM(FV$4:FV8)*12/D8 | GD8: =IF(AU8=0,0,CJ8/AU8*C8) | GE8: =IF(V8=0,0,CK8/V8*C8) | GF8: =IF(V8=0,0,CL8/V8*C8) | GG8: =IF(OR(AS8=0,AT8=0,AV8=0),0,100*((AU8/AS8)/(AV8/AT8)-1)) | GH8: =SUM('Entity Inputs'!FV8,'Entity Inputs'!FV14) | GI8: =SUM('Entity Inputs'!FW8,'Entity Inputs'!FW14) | GJ8: =SUM('Entity Inputs'!FX8,'Entity Inputs'!FX14) | GK8: =SUM('Entity Inputs'!FY8,'Entity Inputs'!FY14) | GL8: =SUM('Entity Inputs'!FZ8,'Entity Inputs'!FZ14) | GM8: =SUM('Entity Inputs'!GA8,'Entity Inputs'!GA14) | GN8: =SQRT('Entity Inputs'!GB8^2+'Entity Inputs'!GB14^2) | GO8: =MIN('Entity Inputs'!GC8,'Entity Inputs'!GC14) | GP8: =SUM('Entity Inputs'!GD8,'Entity Inputs'!GD14) | GQ8: ='Entity Inputs'!GE8 | GR8: =SUM('Entity Inputs'!GF8,'Entity Inputs'!GF14)
A9: Group | B9: 2026-09 | C9: 30 | D9: 6 | E9: =SUM('Entity Inputs'!E9,'Entity Inputs'!E15) | F9: =SUM('Entity Inputs'!F9,'Entity Inputs'!F15) | G9: =SUM('Entity Inputs'!G9,'Entity Inputs'!G15) | H9: =SUM('Entity Inputs'!H9,'Entity Inputs'!H15) | I9: =SUM('Entity Inputs'!I9,'Entity Inputs'!I15) | J9: =SUM('Entity Inputs'!J9,'Entity Inputs'!J15) | K9: =SUM('Entity Inputs'!K9,'Entity Inputs'!K15) | L9: =SUM('Entity Inputs'!L9,'Entity Inputs'!L15) | ... AQ9: =SUM('Entity Inputs'!AQ9,'Entity Inputs'!AQ15) | AR9: =MIN('Entity Inputs'!AR9,'Entity Inputs'!AR15) | AS9: =SUM('Entity Inputs'!AS9,'Entity Inputs'!AS15) | AT9: =SUM('Entity Inputs'!AT9,'Entity Inputs'!AT15) | AU9: =SUM('Entity Inputs'!AU9,'Entity Inputs'!AU15) | AV9: =SUM('Entity Inputs'!AV9,'Entity Inputs'!AV15) | AW9: =SUM('Entity Inputs'!AW9,'Entity Inputs'!AW15) | AX9: =SUM('Entity Inputs'!AX9,'Entity Inputs'!AX15) | AY9: =SUM('Entity Inputs'!AY9,'Entity Inputs'!AY15) | AZ9: =SUM('Entity Inputs'!AZ9,'Entity Inputs'!AZ15) | ... BR9: =SUM('Entity Inputs'!BR9,'Entity Inputs'!BR15) | BS9: =MIN('Entity Inputs'!BS9,'Entity Inputs'!BS15) | BT9: =SUM('Entity Inputs'!BT9,'Entity Inputs'!BT15) | BU9: =SUM('Entity Inputs'!BU9,'Entity Inputs'!BU15) | BV9: =SUM('Entity Inputs'!BV9,'Entity Inputs'!BV15) | BW9: =SUM('Entity Inputs'!BW9,'Entity Inputs'!BW15) | BX9: =SUM('Entity Inputs'!BX9,'Entity Inputs'!BX15) | BY9: =SUM('Entity Inputs'!BY9,'Entity Inputs'!BY15) | BZ9: =SUM('Entity Inputs'!BZ9,'Entity Inputs'!BZ15) | CA9: =SUM('Entity Inputs'!CA9,'Entity Inputs'!CA15) | ... FU9: =SUM('Entity Inputs'!FU9,'Entity Inputs'!FU15) | FV9: =AU9-V9-X9-BY9 | FW9: =FV9-AX9 | FX9: =CJ9+CL9-CK9 | FY9: =FX9-FX8 | FZ9: =FV9-BZ9-FY9 | GA9: =FZ9-DJ9 | GB9: =CB9-CC9 | GC9: =SUM(FV$4:FV9)*12/D9 | GD9: =IF(AU9=0,0,CJ9/AU9*C9) | GE9: =IF(V9=0,0,CK9/V9*C9) | GF9: =IF(V9=0,0,CL9/V9*C9) | GG9: =IF(OR(AS9=0,AT9=0,AV9=0),0,100*((AU9/AS9)/(AV9/AT9)-1)) | GH9: =SUM('Entity Inputs'!FV9,'Entity Inputs'!FV15) | GI9: =SUM('Entity Inputs'!FW9,'Entity Inputs'!FW15) | GJ9: =SUM('Entity Inputs'!FX9,'Entity Inputs'!FX15) | GK9: =SUM('Entity Inputs'!FY9,'Entity Inputs'!FY15) | GL9: =SUM('Entity Inputs'!FZ9,'Entity Inputs'!FZ15) | GM9: =SUM('Entity Inputs'!GA9,'Entity Inputs'!GA15) | GN9: =SQRT('Entity Inputs'!GB9^2+'Entity Inputs'!GB15^2) | GO9: =MIN('Entity Inputs'!GC9,'Entity Inputs'!GC15) | GP9: =SUM('Entity Inputs'!GD9,'Entity Inputs'!GD15) | GQ9: ='Entity Inputs'!GE9 | GR9: =SUM('Entity Inputs'!GF9,'Entity Inputs'!GF15)

Sheet Entity Inputs
A1: Group | B1: Entity | C1: Month | D1: Days in month | E1: Calendar hours (h) | F1: Planned operating hours (h) | G1: Run hours (h) | H1: Unplanned downtime (h) | I1: Ideal output (t) | J1: Installed capacity (t) | K1: Planned production (t) | L1: Gross output (t) | M1: Good output (t) | N1: Feed input (t) | O1: Valuable content in feed (t) | P1: Valuable content recovered (t) | Q1: Production lost to downtime (t) | R1: Breakdowns (count) | S1: Repair hours (h) | T1: Preventive maintenance scheduled (count) | U1: Preventive maintenance completed (count) | V1: Variable cost (₹ thousand) | W1: Fuel cost (₹ thousand) | X1: Fixed cost (₹ thousand) | Y1: Water used (m³) | Z1: Emissions (t CO2e) | AA1: Energy used (GJ) | AB1: Production at risk (t) | AC1: Critical plant alerts (count) | AD1: Hours worked (h) | AE1: Recordable injuries (count) | AF1: Severity incidents (count) | AG1: Near misses (count) | AH1: Critical safety incidents (count) | AI1: Environmental excursions (count) | AJ1: Environmental violations (count) | AK1: Open EHS corrective actions (count) | AL1: Overdue EHS corrective actions (count) | AM1: EHS investigations due (count) | AN1: EHS investigations completed (count) | AO1: Critical materials at risk (count) | AP1: Dispatches (count) | AQ1: Delayed dispatches (count) | AR1: Days to permit expiry (days) | AS1: Sales volume (t) | AT1: Planned sales volume (t) | AU1: Revenue (₹ thousand) | AV1: Planned revenue (₹ thousand) | AW1: Power cost, part of variable cost (₹ thousand) | AX1: Depreciation and amortisation (₹ thousand) | AY1: Purchase-order lines due (count) | AZ1: Purchase-order lines delivered on time (count) | BA1: Quantity ordered from suppliers (t) | BB1: Quantity received (t) | BC1: Quantity rejected on quality (t) | BD1: Planned lead time, all deliveries (days) | BE1: Actual lead time, all deliveries (days) | BF1: Supplier spend (₹ thousand) | BG1: Spend with single-source suppliers (₹ thousand) | BH1: Supplier EHS incidents (count) | BI1: Regulatory filings pending (count) | BJ1: Regulatory deadlines in next 30 days (count) | BK1: Licences expiring in next 12 months (count) | BL1: Regulatory obligations due in next 30 days (count) | BM1: Regulatory obligations overdue (count) | BN1: Open regulatory actions (count) | BO1: Overdue compliance actions (count) | BP1: Regulatory breaches in the month (count) | BQ1: Events that trigger a disclosure clock (count) | BR1: EHS escalation clocks running (count) | BS1: Days until production plan is breached, forecast (days; 99 = not expected) | BT1: Planned production next month (t) | BU1: Forecast good output next month (t) | BV1: Forecast uncertainty next month (variance, t²) | BW1: Ideal output next month (t) | BX1: Forecast production lost to downtime next month (t) | BY1: Overheads, SG&A (₹ thousand) | BZ1: Tax paid (₹ thousand) | CA1: Capital employed, month end (₹ thousand) | CB1: Gross debt, month end (₹ thousand) | CC1: Cash, month end (₹ thousand) | CD1: Undrawn committed facilities (₹ thousand) | CE1: Debt service in the month (₹ thousand) | CF1: Debt maturing in next 12 months (₹ thousand) | CG1: Floating-rate debt (₹ thousand) | CH1: EBITDA as reported in the Board pack (₹ thousand) | CI1: Revenue in the flash report (₹ thousand) | CJ1: Trade receivables, month end (₹ thousand) | CK1: Trade payables, month end (₹ thousand) | CL1: Inventory, month end (₹ thousand) | CM1: Cash collected from customers (₹ thousand) | CN1: Cash released by working-capital actions (₹ thousand) | CO1: Cash due to be upstreamed to Group, next 30 days (₹ thousand) | CP1: Of which covered by available cash (₹ thousand) | CQ1: Invoices collected (count) | CR1: Days taken to collect, all invoices (days) | CS1: Agreed payment terms, all invoices (days) | CT1: Customers more than 30 days overdue (count) | CU1: Forecast EBITDA, rest of year (₹ thousand) | CV1: Planned EBITDA, rest of year (₹ thousand) | CW1: Forecast net cash flow, next 90 days (₹ thousand) | CX1: Forecast net debt at quarter end (₹ thousand) | CY1: Forecast EBITDA, 12 months to quarter end (₹ thousand) | CZ1: Foreign-currency exposure, gross (₹ thousand) | DA1: Foreign-currency exposure hedged (₹ thousand) | DB1: USD exposure, gross (₹ thousand) | DC1: USD exposure hedged (₹ thousand) | DD1: Change in value of hedges (₹ thousand) | DE1: Change in value of hedged items (₹ thousand) | DF1: Forecast foreign-currency flows, next 6 months (₹ thousand) | DG1: Of which hedged (₹ thousand) | DH1: Approved capex budget, full year (₹ thousand) | DI1: Capex committed to date (₹ thousand) | DJ1: Capex spent in the month (₹ thousand) | DK1: Capex work completed, valued at budget (₹ thousand) | DL1: Budget of capex projects at risk (₹ thousand) | DM1: Capex projects on track (count) | DN1: Capex projects at risk (count) | DO1: Capex projects off track (count) | DP1: Capex projects delayed (count) | DQ1: Contractor milestones due (count) | DR1: Contractor days late, all milestones (days) | DS1: Transformation initiatives on track (count) | DT1: Transformation initiatives at risk (count) | DU1: Transformation initiatives delayed (count) | DV1: Transformation milestones in plan (count) | DW1: Transformation milestones completed (count) | DX1: Programme benefits planned in the month (₹ thousand) | DY1: Programme benefits delivered in the month (₹ thousand) | DZ1: EBITDA benefit delivered (₹ thousand) | EA1: Cash benefit delivered (₹ thousand) | EB1: Cost savings delivered (₹ thousand) | EC1: Active supply contracts (count) | ED1: Contracts fully compliant (count) | EE1: Contracts expiring in next 90 days (count) | EF1: Suppliers not meeting EHS requirements (count) | EG1: Critical single-source suppliers (count) | EH1: Control failures (count) | EI1: High-severity control failures (count) | EJ1: Assurance reviews planned (count) | EK1: Assurance reviews completed (count) | EL1: Policy exceptions (count) | EM1: Unauthorised vendor uses (count) | EN1: Segregation-of-duties exceptions (count) | EO1: Unauthorised access events (count) | EP1: Data-sharing exceptions (count) | EQ1: Manual operational or system overrides (count) | ER1: Certification approvals past due date (count) | ES1: KPI values overridden (count) | ET1: Recurring data-quality issues (count) | EU1: Open audit findings (count) | EV1: Overdue assurance actions (count) | EW1: Repeat audit findings (count) | EX1: Leadership KPIs affected by open findings (count) | EY1: Evidence items required (count) | EZ1: Evidence items complete (count) | FA1: Audit findings closed in the month (count) | FB1: Days taken to close those findings (days) | FC1: Leadership KPI values reported (count) | FD1: Of which certified (count) | FE1: Of which inside the certification process (count) | FF1: Certifications overdue (count) | FG1: Open reconciliation breaks (count) | FH1: Material reconciliation breaks (count) | FI1: Records loaded to the data lake (count) | FJ1: Records reconciled to source (count) | FK1: Flash report lines (count) | FL1: Flash lines matching MIS (count) | FM1: Open critical alerts (count) | FN1: Alerts with no accepted owner (count) | FO1: Overdue actions (count) | FP1: Alerts resolved in the month (count) | FQ1: Days taken to resolve those alerts (days) | FR1: Escalations closed in the month (count) | FS1: Repeat issues raised in the month (count) | FT1: Root causes identified (count) | FU1: Root causes eliminated (count) | FV1: Full-time employees (FTE, count) | FW1: FCF plan, full year (₹ thousand) | FX1: Forecast FCF, rest of year (₹ thousand) | FY1: Forecast EBIT, rest of year (₹ thousand) | FZ1: Forecast capital employed at P12 (₹ thousand) | GA1: EBITDA plan, full year (₹ thousand) | GB1: EBITDA full-year forecast uncertainty, 1σ (₹ thousand) | GC1: Hours to nearest open disclosure deadline (999 = none) | GD1: Single-source suppliers with cover below lead time (count) | GE1: RM-1 price index (external, same for every entity) | GF1: Supply lanes with a disruption flag (count)
A2: group | B2: entity | C2: period | D2: days | E2: calendar_hours | F2: planned_op_hours | G2: run_hours | H2: unplanned_downtime_hours | I2: ideal_output_t | J2: installed_capacity_t | K2: planned_production_t | L2: gross_output_t | M2: good_output_t | N2: feed_input_t | O2: feed_contained_t | P2: recovered_contained_t | Q2: prod_loss_downtime_t | R2: failures | S2: repair_hours | T2: pm_scheduled | U2: pm_completed | V2: variable_cost_k | W2: fuel_cost_k | X2: fixed_cost_k | Y2: water_m3 | Z2: emissions_tco2e | AA2: energy_gj | AB2: production_at_risk_t | AC2: critical_plant_alerts | AD2: hours_worked | AE2: recordable_injuries | AF2: severity_incidents | AG2: near_misses | AH2: critical_safety_incidents | AI2: env_excursions | AJ2: env_violations | AK2: ehs_ca_open | AL2: ehs_ca_overdue | AM2: investigations_due | AN2: investigations_completed | AO2: critical_material_risks | AP2: dispatches_total | AQ2: dispatches_delayed | AR2: permit_days_to_expiry | AS2: sales_t | AT2: planned_sales_t | AU2: revenue_k | AV2: planned_revenue_k | AW2: power_cost_k | AX2: depreciation_k | AY2: po_lines_due | AZ2: po_lines_on_time | BA2: qty_ordered_t | BB2: qty_received_t | BC2: qty_rejected_t | BD2: lead_time_planned_days | BE2: lead_time_actual_days | BF2: supplier_spend_k | BG2: single_source_spend_k | BH2: supplier_ehs_incidents | BI2: pending_filings | BJ2: reg_deadlines_30d | BK2: licences_expiring_12m | BL2: reg_obligations_due_30d | BM2: reg_obligations_overdue | BN2: reg_actions_open | BO2: compliance_actions_overdue | BP2: reg_breaches | BQ2: disclosure_events_open | BR2: ehs_escalation_clocks | BS2: days_to_breach | BT2: planned_production_next_t | BU2: forecast_good_next_t | BV2: forecast_good_var_next | BW2: ideal_output_next_t | BX2: forecast_downtime_loss_next_t | BY2: overhead_k | BZ2: tax_paid_k | CA2: capital_employed_k | CB2: gross_debt_k | CC2: cash_k | CD2: undrawn_facilities_k | CE2: debt_service_k | CF2: debt_maturing_12m_k | CG2: floating_rate_debt_k | CH2: board_ebitda_k | CI2: flash_revenue_k | CJ2: receivables_k | CK2: payables_k | CL2: inventory_k | CM2: collections_k | CN2: cash_released_k | CO2: upstream_due_k | CP2: upstream_covered_k | CQ2: invoices_collected | CR2: collection_days | CS2: terms_days | CT2: customers_overdue | CU2: forecast_ebitda_rest_k | CV2: planned_ebitda_rest_k | CW2: forecast_net_cash_flow_90d_k | CX2: forecast_net_debt_k | CY2: forecast_ebitda_ltm_k | CZ2: fx_exposure_k | DA2: fx_hedged_k | DB2: usd_exposure_k | DC2: usd_hedged_k | DD2: hedge_value_change_k | DE2: hedged_item_value_change_k | DF2: fx_flows_6m_k | DG2: fx_hedged_6m_k | DH2: capex_budget_k | DI2: capex_committed_k | DJ2: capex_spend_k | DK2: capex_earned_value_k | DL2: capex_at_risk_k | DM2: projects_on_track | DN2: projects_at_risk | DO2: projects_off_track | DP2: projects_delayed | DQ2: contractor_milestones_due | DR2: contractor_days_late | DS2: initiatives_on_track | DT2: initiatives_at_risk | DU2: initiatives_delayed | DV2: milestones_total | DW2: milestones_done | DX2: benefits_planned_k | DY2: benefits_delivered_k | DZ2: ebitda_benefit_k | EA2: cash_benefit_k | EB2: cost_savings_k | EC2: contracts_total | ED2: contracts_compliant | EE2: contracts_expiring_90d | EF2: supplier_ehs_noncompliance | EG2: single_source_suppliers | EH2: control_failures | EI2: control_failures_high | EJ2: assurance_reviews_planned | EK2: assurance_reviews_done | EL2: policy_exceptions | EM2: unauthorized_vendor_uses | EN2: sod_exceptions | EO2: unauthorized_access_events | EP2: data_sharing_exceptions | EQ2: manual_overrides | ER2: cert_approvals_ageing | ES2: kpi_overrides | ET2: dq_issues_recurring | EU2: audit_findings_open | EV2: assurance_actions_overdue | EW2: repeat_findings | EX2: leadership_kpis_affected | EY2: evidence_required | EZ2: evidence_complete | FA2: findings_closed | FB2: finding_closure_days | FC2: kpis_leadership | FD2: kpis_certified | FE2: kpis_in_scope | FF2: certifications_overdue | FG2: recon_breaks_open | FH2: recon_breaks_material | FI2: lake_records_loaded | FJ2: lake_records_reconciled | FK2: mis_lines_total | FL2: mis_lines_matched | FM2: critical_alerts_open | FN2: alerts_unowned | FO2: actions_overdue | FP2: alerts_resolved | FQ2: alert_resolution_days | FR2: escalations_closed | FS2: repeat_issues | FT2: root_causes_identified | FU2: root_causes_eliminated | FV2: fte | FW2: fcf_plan_fy_k | FX2: forecast_fcf_rest_k | FY2: ebit_fcst_rest_k | FZ2: capital_employed_p12_k | GA2: ebitda_plan_fy_k | GB2: ebitda_fy_sigma_k | GC2: disclosure_deadline_h | GD2: single_source_elevated | GE2: rm1_price_index | GF2: freight_lanes_disrupted
E3: Sum of the entity's 3 plants (Plant Inputs sheet) | F3: Sum of the entity's 3 plants (Plant Inputs sheet) | G3: Sum of the entity's 3 plants (Plant Inputs sheet) | H3: Sum of the entity's 3 plants (Plant Inputs sheet) | I3: Sum of the entity's 3 plants (Plant Inputs sheet) | J3: Sum of the entity's 3 plants (Plant Inputs sheet) | K3: Sum of the entity's 3 plants (Plant Inputs sheet) | L3: Sum of the entity's 3 plants (Plant Inputs sheet) | M3: Sum of the entity's 3 plants (Plant Inputs sheet) | N3: Sum of the entity's 3 plants (Plant Inputs sheet) | O3: Sum of the entity's 3 plants (Plant Inputs sheet) | P3: Sum of the entity's 3 plants (Plant Inputs sheet) | Q3: Sum of the entity's 3 plants (Plant Inputs sheet) | R3: Sum of the entity's 3 plants (Plant Inputs sheet) | S3: Sum of the entity's 3 plants (Plant Inputs sheet) | T3: Sum of the entity's 3 plants (Plant Inputs sheet) | U3: Sum of the entity's 3 plants (Plant Inputs sheet) | V3: Sum of the entity's 3 plants (Plant Inputs sheet) | W3: Sum of the entity's 3 plants (Plant Inputs sheet) | X3: Sum of the entity's 3 plants (Plant Inputs sheet) | Y3: Sum of the entity's 3 plants (Plant Inputs sheet) | Z3: Sum of the entity's 3 plants (Plant Inputs sheet) | AA3: Sum of the entity's 3 plants (Plant Inputs sheet) | AB3: Sum of the entity's 3 plants (Plant Inputs sheet) | AC3: Sum of the entity's 3 plants (Plant Inputs sheet) | AD3: Sum of the entity's 3 plants (Plant Inputs sheet) | AE3: Sum of the entity's 3 plants (Plant Inputs sheet) | AF3: Sum of the entity's 3 plants (Plant Inputs sheet) | AG3: Sum of the entity's 3 plants (Plant Inputs sheet) | AH3: Sum of the entity's 3 plants (Plant Inputs sheet) | AI3: Sum of the entity's 3 plants (Plant Inputs sheet) | AJ3: Sum of the entity's 3 plants (Plant Inputs sheet) | AK3: Sum of the entity's 3 plants (Plant Inputs sheet) | AL3: Sum of the entity's 3 plants (Plant Inputs sheet) | AM3: Sum of the entity's 3 plants (Plant Inputs sheet) | AN3: Sum of the entity's 3 plants (Plant Inputs sheet) | AO3: Sum of the entity's 3 plants (Plant Inputs sheet) | AP3: Sum of the entity's 3 plants (Plant Inputs sheet) | AQ3: Sum of the entity's 3 plants (Plant Inputs sheet) | AR3: Lowest of the entity's 3 plants (Plant Inputs sheet) | AS3: Sum of the entity's 3 plants (Plant Inputs sheet) | AT3: Sum of the entity's 3 plants (Plant Inputs sheet) | AU3: Sum of the entity's 3 plants (Plant Inputs sheet) | AV3: Sum of the entity's 3 plants (Plant Inputs sheet) | AW3: Sum of the entity's 3 plants (Plant Inputs sheet) | AX3: Sum of the entity's 3 plants (Plant Inputs sheet) | AY3: Sum of the entity's 3 plants (Plant Inputs sheet) | AZ3: Sum of the entity's 3 plants (Plant Inputs sheet) | BA3: Sum of the entity's 3 plants (Plant Inputs sheet) | BB3: Sum of the entity's 3 plants (Plant Inputs sheet) | BC3: Sum of the entity's 3 plants (Plant Inputs sheet) | BD3: Sum of the entity's 3 plants (Plant Inputs sheet) | BE3: Sum of the entity's 3 plants (Plant Inputs sheet) | BF3: Sum of the entity's 3 plants (Plant Inputs sheet) | BG3: Sum of the entity's 3 plants (Plant Inputs sheet) | BH3: Sum of the entity's 3 plants (Plant Inputs sheet) | BI3: Sum of the entity's 3 plants (Plant Inputs sheet) | BJ3: Sum of the entity's 3 plants (Plant Inputs sheet) | BK3: Sum of the entity's 3 plants (Plant Inputs sheet) | BL3: Sum of the entity's 3 plants (Plant Inputs sheet) | BM3: Sum of the entity's 3 plants (Plant Inputs sheet) | BN3: Sum of the entity's 3 plants (Plant Inputs sheet) | BO3: Sum of the entity's 3 plants (Plant Inputs sheet) | BP3: Sum of the entity's 3 plants (Plant Inputs sheet) | BQ3: Sum of the entity's 3 plants (Plant Inputs sheet) | BR3: Sum of the entity's 3 plants (Plant Inputs sheet) | BS3: Lowest of the entity's 3 plants (Plant Inputs sheet) | BT3: Sum of the entity's 3 plants (Plant Inputs sheet) | BU3: Sum of the entity's 3 plants (Plant Inputs sheet) | BV3: Sum of the entity's 3 plants (Plant Inputs sheet) | BW3: Sum of the entity's 3 plants (Plant Inputs sheet) | BX3: Sum of the entity's 3 plants (Plant Inputs sheet) | BY3: Entity input (only exists at entity level) | BZ3: Entity input (only exists at entity level) | CA3: Entity input (only exists at entity level) | CB3: Entity input (only exists at entity level) | CC3: Entity input (only exists at entity level) | CD3: Entity input (only exists at entity level) | CE3: Entity input (only exists at entity level) | CF3: Entity input (only exists at entity level) | CG3: Entity input (only exists at entity level) | CH3: Entity input (only exists at entity level) | CI3: Entity input (only exists at entity level) | CJ3: Entity input (only exists at entity level) | CK3: Entity input (only exists at entity level) | CL3: Entity input (only exists at entity level) | CM3: Entity input (only exists at entity level) | CN3: Entity input (only exists at entity level) | CO3: Entity input (only exists at entity level) | CP3: Entity input (only exists at entity level) | CQ3: Entity input (only exists at entity level) | CR3: Entity input (only exists at entity level) | CS3: Entity input (only exists at entity level) | CT3: Entity input (only exists at entity level) | CU3: Entity input (only exists at entity level) | CV3: Entity input (only exists at entity level) | CW3: Entity input (only exists at entity level) | CX3: Entity input (only exists at entity level) | CY3: Entity input (only exists at entity level) | CZ3: Entity input (only exists at entity level) | DA3: Entity input (only exists at entity level) | DB3: Entity input (only exists at entity level) | DC3: Entity input (only exists at entity level) | DD3: Entity input (only exists at entity level) | DE3: Entity input (only exists at entity level) | DF3: Entity input (only exists at entity level) | DG3: Entity input (only exists at entity level) | DH3: Entity input (only exists at entity level) | DI3: Entity input (only exists at entity level) | DJ3: Entity input (only exists at entity level) | DK3: Entity input (only exists at entity level) | DL3: Entity input (only exists at entity level) | DM3: Entity input (only exists at entity level) | DN3: Entity input (only exists at entity level) | DO3: Entity input (only exists at entity level) | DP3: Entity input (only exists at entity level) | DQ3: Entity input (only exists at entity level) | DR3: Entity input (only exists at entity level) | DS3: Entity input (only exists at entity level) | DT3: Entity input (only exists at entity level) | DU3: Entity input (only exists at entity level) | DV3: Entity input (only exists at entity level) | DW3: Entity input (only exists at entity level) | DX3: Entity input (only exists at entity level) | DY3: Entity input (only exists at entity level) | DZ3: Entity input (only exists at entity level) | EA3: Entity input (only exists at entity level) | EB3: Entity input (only exists at entity level) | EC3: Entity input (only exists at entity level) | ED3: Entity input (only exists at entity level) | EE3: Entity input (only exists at entity level) | EF3: Entity input (only exists at entity level) | EG3: Entity input (only exists at entity level) | EH3: Entity input (only exists at entity level) | EI3: Entity input (only exists at entity level) | EJ3: Entity input (only exists at entity level) | EK3: Entity input (only exists at entity level) | EL3: Entity input (only exists at entity level) | EM3: Entity input (only exists at entity level) | EN3: Entity input (only exists at entity level) | EO3: Entity input (only exists at entity level) | EP3: Entity input (only exists at entity level) | EQ3: Entity input (only exists at entity level) | ER3: Entity input (only exists at entity level) | ES3: Entity input (only exists at entity level) | ET3: Entity input (only exists at entity level) | EU3: Entity input (only exists at entity level) | EV3: Entity input (only exists at entity level) | EW3: Entity input (only exists at entity level) | EX3: Entity input (only exists at entity level) | EY3: Entity input (only exists at entity level) | EZ3: Entity input (only exists at entity level) | FA3: Entity input (only exists at entity level) | FB3: Entity input (only exists at entity level) | FC3: Entity input (only exists at entity level) | FD3: Entity input (only exists at entity level) | FE3: Entity input (only exists at entity level) | FF3: Entity input (only exists at entity level) | FG3: Entity input (only exists at entity level) | FH3: Entity input (only exists at entity level) | FI3: Entity input (only exists at entity level) | FJ3: Entity input (only exists at entity level) | FK3: Entity input (only exists at entity level) | FL3: Entity input (only exists at entity level) | FM3: Entity input (only exists at entity level) | FN3: Entity input (only exists at entity level) | FO3: Entity input (only exists at entity level) | FP3: Entity input (only exists at entity level) | FQ3: Entity input (only exists at entity level) | FR3: Entity input (only exists at entity level) | FS3: Entity input (only exists at entity level) | FT3: Entity input (only exists at entity level) | FU3: Entity input (only exists at entity level) | FV3: Added (synthetic) for UI KPIs not in the source model | FW3: Added (synthetic) for UI KPIs not in the source model | FX3: Added (synthetic) for UI KPIs not in the source model | FY3: Added (synthetic) for UI KPIs not in the source model | FZ3: Added (synthetic) for UI KPIs not in the source model | GA3: Added (synthetic) for UI KPIs not in the source model | GB3: Added (synthetic) for UI KPIs not in the source model | GC3: Added (synthetic) for UI KPIs not in the source model | GD3: Added (synthetic) for UI KPIs not in the source model | GE3: Added (synthetic) for UI KPIs not in the source model | GF3: Added (synthetic) for UI KPIs not in the source model
A4: Group | B4: Entity A1 | C4: 2026-04 | D4: 30 | E4: =SUM('Plant Inputs'!F4,'Plant Inputs'!F10,'Plant Inputs'!F16) | F4: =SUM('Plant Inputs'!G4,'Plant Inputs'!G10,'Plant Inputs'!G16) | G4: =SUM('Plant Inputs'!H4,'Plant Inputs'!H10,'Plant Inputs'!H16) | H4: =SUM('Plant Inputs'!I4,'Plant Inputs'!I10,'Plant Inputs'!I16) | I4: =SUM('Plant Inputs'!J4,'Plant Inputs'!J10,'Plant Inputs'!J16) | J4: =SUM('Plant Inputs'!K4,'Plant Inputs'!K10,'Plant Inputs'!K16) | K4: =SUM('Plant Inputs'!L4,'Plant Inputs'!L10,'Plant Inputs'!L16) | L4: =SUM('Plant Inputs'!M4,'Plant Inputs'!M10,'Plant Inputs'!M16) | ... AQ4: =SUM('Plant Inputs'!AR4,'Plant Inputs'!AR10,'Plant Inputs'!AR16) | AR4: =MIN('Plant Inputs'!AS4,'Plant Inputs'!AS10,'Plant Inputs'!AS16) | AS4: =SUM('Plant Inputs'!AT4,'Plant Inputs'!AT10,'Plant Inputs'!AT16) | AT4: =SUM('Plant Inputs'!AU4,'Plant Inputs'!AU10,'Plant Inputs'!AU16) | AU4: =SUM('Plant Inputs'!AV4,'Plant Inputs'!AV10,'Plant Inputs'!AV16) | AV4: =SUM('Plant Inputs'!AW4,'Plant Inputs'!AW10,'Plant Inputs'!AW16) | AW4: =SUM('Plant Inputs'!AX4,'Plant Inputs'!AX10,'Plant Inputs'!AX16) | AX4: =SUM('Plant Inputs'!AY4,'Plant Inputs'!AY10,'Plant Inputs'!AY16) | AY4: =SUM('Plant Inputs'!AZ4,'Plant Inputs'!AZ10,'Plant Inputs'!AZ16) | AZ4: =SUM('Plant Inputs'!BA4,'Plant Inputs'!BA10,'Plant Inputs'!BA16) | ... BR4: =SUM('Plant Inputs'!BS4,'Plant Inputs'!BS10,'Plant Inputs'!BS16) | BS4: =MIN('Plant Inputs'!BT4,'Plant Inputs'!BT10,'Plant Inputs'!BT16) | BT4: =SUM('Plant Inputs'!BU4,'Plant Inputs'!BU10,'Plant Inputs'!BU16) | BU4: =SUM('Plant Inputs'!BV4,'Plant Inputs'!BV10,'Plant Inputs'!BV16) | BV4: =SUM('Plant Inputs'!BW4,'Plant Inputs'!BW10,'Plant Inputs'!BW16) | BW4: =SUM('Plant Inputs'!BX4,'Plant Inputs'!BX10,'Plant Inputs'!BX16) | BX4: =SUM('Plant Inputs'!BY4,'Plant Inputs'!BY10,'Plant Inputs'!BY16) | BY4: 54938.6 | BZ4: 35929.2 | CA4: 10800000 | CB4: 4736181 | CC4: 936181 | CD4: 436986.6 | CE4: 39900 | CF4: 442623.4 | CG4: 1357977.9 | CH4: 167684.4 | CI4: 1183542.5 | CJ4: 2022544.1 | CK4: 1234856.8 | CL4: 1354000.8 | CM4: 1181957.8 | CN4: 519.8 | CO4: 115844.2 | CP4: 115844.2 | CQ4: 418 | CR4: 18974 | CS4: 18810 | CT4: 0 | CU4: 997106.1 | CV4: 1011641.5 | CW4: 195977 | CX4: 3747391.4 | CY4: 1976093.2 | CZ4: 425331 | DA4: 314182 | DB4: 339270.5 | DC4: 248759 | DD4: 5649.1 | DE4: 6321.3 | DF4: 2572845.7 | DG4: 1994270.3 | DH4: 1000000 | DI4: 449046.9 | DJ4: 76777.1 | DK4: 380000 | DL4: 22271.5 | DM4: 5 | DN4: 1 | DO4: 0 | DP4: 0 | DQ4: 7 | DR4: 21 | DS4: 5 | DT4: 2 | DU4: 1 | DV4: 60 | DW4: 18 | DX4: 4834.8 | DY4: 3489.6 | DZ4: 987.8 | EA4: 352.3 | EB4: 600.2 | EC4: 72 | ED4: 69 | EE4: 1 | EF4: 0 | EG4: 2 | EH4: 1 | EI4: 0 | EJ4: 1 | EK4: 1 | EL4: 0 | EM4: 0 | EN4: 0 | EO4: 0 | EP4: 0 | EQ4: 1 | ER4: 1 | ES4: 0 | ET4: 1 | EU4: 2 | EV4: 0 | EW4: 0 | EX4: 0 | EY4: 50 | EZ4: 43 | FA4: 2 | FB4: 55 | FC4: 28 | FD4: 23 | FE4: 26 | FF4: 0 | FG4: 1 | FH4: 0 | FI4: 482362 | FJ4: 479530 | FK4: 400 | FL4: 381 | FM4: 0 | FN4: 0 | FO4: 0 | FP4: 6 | FQ4: 17.8 | FR4: 4 | FS4: 0 | FT4: 0 | FU4: 0 | FV4: 1340 | FW4: 309437.2 | FX4: 238064 | FY4: 1266630.9 | FZ4: 11124000 | GA4: 1199910.1 | GB4: 40773.6 | GC4: 999 | GD4: 0 | GE4: 100 | GF4: 0
A5: Group | B5: Entity A1 | C5: 2026-05 | D5: 31 | E5: =SUM('Plant Inputs'!F5,'Plant Inputs'!F11,'Plant Inputs'!F17) | F5: =SUM('Plant Inputs'!G5,'Plant Inputs'!G11,'Plant Inputs'!G17) | G5: =SUM('Plant Inputs'!H5,'Plant Inputs'!H11,'Plant Inputs'!H17) | H5: =SUM('Plant Inputs'!I5,'Plant Inputs'!I11,'Plant Inputs'!I17) | I5: =SUM('Plant Inputs'!J5,'Plant Inputs'!J11,'Plant Inputs'!J17) | J5: =SUM('Plant Inputs'!K5,'Plant Inputs'!K11,'Plant Inputs'!K17) | K5: =SUM('Plant Inputs'!L5,'Plant Inputs'!L11,'Plant Inputs'!L17) | L5: =SUM('Plant Inputs'!M5,'Plant Inputs'!M11,'Plant Inputs'!M17) | ... AQ5: =SUM('Plant Inputs'!AR5,'Plant Inputs'!AR11,'Plant Inputs'!AR17) | AR5: =MIN('Plant Inputs'!AS5,'Plant Inputs'!AS11,'Plant Inputs'!AS17) | AS5: =SUM('Plant Inputs'!AT5,'Plant Inputs'!AT11,'Plant Inputs'!AT17) | AT5: =SUM('Plant Inputs'!AU5,'Plant Inputs'!AU11,'Plant Inputs'!AU17) | AU5: =SUM('Plant Inputs'!AV5,'Plant Inputs'!AV11,'Plant Inputs'!AV17) | AV5: =SUM('Plant Inputs'!AW5,'Plant Inputs'!AW11,'Plant Inputs'!AW17) | AW5: =SUM('Plant Inputs'!AX5,'Plant Inputs'!AX11,'Plant Inputs'!AX17) | AX5: =SUM('Plant Inputs'!AY5,'Plant Inputs'!AY11,'Plant Inputs'!AY17) | AY5: =SUM('Plant Inputs'!AZ5,'Plant Inputs'!AZ11,'Plant Inputs'!AZ17) | AZ5: =SUM('Plant Inputs'!BA5,'Plant Inputs'!BA11,'Plant Inputs'!BA17) | ... BR5: =SUM('Plant Inputs'!BS5,'Plant Inputs'!BS11,'Plant Inputs'!BS17) | BS5: =MIN('Plant Inputs'!BT5,'Plant Inputs'!BT11,'Plant Inputs'!BT17) | BT5: =SUM('Plant Inputs'!BU5,'Plant Inputs'!BU11,'Plant Inputs'!BU17) | BU5: =SUM('Plant Inputs'!BV5,'Plant Inputs'!BV11,'Plant Inputs'!BV17) | BV5: =SUM('Plant Inputs'!BW5,'Plant Inputs'!BW11,'Plant Inputs'!BW17) | BW5: =SUM('Plant Inputs'!BX5,'Plant Inputs'!BX11,'Plant Inputs'!BX17) | BX5: =SUM('Plant Inputs'!BY5,'Plant Inputs'!BY11,'Plant Inputs'!BY17) | BY5: 50704.9 | BZ5: 14276.1 | CA5: 10843200 | CB5: 4689727.1 | CC5: 927727.1 | CD5: 438182.1 | CE5: 39501 | CF5: 484600.2 | CG5: 1326721.5 | CH5: 67821.9 | CI5: 1128801.3 | CJ5: 1918893.1 | CK5: 1294064.9 | CL5: 1295301.1 | CM5: 1117881.8 | CN5: 812.1 | CO5: 123248 | CP5: 123248 | CQ5: 382 | CR5: 17264 | CS5: 17190 | CT5: 0 | CU5: 403490.1 | CV5: 409969.6 | CW5: 76015 | CX5: 3729497.8 | CY5: 797457 | CZ5: 402268.2 | DA5: 277847.9 | DB5: 324638.2 | DC5: 229566.1 | DD5: 3941.5 | DE5: 4320.5 | DF5: 2519902.8 | DG5: 1969944 | DH5: 1000000 | DI5: 500855.7 | DJ5: 75177.6 | DK5: 422000 | DL5: 25527.6 | DM5: 5 | DN5: 1 | DO5: 0 | DP5: 0 | DQ5: 6 | DR5: 17 | DS5: 5 | DT5: 2 | DU5: 1 | DV5: 60 | DW5: 21 | DX5: 5163.3 | DY5: 3608.4 | DZ5: 951.1 | EA5: 446.1 | EB5: 650.5 | EC5: 72 | ED5: 68 | EE5: 2 | EF5: 0 | EG5: 2 | EH5: 0 | EI5: 0 | EJ5: 1 | EK5: 0 | EL5: 0 | EM5: 0 | EN5: 0 | EO5: 0 | EP5: 0 | EQ5: 0 | ER5: 1 | ES5: 0 | ET5: 1 | EU5: 3 | EV5: 0 | EW5: 0 | EX5: 0 | EY5: 50 | EZ5: 43 | FA5: 3 | FB5: 85 | FC5: 28 | FD5: 23 | FE5: 26 | FF5: 0 | FG5: 1 | FH5: 0 | FI5: 488893 | FJ5: 485890 | FK5: 400 | FL5: 379 | FM5: 0 | FN5: 0 | FO5: 0 | FP5: 4 | FQ5: 11.6 | FR5: 3 | FS5: 0 | FT5: 0 | FU5: 0 | FV5: 1344 | FW5: 1497784.5 | FX5: 1047557.6 | FY5: 678302.4 | FZ5: 11168496 | GA5: 658274.2 | GB5: 22368.5 | GC5: 999 | GD5: 0 | GE5: 101.2 | GF5: 0
A6: Group | B6: Entity A1 | C6: 2026-06 | D6: 30 | E6: =SUM('Plant Inputs'!F6,'Plant Inputs'!F12,'Plant Inputs'!F18) | F6: =SUM('Plant Inputs'!G6,'Plant Inputs'!G12,'Plant Inputs'!G18) | G6: =SUM('Plant Inputs'!H6,'Plant Inputs'!H12,'Plant Inputs'!H18) | H6: =SUM('Plant Inputs'!I6,'Plant Inputs'!I12,'Plant Inputs'!I18) | I6: =SUM('Plant Inputs'!J6,'Plant Inputs'!J12,'Plant Inputs'!J18) | J6: =SUM('Plant Inputs'!K6,'Plant Inputs'!K12,'Plant Inputs'!K18) | K6: =SUM('Plant Inputs'!L6,'Plant Inputs'!L12,'Plant Inputs'!L18) | L6: =SUM('Plant Inputs'!M6,'Plant Inputs'!M12,'Plant Inputs'!M18) | ... AQ6: =SUM('Plant Inputs'!AR6,'Plant Inputs'!AR12,'Plant Inputs'!AR18) | AR6: =MIN('Plant Inputs'!AS6,'Plant Inputs'!AS12,'Plant Inputs'!AS18) | AS6: =SUM('Plant Inputs'!AT6,'Plant Inputs'!AT12,'Plant Inputs'!AT18) | AT6: =SUM('Plant Inputs'!AU6,'Plant Inputs'!AU12,'Plant Inputs'!AU18) | AU6: =SUM('Plant Inputs'!AV6,'Plant Inputs'!AV12,'Plant Inputs'!AV18) | AV6: =SUM('Plant Inputs'!AW6,'Plant Inputs'!AW12,'Plant Inputs'!AW18) | AW6: =SUM('Plant Inputs'!AX6,'Plant Inputs'!AX12,'Plant Inputs'!AX18) | AX6: =SUM('Plant Inputs'!AY6,'Plant Inputs'!AY12,'Plant Inputs'!AY18) | AY6: =SUM('Plant Inputs'!AZ6,'Plant Inputs'!AZ12,'Plant Inputs'!AZ18) | AZ6: =SUM('Plant Inputs'!BA6,'Plant Inputs'!BA12,'Plant Inputs'!BA18) | ... BR6: =SUM('Plant Inputs'!BS6,'Plant Inputs'!BS12,'Plant Inputs'!BS18) | BS6: =MIN('Plant Inputs'!BT6,'Plant Inputs'!BT12,'Plant Inputs'!BT18) | BT6: =SUM('Plant Inputs'!BU6,'Plant Inputs'!BU12,'Plant Inputs'!BU18) | BU6: =SUM('Plant Inputs'!BV6,'Plant Inputs'!BV12,'Plant Inputs'!BV18) | BV6: =SUM('Plant Inputs'!BW6,'Plant Inputs'!BW12,'Plant Inputs'!BW18) | BW6: =SUM('Plant Inputs'!BX6,'Plant Inputs'!BX12,'Plant Inputs'!BX18) | BX6: =SUM('Plant Inputs'!BY6,'Plant Inputs'!BY12,'Plant Inputs'!BY18) | BY6: 48811.1 | BZ6: 29278.7 | CA6: 10886400 | CB6: 4635169.6 | CC6: 911169.6 | CD6: 460112.3 | CE6: 39102 | CF6: 476219.3 | CG6: 1378110 | CH6: 133983.3 | CI6: 1126086 | CJ6: 1943165.8 | CK6: 1271185.4 | CL6: 1281353 | CM6: 1116529.3 | CN6: 735.6 | CO6: 117650.6 | CP6: 117650.6 | CQ6: 425 | CR6: 19112 | CS6: 19125 | CT6: 0 | CU6: 802788 | CV6: 808463.3 | CW6: 155641.9 | CX6: 3675892.6 | CY6: 1569788.9 | CZ6: 418805.1 | DA6: 306320.8 | DB6: 327500.7 | DC6: 240203.5 | DD6: 4261.9 | DE6: 4555.5 | DF6: 2534835.3 | DG6: 1925015.9 | DH6: 1000000 | DI6: 561019.6 | DJ6: 73628.5 | DK6: 464000 | DL6: 21951.6 | DM6: 5 | DN6: 1 | DO6: 0 | DP6: 0 | DQ6: 4 | DR6: 14 | DS6: 5 | DT6: 2 | DU6: 1 | DV6: 60 | DW6: 24 | DX6: 5112.3 | DY6: 3419.9 | DZ6: 1071.3 | EA6: 417.2 | EB6: 665.8 | EC6: 72 | ED6: 69 | EE6: 2 | EF6: 0 | EG6: 2 | EH6: 0 | EI6: 0 | EJ6: 0 | EK6: 0 | EL6: 0 | EM6: 0 | EN6: 0 | EO6: 0 | EP6: 0 | EQ6: 2 | ER6: 0 | ES6: 0 | ET6: 1 | EU6: 2 | EV6: 0 | EW6: 0 | EX6: 0 | EY6: 50 | EZ6: 43 | FA6: 1 | FB6: 30 | FC6: 28 | FD6: 23 | FE6: 26 | FF6: 0 | FG6: 1 | FH6: 0 | FI6: 488990 | FJ6: 485052 | FK6: 400 | FL6: 378 | FM6: 0 | FN6: 0 | FO6: 0 | FP6: 4 | FQ6: 11.7 | FR6: 4 | FS6: 1 | FT6: 1 | FU6: 1 | FV6: 1348 | FW6: 990689.3 | FX6: 623603.5 | FY6: 657262.7 | FZ6: 11212992 | GA6: 1207944.7 | GB6: 41046.7 | GC6: 999 | GD6: 0 | GE6: 100.6 | GF6: 0
A7: Group | B7: Entity A1 | C7: 2026-07 | D7: 31 | E7: =SUM('Plant Inputs'!F7,'Plant Inputs'!F13,'Plant Inputs'!F19) | F7: =SUM('Plant Inputs'!G7,'Plant Inputs'!G13,'Plant Inputs'!G19) | G7: =SUM('Plant Inputs'!H7,'Plant Inputs'!H13,'Plant Inputs'!H19) | H7: =SUM('Plant Inputs'!I7,'Plant Inputs'!I13,'Plant Inputs'!I19) | I7: =SUM('Plant Inputs'!J7,'Plant Inputs'!J13,'Plant Inputs'!J19) | J7: =SUM('Plant Inputs'!K7,'Plant Inputs'!K13,'Plant Inputs'!K19) | K7: =SUM('Plant Inputs'!L7,'Plant Inputs'!L13,'Plant Inputs'!L19) | L7: =SUM('Plant Inputs'!M7,'Plant Inputs'!M13,'Plant Inputs'!M19) | ... AQ7: =SUM('Plant Inputs'!AR7,'Plant Inputs'!AR13,'Plant Inputs'!AR19) | AR7: =MIN('Plant Inputs'!AS7,'Plant Inputs'!AS13,'Plant Inputs'!AS19) | AS7: =SUM('Plant Inputs'!AT7,'Plant Inputs'!AT13,'Plant Inputs'!AT19) | AT7: =SUM('Plant Inputs'!AU7,'Plant Inputs'!AU13,'Plant Inputs'!AU19) | AU7: =SUM('Plant Inputs'!AV7,'Plant Inputs'!AV13,'Plant Inputs'!AV19) | AV7: =SUM('Plant Inputs'!AW7,'Plant Inputs'!AW13,'Plant Inputs'!AW19) | AW7: =SUM('Plant Inputs'!AX7,'Plant Inputs'!AX13,'Plant Inputs'!AX19) | AX7: =SUM('Plant Inputs'!AY7,'Plant Inputs'!AY13,'Plant Inputs'!AY19) | AY7: =SUM('Plant Inputs'!AZ7,'Plant Inputs'!AZ13,'Plant Inputs'!AZ19) | AZ7: =SUM('Plant Inputs'!BA7,'Plant Inputs'!BA13,'Plant Inputs'!BA19) | ... BR7: =SUM('Plant Inputs'!BS7,'Plant Inputs'!BS13,'Plant Inputs'!BS19) | BS7: =MIN('Plant Inputs'!BT7,'Plant Inputs'!BT13,'Plant Inputs'!BT19) | BT7: =SUM('Plant Inputs'!BU7,'Plant Inputs'!BU13,'Plant Inputs'!BU19) | BU7: =SUM('Plant Inputs'!BV7,'Plant Inputs'!BV13,'Plant Inputs'!BV19) | BV7: =SUM('Plant Inputs'!BW7,'Plant Inputs'!BW13,'Plant Inputs'!BW19) | BW7: =SUM('Plant Inputs'!BX7,'Plant Inputs'!BX13,'Plant Inputs'!BX19) | BX7: =SUM('Plant Inputs'!BY7,'Plant Inputs'!BY13,'Plant Inputs'!BY19) | BY7: 54606.3 | BZ7: 39213.2 | CA7: 10929600 | CB7: 4608966.7 | CC7: 922966.7 | CD7: 458165.4 | CE7: 38703 | CF7: 484735.8 | CG7: 1328589.5 | CH7: 178047.3 | CI7: 1185026 | CJ7: 1960349 | CK7: 1201672 | CL7: 1233450.9 | CM7: 1188396 | CN7: 694.8 | CO7: 119061.7 | CP7: 119061.7 | CQ7: 438 | CR7: 19650 | CS7: 19710 | CT7: 0 | CU7: 1065509.6 | CV7: 1075543.1 | CW7: 172153.2 | CX7: 3675766.9 | CY7: 2119721.6 | CZ7: 446718.8 | DA7: 323811.5 | DB7: 364424.2 | DC7: 266166.7 | DD7: 6450.1 | DE7: 7325.1 | DF7: 2637874.2 | DG7: 2001983.7 | DH7: 1000000 | DI7: 608680.1 | DJ7: 80895.5 | DK7: 506000 | DL7: 24159.6 | DM7: 5 | DN7: 1 | DO7: 0 | DP7: 0 | DQ7: 6 | DR7: 17 | DS7: 5 | DT7: 2 | DU7: 1 | DV7: 60 | DW7: 27 | DX7: 5177.6 | DY7: 3634.4 | DZ7: 1084 | EA7: 415.8 | EB7: 690.3 | EC7: 72 | ED7: 68 | EE7: 2 | EF7: 0 | EG7: 2 | EH7: 1 | EI7: 0 | EJ7: 1 | EK7: 0 | EL7: 0 | EM7: 0 | EN7: 0 | EO7: 0 | EP7: 0 | EQ7: 1 | ER7: 1 | ES7: 0 | ET7: 1 | EU7: 2 | EV7: 0 | EW7: 0 | EX7: 0 | EY7: 50 | EZ7: 43 | FA7: 3 | FB7: 82 | FC7: 28 | FD7: 23 | FE7: 26 | FF7: 0 | FG7: 1 | FH7: 0 | FI7: 517040 | FJ7: 512116 | FK7: 400 | FL7: 380 | FM7: 0 | FN7: 0 | FO7: 0 | FP7: 4 | FQ7: 12 | FR7: 3 | FS7: 1 | FT7: 1 | FU7: 1 | FV7: 1340 | FW7: 808451.6 | FX7: 452347.9 | FY7: 687792.6 | FZ7: 11257488 | GA7: 1662277 | GB7: 56485.1 | GC7: 999 | GD7: 0 | GE7: 102.3 | GF7: 0
A8: Group | B8: Entity A1 | C8: 2026-08 | D8: 31 | E8: =SUM('Plant Inputs'!F8,'Plant Inputs'!F14,'Plant Inputs'!F20) | F8: =SUM('Plant Inputs'!G8,'Plant Inputs'!G14,'Plant Inputs'!G20) | G8: =SUM('Plant Inputs'!H8,'Plant Inputs'!H14,'Plant Inputs'!H20) | H8: =SUM('Plant Inputs'!I8,'Plant Inputs'!I14,'Plant Inputs'!I20) | I8: =SUM('Plant Inputs'!J8,'Plant Inputs'!J14,'Plant Inputs'!J20) | J8: =SUM('Plant Inputs'!K8,'Plant Inputs'!K14,'Plant Inputs'!K20) | K8: =SUM('Plant Inputs'!L8,'Plant Inputs'!L14,'Plant Inputs'!L20) | L8: =SUM('Plant Inputs'!M8,'Plant Inputs'!M14,'Plant Inputs'!M20) | ... AQ8: =SUM('Plant Inputs'!AR8,'Plant Inputs'!AR14,'Plant Inputs'!AR20) | AR8: =MIN('Plant Inputs'!AS8,'Plant Inputs'!AS14,'Plant Inputs'!AS20) | AS8: =SUM('Plant Inputs'!AT8,'Plant Inputs'!AT14,'Plant Inputs'!AT20) | AT8: =SUM('Plant Inputs'!AU8,'Plant Inputs'!AU14,'Plant Inputs'!AU20) | AU8: =SUM('Plant Inputs'!AV8,'Plant Inputs'!AV14,'Plant Inputs'!AV20) | AV8: =SUM('Plant Inputs'!AW8,'Plant Inputs'!AW14,'Plant Inputs'!AW20) | AW8: =SUM('Plant Inputs'!AX8,'Plant Inputs'!AX14,'Plant Inputs'!AX20) | AX8: =SUM('Plant Inputs'!AY8,'Plant Inputs'!AY14,'Plant Inputs'!AY20) | AY8: =SUM('Plant Inputs'!AZ8,'Plant Inputs'!AZ14,'Plant Inputs'!AZ20) | AZ8: =SUM('Plant Inputs'!BA8,'Plant Inputs'!BA14,'Plant Inputs'!BA20) | ... BR8: =SUM('Plant Inputs'!BS8,'Plant Inputs'!BS14,'Plant Inputs'!BS20) | BS8: =MIN('Plant Inputs'!BT8,'Plant Inputs'!BT14,'Plant Inputs'!BT20) | BT8: =SUM('Plant Inputs'!BU8,'Plant Inputs'!BU14,'Plant Inputs'!BU20) | BU8: =SUM('Plant Inputs'!BV8,'Plant Inputs'!BV14,'Plant Inputs'!BV20) | BV8: =SUM('Plant Inputs'!BW8,'Plant Inputs'!BW14,'Plant Inputs'!BW20) | BW8: =SUM('Plant Inputs'!BX8,'Plant Inputs'!BX14,'Plant Inputs'!BX20) | BX8: =SUM('Plant Inputs'!BY8,'Plant Inputs'!BY14,'Plant Inputs'!BY20) | BY8: 51744.4 | BZ8: 26325.4 | CA8: 10972800 | CB8: 4538500.4 | CC8: 890500.4 | CD8: 450000.3 | CE8: 38304 | CF8: 430017.2 | CG8: 1434553 | CH8: 141020.6 | CI8: 1178034.5 | CJ8: 1942517.4 | CK8: 1220348.1 | CL8: 1299238.7 | CM8: 1172897 | CN8: 595.6 | CO8: 111451.4 | CP8: 85831.1 | CQ8: 429 | CR8: 20245 | CS8: 19305 | CT8: 2 | CU8: 814011.1 | CV8: 844976.7 | CW8: 168030.4 | CX8: 3603080.9 | CY8: 1658464.7 | CZ8: 420833 | DA8: 289646.6 | DB8: 345045.2 | DC8: 254976 | DD8: 5930.1 | DE8: 6390.2 | DF8: 2577012.3 | DG8: 2005260.4 | DH8: 1000000 | DI8: 671475.8 | DJ8: 82465.6 | DK8: 548000 | DL8: 21559.1 | DM8: 5 | DN8: 1 | DO8: 0 | DP8: 0 | DQ8: 7 | DR8: 21 | DS8: 5 | DT8: 2 | DU8: 1 | DV8: 60 | DW8: 30 | DX8: 5059.6 | DY8: 3578 | DZ8: 1035 | EA8: 350.8 | EB8: 639.5 | EC8: 72 | ED8: 68 | EE8: 2 | EF8: 0 | EG8: 2 | EH8: 0 | EI8: 0 | EJ8: 1 | EK8: 1 | EL8: 1 | EM8: 0 | EN8: 0 | EO8: 0 | EP8: 0 | EQ8: 2 | ER8: 1 | ES8: 0 | ET8: 1 | EU8: 3 | EV8: 0 | EW8: 0 | EX8: 0 | EY8: 50 | EZ8: 43 | FA8: 2 | FB8: 60 | FC8: 28 | FD8: 23 | FE8: 26 | FF8: 0 | FG8: 1 | FH8: 1 | FI8: 489715 | FJ8: 486862 | FK8: 400 | FL8: 382 | FM8: 1 | FN8: 0 | FO8: 0 | FP8: 4 | FQ8: 12.2 | FR8: 3 | FS8: 1 | FT8: 1 | FU8: 1 | FV8: 1344 | FW8: 654005.2 | FX8: 320190 | FY8: 606400.6 | FZ8: 11301984 | GA8: 1548222.6 | GB8: 52609.5 | GC8: 999 | GD8: 1 | GE8: 103.1 | GF8: 0
A9: Group | B9: Entity A1 | C9: 2026-09 | D9: 30 | E9: =SUM('Plant Inputs'!F9,'Plant Inputs'!F15,'Plant Inputs'!F21) | F9: =SUM('Plant Inputs'!G9,'Plant Inputs'!G15,'Plant Inputs'!G21) | G9: =SUM('Plant Inputs'!H9,'Plant Inputs'!H15,'Plant Inputs'!H21) | H9: =SUM('Plant Inputs'!I9,'Plant Inputs'!I15,'Plant Inputs'!I21) | I9: =SUM('Plant Inputs'!J9,'Plant Inputs'!J15,'Plant Inputs'!J21) | J9: =SUM('Plant Inputs'!K9,'Plant Inputs'!K15,'Plant Inputs'!K21) | K9: =SUM('Plant Inputs'!L9,'Plant Inputs'!L15,'Plant Inputs'!L21) | L9: =SUM('Plant Inputs'!M9,'Plant Inputs'!M15,'Plant Inputs'!M21) | ... AQ9: =SUM('Plant Inputs'!AR9,'Plant Inputs'!AR15,'Plant Inputs'!AR21) | AR9: =MIN('Plant Inputs'!AS9,'Plant Inputs'!AS15,'Plant Inputs'!AS21) | AS9: =SUM('Plant Inputs'!AT9,'Plant Inputs'!AT15,'Plant Inputs'!AT21) | AT9: =SUM('Plant Inputs'!AU9,'Plant Inputs'!AU15,'Plant Inputs'!AU21) | AU9: =SUM('Plant Inputs'!AV9,'Plant Inputs'!AV15,'Plant Inputs'!AV21) | AV9: =SUM('Plant Inputs'!AW9,'Plant Inputs'!AW15,'Plant Inputs'!AW21) | AW9: =SUM('Plant Inputs'!AX9,'Plant Inputs'!AX15,'Plant Inputs'!AX21) | AX9: =SUM('Plant Inputs'!AY9,'Plant Inputs'!AY15,'Plant Inputs'!AY21) | AY9: =SUM('Plant Inputs'!AZ9,'Plant Inputs'!AZ15,'Plant Inputs'!AZ21) | AZ9: =SUM('Plant Inputs'!BA9,'Plant Inputs'!BA15,'Plant Inputs'!BA21) | ... BR9: =SUM('Plant Inputs'!BS9,'Plant Inputs'!BS15,'Plant Inputs'!BS21) | BS9: =MIN('Plant Inputs'!BT9,'Plant Inputs'!BT15,'Plant Inputs'!BT21) | BT9: =SUM('Plant Inputs'!BU9,'Plant Inputs'!BU15,'Plant Inputs'!BU21) | BU9: =SUM('Plant Inputs'!BV9,'Plant Inputs'!BV15,'Plant Inputs'!BV21) | BV9: =SUM('Plant Inputs'!BW9,'Plant Inputs'!BW15,'Plant Inputs'!BW21) | BW9: =SUM('Plant Inputs'!BX9,'Plant Inputs'!BX15,'Plant Inputs'!BX21) | BX9: =SUM('Plant Inputs'!BY9,'Plant Inputs'!BY15,'Plant Inputs'!BY21) | BY9: 50448.8 | BZ9: 37174.1 | CA9: 11016000 | CB9: 4577082.6 | CC9: 967082.6 | CD9: 449031.4 | CE9: 37905 | CF9: 486342.3 | CG9: 1440701.8 | CH9: 201088.9 | CI9: 1153045 | CJ9: 2003213.3 | CK9: 1205957.8 | CL9: 1214918.8 | CM9: 1158127.3 | CN9: 843.3 | CO9: 122055.2 | CP9: 94842.6 | CQ9: 395 | CR9: 18541 | CS9: 17775 | CT9: 2 | CU9: 1161973.5 | CV9: 1210504.1 | CW9: 164691.3 | CX9: 3584699.7 | CY9: 2391562.6 | CZ9: 437492.4 | DA9: 314223.8 | DB9: 354951.3 | DC9: 255711.3 | DD9: 7006.3 | DE9: 7653.2 | DF9: 2579231.2 | DG9: 2009224.9 | DH9: 1000000 | DI9: 722629.1 | DJ9: 79170.5 | DK9: 590000 | DL9: 20798.4 | DM9: 5 | DN9: 1 | DO9: 0 | DP9: 0 | DQ9: 4 | DR9: 10 | DS9: 5 | DT9: 2 | DU9: 1 | DV9: 60 | DW9: 32 | DX9: 4825.8 | DY9: 3192.7 | DZ9: 1075 | EA9: 391.3 | EB9: 648.2 | EC9: 72 | ED9: 69 | EE9: 2 | EF9: 0 | EG9: 2 | EH9: 0 | EI9: 0 | EJ9: 0 | EK9: 0 | EL9: 1 | EM9: 0 | EN9: 0 | EO9: 0 | EP9: 0 | EQ9: 1 | ER9: 1 | ES9: 0 | ET9: 1 | EU9: 2 | EV9: 0 | EW9: 0 | EX9: 0 | EY9: 50 | EZ9: 43 | FA9: 3 | FB9: 88 | FC9: 28 | FD9: 23 | FE9: 26 | FF9: 0 | FG9: 1 | FH9: 1 | FI9: 500044 | FJ9: 494690 | FK9: 400 | FL9: 377 | FM9: 1 | FN9: 0 | FO9: 0 | FP9: 6 | FQ9: 16.7 | FR9: 3 | FS9: 1 | FT9: 1 | FU9: 1 | FV9: 1348 | FW9: 756293 | FX9: 317373 | FY9: 579545.9 | FZ9: 11346480 | GA9: 2114103.1 | GB9: 71838.5 | GC9: 38 | GD9: 1 | GE9: 105.3 | GF9: 1
A10: Group | B10: Entity A2 | C10: 2026-04 | D10: 30 | E10: =SUM('Plant Inputs'!F22,'Plant Inputs'!F28,'Plant Inputs'!F34) | F10: =SUM('Plant Inputs'!G22,'Plant Inputs'!G28,'Plant Inputs'!G34) | G10: =SUM('Plant Inputs'!H22,'Plant Inputs'!H28,'Plant Inputs'!H34) | H10: =SUM('Plant Inputs'!I22,'Plant Inputs'!I28,'Plant Inputs'!I34) | I10: =SUM('Plant Inputs'!J22,'Plant Inputs'!J28,'Plant Inputs'!J34) | J10: =SUM('Plant Inputs'!K22,'Plant Inputs'!K28,'Plant Inputs'!K34) | K10: =SUM('Plant Inputs'!L22,'Plant Inputs'!L28,'Plant Inputs'!L34) | L10: =SUM('Plant Inputs'!M22,'Plant Inputs'!M28,'Plant Inputs'!M34) | ... AQ10: =SUM('Plant Inputs'!AR22,'Plant Inputs'!AR28,'Plant Inputs'!AR34) | AR10: =MIN('Plant Inputs'!AS22,'Plant Inputs'!AS28,'Plant Inputs'!AS34) | AS10: =SUM('Plant Inputs'!AT22,'Plant Inputs'!AT28,'Plant Inputs'!AT34) | AT10: =SUM('Plant Inputs'!AU22,'Plant Inputs'!AU28,'Plant Inputs'!AU34) | AU10: =SUM('Plant Inputs'!AV22,'Plant Inputs'!AV28,'Plant Inputs'!AV34) | AV10: =SUM('Plant Inputs'!AW22,'Plant Inputs'!AW28,'Plant Inputs'!AW34) | AW10: =SUM('Plant Inputs'!AX22,'Plant Inputs'!AX28,'Plant Inputs'!AX34) | AX10: =SUM('Plant Inputs'!AY22,'Plant Inputs'!AY28,'Plant Inputs'!AY34) | AY10: =SUM('Plant Inputs'!AZ22,'Plant Inputs'!AZ28,'Plant Inputs'!AZ34) | AZ10: =SUM('Plant Inputs'!BA22,'Plant Inputs'!BA28,'Plant Inputs'!BA34) | ... BR10: =SUM('Plant Inputs'!BS22,'Plant Inputs'!BS28,'Plant Inputs'!BS34) | BS10: =MIN('Plant Inputs'!BT22,'Plant Inputs'!BT28,'Plant Inputs'!BT34) | BT10: =SUM('Plant Inputs'!BU22,'Plant Inputs'!BU28,'Plant Inputs'!BU34) | BU10: =SUM('Plant Inputs'!BV22,'Plant Inputs'!BV28,'Plant Inputs'!BV34) | BV10: =SUM('Plant Inputs'!BW22,'Plant Inputs'!BW28,'Plant Inputs'!BW34) | BW10: =SUM('Plant Inputs'!BX22,'Plant Inputs'!BX28,'Plant Inputs'!BX34) | BX10: =SUM('Plant Inputs'!BY22,'Plant Inputs'!BY28,'Plant Inputs'!BY34) | BY10: 53970.6 | BZ10: 29831.4 | CA10: 10000000 | CB10: 4362932.7 | CC10: 1162932.7 | CD10: 466410.4 | CE10: 33600 | CF10: 401681.3 | CG10: 1363476.4 | CH10: 154555.6 | CI10: 1144080.8 | CJ10: 1670373.1 | CK10: 1974556.3 | CL10: 1075076.8 | CM10: 1128578.1 | CN10: 3306.5 | CO10: 70251.8 | CP10: 70251.8 | CQ10: 374 | CR10: 16795 | CS10: 16830 | CT10: 0 | CU10: 924339.3 | CV10: 930922.9 | CW10: 142690.9 | CX10: 3180825.9 | CY10: 1800841.3 | CZ10: 298827.6 | DA10: 219185.2 | DB10: 234572 | DC10: 172016.9 | DD10: 4570.2 | DE10: 5149.9 | DF10: 1763562.5 | DG10: 1050789.6 | DH10: 860000 | DI10: 389482.4 | DJ10: 69779.5 | DK10: 326800 | DL10: 116966 | DM10: 4 | DN10: 1 | DO10: 0 | DP10: 0 | DQ10: 4 | DR10: 5 | DS10: 10 | DT10: 4 | DU10: 2 | DV10: 64 | DW10: 19 | DX10: 9130.7 | DY10: 3031.5 | DZ10: 1376 | EA10: 1091.6 | EB10: 1173.7 | EC10: 68 | ED10: 66 | EE10: 2 | EF10: 1 | EG10: 1 | EH10: 0 | EI10: 0 | EJ10: 1 | EK10: 1 | EL10: 0 | EM10: 0 | EN10: 0 | EO10: 0 | EP10: 0 | EQ10: 0 | ER10: 0 | ES10: 0 | ET10: 0 | EU10: 6 | EV10: 0 | EW10: 1 | EX10: 1 | EY10: 58 | EZ10: 52 | FA10: 3 | FB10: 111 | FC10: 28 | FD10: 24 | FE10: 26 | FF10: 1 | FG10: 0 | FH10: 0 | FI10: 514962 | FJ10: 512268 | FK10: 420 | FL10: 413 | FM10: 0 | FN10: 0 | FO10: 0 | FP10: 6 | FQ10: 12.9 | FR10: 8 | FS10: 0 | FT10: 1 | FU10: 1 | FV10: 1290 | FW10: 535811.3 | FX10: 476992.3 | FY10: 1250750.6 | FZ10: 10100000 | GA10: 1073055 | GB10: 37745.7 | GC10: 999 | GD10: 0 | GE10: 100 | GF10: 0
A11: Group | B11: Entity A2 | C11: 2026-05 | D11: 31 | E11: =SUM('Plant Inputs'!F23,'Plant Inputs'!F29,'Plant Inputs'!F35) | F11: =SUM('Plant Inputs'!G23,'Plant Inputs'!G29,'Plant Inputs'!G35) | G11: =SUM('Plant Inputs'!H23,'Plant Inputs'!H29,'Plant Inputs'!H35) | H11: =SUM('Plant Inputs'!I23,'Plant Inputs'!I29,'Plant Inputs'!I35) | I11: =SUM('Plant Inputs'!J23,'Plant Inputs'!J29,'Plant Inputs'!J35) | J11: =SUM('Plant Inputs'!K23,'Plant Inputs'!K29,'Plant Inputs'!K35) | K11: =SUM('Plant Inputs'!L23,'Plant Inputs'!L29,'Plant Inputs'!L35) | L11: =SUM('Plant Inputs'!M23,'Plant Inputs'!M29,'Plant Inputs'!M35) | ... AQ11: =SUM('Plant Inputs'!AR23,'Plant Inputs'!AR29,'Plant Inputs'!AR35) | AR11: =MIN('Plant Inputs'!AS23,'Plant Inputs'!AS29,'Plant Inputs'!AS35) | AS11: =SUM('Plant Inputs'!AT23,'Plant Inputs'!AT29,'Plant Inputs'!AT35) | AT11: =SUM('Plant Inputs'!AU23,'Plant Inputs'!AU29,'Plant Inputs'!AU35) | AU11: =SUM('Plant Inputs'!AV23,'Plant Inputs'!AV29,'Plant Inputs'!AV35) | AV11: =SUM('Plant Inputs'!AW23,'Plant Inputs'!AW29,'Plant Inputs'!AW35) | AW11: =SUM('Plant Inputs'!AX23,'Plant Inputs'!AX29,'Plant Inputs'!AX35) | AX11: =SUM('Plant Inputs'!AY23,'Plant Inputs'!AY29,'Plant Inputs'!AY35) | AY11: =SUM('Plant Inputs'!AZ23,'Plant Inputs'!AZ29,'Plant Inputs'!AZ35) | AZ11: =SUM('Plant Inputs'!BA23,'Plant Inputs'!BA29,'Plant Inputs'!BA35) | ... BR11: =SUM('Plant Inputs'!BS23,'Plant Inputs'!BS29,'Plant Inputs'!BS35) | BS11: =MIN('Plant Inputs'!BT23,'Plant Inputs'!BT29,'Plant Inputs'!BT35) | BT11: =SUM('Plant Inputs'!BU23,'Plant Inputs'!BU29,'Plant Inputs'!BU35) | BU11: =SUM('Plant Inputs'!BV23,'Plant Inputs'!BV29,'Plant Inputs'!BV35) | BV11: =SUM('Plant Inputs'!BW23,'Plant Inputs'!BW29,'Plant Inputs'!BW35) | BW11: =SUM('Plant Inputs'!BX23,'Plant Inputs'!BX29,'Plant Inputs'!BX35) | BX11: =SUM('Plant Inputs'!BY23,'Plant Inputs'!BY29,'Plant Inputs'!BY35) | BY11: 50050.4 | BZ11: 40075 | CA11: 10040000 | CB11: 4257934.5 | CC11: 1089934.5 | CD11: 435228.2 | CE11: 33264 | CF11: 438317.9 | CG11: 1192536.2 | CH11: 184420.1 | CI11: 1082983.6 | CJ11: 1563623.2 | CK11: 1768166.1 | CL11: 1004411.8 | CM11: 1072786 | CN11: 2852.3 | CO11: 74102.9 | CP11: 74102.9 | CQ11: 352 | CR11: 15761 | CS11: 15840 | CT11: 1 | CU11: 1097997.4 | CV11: 1112277.8 | CW11: 184653.8 | CX11: 3151290.2 | CY11: 2164395 | CZ11: 313040.6 | DA11: 229961.2 | DB11: 256509 | DC11: 181113.8 | DD11: 4017.3 | DE11: 4281.1 | DF11: 1785518 | DG11: 1091259.8 | DH11: 860000 | DI11: 432467.4 | DJ11: 69889.8 | DK11: 369800 | DL11: 136303.5 | DM11: 4 | DN11: 1 | DO11: 0 | DP11: 0 | DQ11: 4 | DR11: 5 | DS11: 10 | DT11: 4 | DU11: 2 | DV11: 64 | DW11: 22 | DX11: 9302.1 | DY11: 3474.3 | DZ11: 1389.1 | EA11: 1046.6 | EB11: 1244.6 | EC11: 68 | ED11: 65 | EE11: 3 | EF11: 1 | EG11: 1 | EH11: 0 | EI11: 0 | EJ11: 1 | EK11: 1 | EL11: 0 | EM11: 0 | EN11: 0 | EO11: 0 | EP11: 0 | EQ11: 2 | ER11: 1 | ES11: 0 | ET11: 0 | EU11: 5 | EV11: 0 | EW11: 1 | EX11: 1 | EY11: 58 | EZ11: 52 | FA11: 1 | FB11: 37 | FC11: 28 | FD11: 24 | FE11: 26 | FF11: 1 | FG11: 0 | FH11: 0 | FI11: 481373 | FJ11: 478757 | FK11: 420 | FL11: 411 | FM11: 0 | FN11: 0 | FO11: 0 | FP11: 4 | FQ11: 7.7 | FR11: 7 | FS11: 1 | FT11: 1 | FU11: 1 | FV11: 1287 | FW11: 554094.5 | FX11: 448425.9 | FY11: 1297723.1 | FZ11: 10140400 | GA11: 1429724.5 | GB11: 50291.8 | GC11: 999 | GD11: 0 | GE11: 101.2 | GF11: 0
A12: Group | B12: Entity A2 | C12: 2026-06 | D12: 30 | E12: =SUM('Plant Inputs'!F24,'Plant Inputs'!F30,'Plant Inputs'!F36) | F12: =SUM('Plant Inputs'!G24,'Plant Inputs'!G30,'Plant Inputs'!G36) | G12: =SUM('Plant Inputs'!H24,'Plant Inputs'!H30,'Plant Inputs'!H36) | H12: =SUM('Plant Inputs'!I24,'Plant Inputs'!I30,'Plant Inputs'!I36) | I12: =SUM('Plant Inputs'!J24,'Plant Inputs'!J30,'Plant Inputs'!J36) | J12: =SUM('Plant Inputs'!K24,'Plant Inputs'!K30,'Plant Inputs'!K36) | K12: =SUM('Plant Inputs'!L24,'Plant Inputs'!L30,'Plant Inputs'!L36) | L12: =SUM('Plant Inputs'!M24,'Plant Inputs'!M30,'Plant Inputs'!M36) | ... AQ12: =SUM('Plant Inputs'!AR24,'Plant Inputs'!AR30,'Plant Inputs'!AR36) | AR12: =MIN('Plant Inputs'!AS24,'Plant Inputs'!AS30,'Plant Inputs'!AS36) | AS12: =SUM('Plant Inputs'!AT24,'Plant Inputs'!AT30,'Plant Inputs'!AT36) | AT12: =SUM('Plant Inputs'!AU24,'Plant Inputs'!AU30,'Plant Inputs'!AU36) | AU12: =SUM('Plant Inputs'!AV24,'Plant Inputs'!AV30,'Plant Inputs'!AV36) | AV12: =SUM('Plant Inputs'!AW24,'Plant Inputs'!AW30,'Plant Inputs'!AW36) | AW12: =SUM('Plant Inputs'!AX24,'Plant Inputs'!AX30,'Plant Inputs'!AX36) | AX12: =SUM('Plant Inputs'!AY24,'Plant Inputs'!AY30,'Plant Inputs'!AY36) | AY12: =SUM('Plant Inputs'!AZ24,'Plant Inputs'!AZ30,'Plant Inputs'!AZ36) | AZ12: =SUM('Plant Inputs'!BA24,'Plant Inputs'!BA30,'Plant Inputs'!BA36) | ... BR12: =SUM('Plant Inputs'!BS24,'Plant Inputs'!BS30,'Plant Inputs'!BS36) | BS12: =MIN('Plant Inputs'!BT24,'Plant Inputs'!BT30,'Plant Inputs'!BT36) | BT12: =SUM('Plant Inputs'!BU24,'Plant Inputs'!BU30,'Plant Inputs'!BU36) | BU12: =SUM('Plant Inputs'!BV24,'Plant Inputs'!BV30,'Plant Inputs'!BV36) | BV12: =SUM('Plant Inputs'!BW24,'Plant Inputs'!BW30,'Plant Inputs'!BW36) | BW12: =SUM('Plant Inputs'!BX24,'Plant Inputs'!BX30,'Plant Inputs'!BX36) | BX12: =SUM('Plant Inputs'!BY24,'Plant Inputs'!BY30,'Plant Inputs'!BY36) | BY12: 51654.7 | BZ12: 22449.1 | CA12: 10080000 | CB12: 4211021.8 | CC12: 1075021.8 | CD12: 436315.8 | CE12: 32928 | CF12: 405014 | CG12: 1190070.9 | CH12: 107481.4 | CI12: 1119343.6 | CJ12: 1665189.5 | CK12: 2023734.9 | CL12: 1155573.9 | CM12: 1086928.3 | CN12: 3048.7 | CO12: 78617.1 | CP12: 78617.1 | CQ12: 333 | CR12: 15098 | CS12: 14985 | CT12: 0 | CU12: 640845.8 | CV12: 647178.6 | CW12: 92062 | CX12: 3085667.3 | CY12: 1265494.8 | CZ12: 287638.8 | DA12: 211841.6 | DB12: 231613.6 | DC12: 171021.1 | DD12: 3471.9 | DE12: 3774.8 | DF12: 1772808 | DG12: 1085587.8 | DH12: 860000 | DI12: 476244.8 | DJ12: 70024 | DK12: 412800 | DL12: 130334.1 | DM12: 4 | DN12: 1 | DO12: 0 | DP12: 0 | DQ12: 7 | DR12: 10 | DS12: 10 | DT12: 4 | DU12: 2 | DV12: 64 | DW12: 25 | DX12: 8998.7 | DY12: 3287.2 | DZ12: 1313.6 | EA12: 1018 | EB12: 1229.3 | EC12: 68 | ED12: 66 | EE12: 2 | EF12: 0 | EG12: 1 | EH12: 0 | EI12: 0 | EJ12: 0 | EK12: 0 | EL12: 0 | EM12: 0 | EN12: 1 | EO12: 0 | EP12: 0 | EQ12: 1 | ER12: 0 | ES12: 0 | ET12: 0 | EU12: 6 | EV12: 0 | EW12: 1 | EX12: 1 | EY12: 58 | EZ12: 52 | FA12: 3 | FB12: 115 | FC12: 28 | FD12: 24 | FE12: 26 | FF12: 1 | FG12: 0 | FH12: 0 | FI12: 499474 | FJ12: 495766 | FK12: 420 | FL12: 413 | FM12: 0 | FN12: 0 | FO12: 0 | FP12: 4 | FQ12: 7.8 | FR12: 7 | FS12: 0 | FT12: 0 | FU12: -1 | FV12: 1284 | FW12: 444043.8 | FX12: 323426.1 | FY12: 979534.2 | FZ12: 10180800 | GA12: 1081897.5 | GB12: 38056.7 | GC12: 999 | GD12: 0 | GE12: 100.6 | GF12: 0
A13: Group | B13: Entity A2 | C13: 2026-07 | D13: 31 | E13: =SUM('Plant Inputs'!F25,'Plant Inputs'!F31,'Plant Inputs'!F37) | F13: =SUM('Plant Inputs'!G25,'Plant Inputs'!G31,'Plant Inputs'!G37) | G13: =SUM('Plant Inputs'!H25,'Plant Inputs'!H31,'Plant Inputs'!H37) | H13: =SUM('Plant Inputs'!I25,'Plant Inputs'!I31,'Plant Inputs'!I37) | I13: =SUM('Plant Inputs'!J25,'Plant Inputs'!J31,'Plant Inputs'!J37) | J13: =SUM('Plant Inputs'!K25,'Plant Inputs'!K31,'Plant Inputs'!K37) | K13: =SUM('Plant Inputs'!L25,'Plant Inputs'!L31,'Plant Inputs'!L37) | L13: =SUM('Plant Inputs'!M25,'Plant Inputs'!M31,'Plant Inputs'!M37) | ... AQ13: =SUM('Plant Inputs'!AR25,'Plant Inputs'!AR31,'Plant Inputs'!AR37) | AR13: =MIN('Plant Inputs'!AS25,'Plant Inputs'!AS31,'Plant Inputs'!AS37) | AS13: =SUM('Plant Inputs'!AT25,'Plant Inputs'!AT31,'Plant Inputs'!AT37) | AT13: =SUM('Plant Inputs'!AU25,'Plant Inputs'!AU31,'Plant Inputs'!AU37) | AU13: =SUM('Plant Inputs'!AV25,'Plant Inputs'!AV31,'Plant Inputs'!AV37) | AV13: =SUM('Plant Inputs'!AW25,'Plant Inputs'!AW31,'Plant Inputs'!AW37) | AW13: =SUM('Plant Inputs'!AX25,'Plant Inputs'!AX31,'Plant Inputs'!AX37) | AX13: =SUM('Plant Inputs'!AY25,'Plant Inputs'!AY31,'Plant Inputs'!AY37) | AY13: =SUM('Plant Inputs'!AZ25,'Plant Inputs'!AZ31,'Plant Inputs'!AZ37) | AZ13: =SUM('Plant Inputs'!BA25,'Plant Inputs'!BA31,'Plant Inputs'!BA37) | ... BR13: =SUM('Plant Inputs'!BS25,'Plant Inputs'!BS31,'Plant Inputs'!BS37) | BS13: =MIN('Plant Inputs'!BT25,'Plant Inputs'!BT31,'Plant Inputs'!BT37) | BT13: =SUM('Plant Inputs'!BU25,'Plant Inputs'!BU31,'Plant Inputs'!BU37) | BU13: =SUM('Plant Inputs'!BV25,'Plant Inputs'!BV31,'Plant Inputs'!BV37) | BV13: =SUM('Plant Inputs'!BW25,'Plant Inputs'!BW31,'Plant Inputs'!BW37) | BW13: =SUM('Plant Inputs'!BX25,'Plant Inputs'!BX31,'Plant Inputs'!BX37) | BX13: =SUM('Plant Inputs'!BY25,'Plant Inputs'!BY31,'Plant Inputs'!BY37) | BY13: 54610.5 | BZ13: 23755.2 | CA13: 10120000 | CB13: 4323104.5 | CC13: 1219104.5 | CD13: 442574.4 | CE13: 32592 | CF13: 425574.5 | CG13: 1293891.3 | CH13: 119814.6 | CI13: 1202019.5 | CJ13: 1734551.6 | CK13: 2055982.4 | CL13: 1122026.2 | CM13: 1161124.7 | CN13: 2912.2 | CO13: 78725.2 | CP13: 78725.2 | CQ13: 342 | CR13: 15474 | CS13: 15390 | CT13: 1 | CU13: 714775.5 | CV13: 718721.9 | CW13: 139958.6 | CX13: 3047312.3 | CY13: 1412231.8 | CZ13: 347025.2 | DA13: 242148.9 | DB13: 284119.2 | DC13: 199411 | DD13: 6393 | DE13: 6859.8 | DF13: 1997749.7 | DG13: 1170469.4 | DH13: 860000 | DI13: 526173.4 | DJ13: 66726.9 | DK13: 455800 | DL13: 129811.4 | DM13: 4 | DN13: 1 | DO13: 0 | DP13: 1 | DQ13: 4 | DR13: 4 | DS13: 10 | DT13: 4 | DU13: 2 | DV13: 64 | DW13: 28 | DX13: 9318.7 | DY13: 3457.6 | DZ13: 1294.6 | EA13: 1069.1 | EB13: 1220.3 | EC13: 68 | ED13: 65 | EE13: 3 | EF13: 1 | EG13: 1 | EH13: 0 | EI13: 0 | EJ13: 1 | EK13: 1 | EL13: 1 | EM13: 0 | EN13: 0 | EO13: 0 | EP13: 0 | EQ13: 0 | ER13: 0 | ES13: 0 | ET13: 0 | EU13: 5 | EV13: 0 | EW13: 1 | EX13: 1 | EY13: 58 | EZ13: 53 | FA13: 1 | FB13: 36 | FC13: 28 | FD13: 24 | FE13: 26 | FF13: 1 | FG13: 0 | FH13: 0 | FI13: 512122 | FJ13: 506494 | FK13: 420 | FL13: 415 | FM13: 0 | FN13: 0 | FO13: 0 | FP13: 4 | FQ13: 8.5 | FR13: 8 | FS13: 1 | FT13: 1 | FU13: 1 | FV13: 1290 | FW13: 412681.2 | FX13: 267184.6 | FY13: 812149.3 | FZ13: 10221200 | GA13: 1274437 | GB13: 44829.4 | GC13: 999 | GD13: 0 | GE13: 102.3 | GF13: 0
A14: Group | B14: Entity A2 | C14: 2026-08 | D14: 31 | E14: =SUM('Plant Inputs'!F26,'Plant Inputs'!F32,'Plant Inputs'!F38) | F14: =SUM('Plant Inputs'!G26,'Plant Inputs'!G32,'Plant Inputs'!G38) | G14: =SUM('Plant Inputs'!H26,'Plant Inputs'!H32,'Plant Inputs'!H38) | H14: =SUM('Plant Inputs'!I26,'Plant Inputs'!I32,'Plant Inputs'!I38) | I14: =SUM('Plant Inputs'!J26,'Plant Inputs'!J32,'Plant Inputs'!J38) | J14: =SUM('Plant Inputs'!K26,'Plant Inputs'!K32,'Plant Inputs'!K38) | K14: =SUM('Plant Inputs'!L26,'Plant Inputs'!L32,'Plant Inputs'!L38) | L14: =SUM('Plant Inputs'!M26,'Plant Inputs'!M32,'Plant Inputs'!M38) | ... AQ14: =SUM('Plant Inputs'!AR26,'Plant Inputs'!AR32,'Plant Inputs'!AR38) | AR14: =MIN('Plant Inputs'!AS26,'Plant Inputs'!AS32,'Plant Inputs'!AS38) | AS14: =SUM('Plant Inputs'!AT26,'Plant Inputs'!AT32,'Plant Inputs'!AT38) | AT14: =SUM('Plant Inputs'!AU26,'Plant Inputs'!AU32,'Plant Inputs'!AU38) | AU14: =SUM('Plant Inputs'!AV26,'Plant Inputs'!AV32,'Plant Inputs'!AV38) | AV14: =SUM('Plant Inputs'!AW26,'Plant Inputs'!AW32,'Plant Inputs'!AW38) | AW14: =SUM('Plant Inputs'!AX26,'Plant Inputs'!AX32,'Plant Inputs'!AX38) | AX14: =SUM('Plant Inputs'!AY26,'Plant Inputs'!AY32,'Plant Inputs'!AY38) | AY14: =SUM('Plant Inputs'!AZ26,'Plant Inputs'!AZ32,'Plant Inputs'!AZ38) | AZ14: =SUM('Plant Inputs'!BA26,'Plant Inputs'!BA32,'Plant Inputs'!BA38) | ... BR14: =SUM('Plant Inputs'!BS26,'Plant Inputs'!BS32,'Plant Inputs'!BS38) | BS14: =MIN('Plant Inputs'!BT26,'Plant Inputs'!BT32,'Plant Inputs'!BT38) | BT14: =SUM('Plant Inputs'!BU26,'Plant Inputs'!BU32,'Plant Inputs'!BU38) | BU14: =SUM('Plant Inputs'!BV26,'Plant Inputs'!BV32,'Plant Inputs'!BV38) | BV14: =SUM('Plant Inputs'!BW26,'Plant Inputs'!BW32,'Plant Inputs'!BW38) | BW14: =SUM('Plant Inputs'!BX26,'Plant Inputs'!BX32,'Plant Inputs'!BX38) | BX14: =SUM('Plant Inputs'!BY26,'Plant Inputs'!BY32,'Plant Inputs'!BY38) | BY14: 52643.9 | BZ14: 23550.4 | CA14: 10160000 | CB14: 4208810.1 | CC14: 1136810.1 | CD14: 425899.5 | CE14: 32256 | CF14: 436100.5 | CG14: 1192966.9 | CH14: 107683.3 | CI14: 1114419.8 | CJ14: 1562844.7 | CK14: 1909315.9 | CL14: 1088791.2 | CM14: 1109116.5 | CN14: 3143.6 | CO14: 71435.8 | CP14: 71435.8 | CQ14: 326 | CR14: 14795 | CS14: 14670 | CT14: 1 | CU14: 645320.4 | CV14: 653271.4 | CW14: 123824.7 | CX14: 3032458.5 | CY14: 1267817.3 | CZ14: 301775.9 | DA14: 207433.2 | DB14: 239804.4 | DC14: 168954.7 | DD14: 3637.5 | DE14: 3899 | DF14: 1830360.2 | DG14: 1065570.5 | DH14: 860000 | DI14: 567051.2 | DJ14: 69472.5 | DK14: 498800 | DL14: 131528.7 | DM14: 4 | DN14: 1 | DO14: 0 | DP14: 1 | DQ14: 6 | DR14: 7 | DS14: 10 | DT14: 4 | DU14: 2 | DV14: 64 | DW14: 31 | DX14: 9144.2 | DY14: 3287.9 | DZ14: 1358.2 | EA14: 1070.2 | EB14: 1243.8 | EC14: 68 | ED14: 65 | EE14: 2 | EF14: 0 | EG14: 1 | EH14: 1 | EI14: 0 | EJ14: 1 | EK14: 1 | EL14: 1 | EM14: 0 | EN14: 0 | EO14: 0 | EP14: 0 | EQ14: 2 | ER14: 1 | ES14: 0 | ET14: 0 | EU14: 5 | EV14: 0 | EW14: 1 | EX14: 1 | EY14: 58 | EZ14: 52 | FA14: 2 | FB14: 76 | FC14: 28 | FD14: 24 | FE14: 26 | FF14: 2 | FG14: 0 | FH14: 0 | FI14: 498702 | FJ14: 494943 | FK14: 420 | FL14: 412 | FM14: 0 | FN14: 0 | FO14: 0 | FP14: 5 | FQ14: 9.9 | FR14: 8 | FS14: 0 | FT14: 1 | FU14: 1 | FV14: 1287 | FW14: 512807.4 | FX14: 290508.7 | FY14: 663586.6 | FZ14: 10261600 | GA14: 1312719.1 | GB14: 46176 | GC14: 999 | GD14: 0 | GE14: 103.1 | GF14: 0
A15: Group | B15: Entity A2 | C15: 2026-09 | D15: 30 | E15: =SUM('Plant Inputs'!F27,'Plant Inputs'!F33,'Plant Inputs'!F39) | F15: =SUM('Plant Inputs'!G27,'Plant Inputs'!G33,'Plant Inputs'!G39) | G15: =SUM('Plant Inputs'!H27,'Plant Inputs'!H33,'Plant Inputs'!H39) | H15: =SUM('Plant Inputs'!I27,'Plant Inputs'!I33,'Plant Inputs'!I39) | I15: =SUM('Plant Inputs'!J27,'Plant Inputs'!J33,'Plant Inputs'!J39) | J15: =SUM('Plant Inputs'!K27,'Plant Inputs'!K33,'Plant Inputs'!K39) | K15: =SUM('Plant Inputs'!L27,'Plant Inputs'!L33,'Plant Inputs'!L39) | L15: =SUM('Plant Inputs'!M27,'Plant Inputs'!M33,'Plant Inputs'!M39) | ... AQ15: =SUM('Plant Inputs'!AR27,'Plant Inputs'!AR33,'Plant Inputs'!AR39) | AR15: =MIN('Plant Inputs'!AS27,'Plant Inputs'!AS33,'Plant Inputs'!AS39) | AS15: =SUM('Plant Inputs'!AT27,'Plant Inputs'!AT33,'Plant Inputs'!AT39) | AT15: =SUM('Plant Inputs'!AU27,'Plant Inputs'!AU33,'Plant Inputs'!AU39) | AU15: =SUM('Plant Inputs'!AV27,'Plant Inputs'!AV33,'Plant Inputs'!AV39) | AV15: =SUM('Plant Inputs'!AW27,'Plant Inputs'!AW33,'Plant Inputs'!AW39) | AW15: =SUM('Plant Inputs'!AX27,'Plant Inputs'!AX33,'Plant Inputs'!AX39) | AX15: =SUM('Plant Inputs'!AY27,'Plant Inputs'!AY33,'Plant Inputs'!AY39) | AY15: =SUM('Plant Inputs'!AZ27,'Plant Inputs'!AZ33,'Plant Inputs'!AZ39) | AZ15: =SUM('Plant Inputs'!BA27,'Plant Inputs'!BA33,'Plant Inputs'!BA39) | ... BR15: =SUM('Plant Inputs'!BS27,'Plant Inputs'!BS33,'Plant Inputs'!BS39) | BS15: =MIN('Plant Inputs'!BT27,'Plant Inputs'!BT33,'Plant Inputs'!BT39) | BT15: =SUM('Plant Inputs'!BU27,'Plant Inputs'!BU33,'Plant Inputs'!BU39) | BU15: =SUM('Plant Inputs'!BV27,'Plant Inputs'!BV33,'Plant Inputs'!BV39) | BV15: =SUM('Plant Inputs'!BW27,'Plant Inputs'!BW33,'Plant Inputs'!BW39) | BW15: =SUM('Plant Inputs'!BX27,'Plant Inputs'!BX33,'Plant Inputs'!BX39) | BX15: =SUM('Plant Inputs'!BY27,'Plant Inputs'!BY33,'Plant Inputs'!BY39) | BY15: 52845 | BZ15: 40246.8 | CA15: 10200000 | CB15: 4214739.8 | CC15: 1174739.8 | CD15: 431783.2 | CE15: 31920 | CF15: 405067.9 | CG15: 1280130.3 | CH15: 195011.3 | CI15: 1173926.1 | CJ15: 1654275.7 | CK15: 1971156.1 | CL15: 1085692.7 | CM15: 1145104.1 | CN15: 2567.4 | CO15: 83215.8 | CP15: 83215.8 | CQ15: 355 | CR15: 16051 | CS15: 15975 | CT15: 1 | CU15: 1172252.9 | CV15: 1179902.4 | CW15: 182427 | CX15: 2999569.4 | CY15: 2303674.3 | CZ15: 330230.9 | DA15: 231774.8 | DB15: 259974.1 | DC15: 191082.1 | DD15: 4370.6 | DE15: 4752.9 | DF15: 1953973.8 | DG15: 1193687.3 | DH15: 860000 | DI15: 625104.2 | DJ15: 65703.7 | DK15: 541800 | DL15: 127233 | DM15: 4 | DN15: 1 | DO15: 0 | DP15: 1 | DQ15: 7 | DR15: 9 | DS15: 10 | DT15: 4 | DU15: 2 | DV15: 64 | DW15: 35 | DX15: 9329.9 | DY15: 3492 | DZ15: 1271.7 | EA15: 1040.2 | EB15: 1241.7 | EC15: 68 | ED15: 65 | EE15: 2 | EF15: 0 | EG15: 1 | EH15: 1 | EI15: 0 | EJ15: 0 | EK15: 0 | EL15: 0 | EM15: 0 | EN15: 0 | EO15: 0 | EP15: 0 | EQ15: 2 | ER15: 1 | ES15: 0 | ET15: 0 | EU15: 5 | EV15: 0 | EW15: 1 | EX15: 1 | EY15: 58 | EZ15: 52 | FA15: 2 | FB15: 78 | FC15: 28 | FD15: 24 | FE15: 26 | FF15: 2 | FG15: 0 | FH15: 0 | FI15: 504265 | FJ15: 499753 | FK15: 420 | FL15: 410 | FM15: 0 | FN15: 1 | FO15: 0 | FP15: 5 | FQ15: 10.3 | FR15: 8 | FS15: 0 | FT15: 1 | FU15: 1 | FV15: 1284 | FW15: 558590.2 | FX15: 271238.5 | FY15: 630457 | FZ15: 10302000 | GA15: 2031583.3 | GB15: 71462.7 | GC15: 999 | GD15: 0 | GE15: 105.3 | GF15: 0

Sheet Plant Inputs
A1: Group | B1: Entity | C1: Plant | D1: Month | E1: Nameplate rate (t/hour) | F1: Calendar hours (h) | G1: Planned operating hours (h) | H1: Run hours (h) | I1: Unplanned downtime (h) | J1: Ideal output (t) | K1: Installed capacity (t) | L1: Planned production (t) | M1: Gross output (t) | N1: Good output (t) | O1: Feed input (t) | P1: Valuable content in feed (t) | Q1: Valuable content recovered (t) | R1: Production lost to downtime (t) | S1: Breakdowns (count) | T1: Repair hours (h) | U1: Preventive maintenance scheduled (count) | V1: Preventive maintenance completed (count) | W1: Variable cost (₹ thousand) | X1: Fuel cost (₹ thousand) | Y1: Fixed cost (₹ thousand) | Z1: Water used (m³) | AA1: Emissions (t CO2e) | AB1: Energy used (GJ) | AC1: Production at risk (t) | AD1: Critical plant alerts (count) | AE1: Hours worked (h) | AF1: Recordable injuries (count) | AG1: Severity incidents (count) | AH1: Near misses (count) | AI1: Critical safety incidents (count) | AJ1: Environmental excursions (count) | AK1: Environmental violations (count) | AL1: Open EHS corrective actions (count) | AM1: Overdue EHS corrective actions (count) | AN1: EHS investigations due (count) | AO1: EHS investigations completed (count) | AP1: Critical materials at risk (count) | AQ1: Dispatches (count) | AR1: Delayed dispatches (count) | AS1: Days to permit expiry (days) | AT1: Sales volume (t) | AU1: Planned sales volume (t) | AV1: Revenue (₹ thousand) | AW1: Planned revenue (₹ thousand) | AX1: Power cost, part of variable cost (₹ thousand) | AY1: Depreciation and amortisation (₹ thousand) | AZ1: Purchase-order lines due (count) | BA1: Purchase-order lines delivered on time (count) | BB1: Quantity ordered from suppliers (t) | BC1: Quantity received (t) | BD1: Quantity rejected on quality (t) | BE1: Planned lead time, all deliveries (days) | BF1: Actual lead time, all deliveries (days) | BG1: Supplier spend (₹ thousand) | BH1: Spend with single-source suppliers (₹ thousand) | BI1: Supplier EHS incidents (count) | BJ1: Regulatory filings pending (count) | BK1: Regulatory deadlines in next 30 days (count) | BL1: Licences expiring in next 12 months (count) | BM1: Regulatory obligations due in next 30 days (count) | BN1: Regulatory obligations overdue (count) | BO1: Open regulatory actions (count) | BP1: Overdue compliance actions (count) | BQ1: Regulatory breaches in the month (count) | BR1: Events that trigger a disclosure clock (count) | BS1: EHS escalation clocks running (count) | BT1: Days until production plan is breached, forecast (days; 99 = not expected) | BU1: Planned production next month (t) | BV1: Forecast good output next month (t) | BW1: Forecast uncertainty next month (variance, t²) | BX1: Ideal output next month (t) | BY1: Forecast production lost to downtime next month (t)
A2: group | B2: entity | C2: plant | D2: period | E2: nameplate_tph | F2: calendar_hours | G2: planned_op_hours | H2: run_hours | I2: unplanned_downtime_hours | J2: ideal_output_t | K2: installed_capacity_t | L2: planned_production_t | M2: gross_output_t | N2: good_output_t | O2: feed_input_t | P2: feed_contained_t | Q2: recovered_contained_t | R2: prod_loss_downtime_t | S2: failures | T2: repair_hours | U2: pm_scheduled | V2: pm_completed | W2: variable_cost_k | X2: fuel_cost_k | Y2: fixed_cost_k | Z2: water_m3 | AA2: emissions_tco2e | AB2: energy_gj | AC2: production_at_risk_t | AD2: critical_plant_alerts | AE2: hours_worked | AF2: recordable_injuries | AG2: severity_incidents | AH2: near_misses | AI2: critical_safety_incidents | AJ2: env_excursions | AK2: env_violations | AL2: ehs_ca_open | AM2: ehs_ca_overdue | AN2: investigations_due | AO2: investigations_completed | AP2: critical_material_risks | AQ2: dispatches_total | AR2: dispatches_delayed | AS2: permit_days_to_expiry | AT2: sales_t | AU2: planned_sales_t | AV2: revenue_k | AW2: planned_revenue_k | AX2: power_cost_k | AY2: depreciation_k | AZ2: po_lines_due | BA2: po_lines_on_time | BB2: qty_ordered_t | BC2: qty_received_t | BD2: qty_rejected_t | BE2: lead_time_planned_days | BF2: lead_time_actual_days | BG2: supplier_spend_k | BH2: single_source_spend_k | BI2: supplier_ehs_incidents | BJ2: pending_filings | BK2: reg_deadlines_30d | BL2: licences_expiring_12m | BM2: reg_obligations_due_30d | BN2: reg_obligations_overdue | BO2: reg_actions_open | BP2: compliance_actions_overdue | BQ2: reg_breaches | BR2: disclosure_events_open | BS2: ehs_escalation_clocks | BT2: days_to_breach | BU2: planned_production_next_t | BV2: forecast_good_next_t | BW2: forecast_good_var_next | BX2: ideal_output_next_t | BY2: forecast_downtime_loss_next_t
E3: Input | F3: Input | G3: Input | H3: Input | I3: Input | J3: Input | K3: Input | L3: Input | M3: Input | N3: Input | O3: Input | P3: Input | Q3: Input | R3: Input | S3: Input | T3: Input | U3: Input | V3: Input | W3: Input | X3: Input | Y3: Input | Z3: Input | AA3: Input | AB3: Input | AC3: Input | AD3: Input | AE3: Input | AF3: Input | AG3: Input | AH3: Input | AI3: Input | AJ3: Input | AK3: Input | AL3: Input | AM3: Input | AN3: Input | AO3: Input | AP3: Input | AQ3: Input | AR3: Input | AS3: Input | AT3: Input | AU3: Input | AV3: Input | AW3: Input | AX3: Input | AY3: Input | AZ3: Input | BA3: Input | BB3: Input | BC3: Input | BD3: Input | BE3: Input | BF3: Input | BG3: Input | BH3: Input | BI3: Input | BJ3: Input | BK3: Input | BL3: Input | BM3: Input | BN3: Input | BO3: Input | BP3: Input | BQ3: Input | BR3: Input | BS3: Input | BT3: Input | BU3: Input | BV3: Input | BW3: Input | BX3: Input | BY3: Input
A4: Group | B4: Entity A1 | C4: Plant 01 | D4: 2026-04 | E4: 137.1 | F4: 720 | G4: 714 | H4: 692.3 | I4: 13.3 | J4: 97889 | K4: 98712 | L4: 88515 | M4: 89648 | N4: 87087 | O4: 95600 | P4: 19579 | Q4: 17553 | R4: 1823 | S4: 2 | T4: 7.1 | U4: 37 | V4: 36 | W4: 251985.8 | X4: 62832 | Y4: 1091.7 | Z4: 167244 | AA4: 61316 | AB4: 311042 | AC4: 3223 | AD4: 1 | AE4: 79000 | AF4: 0 | AG4: 1 | AH4: 10 | AI4: 0 | AJ4: 0 | AK4: 0 | AL4: 14 | AM4: 4 | AN4: 0 | AO4: 0 | AP4: 0 | AQ4: 158 | AR4: 9 | AS4: 311 | AT4: 87409 | AU4: 89254 | AV4: 329486.5 | AW4: 335595 | AX4: 15168.7 | AY4: 11886.3 | AZ4: 209 | BA4: 195 | BB4: 95742 | BC4: 92606 | BD4: 1350 | BE4: 588 | BF4: 583 | BG4: 131922.8 | BH4: 40636.9 | BI4: 0 | BJ4: 0 | BK4: 1 | BL4: 0 | BM4: 1 | BN4: 0 | BO4: 0 | BP4: 0 | BQ4: 0 | BR4: 0 | BS4: 0 | BT4: 99 | BU4: 87645 | BV4: 87637 | BW4: 24380601 | BX4: 97889 | BY4: 1620
A5: Group | B5: Entity A1 | C5: Plant 01 | D5: 2026-05 | E5: 137.1 | F5: 744 | G5: 744 | H5: 702.5 | I5: 19.6 | J5: 102002 | K5: 102002 | L5: 88139 | M5: 84940 | N5: 80872 | O5: 86252 | P5: 17739 | Q5: 15002 | R5: 2687 | S5: 3 | T5: 15.5 | U5: 48 | V5: 47 | W5: 272778.7 | X5: 79959.6 | Y5: 1465.4 | Z5: 205726 | AA5: 53724 | AB5: 252523 | AC5: 5217 | AD5: 1 | AE5: 66000 | AF5: 0 | AG5: 0 | AH5: 4 | AI5: 0 | AJ5: 0 | AK5: 0 | AL5: 11 | AM5: 2 | AN5: 3 | AO5: 3 | AP5: 0 | AQ5: 256 | AR5: 10 | AS5: 281 | AT5: 81067 | AU5: 87363 | AV5: 309234.4 | AW5: 328484.9 | AX5: 17277.2 | AY5: 11827.2 | AZ5: 166 | BA5: 151 | BB5: 85077 | BC5: 81619 | BD5: 587 | BE5: 868 | BF5: 870 | BG5: 150305.9 | BH5: 52546 | BI5: 0 | BJ5: 1 | BK5: 0 | BL5: 0 | BM5: 0 | BN5: 0 | BO5: 0 | BP5: 0 | BQ5: 0 | BR5: 0 | BS5: 0 | BT5: 99 | BU5: 89736 | BV5: 91812 | BW5: 30306703 | BX5: 102002 | BY5: 2913
A6: Group | B6: Entity A1 | C6: Plant 01 | D6: 2026-06 | E6: 137.1 | F6: 720 | G6: 720 | H6: 681.5 | I6: 18.6 | J6: 98712 | K6: 98712 | L6: 88801 | M6: 84328 | N6: 81129 | O6: 86263 | P6: 18895 | Q6: 16380 | R6: 2550 | S6: 2 | T6: 14.7 | U6: 48 | V6: 45 | W6: 269800.1 | X6: 63241.6 | Y6: 1103.4 | Z6: 166424 | AA6: 60010 | AB6: 243788 | AC6: 7297 | AD6: 2 | AE6: 91000 | AF6: 1 | AG6: 0 | AH6: 10 | AI6: 0 | AJ6: 1 | AK6: 0 | AL6: 5 | AM6: 1 | AN6: 0 | AO6: 0 | AP6: 0 | AQ6: 148 | AR6: 11 | AS6: 251 | AT6: 78859 | AU6: 89179 | AV6: 300728.2 | AW6: 335313 | AX6: 16758.3 | AY6: 11531.2 | AZ6: 179 | BA6: 167 | BB6: 87881 | BC6: 85157 | BD6: 708 | BE6: 980 | BF6: 979 | BG6: 148313 | BH6: 46780.1 | BI6: 1 | BJ6: 0 | BK6: 0 | BL6: 0 | BM6: 1 | BN6: 0 | BO6: 0 | BP6: 0 | BQ6: 0 | BR6: 0 | BS6: 0 | BT6: 99 | BU6: 89319 | BV6: 90196 | BW6: 26705815 | BX6: 98712 | BY6: 2398
A7: Group | B7: Entity A1 | C7: Plant 01 | D7: 2026-07 | E7: 137.1 | F7: 744 | G7: 741 | H7: 701.6 | I7: 27.2 | J7: 101591 | K7: 102002 | L7: 88152 | M7: 86711 | N7: 83254 | O7: 94209 | P7: 21264 | Q7: 19441 | R7: 3729 | S7: 4 | T7: 21.3 | U7: 55 | V7: 52 | W7: 221284.2 | X7: 64810.6 | Y7: 1144.9 | Z7: 180484 | AA7: 54600 | AB7: 243753 | AC7: 5312 | AD7: 0 | AE7: 76000 | AF7: 1 | AG7: 0 | AH7: 9 | AI7: 0 | AJ7: 1 | AK7: 0 | AL7: 4 | AM7: 1 | AN7: 3 | AO7: 3 | AP7: 1 | AQ7: 198 | AR7: 9 | AS7: 221 | AT7: 84466 | AU7: 87398 | AV7: 321422 | AW7: 328616.5 | AX7: 11354.6 | AY7: 11607.9 | AZ7: 300 | BA7: 281 | BB7: 96576 | BC7: 93033 | BD7: 1429 | BE7: 742 | BF7: 772 | BG7: 112971 | BH7: 43971.6 | BI7: 0 | BJ7: 0 | BK7: 0 | BL7: 0 | BM7: 0 | BN7: 0 | BO7: 1 | BP7: 0 | BQ7: 0 | BR7: 0 | BS7: 0 | BT7: 99 | BU7: 87292 | BV7: 87138 | BW7: 23937559 | BX7: 101591 | BY7: 3863
A8: Group | B8: Entity A1 | C8: Plant 01 | D8: 2026-08 | E8: 137.1 | F8: 744 | G8: 744 | H8: 710.7 | I8: 19.1 | J8: 102002 | K8: 102002 | L8: 91424 | M8: 90032 | N8: 87527 | O8: 94670 | P8: 19426 | Q8: 17234 | R8: 2619 | S8: 2 | T8: 14 | U8: 32 | V8: 31 | W8: 268254.7 | X8: 78893.9 | Y8: 1065.3 | Z8: 192091 | AA8: 54889 | AB8: 306311 | AC8: 1480 | AD8: 2 | AE8: 56000 | AF8: 1 | AG8: 0 | AH8: 6 | AI8: 0 | AJ8: 0 | AK8: 0 | AL8: 5 | AM8: 0 | AN8: 1 | AO8: 1 | AP8: 2 | AQ8: 121 | AR8: 10 | AS8: 191 | AT8: 86793 | AU8: 91102 | AV8: 330981.6 | AW8: 342543.5 | AX8: 16048.6 | AY8: 11694.1 | AZ8: 169 | BA8: 156 | BB8: 95196 | BC8: 92043 | BD8: 1181 | BE8: 868 | BF8: 855 | BG8: 154797 | BH8: 58229.3 | BI8: 0 | BJ8: 0 | BK8: 0 | BL8: 0 | BM8: 1 | BN8: 0 | BO8: 0 | BP8: 0 | BQ8: 0 | BR8: 0 | BS8: 0 | BT8: 99 | BU8: 92975 | BV8: 93639 | BW8: 35960460 | BX8: 102002 | BY8: 2699
A9: Group | B9: Entity A1 | C9: Plant 01 | D9: 2026-09 | E9: 137.1 | F9: 720 | G9: 711 | H9: 664.5 | I9: 30.2 | J9: 97478 | K9: 98712 | L9: 85234 | M9: 84182 | N9: 81854 | O9: 89479 | P9: 19996 | Q9: 18334 | R9: 4140 | S9: 4 | T9: 21.6 | U9: 46 | V9: 43 | W9: 226098.2 | X9: 50616 | Y9: 1375.5 | Z9: 148807 | AA9: 59115 | AB9: 289576 | AC9: 3669 | AD9: 0 | AE9: 55000 | AF9: 0 | AG9: 1 | AH9: 9 | AI9: 0 | AJ9: 0 | AK9: 0 | AL9: 14 | AM9: 4 | AN9: 2 | AO9: 2 | AP9: 2 | AQ9: 120 | AR9: 9 | AS9: 161 | AT9: 79865 | AU9: 86061 | AV9: 300900.3 | AW9: 323589.4 | AX9: 13488.8 | AY9: 11990.8 | AZ9: 151 | BA9: 140 | BB9: 89804 | BC9: 86335 | BD9: 1211 | BE9: 644 | BF9: 676 | BG9: 116619.5 | BH9: 35125 | BI9: 1 | BJ9: 0 | BK9: 1 | BL9: 0 | BM9: 0 | BN9: 0 | BO9: 0 | BP9: 0 | BQ9: 0 | BR9: 0 | BS9: 0 | BT9: 99 | BU9: 85101 | BV9: 86567 | BW9: 26609951 | BX9: 97478 | BY9: 4173
A10: Group | B10: Entity A1 | C10: Plant 02 | D10: 2026-04 | E10: 188.9 | F10: 720 | G10: 718 | H10: 675.1 | I10: 31 | J10: 135630 | K10: 136008 | L10: 117160 | M10: 101595 | N10: 98478 | O10: 110890 | P10: 24227 | Q10: 19946 | R10: 5856 | S10: 5 | T10: 28.6 | U10: 40 | V10: 34 | W10: 293950 | X10: 67780.4 | Y10: 1112.1 | Z10: 202909 | AA10: 69227 | AB10: 349419 | AC10: 17173 | AD10: 2 | AE10: 61000 | AF10: 0 | AG10: 0 | AH10: 6 | AI10: 0 | AJ10: 0 | AK10: 0 | AL10: 6 | AM10: 2 | AN10: 3 | AO10: 3 | AP10: 1 | AQ10: 187 | AR10: 11 | AS10: 215 | AT10: 99647 | AU10: 116251 | AV10: 367581.1 | AW10: 437103.8 | AX10: 20037.9 | AY10: 15943.3 | AZ10: 167 | BA10: 142 | BB10: 108759 | BC10: 107531 | BD10: 1079 | BE10: 574 | BF10: 662 | BG10: 161218.5 | BH10: 73012.8 | BI10: 0 | BJ10: 1 | BK10: 1 | BL10: 1 | BM10: 1 | BN10: 0 | BO10: 0 | BP10: 0 | BQ10: 0 | BR10: 0 | BS10: 0 | BT10: 17 | BU10: 119412 | BV10: 107510 | BW10: 40574219 | BX10: 135630 | BY10: 5356
A11: Group | B11: Entity A1 | C11: Plant 02 | D11: 2026-05 | E11: 188.9 | F11: 744 | G11: 690 | H11: 630.7 | I11: 45.8 | J11: 130341 | K11: 140542 | L11: 118660 | M11: 98372 | N11: 96839 | O11: 102676 | P11: 19541 | Q11: 16926 | R11: 8652 | S11: 5 | T11: 40.5 | U11: 44 | V11: 33 | W11: 350205.1 | X11: 97181.8 | Y11: 1212.1 | Z11: 176546 | AA11: 62330 | AB11: 375349 | AC11: 20499 | AD11: 4 | AE11: 69000 | AF11: 1 | AG11: 0 | AH11: 4 | AI11: 0 | AJ11: 0 | AK11: 0 | AL11: 5 | AM11: 1 | AN11: 0 | AO11: 0 | AP11: 0 | AQ11: 197 | AR11: 21 | AS11: 185 | AT11: 96710 | AU11: 118595 | AV11: 355792.8 | AW11: 445917.2 | AX11: 18442.1 | AY11: 15809.6 | AZ11: 174 | BA11: 142 | BB11: 102899 | BC11: 101308 | BD11: 846 | BE11: 616 | BF11: 696 | BG11: 188788.5 | BH11: 87101.1 | BI11: 0 | BJ11: 0 | BK11: 1 | BL11: 1 | BM11: 0 | BN11: 0 | BO11: 0 | BP11: 0 | BQ11: 0 | BR11: 0 | BS11: 0 | BT11: 12 | BU11: 120898 | BV11: 110663 | BW11: 51573641 | BX11: 130341 | BY11: 8040
A12: Group | B12: Entity A1 | C12: Plant 02 | D12: 2026-06 | E12: 188.9 | F12: 720 | G12: 718 | H12: 669.9 | I12: 37.1 | J12: 135630 | K12: 136008 | L12: 120521 | M12: 96232 | N12: 91848 | O12: 97224 | P12: 21417 | Q12: 17596 | R12: 7008 | S12: 4 | T12: 32.6 | U12: 36 | V12: 31 | W12: 321487.9 | X12: 71503.8 | Y12: 1098.9 | Z12: 174177 | AA12: 54970 | AB12: 368624 | AC12: 28075 | AD12: 2 | AE12: 62000 | AF12: 1 | AG12: 0 | AH12: 4 | AI12: 0 | AJ12: 0 | AK12: 0 | AL12: 5 | AM12: 0 | AN12: 2 | AO12: 1 | AP12: 1 | AQ12: 194 | AR12: 21 | AS12: 155 | AT12: 93443 | AU12: 119908 | AV12: 341097.4 | AW12: 450854.1 | AX12: 17509.3 | AY12: 15920 | AZ12: 150 | BA12: 124 | BB12: 98097 | BC12: 96415 | BD12: 1343 | BE12: 630 | BF12: 704 | BG12: 190497.7 | BH12: 86054.4 | BI12: 0 | BJ12: 0 | BK12: 0 | BL12: 1 | BM12: 1 | BN12: 0 | BO12: 0 | BP12: 0 | BQ12: 0 | BR12: 0 | BS12: 0 | BT12: 18 | BU12: 119591 | BV12: 108329 | BW12: 44645372 | BX12: 135630 | BY12: 6878
A13: Group | B13: Entity A1 | C13: Plant 02 | D13: 2026-07 | E13: 188.9 | F13: 744 | G13: 737 | H13: 655.4 | I13: 69.3 | J13: 139219 | K13: 140542 | L13: 122135 | M13: 101413 | N13: 97731 | O13: 108037 | P13: 20571 | Q13: 17916 | R13: 13091 | S13: 6 | T13: 65.7 | U13: 56 | V13: 44 | W13: 350472.9 | X13: 93258.3 | Y13: 1434.2 | Z13: 204288 | AA13: 57701 | AB13: 356252 | AC13: 22870 | AD13: 2 | AE13: 68000 | AF13: 0 | AG13: 1 | AH13: 6 | AI13: 0 | AJ13: 1 | AK13: 0 | AL13: 7 | AM13: 0 | AN13: 1 | AO13: 1 | AP13: 0 | AQ13: 129 | AR13: 15 | AS13: 125 | AT13: 95686 | AU13: 120914 | AV13: 355004.6 | AW13: 454636.6 | AX13: 21552.3 | AY13: 15764.7 | AZ13: 159 | BA13: 128 | BB13: 105180 | BC13: 101093 | BD13: 720 | BE13: 658 | BF13: 772 | BG13: 179819.6 | BH13: 82831.7 | BI13: 0 | BJ13: 0 | BK13: 0 | BL13: 1 | BM13: 1 | BN13: 0 | BO13: 0 | BP13: 0 | BQ13: 0 | BR13: 0 | BS13: 0 | BT13: 12 | BU13: 123620 | BV13: 113701 | BW13: 53958022 | BX13: 139219 | BY13: 13208
A14: Group | B14: Entity A1 | C14: Plant 02 | D14: 2026-08 | E14: 188.9 | F14: 744 | G14: 674 | H14: 603.4 | I14: 53.5 | J14: 127319 | K14: 140542 | L14: 109907 | M14: 90236 | N14: 86596 | O14: 97767 | P14: 22655 | Q14: 18611 | R14: 10106 | S14: 4 | T14: 46.8 | U14: 39 | V14: 37 | W14: 293787.6 | X14: 89718.1 | Y14: 1404.1 | Z14: 164589 | AA14: 62319 | AB14: 347920 | AC14: 23073 | AD14: 3 | AE14: 69000 | AF14: 0 | AG14: 1 | AH14: 5 | AI14: 1 | AJ14: 0 | AK14: 0 | AL14: 8 | AM14: 1 | AN14: 0 | AO14: 0 | AP14: 0 | AQ14: 212 | AR14: 32 | AS14: 95 | AT14: 87463 | AU14: 110393 | AV14: 324045 | AW14: 415077.7 | AX14: 17217.2 | AY14: 16383.2 | AZ14: 157 | BA14: 131 | BB14: 94985 | BC14: 92164 | BD14: 1526 | BE14: 560 | BF14: 665 | BG14: 153621.7 | BH14: 72743.6 | BI14: 0 | BJ14: 0 | BK14: 0 | BL14: 1 | BM14: 0 | BN14: 0 | BO14: 0 | BP14: 0 | BQ14: 0 | BR14: 0 | BS14: 0 | BT14: 10 | BU14: 111815 | BV14: 102323 | BW14: 35614658 | BX14: 127319 | BY14: 8914
