Workbook

Sheet Calculated vs Shown
A1: KPI ID | B1: Measure | C1: Unit | D1: Formula | E1: Calculated value, Sep 2026 (P06) | F1: Shown on the Owner screens (Group scope) | G1: Same or different | H1: Screens | I1: Where the inputs come from
A2: OPS-001 | B2: Production vs plan | C2: % | D2: Good output ÷ Planned production × 100 | E2: ='Owner KPIs'!K2 | F2: 95.5 % of plan | G2: Different | H2: O-01, O-01 · large display ≥ 1600, O-09, S-03 · Owner view, S-10, STATE GALLERY · O-01 + S-02 | I2: Original plant data (plant_base.csv, synthetic)
A3: OPS-003 | B3: Capacity utilization | C3: % | D3: Good output ÷ Installed capacity × 100 | E3: ='Owner KPIs'!K3 | F3: 83.4 % | G3: Different | H3: O-01, O-01 · large display ≥ 1600, STATE GALLERY · O-01 + S-02 | I3: Original plant data (plant_base.csv, synthetic)
A4: REL-001 | B4: MTBF | C4: h | D4: Run hours ÷ Breakdowns | E4: ='Owner KPIs'!K4 | F4: 270 h | G4: Different | H4: O-09 | I4: Original plant data (plant_base.csv, synthetic)
A5: REL-002 | B5: Mean Time to Repair | C5: h | D5: Repair hours ÷ Breakdowns | E5: ='Owner KPIs'!K5 | F5: Not on a screen | G5: — | H5: — | I5: Original plant data (plant_base.csv, synthetic)
A6: REL-003 | B6: Unplanned downtime | C6: h | D6: Unplanned downtime | E6: ='Owner KPIs'!K6 | F6: Not on a screen | G6: — | H6: — | I6: Original plant data (plant_base.csv, synthetic)
A7: REL-005 | B7: Preventive-maintenance compliance | C7: % | D7: Preventive maintenance completed ÷ Preventive maintenance scheduled × 100 | E7: ='Owner KPIs'!K7 | F7: Not on a screen | G7: — | H7: — | I7: Original plant data (plant_base.csv, synthetic)
A8: CST-001 | B8: Cost per tonne | C8: ₹/t | D8: (Variable cost + Fixed cost) × 1000 ÷ Good output | E8: ='Owner KPIs'!K8 | F8: 2,934 ₹/t | G8: Different | H8: O-09, — | I8: Original plant data (plant_base.csv, synthetic)
A9: CST-002 | B9: Variable cost | C9: ₹ thousand | D9: Variable cost | E9: ='Owner KPIs'!K9 | F9: Not on a screen | G9: — | H9: — | I9: Original plant data (plant_base.csv, synthetic)
A10: CST-003 | B10: Fuel cost | C10: ₹ thousand | D10: Fuel cost | E10: ='Owner KPIs'!K10 | F10: Not on a screen | G10: — | H10: — | I10: Original plant data (plant_base.csv, synthetic)
A11: SUS-001 | B11: Water usage | C11: m3 | D11: Water used | E11: ='Owner KPIs'!K11 | F11: 3.1 m³/t | G11: Different | H11: O-05 | I11: Original plant data (plant_base.csv, synthetic)
A12: SUS-002 | B12: Emissions | C12: tCO2e | D12: Emissions | E12: ='Owner KPIs'!K12 | F12: 427.7 kt CO2e | G12: Different | H12: O-05 | I12: Original plant data (plant_base.csv, synthetic)
A13: SUS-003 | B13: Energy intensity | C13: GJ/t | D13: Energy used ÷ Good output | E13: ='Owner KPIs'!K13 | F13: 5.2 GJ/t | G13: Different | H13: O-05 | I13: Original plant data (plant_base.csv, synthetic)
... A119: PRD-007 | B119: Probability OEE below 78%, next month | C119: % | D119: Chance that Forecast good output < 78% × Ideal output next month (same distribution as PRD-002) [Next month] | E119: ='Owner KPIs'!K119 | F119: Not on a screen | G119: — | H119: — | I119: Synthetic inputs added for this model

Sheet Owner KPIs
A1: KPI ID | B1: Measure | C1: Unit | D1: Time basis | E1: How it is calculated | F1: 2026-04 (P01) | G1: 2026-05 (P02) | H1: 2026-06 (P03) | I1: 2026-07 (P04) | J1: 2026-08 (P05) | K1: 2026-09 (P06) | L1: Shown on Owner screens today (value and screens) | M1: Owner screens | N1: Inputs used (Group Inputs columns)
A2: OPS-001 | B2: Production vs plan | C2: % | D2: Month | E2: Good output ÷ Planned production × 100 | F2: =ROUND(IFERROR(100*'Group Inputs'!M4/'Group Inputs'!K4,0),2) | G2: =ROUND(IFERROR(100*'Group Inputs'!M5/'Group Inputs'!K5,0),2) | H2: =ROUND(IFERROR(100*'Group Inputs'!M6/'Group Inputs'!K6,0),2) | I2: =ROUND(IFERROR(100*'Group Inputs'!M7/'Group Inputs'!K7,0),2) | J2: =ROUND(IFERROR(100*'Group Inputs'!M8/'Group Inputs'!K8,0),2) | K2: =ROUND(IFERROR(100*'Group Inputs'!M9/'Group Inputs'!K9,0),2) | L2: 98.1 % of plan (O-01, STATE GALLERY); 103.2 % of plan (flash) (S-03); 100.2 % of plan (S-10); 95.5 % of plan (O-09) | M2: O-01, O-01 · large display ≥ 1600, O-09, S-03 · Owner view, S-10, STATE GALLERY · O-01 + S-02 | N2: planned_production_t, good_output_t
A3: OPS-003 | B3: Capacity utilization | C3: % | D3: Month | E3: Good output ÷ Installed capacity × 100 | F3: =ROUND(IFERROR(100*'Group Inputs'!M4/'Group Inputs'!J4,0),2) | G3: =ROUND(IFERROR(100*'Group Inputs'!M5/'Group Inputs'!J5,0),2) | H3: =ROUND(IFERROR(100*'Group Inputs'!M6/'Group Inputs'!J6,0),2) | I3: =ROUND(IFERROR(100*'Group Inputs'!M7/'Group Inputs'!J7,0),2) | J3: =ROUND(IFERROR(100*'Group Inputs'!M8/'Group Inputs'!J8,0),2) | K3: =ROUND(IFERROR(100*'Group Inputs'!M9/'Group Inputs'!J9,0),2) | L3: 86% (O-01, STATE GALLERY) | M3: O-01, O-01 · large display ≥ 1600, STATE GALLERY · O-01 + S-02 | N3: installed_capacity_t, good_output_t
A4: REL-001 | B4: MTBF | C4: h | D4: Month | E4: Run hours ÷ Breakdowns | F4: =ROUND(IFERROR('Group Inputs'!G4/'Group Inputs'!R4,0),2) | G4: =ROUND(IFERROR('Group Inputs'!G5/'Group Inputs'!R5,0),2) | H4: =ROUND(IFERROR('Group Inputs'!G6/'Group Inputs'!R6,0),2) | I4: =ROUND(IFERROR('Group Inputs'!G7/'Group Inputs'!R7,0),2) | J4: =ROUND(IFERROR('Group Inputs'!G8/'Group Inputs'!R8,0),2) | K4: =ROUND(IFERROR('Group Inputs'!G9/'Group Inputs'!R9,0),2) | L4: 270 h (O-09) | M4: O-09 | N4: run_hours, failures
A5: REL-002 | B5: Mean Time to Repair | C5: h | D5: Month | E5: Repair hours ÷ Breakdowns | F5: =ROUND(IFERROR('Group Inputs'!S4/'Group Inputs'!R4,0),2) | G5: =ROUND(IFERROR('Group Inputs'!S5/'Group Inputs'!R5,0),2) | H5: =ROUND(IFERROR('Group Inputs'!S6/'Group Inputs'!R6,0),2) | I5: =ROUND(IFERROR('Group Inputs'!S7/'Group Inputs'!R7,0),2) | J5: =ROUND(IFERROR('Group Inputs'!S8/'Group Inputs'!R8,0),2) | K5: =ROUND(IFERROR('Group Inputs'!S9/'Group Inputs'!R9,0),2) | L5: Not on a screen | M5: — | N5: failures, repair_hours
A6: REL-003 | B6: Unplanned downtime | C6: h | D6: Month | E6: Unplanned downtime | F6: =ROUND('Group Inputs'!H4,2) | G6: =ROUND('Group Inputs'!H5,2) | H6: =ROUND('Group Inputs'!H6,2) | I6: =ROUND('Group Inputs'!H7,2) | J6: =ROUND('Group Inputs'!H8,2) | K6: =ROUND('Group Inputs'!H9,2) | L6: Not on a screen | M6: — | N6: unplanned_downtime_hours
A7: REL-005 | B7: Preventive-maintenance compliance | C7: % | D7: Month | E7: Preventive maintenance completed ÷ Preventive maintenance scheduled × 100 | F7: =ROUND(IFERROR(100*'Group Inputs'!U4/'Group Inputs'!T4,0),2) | G7: =ROUND(IFERROR(100*'Group Inputs'!U5/'Group Inputs'!T5,0),2) | H7: =ROUND(IFERROR(100*'Group Inputs'!U6/'Group Inputs'!T6,0),2) | I7: =ROUND(IFERROR(100*'Group Inputs'!U7/'Group Inputs'!T7,0),2) | J7: =ROUND(IFERROR(100*'Group Inputs'!U8/'Group Inputs'!T8,0),2) | K7: =ROUND(IFERROR(100*'Group Inputs'!U9/'Group Inputs'!T9,0),2) | L7: Not on a screen | M7: — | N7: pm_scheduled, pm_completed
A8: CST-001 | B8: Cost per tonne | C8: ₹/t | D8: Month | E8: (Variable cost + Fixed cost) × 1000 ÷ Good output | F8: =ROUND(IFERROR(1000*('Group Inputs'!V4+'Group Inputs'!X4)/'Group Inputs'!M4,0),2) | G8: =ROUND(IFERROR(1000*('Group Inputs'!V5+'Group Inputs'!X5)/'Group Inputs'!M5,0),2) | H8: =ROUND(IFERROR(1000*('Group Inputs'!V6+'Group Inputs'!X6)/'Group Inputs'!M6,0),2) | I8: =ROUND(IFERROR(1000*('Group Inputs'!V7+'Group Inputs'!X7)/'Group Inputs'!M7,0),2) | J8: =ROUND(IFERROR(1000*('Group Inputs'!V8+'Group Inputs'!X8)/'Group Inputs'!M8,0),2) | K8: =ROUND(IFERROR(1000*('Group Inputs'!V9+'Group Inputs'!X9)/'Group Inputs'!M9,0),2) | L8: Not on a screen; 2,934 ₹/t (O-09) | M8: O-09, — | N8: good_output_t, variable_cost_k, fixed_cost_k
A9: CST-002 | B9: Variable cost | C9: ₹ thousand | D9: Month | E9: Variable cost | F9: =ROUND('Group Inputs'!V4,2) | G9: =ROUND('Group Inputs'!V5,2) | H9: =ROUND('Group Inputs'!V6,2) | I9: =ROUND('Group Inputs'!V7,2) | J9: =ROUND('Group Inputs'!V8,2) | K9: =ROUND('Group Inputs'!V9,2) | L9: Not on a screen | M9: — | N9: variable_cost_k
A10: CST-003 | B10: Fuel cost | C10: ₹ thousand | D10: Month | E10: Fuel cost | F10: =ROUND('Group Inputs'!W4,2) | G10: =ROUND('Group Inputs'!W5,2) | H10: =ROUND('Group Inputs'!W6,2) | I10: =ROUND('Group Inputs'!W7,2) | J10: =ROUND('Group Inputs'!W8,2) | K10: =ROUND('Group Inputs'!W9,2) | L10: Not on a screen | M10: — | N10: fuel_cost_k
A11: SUS-001 | B11: Water usage | C11: m3 | D11: Month | E11: Water used | F11: =ROUND('Group Inputs'!Y4,2) | G11: =ROUND('Group Inputs'!Y5,2) | H11: =ROUND('Group Inputs'!Y6,2) | I11: =ROUND('Group Inputs'!Y7,2) | J11: =ROUND('Group Inputs'!Y8,2) | K11: =ROUND('Group Inputs'!Y9,2) | L11: 3.1 m³/t (O-05) | M11: O-05 | N11: water_m3
A12: SUS-002 | B12: Emissions | C12: tCO2e | D12: Month | E12: Emissions | F12: =ROUND('Group Inputs'!Z4,2) | G12: =ROUND('Group Inputs'!Z5,2) | H12: =ROUND('Group Inputs'!Z6,2) | I12: =ROUND('Group Inputs'!Z7,2) | J12: =ROUND('Group Inputs'!Z8,2) | K12: =ROUND('Group Inputs'!Z9,2) | L12: 0.82 tCO2e/t (O-05) | M12: O-05 | N12: emissions_tco2e
A13: SUS-003 | B13: Energy intensity | C13: GJ/t | D13: Month | E13: Energy used ÷ Good output | F13: =ROUND(IFERROR('Group Inputs'!AA4/'Group Inputs'!M4,0),2) | G13: =ROUND(IFERROR('Group Inputs'!AA5/'Group Inputs'!M5,0),2) | H13: =ROUND(IFERROR('Group Inputs'!AA6/'Group Inputs'!M6,0),2) | I13: =ROUND(IFERROR('Group Inputs'!AA7/'Group Inputs'!M7,0),2) | J13: =ROUND(IFERROR('Group Inputs'!AA8/'Group Inputs'!M8,0),2) | K13: =ROUND(IFERROR('Group Inputs'!AA9/'Group Inputs'!M9,0),2) | L13: 5.2 GJ/t (O-05) | M13: O-05 | N13: good_output_t, energy_gj
A14: SIG-007 | B14: Production at risk | C14: t | D14: Month | E14: Production at risk | F14: =ROUND('Group Inputs'!AB4,2) | G14: =ROUND('Group Inputs'!AB5,2) | H14: =ROUND('Group Inputs'!AB6,2) | I14: =ROUND('Group Inputs'!AB7,2) | J14: =ROUND('Group Inputs'!AB8,2) | K14: =ROUND('Group Inputs'!AB9,2) | L14: 18.4 kt (FCST) (S-10) | M14: S-10 | N14: production_at_risk_t
A15: SIG-009 | B15: Critical-material shortage risk | C15: count | D15: Month | E15: Critical materials at risk | F15: =ROUND('Group Inputs'!AO4,2) | G15: =ROUND('Group Inputs'!AO5,2) | H15: =ROUND('Group Inputs'!AO6,2) | I15: =ROUND('Group Inputs'!AO7,2) | J15: =ROUND('Group Inputs'!AO8,2) | K15: =ROUND('Group Inputs'!AO9,2) | L15: 3.5 days of cover (S-10) | M15: S-10 | N15: critical_material_risks
A16: SIG-012 | B16: Dispatch delays | C16: % | D16: Month | E16: Delayed dispatches ÷ Dispatches × 100 | F16: =ROUND(IFERROR(100*'Group Inputs'!AQ4/'Group Inputs'!AP4,0),2) | G16: =ROUND(IFERROR(100*'Group Inputs'!AQ5/'Group Inputs'!AP5,0),2) | H16: =ROUND(IFERROR(100*'Group Inputs'!AQ6/'Group Inputs'!AP6,0),2) | I16: =ROUND(IFERROR(100*'Group Inputs'!AQ7/'Group Inputs'!AP7,0),2) | J16: =ROUND(IFERROR(100*'Group Inputs'!AQ8/'Group Inputs'!AP8,0),2) | K16: =ROUND(IFERROR(100*'Group Inputs'!AQ9/'Group Inputs'!AP9,0),2) | L16: 2–4 days (S-11) | M16: S-11 | N16: dispatches_total, dispatches_delayed
A17: EHS-001 | B17: TRIR | C17: per 200,000 h | D17: Month | E17: Recordable injuries × 200,000 ÷ Hours worked | F17: =ROUND(IFERROR(200000*'Group Inputs'!AE4/'Group Inputs'!AD4,0),2) | G17: =ROUND(IFERROR(200000*'Group Inputs'!AE5/'Group Inputs'!AD5,0),2) | H17: =ROUND(IFERROR(200000*'Group Inputs'!AE6/'Group Inputs'!AD6,0),2) | I17: =ROUND(IFERROR(200000*'Group Inputs'!AE7/'Group Inputs'!AD7,0),2) | J17: =ROUND(IFERROR(200000*'Group Inputs'!AE8/'Group Inputs'!AD8,0),2) | K17: =ROUND(IFERROR(200000*'Group Inputs'!AE9/'Group Inputs'!AD9,0),2) | L17: 0.42 (O-05) | M17: O-05 | N17: hours_worked, recordable_injuries
A18: EHS-002 | B18: Severity incidents | C18: count | D18: Month | E18: Severity incidents | F18: =ROUND('Group Inputs'!AF4,2) | G18: =ROUND('Group Inputs'!AF5,2) | H18: =ROUND('Group Inputs'!AF6,2) | I18: =ROUND('Group Inputs'!AF7,2) | J18: =ROUND('Group Inputs'!AF8,2) | K18: =ROUND('Group Inputs'!AF9,2) | L18: 0 (O-05) | M18: O-05 | N18: severity_incidents
A19: EHS-003 | B19: Near misses | C19: count | D19: Month | E19: Near misses | F19: =ROUND('Group Inputs'!AG4,2) | G19: =ROUND('Group Inputs'!AG5,2) | H19: =ROUND('Group Inputs'!AG6,2) | I19: =ROUND('Group Inputs'!AG7,2) | J19: =ROUND('Group Inputs'!AG8,2) | K19: =ROUND('Group Inputs'!AG9,2) | L19: 14 (O-05) | M19: O-05 | N19: near_misses
A20: EHS-004 | B20: Critical safety incidents | C20: count | D20: Month | E20: Critical safety incidents | F20: =ROUND('Group Inputs'!AH4,2) | G20: =ROUND('Group Inputs'!AH5,2) | H20: =ROUND('Group Inputs'!AH6,2) | I20: =ROUND('Group Inputs'!AH7,2) | J20: =ROUND('Group Inputs'!AH8,2) | K20: =ROUND('Group Inputs'!AH9,2) | L20: 0 (O-05) | M20: O-05 | N20: critical_safety_incidents
A21: EHS-005 | B21: Environmental excursions | C21: count | D21: Month | E21: Environmental excursions | F21: =ROUND('Group Inputs'!AI4,2) | G21: =ROUND('Group Inputs'!AI5,2) | H21: =ROUND('Group Inputs'!AI6,2) | I21: =ROUND('Group Inputs'!AI7,2) | J21: =ROUND('Group Inputs'!AI8,2) | K21: =ROUND('Group Inputs'!AI9,2) | L21: 1 (minor, closed) (O-05) | M21: O-05 | N21: env_excursions
A22: EHS-007 | B22: Overdue EHS actions | C22: count | D22: Month | E22: Overdue EHS corrective actions | F22: =ROUND('Group Inputs'!AL4,2) | G22: =ROUND('Group Inputs'!AL5,2) | H22: =ROUND('Group Inputs'!AL6,2) | I22: =ROUND('Group Inputs'!AL7,2) | J22: =ROUND('Group Inputs'!AL8,2) | K22: =ROUND('Group Inputs'!AL9,2) | L22: 0 (O-05) | M22: O-05 | N22: ehs_ca_overdue
A23: REG-006 | B23: Licence or permit expiry clock | C23: days | D23: Month | E23: Days to permit expiry (lowest plant) | F23: =ROUND('Group Inputs'!AR4,2) | G23: =ROUND('Group Inputs'!AR5,2) | H23: =ROUND('Group Inputs'!AR6,2) | I23: =ROUND('Group Inputs'!AR7,2) | J23: =ROUND('Group Inputs'!AR8,2) | K23: =ROUND('Group Inputs'!AR9,2) | L23: 74 days · Entity C1 (O-05) | M23: O-05 | N23: permit_days_to_expiry
A24: OPS-005 | B24: Capacity utilisation (same measure as OPS-003) | C24: % | D24: Month | E24: Good output ÷ Installed capacity × 100 | F24: =ROUND(IFERROR(100*'Group Inputs'!M4/'Group Inputs'!J4,0),2) | G24: =ROUND(IFERROR(100*'Group Inputs'!M5/'Group Inputs'!J5,0),2) | H24: =ROUND(IFERROR(100*'Group Inputs'!M6/'Group Inputs'!J6,0),2) | I24: =ROUND(IFERROR(100*'Group Inputs'!M7/'Group Inputs'!J7,0),2) | J24: =ROUND(IFERROR(100*'Group Inputs'!M8/'Group Inputs'!J8,0),2) | K24: =ROUND(IFERROR(100*'Group Inputs'!M9/'Group Inputs'!J9,0),2) | L24: 86% (O-01) | M24: O-01 | N24: installed_capacity_t, good_output_t
A25: OPS-006 | B25: OEE · Group weighted (same measure as PLT-002) | C25: % | D25: Month | E25: Good output ÷ Ideal output × 100 (weighted by output, not an average of plants) | F25: =ROUND(IFERROR(100*'Group Inputs'!M4/'Group Inputs'!I4,0),2) | G25: =ROUND(IFERROR(100*'Group Inputs'!M5/'Group Inputs'!I5,0),2) | H25: =ROUND(IFERROR(100*'Group Inputs'!M6/'Group Inputs'!I6,0),2) | I25: =ROUND(IFERROR(100*'Group Inputs'!M7/'Group Inputs'!I7,0),2) | J25: =ROUND(IFERROR(100*'Group Inputs'!M8/'Group Inputs'!I8,0),2) | K25: =ROUND(IFERROR(100*'Group Inputs'!M9/'Group Inputs'!I9,0),2) | L25: Not on a screen | M25: — | N25: ideal_output_t, good_output_t
A26: OPS-002 | B26: Sales vs plan | C26: % | D26: Month | E26: Sales volume ÷ Planned sales volume × 100 | F26: =ROUND(IF('Group Inputs'!AT4=0,0,100*'Group Inputs'!AS4/'Group Inputs'!AT4),2) | G26: =ROUND(IF('Group Inputs'!AT5=0,0,100*'Group Inputs'!AS5/'Group Inputs'!AT5),2) | H26: =ROUND(IF('Group Inputs'!AT6=0,0,100*'Group Inputs'!AS6/'Group Inputs'!AT6),2) | I26: =ROUND(IF('Group Inputs'!AT7=0,0,100*'Group Inputs'!AS7/'Group Inputs'!AT7),2) | J26: =ROUND(IF('Group Inputs'!AT8=0,0,100*'Group Inputs'!AS8/'Group Inputs'!AT8),2) | K26: =ROUND(IF('Group Inputs'!AT9=0,0,100*'Group Inputs'!AS9/'Group Inputs'!AT9),2) | L26: 97.6% (O-01, STATE GALLERY) | M26: O-01, STATE GALLERY · O-01 + S-02, O-01 · large display ≥ 1600 | N26: sales_t, planned_sales_t
A27: OPS-004 | B27: Sales vs plan · Group (same measure as OPS-002) | C27: % | D27: Month | E27: Sales volume ÷ Planned sales volume × 100 | F27: =ROUND(IF('Group Inputs'!AT4=0,0,100*'Group Inputs'!AS4/'Group Inputs'!AT4),2) | G27: =ROUND(IF('Group Inputs'!AT5=0,0,100*'Group Inputs'!AS5/'Group Inputs'!AT5),2) | H27: =ROUND(IF('Group Inputs'!AT6=0,0,100*'Group Inputs'!AS6/'Group Inputs'!AT6),2) | I27: =ROUND(IF('Group Inputs'!AT7=0,0,100*'Group Inputs'!AS7/'Group Inputs'!AT7),2) | J27: =ROUND(IF('Group Inputs'!AT8=0,0,100*'Group Inputs'!AS8/'Group Inputs'!AT8),2) | K27: =ROUND(IF('Group Inputs'!AT9=0,0,100*'Group Inputs'!AS9/'Group Inputs'!AT9),2) | L27: 97.6% (O-01) | M27: O-01 | N27: sales_t, planned_sales_t
A28: CST-004 | B28: Power cost per tonne | C28: ₹/t | D28: Month | E28: Power cost × 1000 ÷ Good output | F28: =ROUND(IF('Group Inputs'!M4=0,0,1000*'Group Inputs'!AW4/'Group Inputs'!M4),2) | G28: =ROUND(IF('Group Inputs'!M5=0,0,1000*'Group Inputs'!AW5/'Group Inputs'!M5),2) | H28: =ROUND(IF('Group Inputs'!M6=0,0,1000*'Group Inputs'!AW6/'Group Inputs'!M6),2) | I28: =ROUND(IF('Group Inputs'!M7=0,0,1000*'Group Inputs'!AW7/'Group Inputs'!M7),2) | J28: =ROUND(IF('Group Inputs'!M8=0,0,1000*'Group Inputs'!AW8/'Group Inputs'!M8),2) | K28: =ROUND(IF('Group Inputs'!M9=0,0,1000*'Group Inputs'!AW9/'Group Inputs'!M9),2) | L28: Not on a screen | M28: — | N28: good_output_t, power_cost_k
A29: FIN-001 | B29: EBITDA YTD | C29: ₹ m | D29: Year to date | E29: Sum of monthly EBITDA since April ÷ 1000 | F29: =ROUND(SUM('Group Inputs'!FV$4:FV4)/1000,2) | G29: =ROUND(SUM('Group Inputs'!FV$4:FV5)/1000,2) | H29: =ROUND(SUM('Group Inputs'!FV$4:FV6)/1000,2) | I29: =ROUND(SUM('Group Inputs'!FV$4:FV7)/1000,2) | J29: =ROUND(SUM('Group Inputs'!FV$4:FV8)/1000,2) | K29: =ROUND(SUM('Group Inputs'!FV$4:FV9)/1000,2) | L29: 361.3 ₹ m (O-01, STATE GALLERY) | M29: O-01, STATE GALLERY · O-01 + S-02, O-01 · large display ≥ 1600 | N29: ebitda_k
A30: FIN-002 | B30: EBIT YTD | C30: ₹ m | D30: Year to date | E30: Sum of monthly EBIT since April ÷ 1000 | F30: =ROUND(SUM('Group Inputs'!FW$4:FW4)/1000,2) | G30: =ROUND(SUM('Group Inputs'!FW$4:FW5)/1000,2) | H30: =ROUND(SUM('Group Inputs'!FW$4:FW6)/1000,2) | I30: =ROUND(SUM('Group Inputs'!FW$4:FW7)/1000,2) | J30: =ROUND(SUM('Group Inputs'!FW$4:FW8)/1000,2) | K30: =ROUND(SUM('Group Inputs'!FW$4:FW9)/1000,2) | L30: 238.4 ₹ m (O-01, STATE GALLERY) | M30: O-01, STATE GALLERY · O-01 + S-02, O-01 · large display ≥ 1600 | N30: ebit_k
A31: FIN-003 | B31: Revenue YTD | C31: ₹ m | D31: Year to date | E31: Sum of monthly Revenue since April ÷ 1000 | F31: =ROUND(SUM('Group Inputs'!AU$4:AU4)/1000,2) | G31: =ROUND(SUM('Group Inputs'!AU$4:AU5)/1000,2) | H31: =ROUND(SUM('Group Inputs'!AU$4:AU6)/1000,2) | I31: =ROUND(SUM('Group Inputs'!AU$4:AU7)/1000,2) | J31: =ROUND(SUM('Group Inputs'!AU$4:AU8)/1000,2) | K31: =ROUND(SUM('Group Inputs'!AU$4:AU9)/1000,2) | L31: 2,410 ₹ m (O-01, STATE GALLERY) | M31: O-01, STATE GALLERY · O-01 + S-02, O-01 · large display ≥ 1600 | N31: revenue_k
A32: FIN-004 | B32: Free cash flow YTD | C32: ₹ m | D32: Year to date | E32: Sum of monthly Free cash flow since April ÷ 1000 | F32: =ROUND(SUM('Group Inputs'!GA$4:GA4)/1000,2) | G32: =ROUND(SUM('Group Inputs'!GA$4:GA5)/1000,2) | H32: =ROUND(SUM('Group Inputs'!GA$4:GA6)/1000,2) | I32: =ROUND(SUM('Group Inputs'!GA$4:GA7)/1000,2) | J32: =ROUND(SUM('Group Inputs'!GA$4:GA8)/1000,2) | K32: =ROUND(SUM('Group Inputs'!GA$4:GA9)/1000,2) | L32: 96.4 ₹ m (O-01, STATE GALLERY) | M32: O-01, O-01 · large display ≥ 1600, STATE GALLERY · O-01 + S-02 | N32: fcf_k
A33: FIN-005 | B33: ROCE, annualised | C33: % | D33: Year to date | E33: EBIT since April × 12 ÷ months elapsed ÷ Capital employed × 100 | F33: =ROUND(IF('Group Inputs'!CA4=0,0,100*SUM('Group Inputs'!FW$4:FW4)*12/'Group Inputs'!D4/'Group Inputs'!CA4),2) | G33: =ROUND(IF('Group Inputs'!CA5=0,0,100*SUM('Group Inputs'!FW$4:FW5)*12/'Group Inputs'!D5/'Group Inputs'!CA5),2) | H33: =ROUND(IF('Group Inputs'!CA6=0,0,100*SUM('Group Inputs'!FW$4:FW6)*12/'Group Inputs'!D6/'Group Inputs'!CA6),2) | I33: =ROUND(IF('Group Inputs'!CA7=0,0,100*SUM('Group Inputs'!FW$4:FW7)*12/'Group Inputs'!D7/'Group Inputs'!CA7),2) | J33: =ROUND(IF('Group Inputs'!CA8=0,0,100*SUM('Group Inputs'!FW$4:FW8)*12/'Group Inputs'!D8/'Group Inputs'!CA8),2) | K33: =ROUND(IF('Group Inputs'!CA9=0,0,100*SUM('Group Inputs'!FW$4:FW9)*12/'Group Inputs'!D9/'Group Inputs'!CA9),2) | L33: 11.8 % (O-01); 11.8% (O-01, STATE GALLERY) | M33: O-01, STATE GALLERY · O-01 + S-02, O-01 · large display ≥ 1600 | N33: ytd_months, capital_employed_k, ebit_k
A34: FIN-006 | B34: Net debt | C34: ₹ m | D34: Month end | E34: (Gross debt − Cash) ÷ 1000 | F34: =ROUND('Group Inputs'!GB4/1000,2) | G34: =ROUND('Group Inputs'!GB5/1000,2) | H34: =ROUND('Group Inputs'!GB6/1000,2) | I34: =ROUND('Group Inputs'!GB7/1000,2) | J34: =ROUND('Group Inputs'!GB8/1000,2) | K34: =ROUND('Group Inputs'!GB9/1000,2) | L34: 1,140 ₹ m (O-01, STATE GALLERY); 6,650.0 ₹ m (O-03) | M34: O-01, O-01 · large display ≥ 1600, O-03, STATE GALLERY · O-01 + S-02 | N34: net_debt_k
A35: FIN-007 | B35: Shareholder-value indicator (economic profit YTD) | C35: ₹ m | D35: Year to date | E35: (EBIT since April × (1 − Tax rate) − Capital employed × Cost of capital × months elapsed ÷ 12) ÷ 1000 | F35: =ROUND((SUM('Group Inputs'!FW$4:FW4)*(1-Parameters!$B$2)-'Group Inputs'!CA4*Parameters!$B$3*'Group Inputs'!D4/12)/1000,2) | G35: =ROUND((SUM('Group Inputs'!FW$4:FW5)*(1-Parameters!$B$2)-'Group Inputs'!CA5*Parameters!$B$3*'Group Inputs'!D5/12)/1000,2) | H35: =ROUND((SUM('Group Inputs'!FW$4:FW6)*(1-Parameters!$B$2)-'Group Inputs'!CA6*Parameters!$B$3*'Group Inputs'!D6/12)/1000,2) | I35: =ROUND((SUM('Group Inputs'!FW$4:FW7)*(1-Parameters!$B$2)-'Group Inputs'!CA7*Parameters!$B$3*'Group Inputs'!D7/12)/1000,2) | J35: =ROUND((SUM('Group Inputs'!FW$4:FW8)*(1-Parameters!$B$2)-'Group Inputs'!CA8*Parameters!$B$3*'Group Inputs'!D8/12)/1000,2) | K35: =ROUND((SUM('Group Inputs'!FW$4:FW9)*(1-Parameters!$B$2)-'Group Inputs'!CA9*Parameters!$B$3*'Group Inputs'!D9/12)/1000,2) | L35: [PLACEHOLDER] (O-01, STATE GALLERY) | M35: O-01, STATE GALLERY · O-01 + S-02, O-01 · large display ≥ 1600 | N35: ytd_months, capital_employed_k, ebit_k
A36: CSH-001 | B36: Cash position | C36: ₹ m | D36: Month end | E36: Cash ÷ 1000 | F36: =ROUND('Group Inputs'!CC4/1000,2) | G36: =ROUND('Group Inputs'!CC5/1000,2) | H36: =ROUND('Group Inputs'!CC6/1000,2) | I36: =ROUND('Group Inputs'!CC7/1000,2) | J36: =ROUND('Group Inputs'!CC8/1000,2) | K36: =ROUND('Group Inputs'!CC9/1000,2) | L36: 2,141.8 ₹ m (O-03) | M36: O-03 | N36: cash_k
A37: CSH-002 | B37: Cash released YTD | C37: ₹ m | D37: Year to date | E37: Sum of cash released since April ÷ 1000 | F37: =ROUND(SUM('Group Inputs'!CN$4:CN4)/1000,2) | G37: =ROUND(SUM('Group Inputs'!CN$4:CN5)/1000,2) | H37: =ROUND(SUM('Group Inputs'!CN$4:CN6)/1000,2) | I37: =ROUND(SUM('Group Inputs'!CN$4:CN7)/1000,2) | J37: =ROUND(SUM('Group Inputs'!CN$4:CN8)/1000,2) | K37: =ROUND(SUM('Group Inputs'!CN$4:CN9)/1000,2) | L37: Not on a screen | M37: — | N37: cash_released_k
A38: CSH-003 | B38: Daily collections | C38: ₹ m per day | D38: Month | E38: Cash collected ÷ Days in month ÷ 1000 | F38: =ROUND('Group Inputs'!CM4/'Group Inputs'!C4/1000,2) | G38: =ROUND('Group Inputs'!CM5/'Group Inputs'!C5/1000,2) | H38: =ROUND('Group Inputs'!CM6/'Group Inputs'!C6/1000,2) | I38: =ROUND('Group Inputs'!CM7/'Group Inputs'!C7/1000,2) | J38: =ROUND('Group Inputs'!CM8/'Group Inputs'!C8/1000,2) | K38: =ROUND('Group Inputs'!CM9/'Group Inputs'!C9/1000,2) | L38: 4.1 ₹ m (S-11) | M38: S-11 | N38: days, collections_k
A39: CSH-004 | B39: Cash-conversion cycle | C39: days | D39: Month end | E39: DSO + Inventory days − DPO | F39: =ROUND('Group Inputs'!GD4+'Group Inputs'!GF4-'Group Inputs'!GE4,2) | G39: =ROUND('Group Inputs'!GD5+'Group Inputs'!GF5-'Group Inputs'!GE5,2) | H39: =ROUND('Group Inputs'!GD6+'Group Inputs'!GF6-'Group Inputs'!GE6,2) | I39: =ROUND('Group Inputs'!GD7+'Group Inputs'!GF7-'Group Inputs'!GE7,2) | J39: =ROUND('Group Inputs'!GD8+'Group Inputs'!GF8-'Group Inputs'!GE8,2) | K39: =ROUND('Group Inputs'!GD9+'Group Inputs'!GF9-'Group Inputs'!GE9,2) | L39: Not on a screen | M39: — | N39: dso_d, dpo_d, dio_d
A40: CSH-006 | B40: Cash-upstream exposure | C40: ₹ m | D40: Next 30 days | E40: (Cash due to be upstreamed − Amount covered by available cash) ÷ 1000 | F40: =ROUND(('Group Inputs'!CO4-'Group Inputs'!CP4)/1000,2) | G40: =ROUND(('Group Inputs'!CO5-'Group Inputs'!CP5)/1000,2) | H40: =ROUND(('Group Inputs'!CO6-'Group Inputs'!CP6)/1000,2) | I40: =ROUND(('Group Inputs'!CO7-'Group Inputs'!CP7)/1000,2) | J40: =ROUND(('Group Inputs'!CO8-'Group Inputs'!CP8)/1000,2) | K40: =ROUND(('Group Inputs'!CO9-'Group Inputs'!CP9)/1000,2) | L40: 26 ₹ m (S-11); 27.2 ₹ m (O-03) | M40: O-03, S-11 | N40: upstream_due_k, upstream_covered_k
A41: WCP-001 | B41: DSO | C41: days | D41: Month end | E41: Trade receivables ÷ Revenue × Days in month | F41: =ROUND('Group Inputs'!GD4,2) | G41: =ROUND('Group Inputs'!GD5,2) | H41: =ROUND('Group Inputs'!GD6,2) | I41: =ROUND('Group Inputs'!GD7,2) | J41: =ROUND('Group Inputs'!GD8,2) | K41: =ROUND('Group Inputs'!GD9,2) | L41: 52 days (S-11); 47.0 days (O-03) | M41: O-03, S-11 | N41: dso_d
A42: WCP-002 | B42: DPO | C42: days | D42: Month end | E42: Trade payables ÷ Variable cost × Days in month | F42: =ROUND('Group Inputs'!GE4,2) | G42: =ROUND('Group Inputs'!GE5,2) | H42: =ROUND('Group Inputs'!GE6,2) | I42: =ROUND('Group Inputs'!GE7,2) | J42: =ROUND('Group Inputs'!GE8,2) | K42: =ROUND('Group Inputs'!GE9,2) | L42: Not on a screen | M42: — | N42: dpo_d
A43: WCP-003 | B43: Inventory days | C43: days | D43: Month end | E43: Inventory ÷ Variable cost × Days in month | F43: =ROUND('Group Inputs'!GF4,2) | G43: =ROUND('Group Inputs'!GF5,2) | H43: =ROUND('Group Inputs'!GF6,2) | I43: =ROUND('Group Inputs'!GF7,2) | J43: =ROUND('Group Inputs'!GF8,2) | K43: =ROUND('Group Inputs'!GF9,2) | L43: Not on a screen | M43: — | N43: dio_d
A44: WCP-004 | B44: Net working capital | C44: ₹ m | D44: Month end | E44: (Trade receivables + Inventory − Trade payables) ÷ 1000 | F44: =ROUND('Group Inputs'!FX4/1000,2) | G44: =ROUND('Group Inputs'!FX5/1000,2) | H44: =ROUND('Group Inputs'!FX6/1000,2) | I44: =ROUND('Group Inputs'!FX7/1000,2) | J44: =ROUND('Group Inputs'!FX8/1000,2) | K44: =ROUND('Group Inputs'!FX9/1000,2) | L44: 2,781.0 ₹ m (O-03) | M44: O-03 | N44: nwc_k
A45: WCP-005 | B45: Working-capital movement | C45: ₹ m | D45: Month | E45: (Net working capital − last month's net working capital) ÷ 1000; positive = cash tied up | F45: =ROUND('Group Inputs'!FY4/1000,2) | G45: =ROUND('Group Inputs'!FY5/1000,2) | H45: =ROUND('Group Inputs'!FY6/1000,2) | I45: =ROUND('Group Inputs'!FY7/1000,2) | J45: =ROUND('Group Inputs'!FY8/1000,2) | K45: =ROUND('Group Inputs'!FY9/1000,2) | L45: Not on a screen | M45: — | N45: nwc_change_k
A46: WCP-006 | B46: Working-capital days | C46: days | D46: Month end | E46: Net working capital ÷ Revenue × Days in month | F46: =ROUND(IF('Group Inputs'!AU4=0,0,'Group Inputs'!FX4/'Group Inputs'!AU4*'Group Inputs'!C4),2) | G46: =ROUND(IF('Group Inputs'!AU5=0,0,'Group Inputs'!FX5/'Group Inputs'!AU5*'Group Inputs'!C5),2) | H46: =ROUND(IF('Group Inputs'!AU6=0,0,'Group Inputs'!FX6/'Group Inputs'!AU6*'Group Inputs'!C6),2) | I46: =ROUND(IF('Group Inputs'!AU7=0,0,'Group Inputs'!FX7/'Group Inputs'!AU7*'Group Inputs'!C7),2) | J46: =ROUND(IF('Group Inputs'!AU8=0,0,'Group Inputs'!FX8/'Group Inputs'!AU8*'Group Inputs'!C8),2) | K46: =ROUND(IF('Group Inputs'!AU9=0,0,'Group Inputs'!FX9/'Group Inputs'!AU9*'Group Inputs'!C9),2) | L46: Not on a screen | M46: — | N46: days, revenue_k, nwc_k
A47: LIQ-001 | B47: Liquidity runway | C47: months | D47: Month end | E47: (Cash + Undrawn facilities) ÷ (Fixed cost + Overheads + Debt service) per month | F47: =ROUND(IF(('Group Inputs'!X4+'Group Inputs'!BY4+'Group Inputs'!CE4)=0,0,('Group Inputs'!CC4+'Group Inputs'!CD4)/('Group Inputs'!X4+'Group Inputs'!BY4+'Group Inputs'!CE4)),2) | G47: =ROUND(IF(('Group Inputs'!X5+'Group Inputs'!BY5+'Group Inputs'!CE5)=0,0,('Group Inputs'!CC5+'Group Inputs'!CD5)/('Group Inputs'!X5+'Group Inputs'!BY5+'Group Inputs'!CE5)),2) | H47: =ROUND(IF(('Group Inputs'!X6+'Group Inputs'!BY6+'Group Inputs'!CE6)=0,0,('Group Inputs'!CC6+'Group Inputs'!CD6)/('Group Inputs'!X6+'Group Inputs'!BY6+'Group Inputs'!CE6)),2) | I47: =ROUND(IF(('Group Inputs'!X7+'Group Inputs'!BY7+'Group Inputs'!CE7)=0,0,('Group Inputs'!CC7+'Group Inputs'!CD7)/('Group Inputs'!X7+'Group Inputs'!BY7+'Group Inputs'!CE7)),2) | J47: =ROUND(IF(('Group Inputs'!X8+'Group Inputs'!BY8+'Group Inputs'!CE8)=0,0,('Group Inputs'!CC8+'Group Inputs'!CD8)/('Group Inputs'!X8+'Group Inputs'!BY8+'Group Inputs'!CE8)),2) | K47: =ROUND(IF(('Group Inputs'!X9+'Group Inputs'!BY9+'Group Inputs'!CE9)=0,0,('Group Inputs'!CC9+'Group Inputs'!CD9)/('Group Inputs'!X9+'Group Inputs'!BY9+'Group Inputs'!CE9)),2) | L47: 16.7 months (O-03) | M47: O-03 | N47: fixed_cost_k, overhead_k, cash_k, undrawn_facilities_k, debt_service_k
A48: LIQ-002 | B48: Covenant headroom | C48: % | D48: Month end | E48: (Covenant limit − Net debt ÷ Annualised EBITDA) ÷ Covenant limit × 100 | F48: =ROUND(IF('Group Inputs'!GC4=0,0,100*(Parameters!$B$4-'Group Inputs'!GB4/'Group Inputs'!GC4)/Parameters!$B$4),2) | G48: =ROUND(IF('Group Inputs'!GC5=0,0,100*(Parameters!$B$4-'Group Inputs'!GB5/'Group Inputs'!GC5)/Parameters!$B$4),2) | H48: =ROUND(IF('Group Inputs'!GC6=0,0,100*(Parameters!$B$4-'Group Inputs'!GB6/'Group Inputs'!GC6)/Parameters!$B$4),2) | I48: =ROUND(IF('Group Inputs'!GC7=0,0,100*(Parameters!$B$4-'Group Inputs'!GB7/'Group Inputs'!GC7)/Parameters!$B$4),2) | J48: =ROUND(IF('Group Inputs'!GC8=0,0,100*(Parameters!$B$4-'Group Inputs'!GB8/'Group Inputs'!GC8)/Parameters!$B$4),2) | K48: =ROUND(IF('Group Inputs'!GC9=0,0,100*(Parameters!$B$4-'Group Inputs'!GB9/'Group Inputs'!GC9)/Parameters!$B$4),2) | L48: Not on a screen | M48: — | N48: net_debt_k, ebitda_annualised_k
A49: LIQ-003 | B49: Debt-maturity exposure, next 12 months | C49: ₹ m | D49: Month end | E49: Debt maturing in next 12 months ÷ 1000 | F49: =ROUND('Group Inputs'!CF4/1000,2) | G49: =ROUND('Group Inputs'!CF5/1000,2) | H49: =ROUND('Group Inputs'!CF6/1000,2) | I49: =ROUND('Group Inputs'!CF7/1000,2) | J49: =ROUND('Group Inputs'!CF8/1000,2) | K49: =ROUND('Group Inputs'!CF9/1000,2) | L49: 891.4 ₹ m (O-03) | M49: O-03 | N49: debt_maturing_12m_k
A50: LIQ-004 | B50: Financing exposure (floating-rate debt) | C50: ₹ m | D50: Month end | E50: Floating-rate debt ÷ 1000 | F50: =ROUND('Group Inputs'!CG4/1000,2) | G50: =ROUND('Group Inputs'!CG5/1000,2) | H50: =ROUND('Group Inputs'!CG6/1000,2) | I50: =ROUND('Group Inputs'!CG7/1000,2) | J50: =ROUND('Group Inputs'!CG8/1000,2) | K50: =ROUND('Group Inputs'!CG9/1000,2) | L50: 2,720.8 ₹ m (O-03) | M50: O-03 | N50: floating_rate_debt_k
A51: TRS-001 | B51: FX exposure, unhedged | C51: ₹ m | D51: Month end | E51: (Foreign-currency exposure − Amount hedged) ÷ 1000 | F51: =ROUND(('Group Inputs'!CZ4-'Group Inputs'!DA4)/1000,2) | G51: =ROUND(('Group Inputs'!CZ5-'Group Inputs'!DA5)/1000,2) | H51: =ROUND(('Group Inputs'!CZ6-'Group Inputs'!DA6)/1000,2) | I51: =ROUND(('Group Inputs'!CZ7-'Group Inputs'!DA7)/1000,2) | J51: =ROUND(('Group Inputs'!CZ8-'Group Inputs'!DA8)/1000,2) | K51: =ROUND(('Group Inputs'!CZ9-'Group Inputs'!DA9)/1000,2) | L51: Not on a screen | M51: — | N51: fx_exposure_k, fx_hedged_k
A52: TRS-002 | B52: Hedging effectiveness | C52: % | D52: Month | E52: Change in value of hedges ÷ Change in value of hedged items × 100 | F52: =ROUND(IF('Group Inputs'!DE4=0,0,100*'Group Inputs'!DD4/'Group Inputs'!DE4),2) | G52: =ROUND(IF('Group Inputs'!DE5=0,0,100*'Group Inputs'!DD5/'Group Inputs'!DE5),2) | H52: =ROUND(IF('Group Inputs'!DE6=0,0,100*'Group Inputs'!DD6/'Group Inputs'!DE6),2) | I52: =ROUND(IF('Group Inputs'!DE7=0,0,100*'Group Inputs'!DD7/'Group Inputs'!DE7),2) | J52: =ROUND(IF('Group Inputs'!DE8=0,0,100*'Group Inputs'!DD8/'Group Inputs'!DE8),2) | K52: =ROUND(IF('Group Inputs'!DE9=0,0,100*'Group Inputs'!DD9/'Group Inputs'!DE9),2) | L52: Not on a screen | M52: — | N52: hedge_value_change_k, hedged_item_value_change_k
A53: TRS-003 | B53: USD share of unhedged FX exposure | C53: % | D53: Month end | E53: (USD exposure − USD hedged) ÷ (FX exposure − FX hedged) × 100 | F53: =ROUND(IF(('Group Inputs'!CZ4-'Group Inputs'!DA4)=0,0,100*('Group Inputs'!DB4-'Group Inputs'!DC4)/('Group Inputs'!CZ4-'Group Inputs'!DA4)),2) | G53: =ROUND(IF(('Group Inputs'!CZ5-'Group Inputs'!DA5)=0,0,100*('Group Inputs'!DB5-'Group Inputs'!DC5)/('Group Inputs'!CZ5-'Group Inputs'!DA5)),2) | H53: =ROUND(IF(('Group Inputs'!CZ6-'Group Inputs'!DA6)=0,0,100*('Group Inputs'!DB6-'Group Inputs'!DC6)/('Group Inputs'!CZ6-'Group Inputs'!DA6)),2) | I53: =ROUND(IF(('Group Inputs'!CZ7-'Group Inputs'!DA7)=0,0,100*('Group Inputs'!DB7-'Group Inputs'!DC7)/('Group Inputs'!CZ7-'Group Inputs'!DA7)),2) | J53: =ROUND(IF(('Group Inputs'!CZ8-'Group Inputs'!DA8)=0,0,100*('Group Inputs'!DB8-'Group Inputs'!DC8)/('Group Inputs'!CZ8-'Group Inputs'!DA8)),2) | K53: =ROUND(IF(('Group Inputs'!CZ9-'Group Inputs'!DA9)=0,0,100*('Group Inputs'!DB9-'Group Inputs'!DC9)/('Group Inputs'!CZ9-'Group Inputs'!DA9)),2) | L53: Not on a screen | M53: — | N53: fx_exposure_k, fx_hedged_k, usd_exposure_k, usd_hedged_k
A54: TRS-004 | B54: Hedge cover, next 6 months | C54: % | D54: Next 6 months | E54: Foreign-currency flows hedged ÷ Forecast foreign-currency flows, next 6 months × 100 | F54: =ROUND(IF('Group Inputs'!DF4=0,0,100*'Group Inputs'!DG4/'Group Inputs'!DF4),2) | G54: =ROUND(IF('Group Inputs'!DF5=0,0,100*'Group Inputs'!DG5/'Group Inputs'!DF5),2) | H54: =ROUND(IF('Group Inputs'!DF6=0,0,100*'Group Inputs'!DG6/'Group Inputs'!DF6),2) | I54: =ROUND(IF('Group Inputs'!DF7=0,0,100*'Group Inputs'!DG7/'Group Inputs'!DF7),2) | J54: =ROUND(IF('Group Inputs'!DF8=0,0,100*'Group Inputs'!DG8/'Group Inputs'!DF8),2) | K54: =ROUND(IF('Group Inputs'!DF9=0,0,100*'Group Inputs'!DG9/'Group Inputs'!DF9),2) | L54: 70.7 % (O-03) | M54: O-03 | N54: fx_flows_6m_k, fx_hedged_6m_k
A55: TRS-005 | B55: FX sensitivity, 5% USD move | C55: ₹ m | D55: Month end | E55: 5% × (USD exposure − USD hedged) ÷ 1000 | F55: =ROUND(0.05*('Group Inputs'!DB4-'Group Inputs'!DC4)/1000,2) | G55: =ROUND(0.05*('Group Inputs'!DB5-'Group Inputs'!DC5)/1000,2) | H55: =ROUND(0.05*('Group Inputs'!DB6-'Group Inputs'!DC6)/1000,2) | I55: =ROUND(0.05*('Group Inputs'!DB7-'Group Inputs'!DC7)/1000,2) | J55: =ROUND(0.05*('Group Inputs'!DB8-'Group Inputs'!DC8)/1000,2) | K55: =ROUND(0.05*('Group Inputs'!DB9-'Group Inputs'!DC9)/1000,2) | L55: Not on a screen | M55: — | N55: usd_exposure_k, usd_hedged_k
A56: CPX-001 | B56: Approved capex budget | C56: ₹ m | D56: Full year | E56: Approved capex budget ÷ 1000 | F56: =ROUND('Group Inputs'!DH4/1000,2) | G56: =ROUND('Group Inputs'!DH5/1000,2) | H56: =ROUND('Group Inputs'!DH6/1000,2) | I56: =ROUND('Group Inputs'!DH7/1000,2) | J56: =ROUND('Group Inputs'!DH8/1000,2) | K56: =ROUND('Group Inputs'!DH9/1000,2) | L56: 850 ₹ m (O-04) | M56: O-04 | N56: capex_budget_k
A57: CPX-002 | B57: Committed capex | C57: ₹ m | D57: To date | E57: Capex committed to date ÷ 1000 | F57: =ROUND('Group Inputs'!DI4/1000,2) | G57: =ROUND('Group Inputs'!DI5/1000,2) | H57: =ROUND('Group Inputs'!DI6/1000,2) | I57: =ROUND('Group Inputs'!DI7/1000,2) | J57: =ROUND('Group Inputs'!DI8/1000,2) | K57: =ROUND('Group Inputs'!DI9/1000,2) | L57: 610 ₹ m · 72% (O-04) | M57: O-04 | N57: capex_committed_k
A58: CPX-003 | B58: Capex actual spend YTD | C58: ₹ m | D58: Year to date | E58: Sum of capex spent since April ÷ 1000 | F58: =ROUND(SUM('Group Inputs'!DJ$4:DJ4)/1000,2) | G58: =ROUND(SUM('Group Inputs'!DJ$4:DJ5)/1000,2) | H58: =ROUND(SUM('Group Inputs'!DJ$4:DJ6)/1000,2) | I58: =ROUND(SUM('Group Inputs'!DJ$4:DJ7)/1000,2) | J58: =ROUND(SUM('Group Inputs'!DJ$4:DJ8)/1000,2) | K58: =ROUND(SUM('Group Inputs'!DJ$4:DJ9)/1000,2) | L58: 402 ₹ m · 47% (O-04) | M58: O-04 | N58: capex_spend_k
A59: CPX-004 | B59: Capex physical progress, weighted | C59: % | D59: To date | E59: Work completed valued at budget ÷ Approved budget × 100 (weights each project by its budget) | F59: =ROUND(IF('Group Inputs'!DH4=0,0,100*'Group Inputs'!DK4/'Group Inputs'!DH4),2) | G59: =ROUND(IF('Group Inputs'!DH5=0,0,100*'Group Inputs'!DK5/'Group Inputs'!DH5),2) | H59: =ROUND(IF('Group Inputs'!DH6=0,0,100*'Group Inputs'!DK6/'Group Inputs'!DH6),2) | I59: =ROUND(IF('Group Inputs'!DH7=0,0,100*'Group Inputs'!DK7/'Group Inputs'!DH7),2) | J59: =ROUND(IF('Group Inputs'!DH8=0,0,100*'Group Inputs'!DK8/'Group Inputs'!DH8),2) | K59: =ROUND(IF('Group Inputs'!DH9=0,0,100*'Group Inputs'!DK9/'Group Inputs'!DH9),2) | L59: 61 % weighted (O-01, O-04, STATE GALLERY) | M59: O-01, O-04, STATE GALLERY · O-01 + S-02, O-01 · large display ≥ 1600 | N59: capex_budget_k, capex_earned_value_k
A60: SIG-011 | B60: Capex value at risk | C60: ₹ m | D60: Month end | E60: Budget of projects at risk ÷ 1000 | F60: =ROUND('Group Inputs'!DL4/1000,2) | G60: =ROUND('Group Inputs'!DL5/1000,2) | H60: =ROUND('Group Inputs'!DL6/1000,2) | I60: =ROUND('Group Inputs'!DL7/1000,2) | J60: =ROUND('Group Inputs'!DL8/1000,2) | K60: =ROUND('Group Inputs'!DL9/1000,2) | L60: 34 ₹ m (O-04); ₹34 m (O-04) | M60: O-04 | N60: capex_at_risk_k
A61: PRG-001 | B61: Capex project status | C61: text | D61: Month end | E61: Count of projects by status | F61: ='Group Inputs'!DM4&" on track · "&'Group Inputs'!DN4&" at risk · "&'Group Inputs'!DO4&" off track" | G61: ='Group Inputs'!DM5&" on track · "&'Group Inputs'!DN5&" at risk · "&'Group Inputs'!DO5&" off track" | H61: ='Group Inputs'!DM6&" on track · "&'Group Inputs'!DN6&" at risk · "&'Group Inputs'!DO6&" off track" | I61: ='Group Inputs'!DM7&" on track · "&'Group Inputs'!DN7&" at risk · "&'Group Inputs'!DO7&" off track" | J61: ='Group Inputs'!DM8&" on track · "&'Group Inputs'!DN8&" at risk · "&'Group Inputs'!DO8&" off track" | K61: ='Group Inputs'!DM9&" on track · "&'Group Inputs'!DN9&" at risk · "&'Group Inputs'!DO9&" off track" | L61: 9 on track · 2 at risk · 0 off track (O-04) | M61: O-04 | N61: projects_on_track, projects_at_risk, projects_off_track
A62: PRG-002 | B62: Benefits realisation | C62: % | D62: Year to date | E62: Benefits delivered since April ÷ Benefits planned since April × 100 | F62: =ROUND(IF(SUM('Group Inputs'!DX$4:DX4)=0,0,100*SUM('Group Inputs'!DY$4:DY4)/SUM('Group Inputs'!DX$4:DX4)),2) | G62: =ROUND(IF(SUM('Group Inputs'!DX$4:DX5)=0,0,100*SUM('Group Inputs'!DY$4:DY5)/SUM('Group Inputs'!DX$4:DX5)),2) | H62: =ROUND(IF(SUM('Group Inputs'!DX$4:DX6)=0,0,100*SUM('Group Inputs'!DY$4:DY6)/SUM('Group Inputs'!DX$4:DX6)),2) | I62: =ROUND(IF(SUM('Group Inputs'!DX$4:DX7)=0,0,100*SUM('Group Inputs'!DY$4:DY7)/SUM('Group Inputs'!DX$4:DX7)),2) | J62: =ROUND(IF(SUM('Group Inputs'!DX$4:DX8)=0,0,100*SUM('Group Inputs'!DY$4:DY8)/SUM('Group Inputs'!DX$4:DX8)),2) | K62: =ROUND(IF(SUM('Group Inputs'!DX$4:DX9)=0,0,100*SUM('Group Inputs'!DY$4:DY9)/SUM('Group Inputs'!DX$4:DX9)),2) | L62: 48 % of plan (O-04) | M62: O-04 | N62: benefits_planned_k, benefits_delivered_k
A63: PRG-003 | B63: Delayed projects | C63: count | D63: Month end | E63: Capex projects delayed | F63: =ROUND('Group Inputs'!DP4,2) | G63: =ROUND('Group Inputs'!DP5,2) | H63: =ROUND('Group Inputs'!DP6,2) | I63: =ROUND('Group Inputs'!DP7,2) | J63: =ROUND('Group Inputs'!DP8,2) | K63: =ROUND('Group Inputs'!DP9,2) | L63: 1 (O-04) | M63: O-04 | N63: projects_delayed
A64: PRG-004 | B64: Capex / transformation progress (same measure as STR-002) | C64: % | D64: To date | E64: Transformation milestones completed ÷ Milestones in plan × 100 | F64: =ROUND(IF('Group Inputs'!DV4=0,0,100*'Group Inputs'!DW4/'Group Inputs'!DV4),2) | G64: =ROUND(IF('Group Inputs'!DV5=0,0,100*'Group Inputs'!DW5/'Group Inputs'!DV5),2) | H64: =ROUND(IF('Group Inputs'!DV6=0,0,100*'Group Inputs'!DW6/'Group Inputs'!DV6),2) | I64: =ROUND(IF('Group Inputs'!DV7=0,0,100*'Group Inputs'!DW7/'Group Inputs'!DV7),2) | J64: =ROUND(IF('Group Inputs'!DV8=0,0,100*'Group Inputs'!DW8/'Group Inputs'!DV8),2) | K64: =ROUND(IF('Group Inputs'!DV9=0,0,100*'Group Inputs'!DW9/'Group Inputs'!DV9),2) | L64: 54% (O-01, O-04) | M64: O-01, O-04 | N64: milestones_total, milestones_done
A65: STR-002 | B65: Transformation progress | C65: % | D65: To date | E65: Transformation milestones completed ÷ Milestones in plan × 100 | F65: =ROUND(IF('Group Inputs'!DV4=0,0,100*'Group Inputs'!DW4/'Group Inputs'!DV4),2) | G65: =ROUND(IF('Group Inputs'!DV5=0,0,100*'Group Inputs'!DW5/'Group Inputs'!DV5),2) | H65: =ROUND(IF('Group Inputs'!DV6=0,0,100*'Group Inputs'!DW6/'Group Inputs'!DV6),2) | I65: =ROUND(IF('Group Inputs'!DV7=0,0,100*'Group Inputs'!DW7/'Group Inputs'!DV7),2) | J65: =ROUND(IF('Group Inputs'!DV8=0,0,100*'Group Inputs'!DW8/'Group Inputs'!DV8),2) | K65: =ROUND(IF('Group Inputs'!DV9=0,0,100*'Group Inputs'!DW9/'Group Inputs'!DV9),2) | L65: 54% (O-01, O-04, STATE GALLERY) | M65: O-01, O-04, STATE GALLERY · O-01 + S-02, O-01 · large display ≥ 1600 | N65: milestones_total, milestones_done
A66: PRG-005 | B66: Transformation initiative status | C66: text | D66: Month end | E66: Count of transformation initiatives by status | F66: ='Group Inputs'!DS4&" on track · "&'Group Inputs'!DT4&" at risk · "&'Group Inputs'!DU4&" delayed" | G66: ='Group Inputs'!DS5&" on track · "&'Group Inputs'!DT5&" at risk · "&'Group Inputs'!DU5&" delayed" | H66: ='Group Inputs'!DS6&" on track · "&'Group Inputs'!DT6&" at risk · "&'Group Inputs'!DU6&" delayed" | I66: ='Group Inputs'!DS7&" on track · "&'Group Inputs'!DT7&" at risk · "&'Group Inputs'!DU7&" delayed" | J66: ='Group Inputs'!DS8&" on track · "&'Group Inputs'!DT8&" at risk · "&'Group Inputs'!DU8&" delayed" | K66: ='Group Inputs'!DS9&" on track · "&'Group Inputs'!DT9&" at risk · "&'Group Inputs'!DU9&" delayed" | L66: 15 on track · 6 at risk · 3 delayed (O-04) | M66: O-04 | N66: initiatives_on_track, initiatives_at_risk, initiatives_delayed
A67: VAL-001 | B67: EBITDA benefit YTD | C67: ₹ m | D67: Year to date | E67: Sum of EBITDA benefit since April ÷ 1000 | F67: =ROUND(SUM('Group Inputs'!DZ$4:DZ4)/1000,2) | G67: =ROUND(SUM('Group Inputs'!DZ$4:DZ5)/1000,2) | H67: =ROUND(SUM('Group Inputs'!DZ$4:DZ6)/1000,2) | I67: =ROUND(SUM('Group Inputs'!DZ$4:DZ7)/1000,2) | J67: =ROUND(SUM('Group Inputs'!DZ$4:DZ8)/1000,2) | K67: =ROUND(SUM('Group Inputs'!DZ$4:DZ9)/1000,2) | L67: ₹14 m (O-04) | M67: O-04 | N67: ebitda_benefit_k
A68: VAL-002 | B68: Cash benefit YTD | C68: ₹ m | D68: Year to date | E68: Sum of cash benefit since April ÷ 1000 | F68: =ROUND(SUM('Group Inputs'!EA$4:EA4)/1000,2) | G68: =ROUND(SUM('Group Inputs'!EA$4:EA5)/1000,2) | H68: =ROUND(SUM('Group Inputs'!EA$4:EA6)/1000,2) | I68: =ROUND(SUM('Group Inputs'!EA$4:EA7)/1000,2) | J68: =ROUND(SUM('Group Inputs'!EA$4:EA8)/1000,2) | K68: =ROUND(SUM('Group Inputs'!EA$4:EA9)/1000,2) | L68: ₹9 m (O-04) | M68: O-04 | N68: cash_benefit_k
A69: VAL-003 | B69: Cost savings delivered YTD | C69: ₹ m | D69: Year to date | E69: Sum of cost savings since April ÷ 1000 | F69: =ROUND(SUM('Group Inputs'!EB$4:EB4)/1000,2) | G69: =ROUND(SUM('Group Inputs'!EB$4:EB5)/1000,2) | H69: =ROUND(SUM('Group Inputs'!EB$4:EB6)/1000,2) | I69: =ROUND(SUM('Group Inputs'!EB$4:EB7)/1000,2) | J69: =ROUND(SUM('Group Inputs'!EB$4:EB8)/1000,2) | K69: =ROUND(SUM('Group Inputs'!EB$4:EB9)/1000,2) | L69: ₹11 m (O-04) | M69: O-04 | N69: cost_savings_k
A70: SUP-001 | B70: Supplier on-time delivery | C70: % | D70: Month | E70: Purchase-order lines on time ÷ Lines due × 100 | F70: =ROUND(IF('Group Inputs'!AY4=0,0,100*'Group Inputs'!AZ4/'Group Inputs'!AY4),2) | G70: =ROUND(IF('Group Inputs'!AY5=0,0,100*'Group Inputs'!AZ5/'Group Inputs'!AY5),2) | H70: =ROUND(IF('Group Inputs'!AY6=0,0,100*'Group Inputs'!AZ6/'Group Inputs'!AY6),2) | I70: =ROUND(IF('Group Inputs'!AY7=0,0,100*'Group Inputs'!AZ7/'Group Inputs'!AY7),2) | J70: =ROUND(IF('Group Inputs'!AY8=0,0,100*'Group Inputs'!AZ8/'Group Inputs'!AY8),2) | K70: =ROUND(IF('Group Inputs'!AY9=0,0,100*'Group Inputs'!AZ9/'Group Inputs'!AY9),2) | L70: Not on a screen | M70: — | N70: po_lines_due, po_lines_on_time
A71: SUP-007 | B71: Single-source spend share | C71: % | D71: Month | E71: Spend with single-source suppliers ÷ Supplier spend × 100 | F71: =ROUND(IF('Group Inputs'!BF4=0,0,100*'Group Inputs'!BG4/'Group Inputs'!BF4),2) | G71: =ROUND(IF('Group Inputs'!BF5=0,0,100*'Group Inputs'!BG5/'Group Inputs'!BF5),2) | H71: =ROUND(IF('Group Inputs'!BF6=0,0,100*'Group Inputs'!BG6/'Group Inputs'!BF6),2) | I71: =ROUND(IF('Group Inputs'!BF7=0,0,100*'Group Inputs'!BG7/'Group Inputs'!BF7),2) | J71: =ROUND(IF('Group Inputs'!BF8=0,0,100*'Group Inputs'!BG8/'Group Inputs'!BF8),2) | K71: =ROUND(IF('Group Inputs'!BF9=0,0,100*'Group Inputs'!BG9/'Group Inputs'!BF9),2) | L71: Not on a screen | M71: — | N71: supplier_spend_k, single_source_spend_k
A72: SUP-008 | B72: Supplier EHS incidents YTD | C72: count | D72: Year to date | E72: Sum of supplier EHS incidents since April | F72: =ROUND(SUM('Group Inputs'!BH$4:BH4),2) | G72: =ROUND(SUM('Group Inputs'!BH$4:BH5),2) | H72: =ROUND(SUM('Group Inputs'!BH$4:BH6),2) | I72: =ROUND(SUM('Group Inputs'!BH$4:BH7),2) | J72: =ROUND(SUM('Group Inputs'!BH$4:BH8),2) | K72: =ROUND(SUM('Group Inputs'!BH$4:BH9),2) | L72: Not on a screen | M72: — | N72: supplier_ehs_incidents
A73: CON-001 | B73: Contracts expiring, next 90 days | C73: count | D73: Month end | E73: Contracts expiring in next 90 days | F73: =ROUND('Group Inputs'!EE4,2) | G73: =ROUND('Group Inputs'!EE5,2) | H73: =ROUND('Group Inputs'!EE6,2) | I73: =ROUND('Group Inputs'!EE7,2) | J73: =ROUND('Group Inputs'!EE8,2) | K73: =ROUND('Group Inputs'!EE9,2) | L73: 4 (O-05) | M73: O-05 | N73: contracts_expiring_90d
A74: CON-002 | B74: Contract-compliance rate | C74: % | D74: Month end | E74: Contracts fully compliant ÷ Active contracts × 100 | F74: =ROUND(IF('Group Inputs'!EC4=0,0,100*'Group Inputs'!ED4/'Group Inputs'!EC4),2) | G74: =ROUND(IF('Group Inputs'!EC5=0,0,100*'Group Inputs'!ED5/'Group Inputs'!EC5),2) | H74: =ROUND(IF('Group Inputs'!EC6=0,0,100*'Group Inputs'!ED6/'Group Inputs'!EC6),2) | I74: =ROUND(IF('Group Inputs'!EC7=0,0,100*'Group Inputs'!ED7/'Group Inputs'!EC7),2) | J74: =ROUND(IF('Group Inputs'!EC8=0,0,100*'Group Inputs'!ED8/'Group Inputs'!EC8),2) | K74: =ROUND(IF('Group Inputs'!EC9=0,0,100*'Group Inputs'!ED9/'Group Inputs'!EC9),2) | L74: 96% (O-05) | M74: O-05 | N74: contracts_total, contracts_compliant
A75: CON-003 | B75: Supplier EHS non-compliance | C75: count | D75: Month end | E75: Suppliers not meeting EHS requirements | F75: =ROUND('Group Inputs'!EF4,2) | G75: =ROUND('Group Inputs'!EF5,2) | H75: =ROUND('Group Inputs'!EF6,2) | I75: =ROUND('Group Inputs'!EF7,2) | J75: =ROUND('Group Inputs'!EF8,2) | K75: =ROUND('Group Inputs'!EF9,2) | L75: 1 (O-05) | M75: O-05 | N75: supplier_ehs_noncompliance
A76: REG-005 | B76: Overdue regulatory obligations | C76: count | D76: Month end | E76: Regulatory obligations overdue | F76: =ROUND('Group Inputs'!BM4,2) | G76: =ROUND('Group Inputs'!BM5,2) | H76: =ROUND('Group Inputs'!BM6,2) | I76: =ROUND('Group Inputs'!BM7,2) | J76: =ROUND('Group Inputs'!BM8,2) | K76: =ROUND('Group Inputs'!BM9,2) | L76: 0 (O-05) | M76: O-05 | N76: reg_obligations_overdue
A77: REG-009 | B77: Disclosure-clock status | C77: text | D77: Month end | E77: Triggered if any event that needs disclosure is open, otherwise Not triggered | F77: =IF('Group Inputs'!BQ4>0,"Triggered","Not triggered") | G77: =IF('Group Inputs'!BQ5>0,"Triggered","Not triggered") | H77: =IF('Group Inputs'!BQ6>0,"Triggered","Not triggered") | I77: =IF('Group Inputs'!BQ7>0,"Triggered","Not triggered") | J77: =IF('Group Inputs'!BQ8>0,"Triggered","Not triggered") | K77: =IF('Group Inputs'!BQ9>0,"Triggered","Not triggered") | L77: Not triggered (O-05) | M77: O-05 | N77: disclosure_events_open
A78: REG-010 | B78: Regulatory breaches YTD | C78: count | D78: Year to date | E78: Sum of regulatory breaches since April | F78: =ROUND(SUM('Group Inputs'!BP$4:BP4),2) | G78: =ROUND(SUM('Group Inputs'!BP$4:BP5),2) | H78: =ROUND(SUM('Group Inputs'!BP$4:BP6),2) | I78: =ROUND(SUM('Group Inputs'!BP$4:BP7),2) | J78: =ROUND(SUM('Group Inputs'!BP$4:BP8),2) | K78: =ROUND(SUM('Group Inputs'!BP$4:BP9),2) | L78: 0 (O-05) | M78: O-05 | N78: reg_breaches
A79: RSK-003 | B79: Regulatory breaches YTD (same measure as REG-010) | C79: count | D79: Year to date | E79: Sum of regulatory breaches since April | F79: =ROUND(SUM('Group Inputs'!BP$4:BP4),2) | G79: =ROUND(SUM('Group Inputs'!BP$4:BP5),2) | H79: =ROUND(SUM('Group Inputs'!BP$4:BP6),2) | I79: =ROUND(SUM('Group Inputs'!BP$4:BP7),2) | J79: =ROUND(SUM('Group Inputs'!BP$4:BP8),2) | K79: =ROUND(SUM('Group Inputs'!BP$4:BP9),2) | L79: 0 (O-01, STATE GALLERY) | M79: O-01, STATE GALLERY · O-01 + S-02, O-01 · large display ≥ 1600 | N79: reg_breaches
A80: CMP-005 | B80: Regulatory breaches YTD (same measure as REG-010) | C80: count | D80: Year to date | E80: Sum of regulatory breaches since April | F80: =ROUND(SUM('Group Inputs'!BP$4:BP4),2) | G80: =ROUND(SUM('Group Inputs'!BP$4:BP5),2) | H80: =ROUND(SUM('Group Inputs'!BP$4:BP6),2) | I80: =ROUND(SUM('Group Inputs'!BP$4:BP7),2) | J80: =ROUND(SUM('Group Inputs'!BP$4:BP8),2) | K80: =ROUND(SUM('Group Inputs'!BP$4:BP9),2) | L80: 0 (O-01) | M80: O-01 | N80: reg_breaches
A81: EHS-008 | B81: EHS escalation clocks running | C81: count | D81: Month end | E81: EHS escalation clocks running | F81: =ROUND('Group Inputs'!BR4,2) | G81: =ROUND('Group Inputs'!BR5,2) | H81: =ROUND('Group Inputs'!BR6,2) | I81: =ROUND('Group Inputs'!BR7,2) | J81: =ROUND('Group Inputs'!BR8,2) | K81: =ROUND('Group Inputs'!BR9,2) | L81: 0 running (O-05) | M81: O-05 | N81: ehs_escalation_clocks
A82: CTL-002 | B82: Control failures YTD | C82: count | D82: Year to date | E82: Sum of control failures since April | F82: =ROUND(SUM('Group Inputs'!EH$4:EH4),2) | G82: =ROUND(SUM('Group Inputs'!EH$4:EH5),2) | H82: =ROUND(SUM('Group Inputs'!EH$4:EH6),2) | I82: =ROUND(SUM('Group Inputs'!EH$4:EH7),2) | J82: =ROUND(SUM('Group Inputs'!EH$4:EH8),2) | K82: =ROUND(SUM('Group Inputs'!EH$4:EH9),2) | L82: 4 (O-05) | M82: O-05 | N82: control_failures
A83: CTL-004 | B83: High-severity control failures YTD | C83: count | D83: Year to date | E83: Sum of high-severity control failures since April | F83: =ROUND(SUM('Group Inputs'!EI$4:EI4),2) | G83: =ROUND(SUM('Group Inputs'!EI$4:EI5),2) | H83: =ROUND(SUM('Group Inputs'!EI$4:EI6),2) | I83: =ROUND(SUM('Group Inputs'!EI$4:EI7),2) | J83: =ROUND(SUM('Group Inputs'!EI$4:EI8),2) | K83: =ROUND(SUM('Group Inputs'!EI$4:EI9),2) | L83: 0 (O-05) | M83: O-05 | N83: control_failures_high
A84: CTL-005 | B84: Policy exceptions YTD | C84: count | D84: Year to date | E84: Sum of policy exceptions since April | F84: =ROUND(SUM('Group Inputs'!EL$4:EL4),2) | G84: =ROUND(SUM('Group Inputs'!EL$4:EL5),2) | H84: =ROUND(SUM('Group Inputs'!EL$4:EL6),2) | I84: =ROUND(SUM('Group Inputs'!EL$4:EL7),2) | J84: =ROUND(SUM('Group Inputs'!EL$4:EL8),2) | K84: =ROUND(SUM('Group Inputs'!EL$4:EL9),2) | L84: 3 (O-05) | M84: O-05 | N84: policy_exceptions
A85: CTL-006 | B85: Unauthorised-vendor usage YTD | C85: count | D85: Year to date | E85: Sum of unauthorised vendor uses since April | F85: =ROUND(SUM('Group Inputs'!EM$4:EM4),2) | G85: =ROUND(SUM('Group Inputs'!EM$4:EM5),2) | H85: =ROUND(SUM('Group Inputs'!EM$4:EM6),2) | I85: =ROUND(SUM('Group Inputs'!EM$4:EM7),2) | J85: =ROUND(SUM('Group Inputs'!EM$4:EM8),2) | K85: =ROUND(SUM('Group Inputs'!EM$4:EM9),2) | L85: 0 (O-05) | M85: O-05 | N85: unauthorized_vendor_uses
A86: CTL-007 | B86: Segregation-of-duties exceptions YTD | C86: count | D86: Year to date | E86: Sum of segregation-of-duties exceptions since April | F86: =ROUND(SUM('Group Inputs'!EN$4:EN4),2) | G86: =ROUND(SUM('Group Inputs'!EN$4:EN5),2) | H86: =ROUND(SUM('Group Inputs'!EN$4:EN6),2) | I86: =ROUND(SUM('Group Inputs'!EN$4:EN7),2) | J86: =ROUND(SUM('Group Inputs'!EN$4:EN8),2) | K86: =ROUND(SUM('Group Inputs'!EN$4:EN9),2) | L86: 1 (O-05) | M86: O-05 | N86: sod_exceptions
A87: CTL-008 | B87: Unauthorised-access events YTD | C87: count | D87: Year to date | E87: Sum of unauthorised access events since April | F87: =ROUND(SUM('Group Inputs'!EO$4:EO4),2) | G87: =ROUND(SUM('Group Inputs'!EO$4:EO5),2) | H87: =ROUND(SUM('Group Inputs'!EO$4:EO6),2) | I87: =ROUND(SUM('Group Inputs'!EO$4:EO7),2) | J87: =ROUND(SUM('Group Inputs'!EO$4:EO8),2) | K87: =ROUND(SUM('Group Inputs'!EO$4:EO9),2) | L87: 0 (O-05) | M87: O-05 | N87: unauthorized_access_events
A88: CTL-009 | B88: Data-sharing exceptions YTD | C88: count | D88: Year to date | E88: Sum of data-sharing exceptions since April | F88: =ROUND(SUM('Group Inputs'!EP$4:EP4),2) | G88: =ROUND(SUM('Group Inputs'!EP$4:EP5),2) | H88: =ROUND(SUM('Group Inputs'!EP$4:EP6),2) | I88: =ROUND(SUM('Group Inputs'!EP$4:EP7),2) | J88: =ROUND(SUM('Group Inputs'!EP$4:EP8),2) | K88: =ROUND(SUM('Group Inputs'!EP$4:EP9),2) | L88: 0 (O-05) | M88: O-05 | N88: data_sharing_exceptions
A89: CTL-010 | B89: Manual overrides YTD | C89: count | D89: Year to date | E89: Sum of manual operational or system overrides since April | F89: =ROUND(SUM('Group Inputs'!EQ$4:EQ4),2) | G89: =ROUND(SUM('Group Inputs'!EQ$4:EQ5),2) | H89: =ROUND(SUM('Group Inputs'!EQ$4:EQ6),2) | I89: =ROUND(SUM('Group Inputs'!EQ$4:EQ7),2) | J89: =ROUND(SUM('Group Inputs'!EQ$4:EQ8),2) | K89: =ROUND(SUM('Group Inputs'!EQ$4:EQ9),2) | L89: 12 (O-05) | M89: O-05 | N89: manual_overrides
A90: GOV-001 | B90: Ageing certification approvals | C90: count | D90: Month end | E90: Certification approvals past due date | F90: =ROUND('Group Inputs'!ER4,2) | G90: =ROUND('Group Inputs'!ER5,2) | H90: =ROUND('Group Inputs'!ER6,2) | I90: =ROUND('Group Inputs'!ER7,2) | J90: =ROUND('Group Inputs'!ER8,2) | K90: =ROUND('Group Inputs'!ER9,2) | L90: 2 > [PH] d (G-08) | M90: G-08 · Owner depth | N90: cert_approvals_ageing
A91: GOV-002 | B91: KPI overrides | C91: count | D91: Month end | E91: KPI values overridden | F91: =ROUND('Group Inputs'!ES4,2) | G91: =ROUND('Group Inputs'!ES5,2) | H91: =ROUND('Group Inputs'!ES6,2) | I91: =ROUND('Group Inputs'!ES7,2) | J91: =ROUND('Group Inputs'!ES8,2) | K91: =ROUND('Group Inputs'!ES9,2) | L91: 0 (G-08) | M91: G-08 · Owner depth | N91: kpi_overrides
A92: GOV-003 | B92: Recurring data-quality issues | C92: count | D92: Month end | E92: Recurring data-quality issues | F92: =ROUND('Group Inputs'!ET4,2) | G92: =ROUND('Group Inputs'!ET5,2) | H92: =ROUND('Group Inputs'!ET6,2) | I92: =ROUND('Group Inputs'!ET7,2) | J92: =ROUND('Group Inputs'!ET8,2) | K92: =ROUND('Group Inputs'!ET9,2) | L92: 1 (G-08) | M92: G-08 · Owner depth | N92: dq_issues_recurring
A93: GOV-004 | B93: Open audit findings | C93: count | D93: Month end | E93: Open audit findings | F93: =ROUND('Group Inputs'!EU4,2) | G93: =ROUND('Group Inputs'!EU5,2) | H93: =ROUND('Group Inputs'!EU6,2) | I93: =ROUND('Group Inputs'!EU7,2) | J93: =ROUND('Group Inputs'!EU8,2) | K93: =ROUND('Group Inputs'!EU9,2) | L93: 7 (G-08, O-05) | M93: G-08 · Owner depth, O-05 | N93: audit_findings_open
A94: GOV-005 | B94: Overdue assurance actions | C94: count | D94: Month end | E94: Overdue assurance actions | F94: =ROUND('Group Inputs'!EV4,2) | G94: =ROUND('Group Inputs'!EV5,2) | H94: =ROUND('Group Inputs'!EV6,2) | I94: =ROUND('Group Inputs'!EV7,2) | J94: =ROUND('Group Inputs'!EV8,2) | K94: =ROUND('Group Inputs'!EV9,2) | L94: 0 (G-08) | M94: G-08 · Owner depth | N94: assurance_actions_overdue
A95: GOV-006 | B95: Repeat findings | C95: count | D95: Month end | E95: Repeat audit findings | F95: =ROUND('Group Inputs'!EW4,2) | G95: =ROUND('Group Inputs'!EW5,2) | H95: =ROUND('Group Inputs'!EW6,2) | I95: =ROUND('Group Inputs'!EW7,2) | J95: =ROUND('Group Inputs'!EW8,2) | K95: =ROUND('Group Inputs'!EW9,2) | L95: 1 (G-08) | M95: G-08 · Owner depth | N95: repeat_findings
A96: GOV-007 | B96: Leadership KPIs affected by findings | C96: count | D96: Month end | E96: Leadership KPIs affected by open findings | F96: =ROUND('Group Inputs'!EX4,2) | G96: =ROUND('Group Inputs'!EX5,2) | H96: =ROUND('Group Inputs'!EX6,2) | I96: =ROUND('Group Inputs'!EX7,2) | J96: =ROUND('Group Inputs'!EX8,2) | K96: =ROUND('Group Inputs'!EX9,2) | L96: 1 (G-08) | M96: G-08 · Owner depth | N96: leadership_kpis_affected
A97: TRU-007 | B97: Material reconciliation breaks | C97: count | D97: Month end | E97: Material reconciliation breaks | F97: =ROUND('Group Inputs'!FH4,2) | G97: =ROUND('Group Inputs'!FH5,2) | H97: =ROUND('Group Inputs'!FH6,2) | I97: =ROUND('Group Inputs'!FH7,2) | J97: =ROUND('Group Inputs'!FH8,2) | K97: =ROUND('Group Inputs'!FH9,2) | L97: 1 (G-08) | M97: G-08 · Owner depth | N97: recon_breaks_material
A98: GOV-008 | B98: Evidence completeness rate | C98: % | D98: Month end | E98: Evidence items complete ÷ Evidence items required × 100 | F98: =ROUND(IF('Group Inputs'!EY4=0,0,100*'Group Inputs'!EZ4/'Group Inputs'!EY4),2) | G98: =ROUND(IF('Group Inputs'!EY5=0,0,100*'Group Inputs'!EZ5/'Group Inputs'!EY5),2) | H98: =ROUND(IF('Group Inputs'!EY6=0,0,100*'Group Inputs'!EZ6/'Group Inputs'!EY6),2) | I98: =ROUND(IF('Group Inputs'!EY7=0,0,100*'Group Inputs'!EZ7/'Group Inputs'!EY7),2) | J98: =ROUND(IF('Group Inputs'!EY8=0,0,100*'Group Inputs'!EZ8/'Group Inputs'!EY8),2) | K98: =ROUND(IF('Group Inputs'!EY9=0,0,100*'Group Inputs'!EZ9/'Group Inputs'!EY9),2) | L98: 88% (G-08) | M98: G-08 · Owner depth | N98: evidence_required, evidence_complete
A99: GOV-009 | B99: Average finding-closure time | C99: days | D99: Year to date | E99: Days taken to close findings since April ÷ Findings closed since April | F99: =ROUND(IF(SUM('Group Inputs'!FA$4:FA4)=0,0,SUM('Group Inputs'!FB$4:FB4)/SUM('Group Inputs'!FA$4:FA4)),2) | G99: =ROUND(IF(SUM('Group Inputs'!FA$4:FA5)=0,0,SUM('Group Inputs'!FB$4:FB5)/SUM('Group Inputs'!FA$4:FA5)),2) | H99: =ROUND(IF(SUM('Group Inputs'!FA$4:FA6)=0,0,SUM('Group Inputs'!FB$4:FB6)/SUM('Group Inputs'!FA$4:FA6)),2) | I99: =ROUND(IF(SUM('Group Inputs'!FA$4:FA7)=0,0,SUM('Group Inputs'!FB$4:FB7)/SUM('Group Inputs'!FA$4:FA7)),2) | J99: =ROUND(IF(SUM('Group Inputs'!FA$4:FA8)=0,0,SUM('Group Inputs'!FB$4:FB8)/SUM('Group Inputs'!FA$4:FA8)),2) | K99: =ROUND(IF(SUM('Group Inputs'!FA$4:FA9)=0,0,SUM('Group Inputs'!FB$4:FB9)/SUM('Group Inputs'!FA$4:FA9)),2) | L99: 34 d (G-08) | M99: G-08 · Owner depth | N99: findings_closed, finding_closure_days
A100: TRU-001 | B100: Certified KPI percentage | C100: % | D100: Month end | E100: Leadership KPI values certified ÷ Leadership KPI values reported × 100 | F100: =ROUND(IF('Group Inputs'!FC4=0,0,100*'Group Inputs'!FD4/'Group Inputs'!FC4),2) | G100: =ROUND(IF('Group Inputs'!FC5=0,0,100*'Group Inputs'!FD5/'Group Inputs'!FC5),2) | H100: =ROUND(IF('Group Inputs'!FC6=0,0,100*'Group Inputs'!FD6/'Group Inputs'!FC6),2) | I100: =ROUND(IF('Group Inputs'!FC7=0,0,100*'Group Inputs'!FD7/'Group Inputs'!FC7),2) | J100: =ROUND(IF('Group Inputs'!FC8=0,0,100*'Group Inputs'!FD8/'Group Inputs'!FC8),2) | K100: =ROUND(IF('Group Inputs'!FC9=0,0,100*'Group Inputs'!FD9/'Group Inputs'!FC9),2) | L100: 84 % of leadership KPIs (G-08) | M100: G-08 · Owner depth | N100: kpis_leadership, kpis_certified
...

Sheet Owner Screens
A1: No. | B1: Screen | C1: Screen title | D1: Element | E1: Label on the screen | F1: KPI ID | G1: Scope | H1: Shown on the screen | I1: Model value, P06 (Sep 2026) | J1: Where the model value comes from
A2: 1 | B2: O-01 | C2: Enterprise Health | D2: Card | E2: Production vs plan · Group MTD | F2: OPS-001 | G2: Group | H2: 98.1 % of plan | I2: ='Owner KPIs'!K2 | J2: Owner KPIs sheet, row 2 (Group, Sep 2026)
A3: 2 | B3: O-01 | C3: Enterprise Health | D3: Card | E3: EBITDA YTD (to P06) | F3: FIN-001 | G3: Group | H3: 361.3 ₹ m | I3: ='Owner KPIs'!K29 | J3: Owner KPIs sheet, row 29 (Group, Sep 2026)
A4: 3 | B4: O-01 | C4: Enterprise Health | D4: Card | E4: EBIT YTD (to P06) | F4: FIN-002 | G4: Group | H4: 238.4 ₹ m | I4: ='Owner KPIs'!K30 | J4: Owner KPIs sheet, row 30 (Group, Sep 2026)
A5: 4 | B5: O-01 | C5: Enterprise Health | D5: Card | E5: Free Cash Flow YTD | F5: FIN-004 | G5: Group | H5: 96.4 ₹ m | I5: ='Owner KPIs'!K32 | J5: Owner KPIs sheet, row 32 (Group, Sep 2026)
A6: 5 | B6: O-01 | C6: Enterprise Health | D6: Card | E6: ROCE · rolling 12 m | F6: FIN-005 | G6: Group | H6: 11.8 % | I6: ='Owner KPIs'!K33 | J6: Owner KPIs sheet, row 33 (Group, Sep 2026)
A7: 6 | B7: O-01 | C7: Enterprise Health | D7: Card | E7: Net Debt | F7: FIN-006 | G7: Group | H7: 1,140 ₹ m | I7: ='Owner KPIs'!K34 | J7: Owner KPIs sheet, row 34 (Group, Sep 2026)
A8: 7 | B8: O-01 | C8: Enterprise Health | D8: Card | E8: Capex physical progress | F8: CPX-004 | G8: Group | H8: 61 % weighted | I8: ='Owner KPIs'!K59 | J8: Owner KPIs sheet, row 59 (Group, Sep 2026)
A9: 8 | B9: O-01 | C9: Enterprise Health | D9: Card | E9: Open critical alerts | F9: EFF-002 | G9: Group | H9: 1 alert | I9: ='Owner KPIs'!K106 | J9: Owner KPIs sheet, row 106 (Group, Sep 2026)
A10: 9 | B10: O-01 | C10: Enterprise Health | D10: Tile | E10: Days to breach · Plant 02 plan | F10: PRD-001 | G10: Plant 02 | H10: 4 days | I10: =ROUND('Plant Inputs'!BT15,2) | J10: Same formula on Plant Inputs row 15 (Plant 02, Sep 2026)
A11: 10 | B11: O-01 | C11: Enterprise Health | D11: Tile | E11: Probability of plan miss · P07 | F11: PRD-002 | G11: Group | H11: 64% | I11: ='Owner KPIs'!K114 | J11: Owner KPIs sheet, row 114 (Group, Sep 2026)
A12: 11 | B12: O-01 | C12: Enterprise Health | D12: Tile | E12: Projected EBITDA gap · P07–P12 | F12: PRD-003 | G12: Group | H12: −₹9.2 m | I12: ='Owner KPIs'!K115 | J12: Owner KPIs sheet, row 115 (Group, Sep 2026)
A13: 12 | B13: O-01 | C13: Enterprise Health | D13: Table | E13: Capacity utilization | F13: OPS-003 | G13: Group | H13: 86% | I13: ='Owner KPIs'!K3 | J13: Owner KPIs sheet, row 3 (Group, Sep 2026)
A14: 13 | B14: O-01 | C14: Enterprise Health | D14: Table | E14: Capacity utilisation | F14: OPS-005 | G14: Group | H14: 86% | I14: ='Owner KPIs'!K24 | J14: Owner KPIs sheet, row 24 (Group, Sep 2026)
A15: 14 | B15: O-01 | C15: Enterprise Health | D15: Table | E15: Sales vs plan · MTD | F15: OPS-002 | G15: Group | H15: 97.6% | I15: ='Owner KPIs'!K26 | J15: Owner KPIs sheet, row 26 (Group, Sep 2026)
A16: 15 | B16: O-01 | C16: Enterprise Health | D16: Table | E16: Sales vs plan · Group MTD | F16: OPS-004 | G16: Group | H16: 97.6% | I16: ='Owner KPIs'!K27 | J16: Owner KPIs sheet, row 27 (Group, Sep 2026)
A17: 16 | B17: O-01 | C17: Enterprise Health | D17: Table | E17: EBIT YTD | F17: FIN-002 | G17: Group | H17: 238.4 ₹ m | I17: ='Owner KPIs'!K30 | J17: Owner KPIs sheet, row 30 (Group, Sep 2026)
A18: 17 | B18: O-01 | C18: Enterprise Health | D18: Table | E18: Revenue YTD | F18: FIN-003 | G18: Group | H18: 2,410 ₹ m | I18: ='Owner KPIs'!K31 | J18: Owner KPIs sheet, row 31 (Group, Sep 2026)
A19: 18 | B19: O-01 | C19: Enterprise Health | D19: Table | E19: ROCE (rolling 12 m) | F19: FIN-005 | G19: Group | H19: 11.8% | I19: ='Owner KPIs'!K33 | J19: Owner KPIs sheet, row 33 (Group, Sep 2026)
A20: 19 | B20: O-01 | C20: Enterprise Health | D20: Table | E20: Shareholder-value indicator | F20: FIN-007 | G20: Group | H20: [PLACEHOLDER] | I20: ='Owner KPIs'!K35 | J20: Owner KPIs sheet, row 35 (Group, Sep 2026)
A21: 20 | B21: O-01 | C21: Enterprise Health | D21: Table | E21: Transformation progress (weighted) | F21: PRG-004 | G21: Group | H21: 54% | I21: ='Owner KPIs'!K64 | J21: Owner KPIs sheet, row 64 (Group, Sep 2026)
A22: 21 | B22: O-01 | C22: Enterprise Health | D22: Table | E22: Transformation progress | F22: STR-002 | G22: Group | H22: 54% | I22: ='Owner KPIs'!K65 | J22: Owner KPIs sheet, row 65 (Group, Sep 2026)
A23: 22 | B23: O-01 | C23: Enterprise Health | D23: Table | E23: Regulatory breaches · YTD | F23: RSK-003 | G23: Group | H23: 0 | I23: ='Owner KPIs'!K79 | J23: Owner KPIs sheet, row 79 (Group, Sep 2026)
A24: 23 | B24: O-01 | C24: Enterprise Health | D24: Table | E24: Regulatory breaches · YTD | F24: CMP-005 | G24: Group | H24: 0 | I24: ='Owner KPIs'!K80 | J24: Owner KPIs sheet, row 80 (Group, Sep 2026)
A25: 24 | B25: O-02 | C25: 24-Hour Executive Change Report | D25: Tile | E25: Days to breach · Plant 02 plan | F25: PRD-001 | G25: Plant 02 | H25: 4 days | I25: =ROUND('Plant Inputs'!BT15,2) | J25: Same formula on Plant Inputs row 15 (Plant 02, Sep 2026)
A26: 25 | B26: O-02 | C26: 24-Hour Executive Change Report | D26: Tile | E26: Probability of plan miss · P07 | F26: PRD-002 | G26: Group | H26: 64% | I26: ='Owner KPIs'!K114 | J26: Owner KPIs sheet, row 114 (Group, Sep 2026)
A27: 26 | B27: O-02 | C27: 24-Hour Executive Change Report | D27: Tile | E27: Projected EBITDA gap P07–P12 | F27: PRD-003 | G27: Group | H27: −₹9.2 m | I27: ='Owner KPIs'!K115 | J27: Owner KPIs sheet, row 115 (Group, Sep 2026)
A28: 27 | B28: O-02 | C28: 24-Hour Executive Change Report | D28: Tile | E28: Projected liquidity gap | F28: PRD-004 | G28: Group | H28: None | I28: ='Owner KPIs'!K116 | J28: Owner KPIs sheet, row 116 (Group, Sep 2026)
A29: 28 | B29: O-02 | C29: 24-Hour Executive Change Report | D29: Tile | E29: Forecast covenant breach | F29: PRD-005 | G29: Group | H29: Not forecast | I29: ='Owner KPIs'!K117 | J29: Owner KPIs sheet, row 117 (Group, Sep 2026)
A30: 29 | B30: O-03 | C30: Cash & Liquidity Dashboard | D30: Card | E30: Cash position | F30: CSH-001 | G30: Group | H30: 2,141.8 ₹ m | I30: 2141.82 | J30: Owner KPIs sheet, row 36 (Group, Sep 2026)
A31: 30 | B31: O-03 | C31: Cash & Liquidity Dashboard | D31: Card | E31: Liquidity runway | F31: LIQ-001 | G31: Group | H31: 16.7 months | I31: 16.71 | J31: Owner KPIs sheet, row 47 (Group, Sep 2026)
A32: 31 | B32: O-03 | C32: Cash & Liquidity Dashboard | D32: Card | E32: Net debt | F32: FIN-006 | G32: Group | H32: 6,650.0 ₹ m | I32: 6650 | J32: Owner KPIs sheet, row 34 (Group, Sep 2026)
A33: 32 | B33: O-03 | C33: Cash & Liquidity Dashboard | D33: Card | E33: Debt maturity (next 12 months) | F33: LIQ-003 | G33: Group | H33: 891.4 ₹ m | I33: 891.41 | J33: Owner KPIs sheet, row 49 (Group, Sep 2026)
A34: 33 | B34: O-03 | C34: Cash & Liquidity Dashboard | D34: Card | E34: DSO above target | F34: WCP-001 | G34: Group | H34: 47.0 days | I34: 46.97 | J34: Owner KPIs sheet, row 41 (Group, Sep 2026)
A35: 34 | B35: O-03 | C35: Cash & Liquidity Dashboard | D35: Card | E35: Working capital | F35: WCP-004 | G35: Group | H35: 2,781.0 ₹ m | I35: 2780.99 | J35: Owner KPIs sheet, row 44 (Group, Sep 2026)
A36: 35 | B36: O-03 | C36: Cash & Liquidity Dashboard | D36: Card | E36: FX hedge ratio (next 6 months) | F36: TRS-004 | G36: Group | H36: 70.7 % | I36: 70.65 | J36: Owner KPIs sheet, row 54 (Group, Sep 2026)
A37: 36 | B37: O-03 | C37: Cash & Liquidity Dashboard | D37: Card detail | E37: FX hedge ratio (next 6 months) · Hedged (Sep) | G37: Group | H37: ₹546.0 m | I37: 546 | J37: Group Inputs, fx_hedged_k ÷ 1000 (Sep 2026)
A38: 37 | B38: O-03 | C38: Cash & Liquidity Dashboard | D38: Card detail | E38: FX hedge ratio (next 6 months) · Gross FX exposure (Sep) | G38: Group | H38: ₹767.7 m | I38: 767.72 | J38: Group Inputs, fx_exposure_k ÷ 1000 (Sep 2026)
A39: 38 | B39: O-03 | C39: Cash & Liquidity Dashboard | D39: Card | E39: Financing exposure | F39: LIQ-004 | G39: Group | H39: 2,720.8 ₹ m | I39: 2720.83 | J39: Owner KPIs sheet, row 50 (Group, Sep 2026)
A40: 39 | B40: O-03 | C40: Cash & Liquidity Dashboard | D40: Card | E40: Upstream exposure | F40: CSH-006 | G40: Group | H40: 27.2 ₹ m | I40: 27.21 | J40: Owner KPIs sheet, row 40 (Group, Sep 2026)
A41: 40 | B41: O-03 | C41: Cash & Liquidity Dashboard | D41: Chart | E41: DSO trend | F41: WCP-001 | G41: Group | H41: Apr–Sep monthly series | I41: Apr–Sep: 47.16, 48.66, 48.42, 48.03, 47.51, 46.97 | J41: Owner KPIs sheet, row 41 (Group, Apr–Sep 2026)
A42: 41 | B42: O-03 | C42: Cash & Liquidity Dashboard | D42: Chart | E42: Net debt evolution | F42: FIN-006 | G42: Group | H42: Apr–Sep monthly series | I42: Apr–Sep: 7000.0, 6930.0, 6860.0, 6790.0, 6720.0, 6650.0 | J42: Owner KPIs sheet, row 34 (Group, Apr–Sep 2026)
A43: 42 | B43: O-03 | C43: Cash & Liquidity Dashboard | D43: Chart | E43: FX exposure vs hedge | G43: Group | H43: Apr–Sep monthly series | I43: Exposure 724.2, 715.3, 706.4, 793.7, 722.6, 767.7 · hedged 533.4, 507.8, 518.2, 566.0, 497.1, 546.0 | J43: Group Inputs, fx_exposure_k and fx_hedged_k ÷ 1000 (Apr–Sep 2026)
A44: 43 | B44: O-04 | C44: Major Capex and Strategic Initiatives | D44: Card | E44: Approved budget | F44: CPX-001 | G44: Group | H44: 850 ₹ m | I44: ='Owner KPIs'!K56 | J44: Owner KPIs sheet, row 56 (Group, Sep 2026)
A45: 44 | B45: O-04 | C45: Major Capex and Strategic Initiatives | D45: Card | E45: Committed Capex | F45: CPX-002 | G45: Group | H45: 610 ₹ m · 72% | I45: ='Owner KPIs'!K57 | J45: Owner KPIs sheet, row 57 (Group, Sep 2026)
A46: 45 | B46: O-04 | C46: Major Capex and Strategic Initiatives | D46: Card | E46: Actual spend | F46: CPX-003 | G46: Group | H46: 402 ₹ m · 47% | I46: ='Owner KPIs'!K58 | J46: Owner KPIs sheet, row 58 (Group, Sep 2026)
A47: 46 | B47: O-04 | C47: Major Capex and Strategic Initiatives | D47: Card | E47: Capex physical progress | F47: CPX-004 | G47: Group | H47: 61 % weighted | I47: ='Owner KPIs'!K59 | J47: Owner KPIs sheet, row 59 (Group, Sep 2026)
A48: 47 | B48: O-04 | C48: Major Capex and Strategic Initiatives | D48: Card | E48: Capex value at risk | F48: SIG-011 | G48: Group | H48: 34 ₹ m | I48: ='Owner KPIs'!K60 | J48: Owner KPIs sheet, row 60 (Group, Sep 2026)
A49: 48 | B49: O-04 | C49: Major Capex and Strategic Initiatives | D49: Card | E49: Benefits realization | F49: PRG-002 | G49: Group | H49: 48 % of plan | I49: ='Owner KPIs'!K62 | J49: Owner KPIs sheet, row 62 (Group, Sep 2026)
A50: 49 | B50: O-04 | C50: Major Capex and Strategic Initiatives | D50: Card | E50: EBITDA benefit delivered YTD | F50: VAL-001 | G50: Group | H50: ₹14 m | I50: ='Owner KPIs'!K67 | J50: Owner KPIs sheet, row 67 (Group, Sep 2026)
A51: 50 | B51: O-04 | C51: Major Capex and Strategic Initiatives | D51: Card | E51: Cash benefit delivered YTD | F51: VAL-002 | G51: Group | H51: ₹9 m | I51: ='Owner KPIs'!K68 | J51: Owner KPIs sheet, row 68 (Group, Sep 2026)
A52: 51 | B52: O-04 | C52: Major Capex and Strategic Initiatives | D52: Card | E52: Cost savings delivered YTD | F52: VAL-003 | G52: Group | H52: ₹11 m | I52: ='Owner KPIs'!K69 | J52: Owner KPIs sheet, row 69 (Group, Sep 2026)
A53: 52 | B53: O-04 | C53: Major Capex and Strategic Initiatives | D53: Tile | E53: Capex value at risk | F53: SIG-011 | G53: Group | H53: ₹34 m | I53: ='Owner KPIs'!K60 | J53: Owner KPIs sheet, row 60 (Group, Sep 2026)
A54: 53 | B54: O-04 | C54: Major Capex and Strategic Initiatives | D54: Tile | E54: Delayed projects | F54: PRG-003 | G54: Group | H54: 1 | I54: ='Owner KPIs'!K63 | J54: Owner KPIs sheet, row 63 (Group, Sep 2026)
A55: 54 | B55: O-04 | C55: Major Capex and Strategic Initiatives | D55: Table | E55: Initiative status | F55: PRG-001 | G55: Group | H55: 9 on track · 2 at risk · 0 off track | I55: ='Owner KPIs'!K61 | J55: Owner KPIs sheet, row 61 (Group, Sep 2026)
A56: 55 | B56: O-04 | C56: Major Capex and Strategic Initiatives | D56: Table | E56: Delayed projects | F56: PRG-003 | G56: Group | H56: 1 | I56: ='Owner KPIs'!K63 | J56: Owner KPIs sheet, row 63 (Group, Sep 2026)
A57: 56 | B57: O-04 | C57: Major Capex and Strategic Initiatives | D57: Table | E57: Transformation progress (weighted) | F57: PRG-004 | G57: Group | H57: 54% | I57: ='Owner KPIs'!K64 | J57: Owner KPIs sheet, row 64 (Group, Sep 2026)
A58: 57 | B58: O-04 | C58: Major Capex and Strategic Initiatives | D58: Table | E58: Transformation progress | F58: STR-002 | G58: Group | H58: 54% | I58: ='Owner KPIs'!K65 | J58: Owner KPIs sheet, row 65 (Group, Sep 2026)
A59: 58 | B59: O-04 | C59: Major Capex and Strategic Initiatives | D59: Table | E59: Initiative status · 24 initiatives | F59: PRG-005 | G59: Group | H59: 15 on track · 6 at risk · 3 delayed | I59: ='Owner KPIs'!K66 | J59: Owner KPIs sheet, row 66 (Group, Sep 2026)
A60: 59 | B60: O-04 | C60: Major Capex and Strategic Initiatives | D60: Table | E60: EBITDA benefit | F60: VAL-001 | G60: Group | H60: ₹14 m | I60: ='Owner KPIs'!K67 | J60: Owner KPIs sheet, row 67 (Group, Sep 2026)
A61: 60 | B61: O-04 | C61: Major Capex and Strategic Initiatives | D61: Table | E61: Cash benefit | F61: VAL-002 | G61: Group | H61: ₹9 m | I61: ='Owner KPIs'!K68 | J61: Owner KPIs sheet, row 68 (Group, Sep 2026)
A62: 61 | B62: O-04 | C62: Major Capex and Strategic Initiatives | D62: Table | E62: Cost savings delivered | F62: VAL-003 | G62: Group | H62: ₹11 m | I62: ='Owner KPIs'!K69 | J62: Owner KPIs sheet, row 69 (Group, Sep 2026)
A63: 62 | B63: O-05 | C63: Material Risk, Compliance and EHS | D63: Card | E63: TRIR · rolling 12 m | F63: EHS-001 | G63: Group | H63: 0.42 | I63: ='Owner KPIs'!K17 | J63: Owner KPIs sheet, row 17 (Group, Sep 2026)
A64: 63 | B64: O-05 | C64: Material Risk, Compliance and EHS | D64: Card | E64: Critical safety incidents · YTD | F64: EHS-004 | G64: Group | H64: 0 | I64: ='Owner KPIs'!K20 | J64: Owner KPIs sheet, row 20 (Group, Sep 2026)
A65: 64 | B65: O-05 | C65: Material Risk, Compliance and EHS | D65: Card | E65: Nearest licence or permit expiry | F65: REG-006 | G65: Group | H65: 74 days · Entity C1 | I65: ='Owner KPIs'!K23 | J65: Owner KPIs sheet, row 23 (Group, Sep 2026)
A66: 65 | B66: O-05 | C66: Material Risk, Compliance and EHS | D66: Card | E66: Overdue regulatory obligations | F66: REG-005 | G66: Group | H66: 0 | I66: ='Owner KPIs'!K76 | J66: Owner KPIs sheet, row 76 (Group, Sep 2026)
A67: 66 | B67: O-05 | C67: Material Risk, Compliance and EHS | D67: Card | E67: Disclosure-clock status | F67: REG-009 | G67: Group | H67: Not triggered | I67: ='Owner KPIs'!K77 | J67: Owner KPIs sheet, row 77 (Group, Sep 2026)
A68: 67 | B68: O-05 | C68: Material Risk, Compliance and EHS | D68: Card | E68: High-severity control failures | F68: CTL-004 | G68: Group | H68: 0 | I68: ='Owner KPIs'!K83 | J68: Owner KPIs sheet, row 83 (Group, Sep 2026)
A69: 68 | B69: O-05 | C69: Material Risk, Compliance and EHS | D69: Table | E69: Water usage | F69: SUS-001 | G69: Group | H69: 3.1 m³/t | I69: ='Owner KPIs'!K11 | J69: Owner KPIs sheet, row 11 (Group, Sep 2026)
A70: 69 | B70: O-05 | C70: Material Risk, Compliance and EHS | D70: Table | E70: Emissions | F70: SUS-002 | G70: Group | H70: 0.82 tCO2e/t | I70: ='Owner KPIs'!K12 | J70: Owner KPIs sheet, row 12 (Group, Sep 2026)
A71: 70 | B71: O-05 | C71: Material Risk, Compliance and EHS | D71: Table | E71: Energy intensity | F71: SUS-003 | G71: Group | H71: 5.2 GJ/t | I71: ='Owner KPIs'!K13 | J71: Owner KPIs sheet, row 13 (Group, Sep 2026)
A72: 71 | B72: O-05 | C72: Material Risk, Compliance and EHS | D72: Table | E72: TRIR · rolling 12 m | F72: EHS-001 | G72: Group | H72: 0.42 | I72: ='Owner KPIs'!K17 | J72: Owner KPIs sheet, row 17 (Group, Sep 2026)
A73: 72 | B73: O-05 | C73: Material Risk, Compliance and EHS | D73: Table | E73: Severity incidents · MTD | F73: EHS-002 | G73: Group | H73: 0 | I73: ='Owner KPIs'!K18 | J73: Owner KPIs sheet, row 18 (Group, Sep 2026)
A74: 73 | B74: O-05 | C74: Material Risk, Compliance and EHS | D74: Table | E74: Near misses · MTD | F74: EHS-003 | G74: Group | H74: 14 | I74: ='Owner KPIs'!K19 | J74: Owner KPIs sheet, row 19 (Group, Sep 2026)
A75: 74 | B75: O-05 | C75: Material Risk, Compliance and EHS | D75: Table | E75: Environmental excursions · MTD | F75: EHS-005 | G75: Group | H75: 1 (minor, closed) | I75: ='Owner KPIs'!K21 | J75: Owner KPIs sheet, row 21 (Group, Sep 2026)
A76: 75 | B76: O-05 | C76: Material Risk, Compliance and EHS | D76: Table | E76: Overdue EHS actions | F76: EHS-007 | G76: Group | H76: 0 | I76: ='Owner KPIs'!K22 | J76: Owner KPIs sheet, row 22 (Group, Sep 2026)
A77: 76 | B77: O-05 | C77: Material Risk, Compliance and EHS | D77: Table | E77: Contracts expiring · 90 d | F77: CON-001 | G77: Group | H77: 4 | I77: ='Owner KPIs'!K73 | J77: Owner KPIs sheet, row 73 (Group, Sep 2026)
A78: 77 | B78: O-05 | C78: Material Risk, Compliance and EHS | D78: Table | E78: Contract-compliance rate | F78: CON-002 | G78: Group | H78: 96% | I78: ='Owner KPIs'!K74 | J78: Owner KPIs sheet, row 74 (Group, Sep 2026)
A79: 78 | B79: O-05 | C79: Material Risk, Compliance and EHS | D79: Table | E79: Supplier EHS non-compliance | F79: CON-003 | G79: Group | H79: 1 | I79: ='Owner KPIs'!K75 | J79: Owner KPIs sheet, row 75 (Group, Sep 2026)
A80: 79 | B80: O-05 | C80: Material Risk, Compliance and EHS | D80: Table | E80: Regulatory breaches · YTD | F80: REG-010 | G80: Group | H80: 0 | I80: ='Owner KPIs'!K78 | J80: Owner KPIs sheet, row 78 (Group, Sep 2026)
A81: 80 | B81: O-05 | C81: Material Risk, Compliance and EHS | D81: Table | E81: EHS escalation clocks running | F81: EHS-008 | G81: Group | H81: 0 running | I81: ='Owner KPIs'!K81 | J81: Owner KPIs sheet, row 81 (Group, Sep 2026)
A82: 81 | B82: O-05 | C82: Material Risk, Compliance and EHS | D82: Table | E82: Control failures · YTD | F82: CTL-002 | G82: Group | H82: 4 | I82: ='Owner KPIs'!K82 | J82: Owner KPIs sheet, row 82 (Group, Sep 2026)
A83: 82 | B83: O-05 | C83: Material Risk, Compliance and EHS | D83: Table | E83: Policy exceptions | F83: CTL-005 | G83: Group | H83: 3 | I83: ='Owner KPIs'!K84 | J83: Owner KPIs sheet, row 84 (Group, Sep 2026)
A84: 83 | B84: O-05 | C84: Material Risk, Compliance and EHS | D84: Table | E84: Unauthorized-vendor usage | F84: CTL-006 | G84: Group | H84: 0 | I84: ='Owner KPIs'!K85 | J84: Owner KPIs sheet, row 85 (Group, Sep 2026)
A85: 84 | B85: O-05 | C85: Material Risk, Compliance and EHS | D85: Table | E85: SoD exceptions | F85: CTL-007 | G85: Group | H85: 1 | I85: ='Owner KPIs'!K86 | J85: Owner KPIs sheet, row 86 (Group, Sep 2026)
A86: 85 | B86: O-05 | C86: Material Risk, Compliance and EHS | D86: Table | E86: Unauthorized-access events | F86: CTL-008 | G86: Group | H86: 0 | I86: ='Owner KPIs'!K87 | J86: Owner KPIs sheet, row 87 (Group, Sep 2026)
A87: 86 | B87: O-05 | C87: Material Risk, Compliance and EHS | D87: Table | E87: Data-sharing exceptions | F87: CTL-009 | G87: Group | H87: 0 | I87: ='Owner KPIs'!K88 | J87: Owner KPIs sheet, row 88 (Group, Sep 2026)
A88: 87 | B88: O-05 | C88: Material Risk, Compliance and EHS | D88: Table | E88: Manual overrides (operational) | F88: CTL-010 | G88: Group | H88: 12 | I88: ='Owner KPIs'!K89 | J88: Owner KPIs sheet, row 89 (Group, Sep 2026)
A89: 88 | B89: O-05 | C89: Material Risk, Compliance and EHS | D89: Table | E89: Open audit findings | F89: GOV-004 | G89: Group | H89: 7 | I89: ='Owner KPIs'!K93 | J89: Owner KPIs sheet, row 93 (Group, Sep 2026)
A90: 89 | B90: O-06 | C90: Decisions Required | D90: Tile | E90: Alert resolution time | F90: EFF-008 | G90: Group | H90: 2.4 d | I90: ='Owner KPIs'!K107 | J90: Owner KPIs sheet, row 107 (Group, Sep 2026)
A91: 90 | B91: O-06 | C91: Decisions Required | D91: Tile | E91: Closed escalations · 30 d | F91: EFF-009 | G91: Group | H91: 11 | I91: ='Owner KPIs'!K108 | J91: Owner KPIs sheet, row 108 (Group, Sep 2026)
A92: 91 | B92: O-06 | C92: Decisions Required | D92: Tile | E92: Repeat issues · 90 d | F92: EFF-010 | G92: Group | H92: 2 | I92: ='Owner KPIs'!K109 | J92: Owner KPIs sheet, row 109 (Group, Sep 2026)
A93: 92 | B93: O-06 | C93: Decisions Required | D93: Tile | E93: Root causes eliminated · YTD | F93: EFF-011 | G93: Group | H93: 7 of 9 | I93: ='Owner KPIs'!K110 | J93: Owner KPIs sheet, row 110 (Group, Sep 2026)
A94: 93 | B94: O-09 | C94: Operations Command View | D94: Card | E94: Production vs plan · Group | F94: OPS-001 | G94: Group | H94: 95.5 % of plan | J94: Owner KPIs sheet, row 2 (Group, Sep 2026)
A95: 94 | B95: O-09 | C95: Operations Command View | D95: Card | E95: MTBF · Group | F95: REL-001 | G95: Group | H95: 270 h | J95: Owner KPIs sheet, row 4 (Group, Sep 2026)
A96: 95 | B96: O-09 | C96: Operations Command View | D96: Card | E96: Cost per tonne · Group | F96: CST-001 | G96: Group | H96: 2,934 ₹/t | J96: Owner KPIs sheet, row 8 (Group, Sep 2026)
A97: 96 | B97: O-09 | C97: Operations Command View | D97: Chart | E97: Production vs plan | F97: OPS-001 | G97: Group | H97: Apr–Sep monthly series | I97: Apr–Sep: None, None, None, None, None, None | J97: Owner KPIs sheet, row 2 (Group, Apr–Sep 2026)
A98: 97 | B98: O-09 | C98: Operations Command View | D98: Chart | E98: Reliability trend · mean time to repair | F98: REL-002 | G98: Group | H98: Apr–Sep monthly series | I98: Apr–Sep: None, None, None, None, None, None | J98: Owner KPIs sheet, row 5 (Group, Apr–Sep 2026)
A99: 98 | B99: O-09 | C99: Operations Command View | D99: Chart | E99: Sustainability curve · emissions | F99: SUS-002 | G99: Group | H99: Apr–Sep monthly series | I99: Apr–Sep: None, None, None, None, None, None | J99: Owner KPIs sheet, row 12 (Group, Apr–Sep 2026)
A100: 99 | B100: G-08 · Owner depth | C100: Trust Summary (Owner depth) | D100: Card | E100: Leadership KPIs affected by findings | F100: GOV-007 | G100: Group | H100: 1 | I100: ='Owner KPIs'!K96 | J100: Owner KPIs sheet, row 96 (Group, Sep 2026)
...

Sheet Group Inputs
A1: Group | B1: Month | C1: Days in month | D1: Months since April (YTD) | E1: Calendar hours (h) | F1: Planned operating hours (h) | G1: Run hours (h) | H1: Unplanned downtime (h) | I1: Ideal output (t) | J1: Installed capacity (t) | K1: Planned production (t) | L1: Gross output (t) | M1: Good output (t) | N1: Feed input (t) | O1: Valuable content in feed (t) | P1: Valuable content recovered (t) | Q1: Production lost to downtime (t) | R1: Breakdowns (count) | S1: Repair hours (h) | T1: Preventive maintenance scheduled (count) | U1: Preventive maintenance completed (count) | V1: Variable cost (₹ thousand) | W1: Fuel cost (₹ thousand) | X1: Fixed cost (₹ thousand) | Y1: Water used (m³) | Z1: Emissions (t CO2e) | AA1: Energy used (GJ) | AB1: Production at risk (t) | AC1: Critical plant alerts (count) | AD1: Hours worked (h) | AE1: Recordable injuries (count) | AF1: Severity incidents (count) | AG1: Near misses (count) | AH1: Critical safety incidents (count) | AI1: Environmental excursions (count) | AJ1: Environmental violations (count) | AK1: Open EHS corrective actions (count) | AL1: Overdue EHS corrective actions (count) | AM1: EHS investigations due (count) | AN1: EHS investigations completed (count) | AO1: Critical materials at risk (count) | AP1: Dispatches (count) | AQ1: Delayed dispatches (count) | AR1: Days to permit expiry (days) | AS1: Sales volume (t) | AT1: Planned sales volume (t) | AU1: Revenue (₹ thousand) | AV1: Planned revenue (₹ thousand) | AW1: Power cost, part of variable cost (₹ thousand) | AX1: Depreciation and amortisation (₹ thousand) | AY1: Purchase-order lines due (count) | AZ1: Purchase-order lines delivered on time (count) | BA1: Quantity ordered from suppliers (t) | BB1: Quantity received (t) | BC1: Quantity rejected on quality (t) | BD1: Planned lead time, all deliveries (days) | BE1: Actual lead time, all deliveries (days) | BF1: Supplier spend (₹ thousand) | BG1: Spend with single-source suppliers (₹ thousand) | BH1: Supplier EHS incidents (count) | BI1: Regulatory filings pending (count) | BJ1: Regulatory deadlines in next 30 days (count) | BK1: Licences expiring in next 12 months (count) | BL1: Regulatory obligations due in next 30 days (count) | BM1: Regulatory obligations overdue (count) | BN1: Open regulatory actions (count) | BO1: Overdue compliance actions (count) | BP1: Regulatory breaches in the month (count) | BQ1: Events that trigger a disclosure clock (count) | BR1: EHS escalation clocks running (count) | BS1: Days until production plan is breached, forecast (days; 99 = not expected) | BT1: Planned production next month (t) | BU1: Forecast good output next month (t) | BV1: Forecast uncertainty next month (variance, t²) | BW1: Ideal output next month (t) | BX1: Forecast production lost to downtime next month (t) | BY1: Overheads, SG&A (₹ thousand) | BZ1: Tax paid (₹ thousand) | CA1: Capital employed, month end (₹ thousand) | CB1: Gross debt, month end (₹ thousand) | CC1: Cash, month end (₹ thousand) | CD1: Undrawn committed facilities (₹ thousand) | CE1: Debt service in the month (₹ thousand) | CF1: Debt maturing in next 12 months (₹ thousand) | CG1: Floating-rate debt (₹ thousand) | CH1: EBITDA as reported in the Board pack (₹ thousand) | CI1: Revenue in the flash report (₹ thousand) | CJ1: Trade receivables, month end (₹ thousand) | CK1: Trade payables, month end (₹ thousand) | CL1: Inventory, month end (₹ thousand) | CM1: Cash collected from customers (₹ thousand) | CN1: Cash released by working-capital actions (₹ thousand) | CO1: Cash due to be upstreamed to Group, next 30 days (₹ thousand) | CP1: Of which covered by available cash (₹ thousand) | CQ1: Invoices collected (count) | CR1: Days taken to collect, all invoices (days) | CS1: Agreed payment terms, all invoices (days) | CT1: Customers more than 30 days overdue (count) | CU1: Forecast EBITDA, rest of year (₹ thousand) | CV1: Planned EBITDA, rest of year (₹ thousand) | CW1: Forecast net cash flow, next 90 days (₹ thousand) | CX1: Forecast net debt at quarter end (₹ thousand) | CY1: Forecast EBITDA, 12 months to quarter end (₹ thousand) | CZ1: Foreign-currency exposure, gross (₹ thousand) | DA1: Foreign-currency exposure hedged (₹ thousand) | DB1: USD exposure, gross (₹ thousand) | DC1: USD exposure hedged (₹ thousand) | DD1: Change in value of hedges (₹ thousand) | DE1: Change in value of hedged items (₹ thousand) | DF1: Forecast foreign-currency flows, next 6 months (₹ thousand) | DG1: Of which hedged (₹ thousand) | DH1: Approved capex budget, full year (₹ thousand) | DI1: Capex committed to date (₹ thousand) | DJ1: Capex spent in the month (₹ thousand) | DK1: Capex work completed, valued at budget (₹ thousand) | DL1: Budget of capex projects at risk (₹ thousand) | DM1: Capex projects on track (count) | DN1: Capex projects at risk (count) | DO1: Capex projects off track (count) | DP1: Capex projects delayed (count) | DQ1: Contractor milestones due (count) | DR1: Contractor days late, all milestones (days) | DS1: Transformation initiatives on track (count) | DT1: Transformation initiatives at risk (count) | DU1: Transformation initiatives delayed (count) | DV1: Transformation milestones in plan (count) | DW1: Transformation milestones completed (count) | DX1: Programme benefits planned in the month (₹ thousand) | DY1: Programme benefits delivered in the month (₹ thousand) | DZ1: EBITDA benefit delivered (₹ thousand) | EA1: Cash benefit delivered (₹ thousand) | EB1: Cost savings delivered (₹ thousand) | EC1: Active supply contracts (count) | ED1: Contracts fully compliant (count) | EE1: Contracts expiring in next 90 days (count) | EF1: Suppliers not meeting EHS requirements (count) | EG1: Critical single-source suppliers (count) | EH1: Control failures (count) | EI1: High-severity control failures (count) | EJ1: Assurance reviews planned (count) | EK1: Assurance reviews completed (count) | EL1: Policy exceptions (count) | EM1: Unauthorised vendor uses (count) | EN1: Segregation-of-duties exceptions (count) | EO1: Unauthorised access events (count) | EP1: Data-sharing exceptions (count) | EQ1: Manual operational or system overrides (count) | ER1: Certification approvals past due date (count) | ES1: KPI values overridden (count) | ET1: Recurring data-quality issues (count) | EU1: Open audit findings (count) | EV1: Overdue assurance actions (count) | EW1: Repeat audit findings (count) | EX1: Leadership KPIs affected by open findings (count) | EY1: Evidence items required (count) | EZ1: Evidence items complete (count) | FA1: Audit findings closed in the month (count) | FB1: Days taken to close those findings (days) | FC1: Leadership KPI values reported (count) | FD1: Of which certified (count) | FE1: Of which inside the certification process (count) | FF1: Certifications overdue (count) | FG1: Open reconciliation breaks (count) | FH1: Material reconciliation breaks (count) | FI1: Records loaded to the data lake (count) | FJ1: Records reconciled to source (count) | FK1: Flash report lines (count) | FL1: Flash lines matching MIS (count) | FM1: Open critical alerts (count) | FN1: Alerts with no accepted owner (count) | FO1: Overdue actions (count) | FP1: Alerts resolved in the month (count) | FQ1: Days taken to resolve those alerts (days) | FR1: Escalations closed in the month (count) | FS1: Repeat issues raised in the month (count) | FT1: Root causes identified (count) | FU1: Root causes eliminated (count) | FV1: EBITDA (₹ thousand) | FW1: EBIT (₹ thousand) | FX1: Net working capital (₹ thousand) | FY1: Change in net working capital (₹ thousand) | FZ1: Operating cash flow (₹ thousand) | GA1: Free cash flow (₹ thousand) | GB1: Net debt (₹ thousand) | GC1: EBITDA, annualised (₹ thousand) | GD1: DSO (days) | GE1: DPO (days) | GF1: Inventory days (days) | GG1: Realised price vs plan (%)
A2: group | B2: period | C2: days | D2: ytd_months | E2: calendar_hours | F2: planned_op_hours | G2: run_hours | H2: unplanned_downtime_hours | I2: ideal_output_t | J2: installed_capacity_t | K2: planned_production_t | L2: gross_output_t | M2: good_output_t | N2: feed_input_t | O2: feed_contained_t | P2: recovered_contained_t | Q2: prod_loss_downtime_t | R2: failures | S2: repair_hours | T2: pm_scheduled | U2: pm_completed | V2: variable_cost_k | W2: fuel_cost_k | X2: fixed_cost_k | Y2: water_m3 | Z2: emissions_tco2e | AA2: energy_gj | AB2: production_at_risk_t | AC2: critical_plant_alerts | AD2: hours_worked | AE2: recordable_injuries | AF2: severity_incidents | AG2: near_misses | AH2: critical_safety_incidents | AI2: env_excursions | AJ2: env_violations | AK2: ehs_ca_open | AL2: ehs_ca_overdue | AM2: investigations_due | AN2: investigations_completed | AO2: critical_material_risks | AP2: dispatches_total | AQ2: dispatches_delayed | AR2: permit_days_to_expiry | AS2: sales_t | AT2: planned_sales_t | AU2: revenue_k | AV2: planned_revenue_k | AW2: power_cost_k | AX2: depreciation_k | AY2: po_lines_due | AZ2: po_lines_on_time | BA2: qty_ordered_t | BB2: qty_received_t | BC2: qty_rejected_t | BD2: lead_time_planned_days | BE2: lead_time_actual_days | BF2: supplier_spend_k | BG2: single_source_spend_k | BH2: supplier_ehs_incidents | BI2: pending_filings | BJ2: reg_deadlines_30d | BK2: licences_expiring_12m | BL2: reg_obligations_due_30d | BM2: reg_obligations_overdue | BN2: reg_actions_open | BO2: compliance_actions_overdue | BP2: reg_breaches | BQ2: disclosure_events_open | BR2: ehs_escalation_clocks | BS2: days_to_breach | BT2: planned_production_next_t | BU2: forecast_good_next_t | BV2: forecast_good_var_next | BW2: ideal_output_next_t | BX2: forecast_downtime_loss_next_t | BY2: overhead_k | BZ2: tax_paid_k | CA2: capital_employed_k | CB2: gross_debt_k | CC2: cash_k | CD2: undrawn_facilities_k | CE2: debt_service_k | CF2: debt_maturing_12m_k | CG2: floating_rate_debt_k | CH2: board_ebitda_k | CI2: flash_revenue_k | CJ2: receivables_k | CK2: payables_k | CL2: inventory_k | CM2: collections_k | CN2: cash_released_k | CO2: upstream_due_k | CP2: upstream_covered_k | CQ2: invoices_collected | CR2: collection_days | CS2: terms_days | CT2: customers_overdue | CU2: forecast_ebitda_rest_k | CV2: planned_ebitda_rest_k | CW2: forecast_net_cash_flow_90d_k | CX2: forecast_net_debt_k | CY2: forecast_ebitda_ltm_k | CZ2: fx_exposure_k | DA2: fx_hedged_k | DB2: usd_exposure_k | DC2: usd_hedged_k | DD2: hedge_value_change_k | DE2: hedged_item_value_change_k | DF2: fx_flows_6m_k | DG2: fx_hedged_6m_k | DH2: capex_budget_k | DI2: capex_committed_k | DJ2: capex_spend_k | DK2: capex_earned_value_k | DL2: capex_at_risk_k | DM2: projects_on_track | DN2: projects_at_risk | DO2: projects_off_track | DP2: projects_delayed | DQ2: contractor_milestones_due | DR2: contractor_days_late | DS2: initiatives_on_track | DT2: initiatives_at_risk | DU2: initiatives_delayed | DV2: milestones_total | DW2: milestones_done | DX2: benefits_planned_k | DY2: benefits_delivered_k | DZ2: ebitda_benefit_k | EA2: cash_benefit_k | EB2: cost_savings_k | EC2: contracts_total | ED2: contracts_compliant | EE2: contracts_expiring_90d | EF2: supplier_ehs_noncompliance | EG2: single_source_suppliers | EH2: control_failures | EI2: control_failures_high | EJ2: assurance_reviews_planned | EK2: assurance_reviews_done | EL2: policy_exceptions | EM2: unauthorized_vendor_uses | EN2: sod_exceptions | EO2: unauthorized_access_events | EP2: data_sharing_exceptions | EQ2: manual_overrides | ER2: cert_approvals_ageing | ES2: kpi_overrides | ET2: dq_issues_recurring | EU2: audit_findings_open | EV2: assurance_actions_overdue | EW2: repeat_findings | EX2: leadership_kpis_affected | EY2: evidence_required | EZ2: evidence_complete | FA2: findings_closed | FB2: finding_closure_days | FC2: kpis_leadership | FD2: kpis_certified | FE2: kpis_in_scope | FF2: certifications_overdue | FG2: recon_breaks_open | FH2: recon_breaks_material | FI2: lake_records_loaded | FJ2: lake_records_reconciled | FK2: mis_lines_total | FL2: mis_lines_matched | FM2: critical_alerts_open | FN2: alerts_unowned | FO2: actions_overdue | FP2: alerts_resolved | FQ2: alert_resolution_days | FR2: escalations_closed | FS2: repeat_issues | FT2: root_causes_identified | FU2: root_causes_eliminated | FV2: ebitda_k | FW2: ebit_k | FX2: nwc_k | FY2: nwc_change_k | FZ2: op_cash_flow_k | GA2: fcf_k | GB2: net_debt_k | GC2: ebitda_annualised_k | GD2: dso_d | GE2: dpo_d | GF2: dio_d | GG2: price_vs_plan_pct
E3: Sum of Entity A1 and Entity A2 (Entity Inputs sheet) | F3: Sum of Entity A1 and Entity A2 (Entity Inputs sheet) | G3: Sum of Entity A1 and Entity A2 (Entity Inputs sheet) | H3: Sum of Entity A1 and Entity A2 (Entity Inputs sheet) | I3: Sum of Entity A1 and Entity A2 (Entity Inputs sheet) | J3: Sum of Entity A1 and Entity A2 (Entity Inputs sheet) | K3: Sum of Entity A1 and Entity A2 (Entity Inputs sheet) | L3: Sum of Entity A1 and Entity A2 (Entity Inputs sheet) | M3: Sum of Entity A1 and Entity A2 (Entity Inputs sheet) | N3: Sum of Entity A1 and Entity A2 (Entity Inputs sheet) | O3: Sum of Entity A1 and Entity A2 (Entity Inputs sheet) | P3: Sum of Entity A1 and Entity A2 (Entity Inputs sheet) | Q3: Sum of Entity A1 and Entity A2 (Entity Inputs sheet) | R3: Sum of Entity A1 and Entity A2 (Entity Inputs sheet) | S3: Sum of Entity A1 and Entity A2 (Entity Inputs sheet) | T3: Sum of Entity A1 and Entity A2 (Entity Inputs sheet) | U3: Sum of Entity A1 and Entity A2 (Entity Inputs sheet) | V3: Sum of Entity A1 and Entity A2 (Entity Inputs sheet) | W3: Sum of Entity A1 and Entity A2 (Entity Inputs sheet) | X3: Sum of Entity A1 and Entity A2 (Entity Inputs sheet) | Y3: Sum of Entity A1 and Entity A2 (Entity Inputs sheet) | Z3: Sum of Entity A1 and Entity A2 (Entity Inputs sheet) | AA3: Sum of Entity A1 and Entity A2 (Entity Inputs sheet) | AB3: Sum of Entity A1 and Entity A2 (Entity Inputs sheet) | AC3: Sum of Entity A1 and Entity A2 (Entity Inputs sheet) | AD3: Sum of Entity A1 and Entity A2 (Entity Inputs sheet) | AE3: Sum of Entity A1 and Entity A2 (Entity Inputs sheet) | AF3: Sum of Entity A1 and Entity A2 (Entity Inputs sheet) | AG3: Sum of Entity A1 and Entity A2 (Entity Inputs sheet) | AH3: Sum of Entity A1 and Entity A2 (Entity Inputs sheet) | AI3: Sum of Entity A1 and Entity A2 (Entity Inputs sheet) | AJ3: Sum of Entity A1 and Entity A2 (Entity Inputs sheet) | AK3: Sum of Entity A1 and Entity A2 (Entity Inputs sheet) | AL3: Sum of Entity A1 and Entity A2 (Entity Inputs sheet) | AM3: Sum of Entity A1 and Entity A2 (Entity Inputs sheet) | AN3: Sum of Entity A1 and Entity A2 (Entity Inputs sheet) | AO3: Sum of Entity A1 and Entity A2 (Entity Inputs sheet) | AP3: Sum of Entity A1 and Entity A2 (Entity Inputs sheet) | AQ3: Sum of Entity A1 and Entity A2 (Entity Inputs sheet) | AR3: Lowest of Entity A1 and Entity A2 (Entity Inputs sheet) | AS3: Sum of Entity A1 and Entity A2 (Entity Inputs sheet) | AT3: Sum of Entity A1 and Entity A2 (Entity Inputs sheet) | AU3: Sum of Entity A1 and Entity A2 (Entity Inputs sheet) | AV3: Sum of Entity A1 and Entity A2 (Entity Inputs sheet) | AW3: Sum of Entity A1 and Entity A2 (Entity Inputs sheet) | AX3: Sum of Entity A1 and Entity A2 (Entity Inputs sheet) | AY3: Sum of Entity A1 and Entity A2 (Entity Inputs sheet) | AZ3: Sum of Entity A1 and Entity A2 (Entity Inputs sheet) | BA3: Sum of Entity A1 and Entity A2 (Entity Inputs sheet) | BB3: Sum of Entity A1 and Entity A2 (Entity Inputs sheet) | BC3: Sum of Entity A1 and Entity A2 (Entity Inputs sheet) | BD3: Sum of Entity A1 and Entity A2 (Entity Inputs sheet) | BE3: Sum of Entity A1 and Entity A2 (Entity Inputs sheet) | BF3: Sum of Entity A1 and Entity A2 (Entity Inputs sheet) | BG3: Sum of Entity A1 and Entity A2 (Entity Inputs sheet) | BH3: Sum of Entity A1 and Entity A2 (Entity Inputs sheet) | BI3: Sum of Entity A1 and Entity A2 (Entity Inputs sheet) | BJ3: Sum of Entity A1 and Entity A2 (Entity Inputs sheet) | BK3: Sum of Entity A1 and Entity A2 (Entity Inputs sheet) | BL3: Sum of Entity A1 and Entity A2 (Entity Inputs sheet) | BM3: Sum of Entity A1 and Entity A2 (Entity Inputs sheet) | BN3: Sum of Entity A1 and Entity A2 (Entity Inputs sheet) | BO3: Sum of Entity A1 and Entity A2 (Entity Inputs sheet) | BP3: Sum of Entity A1 and Entity A2 (Entity Inputs sheet) | BQ3: Sum of Entity A1 and Entity A2 (Entity Inputs sheet) | BR3: Sum of Entity A1 and Entity A2 (Entity Inputs sheet) | BS3: Lowest of Entity A1 and Entity A2 (Entity Inputs sheet) | BT3: Sum of Entity A1 and Entity A2 (Entity Inputs sheet) | BU3: Sum of Entity A1 and Entity A2 (Entity Inputs sheet) | BV3: Sum of Entity A1 and Entity A2 (Entity Inputs sheet) | BW3: Sum of Entity A1 and Entity A2 (Entity Inputs sheet) | BX3: Sum of Entity A1 and Entity A2 (Entity Inputs sheet) | BY3: Sum of Entity A1 and Entity A2 (Entity Inputs sheet) | BZ3: Sum of Entity A1 and Entity A2 (Entity Inputs sheet) | CA3: Sum of Entity A1 and Entity A2 (Entity Inputs sheet) | CB3: Sum of Entity A1 and Entity A2 (Entity Inputs sheet) | CC3: Sum of Entity A1 and Entity A2 (Entity Inputs sheet) | CD3: Sum of Entity A1 and Entity A2 (Entity Inputs sheet) | CE3: Sum of Entity A1 and Entity A2 (Entity Inputs sheet) | CF3: Sum of Entity A1 and Entity A2 (Entity Inputs sheet) | CG3: Sum of Entity A1 and Entity A2 (Entity Inputs sheet) | CH3: Sum of Entity A1 and Entity A2 (Entity Inputs sheet) | CI3: Sum of Entity A1 and Entity A2 (Entity Inputs sheet) | CJ3: Sum of Entity A1 and Entity A2 (Entity Inputs sheet) | CK3: Sum of Entity A1 and Entity A2 (Entity Inputs sheet) | CL3: Sum of Entity A1 and Entity A2 (Entity Inputs sheet) | CM3: Sum of Entity A1 and Entity A2 (Entity Inputs sheet) | CN3: Sum of Entity A1 and Entity A2 (Entity Inputs sheet) | CO3: Sum of Entity A1 and Entity A2 (Entity Inputs sheet) | CP3: Sum of Entity A1 and Entity A2 (Entity Inputs sheet) | CQ3: Sum of Entity A1 and Entity A2 (Entity Inputs sheet) | CR3: Sum of Entity A1 and Entity A2 (Entity Inputs sheet) | CS3: Sum of Entity A1 and Entity A2 (Entity Inputs sheet) | CT3: Sum of Entity A1 and Entity A2 (Entity Inputs sheet) | CU3: Sum of Entity A1 and Entity A2 (Entity Inputs sheet) | CV3: Sum of Entity A1 and Entity A2 (Entity Inputs sheet) | CW3: Sum of Entity A1 and Entity A2 (Entity Inputs sheet) | CX3: Sum of Entity A1 and Entity A2 (Entity Inputs sheet) | CY3: Sum of Entity A1 and Entity A2 (Entity Inputs sheet) | CZ3: Sum of Entity A1 and Entity A2 (Entity Inputs sheet) | DA3: Sum of Entity A1 and Entity A2 (Entity Inputs sheet) | DB3: Sum of Entity A1 and Entity A2 (Entity Inputs sheet) | DC3: Sum of Entity A1 and Entity A2 (Entity Inputs sheet) | DD3: Sum of Entity A1 and Entity A2 (Entity Inputs sheet) | DE3: Sum of Entity A1 and Entity A2 (Entity Inputs sheet) | DF3: Sum of Entity A1 and Entity A2 (Entity Inputs sheet) | DG3: Sum of Entity A1 and Entity A2 (Entity Inputs sheet) | DH3: Sum of Entity A1 and Entity A2 (Entity Inputs sheet) | DI3: Sum of Entity A1 and Entity A2 (Entity Inputs sheet) | DJ3: Sum of Entity A1 and Entity A2 (Entity Inputs sheet) | DK3: Sum of Entity A1 and Entity A2 (Entity Inputs sheet) | DL3: Sum of Entity A1 and Entity A2 (Entity Inputs sheet) | DM3: Sum of Entity A1 and Entity A2 (Entity Inputs sheet) | DN3: Sum of Entity A1 and Entity A2 (Entity Inputs sheet) | DO3: Sum of Entity A1 and Entity A2 (Entity Inputs sheet) | DP3: Sum of Entity A1 and Entity A2 (Entity Inputs sheet) | DQ3: Sum of Entity A1 and Entity A2 (Entity Inputs sheet) | DR3: Sum of Entity A1 and Entity A2 (Entity Inputs sheet) | DS3: Sum of Entity A1 and Entity A2 (Entity Inputs sheet) | DT3: Sum of Entity A1 and Entity A2 (Entity Inputs sheet) | DU3: Sum of Entity A1 and Entity A2 (Entity Inputs sheet) | DV3: Sum of Entity A1 and Entity A2 (Entity Inputs sheet) | DW3: Sum of Entity A1 and Entity A2 (Entity Inputs sheet) | DX3: Sum of Entity A1 and Entity A2 (Entity Inputs sheet) | DY3: Sum of Entity A1 and Entity A2 (Entity Inputs sheet) | DZ3: Sum of Entity A1 and Entity A2 (Entity Inputs sheet) | EA3: Sum of Entity A1 and Entity A2 (Entity Inputs sheet) | EB3: Sum of Entity A1 and Entity A2 (Entity Inputs sheet) | EC3: Sum of Entity A1 and Entity A2 (Entity Inputs sheet) | ED3: Sum of Entity A1 and Entity A2 (Entity Inputs sheet) | EE3: Sum of Entity A1 and Entity A2 (Entity Inputs sheet) | EF3: Sum of Entity A1 and Entity A2 (Entity Inputs sheet) | EG3: Sum of Entity A1 and Entity A2 (Entity Inputs sheet) | EH3: Sum of Entity A1 and Entity A2 (Entity Inputs sheet) | EI3: Sum of Entity A1 and Entity A2 (Entity Inputs sheet) | EJ3: Sum of Entity A1 and Entity A2 (Entity Inputs sheet) | EK3: Sum of Entity A1 and Entity A2 (Entity Inputs sheet) | EL3: Sum of Entity A1 and Entity A2 (Entity Inputs sheet) | EM3: Sum of Entity A1 and Entity A2 (Entity Inputs sheet) | EN3: Sum of Entity A1 and Entity A2 (Entity Inputs sheet) | EO3: Sum of Entity A1 and Entity A2 (Entity Inputs sheet) | EP3: Sum of Entity A1 and Entity A2 (Entity Inputs sheet) | EQ3: Sum of Entity A1 and Entity A2 (Entity Inputs sheet) | ER3: Sum of Entity A1 and Entity A2 (Entity Inputs sheet) | ES3: Sum of Entity A1 and Entity A2 (Entity Inputs sheet) | ET3: Sum of Entity A1 and Entity A2 (Entity Inputs sheet) | EU3: Sum of Entity A1 and Entity A2 (Entity Inputs sheet) | EV3: Sum of Entity A1 and Entity A2 (Entity Inputs sheet) | EW3: Sum of Entity A1 and Entity A2 (Entity Inputs sheet) | EX3: Sum of Entity A1 and Entity A2 (Entity Inputs sheet) | EY3: Sum of Entity A1 and Entity A2 (Entity Inputs sheet) | EZ3: Sum of Entity A1 and Entity A2 (Entity Inputs sheet) | FA3: Sum of Entity A1 and Entity A2 (Entity Inputs sheet) | FB3: Sum of Entity A1 and Entity A2 (Entity Inputs sheet) | FC3: Sum of Entity A1 and Entity A2 (Entity Inputs sheet) | FD3: Sum of Entity A1 and Entity A2 (Entity Inputs sheet) | FE3: Sum of Entity A1 and Entity A2 (Entity Inputs sheet) | FF3: Sum of Entity A1 and Entity A2 (Entity Inputs sheet) | FG3: Sum of Entity A1 and Entity A2 (Entity Inputs sheet) | FH3: Sum of Entity A1 and Entity A2 (Entity Inputs sheet) | FI3: Sum of Entity A1 and Entity A2 (Entity Inputs sheet) | FJ3: Sum of Entity A1 and Entity A2 (Entity Inputs sheet) | FK3: Sum of Entity A1 and Entity A2 (Entity Inputs sheet) | FL3: Sum of Entity A1 and Entity A2 (Entity Inputs sheet) | FM3: Sum of Entity A1 and Entity A2 (Entity Inputs sheet) | FN3: Sum of Entity A1 and Entity A2 (Entity Inputs sheet) | FO3: Sum of Entity A1 and Entity A2 (Entity Inputs sheet) | FP3: Sum of Entity A1 and Entity A2 (Entity Inputs sheet) | FQ3: Sum of Entity A1 and Entity A2 (Entity Inputs sheet) | FR3: Sum of Entity A1 and Entity A2 (Entity Inputs sheet) | FS3: Sum of Entity A1 and Entity A2 (Entity Inputs sheet) | FT3: Sum of Entity A1 and Entity A2 (Entity Inputs sheet) | FU3: Sum of Entity A1 and Entity A2 (Entity Inputs sheet) | FV3: Calculated: Revenue − Variable cost − Fixed cost − Overheads | FW3: Calculated: EBITDA − Depreciation and amortisation | FX3: Calculated: Trade receivables + Inventory − Trade payables | FY3: Calculated: Net working capital − last month's net working capital (April uses the 31 March balance on Parameters) | FZ3: Calculated: EBITDA − Tax paid − Change in net working capital | GA3: Calculated: Operating cash flow − Capex spent | GB3: Calculated: Gross debt − Cash | GC3: Calculated: EBITDA since April × 12 ÷ months elapsed | GD3: Calculated: Trade receivables ÷ Revenue × Days in month | GE3: Calculated: Trade payables ÷ Variable cost × Days in month | GF3: Calculated: Inventory ÷ Variable cost × Days in month | GG3: Calculated: (Revenue ÷ Sales volume) ÷ (Planned revenue ÷ Planned sales volume) − 1, as %
A4: Group | B4: 2026-04 | C4: 30 | D4: 1 | E4: =SUM('Entity Inputs'!E4,'Entity Inputs'!E10) | F4: =SUM('Entity Inputs'!F4,'Entity Inputs'!F10) | G4: =SUM('Entity Inputs'!G4,'Entity Inputs'!G10) | H4: =SUM('Entity Inputs'!H4,'Entity Inputs'!H10) | I4: =SUM('Entity Inputs'!I4,'Entity Inputs'!I10) | J4: =SUM('Entity Inputs'!J4,'Entity Inputs'!J10) | K4: =SUM('Entity Inputs'!K4,'Entity Inputs'!K10) | L4: =SUM('Entity Inputs'!L4,'Entity Inputs'!L10) | ... AQ4: =SUM('Entity Inputs'!AQ4,'Entity Inputs'!AQ10) | AR4: =MIN('Entity Inputs'!AR4,'Entity Inputs'!AR10) | AS4: =SUM('Entity Inputs'!AS4,'Entity Inputs'!AS10) | AT4: =SUM('Entity Inputs'!AT4,'Entity Inputs'!AT10) | AU4: =SUM('Entity Inputs'!AU4,'Entity Inputs'!AU10) | AV4: =SUM('Entity Inputs'!AV4,'Entity Inputs'!AV10) | AW4: =SUM('Entity Inputs'!AW4,'Entity Inputs'!AW10) | AX4: =SUM('Entity Inputs'!AX4,'Entity Inputs'!AX10) | AY4: =SUM('Entity Inputs'!AY4,'Entity Inputs'!AY10) | AZ4: =SUM('Entity Inputs'!AZ4,'Entity Inputs'!AZ10) | ... BR4: =SUM('Entity Inputs'!BR4,'Entity Inputs'!BR10) | BS4: =MIN('Entity Inputs'!BS4,'Entity Inputs'!BS10) | BT4: =SUM('Entity Inputs'!BT4,'Entity Inputs'!BT10) | BU4: =SUM('Entity Inputs'!BU4,'Entity Inputs'!BU10) | BV4: =SUM('Entity Inputs'!BV4,'Entity Inputs'!BV10) | BW4: =SUM('Entity Inputs'!BW4,'Entity Inputs'!BW10) | BX4: =SUM('Entity Inputs'!BX4,'Entity Inputs'!BX10) | BY4: =SUM('Entity Inputs'!BY4,'Entity Inputs'!BY10) | BZ4: =SUM('Entity Inputs'!BZ4,'Entity Inputs'!BZ10) | CA4: =SUM('Entity Inputs'!CA4,'Entity Inputs'!CA10) | ... FU4: =SUM('Entity Inputs'!FU4,'Entity Inputs'!FU10) | FV4: =AU4-V4-X4-BY4 | FW4: =FV4-AX4 | FX4: =CJ4+CL4-CK4 | FY4: =FX4-Parameters!$B$7 | FZ4: =FV4-BZ4-FY4 | GA4: =FZ4-DJ4 | GB4: =CB4-CC4 | GC4: =SUM(FV$4:FV4)*12/D4 | GD4: =IF(AU4=0,0,CJ4/AU4*C4) | GE4: =IF(V4=0,0,CK4/V4*C4) | GF4: =IF(V4=0,0,CL4/V4*C4) | GG4: =IF(OR(AS4=0,AT4=0,AV4=0),0,100*((AU4/AS4)/(AV4/AT4)-1))
A5: Group | B5: 2026-05 | C5: 31 | D5: 2 | E5: =SUM('Entity Inputs'!E5,'Entity Inputs'!E11) | F5: =SUM('Entity Inputs'!F5,'Entity Inputs'!F11) | G5: =SUM('Entity Inputs'!G5,'Entity Inputs'!G11) | H5: =SUM('Entity Inputs'!H5,'Entity Inputs'!H11) | I5: =SUM('Entity Inputs'!I5,'Entity Inputs'!I11) | J5: =SUM('Entity Inputs'!J5,'Entity Inputs'!J11) | K5: =SUM('Entity Inputs'!K5,'Entity Inputs'!K11) | L5: =SUM('Entity Inputs'!L5,'Entity Inputs'!L11) | ... AQ5: =SUM('Entity Inputs'!AQ5,'Entity Inputs'!AQ11) | AR5: =MIN('Entity Inputs'!AR5,'Entity Inputs'!AR11) | AS5: =SUM('Entity Inputs'!AS5,'Entity Inputs'!AS11) | AT5: =SUM('Entity Inputs'!AT5,'Entity Inputs'!AT11) | AU5: =SUM('Entity Inputs'!AU5,'Entity Inputs'!AU11) | AV5: =SUM('Entity Inputs'!AV5,'Entity Inputs'!AV11) | AW5: =SUM('Entity Inputs'!AW5,'Entity Inputs'!AW11) | AX5: =SUM('Entity Inputs'!AX5,'Entity Inputs'!AX11) | AY5: =SUM('Entity Inputs'!AY5,'Entity Inputs'!AY11) | AZ5: =SUM('Entity Inputs'!AZ5,'Entity Inputs'!AZ11) | ... BR5: =SUM('Entity Inputs'!BR5,'Entity Inputs'!BR11) | BS5: =MIN('Entity Inputs'!BS5,'Entity Inputs'!BS11) | BT5: =SUM('Entity Inputs'!BT5,'Entity Inputs'!BT11) | BU5: =SUM('Entity Inputs'!BU5,'Entity Inputs'!BU11) | BV5: =SUM('Entity Inputs'!BV5,'Entity Inputs'!BV11) | BW5: =SUM('Entity Inputs'!BW5,'Entity Inputs'!BW11) | BX5: =SUM('Entity Inputs'!BX5,'Entity Inputs'!BX11) | BY5: =SUM('Entity Inputs'!BY5,'Entity Inputs'!BY11) | BZ5: =SUM('Entity Inputs'!BZ5,'Entity Inputs'!BZ11) | CA5: =SUM('Entity Inputs'!CA5,'Entity Inputs'!CA11) | ... FU5: =SUM('Entity Inputs'!FU5,'Entity Inputs'!FU11) | FV5: =AU5-V5-X5-BY5 | FW5: =FV5-AX5 | FX5: =CJ5+CL5-CK5 | FY5: =FX5-FX4 | FZ5: =FV5-BZ5-FY5 | GA5: =FZ5-DJ5 | GB5: =CB5-CC5 | GC5: =SUM(FV$4:FV5)*12/D5 | GD5: =IF(AU5=0,0,CJ5/AU5*C5) | GE5: =IF(V5=0,0,CK5/V5*C5) | GF5: =IF(V5=0,0,CL5/V5*C5) | GG5: =IF(OR(AS5=0,AT5=0,AV5=0),0,100*((AU5/AS5)/(AV5/AT5)-1))
A6: Group | B6: 2026-06 | C6: 30 | D6: 3 | E6: =SUM('Entity Inputs'!E6,'Entity Inputs'!E12) | F6: =SUM('Entity Inputs'!F6,'Entity Inputs'!F12) | G6: =SUM('Entity Inputs'!G6,'Entity Inputs'!G12) | H6: =SUM('Entity Inputs'!H6,'Entity Inputs'!H12) | I6: =SUM('Entity Inputs'!I6,'Entity Inputs'!I12) | J6: =SUM('Entity Inputs'!J6,'Entity Inputs'!J12) | K6: =SUM('Entity Inputs'!K6,'Entity Inputs'!K12) | L6: =SUM('Entity Inputs'!L6,'Entity Inputs'!L12) | ... AQ6: =SUM('Entity Inputs'!AQ6,'Entity Inputs'!AQ12) | AR6: =MIN('Entity Inputs'!AR6,'Entity Inputs'!AR12) | AS6: =SUM('Entity Inputs'!AS6,'Entity Inputs'!AS12) | AT6: =SUM('Entity Inputs'!AT6,'Entity Inputs'!AT12) | AU6: =SUM('Entity Inputs'!AU6,'Entity Inputs'!AU12) | AV6: =SUM('Entity Inputs'!AV6,'Entity Inputs'!AV12) | AW6: =SUM('Entity Inputs'!AW6,'Entity Inputs'!AW12) | AX6: =SUM('Entity Inputs'!AX6,'Entity Inputs'!AX12) | AY6: =SUM('Entity Inputs'!AY6,'Entity Inputs'!AY12) | AZ6: =SUM('Entity Inputs'!AZ6,'Entity Inputs'!AZ12) | ... BR6: =SUM('Entity Inputs'!BR6,'Entity Inputs'!BR12) | BS6: =MIN('Entity Inputs'!BS6,'Entity Inputs'!BS12) | BT6: =SUM('Entity Inputs'!BT6,'Entity Inputs'!BT12) | BU6: =SUM('Entity Inputs'!BU6,'Entity Inputs'!BU12) | BV6: =SUM('Entity Inputs'!BV6,'Entity Inputs'!BV12) | BW6: =SUM('Entity Inputs'!BW6,'Entity Inputs'!BW12) | BX6: =SUM('Entity Inputs'!BX6,'Entity Inputs'!BX12) | BY6: =SUM('Entity Inputs'!BY6,'Entity Inputs'!BY12) | BZ6: =SUM('Entity Inputs'!BZ6,'Entity Inputs'!BZ12) | CA6: =SUM('Entity Inputs'!CA6,'Entity Inputs'!CA12) | ... FU6: =SUM('Entity Inputs'!FU6,'Entity Inputs'!FU12) | FV6: =AU6-V6-X6-BY6 | FW6: =FV6-AX6 | FX6: =CJ6+CL6-CK6 | FY6: =FX6-FX5 | FZ6: =FV6-BZ6-FY6 | GA6: =FZ6-DJ6 | GB6: =CB6-CC6 | GC6: =SUM(FV$4:FV6)*12/D6 | GD6: =IF(AU6=0,0,CJ6/AU6*C6) | GE6: =IF(V6=0,0,CK6/V6*C6) | GF6: =IF(V6=0,0,CL6/V6*C6) | GG6: =IF(OR(AS6=0,AT6=0,AV6=0),0,100*((AU6/AS6)/(AV6/AT6)-1))
A7: Group | B7: 2026-07 | C7: 31 | D7: 4 | E7: =SUM('Entity Inputs'!E7,'Entity Inputs'!E13) | F7: =SUM('Entity Inputs'!F7,'Entity Inputs'!F13) | G7: =SUM('Entity Inputs'!G7,'Entity Inputs'!G13) | H7: =SUM('Entity Inputs'!H7,'Entity Inputs'!H13) | I7: =SUM('Entity Inputs'!I7,'Entity Inputs'!I13) | J7: =SUM('Entity Inputs'!J7,'Entity Inputs'!J13) | K7: =SUM('Entity Inputs'!K7,'Entity Inputs'!K13) | L7: =SUM('Entity Inputs'!L7,'Entity Inputs'!L13) | ... AQ7: =SUM('Entity Inputs'!AQ7,'Entity Inputs'!AQ13) | AR7: =MIN('Entity Inputs'!AR7,'Entity Inputs'!AR13) | AS7: =SUM('Entity Inputs'!AS7,'Entity Inputs'!AS13) | AT7: =SUM('Entity Inputs'!AT7,'Entity Inputs'!AT13) | AU7: =SUM('Entity Inputs'!AU7,'Entity Inputs'!AU13) | AV7: =SUM('Entity Inputs'!AV7,'Entity Inputs'!AV13) | AW7: =SUM('Entity Inputs'!AW7,'Entity Inputs'!AW13) | AX7: =SUM('Entity Inputs'!AX7,'Entity Inputs'!AX13) | AY7: =SUM('Entity Inputs'!AY7,'Entity Inputs'!AY13) | AZ7: =SUM('Entity Inputs'!AZ7,'Entity Inputs'!AZ13) | ... BR7: =SUM('Entity Inputs'!BR7,'Entity Inputs'!BR13) | BS7: =MIN('Entity Inputs'!BS7,'Entity Inputs'!BS13) | BT7: =SUM('Entity Inputs'!BT7,'Entity Inputs'!BT13) | BU7: =SUM('Entity Inputs'!BU7,'Entity Inputs'!BU13) | BV7: =SUM('Entity Inputs'!BV7,'Entity Inputs'!BV13) | BW7: =SUM('Entity Inputs'!BW7,'Entity Inputs'!BW13) | BX7: =SUM('Entity Inputs'!BX7,'Entity Inputs'!BX13) | BY7: =SUM('Entity Inputs'!BY7,'Entity Inputs'!BY13) | BZ7: =SUM('Entity Inputs'!BZ7,'Entity Inputs'!BZ13) | CA7: =SUM('Entity Inputs'!CA7,'Entity Inputs'!CA13) | ... FU7: =SUM('Entity Inputs'!FU7,'Entity Inputs'!FU13) | FV7: =AU7-V7-X7-BY7 | FW7: =FV7-AX7 | FX7: =CJ7+CL7-CK7 | FY7: =FX7-FX6 | FZ7: =FV7-BZ7-FY7 | GA7: =FZ7-DJ7 | GB7: =CB7-CC7 | GC7: =SUM(FV$4:FV7)*12/D7 | GD7: =IF(AU7=0,0,CJ7/AU7*C7) | GE7: =IF(V7=0,0,CK7/V7*C7) | GF7: =IF(V7=0,0,CL7/V7*C7) | GG7: =IF(OR(AS7=0,AT7=0,AV7=0),0,100*((AU7/AS7)/(AV7/AT7)-1))
A8: Group | B8: 2026-08 | C8: 31 | D8: 5 | E8: =SUM('Entity Inputs'!E8,'Entity Inputs'!E14) | F8: =SUM('Entity Inputs'!F8,'Entity Inputs'!F14) | G8: =SUM('Entity Inputs'!G8,'Entity Inputs'!G14) | H8: =SUM('Entity Inputs'!H8,'Entity Inputs'!H14) | I8: =SUM('Entity Inputs'!I8,'Entity Inputs'!I14) | J8: =SUM('Entity Inputs'!J8,'Entity Inputs'!J14) | K8: =SUM('Entity Inputs'!K8,'Entity Inputs'!K14) | L8: =SUM('Entity Inputs'!L8,'Entity Inputs'!L14) | ... AQ8: =SUM('Entity Inputs'!AQ8,'Entity Inputs'!AQ14) | AR8: =MIN('Entity Inputs'!AR8,'Entity Inputs'!AR14) | AS8: =SUM('Entity Inputs'!AS8,'Entity Inputs'!AS14) | AT8: =SUM('Entity Inputs'!AT8,'Entity Inputs'!AT14) | AU8: =SUM('Entity Inputs'!AU8,'Entity Inputs'!AU14) | AV8: =SUM('Entity Inputs'!AV8,'Entity Inputs'!AV14) | AW8: =SUM('Entity Inputs'!AW8,'Entity Inputs'!AW14) | AX8: =SUM('Entity Inputs'!AX8,'Entity Inputs'!AX14) | AY8: =SUM('Entity Inputs'!AY8,'Entity Inputs'!AY14) | AZ8: =SUM('Entity Inputs'!AZ8,'Entity Inputs'!AZ14) | ... BR8: =SUM('Entity Inputs'!BR8,'Entity Inputs'!BR14) | BS8: =MIN('Entity Inputs'!BS8,'Entity Inputs'!BS14) | BT8: =SUM('Entity Inputs'!BT8,'Entity Inputs'!BT14) | BU8: =SUM('Entity Inputs'!BU8,'Entity Inputs'!BU14) | BV8: =SUM('Entity Inputs'!BV8,'Entity Inputs'!BV14) | BW8: =SUM('Entity Inputs'!BW8,'Entity Inputs'!BW14) | BX8: =SUM('Entity Inputs'!BX8,'Entity Inputs'!BX14) | BY8: =SUM('Entity Inputs'!BY8,'Entity Inputs'!BY14) | BZ8: =SUM('Entity Inputs'!BZ8,'Entity Inputs'!BZ14) | CA8: =SUM('Entity Inputs'!CA8,'Entity Inputs'!CA14) | ... FU8: =SUM('Entity Inputs'!FU8,'Entity Inputs'!FU14) | FV8: =AU8-V8-X8-BY8 | FW8: =FV8-AX8 | FX8: =CJ8+CL8-CK8 | FY8: =FX8-FX7 | FZ8: =FV8-BZ8-FY8 | GA8: =FZ8-DJ8 | GB8: =CB8-CC8 | GC8: =SUM(FV$4:FV8)*12/D8 | GD8: =IF(AU8=0,0,CJ8/AU8*C8) | GE8: =IF(V8=0,0,CK8/V8*C8) | GF8: =IF(V8=0,0,CL8/V8*C8) | GG8: =IF(OR(AS8=0,AT8=0,AV8=0),0,100*((AU8/AS8)/(AV8/AT8)-1))
A9: Group | B9: 2026-09 | C9: 30 | D9: 6 | E9: =SUM('Entity Inputs'!E9,'Entity Inputs'!E15) | F9: =SUM('Entity Inputs'!F9,'Entity Inputs'!F15) | G9: =SUM('Entity Inputs'!G9,'Entity Inputs'!G15) | H9: =SUM('Entity Inputs'!H9,'Entity Inputs'!H15) | I9: =SUM('Entity Inputs'!I9,'Entity Inputs'!I15) | J9: =SUM('Entity Inputs'!J9,'Entity Inputs'!J15) | K9: =SUM('Entity Inputs'!K9,'Entity Inputs'!K15) | L9: =SUM('Entity Inputs'!L9,'Entity Inputs'!L15) | ... AQ9: =SUM('Entity Inputs'!AQ9,'Entity Inputs'!AQ15) | AR9: =MIN('Entity Inputs'!AR9,'Entity Inputs'!AR15) | AS9: =SUM('Entity Inputs'!AS9,'Entity Inputs'!AS15) | AT9: =SUM('Entity Inputs'!AT9,'Entity Inputs'!AT15) | AU9: =SUM('Entity Inputs'!AU9,'Entity Inputs'!AU15) | AV9: =SUM('Entity Inputs'!AV9,'Entity Inputs'!AV15) | AW9: =SUM('Entity Inputs'!AW9,'Entity Inputs'!AW15) | AX9: =SUM('Entity Inputs'!AX9,'Entity Inputs'!AX15) | AY9: =SUM('Entity Inputs'!AY9,'Entity Inputs'!AY15) | AZ9: =SUM('Entity Inputs'!AZ9,'Entity Inputs'!AZ15) | ... BR9: =SUM('Entity Inputs'!BR9,'Entity Inputs'!BR15) | BS9: =MIN('Entity Inputs'!BS9,'Entity Inputs'!BS15) | BT9: =SUM('Entity Inputs'!BT9,'Entity Inputs'!BT15) | BU9: =SUM('Entity Inputs'!BU9,'Entity Inputs'!BU15) | BV9: =SUM('Entity Inputs'!BV9,'Entity Inputs'!BV15) | BW9: =SUM('Entity Inputs'!BW9,'Entity Inputs'!BW15) | BX9: =SUM('Entity Inputs'!BX9,'Entity Inputs'!BX15) | BY9: =SUM('Entity Inputs'!BY9,'Entity Inputs'!BY15) | BZ9: =SUM('Entity Inputs'!BZ9,'Entity Inputs'!BZ15) | CA9: =SUM('Entity Inputs'!CA9,'Entity Inputs'!CA15) | ... FU9: =SUM('Entity Inputs'!FU9,'Entity Inputs'!FU15) | FV9: =AU9-V9-X9-BY9 | FW9: =FV9-AX9 | FX9: =CJ9+CL9-CK9 | FY9: =FX9-FX8 | FZ9: =FV9-BZ9-FY9 | GA9: =FZ9-DJ9 | GB9: =CB9-CC9 | GC9: =SUM(FV$4:FV9)*12/D9 | GD9: =IF(AU9=0,0,CJ9/AU9*C9) | GE9: =IF(V9=0,0,CK9/V9*C9) | GF9: =IF(V9=0,0,CL9/V9*C9) | GG9: =IF(OR(AS9=0,AT9=0,AV9=0),0,100*((AU9/AS9)/(AV9/AT9)-1))

Sheet Entity Inputs
A1: Group | B1: Entity | C1: Month | D1: Days in month | E1: Calendar hours (h) | F1: Planned operating hours (h) | G1: Run hours (h) | H1: Unplanned downtime (h) | I1: Ideal output (t) | J1: Installed capacity (t) | K1: Planned production (t) | L1: Gross output (t) | M1: Good output (t) | N1: Feed input (t) | O1: Valuable content in feed (t) | P1: Valuable content recovered (t) | Q1: Production lost to downtime (t) | R1: Breakdowns (count) | S1: Repair hours (h) | T1: Preventive maintenance scheduled (count) | U1: Preventive maintenance completed (count) | V1: Variable cost (₹ thousand) | W1: Fuel cost (₹ thousand) | X1: Fixed cost (₹ thousand) | Y1: Water used (m³) | Z1: Emissions (t CO2e) | AA1: Energy used (GJ) | AB1: Production at risk (t) | AC1: Critical plant alerts (count) | AD1: Hours worked (h) | AE1: Recordable injuries (count) | AF1: Severity incidents (count) | AG1: Near misses (count) | AH1: Critical safety incidents (count) | AI1: Environmental excursions (count) | AJ1: Environmental violations (count) | AK1: Open EHS corrective actions (count) | AL1: Overdue EHS corrective actions (count) | AM1: EHS investigations due (count) | AN1: EHS investigations completed (count) | AO1: Critical materials at risk (count) | AP1: Dispatches (count) | AQ1: Delayed dispatches (count) | AR1: Days to permit expiry (days) | AS1: Sales volume (t) | AT1: Planned sales volume (t) | AU1: Revenue (₹ thousand) | AV1: Planned revenue (₹ thousand) | AW1: Power cost, part of variable cost (₹ thousand) | AX1: Depreciation and amortisation (₹ thousand) | AY1: Purchase-order lines due (count) | AZ1: Purchase-order lines delivered on time (count) | BA1: Quantity ordered from suppliers (t) | BB1: Quantity received (t) | BC1: Quantity rejected on quality (t) | BD1: Planned lead time, all deliveries (days) | BE1: Actual lead time, all deliveries (days) | BF1: Supplier spend (₹ thousand) | BG1: Spend with single-source suppliers (₹ thousand) | BH1: Supplier EHS incidents (count) | BI1: Regulatory filings pending (count) | BJ1: Regulatory deadlines in next 30 days (count) | BK1: Licences expiring in next 12 months (count) | BL1: Regulatory obligations due in next 30 days (count) | BM1: Regulatory obligations overdue (count) | BN1: Open regulatory actions (count) | BO1: Overdue compliance actions (count) | BP1: Regulatory breaches in the month (count) | BQ1: Events that trigger a disclosure clock (count) | BR1: EHS escalation clocks running (count) | BS1: Days until production plan is breached, forecast (days; 99 = not expected) | BT1: Planned production next month (t) | BU1: Forecast good output next month (t) | BV1: Forecast uncertainty next month (variance, t²) | BW1: Ideal output next month (t) | BX1: Forecast production lost to downtime next month (t) | BY1: Overheads, SG&A (₹ thousand) | BZ1: Tax paid (₹ thousand) | CA1: Capital employed, month end (₹ thousand) | CB1: Gross debt, month end (₹ thousand) | CC1: Cash, month end (₹ thousand) | CD1: Undrawn committed facilities (₹ thousand) | CE1: Debt service in the month (₹ thousand) | CF1: Debt maturing in next 12 months (₹ thousand) | CG1: Floating-rate debt (₹ thousand) | CH1: EBITDA as reported in the Board pack (₹ thousand) | CI1: Revenue in the flash report (₹ thousand) | CJ1: Trade receivables, month end (₹ thousand) | CK1: Trade payables, month end (₹ thousand) | CL1: Inventory, month end (₹ thousand) | CM1: Cash collected from customers (₹ thousand) | CN1: Cash released by working-capital actions (₹ thousand) | CO1: Cash due to be upstreamed to Group, next 30 days (₹ thousand) | CP1: Of which covered by available cash (₹ thousand) | CQ1: Invoices collected (count) | CR1: Days taken to collect, all invoices (days) | CS1: Agreed payment terms, all invoices (days) | CT1: Customers more than 30 days overdue (count) | CU1: Forecast EBITDA, rest of year (₹ thousand) | CV1: Planned EBITDA, rest of year (₹ thousand) | CW1: Forecast net cash flow, next 90 days (₹ thousand) | CX1: Forecast net debt at quarter end (₹ thousand) | CY1: Forecast EBITDA, 12 months to quarter end (₹ thousand) | CZ1: Foreign-currency exposure, gross (₹ thousand) | DA1: Foreign-currency exposure hedged (₹ thousand) | DB1: USD exposure, gross (₹ thousand) | DC1: USD exposure hedged (₹ thousand) | DD1: Change in value of hedges (₹ thousand) | DE1: Change in value of hedged items (₹ thousand) | DF1: Forecast foreign-currency flows, next 6 months (₹ thousand) | DG1: Of which hedged (₹ thousand) | DH1: Approved capex budget, full year (₹ thousand) | DI1: Capex committed to date (₹ thousand) | DJ1: Capex spent in the month (₹ thousand) | DK1: Capex work completed, valued at budget (₹ thousand) | DL1: Budget of capex projects at risk (₹ thousand) | DM1: Capex projects on track (count) | DN1: Capex projects at risk (count) | DO1: Capex projects off track (count) | DP1: Capex projects delayed (count) | DQ1: Contractor milestones due (count) | DR1: Contractor days late, all milestones (days) | DS1: Transformation initiatives on track (count) | DT1: Transformation initiatives at risk (count) | DU1: Transformation initiatives delayed (count) | DV1: Transformation milestones in plan (count) | DW1: Transformation milestones completed (count) | DX1: Programme benefits planned in the month (₹ thousand) | DY1: Programme benefits delivered in the month (₹ thousand) | DZ1: EBITDA benefit delivered (₹ thousand) | EA1: Cash benefit delivered (₹ thousand) | EB1: Cost savings delivered (₹ thousand) | EC1: Active supply contracts (count) | ED1: Contracts fully compliant (count) | EE1: Contracts expiring in next 90 days (count) | EF1: Suppliers not meeting EHS requirements (count) | EG1: Critical single-source suppliers (count) | EH1: Control failures (count) | EI1: High-severity control failures (count) | EJ1: Assurance reviews planned (count) | EK1: Assurance reviews completed (count) | EL1: Policy exceptions (count) | EM1: Unauthorised vendor uses (count) | EN1: Segregation-of-duties exceptions (count) | EO1: Unauthorised access events (count) | EP1: Data-sharing exceptions (count) | EQ1: Manual operational or system overrides (count) | ER1: Certification approvals past due date (count) | ES1: KPI values overridden (count) | ET1: Recurring data-quality issues (count) | EU1: Open audit findings (count) | EV1: Overdue assurance actions (count) | EW1: Repeat audit findings (count) | EX1: Leadership KPIs affected by open findings (count) | EY1: Evidence items required (count) | EZ1: Evidence items complete (count) | FA1: Audit findings closed in the month (count) | FB1: Days taken to close those findings (days) | FC1: Leadership KPI values reported (count) | FD1: Of which certified (count) | FE1: Of which inside the certification process (count) | FF1: Certifications overdue (count) | FG1: Open reconciliation breaks (count) | FH1: Material reconciliation breaks (count) | FI1: Records loaded to the data lake (count) | FJ1: Records reconciled to source (count) | FK1: Flash report lines (count) | FL1: Flash lines matching MIS (count) | FM1: Open critical alerts (count) | FN1: Alerts with no accepted owner (count) | FO1: Overdue actions (count) | FP1: Alerts resolved in the month (count) | FQ1: Days taken to resolve those alerts (days) | FR1: Escalations closed in the month (count) | FS1: Repeat issues raised in the month (count) | FT1: Root causes identified (count) | FU1: Root causes eliminated (count)
A2: group | B2: entity | C2: period | D2: days | E2: calendar_hours | F2: planned_op_hours | G2: run_hours | H2: unplanned_downtime_hours | I2: ideal_output_t | J2: installed_capacity_t | K2: planned_production_t | L2: gross_output_t | M2: good_output_t | N2: feed_input_t | O2: feed_contained_t | P2: recovered_contained_t | Q2: prod_loss_downtime_t | R2: failures | S2: repair_hours | T2: pm_scheduled | U2: pm_completed | V2: variable_cost_k | W2: fuel_cost_k | X2: fixed_cost_k | Y2: water_m3 | Z2: emissions_tco2e | AA2: energy_gj | AB2: production_at_risk_t | AC2: critical_plant_alerts | AD2: hours_worked | AE2: recordable_injuries | AF2: severity_incidents | AG2: near_misses | AH2: critical_safety_incidents | AI2: env_excursions | AJ2: env_violations | AK2: ehs_ca_open | AL2: ehs_ca_overdue | AM2: investigations_due | AN2: investigations_completed | AO2: critical_material_risks | AP2: dispatches_total | AQ2: dispatches_delayed | AR2: permit_days_to_expiry | AS2: sales_t | AT2: planned_sales_t | AU2: revenue_k | AV2: planned_revenue_k | AW2: power_cost_k | AX2: depreciation_k | AY2: po_lines_due | AZ2: po_lines_on_time | BA2: qty_ordered_t | BB2: qty_received_t | BC2: qty_rejected_t | BD2: lead_time_planned_days | BE2: lead_time_actual_days | BF2: supplier_spend_k | BG2: single_source_spend_k | BH2: supplier_ehs_incidents | BI2: pending_filings | BJ2: reg_deadlines_30d | BK2: licences_expiring_12m | BL2: reg_obligations_due_30d | BM2: reg_obligations_overdue | BN2: reg_actions_open | BO2: compliance_actions_overdue | BP2: reg_breaches | BQ2: disclosure_events_open | BR2: ehs_escalation_clocks | BS2: days_to_breach | BT2: planned_production_next_t | BU2: forecast_good_next_t | BV2: forecast_good_var_next | BW2: ideal_output_next_t | BX2: forecast_downtime_loss_next_t | BY2: overhead_k | BZ2: tax_paid_k | CA2: capital_employed_k | CB2: gross_debt_k | CC2: cash_k | CD2: undrawn_facilities_k | CE2: debt_service_k | CF2: debt_maturing_12m_k | CG2: floating_rate_debt_k | CH2: board_ebitda_k | CI2: flash_revenue_k | CJ2: receivables_k | CK2: payables_k | CL2: inventory_k | CM2: collections_k | CN2: cash_released_k | CO2: upstream_due_k | CP2: upstream_covered_k | CQ2: invoices_collected | CR2: collection_days | CS2: terms_days | CT2: customers_overdue | CU2: forecast_ebitda_rest_k | CV2: planned_ebitda_rest_k | CW2: forecast_net_cash_flow_90d_k | CX2: forecast_net_debt_k | CY2: forecast_ebitda_ltm_k | CZ2: fx_exposure_k | DA2: fx_hedged_k | DB2: usd_exposure_k | DC2: usd_hedged_k | DD2: hedge_value_change_k | DE2: hedged_item_value_change_k | DF2: fx_flows_6m_k | DG2: fx_hedged_6m_k | DH2: capex_budget_k | DI2: capex_committed_k | DJ2: capex_spend_k | DK2: capex_earned_value_k | DL2: capex_at_risk_k | DM2: projects_on_track | DN2: projects_at_risk | DO2: projects_off_track | DP2: projects_delayed | DQ2: contractor_milestones_due | DR2: contractor_days_late | DS2: initiatives_on_track | DT2: initiatives_at_risk | DU2: initiatives_delayed | DV2: milestones_total | DW2: milestones_done | DX2: benefits_planned_k | DY2: benefits_delivered_k | DZ2: ebitda_benefit_k | EA2: cash_benefit_k | EB2: cost_savings_k | EC2: contracts_total | ED2: contracts_compliant | EE2: contracts_expiring_90d | EF2: supplier_ehs_noncompliance | EG2: single_source_suppliers | EH2: control_failures | EI2: control_failures_high | EJ2: assurance_reviews_planned | EK2: assurance_reviews_done | EL2: policy_exceptions | EM2: unauthorized_vendor_uses | EN2: sod_exceptions | EO2: unauthorized_access_events | EP2: data_sharing_exceptions | EQ2: manual_overrides | ER2: cert_approvals_ageing | ES2: kpi_overrides | ET2: dq_issues_recurring | EU2: audit_findings_open | EV2: assurance_actions_overdue | EW2: repeat_findings | EX2: leadership_kpis_affected | EY2: evidence_required | EZ2: evidence_complete | FA2: findings_closed | FB2: finding_closure_days | FC2: kpis_leadership | FD2: kpis_certified | FE2: kpis_in_scope | FF2: certifications_overdue | FG2: recon_breaks_open | FH2: recon_breaks_material | FI2: lake_records_loaded | FJ2: lake_records_reconciled | FK2: mis_lines_total | FL2: mis_lines_matched | FM2: critical_alerts_open | FN2: alerts_unowned | FO2: actions_overdue | FP2: alerts_resolved | FQ2: alert_resolution_days | FR2: escalations_closed | FS2: repeat_issues | FT2: root_causes_identified | FU2: root_causes_eliminated
E3: Sum of the entity's 3 plants (Plant Inputs sheet) | F3: Sum of the entity's 3 plants (Plant Inputs sheet) | G3: Sum of the entity's 3 plants (Plant Inputs sheet) | H3: Sum of the entity's 3 plants (Plant Inputs sheet) | I3: Sum of the entity's 3 plants (Plant Inputs sheet) | J3: Sum of the entity's 3 plants (Plant Inputs sheet) | K3: Sum of the entity's 3 plants (Plant Inputs sheet) | L3: Sum of the entity's 3 plants (Plant Inputs sheet) | M3: Sum of the entity's 3 plants (Plant Inputs sheet) | N3: Sum of the entity's 3 plants (Plant Inputs sheet) | O3: Sum of the entity's 3 plants (Plant Inputs sheet) | P3: Sum of the entity's 3 plants (Plant Inputs sheet) | Q3: Sum of the entity's 3 plants (Plant Inputs sheet) | R3: Sum of the entity's 3 plants (Plant Inputs sheet) | S3: Sum of the entity's 3 plants (Plant Inputs sheet) | T3: Sum of the entity's 3 plants (Plant Inputs sheet) | U3: Sum of the entity's 3 plants (Plant Inputs sheet) | V3: Sum of the entity's 3 plants (Plant Inputs sheet) | W3: Sum of the entity's 3 plants (Plant Inputs sheet) | X3: Sum of the entity's 3 plants (Plant Inputs sheet) | Y3: Sum of the entity's 3 plants (Plant Inputs sheet) | Z3: Sum of the entity's 3 plants (Plant Inputs sheet) | AA3: Sum of the entity's 3 plants (Plant Inputs sheet) | AB3: Sum of the entity's 3 plants (Plant Inputs sheet) | AC3: Sum of the entity's 3 plants (Plant Inputs sheet) | AD3: Sum of the entity's 3 plants (Plant Inputs sheet) | AE3: Sum of the entity's 3 plants (Plant Inputs sheet) | AF3: Sum of the entity's 3 plants (Plant Inputs sheet) | AG3: Sum of the entity's 3 plants (Plant Inputs sheet) | AH3: Sum of the entity's 3 plants (Plant Inputs sheet) | AI3: Sum of the entity's 3 plants (Plant Inputs sheet) | AJ3: Sum of the entity's 3 plants (Plant Inputs sheet) | AK3: Sum of the entity's 3 plants (Plant Inputs sheet) | AL3: Sum of the entity's 3 plants (Plant Inputs sheet) | AM3: Sum of the entity's 3 plants (Plant Inputs sheet) | AN3: Sum of the entity's 3 plants (Plant Inputs sheet) | AO3: Sum of the entity's 3 plants (Plant Inputs sheet) | AP3: Sum of the entity's 3 plants (Plant Inputs sheet) | AQ3: Sum of the entity's 3 plants (Plant Inputs sheet) | AR3: Lowest of the entity's 3 plants (Plant Inputs sheet) | AS3: Sum of the entity's 3 plants (Plant Inputs sheet) | AT3: Sum of the entity's 3 plants (Plant Inputs sheet) | AU3: Sum of the entity's 3 plants (Plant Inputs sheet) | AV3: Sum of the entity's 3 plants (Plant Inputs sheet) | AW3: Sum of the entity's 3 plants (Plant Inputs sheet) | AX3: Sum of the entity's 3 plants (Plant Inputs sheet) | AY3: Sum of the entity's 3 plants (Plant Inputs sheet) | AZ3: Sum of the entity's 3 plants (Plant Inputs sheet) | BA3: Sum of the entity's 3 plants (Plant Inputs sheet) | BB3: Sum of the entity's 3 plants (Plant Inputs sheet) | BC3: Sum of the entity's 3 plants (Plant Inputs sheet) | BD3: Sum of the entity's 3 plants (Plant Inputs sheet) | BE3: Sum of the entity's 3 plants (Plant Inputs sheet) | BF3: Sum of the entity's 3 plants (Plant Inputs sheet) | BG3: Sum of the entity's 3 plants (Plant Inputs sheet) | BH3: Sum of the entity's 3 plants (Plant Inputs sheet) | BI3: Sum of the entity's 3 plants (Plant Inputs sheet) | BJ3: Sum of the entity's 3 plants (Plant Inputs sheet) | BK3: Sum of the entity's 3 plants (Plant Inputs sheet) | BL3: Sum of the entity's 3 plants (Plant Inputs sheet) | BM3: Sum of the entity's 3 plants (Plant Inputs sheet) | BN3: Sum of the entity's 3 plants (Plant Inputs sheet) | BO3: Sum of the entity's 3 plants (Plant Inputs sheet) | BP3: Sum of the entity's 3 plants (Plant Inputs sheet) | BQ3: Sum of the entity's 3 plants (Plant Inputs sheet) | BR3: Sum of the entity's 3 plants (Plant Inputs sheet) | BS3: Lowest of the entity's 3 plants (Plant Inputs sheet) | BT3: Sum of the entity's 3 plants (Plant Inputs sheet) | BU3: Sum of the entity's 3 plants (Plant Inputs sheet) | BV3: Sum of the entity's 3 plants (Plant Inputs sheet) | BW3: Sum of the entity's 3 plants (Plant Inputs sheet) | BX3: Sum of the entity's 3 plants (Plant Inputs sheet) | BY3: Entity input (only exists at entity level) | BZ3: Entity input (only exists at entity level) | CA3: Entity input (only exists at entity level) | CB3: Entity input (only exists at entity level) | CC3: Entity input (only exists at entity level) | CD3: Entity input (only exists at entity level) | CE3: Entity input (only exists at entity level) | CF3: Entity input (only exists at entity level) | CG3: Entity input (only exists at entity level) | CH3: Entity input (only exists at entity level) | CI3: Entity input (only exists at entity level) | CJ3: Entity input (only exists at entity level) | CK3: Entity input (only exists at entity level) | CL3: Entity input (only exists at entity level) | CM3: Entity input (only exists at entity level) | CN3: Entity input (only exists at entity level) | CO3: Entity input (only exists at entity level) | CP3: Entity input (only exists at entity level) | CQ3: Entity input (only exists at entity level) | CR3: Entity input (only exists at entity level) | CS3: Entity input (only exists at entity level) | CT3: Entity input (only exists at entity level) | CU3: Entity input (only exists at entity level) | CV3: Entity input (only exists at entity level) | CW3: Entity input (only exists at entity level) | CX3: Entity input (only exists at entity level) | CY3: Entity input (only exists at entity level) | CZ3: Entity input (only exists at entity level) | DA3: Entity input (only exists at entity level) | DB3: Entity input (only exists at entity level) | DC3: Entity input (only exists at entity level) | DD3: Entity input (only exists at entity level) | DE3: Entity input (only exists at entity level) | DF3: Entity input (only exists at entity level) | DG3: Entity input (only exists at entity level) | DH3: Entity input (only exists at entity level) | DI3: Entity input (only exists at entity level) | DJ3: Entity input (only exists at entity level) | DK3: Entity input (only exists at entity level) | DL3: Entity input (only exists at entity level) | DM3: Entity input (only exists at entity level) | DN3: Entity input (only exists at entity level) | DO3: Entity input (only exists at entity level) | DP3: Entity input (only exists at entity level) | DQ3: Entity input (only exists at entity level) | DR3: Entity input (only exists at entity level) | DS3: Entity input (only exists at entity level) | DT3: Entity input (only exists at entity level) | DU3: Entity input (only exists at entity level) | DV3: Entity input (only exists at entity level) | DW3: Entity input (only exists at entity level) | DX3: Entity input (only exists at entity level) | DY3: Entity input (only exists at entity level) | DZ3: Entity input (only exists at entity level) | EA3: Entity input (only exists at entity level) | EB3: Entity input (only exists at entity level) | EC3: Entity input (only exists at entity level) | ED3: Entity input (only exists at entity level) | EE3: Entity input (only exists at entity level) | EF3: Entity input (only exists at entity level) | EG3: Entity input (only exists at entity level) | EH3: Entity input (only exists at entity level) | EI3: Entity input (only exists at entity level) | EJ3: Entity input (only exists at entity level) | EK3: Entity input (only exists at entity level) | EL3: Entity input (only exists at entity level) | EM3: Entity input (only exists at entity level) | EN3: Entity input (only exists at entity level) | EO3: Entity input (only exists at entity level) | EP3: Entity input (only exists at entity level) | EQ3: Entity input (only exists at entity level) | ER3: Entity input (only exists at entity level) | ES3: Entity input (only exists at entity level) | ET3: Entity input (only exists at entity level) | EU3: Entity input (only exists at entity level) | EV3: Entity input (only exists at entity level) | EW3: Entity input (only exists at entity level) | EX3: Entity input (only exists at entity level) | EY3: Entity input (only exists at entity level) | EZ3: Entity input (only exists at entity level) | FA3: Entity input (only exists at entity level) | FB3: Entity input (only exists at entity level) | FC3: Entity input (only exists at entity level) | FD3: Entity input (only exists at entity level) | FE3: Entity input (only exists at entity level) | FF3: Entity input (only exists at entity level) | FG3: Entity input (only exists at entity level) | FH3: Entity input (only exists at entity level) | FI3: Entity input (only exists at entity level) | FJ3: Entity input (only exists at entity level) | FK3: Entity input (only exists at entity level) | FL3: Entity input (only exists at entity level) | FM3: Entity input (only exists at entity level) | FN3: Entity input (only exists at entity level) | FO3: Entity input (only exists at entity level) | FP3: Entity input (only exists at entity level) | FQ3: Entity input (only exists at entity level) | FR3: Entity input (only exists at entity level) | FS3: Entity input (only exists at entity level) | FT3: Entity input (only exists at entity level) | FU3: Entity input (only exists at entity level)
A4: Group | B4: Entity A1 | C4: 2026-04 | D4: 30 | E4: =SUM('Plant Inputs'!F4,'Plant Inputs'!F10,'Plant Inputs'!F16) | F4: =SUM('Plant Inputs'!G4,'Plant Inputs'!G10,'Plant Inputs'!G16) | G4: =SUM('Plant Inputs'!H4,'Plant Inputs'!H10,'Plant Inputs'!H16) | H4: =SUM('Plant Inputs'!I4,'Plant Inputs'!I10,'Plant Inputs'!I16) | I4: =SUM('Plant Inputs'!J4,'Plant Inputs'!J10,'Plant Inputs'!J16) | J4: =SUM('Plant Inputs'!K4,'Plant Inputs'!K10,'Plant Inputs'!K16) | K4: =SUM('Plant Inputs'!L4,'Plant Inputs'!L10,'Plant Inputs'!L16) | L4: =SUM('Plant Inputs'!M4,'Plant Inputs'!M10,'Plant Inputs'!M16) | ... AQ4: =SUM('Plant Inputs'!AR4,'Plant Inputs'!AR10,'Plant Inputs'!AR16) | AR4: =MIN('Plant Inputs'!AS4,'Plant Inputs'!AS10,'Plant Inputs'!AS16) | AS4: =SUM('Plant Inputs'!AT4,'Plant Inputs'!AT10,'Plant Inputs'!AT16) | AT4: =SUM('Plant Inputs'!AU4,'Plant Inputs'!AU10,'Plant Inputs'!AU16) | AU4: =SUM('Plant Inputs'!AV4,'Plant Inputs'!AV10,'Plant Inputs'!AV16) | AV4: =SUM('Plant Inputs'!AW4,'Plant Inputs'!AW10,'Plant Inputs'!AW16) | AW4: =SUM('Plant Inputs'!AX4,'Plant Inputs'!AX10,'Plant Inputs'!AX16) | AX4: =SUM('Plant Inputs'!AY4,'Plant Inputs'!AY10,'Plant Inputs'!AY16) | AY4: =SUM('Plant Inputs'!AZ4,'Plant Inputs'!AZ10,'Plant Inputs'!AZ16) | AZ4: =SUM('Plant Inputs'!BA4,'Plant Inputs'!BA10,'Plant Inputs'!BA16) | ... BR4: =SUM('Plant Inputs'!BS4,'Plant Inputs'!BS10,'Plant Inputs'!BS16) | BS4: =MIN('Plant Inputs'!BT4,'Plant Inputs'!BT10,'Plant Inputs'!BT16) | BT4: =SUM('Plant Inputs'!BU4,'Plant Inputs'!BU10,'Plant Inputs'!BU16) | BU4: =SUM('Plant Inputs'!BV4,'Plant Inputs'!BV10,'Plant Inputs'!BV16) | BV4: =SUM('Plant Inputs'!BW4,'Plant Inputs'!BW10,'Plant Inputs'!BW16) | BW4: =SUM('Plant Inputs'!BX4,'Plant Inputs'!BX10,'Plant Inputs'!BX16) | BX4: =SUM('Plant Inputs'!BY4,'Plant Inputs'!BY10,'Plant Inputs'!BY16) | BY4: 54938.6 | BZ4: 35929.2 | CA4: 10800000 | CB4: 4736181 | CC4: 936181 | CD4: 436986.6 | CE4: 39900 | CF4: 442623.4 | CG4: 1357977.9 | CH4: 167684.4 | CI4: 1183542.5 | CJ4: 2022544.1 | CK4: 1234856.8 | CL4: 1354000.8 | CM4: 1181957.8 | CN4: 519.8 | CO4: 115844.2 | CP4: 115844.2 | CQ4: 418 | CR4: 18974 | CS4: 18810 | CT4: 0 | CU4: 997106.1 | CV4: 1011641.5 | CW4: 195977 | CX4: 3747391.4 | CY4: 1976093.2 | CZ4: 425331 | DA4: 314182 | DB4: 339270.5 | DC4: 248759 | DD4: 5649.1 | DE4: 6321.3 | DF4: 2572845.7 | DG4: 1994270.3 | DH4: 1000000 | DI4: 449046.9 | DJ4: 76777.1 | DK4: 380000 | DL4: 22271.5 | DM4: 5 | DN4: 1 | DO4: 0 | DP4: 0 | DQ4: 7 | DR4: 21 | DS4: 5 | DT4: 2 | DU4: 1 | DV4: 60 | DW4: 18 | DX4: 4834.8 | DY4: 3489.6 | DZ4: 987.8 | EA4: 352.3 | EB4: 600.2 | EC4: 72 | ED4: 69 | EE4: 1 | EF4: 0 | EG4: 2 | EH4: 1 | EI4: 0 | EJ4: 1 | EK4: 1 | EL4: 0 | EM4: 0 | EN4: 0 | EO4: 0 | EP4: 0 | EQ4: 1 | ER4: 1 | ES4: 0 | ET4: 1 | EU4: 2 | EV4: 0 | EW4: 0 | EX4: 0 | EY4: 50 | EZ4: 43 | FA4: 2 | FB4: 55 | FC4: 28 | FD4: 23 | FE4: 26 | FF4: 0 | FG4: 1 | FH4: 0 | FI4: 482362 | FJ4: 479530 | FK4: 400 | FL4: 381 | FM4: 0 | FN4: 0 | FO4: 0 | FP4: 6 | FQ4: 17.8 | FR4: 4 | FS4: 0 | FT4: 0 | FU4: 0
A5: Group | B5: Entity A1 | C5: 2026-05 | D5: 31 | E5: =SUM('Plant Inputs'!F5,'Plant Inputs'!F11,'Plant Inputs'!F17) | F5: =SUM('Plant Inputs'!G5,'Plant Inputs'!G11,'Plant Inputs'!G17) | G5: =SUM('Plant Inputs'!H5,'Plant Inputs'!H11,'Plant Inputs'!H17) | H5: =SUM('Plant Inputs'!I5,'Plant Inputs'!I11,'Plant Inputs'!I17) | I5: =SUM('Plant Inputs'!J5,'Plant Inputs'!J11,'Plant Inputs'!J17) | J5: =SUM('Plant Inputs'!K5,'Plant Inputs'!K11,'Plant Inputs'!K17) | K5: =SUM('Plant Inputs'!L5,'Plant Inputs'!L11,'Plant Inputs'!L17) | L5: =SUM('Plant Inputs'!M5,'Plant Inputs'!M11,'Plant Inputs'!M17) | ... AQ5: =SUM('Plant Inputs'!AR5,'Plant Inputs'!AR11,'Plant Inputs'!AR17) | AR5: =MIN('Plant Inputs'!AS5,'Plant Inputs'!AS11,'Plant Inputs'!AS17) | AS5: =SUM('Plant Inputs'!AT5,'Plant Inputs'!AT11,'Plant Inputs'!AT17) | AT5: =SUM('Plant Inputs'!AU5,'Plant Inputs'!AU11,'Plant Inputs'!AU17) | AU5: =SUM('Plant Inputs'!AV5,'Plant Inputs'!AV11,'Plant Inputs'!AV17) | AV5: =SUM('Plant Inputs'!AW5,'Plant Inputs'!AW11,'Plant Inputs'!AW17) | AW5: =SUM('Plant Inputs'!AX5,'Plant Inputs'!AX11,'Plant Inputs'!AX17) | AX5: =SUM('Plant Inputs'!AY5,'Plant Inputs'!AY11,'Plant Inputs'!AY17) | AY5: =SUM('Plant Inputs'!AZ5,'Plant Inputs'!AZ11,'Plant Inputs'!AZ17) | AZ5: =SUM('Plant Inputs'!BA5,'Plant Inputs'!BA11,'Plant Inputs'!BA17) | ... BR5: =SUM('Plant Inputs'!BS5,'Plant Inputs'!BS11,'Plant Inputs'!BS17) | BS5: =MIN('Plant Inputs'!BT5,'Plant Inputs'!BT11,'Plant Inputs'!BT17) | BT5: =SUM('Plant Inputs'!BU5,'Plant Inputs'!BU11,'Plant Inputs'!BU17) | BU5: =SUM('Plant Inputs'!BV5,'Plant Inputs'!BV11,'Plant Inputs'!BV17) | BV5: =SUM('Plant Inputs'!BW5,'Plant Inputs'!BW11,'Plant Inputs'!BW17) | BW5: =SUM('Plant Inputs'!BX5,'Plant Inputs'!BX11,'Plant Inputs'!BX17) | BX5: =SUM('Plant Inputs'!BY5,'Plant Inputs'!BY11,'Plant Inputs'!BY17) | BY5: 50704.9 | BZ5: 14276.1 | CA5: 10843200 | CB5: 4689727.1 | CC5: 927727.1 | CD5: 438182.1 | CE5: 39501 | CF5: 484600.2 | CG5: 1326721.5 | CH5: 67821.9 | CI5: 1128801.3 | CJ5: 1918893.1 | CK5: 1294064.9 | CL5: 1295301.1 | CM5: 1117881.8 | CN5: 812.1 | CO5: 123248 | CP5: 123248 | CQ5: 382 | CR5: 17264 | CS5: 17190 | CT5: 0 | CU5: 403490.1 | CV5: 409969.6 | CW5: 76015 | CX5: 3729497.8 | CY5: 797457 | CZ5: 402268.2 | DA5: 277847.9 | DB5: 324638.2 | DC5: 229566.1 | DD5: 3941.5 | DE5: 4320.5 | DF5: 2519902.8 | DG5: 1969944 | DH5: 1000000 | DI5: 500855.7 | DJ5: 75177.6 | DK5: 422000 | DL5: 25527.6 | DM5: 5 | DN5: 1 | DO5: 0 | DP5: 0 | DQ5: 6 | DR5: 17 | DS5: 5 | DT5: 2 | DU5: 1 | DV5: 60 | DW5: 21 | DX5: 5163.3 | DY5: 3608.4 | DZ5: 951.1 | EA5: 446.1 | EB5: 650.5 | EC5: 72 | ED5: 68 | EE5: 2 | EF5: 0 | EG5: 2 | EH5: 0 | EI5: 0 | EJ5: 1 | EK5: 0 | EL5: 0 | EM5: 0 | EN5: 0 | EO5: 0 | EP5: 0 | EQ5: 0 | ER5: 1 | ES5: 0 | ET5: 1 | EU5: 3 | EV5: 0 | EW5: 0 | EX5: 0 | EY5: 50 | EZ5: 43 | FA5: 3 | FB5: 85 | FC5: 28 | FD5: 23 | FE5: 26 | FF5: 0 | FG5: 1 | FH5: 0 | FI5: 488893 | FJ5: 485890 | FK5: 400 | FL5: 379 | FM5: 0 | FN5: 0 | FO5: 0 | FP5: 4 | FQ5: 11.6 | FR5: 3 | FS5: 0 | FT5: 0 | FU5: 0
A6: Group | B6: Entity A1 | C6: 2026-06 | D6: 30 | E6: =SUM('Plant Inputs'!F6,'Plant Inputs'!F12,'Plant Inputs'!F18) | F6: =SUM('Plant Inputs'!G6,'Plant Inputs'!G12,'Plant Inputs'!G18) | G6: =SUM('Plant Inputs'!H6,'Plant Inputs'!H12,'Plant Inputs'!H18) | H6: =SUM('Plant Inputs'!I6,'Plant Inputs'!I12,'Plant Inputs'!I18) | I6: =SUM('Plant Inputs'!J6,'Plant Inputs'!J12,'Plant Inputs'!J18) | J6: =SUM('Plant Inputs'!K6,'Plant Inputs'!K12,'Plant Inputs'!K18) | K6: =SUM('Plant Inputs'!L6,'Plant Inputs'!L12,'Plant Inputs'!L18) | L6: =SUM('Plant Inputs'!M6,'Plant Inputs'!M12,'Plant Inputs'!M18) | ... AQ6: =SUM('Plant Inputs'!AR6,'Plant Inputs'!AR12,'Plant Inputs'!AR18) | AR6: =MIN('Plant Inputs'!AS6,'Plant Inputs'!AS12,'Plant Inputs'!AS18) | AS6: =SUM('Plant Inputs'!AT6,'Plant Inputs'!AT12,'Plant Inputs'!AT18) | AT6: =SUM('Plant Inputs'!AU6,'Plant Inputs'!AU12,'Plant Inputs'!AU18) | AU6: =SUM('Plant Inputs'!AV6,'Plant Inputs'!AV12,'Plant Inputs'!AV18) | AV6: =SUM('Plant Inputs'!AW6,'Plant Inputs'!AW12,'Plant Inputs'!AW18) | AW6: =SUM('Plant Inputs'!AX6,'Plant Inputs'!AX12,'Plant Inputs'!AX18) | AX6: =SUM('Plant Inputs'!AY6,'Plant Inputs'!AY12,'Plant Inputs'!AY18) | AY6: =SUM('Plant Inputs'!AZ6,'Plant Inputs'!AZ12,'Plant Inputs'!AZ18) | AZ6: =SUM('Plant Inputs'!BA6,'Plant Inputs'!BA12,'Plant Inputs'!BA18) | ... BR6: =SUM('Plant Inputs'!BS6,'Plant Inputs'!BS12,'Plant Inputs'!BS18) | BS6: =MIN('Plant Inputs'!BT6,'Plant Inputs'!BT12,'Plant Inputs'!BT18) | BT6: =SUM('Plant Inputs'!BU6,'Plant Inputs'!BU12,'Plant Inputs'!BU18) | BU6: =SUM('Plant Inputs'!BV6,'Plant Inputs'!BV12,'Plant Inputs'!BV18) | BV6: =SUM('Plant Inputs'!BW6,'Plant Inputs'!BW12,'Plant Inputs'!BW18) | BW6: =SUM('Plant Inputs'!BX6,'Plant Inputs'!BX12,'Plant Inputs'!BX18) | BX6: =SUM('Plant Inputs'!BY6,'Plant Inputs'!BY12,'Plant Inputs'!BY18) | BY6: 48811.1 | BZ6: 29278.7 | CA6: 10886400 | CB6: 4635169.6 | CC6: 911169.6 | CD6: 460112.3 | CE6: 39102 | CF6: 476219.3 | CG6: 1378110 | CH6: 133983.3 | CI6: 1126086 | CJ6: 1943165.8 | CK6: 1271185.4 | CL6: 1281353 | CM6: 1116529.3 | CN6: 735.6 | CO6: 117650.6 | CP6: 117650.6 | CQ6: 425 | CR6: 19112 | CS6: 19125 | CT6: 0 | CU6: 802788 | CV6: 808463.3 | CW6: 155641.9 | CX6: 3675892.6 | CY6: 1569788.9 | CZ6: 418805.1 | DA6: 306320.8 | DB6: 327500.7 | DC6: 240203.5 | DD6: 4261.9 | DE6: 4555.5 | DF6: 2534835.3 | DG6: 1925015.9 | DH6: 1000000 | DI6: 561019.6 | DJ6: 73628.5 | DK6: 464000 | DL6: 21951.6 | DM6: 5 | DN6: 1 | DO6: 0 | DP6: 0 | DQ6: 4 | DR6: 14 | DS6: 5 | DT6: 2 | DU6: 1 | DV6: 60 | DW6: 24 | DX6: 5112.3 | DY6: 3419.9 | DZ6: 1071.3 | EA6: 417.2 | EB6: 665.8 | EC6: 72 | ED6: 69 | EE6: 2 | EF6: 0 | EG6: 2 | EH6: 0 | EI6: 0 | EJ6: 0 | EK6: 0 | EL6: 0 | EM6: 0 | EN6: 0 | EO6: 0 | EP6: 0 | EQ6: 2 | ER6: 0 | ES6: 0 | ET6: 1 | EU6: 2 | EV6: 0 | EW6: 0 | EX6: 0 | EY6: 50 | EZ6: 43 | FA6: 1 | FB6: 30 | FC6: 28 | FD6: 23 | FE6: 26 | FF6: 0 | FG6: 1 | FH6: 0 | FI6: 488990 | FJ6: 485052 | FK6: 400 | FL6: 378 | FM6: 0 | FN6: 0 | FO6: 0 | FP6: 4 | FQ6: 11.7 | FR6: 4 | FS6: 1 | FT6: 1 | FU6: 1
A7: Group | B7: Entity A1 | C7: 2026-07 | D7: 31 | E7: =SUM('Plant Inputs'!F7,'Plant Inputs'!F13,'Plant Inputs'!F19) | F7: =SUM('Plant Inputs'!G7,'Plant Inputs'!G13,'Plant Inputs'!G19) | G7: =SUM('Plant Inputs'!H7,'Plant Inputs'!H13,'Plant Inputs'!H19) | H7: =SUM('Plant Inputs'!I7,'Plant Inputs'!I13,'Plant Inputs'!I19) | I7: =SUM('Plant Inputs'!J7,'Plant Inputs'!J13,'Plant Inputs'!J19) | J7: =SUM('Plant Inputs'!K7,'Plant Inputs'!K13,'Plant Inputs'!K19) | K7: =SUM('Plant Inputs'!L7,'Plant Inputs'!L13,'Plant Inputs'!L19) | L7: =SUM('Plant Inputs'!M7,'Plant Inputs'!M13,'Plant Inputs'!M19) | ... AQ7: =SUM('Plant Inputs'!AR7,'Plant Inputs'!AR13,'Plant Inputs'!AR19) | AR7: =MIN('Plant Inputs'!AS7,'Plant Inputs'!AS13,'Plant Inputs'!AS19) | AS7: =SUM('Plant Inputs'!AT7,'Plant Inputs'!AT13,'Plant Inputs'!AT19) | AT7: =SUM('Plant Inputs'!AU7,'Plant Inputs'!AU13,'Plant Inputs'!AU19) | AU7: =SUM('Plant Inputs'!AV7,'Plant Inputs'!AV13,'Plant Inputs'!AV19) | AV7: =SUM('Plant Inputs'!AW7,'Plant Inputs'!AW13,'Plant Inputs'!AW19) | AW7: =SUM('Plant Inputs'!AX7,'Plant Inputs'!AX13,'Plant Inputs'!AX19) | AX7: =SUM('Plant Inputs'!AY7,'Plant Inputs'!AY13,'Plant Inputs'!AY19) | AY7: =SUM('Plant Inputs'!AZ7,'Plant Inputs'!AZ13,'Plant Inputs'!AZ19) | AZ7: =SUM('Plant Inputs'!BA7,'Plant Inputs'!BA13,'Plant Inputs'!BA19) | ... BR7: =SUM('Plant Inputs'!BS7,'Plant Inputs'!BS13,'Plant Inputs'!BS19) | BS7: =MIN('Plant Inputs'!BT7,'Plant Inputs'!BT13,'Plant Inputs'!BT19) | BT7: =SUM('Plant Inputs'!BU7,'Plant Inputs'!BU13,'Plant Inputs'!BU19) | BU7: =SUM('Plant Inputs'!BV7,'Plant Inputs'!BV13,'Plant Inputs'!BV19) | BV7: =SUM('Plant Inputs'!BW7,'Plant Inputs'!BW13,'Plant Inputs'!BW19) | BW7: =SUM('Plant Inputs'!BX7,'Plant Inputs'!BX13,'Plant Inputs'!BX19) | BX7: =SUM('Plant Inputs'!BY7,'Plant Inputs'!BY13,'Plant Inputs'!BY19) | BY7: 54606.3 | BZ7: 39213.2 | CA7: 10929600 | CB7: 4608966.7 | CC7: 922966.7 | CD7: 458165.4 | CE7: 38703 | CF7: 484735.8 | CG7: 1328589.5 | CH7: 178047.3 | CI7: 1185026 | CJ7: 1960349 | CK7: 1201672 | CL7: 1233450.9 | CM7: 1188396 | CN7: 694.8 | CO7: 119061.7 | CP7: 119061.7 | CQ7: 438 | CR7: 19650 | CS7: 19710 | CT7: 0 | CU7: 1065509.6 | CV7: 1075543.1 | CW7: 172153.2 | CX7: 3675766.9 | CY7: 2119721.6 | CZ7: 446718.8 | DA7: 323811.5 | DB7: 364424.2 | DC7: 266166.7 | DD7: 6450.1 | DE7: 7325.1 | DF7: 2637874.2 | DG7: 2001983.7 | DH7: 1000000 | DI7: 608680.1 | DJ7: 80895.5 | DK7: 506000 | DL7: 24159.6 | DM7: 5 | DN7: 1 | DO7: 0 | DP7: 0 | DQ7: 6 | DR7: 17 | DS7: 5 | DT7: 2 | DU7: 1 | DV7: 60 | DW7: 27 | DX7: 5177.6 | DY7: 3634.4 | DZ7: 1084 | EA7: 415.8 | EB7: 690.3 | EC7: 72 | ED7: 68 | EE7: 2 | EF7: 0 | EG7: 2 | EH7: 1 | EI7: 0 | EJ7: 1 | EK7: 0 | EL7: 0 | EM7: 0 | EN7: 0 | EO7: 0 | EP7: 0 | EQ7: 1 | ER7: 1 | ES7: 0 | ET7: 1 | EU7: 2 | EV7: 0 | EW7: 0 | EX7: 0 | EY7: 50 | EZ7: 43 | FA7: 3 | FB7: 82 | FC7: 28 | FD7: 23 | FE7: 26 | FF7: 0 | FG7: 1 | FH7: 0 | FI7: 517040 | FJ7: 512116 | FK7: 400 | FL7: 380 | FM7: 0 | FN7: 0 | FO7: 0 | FP7: 4 | FQ7: 12 | FR7: 3 | FS7: 1 | FT7: 1 | FU7: 1
A8: Group | B8: Entity A1 | C8: 2026-08 | D8: 31 | E8: =SUM('Plant Inputs'!F8,'Plant Inputs'!F14,'Plant Inputs'!F20) | F8: =SUM('Plant Inputs'!G8,'Plant Inputs'!G14,'Plant Inputs'!G20) | G8: =SUM('Plant Inputs'!H8,'Plant Inputs'!H14,'Plant Inputs'!H20) | H8: =SUM('Plant Inputs'!I8,'Plant Inputs'!I14,'Plant Inputs'!I20) | I8: =SUM('Plant Inputs'!J8,'Plant Inputs'!J14,'Plant Inputs'!J20) | J8: =SUM('Plant Inputs'!K8,'Plant Inputs'!K14,'Plant Inputs'!K20) | K8: =SUM('Plant Inputs'!L8,'Plant Inputs'!L14,'Plant Inputs'!L20) | L8: =SUM('Plant Inputs'!M8,'Plant Inputs'!M14,'Plant Inputs'!M20) | ... AQ8: =SUM('Plant Inputs'!AR8,'Plant Inputs'!AR14,'Plant Inputs'!AR20) | AR8: =MIN('Plant Inputs'!AS8,'Plant Inputs'!AS14,'Plant Inputs'!AS20) | AS8: =SUM('Plant Inputs'!AT8,'Plant Inputs'!AT14,'Plant Inputs'!AT20) | AT8: =SUM('Plant Inputs'!AU8,'Plant Inputs'!AU14,'Plant Inputs'!AU20) | AU8: =SUM('Plant Inputs'!AV8,'Plant Inputs'!AV14,'Plant Inputs'!AV20) | AV8: =SUM('Plant Inputs'!AW8,'Plant Inputs'!AW14,'Plant Inputs'!AW20) | AW8: =SUM('Plant Inputs'!AX8,'Plant Inputs'!AX14,'Plant Inputs'!AX20) | AX8: =SUM('Plant Inputs'!AY8,'Plant Inputs'!AY14,'Plant Inputs'!AY20) | AY8: =SUM('Plant Inputs'!AZ8,'Plant Inputs'!AZ14,'Plant Inputs'!AZ20) | AZ8: =SUM('Plant Inputs'!BA8,'Plant Inputs'!BA14,'Plant Inputs'!BA20) | ... BR8: =SUM('Plant Inputs'!BS8,'Plant Inputs'!BS14,'Plant Inputs'!BS20) | BS8: =MIN('Plant Inputs'!BT8,'Plant Inputs'!BT14,'Plant Inputs'!BT20) | BT8: =SUM('Plant Inputs'!BU8,'Plant Inputs'!BU14,'Plant Inputs'!BU20) | BU8: =SUM('Plant Inputs'!BV8,'Plant Inputs'!BV14,'Plant Inputs'!BV20) | BV8: =SUM('Plant Inputs'!BW8,'Plant Inputs'!BW14,'Plant Inputs'!BW20) | BW8: =SUM('Plant Inputs'!BX8,'Plant Inputs'!BX14,'Plant Inputs'!BX20) | BX8: =SUM('Plant Inputs'!BY8,'Plant Inputs'!BY14,'Plant Inputs'!BY20) | BY8: 51744.4 | BZ8: 26325.4 | CA8: 10972800 | CB8: 4538500.4 | CC8: 890500.4 | CD8: 450000.3 | CE8: 38304 | CF8: 430017.2 | CG8: 1434553 | CH8: 141020.6 | CI8: 1178034.5 | CJ8: 1942517.4 | CK8: 1220348.1 | CL8: 1299238.7 | CM8: 1172897 | CN8: 595.6 | CO8: 111451.4 | CP8: 85831.1 | CQ8: 429 | CR8: 20245 | CS8: 19305 | CT8: 2 | CU8: 814011.1 | CV8: 844976.7 | CW8: 168030.4 | CX8: 3603080.9 | CY8: 1658464.7 | CZ8: 420833 | DA8: 289646.6 | DB8: 345045.2 | DC8: 254976 | DD8: 5930.1 | DE8: 6390.2 | DF8: 2577012.3 | DG8: 2005260.4 | DH8: 1000000 | DI8: 671475.8 | DJ8: 82465.6 | DK8: 548000 | DL8: 21559.1 | DM8: 5 | DN8: 1 | DO8: 0 | DP8: 0 | DQ8: 7 | DR8: 21 | DS8: 5 | DT8: 2 | DU8: 1 | DV8: 60 | DW8: 30 | DX8: 5059.6 | DY8: 3578 | DZ8: 1035 | EA8: 350.8 | EB8: 639.5 | EC8: 72 | ED8: 68 | EE8: 2 | EF8: 0 | EG8: 2 | EH8: 0 | EI8: 0 | EJ8: 1 | EK8: 1 | EL8: 1 | EM8: 0 | EN8: 0 | EO8: 0 | EP8: 0 | EQ8: 2 | ER8: 1 | ES8: 0 | ET8: 1 | EU8: 3 | EV8: 0 | EW8: 0 | EX8: 0 | EY8: 50 | EZ8: 43 | FA8: 2 | FB8: 60 | FC8: 28 | FD8: 23 | FE8: 26 | FF8: 0 | FG8: 1 | FH8: 1 | FI8: 489715 | FJ8: 486862 | FK8: 400 | FL8: 382 | FM8: 1 | FN8: 0 | FO8: 0 | FP8: 4 | FQ8: 12.2 | FR8: 3 | FS8: 1 | FT8: 1 | FU8: 1
A9: Group | B9: Entity A1 | C9: 2026-09 | D9: 30 | E9: =SUM('Plant Inputs'!F9,'Plant Inputs'!F15,'Plant Inputs'!F21) | F9: =SUM('Plant Inputs'!G9,'Plant Inputs'!G15,'Plant Inputs'!G21) | G9: =SUM('Plant Inputs'!H9,'Plant Inputs'!H15,'Plant Inputs'!H21) | H9: =SUM('Plant Inputs'!I9,'Plant Inputs'!I15,'Plant Inputs'!I21) | I9: =SUM('Plant Inputs'!J9,'Plant Inputs'!J15,'Plant Inputs'!J21) | J9: =SUM('Plant Inputs'!K9,'Plant Inputs'!K15,'Plant Inputs'!K21) | K9: =SUM('Plant Inputs'!L9,'Plant Inputs'!L15,'Plant Inputs'!L21) | L9: =SUM('Plant Inputs'!M9,'Plant Inputs'!M15,'Plant Inputs'!M21) | ... AQ9: =SUM('Plant Inputs'!AR9,'Plant Inputs'!AR15,'Plant Inputs'!AR21) | AR9: =MIN('Plant Inputs'!AS9,'Plant Inputs'!AS15,'Plant Inputs'!AS21) | AS9: =SUM('Plant Inputs'!AT9,'Plant Inputs'!AT15,'Plant Inputs'!AT21) | AT9: =SUM('Plant Inputs'!AU9,'Plant Inputs'!AU15,'Plant Inputs'!AU21) | AU9: =SUM('Plant Inputs'!AV9,'Plant Inputs'!AV15,'Plant Inputs'!AV21) | AV9: =SUM('Plant Inputs'!AW9,'Plant Inputs'!AW15,'Plant Inputs'!AW21) | AW9: =SUM('Plant Inputs'!AX9,'Plant Inputs'!AX15,'Plant Inputs'!AX21) | AX9: =SUM('Plant Inputs'!AY9,'Plant Inputs'!AY15,'Plant Inputs'!AY21) | AY9: =SUM('Plant Inputs'!AZ9,'Plant Inputs'!AZ15,'Plant Inputs'!AZ21) | AZ9: =SUM('Plant Inputs'!BA9,'Plant Inputs'!BA15,'Plant Inputs'!BA21) | ... BR9: =SUM('Plant Inputs'!BS9,'Plant Inputs'!BS15,'Plant Inputs'!BS21) | BS9: =MIN('Plant Inputs'!BT9,'Plant Inputs'!BT15,'Plant Inputs'!BT21) | BT9: =SUM('Plant Inputs'!BU9,'Plant Inputs'!BU15,'Plant Inputs'!BU21) | BU9: =SUM('Plant Inputs'!BV9,'Plant Inputs'!BV15,'Plant Inputs'!BV21) | BV9: =SUM('Plant Inputs'!BW9,'Plant Inputs'!BW15,'Plant Inputs'!BW21) | BW9: =SUM('Plant Inputs'!BX9,'Plant Inputs'!BX15,'Plant Inputs'!BX21) | BX9: =SUM('Plant Inputs'!BY9,'Plant Inputs'!BY15,'Plant Inputs'!BY21) | BY9: 50448.8 | BZ9: 37174.1 | CA9: 11016000 | CB9: 4577082.6 | CC9: 967082.6 | CD9: 449031.4 | CE9: 37905 | CF9: 486342.3 | CG9: 1440701.8 | CH9: 201088.9 | CI9: 1153045 | CJ9: 2003213.3 | CK9: 1205957.8 | CL9: 1214918.8 | CM9: 1158127.3 | CN9: 843.3 | CO9: 122055.2 | CP9: 94842.6 | CQ9: 395 | CR9: 18541 | CS9: 17775 | CT9: 2 | CU9: 1161973.5 | CV9: 1210504.1 | CW9: 164691.3 | CX9: 3584699.7 | CY9: 2391562.6 | CZ9: 437492.4 | DA9: 314223.8 | DB9: 354951.3 | DC9: 255711.3 | DD9: 7006.3 | DE9: 7653.2 | DF9: 2579231.2 | DG9: 2009224.9 | DH9: 1000000 | DI9: 722629.1 | DJ9: 79170.5 | DK9: 590000 | DL9: 20798.4 | DM9: 5 | DN9: 1 | DO9: 0 | DP9: 0 | DQ9: 4 | DR9: 10 | DS9: 5 | DT9: 2 | DU9: 1 | DV9: 60 | DW9: 32 | DX9: 4825.8 | DY9: 3192.7 | DZ9: 1075 | EA9: 391.3 | EB9: 648.2 | EC9: 72 | ED9: 69 | EE9: 2 | EF9: 0 | EG9: 2 | EH9: 0 | EI9: 0 | EJ9: 0 | EK9: 0 | EL9: 1 | EM9: 0 | EN9: 0 | EO9: 0 | EP9: 0 | EQ9: 1 | ER9: 1 | ES9: 0 | ET9: 1 | EU9: 2 | EV9: 0 | EW9: 0 | EX9: 0 | EY9: 50 | EZ9: 43 | FA9: 3 | FB9: 88 | FC9: 28 | FD9: 23 | FE9: 26 | FF9: 0 | FG9: 1 | FH9: 1 | FI9: 500044 | FJ9: 494690 | FK9: 400 | FL9: 377 | FM9: 1 | FN9: 0 | FO9: 0 | FP9: 6 | FQ9: 16.7 | FR9: 3 | FS9: 1 | FT9: 1 | FU9: 1
A10: Group | B10: Entity A2 | C10: 2026-04 | D10: 30 | E10: =SUM('Plant Inputs'!F22,'Plant Inputs'!F28,'Plant Inputs'!F34) | F10: =SUM('Plant Inputs'!G22,'Plant Inputs'!G28,'Plant Inputs'!G34) | G10: =SUM('Plant Inputs'!H22,'Plant Inputs'!H28,'Plant Inputs'!H34) | H10: =SUM('Plant Inputs'!I22,'Plant Inputs'!I28,'Plant Inputs'!I34) | I10: =SUM('Plant Inputs'!J22,'Plant Inputs'!J28,'Plant Inputs'!J34) | J10: =SUM('Plant Inputs'!K22,'Plant Inputs'!K28,'Plant Inputs'!K34) | K10: =SUM('Plant Inputs'!L22,'Plant Inputs'!L28,'Plant Inputs'!L34) | L10: =SUM('Plant Inputs'!M22,'Plant Inputs'!M28,'Plant Inputs'!M34) | ... AQ10: =SUM('Plant Inputs'!AR22,'Plant Inputs'!AR28,'Plant Inputs'!AR34) | AR10: =MIN('Plant Inputs'!AS22,'Plant Inputs'!AS28,'Plant Inputs'!AS34) | AS10: =SUM('Plant Inputs'!AT22,'Plant Inputs'!AT28,'Plant Inputs'!AT34) | AT10: =SUM('Plant Inputs'!AU22,'Plant Inputs'!AU28,'Plant Inputs'!AU34) | AU10: =SUM('Plant Inputs'!AV22,'Plant Inputs'!AV28,'Plant Inputs'!AV34) | AV10: =SUM('Plant Inputs'!AW22,'Plant Inputs'!AW28,'Plant Inputs'!AW34) | AW10: =SUM('Plant Inputs'!AX22,'Plant Inputs'!AX28,'Plant Inputs'!AX34) | AX10: =SUM('Plant Inputs'!AY22,'Plant Inputs'!AY28,'Plant Inputs'!AY34) | AY10: =SUM('Plant Inputs'!AZ22,'Plant Inputs'!AZ28,'Plant Inputs'!AZ34) | AZ10: =SUM('Plant Inputs'!BA22,'Plant Inputs'!BA28,'Plant Inputs'!BA34) | ... BR10: =SUM('Plant Inputs'!BS22,'Plant Inputs'!BS28,'Plant Inputs'!BS34) | BS10: =MIN('Plant Inputs'!BT22,'Plant Inputs'!BT28,'Plant Inputs'!BT34) | BT10: =SUM('Plant Inputs'!BU22,'Plant Inputs'!BU28,'Plant Inputs'!BU34) | BU10: =SUM('Plant Inputs'!BV22,'Plant Inputs'!BV28,'Plant Inputs'!BV34) | BV10: =SUM('Plant Inputs'!BW22,'Plant Inputs'!BW28,'Plant Inputs'!BW34) | BW10: =SUM('Plant Inputs'!BX22,'Plant Inputs'!BX28,'Plant Inputs'!BX34) | BX10: =SUM('Plant Inputs'!BY22,'Plant Inputs'!BY28,'Plant Inputs'!BY34) | BY10: 53970.6 | BZ10: 29831.4 | CA10: 10000000 | CB10: 4362932.7 | CC10: 1162932.7 | CD10: 466410.4 | CE10: 33600 | CF10: 401681.3 | CG10: 1363476.4 | CH10: 154555.6 | CI10: 1144080.8 | CJ10: 1670373.1 | CK10: 1974556.3 | CL10: 1075076.8 | CM10: 1128578.1 | CN10: 3306.5 | CO10: 70251.8 | CP10: 70251.8 | CQ10: 374 | CR10: 16795 | CS10: 16830 | CT10: 0 | CU10: 924339.3 | CV10: 930922.9 | CW10: 142690.9 | CX10: 3180825.9 | CY10: 1800841.3 | CZ10: 298827.6 | DA10: 219185.2 | DB10: 234572 | DC10: 172016.9 | DD10: 4570.2 | DE10: 5149.9 | DF10: 1763562.5 | DG10: 1050789.6 | DH10: 860000 | DI10: 389482.4 | DJ10: 69779.5 | DK10: 326800 | DL10: 116966 | DM10: 4 | DN10: 1 | DO10: 0 | DP10: 0 | DQ10: 4 | DR10: 5 | DS10: 10 | DT10: 4 | DU10: 2 | DV10: 64 | DW10: 19 | DX10: 9130.7 | DY10: 3031.5 | DZ10: 1376 | EA10: 1091.6 | EB10: 1173.7 | EC10: 68 | ED10: 66 | EE10: 2 | EF10: 1 | EG10: 1 | EH10: 0 | EI10: 0 | EJ10: 1 | EK10: 1 | EL10: 0 | EM10: 0 | EN10: 0 | EO10: 0 | EP10: 0 | EQ10: 0 | ER10: 0 | ES10: 0 | ET10: 0 | EU10: 6 | EV10: 0 | EW10: 1 | EX10: 1 | EY10: 58 | EZ10: 52 | FA10: 3 | FB10: 111 | FC10: 28 | FD10: 24 | FE10: 26 | FF10: 1 | FG10: 0 | FH10: 0 | FI10: 514962 | FJ10: 512268 | FK10: 420 | FL10: 413 | FM10: 0 | FN10: 0 | FO10: 0 | FP10: 6 | FQ10: 12.9 | FR10: 8 | FS10: 0 | FT10: 1 | FU10: 1
A11: Group | B11: Entity A2 | C11: 2026-05 | D11: 31 | E11: =SUM('Plant Inputs'!F23,'Plant Inputs'!F29,'Plant Inputs'!F35) | F11: =SUM('Plant Inputs'!G23,'Plant Inputs'!G29,'Plant Inputs'!G35) | G11: =SUM('Plant Inputs'!H23,'Plant Inputs'!H29,'Plant Inputs'!H35) | H11: =SUM('Plant Inputs'!I23,'Plant Inputs'!I29,'Plant Inputs'!I35) | I11: =SUM('Plant Inputs'!J23,'Plant Inputs'!J29,'Plant Inputs'!J35) | J11: =SUM('Plant Inputs'!K23,'Plant Inputs'!K29,'Plant Inputs'!K35) | K11: =SUM('Plant Inputs'!L23,'Plant Inputs'!L29,'Plant Inputs'!L35) | L11: =SUM('Plant Inputs'!M23,'Plant Inputs'!M29,'Plant Inputs'!M35) | ... AQ11: =SUM('Plant Inputs'!AR23,'Plant Inputs'!AR29,'Plant Inputs'!AR35) | AR11: =MIN('Plant Inputs'!AS23,'Plant Inputs'!AS29,'Plant Inputs'!AS35) | AS11: =SUM('Plant Inputs'!AT23,'Plant Inputs'!AT29,'Plant Inputs'!AT35) | AT11: =SUM('Plant Inputs'!AU23,'Plant Inputs'!AU29,'Plant Inputs'!AU35) | AU11: =SUM('Plant Inputs'!AV23,'Plant Inputs'!AV29,'Plant Inputs'!AV35) | AV11: =SUM('Plant Inputs'!AW23,'Plant Inputs'!AW29,'Plant Inputs'!AW35) | AW11: =SUM('Plant Inputs'!AX23,'Plant Inputs'!AX29,'Plant Inputs'!AX35) | AX11: =SUM('Plant Inputs'!AY23,'Plant Inputs'!AY29,'Plant Inputs'!AY35) | AY11: =SUM('Plant Inputs'!AZ23,'Plant Inputs'!AZ29,'Plant Inputs'!AZ35) | AZ11: =SUM('Plant Inputs'!BA23,'Plant Inputs'!BA29,'Plant Inputs'!BA35) | ... BR11: =SUM('Plant Inputs'!BS23,'Plant Inputs'!BS29,'Plant Inputs'!BS35) | BS11: =MIN('Plant Inputs'!BT23,'Plant Inputs'!BT29,'Plant Inputs'!BT35) | BT11: =SUM('Plant Inputs'!BU23,'Plant Inputs'!BU29,'Plant Inputs'!BU35) | BU11: =SUM('Plant Inputs'!BV23,'Plant Inputs'!BV29,'Plant Inputs'!BV35) | BV11: =SUM('Plant Inputs'!BW23,'Plant Inputs'!BW29,'Plant Inputs'!BW35) | BW11: =SUM('Plant Inputs'!BX23,'Plant Inputs'!BX29,'Plant Inputs'!BX35) | BX11: =SUM('Plant Inputs'!BY23,'Plant Inputs'!BY29,'Plant Inputs'!BY35) | BY11: 50050.4 | BZ11: 40075 | CA11: 10040000 | CB11: 4257934.5 | CC11: 1089934.5 | CD11: 435228.2 | CE11: 33264 | CF11: 438317.9 | CG11: 1192536.2 | CH11: 184420.1 | CI11: 1082983.6 | CJ11: 1563623.2 | CK11: 1768166.1 | CL11: 1004411.8 | CM11: 1072786 | CN11: 2852.3 | CO11: 74102.9 | CP11: 74102.9 | CQ11: 352 | CR11: 15761 | CS11: 15840 | CT11: 1 | CU11: 1097997.4 | CV11: 1112277.8 | CW11: 184653.8 | CX11: 3151290.2 | CY11: 2164395 | CZ11: 313040.6 | DA11: 229961.2 | DB11: 256509 | DC11: 181113.8 | DD11: 4017.3 | DE11: 4281.1 | DF11: 1785518 | DG11: 1091259.8 | DH11: 860000 | DI11: 432467.4 | DJ11: 69889.8 | DK11: 369800 | DL11: 136303.5 | DM11: 4 | DN11: 1 | DO11: 0 | DP11: 0 | DQ11: 4 | DR11: 5 | DS11: 10 | DT11: 4 | DU11: 2 | DV11: 64 | DW11: 22 | DX11: 9302.1 | DY11: 3474.3 | DZ11: 1389.1 | EA11: 1046.6 | EB11: 1244.6 | EC11: 68 | ED11: 65 | EE11: 3 | EF11: 1 | EG11: 1 | EH11: 0 | EI11: 0 | EJ11: 1 | EK11: 1 | EL11: 0 | EM11: 0 | EN11: 0 | EO11: 0 | EP11: 0 | EQ11: 2 | ER11: 1 | ES11: 0 | ET11: 0 | EU11: 5 | EV11: 0 | EW11: 1 | EX11: 1 | EY11: 58 | EZ11: 52 | FA11: 1 | FB11: 37 | FC11: 28 | FD11: 24 | FE11: 26 | FF11: 1 | FG11: 0 | FH11: 0 | FI11: 481373 | FJ11: 478757 | FK11: 420 | FL11: 411 | FM11: 0 | FN11: 0 | FO11: 0 | FP11: 4 | FQ11: 7.7 | FR11: 7 | FS11: 1 | FT11: 1 | FU11: 1
A12: Group | B12: Entity A2 | C12: 2026-06 | D12: 30 | E12: =SUM('Plant Inputs'!F24,'Plant Inputs'!F30,'Plant Inputs'!F36) | F12: =SUM('Plant Inputs'!G24,'Plant Inputs'!G30,'Plant Inputs'!G36) | G12: =SUM('Plant Inputs'!H24,'Plant Inputs'!H30,'Plant Inputs'!H36) | H12: =SUM('Plant Inputs'!I24,'Plant Inputs'!I30,'Plant Inputs'!I36) | I12: =SUM('Plant Inputs'!J24,'Plant Inputs'!J30,'Plant Inputs'!J36) | J12: =SUM('Plant Inputs'!K24,'Plant Inputs'!K30,'Plant Inputs'!K36) | K12: =SUM('Plant Inputs'!L24,'Plant Inputs'!L30,'Plant Inputs'!L36) | L12: =SUM('Plant Inputs'!M24,'Plant Inputs'!M30,'Plant Inputs'!M36) | ... AQ12: =SUM('Plant Inputs'!AR24,'Plant Inputs'!AR30,'Plant Inputs'!AR36) | AR12: =MIN('Plant Inputs'!AS24,'Plant Inputs'!AS30,'Plant Inputs'!AS36) | AS12: =SUM('Plant Inputs'!AT24,'Plant Inputs'!AT30,'Plant Inputs'!AT36) | AT12: =SUM('Plant Inputs'!AU24,'Plant Inputs'!AU30,'Plant Inputs'!AU36) | AU12: =SUM('Plant Inputs'!AV24,'Plant Inputs'!AV30,'Plant Inputs'!AV36) | AV12: =SUM('Plant Inputs'!AW24,'Plant Inputs'!AW30,'Plant Inputs'!AW36) | AW12: =SUM('Plant Inputs'!AX24,'Plant Inputs'!AX30,'Plant Inputs'!AX36) | AX12: =SUM('Plant Inputs'!AY24,'Plant Inputs'!AY30,'Plant Inputs'!AY36) | AY12: =SUM('Plant Inputs'!AZ24,'Plant Inputs'!AZ30,'Plant Inputs'!AZ36) | AZ12: =SUM('Plant Inputs'!BA24,'Plant Inputs'!BA30,'Plant Inputs'!BA36) | ... BR12: =SUM('Plant Inputs'!BS24,'Plant Inputs'!BS30,'Plant Inputs'!BS36) | BS12: =MIN('Plant Inputs'!BT24,'Plant Inputs'!BT30,'Plant Inputs'!BT36) | BT12: =SUM('Plant Inputs'!BU24,'Plant Inputs'!BU30,'Plant Inputs'!BU36) | BU12: =SUM('Plant Inputs'!BV24,'Plant Inputs'!BV30,'Plant Inputs'!BV36) | BV12: =SUM('Plant Inputs'!BW24,'Plant Inputs'!BW30,'Plant Inputs'!BW36) | BW12: =SUM('Plant Inputs'!BX24,'Plant Inputs'!BX30,'Plant Inputs'!BX36) | BX12: =SUM('Plant Inputs'!BY24,'Plant Inputs'!BY30,'Plant Inputs'!BY36) | BY12: 51654.7 | BZ12: 22449.1 | CA12: 10080000 | CB12: 4211021.8 | CC12: 1075021.8 | CD12: 436315.8 | CE12: 32928 | CF12: 405014 | CG12: 1190070.9 | CH12: 107481.4 | CI12: 1119343.6 | CJ12: 1665189.5 | CK12: 2023734.9 | CL12: 1155573.9 | CM12: 1086928.3 | CN12: 3048.7 | CO12: 78617.1 | CP12: 78617.1 | CQ12: 333 | CR12: 15098 | CS12: 14985 | CT12: 0 | CU12: 640845.8 | CV12: 647178.6 | CW12: 92062 | CX12: 3085667.3 | CY12: 1265494.8 | CZ12: 287638.8 | DA12: 211841.6 | DB12: 231613.6 | DC12: 171021.1 | DD12: 3471.9 | DE12: 3774.8 | DF12: 1772808 | DG12: 1085587.8 | DH12: 860000 | DI12: 476244.8 | DJ12: 70024 | DK12: 412800 | DL12: 130334.1 | DM12: 4 | DN12: 1 | DO12: 0 | DP12: 0 | DQ12: 7 | DR12: 10 | DS12: 10 | DT12: 4 | DU12: 2 | DV12: 64 | DW12: 25 | DX12: 8998.7 | DY12: 3287.2 | DZ12: 1313.6 | EA12: 1018 | EB12: 1229.3 | EC12: 68 | ED12: 66 | EE12: 2 | EF12: 0 | EG12: 1 | EH12: 0 | EI12: 0 | EJ12: 0 | EK12: 0 | EL12: 0 | EM12: 0 | EN12: 1 | EO12: 0 | EP12: 0 | EQ12: 1 | ER12: 0 | ES12: 0 | ET12: 0 | EU12: 6 | EV12: 0 | EW12: 1 | EX12: 1 | EY12: 58 | EZ12: 52 | FA12: 3 | FB12: 115 | FC12: 28 | FD12: 24 | FE12: 26 | FF12: 1 | FG12: 0 | FH12: 0 | FI12: 499474 | FJ12: 495766 | FK12: 420 | FL12: 413 | FM12: 0 | FN12: 0 | FO12: 0 | FP12: 4 | FQ12: 7.8 | FR12: 7 | FS12: 0 | FT12: 0 | FU12: -1
A13: Group | B13: Entity A2 | C13: 2026-07 | D13: 31 | E13: =SUM('Plant Inputs'!F25,'Plant Inputs'!F31,'Plant Inputs'!F37) | F13: =SUM('Plant Inputs'!G25,'Plant Inputs'!G31,'Plant Inputs'!G37) | G13: =SUM('Plant Inputs'!H25,'Plant Inputs'!H31,'Plant Inputs'!H37) | H13: =SUM('Plant Inputs'!I25,'Plant Inputs'!I31,'Plant Inputs'!I37) | I13: =SUM('Plant Inputs'!J25,'Plant Inputs'!J31,'Plant Inputs'!J37) | J13: =SUM('Plant Inputs'!K25,'Plant Inputs'!K31,'Plant Inputs'!K37) | K13: =SUM('Plant Inputs'!L25,'Plant Inputs'!L31,'Plant Inputs'!L37) | L13: =SUM('Plant Inputs'!M25,'Plant Inputs'!M31,'Plant Inputs'!M37) | ... AQ13: =SUM('Plant Inputs'!AR25,'Plant Inputs'!AR31,'Plant Inputs'!AR37) | AR13: =MIN('Plant Inputs'!AS25,'Plant Inputs'!AS31,'Plant Inputs'!AS37) | AS13: =SUM('Plant Inputs'!AT25,'Plant Inputs'!AT31,'Plant Inputs'!AT37) | AT13: =SUM('Plant Inputs'!AU25,'Plant Inputs'!AU31,'Plant Inputs'!AU37) | AU13: =SUM('Plant Inputs'!AV25,'Plant Inputs'!AV31,'Plant Inputs'!AV37) | AV13: =SUM('Plant Inputs'!AW25,'Plant Inputs'!AW31,'Plant Inputs'!AW37) | AW13: =SUM('Plant Inputs'!AX25,'Plant Inputs'!AX31,'Plant Inputs'!AX37) | AX13: =SUM('Plant Inputs'!AY25,'Plant Inputs'!AY31,'Plant Inputs'!AY37) | AY13: =SUM('Plant Inputs'!AZ25,'Plant Inputs'!AZ31,'Plant Inputs'!AZ37) | AZ13: =SUM('Plant Inputs'!BA25,'Plant Inputs'!BA31,'Plant Inputs'!BA37) | ... BR13: =SUM('Plant Inputs'!BS25,'Plant Inputs'!BS31,'Plant Inputs'!BS37) | BS13: =MIN('Plant Inputs'!BT25,'Plant Inputs'!BT31,'Plant Inputs'!BT37) | BT13: =SUM('Plant Inputs'!BU25,'Plant Inputs'!BU31,'Plant Inputs'!BU37) | BU13: =SUM('Plant Inputs'!BV25,'Plant Inputs'!BV31,'Plant Inputs'!BV37) | BV13: =SUM('Plant Inputs'!BW25,'Plant Inputs'!BW31,'Plant Inputs'!BW37) | BW13: =SUM('Plant Inputs'!BX25,'Plant Inputs'!BX31,'Plant Inputs'!BX37) | BX13: =SUM('Plant Inputs'!BY25,'Plant Inputs'!BY31,'Plant Inputs'!BY37) | BY13: 54610.5 | BZ13: 23755.2 | CA13: 10120000 | CB13: 4323104.5 | CC13: 1219104.5 | CD13: 442574.4 | CE13: 32592 | CF13: 425574.5 | CG13: 1293891.3 | CH13: 119814.6 | CI13: 1202019.5 | CJ13: 1734551.6 | CK13: 2055982.4 | CL13: 1122026.2 | CM13: 1161124.7 | CN13: 2912.2 | CO13: 78725.2 | CP13: 78725.2 | CQ13: 342 | CR13: 15474 | CS13: 15390 | CT13: 1 | CU13: 714775.5 | CV13: 718721.9 | CW13: 139958.6 | CX13: 3047312.3 | CY13: 1412231.8 | CZ13: 347025.2 | DA13: 242148.9 | DB13: 284119.2 | DC13: 199411 | DD13: 6393 | DE13: 6859.8 | DF13: 1997749.7 | DG13: 1170469.4 | DH13: 860000 | DI13: 526173.4 | DJ13: 66726.9 | DK13: 455800 | DL13: 129811.4 | DM13: 4 | DN13: 1 | DO13: 0 | DP13: 1 | DQ13: 4 | DR13: 4 | DS13: 10 | DT13: 4 | DU13: 2 | DV13: 64 | DW13: 28 | DX13: 9318.7 | DY13: 3457.6 | DZ13: 1294.6 | EA13: 1069.1 | EB13: 1220.3 | EC13: 68 | ED13: 65 | EE13: 3 | EF13: 1 | EG13: 1 | EH13: 0 | EI13: 0 | EJ13: 1 | EK13: 1 | EL13: 1 | EM13: 0 | EN13: 0 | EO13: 0 | EP13: 0 | EQ13: 0 | ER13: 0 | ES13: 0 | ET13: 0 | EU13: 5 | EV13: 0 | EW13: 1 | EX13: 1 | EY13: 58 | EZ13: 53 | FA13: 1 | FB13: 36 | FC13: 28 | FD13: 24 | FE13: 26 | FF13: 1 | FG13: 0 | FH13: 0 | FI13: 512122 | FJ13: 506494 | FK13: 420 | FL13: 415 | FM13: 0 | FN13: 0 | FO13: 0 | FP13: 4 | FQ13: 8.5 | FR13: 8 | FS13: 1 | FT13: 1 | FU13: 1
A14: Group | B14: Entity A2 | C14: 2026-08 | D14: 31 | E14: =SUM('Plant Inputs'!F26,'Plant Inputs'!F32,'Plant Inputs'!F38) | F14: =SUM('Plant Inputs'!G26,'Plant Inputs'!G32,'Plant Inputs'!G38) | G14: =SUM('Plant Inputs'!H26,'Plant Inputs'!H32,'Plant Inputs'!H38) | H14: =SUM('Plant Inputs'!I26,'Plant Inputs'!I32,'Plant Inputs'!I38) | I14: =SUM('Plant Inputs'!J26,'Plant Inputs'!J32,'Plant Inputs'!J38) | J14: =SUM('Plant Inputs'!K26,'Plant Inputs'!K32,'Plant Inputs'!K38) | K14: =SUM('Plant Inputs'!L26,'Plant Inputs'!L32,'Plant Inputs'!L38) | L14: =SUM('Plant Inputs'!M26,'Plant Inputs'!M32,'Plant Inputs'!M38) | ... AQ14: =SUM('Plant Inputs'!AR26,'Plant Inputs'!AR32,'Plant Inputs'!AR38) | AR14: =MIN('Plant Inputs'!AS26,'Plant Inputs'!AS32,'Plant Inputs'!AS38) | AS14: =SUM('Plant Inputs'!AT26,'Plant Inputs'!AT32,'Plant Inputs'!AT38) | AT14: =SUM('Plant Inputs'!AU26,'Plant Inputs'!AU32,'Plant Inputs'!AU38) | AU14: =SUM('Plant Inputs'!AV26,'Plant Inputs'!AV32,'Plant Inputs'!AV38) | AV14: =SUM('Plant Inputs'!AW26,'Plant Inputs'!AW32,'Plant Inputs'!AW38) | AW14: =SUM('Plant Inputs'!AX26,'Plant Inputs'!AX32,'Plant Inputs'!AX38) | AX14: =SUM('Plant Inputs'!AY26,'Plant Inputs'!AY32,'Plant Inputs'!AY38) | AY14: =SUM('Plant Inputs'!AZ26,'Plant Inputs'!AZ32,'Plant Inputs'!AZ38) | AZ14: =SUM('Plant Inputs'!BA26,'Plant Inputs'!BA32,'Plant Inputs'!BA38) | ... BR14: =SUM('Plant Inputs'!BS26,'Plant Inputs'!BS32,'Plant Inputs'!BS38) | BS14: =MIN('Plant Inputs'!BT26,'Plant Inputs'!BT32,'Plant Inputs'!BT38) | BT14: =SUM('Plant Inputs'!BU26,'Plant Inputs'!BU32,'Plant Inputs'!BU38) | BU14: =SUM('Plant Inputs'!BV26,'Plant Inputs'!BV32,'Plant Inputs'!BV38) | BV14: =SUM('Plant Inputs'!BW26,'Plant Inputs'!BW32,'Plant Inputs'!BW38) | BW14: =SUM('Plant Inputs'!BX26,'Plant Inputs'!BX32,'Plant Inputs'!BX38) | BX14: =SUM('Plant Inputs'!BY26,'Plant Inputs'!BY32,'Plant Inputs'!BY38) | BY14: 52643.9 | BZ14: 23550.4 | CA14: 10160000 | CB14: 4208810.1 | CC14: 1136810.1 | CD14: 425899.5 | CE14: 32256 | CF14: 436100.5 | CG14: 1192966.9 | CH14: 107683.3 | CI14: 1114419.8 | CJ14: 1562844.7 | CK14: 1909315.9 | CL14: 1088791.2 | CM14: 1109116.5 | CN14: 3143.6 | CO14: 71435.8 | CP14: 71435.8 | CQ14: 326 | CR14: 14795 | CS14: 14670 | CT14: 1 | CU14: 645320.4 | CV14: 653271.4 | CW14: 123824.7 | CX14: 3032458.5 | CY14: 1267817.3 | CZ14: 301775.9 | DA14: 207433.2 | DB14: 239804.4 | DC14: 168954.7 | DD14: 3637.5 | DE14: 3899 | DF14: 1830360.2 | DG14: 1065570.5 | DH14: 860000 | DI14: 567051.2 | DJ14: 69472.5 | DK14: 498800 | DL14: 131528.7 | DM14: 4 | DN14: 1 | DO14: 0 | DP14: 1 | DQ14: 6 | DR14: 7 | DS14: 10 | DT14: 4 | DU14: 2 | DV14: 64 | DW14: 31 | DX14: 9144.2 | DY14: 3287.9 | DZ14: 1358.2 | EA14: 1070.2 | EB14: 1243.8 | EC14: 68 | ED14: 65 | EE14: 2 | EF14: 0 | EG14: 1 | EH14: 1 | EI14: 0 | EJ14: 1 | EK14: 1 | EL14: 1 | EM14: 0 | EN14: 0 | EO14: 0 | EP14: 0 | EQ14: 2 | ER14: 1 | ES14: 0 | ET14: 0 | EU14: 5 | EV14: 0 | EW14: 1 | EX14: 1 | EY14: 58 | EZ14: 52 | FA14: 2 | FB14: 76 | FC14: 28 | FD14: 24 | FE14: 26 | FF14: 2 | FG14: 0 | FH14: 0 | FI14: 498702 | FJ14: 494943 | FK14: 420 | FL14: 412 | FM14: 0 | FN14: 0 | FO14: 0 | FP14: 5 | FQ14: 9.9 | FR14: 8 | FS14: 0 | FT14: 1 | FU14: 1
A15: Group | B15: Entity A2 | C15: 2026-09 | D15: 30 | E15: =SUM('Plant Inputs'!F27,'Plant Inputs'!F33,'Plant Inputs'!F39) | F15: =SUM('Plant Inputs'!G27,'Plant Inputs'!G33,'Plant Inputs'!G39) | G15: =SUM('Plant Inputs'!H27,'Plant Inputs'!H33,'Plant Inputs'!H39) | H15: =SUM('Plant Inputs'!I27,'Plant Inputs'!I33,'Plant Inputs'!I39) | I15: =SUM('Plant Inputs'!J27,'Plant Inputs'!J33,'Plant Inputs'!J39) | J15: =SUM('Plant Inputs'!K27,'Plant Inputs'!K33,'Plant Inputs'!K39) | K15: =SUM('Plant Inputs'!L27,'Plant Inputs'!L33,'Plant Inputs'!L39) | L15: =SUM('Plant Inputs'!M27,'Plant Inputs'!M33,'Plant Inputs'!M39) | ... AQ15: =SUM('Plant Inputs'!AR27,'Plant Inputs'!AR33,'Plant Inputs'!AR39) | AR15: =MIN('Plant Inputs'!AS27,'Plant Inputs'!AS33,'Plant Inputs'!AS39) | AS15: =SUM('Plant Inputs'!AT27,'Plant Inputs'!AT33,'Plant Inputs'!AT39) | AT15: =SUM('Plant Inputs'!AU27,'Plant Inputs'!AU33,'Plant Inputs'!AU39) | AU15: =SUM('Plant Inputs'!AV27,'Plant Inputs'!AV33,'Plant Inputs'!AV39) | AV15: =SUM('Plant Inputs'!AW27,'Plant Inputs'!AW33,'Plant Inputs'!AW39) | AW15: =SUM('Plant Inputs'!AX27,'Plant Inputs'!AX33,'Plant Inputs'!AX39) | AX15: =SUM('Plant Inputs'!AY27,'Plant Inputs'!AY33,'Plant Inputs'!AY39) | AY15: =SUM('Plant Inputs'!AZ27,'Plant Inputs'!AZ33,'Plant Inputs'!AZ39) | AZ15: =SUM('Plant Inputs'!BA27,'Plant Inputs'!BA33,'Plant Inputs'!BA39) | ... BR15: =SUM('Plant Inputs'!BS27,'Plant Inputs'!BS33,'Plant Inputs'!BS39) | BS15: =MIN('Plant Inputs'!BT27,'Plant Inputs'!BT33,'Plant Inputs'!BT39) | BT15: =SUM('Plant Inputs'!BU27,'Plant Inputs'!BU33,'Plant Inputs'!BU39) | BU15: =SUM('Plant Inputs'!BV27,'Plant Inputs'!BV33,'Plant Inputs'!BV39) | BV15: =SUM('Plant Inputs'!BW27,'Plant Inputs'!BW33,'Plant Inputs'!BW39) | BW15: =SUM('Plant Inputs'!BX27,'Plant Inputs'!BX33,'Plant Inputs'!BX39) | BX15: =SUM('Plant Inputs'!BY27,'Plant Inputs'!BY33,'Plant Inputs'!BY39) | BY15: 52845 | BZ15: 40246.8 | CA15: 10200000 | CB15: 4214739.8 | CC15: 1174739.8 | CD15: 431783.2 | CE15: 31920 | CF15: 405067.9 | CG15: 1280130.3 | CH15: 195011.3 | CI15: 1173926.1 | CJ15: 1654275.7 | CK15: 1971156.1 | CL15: 1085692.7 | CM15: 1145104.1 | CN15: 2567.4 | CO15: 83215.8 | CP15: 83215.8 | CQ15: 355 | CR15: 16051 | CS15: 15975 | CT15: 1 | CU15: 1172252.9 | CV15: 1179902.4 | CW15: 182427 | CX15: 2999569.4 | CY15: 2303674.3 | CZ15: 330230.9 | DA15: 231774.8 | DB15: 259974.1 | DC15: 191082.1 | DD15: 4370.6 | DE15: 4752.9 | DF15: 1953973.8 | DG15: 1193687.3 | DH15: 860000 | DI15: 625104.2 | DJ15: 65703.7 | DK15: 541800 | DL15: 127233 | DM15: 4 | DN15: 1 | DO15: 0 | DP15: 1 | DQ15: 7 | DR15: 9 | DS15: 10 | DT15: 4 | DU15: 2 | DV15: 64 | DW15: 35 | DX15: 9329.9 | DY15: 3492 | DZ15: 1271.7 | EA15: 1040.2 | EB15: 1241.7 | EC15: 68 | ED15: 65 | EE15: 2 | EF15: 0 | EG15: 1 | EH15: 1 | EI15: 0 | EJ15: 0 | EK15: 0 | EL15: 0 | EM15: 0 | EN15: 0 | EO15: 0 | EP15: 0 | EQ15: 2 | ER15: 1 | ES15: 0 | ET15: 0 | EU15: 5 | EV15: 0 | EW15: 1 | EX15: 1 | EY15: 58 | EZ15: 52 | FA15: 2 | FB15: 78 | FC15: 28 | FD15: 24 | FE15: 26 | FF15: 2 | FG15: 0 | FH15: 0 | FI15: 504265 | FJ15: 499753 | FK15: 420 | FL15: 410 | FM15: 0 | FN15: 1 | FO15: 0 | FP15: 5 | FQ15: 10.3 | FR15: 8 | FS15: 0 | FT15: 1 | FU15: 1

Sheet Plant Inputs
A1: Group | B1: Entity | C1: Plant | D1: Month | E1: Nameplate rate (t/hour) | F1: Calendar hours (h) | G1: Planned operating hours (h) | H1: Run hours (h) | I1: Unplanned downtime (h) | J1: Ideal output (t) | K1: Installed capacity (t) | L1: Planned production (t) | M1: Gross output (t) | N1: Good output (t) | O1: Feed input (t) | P1: Valuable content in feed (t) | Q1: Valuable content recovered (t) | R1: Production lost to downtime (t) | S1: Breakdowns (count) | T1: Repair hours (h) | U1: Preventive maintenance scheduled (count) | V1: Preventive maintenance completed (count) | W1: Variable cost (₹ thousand) | X1: Fuel cost (₹ thousand) | Y1: Fixed cost (₹ thousand) | Z1: Water used (m³) | AA1: Emissions (t CO2e) | AB1: Energy used (GJ) | AC1: Production at risk (t) | AD1: Critical plant alerts (count) | AE1: Hours worked (h) | AF1: Recordable injuries (count) | AG1: Severity incidents (count) | AH1: Near misses (count) | AI1: Critical safety incidents (count) | AJ1: Environmental excursions (count) | AK1: Environmental violations (count) | AL1: Open EHS corrective actions (count) | AM1: Overdue EHS corrective actions (count) | AN1: EHS investigations due (count) | AO1: EHS investigations completed (count) | AP1: Critical materials at risk (count) | AQ1: Dispatches (count) | AR1: Delayed dispatches (count) | AS1: Days to permit expiry (days) | AT1: Sales volume (t) | AU1: Planned sales volume (t) | AV1: Revenue (₹ thousand) | AW1: Planned revenue (₹ thousand) | AX1: Power cost, part of variable cost (₹ thousand) | AY1: Depreciation and amortisation (₹ thousand) | AZ1: Purchase-order lines due (count) | BA1: Purchase-order lines delivered on time (count) | BB1: Quantity ordered from suppliers (t) | BC1: Quantity received (t) | BD1: Quantity rejected on quality (t) | BE1: Planned lead time, all deliveries (days) | BF1: Actual lead time, all deliveries (days) | BG1: Supplier spend (₹ thousand) | BH1: Spend with single-source suppliers (₹ thousand) | BI1: Supplier EHS incidents (count) | BJ1: Regulatory filings pending (count) | BK1: Regulatory deadlines in next 30 days (count) | BL1: Licences expiring in next 12 months (count) | BM1: Regulatory obligations due in next 30 days (count) | BN1: Regulatory obligations overdue (count) | BO1: Open regulatory actions (count) | BP1: Overdue compliance actions (count) | BQ1: Regulatory breaches in the month (count) | BR1: Events that trigger a disclosure clock (count) | BS1: EHS escalation clocks running (count) | BT1: Days until production plan is breached, forecast (days; 99 = not expected) | BU1: Planned production next month (t) | BV1: Forecast good output next month (t) | BW1: Forecast uncertainty next month (variance, t²) | BX1: Ideal output next month (t) | BY1: Forecast production lost to downtime next month (t)
A2: group | B2: entity | C2: plant | D2: period | E2: nameplate_tph | F2: calendar_hours | G2: planned_op_hours | H2: run_hours | I2: unplanned_downtime_hours | J2: ideal_output_t | K2: installed_capacity_t | L2: planned_production_t | M2: gross_output_t | N2: good_output_t | O2: feed_input_t | P2: feed_contained_t | Q2: recovered_contained_t | R2: prod_loss_downtime_t | S2: failures | T2: repair_hours | U2: pm_scheduled | V2: pm_completed | W2: variable_cost_k | X2: fuel_cost_k | Y2: fixed_cost_k | Z2: water_m3 | AA2: emissions_tco2e | AB2: energy_gj | AC2: production_at_risk_t | AD2: critical_plant_alerts | AE2: hours_worked | AF2: recordable_injuries | AG2: severity_incidents | AH2: near_misses | AI2: critical_safety_incidents | AJ2: env_excursions | AK2: env_violations | AL2: ehs_ca_open | AM2: ehs_ca_overdue | AN2: investigations_due | AO2: investigations_completed | AP2: critical_material_risks | AQ2: dispatches_total | AR2: dispatches_delayed | AS2: permit_days_to_expiry | AT2: sales_t | AU2: planned_sales_t | AV2: revenue_k | AW2: planned_revenue_k | AX2: power_cost_k | AY2: depreciation_k | AZ2: po_lines_due | BA2: po_lines_on_time | BB2: qty_ordered_t | BC2: qty_received_t | BD2: qty_rejected_t | BE2: lead_time_planned_days | BF2: lead_time_actual_days | BG2: supplier_spend_k | BH2: single_source_spend_k | BI2: supplier_ehs_incidents | BJ2: pending_filings | BK2: reg_deadlines_30d | BL2: licences_expiring_12m | BM2: reg_obligations_due_30d | BN2: reg_obligations_overdue | BO2: reg_actions_open | BP2: compliance_actions_overdue | BQ2: reg_breaches | BR2: disclosure_events_open | BS2: ehs_escalation_clocks | BT2: days_to_breach | BU2: planned_production_next_t | BV2: forecast_good_next_t | BW2: forecast_good_var_next | BX2: ideal_output_next_t | BY2: forecast_downtime_loss_next_t
E3: Input | F3: Input | G3: Input | H3: Input | I3: Input | J3: Input | K3: Input | L3: Input | M3: Input | N3: Input | O3: Input | P3: Input | Q3: Input | R3: Input | S3: Input | T3: Input | U3: Input | V3: Input | W3: Input | X3: Input | Y3: Input | Z3: Input | AA3: Input | AB3: Input | AC3: Input | AD3: Input | AE3: Input | AF3: Input | AG3: Input | AH3: Input | AI3: Input | AJ3: Input | AK3: Input | AL3: Input | AM3: Input | AN3: Input | AO3: Input | AP3: Input | AQ3: Input | AR3: Input | AS3: Input | AT3: Input | AU3: Input | AV3: Input | AW3: Input | AX3: Input | AY3: Input | AZ3: Input | BA3: Input | BB3: Input | BC3: Input | BD3: Input | BE3: Input | BF3: Input | BG3: Input | BH3: Input | BI3: Input | BJ3: Input | BK3: Input | BL3: Input | BM3: Input | BN3: Input | BO3: Input | BP3: Input | BQ3: Input | BR3: Input | BS3: Input | BT3: Input | BU3: Input | BV3: Input | BW3: Input | BX3: Input | BY3: Input
A4: Group | B4: Entity A1 | C4: Plant 01 | D4: 2026-04 | E4: 137.1 | F4: 720 | G4: 714 | H4: 692.3 | I4: 13.3 | J4: 97889 | K4: 98712 | L4: 88515 | M4: 89648 | N4: 87087 | O4: 95600 | P4: 19579 | Q4: 17553 | R4: 1823 | S4: 2 | T4: 7.1 | U4: 37 | V4: 36 | W4: 251985.8 | X4: 62832 | Y4: 1091.7 | Z4: 167244 | AA4: 61316 | AB4: 311042 | AC4: 3223 | AD4: 1 | AE4: 79000 | AF4: 0 | AG4: 1 | AH4: 10 | AI4: 0 | AJ4: 0 | AK4: 0 | AL4: 14 | AM4: 4 | AN4: 0 | AO4: 0 | AP4: 0 | AQ4: 158 | AR4: 9 | AS4: 311 | AT4: 87409 | AU4: 89254 | AV4: 329486.5 | AW4: 335595 | AX4: 15168.7 | AY4: 11886.3 | AZ4: 209 | BA4: 195 | BB4: 95742 | BC4: 92606 | BD4: 1350 | BE4: 588 | BF4: 583 | BG4: 131922.8 | BH4: 40636.9 | BI4: 0 | BJ4: 0 | BK4: 1 | BL4: 0 | BM4: 1 | BN4: 0 | BO4: 0 | BP4: 0 | BQ4: 0 | BR4: 0 | BS4: 0 | BT4: 99 | BU4: 87645 | BV4: 87637 | BW4: 24380601 | BX4: 97889 | BY4: 1620
A5: Group | B5: Entity A1 | C5: Plant 01 | D5: 2026-05 | E5: 137.1 | F5: 744 | G5: 744 | H5: 702.5 | I5: 19.6 | J5: 102002 | K5: 102002 | L5: 88139 | M5: 84940 | N5: 80872 | O5: 86252 | P5: 17739 | Q5: 15002 | R5: 2687 | S5: 3 | T5: 15.5 | U5: 48 | V5: 47 | W5: 272778.7 | X5: 79959.6 | Y5: 1465.4 | Z5: 205726 | AA5: 53724 | AB5: 252523 | AC5: 5217 | AD5: 1 | AE5: 66000 | AF5: 0 | AG5: 0 | AH5: 4 | AI5: 0 | AJ5: 0 | AK5: 0 | AL5: 11 | AM5: 2 | AN5: 3 | AO5: 3 | AP5: 0 | AQ5: 256 | AR5: 10 | AS5: 281 | AT5: 81067 | AU5: 87363 | AV5: 309234.4 | AW5: 328484.9 | AX5: 17277.2 | AY5: 11827.2 | AZ5: 166 | BA5: 151 | BB5: 85077 | BC5: 81619 | BD5: 587 | BE5: 868 | BF5: 870 | BG5: 150305.9 | BH5: 52546 | BI5: 0 | BJ5: 1 | BK5: 0 | BL5: 0 | BM5: 0 | BN5: 0 | BO5: 0 | BP5: 0 | BQ5: 0 | BR5: 0 | BS5: 0 | BT5: 99 | BU5: 89736 | BV5: 91812 | BW5: 30306703 | BX5: 102002 | BY5: 2913
A6: Group | B6: Entity A1 | C6: Plant 01 | D6: 2026-06 | E6: 137.1 | F6: 720 | G6: 720 | H6: 681.5 | I6: 18.6 | J6: 98712 | K6: 98712 | L6: 88801 | M6: 84328 | N6: 81129 | O6: 86263 | P6: 18895 | Q6: 16380 | R6: 2550 | S6: 2 | T6: 14.7 | U6: 48 | V6: 45 | W6: 269800.1 | X6: 63241.6 | Y6: 1103.4 | Z6: 166424 | AA6: 60010 | AB6: 243788 | AC6: 7297 | AD6: 2 | AE6: 91000 | AF6: 1 | AG6: 0 | AH6: 10 | AI6: 0 | AJ6: 1 | AK6: 0 | AL6: 5 | AM6: 1 | AN6: 0 | AO6: 0 | AP6: 0 | AQ6: 148 | AR6: 11 | AS6: 251 | AT6: 78859 | AU6: 89179 | AV6: 300728.2 | AW6: 335313 | AX6: 16758.3 | AY6: 11531.2 | AZ6: 179 | BA6: 167 | BB6: 87881 | BC6: 85157 | BD6: 708 | BE6: 980 | BF6: 979 | BG6: 148313 | BH6: 46780.1 | BI6: 1 | BJ6: 0 | BK6: 0 | BL6: 0 | BM6: 1 | BN6: 0 | BO6: 0 | BP6: 0 | BQ6: 0 | BR6: 0 | BS6: 0 | BT6: 99 | BU6: 89319 | BV6: 90196 | BW6: 26705815 | BX6: 98712 | BY6: 2398
A7: Group | B7: Entity A1 | C7: Plant 01 | D7: 2026-07 | E7: 137.1 | F7: 744 | G7: 741 | H7: 701.6 | I7: 27.2 | J7: 101591 | K7: 102002 | L7: 88152 | M7: 86711 | N7: 83254 | O7: 94209 | P7: 21264 | Q7: 19441 | R7: 3729 | S7: 4 | T7: 21.3 | U7: 55 | V7: 52 | W7: 221284.2 | X7: 64810.6 | Y7: 1144.9 | Z7: 180484 | AA7: 54600 | AB7: 243753 | AC7: 5312 | AD7: 0 | AE7: 76000 | AF7: 1 | AG7: 0 | AH7: 9 | AI7: 0 | AJ7: 1 | AK7: 0 | AL7: 4 | AM7: 1 | AN7: 3 | AO7: 3 | AP7: 1 | AQ7: 198 | AR7: 9 | AS7: 221 | AT7: 84466 | AU7: 87398 | AV7: 321422 | AW7: 328616.5 | AX7: 11354.6 | AY7: 11607.9 | AZ7: 300 | BA7: 281 | BB7: 96576 | BC7: 93033 | BD7: 1429 | BE7: 742 | BF7: 772 | BG7: 112971 | BH7: 43971.6 | BI7: 0 | BJ7: 0 | BK7: 0 | BL7: 0 | BM7: 0 | BN7: 0 | BO7: 1 | BP7: 0 | BQ7: 0 | BR7: 0 | BS7: 0 | BT7: 99 | BU7: 87292 | BV7: 87138 | BW7: 23937559 | BX7: 101591 | BY7: 3863
A8: Group | B8: Entity A1 | C8: Plant 01 | D8: 2026-08 | E8: 137.1 | F8: 744 | G8: 744 | H8: 710.7 | I8: 19.1 | J8: 102002 | K8: 102002 | L8: 91424 | M8: 90032 | N8: 87527 | O8: 94670 | P8: 19426 | Q8: 17234 | R8: 2619 | S8: 2 | T8: 14 | U8: 32 | V8: 31 | W8: 268254.7 | X8: 78893.9 | Y8: 1065.3 | Z8: 192091 | AA8: 54889 | AB8: 306311 | AC8: 1480 | AD8: 2 | AE8: 56000 | AF8: 1 | AG8: 0 | AH8: 6 | AI8: 0 | AJ8: 0 | AK8: 0 | AL8: 5 | AM8: 0 | AN8: 1 | AO8: 1 | AP8: 2 | AQ8: 121 | AR8: 10 | AS8: 191 | AT8: 86793 | AU8: 91102 | AV8: 330981.6 | AW8: 342543.5 | AX8: 16048.6 | AY8: 11694.1 | AZ8: 169 | BA8: 156 | BB8: 95196 | BC8: 92043 | BD8: 1181 | BE8: 868 | BF8: 855 | BG8: 154797 | BH8: 58229.3 | BI8: 0 | BJ8: 0 | BK8: 0 | BL8: 0 | BM8: 1 | BN8: 0 | BO8: 0 | BP8: 0 | BQ8: 0 | BR8: 0 | BS8: 0 | BT8: 99 | BU8: 92975 | BV8: 93639 | BW8: 35960460 | BX8: 102002 | BY8: 2699
A9: Group | B9: Entity A1 | C9: Plant 01 | D9: 2026-09 | E9: 137.1 | F9: 720 | G9: 711 | H9: 664.5 | I9: 30.2 | J9: 97478 | K9: 98712 | L9: 85234 | M9: 84182 | N9: 81854 | O9: 89479 | P9: 19996 | Q9: 18334 | R9: 4140 | S9: 4 | T9: 21.6 | U9: 46 | V9: 43 | W9: 226098.2 | X9: 50616 | Y9: 1375.5 | Z9: 148807 | AA9: 59115 | AB9: 289576 | AC9: 3669 | AD9: 0 | AE9: 55000 | AF9: 0 | AG9: 1 | AH9: 9 | AI9: 0 | AJ9: 0 | AK9: 0 | AL9: 14 | AM9: 4 | AN9: 2 | AO9: 2 | AP9: 2 | AQ9: 120 | AR9: 9 | AS9: 161 | AT9: 79865 | AU9: 86061 | AV9: 300900.3 | AW9: 323589.4 | AX9: 13488.8 | AY9: 11990.8 | AZ9: 151 | BA9: 140 | BB9: 89804 | BC9: 86335 | BD9: 1211 | BE9: 644 | BF9: 676 | BG9: 116619.5 | BH9: 35125 | BI9: 1 | BJ9: 0 | BK9: 1 | BL9: 0 | BM9: 0 | BN9: 0 | BO9: 0 | BP9: 0 | BQ9: 0 | BR9: 0 | BS9: 0 | BT9: 99 | BU9: 85101 | BV9: 86567 | BW9: 26609951 | BX9: 97478 | BY9: 4173
A10: Group | B10: Entity A1 | C10: Plant 02 | D10: 2026-04 | E10: 188.9 | F10: 720 | G10: 718 | H10: 675.1 | I10: 31 | J10: 135630 | K10: 136008 | L10: 117160 | M10: 101595 | N10: 98478 | O10: 110890 | P10: 24227 | Q10: 19946 | R10: 5856 | S10: 5 | T10: 28.6 | U10: 40 | V10: 34 | W10: 293950 | X10: 67780.4 | Y10: 1112.1 | Z10: 202909 | AA10: 69227 | AB10: 349419 | AC10: 17173 | AD10: 2 | AE10: 61000 | AF10: 0 | AG10: 0 | AH10: 6 | AI10: 0 | AJ10: 0 | AK10: 0 | AL10: 6 | AM10: 2 | AN10: 3 | AO10: 3 | AP10: 1 | AQ10: 187 | AR10: 11 | AS10: 215 | AT10: 99647 | AU10: 116251 | AV10: 367581.1 | AW10: 437103.8 | AX10: 20037.9 | AY10: 15943.3 | AZ10: 167 | BA10: 142 | BB10: 108759 | BC10: 107531 | BD10: 1079 | BE10: 574 | BF10: 662 | BG10: 161218.5 | BH10: 73012.8 | BI10: 0 | BJ10: 1 | BK10: 1 | BL10: 1 | BM10: 1 | BN10: 0 | BO10: 0 | BP10: 0 | BQ10: 0 | BR10: 0 | BS10: 0 | BT10: 17 | BU10: 119412 | BV10: 107510 | BW10: 40574219 | BX10: 135630 | BY10: 5356
A11: Group | B11: Entity A1 | C11: Plant 02 | D11: 2026-05 | E11: 188.9 | F11: 744 | G11: 690 | H11: 630.7 | I11: 45.8 | J11: 130341 | K11: 140542 | L11: 118660 | M11: 98372 | N11: 96839 | O11: 102676 | P11: 19541 | Q11: 16926 | R11: 8652 | S11: 5 | T11: 40.5 | U11: 44 | V11: 33 | W11: 350205.1 | X11: 97181.8 | Y11: 1212.1 | Z11: 176546 | AA11: 62330 | AB11: 375349 | AC11: 20499 | AD11: 4 | AE11: 69000 | AF11: 1 | AG11: 0 | AH11: 4 | AI11: 0 | AJ11: 0 | AK11: 0 | AL11: 5 | AM11: 1 | AN11: 0 | AO11: 0 | AP11: 0 | AQ11: 197 | AR11: 21 | AS11: 185 | AT11: 96710 | AU11: 118595 | AV11: 355792.8 | AW11: 445917.2 | AX11: 18442.1 | AY11: 15809.6 | AZ11: 174 | BA11: 142 | BB11: 102899 | BC11: 101308 | BD11: 846 | BE11: 616 | BF11: 696 | BG11: 188788.5 | BH11: 87101.1 | BI11: 0 | BJ11: 0 | BK11: 1 | BL11: 1 | BM11: 0 | BN11: 0 | BO11: 0 | BP11: 0 | BQ11: 0 | BR11: 0 | BS11: 0 | BT11: 12 | BU11: 120898 | BV11: 110663 | BW11: 51573641 | BX11: 130341 | BY11: 8040
A12: Group | B12: Entity A1 | C12: Plant 02 | D12: 2026-06 | E12: 188.9 | F12: 720 | G12: 718 | H12: 669.9 | I12: 37.1 | J12: 135630 | K12: 136008 | L12: 120521 | M12: 96232 | N12: 91848 | O12: 97224 | P12: 21417 | Q12: 17596 | R12: 7008 | S12: 4 | T12: 32.6 | U12: 36 | V12: 31 | W12: 321487.9 | X12: 71503.8 | Y12: 1098.9 | Z12: 174177 | AA12: 54970 | AB12: 368624 | AC12: 28075 | AD12: 2 | AE12: 62000 | AF12: 1 | AG12: 0 | AH12: 4 | AI12: 0 | AJ12: 0 | AK12: 0 | AL12: 5 | AM12: 0 | AN12: 2 | AO12: 1 | AP12: 1 | AQ12: 194 | AR12: 21 | AS12: 155 | AT12: 93443 | AU12: 119908 | AV12: 341097.4 | AW12: 450854.1 | AX12: 17509.3 | AY12: 15920 | AZ12: 150 | BA12: 124 | BB12: 98097 | BC12: 96415 | BD12: 1343 | BE12: 630 | BF12: 704 | BG12: 190497.7 | BH12: 86054.4 | BI12: 0 | BJ12: 0 | BK12: 0 | BL12: 1 | BM12: 1 | BN12: 0 | BO12: 0 | BP12: 0 | BQ12: 0 | BR12: 0 | BS12: 0 | BT12: 18 | BU12: 119591 | BV12: 108329 | BW12: 44645372 | BX12: 135630 | BY12: 6878
A13: Group | B13: Entity A1 | C13: Plant 02 | D13: 2026-07 | E13: 188.9 | F13: 744 | G13: 737 | H13: 655.4 | I13: 69.3 | J13: 139219 | K13: 140542 | L13: 122135 | M13: 101413 | N13: 97731 | O13: 108037 | P13: 20571 | Q13: 17916 | R13: 13091 | S13: 6 | T13: 65.7 | U13: 56 | V13: 44 | W13: 350472.9 | X13: 93258.3 | Y13: 1434.2 | Z13: 204288 | AA13: 57701 | AB13: 356252 | AC13: 22870 | AD13: 2 | AE13: 68000 | AF13: 0 | AG13: 1 | AH13: 6 | AI13: 0 | AJ13: 1 | AK13: 0 | AL13: 7 | AM13: 0 | AN13: 1 | AO13: 1 | AP13: 0 | AQ13: 129 | AR13: 15 | AS13: 125 | AT13: 95686 | AU13: 120914 | AV13: 355004.6 | AW13: 454636.6 | AX13: 21552.3 | AY13: 15764.7 | AZ13: 159 | BA13: 128 | BB13: 105180 | BC13: 101093 | BD13: 720 | BE13: 658 | BF13: 772 | BG13: 179819.6 | BH13: 82831.7 | BI13: 0 | BJ13: 0 | BK13: 0 | BL13: 1 | BM13: 1 | BN13: 0 | BO13: 0 | BP13: 0 | BQ13: 0 | BR13: 0 | BS13: 0 | BT13: 12 | BU13: 123620 | BV13: 113701 | BW13: 53958022 | BX13: 139219 | BY13: 13208
A14: Group | B14: Entity A1 | C14: Plant 02 | D14: 2026-08 | E14: 188.9 | F14: 744 | G14: 674 | H14: 603.4 | I14: 53.5 | J14: 127319 | K14: 140542 | L14: 109907 | M14: 90236 | N14: 86596 | O14: 97767 | P14: 22655 | Q14: 18611 | R14: 10106 | S14: 4 | T14: 46.8 | U14: 39 | V14: 37 | W14: 293787.6 | X14: 89718.1 | Y14: 1404.1 | Z14: 164589 | AA14: 62319 | AB14: 347920 | AC14: 23073 | AD14: 3 | AE14: 69000 | AF14: 0 | AG14: 1 | AH14: 5 | AI14: 1 | AJ14: 0 | AK14: 0 | AL14: 8 | AM14: 1 | AN14: 0 | AO14: 0 | AP14: 0 | AQ14: 212 | AR14: 32 | AS14: 95 | AT14: 87463 | AU14: 110393 | AV14: 324045 | AW14: 415077.7 | AX14: 17217.2 | AY14: 16383.2 | AZ14: 157 | BA14: 131 | BB14: 94985 | BC14: 92164 | BD14: 1526 | BE14: 560 | BF14: 665 | BG14: 153621.7 | BH14: 72743.6 | BI14: 0 | BJ14: 0 | BK14: 0 | BL14: 1 | BM14: 0 | BN14: 0 | BO14: 0 | BP14: 0 | BQ14: 0 | BR14: 0 | BS14: 0 | BT14: 10 | BU14: 111815 | BV14: 102323 | BW14: 35614658 | BX14: 127319 | BY14: 8914
A15: Group | B15: Entity A1 | C15: Plant 02 | D15: 2026-09 | E15: 188.9 | F15: 720 | G15: 717 | H15: 624.3 | I15: 78.2 | J15: 135441 | K15: 136008 | L15: 121475 | M15: 97250 | N15: 95233 | O15: 102279 | P15: 20791 | Q15: 17994 | R15: 14772 | S15: 6 | T15: 68.5 | U15: 33 | V15: 27 | W15: 308111 | X15: 70784.4 | Y15: 940.2 | Z15: 245659 | AA15: 68824 | AB15: 358135 | AC15: 24322 | AD15: 4 | AE15: 95000 | AF15: 0 | AG15: 0 | AH15: 2 | AI15: 0 | AJ15: 1 | AK15: 0 | AL15: 6 | AM15: 1 | AN15: 2 | AO15: 1 | AP15: 1 | AQ15: 225 | AR15: 36 | AS15: 65 | AT15: 94217 | AU15: 121397 | AV15: 346059.3 | AW15: 456452.7 | AX15: 20557.3 | AY15: 16054.5 | AZ15: 173 | BA15: 147 | BB15: 103840 | BC15: 101122 | BD15: 1125 | BE15: 658 | BF15: 772 | BG15: 171707.4 | BH15: 73868.5 | BI15: 0 | BJ15: 0 | BK15: 0 | BL15: 1 | BM15: 1 | BN15: 0 | BO15: 0 | BP15: 0 | BQ15: 0 | BR15: 0 | BS15: 0 | BT15: 4 | BU15: 121378 | BV15: 108581 | BW15: 36663480 | BX15: 135441 | BY15: 15611
... A39: Group | B39: Entity A2 | C39: Plant 06 | D39: 2026-09 | E39: 158.2 | F39: 720 | G39: 712 | H39: 680.7 | I39: 13.4 | J39: 112638 | K39: 113904 | L39: 98037 | M39: 97437 | N39: 94388 | O39: 101633 | P39: 20587 | Q39: 17410 | R39: 2120 | S39: 1 | T39: 6.5 | U39: 36 | V39: 34 | W39: 262617.2 | X39: 65862.8 | Y39: 1573 | Z39: 230619 | AA39: 63239 | AB39: 287280 | AC39: 5880 | AD39: 1 | AE39: 89000 | AF39: 0 | AG39: 1 | AH39: 9 | AI39: 0 | AJ39: 0 | AK39: 0 | AL39: 5 | AM39: 1 | AN39: 0 | AO39: 0 | AP39: 1 | AQ39: 125 | AR39: 3 | AS39: 110 | AT39: 96056 | AU39: 97878 | AV39: 363110.2 | AW39: 368021.3 | AX39: 14652.5 | AY39: 13440.5 | AZ39: 151 | BA39: 137 | BB39: 100510 | BC39: 95543 | BD39: 1310 | BE39: 616 | BF39: 609 | BG39: 146401.1 | BH39: 58367 | BI39: 0 | BJ39: 0 | BK39: 1 | BL39: 0 | BM39: 0 | BN39: 0 | BO39: 0 | BP39: 0 | BQ39: 0 | BR39: 0 | BS39: 0 | BT39: 99 | BU39: 99398 | BV39: 100389 | BW39: 33437653 | BX39: 112638 | BY39: 2024

Sheet Parameters
A1: Name | B1: Value | C1: Meaning
A2: TaxRate | B2: 0.25 | C2: Tax rate used for after-tax return
A3: WACC | B3: 0.095 | C3: Cost of capital, per year
A4: CovenantMax | B4: 2.5 | C4: Covenant limit: net debt ÷ EBITDA (times)
A5: OpeningNWC_A1 | B5: 2109562.8 | C5: Net working capital at 31 Mar 2026, Entity A1 (₹ thousand)
A6: OpeningNWC_A2 | B6: 759330.2 | C6: Net working capital at 31 Mar 2026, Entity A2 (₹ thousand)
A7: OpeningNWC | B7: =B5+B6 | C7: Net working capital at 31 Mar 2026, Group (₹ thousand)

Sheet About
A1: Owner lens KPI model: every KPI on the Owner screens and how it is calculated, bottom up
A2: Owner KPIs: the 118 KPIs that appear on the 21 Owner-lens screens (O-01 to O-09, Owner views of G-08, S-03 and S-08, S-04 to S-11, and the large-display, mobile and state-gallery variants). The Owner lens is the Group-wide view, so each KPI is calculated from the Group totals. One row per KPI, one column per month; every value is a live formula.
A3: Owner Screens: every place a KPI appears on an Owner screen (card, tile or table row), what the screen shows today, and the model's value for the same scope in Sep 2026. Most are Group; a few drill-ins show Entity A1 or Plant 02, and those use the same formula on that entity's or plant's inputs.
A4: Group Inputs: each input is the sum of Entity A1 and Entity A2 (or the lowest, for days to permit expiry and days to breach). Blue columns are building blocks calculated from those inputs, such as EBITDA and net working capital.
A5: Entity Inputs: inputs that come from plants are the sum of the entity's 3 plants. Yellow inputs only exist at entity level (finance, cash, treasury, capex, programmes, contracts, controls, governance, data trust, workflow).
A6: Plant Inputs: the plant data. The first 40 input columns are plant_base.csv unchanged; the rest are added for sales, supply, regulatory and forecast KPIs.
A7: Parameters: tax rate, cost of capital, covenant limit and opening working capital used by some formulas.
A8: Rule: KPIs are always recalculated from the Group totals. They are never averages of entity or plant KPIs.
A9: All data is synthetic. Formulas are working assumptions until the KPI catalogue definitions are approved.
A10: Some IDs on the mockups measure the same thing and so show the same value: OPS-005 = OPS-003, OPS-006 = PLT-002, OPS-004 = OPS-002, PRG-004 = STR-002, RSK-003 = CMP-005 = REG-010.
