Workbook

Sheet Read Me
A1: KPI lineage model: every KPI on the mockups, calculated bottom up
A2: All data is synthetic (mock) data. plant_base.csv is the original plant data; the other inputs were added so every KPI on the mockups can be calculated. Every KPI value in this workbook is a live formula; click any value to see it.
A4: How the numbers flow
A5: 1. Plant Inputs: one row per plant per month (6 plants × Apr–Sep 2026).
A6: 2. Entity Inputs: each plant input is the sum of the entity's 3 plants (Entity A1 = Plants 01–03, A2 = Plants 04–06); days to permit expiry, days to breach and disclosure clock take the lowest. Yellow inputs only exist at entity level (finance, cash, treasury, capex, programmes, controls, governance, data trust, workflow). Blue columns are building blocks (EBITDA, net working capital, DSO …) calculated from the inputs.
A7: 3. Group Inputs: each input is the sum (or lowest) of Entity A1 and Entity A2, with the same building blocks.
A8: 4. Plant KPIs, Entity KPIs, Group KPIs: the same formula applied at each level to that level's own totals. A KPI is never an average of the level below. Plant KPIs exist only where every input exists at plant level.
A10: Sheets
A11: Coverage: every KPI ID on the mockups, whether it is in this workbook, which lenses and screens show it.
A12: KPI Register: one row per KPI with its formula, inputs, where the inputs come from, the bottom-up path, the Sep 2026 value at every plant, entity and the Group, and what the mockups show.
A13: Lineage (Sep 2026): for each KPI, every input traced from the 6 plants to the 2 entities to the Group, then the result at each level.
A14: Screen Values: every KPI on every mockup screen (Owner, Core Group, Entity lenses), the value shown, the calculated value for the same scope, and Same / Different (at the precision the screen shows).
... A18: Formulas are working assumptions until the KPI catalogue definitions are approved. Some IDs on the mockups are the same measure and show the same value: OPS-005 = OPS-003, OPS-006 = PLT-002, OPS-004 = OPS-002, PRG-004 = STR-002, RSK-003 = CMP-005 = REG-010.

Sheet Coverage
A1: Coverage of the mockup KPIs
A2: 160 KPI IDs appear on the mockups, 556 times in total. Covered in this workbook: 160 of 160.
A4: KPI ID | B4: Measure | C4: In this workbook | D4: Calculated at | E4: Owner screens | F4: Core Group screens | G4: Entity screens | H4: Screens | I4: Appearances
A5: CMP-005 | B5: Regulatory breaches YTD (same measure as REG-010) | C5: Yes | D5: Plant, Entity, Group | E5: 1 | G5: 1 | H5: E-01, O-01 | I5: 2
A6: CON-001 | B6: Contracts expiring, next 90 days | C6: Yes | D6: Entity, Group | E6: 1 | F6: 1 | G6: 2 | H6: E-04, E-07, G-07, O-05 | I6: 5
A7: CON-002 | B7: Contract-compliance rate | C7: Yes | D7: Entity, Group | E7: 1 | F7: 1 | G7: 2 | H7: E-04, E-07, G-07, O-05 | I7: 4
A8: CON-003 | B8: Supplier EHS non-compliance | C8: Yes | D8: Entity, Group | E8: 1 | F8: 2 | G8: 2 | H8: E-04, E-07, G-05, G-07, O-05 | I8: 5
A9: CPX-001 | B9: Approved capex budget | C9: Yes | D9: Entity, Group | E9: 1 | F9: 1 | G9: 1 | H9: E-06, G-06, O-04 | I9: 3
A10: CPX-002 | B10: Committed capex | C10: Yes | D10: Entity, Group | E10: 1 | F10: 1 | G10: 1 | H10: E-06, G-06, O-04 | I10: 3
A11: CPX-003 | B11: Capex actual spend YTD | C11: Yes | D11: Entity, Group | E11: 1 | F11: 1 | G11: 1 | H11: E-06, G-06, O-04 | I11: 3
A12: CPX-004 | B12: Capex physical progress, weighted | C12: Yes | D12: Entity, Group | E12: 4 | F12: 3 | G12: 1 | H12: E-06, G-01, G-01 · after T7, G-06, O-01, O-04, STATE GALLERY · O-01 + S-02, O-01 · large display ≥ 1600 | I12: 8
A13: CSH-001 | B13: Cash position | C13: Yes | D13: Entity, Group | E13: 1 | F13: 1 | G13: 1 | H13: E-05, G-04, O-03 | I13: 3
A14: CSH-002 | B14: Cash released YTD | C14: Yes | D14: Entity, Group | E14: 1 | F14: 1 | G14: 1 | H14: E-05, G-04, O-03 | I14: 3
A15: CSH-003 | B15: Daily collections | C15: Yes | D15: Entity, Group | E15: 2 | F15: 1 | G15: 2 | H15: E-01, E-05, G-04, O-03, S-11 | I15: 5
A16: CSH-004 | B16: Cash-conversion cycle | C16: Yes | D16: Entity, Group | E16: 1 | F16: 1 | G16: 1 | H16: E-05, G-04, O-03 | I16: 3
A17: CSH-006 | B17: Cash-upstream exposure | C17: Yes | D17: Entity, Group | E17: 2 | F17: 1 | G17: 2 | H17: E-01, E-05, G-04, O-03, S-11 | I17: 5
... A19: CST-002 | B19: Variable cost | C19: Yes | D19: Plant, Entity, Group | E19: 1 | F19: 1 | G19: 2 | H19: E-02, E-11, G-03, O-09 | I19: 4
A20: CST-003 | B20: Fuel cost | C20: Yes | D20: Plant, Entity, Group | E20: 1 | G20: 1 | H20: E-02, O-09 | I20: 2
A21: CST-004 | B21: Power cost per tonne | C21: Yes | D21: Plant, Entity, Group | E21: 1 | H21: O-09 | I21: 1
A22: CST-005 | B22: Fixed cost YTD | C22: Yes | D22: Plant, Entity, Group | G22: 1 | H22: E-11 | I22: 1
A23: CTL-002 | B23: Control failures YTD | C23: Yes | D23: Entity, Group | E23: 1 | F23: 1 | G23: 1 | H23: E-07, G-07, O-05 | I23: 3
A24: CTL-003 | B24: Assurance reviews completed | C24: Yes | D24: Entity, Group | F24: 1 | H24: G-07 | I24: 1
A25: CTL-004 | B25: High-severity control failures YTD | C25: Yes | D25: Entity, Group | E25: 1 | F25: 1 | H25: G-07, O-05 | I25: 2
A26: CTL-005 | B26: Policy exceptions YTD | C26: Yes | D26: Entity, Group | E26: 1 | F26: 1 | G26: 1 | H26: E-07, G-07, O-05 | I26: 3
A27: CTL-006 | B27: Unauthorised-vendor usage YTD | C27: Yes | D27: Entity, Group | E27: 1 | F27: 1 | G27: 2 | H27: E-04, E-07, G-07, O-05 | I27: 4
A28: CTL-007 | B28: Segregation-of-duties exceptions YTD | C28: Yes | D28: Entity, Group | E28: 1 | F28: 1 | G28: 1 | H28: E-07, G-07, O-05 | I28: 3
A29: CTL-008 | B29: Unauthorised-access events YTD | C29: Yes | D29: Entity, Group | E29: 1 | F29: 1 | G29: 1 | H29: E-07, G-07, O-05 | I29: 3
A30: CTL-009 | B30: Data-sharing exceptions YTD | C30: Yes | D30: Entity, Group | E30: 1 | F30: 1 | G30: 1 | H30: E-07, G-07, O-05 | I30: 3
A31: CTL-010 | B31: Manual overrides YTD | C31: Yes | D31: Entity, Group | E31: 1 | F31: 1 | G31: 1 | H31: E-07, G-07, O-05 | I31: 3
A32: EFF-002 | B32: Open critical alerts | C32: Yes | D32: Entity, Group | E32: 3 | F32: 5 | G32: 2 | H32: E-01, E-09, G-01, G-01 · after T7, G-02, G-07, G-09, O-01, STATE GALLERY · O-01 + S-02, O-01 · large display ≥ 1600 | I32: 10
A33: EFF-006 | B33: Alerts without accepted owners | C33: Yes | D33: Entity, Group | F33: 1 | H33: G-09 | I33: 1
A34: EFF-007 | B34: Overdue actions | C34: Yes | D34: Entity, Group | F34: 1 | G34: 2 | H34: E-01, E-09, G-09 | I34: 3
A35: EFF-008 | B35: Average resolution time | C35: Yes | D35: Entity, Group | E35: 1 | F35: 1 | G35: 1 | H35: E-09, G-09, O-06 | I35: 3
A36: EFF-009 | B36: Closed escalations, last 30 days | C36: Yes | D36: Entity, Group | E36: 1 | F36: 1 | G36: 1 | H36: E-09, G-09, O-06 | I36: 3
A37: EFF-010 | B37: Repeat issues, last 90 days | C37: Yes | D37: Entity, Group | E37: 1 | F37: 1 | G37: 1 | H37: E-09, G-09, O-06 | I37: 3
A38: EFF-011 | B38: Root causes eliminated YTD | C38: Yes | D38: Entity, Group | E38: 1 | F38: 1 | G38: 1 | H38: E-09, G-09, O-06 | I38: 3
A39: EHS-001 | B39: TRIR | C39: Yes | D39: Plant, Entity, Group | E39: 1 | F39: 1 | G39: 1 | H39: E-07, G-07, O-05 | I39: 4
A40: EHS-002 | B40: Severity incidents | C40: Yes | D40: Plant, Entity, Group | E40: 1 | F40: 3 | G40: 1 | H40: E-07, G-01, G-01 · after T7, G-07, O-05 | I40: 5
A41: EHS-003 | B41: Near misses | C41: Yes | D41: Plant, Entity, Group | E41: 1 | F41: 1 | G41: 1 | H41: E-07, G-07, O-05 | I41: 3
A42: EHS-004 | B42: Critical safety incidents | C42: Yes | D42: Plant, Entity, Group | E42: 1 | F42: 1 | G42: 1 | H42: E-07, G-07, O-05 | I42: 3
A43: EHS-005 | B43: Environmental excursions | C43: Yes | D43: Plant, Entity, Group | E43: 1 | F43: 1 | G43: 1 | H43: E-07, G-07, O-05 | I43: 3
A44: EHS-006 | B44: Open EHS corrective actions | C44: Yes | D44: Plant, Entity, Group | F44: 1 | G44: 1 | H44: E-07, G-07 | I44: 2
A45: EHS-007 | B45: Overdue EHS actions | C45: Yes | D45: Plant, Entity, Group | E45: 1 | F45: 1 | G45: 1 | H45: E-07, G-07, O-05 | I45: 4
A46: EHS-008 | B46: EHS escalation clocks running | C46: Yes | D46: Plant, Entity, Group | E46: 1 | F46: 1 | G46: 1 | H46: E-07, G-07, O-05 | I46: 3
A47: EHS-009 | B47: EHS investigation completion | C47: Yes | D47: Plant, Entity, Group | F47: 1 | G47: 1 | H47: E-07, G-07 | I47: 2
A48: EHS-010 | B48: EHS investigation completion rate YTD | C48: Yes | D48: Plant, Entity, Group | F48: 1 | H48: G-07 | I48: 1
A49: FIN-001 | B49: EBITDA YTD | C49: Yes | D49: Entity, Group | E49: 3 | F49: 4 | G49: 2 | H49: E-01, E-11, G-01, G-01 · after T7, G-02, G-03, O-01, STATE GALLERY · O-01 + S-02, O-01 · large display ≥ 1600 | I49: 9
A50: FIN-002 | B50: EBIT YTD | C50: Yes | D50: Entity, Group | E50: 3 | F50: 3 | G50: 2 | H50: E-01, E-11, G-01, G-01 · after T7, G-03, O-01, STATE GALLERY · O-01 + S-02, O-01 · large display ≥ 1600 | I50: 10
A51: FIN-003 | B51: Revenue YTD | C51: Yes | D51: Plant, Entity, Group | E51: 3 | F51: 4 | G51: 2 | H51: E-01, E-11, G-01, G-01 · after T7, G-02, G-03, O-01, STATE GALLERY · O-01 + S-02, O-01 · large display ≥ 1600 | I51: 11
A52: FIN-004 | B52: Free cash flow YTD | C52: Yes | D52: Entity, Group | E52: 4 | F52: 3 | G52: 2 | H52: E-01, E-11, G-01, G-01 · after T7, G-03, O-01, O-03, STATE GALLERY · O-01 + S-02, O-01 · large display ≥ 1600 | I52: 9
A53: FIN-005 | B53: ROCE, annualised | C53: Yes | D53: Entity, Group | E53: 3 | F53: 3 | G53: 2 | H53: E-01, E-11, G-01, G-01 · after T7, G-03, O-01, STATE GALLERY · O-01 + S-02, O-01 · large display ≥ 1600 | I53: 10
A54: FIN-006 | B54: Net debt | C54: Yes | D54: Entity, Group | E54: 4 | F54: 3 | H54: G-01, G-01 · after T7, G-03, O-01, O-03, STATE GALLERY · O-01 + S-02, O-01 · large display ≥ 1600 | I54: 7
A55: FIN-007 | B55: Shareholder-value indicator (economic profit YTD) | C55: Yes | D55: Entity, Group | E55: 3 | F55: 1 | H55: G-03, O-01, STATE GALLERY · O-01 + S-02, O-01 · large display ≥ 1600 | I55: 4
A56: FIN-008 | B56: FCF conversion (FCF ÷ EBITDA) | C56: Yes | D56: Entity, Group | F56: 1 | H56: G-03 | I56: 1
A57: GOV-001 | B57: Ageing certification approvals | C57: Yes | D57: Entity, Group | E57: 1 | F57: 1 | G57: 1 | H57: E-08, G-08, G-08 · Owner depth | I57: 3
A58: GOV-002 | B58: KPI overrides | C58: Yes | D58: Entity, Group | E58: 1 | F58: 1 | G58: 1 | H58: E-08, G-08, G-08 · Owner depth | I58: 4
A59: GOV-003 | B59: Recurring data-quality issues | C59: Yes | D59: Entity, Group | E59: 1 | F59: 1 | G59: 1 | H59: E-08, G-08, G-08 · Owner depth | I59: 3
A60: GOV-004 | B60: Open audit findings | C60: Yes | D60: Entity, Group | E60: 2 | F60: 2 | G60: 2 | H60: E-07, E-08, G-07, G-08, G-08 · Owner depth, O-05 | I60: 6
A61: GOV-005 | B61: Overdue assurance actions | C61: Yes | D61: Entity, Group | E61: 1 | F61: 1 | G61: 1 | H61: E-08, G-08, G-08 · Owner depth | I61: 3
A62: GOV-006 | B62: Repeat findings | C62: Yes | D62: Entity, Group | E62: 1 | F62: 1 | G62: 1 | H62: E-08, G-08, G-08 · Owner depth | I62: 3
A63: GOV-007 | B63: Leadership KPIs affected by findings | C63: Yes | D63: Entity, Group | E63: 1 | F63: 1 | H63: G-08, G-08 · Owner depth | I63: 4
A64: GOV-008 | B64: Evidence completeness rate | C64: Yes | D64: Entity, Group | E64: 1 | F64: 1 | G64: 1 | H64: E-08, G-08, G-08 · Owner depth | I64: 4
A65: GOV-009 | B65: Average finding-closure time | C65: Yes | D65: Entity, Group | E65: 1 | F65: 1 | G65: 1 | H65: E-08, G-08, G-08 · Owner depth | I65: 3
A66: LIQ-001 | B66: Liquidity runway | C66: Yes | D66: Entity, Group | E66: 1 | F66: 1 | G66: 1 | H66: E-05, G-04, O-03 | I66: 3
A67: LIQ-002 | B67: Covenant headroom | C67: Yes | D67: Entity, Group | E67: 1 | F67: 1 | G67: 1 | H67: E-05, G-04, O-03 | I67: 3
A68: LIQ-003 | B68: Debt-maturity exposure, next 12 months | C68: Yes | D68: Entity, Group | E68: 1 | F68: 1 | G68: 1 | H68: E-05, G-04, O-03 | I68: 3
A69: LIQ-004 | B69: Financing exposure (floating-rate debt) | C69: Yes | D69: Entity, Group | E69: 1 | F69: 1 | H69: G-04, O-03 | I69: 2
A70: OPS-001 | B70: Production vs plan | C70: Yes | D70: Plant, Entity, Group | E70: 6 | F70: 6 | G70: 4 | H70: E-01, E-02, E-05, G-01, G-01 · after T7, G-02, G-03, G-05, O-01, O-09, S-03, S-03 · Entity view, S-03 · Owner view, S-10, STATE GALLERY · O-01 + S-02, O-01 · large display ≥ 1600 | I70: 16
A71: OPS-002 | B71: Sales vs plan | C71: Yes | D71: Plant, Entity, Group | E71: 3 | F71: 3 | G71: 1 | H71: E-01, G-01, G-01 · after T7, G-03, O-01, STATE GALLERY · O-01 + S-02, O-01 · large display ≥ 1600 | I71: 7
A72: OPS-003 | B72: Capacity utilization | C72: Yes | D72: Plant, Entity, Group | E72: 3 | F72: 1 | G72: 1 | H72: E-02, G-05, O-01, STATE GALLERY · O-01 + S-02, O-01 · large display ≥ 1600 | I72: 5
A73: OPS-004 | B73: Sales vs plan · Group (same measure as OPS-002) | C73: Yes | D73: Plant, Entity, Group | E73: 1 | H73: O-01 | I73: 1
A74: OPS-005 | B74: Capacity utilisation (same measure as OPS-003) | C74: Yes | D74: Plant, Entity, Group | E74: 2 | F74: 2 | G74: 1 | H74: E-01, G-01, G-01 · after T7, O-01, O-09 | I74: 5
A75: OPS-006 | B75: OEE · Group weighted (same measure as PLT-002) | C75: Yes | D75: Plant, Entity, Group | E75: 1 | H75: O-09 | I75: 1
A76: PLT-001 | B76: Asset utilization | C76: Yes | D76: Plant, Entity, Group | G76: 1 | H76: E-02 | I76: 1
A77: PLT-002 | B77: OEE | C77: Yes | D77: Plant, Entity, Group | F77: 1 | G77: 1 | H77: E-02, G-05 | I77: 2
A78: PLT-004 | B78: Recovery percentage | C78: Yes | D78: Plant, Entity, Group | G78: 1 | H78: E-02 | I78: 1
A79: PLT-005 | B79: Yield | C79: Yes | D79: Plant, Entity, Group | G79: 1 | H79: E-02 | I79: 1
A80: PRD-001 | B80: Days to breach (earliest plant) | C80: Yes | D80: Plant, Entity, Group | E80: 6 | F80: 1 | G80: 3 | H80: E-01, E-04, O-01, O-02, O-09, S-10, S-12, S-12 · Entity view, STATE GALLERY · O-01 + S-02, O-01 · large display ≥ 1600 | I80: 10
A81: PRD-002 | B81: Probability of production plan miss, next month | C81: Yes | D81: Plant, Entity, Group | E81: 4 | F81: 4 | G81: 1 | H81: G-01, G-01 · after T7, G-10, O-01, O-02, S-12, S-12 · Entity view, STATE GALLERY · O-01 + S-02, O-01 · large display ≥ 1600 | I81: 9
A82: PRD-003 | B82: Projected EBITDA gap, rest of year | C82: Yes | D82: Entity, Group | E82: 5 | F82: 5 | G82: 1 | H82: G-01, G-01 · after T7, G-03, G-10, O-01, O-02, S-09, S-12, S-12 · Entity view, STATE GALLERY · O-01 + S-02, O-01 · large display ≥ 1600 | I82: 11
A83: PRD-004 | B83: Projected liquidity gap, next 90 days | C83: Yes | D83: Entity, Group | E83: 2 | F83: 4 | G83: 1 | H83: G-01, G-01 · after T7, G-04, O-02, O-03, S-12, S-12 · Entity view | I83: 7
A84: PRD-005 | B84: Forecast covenant breach | C84: Yes | D84: Entity, Group | E84: 2 | F84: 3 | G84: 1 | H84: G-04, G-10, O-02, O-03, S-12, S-12 · Entity view | I84: 7
A85: PRD-006 | B85: Production loss from downtime, next month | C85: Yes | D85: Plant, Entity, Group | E85: 1 | F85: 2 | H85: G-05, G-10, O-09 | I85: 4
A86: PRD-007 | B86: Probability OEE below 78%, next month | C86: Yes | D86: Plant, Entity, Group | E86: 1 | H86: O-09 | I86: 1
A87: PRD-008 | B87: Projected FCF gap, full year | C87: Yes | D87: Entity, Group | G87: 1 | H87: E-11 | I87: 1
A88: PRD-009 | B88: ROCE at P12 (forecast) | C88: Yes | D88: Entity, Group | G88: 1 | H88: E-11 | I88: 1
A89: PRD-010 | B89: Revenue per FTE | C89: Yes | D89: Plant, Entity, Group | G89: 1 | H89: E-11 | I89: 1
A90: PRD-011 | B90: Tonnes per FTE | C90: Yes | D90: Plant, Entity, Group | G90: 1 | H90: E-11 | I90: 1
A91: PRD-012 | B91: Probability of EBITDA plan miss, full year | C91: Yes | D91: Entity, Group | G91: 1 | H91: E-11 | I91: 1
A92: PRG-001 | B92: Capex project status | C92: Yes | D92: Entity, Group | E92: 1 | F92: 1 | H92: G-06, O-04 | I92: 2
A93: PRG-002 | B93: Benefits realisation | C93: Yes | D93: Entity, Group | E93: 1 | F93: 1 | G93: 1 | H93: E-06, G-06, O-04 | I93: 3
A94: PRG-003 | B94: Delayed projects | C94: Yes | D94: Entity, Group | E94: 1 | F94: 1 | G94: 1 | H94: E-06, G-06, O-04 | I94: 4
A95: PRG-004 | B95: Capex / transformation progress (same measure as STR-002) | C95: Yes | D95: Entity, Group | E95: 2 | F95: 2 | G95: 1 | H95: E-01, G-01, G-01 · after T7, O-01, O-04 | I95: 5
A96: PRG-005 | B96: Transformation initiative status | C96: Yes | D96: Entity, Group | E96: 1 | G96: 1 | H96: E-06, O-04 | I96: 2
A97: REG-001 | B97: Pending filings | C97: Yes | D97: Plant, Entity, Group | F97: 1 | G97: 1 | H97: E-07, G-07 | I97: 2
A98: REG-002 | B98: Regulatory deadlines, next 30 days | C98: Yes | D98: Plant, Entity, Group | F98: 1 | G98: 1 | H98: E-07, G-07 | I98: 2
A99: REG-003 | B99: Licence expirations, next 12 months | C99: Yes | D99: Plant, Entity, Group | F99: 1 | G99: 1 | H99: E-07, G-07 | I99: 2
A100: REG-004 | B100: Regulatory obligations due, next 30 days | C100: Yes | D100: Plant, Entity, Group | F100: 1 | G100: 1 | H100: E-07, G-07 | I100: 2
A101: REG-005 | B101: Overdue regulatory obligations | C101: Yes | D101: Plant, Entity, Group | E101: 1 | F101: 1 | G101: 1 | H101: E-07, G-07, O-05 | I101: 3
A102: REG-006 | B102: Licence or permit expiry clock | C102: Yes | D102: Plant, Entity, Group | E102: 1 | G102: 1 | H102: E-07, O-05 | I102: 2
...

Sheet KPI Register
A1: KPI ID | B1: Measure | C1: Unit | D1: Time basis | E1: How it is calculated | F1: Formula with input names | G1: Inputs used | H1: Where the inputs come from | I1: Calculated at | J1: Bottom-up path | K1: Plant 01, Sep 2026 | L1: Plant 02, Sep 2026 | M1: Plant 03, Sep 2026 | N1: Plant 04, Sep 2026 | O1: Plant 05, Sep 2026 | P1: Plant 06, Sep 2026 | Q1: Entity A1, Sep 2026 | R1: Entity A2, Sep 2026 | S1: Group, Sep 2026 | T1: Shown on the mockups (value · lens · screen) | U1: Screen appearances: same / different
A2: OPS-001 | B2: Production vs plan | C2: % | D2: Month | E2: Good output ÷ Planned production × 100 | F2: IFERROR(100*good_output_t/planned_production_t,0) | G2: planned_production_t, good_output_t | H2: Original plant data (plant_base.csv, synthetic) | I2: Plant, Entity, Group | J2: Plant inputs → each plant's KPI; Plant inputs summed to each entity → entity KPI; entities summed to Group → Group KPI (recalculated from totals, never averaged) | K2: ='Plant KPIs'!K2 -> 96.03 | L2: ='Plant KPIs'!Q2 -> 78.4 | M2: ='Plant KPIs'!W2 -> 99.52 | N2: ='Plant KPIs'!AC2 -> 103.35 | O2: ='Plant KPIs'!AI2 -> 101.46 | P2: ='Plant KPIs'!AO2 -> 96.28 | Q2: ='Entity KPIs'!K2 -> 91.27 | R2: ='Entity KPIs'!Q2 -> 100.29 | S2: ='Group KPIs'!K2 -> 95.51 | T2: 103.2 % of plan (flash) · Entity E-01, Entity E-02, Entity E-05, Core Group S-03, Entity S-03, Owner S-03; 98.1 % of plan · Core Group G-01, Core Group G-02, Core Group G-05, Owner O-01, Owner O-09, Owner STATE GALLERY; 97.8 % of plan · Core Group G-01; 98.1% · Core Group G-03; 100.2 % of plan · Owner S-10 | U2: 0 same / 16 different
A3: OPS-003 | B3: Capacity utilization | C3: % | D3: Month | E3: Good output ÷ Installed capacity × 100 | F3: IFERROR(100*good_output_t/installed_capacity_t,0) | G3: installed_capacity_t, good_output_t | H3: Original plant data (plant_base.csv, synthetic) | I3: Plant, Entity, Group | J3: Plant inputs → each plant's KPI; Plant inputs summed to each entity → entity KPI; entities summed to Group → Group KPI (recalculated from totals, never averaged) | K3: ='Plant KPIs'!K3 -> 82.92 | L3: ='Plant KPIs'!Q3 -> 70.02 | M3: ='Plant KPIs'!W3 -> 86.09 | N3: ='Plant KPIs'!AC3 -> 89.48 | O3: ='Plant KPIs'!AI3 -> 89.96 | P3: ='Plant KPIs'!AO3 -> 82.87 | Q3: ='Entity KPIs'!K3 -> 79.8 | R3: ='Entity KPIs'!Q3 -> 87.55 | S3: ='Group KPIs'!K3 -> 83.44 | T3: 88 % · Entity E-02; 86 % · Core Group G-05; 86% · Owner O-01, Owner STATE GALLERY | U3: 0 same / 5 different
A4: PLT-001 | B4: Asset utilization | C4: % | D4: Month | E4: Run hours ÷ Calendar hours × 100 | F4: IFERROR(100*run_hours/calendar_hours,0) | G4: calendar_hours, run_hours | H4: Original plant data (plant_base.csv, synthetic) | I4: Plant, Entity, Group | J4: Plant inputs → each plant's KPI; Plant inputs summed to each entity → entity KPI; entities summed to Group → Group KPI (recalculated from totals, never averaged) | K4: ='Plant KPIs'!K4 -> 92.29 | L4: ='Plant KPIs'!Q4 -> 86.71 | M4: ='Plant KPIs'!W4 -> 96.58 | N4: ='Plant KPIs'!AC4 -> 95.92 | O4: ='Plant KPIs'!AI4 -> 95.82 | P4: ='Plant KPIs'!AO4 -> 94.54 | Q4: ='Entity KPIs'!K4 -> 91.86 | R4: ='Entity KPIs'!Q4 -> 95.43 | S4: ='Group KPIs'!K4 -> 93.64 | T4: 82 % · Entity E-02 | U4: 0 same / 1 different
A5: PLT-002 | B5: OEE | C5: % | D5: Month | E5: Availability × Performance × Quality = Good output ÷ Ideal output × 100 | F5: IFERROR(100*good_output_t/ideal_output_t,0) | G5: ideal_output_t, good_output_t | H5: Original plant data (plant_base.csv, synthetic) | I5: Plant, Entity, Group | J5: Plant inputs → each plant's KPI; Plant inputs summed to each entity → entity KPI; entities summed to Group → Group KPI (recalculated from totals, never averaged) | K5: ='Plant KPIs'!K5 -> 83.97 | L5: ='Plant KPIs'!Q5 -> 70.31 | M5: ='Plant KPIs'!W5 -> 86.21 | N5: ='Plant KPIs'!AC5 -> 89.73 | O5: ='Plant KPIs'!AI5 -> 91.23 | P5: ='Plant KPIs'!AO5 -> 83.8 | Q5: ='Entity KPIs'!K5 -> 80.21 | R5: ='Entity KPIs'!Q5 -> 88.44 | S5: ='Group KPIs'!K5 -> 84.07 | T5: 74 % · Entity E-02; 78 % · Core Group G-05 | U5: 0 same / 2 different
A6: PLT-004 | B6: Recovery percentage | C6: % | D6: Month | E6: Valuable content recovered ÷ Valuable content in feed × 100 | F6: IFERROR(100*recovered_contained_t/feed_contained_t,0) | G6: feed_contained_t, recovered_contained_t | H6: Original plant data (plant_base.csv, synthetic) | I6: Plant, Entity, Group | J6: Plant inputs → each plant's KPI; Plant inputs summed to each entity → entity KPI; entities summed to Group → Group KPI (recalculated from totals, never averaged) | K6: ='Plant KPIs'!K6 -> 91.69 | L6: ='Plant KPIs'!Q6 -> 86.55 | M6: ='Plant KPIs'!W6 -> 85.7 | N6: ='Plant KPIs'!AC6 -> 88.37 | O6: ='Plant KPIs'!AI6 -> 88.33 | P6: ='Plant KPIs'!AO6 -> 84.57 | Q6: ='Entity KPIs'!K6 -> 87.47 | R6: ='Entity KPIs'!Q6 -> 87.23 | S6: ='Group KPIs'!K6 -> 87.35 | T6: 91.3 % · Entity E-02 | U6: 0 same / 1 different
A7: PLT-005 | B7: Yield | C7: % | D7: Month | E7: Good output ÷ Feed input × 100 | F7: IFERROR(100*good_output_t/feed_input_t,0) | G7: good_output_t, feed_input_t | H7: Original plant data (plant_base.csv, synthetic) | I7: Plant, Entity, Group | J7: Plant inputs → each plant's KPI; Plant inputs summed to each entity → entity KPI; entities summed to Group → Group KPI (recalculated from totals, never averaged) | K7: ='Plant KPIs'!K7 -> 91.48 | L7: ='Plant KPIs'!Q7 -> 93.11 | M7: ='Plant KPIs'!W7 -> 90.37 | N7: ='Plant KPIs'!AC7 -> 90.59 | O7: ='Plant KPIs'!AI7 -> 93.25 | P7: ='Plant KPIs'!AO7 -> 92.87 | Q7: ='Entity KPIs'!K7 -> 91.46 | R7: ='Entity KPIs'!Q7 -> 92.42 | S7: ='Group KPIs'!K7 -> 91.93 | T7: 94.1 % · Entity E-02 | U7: 0 same / 1 different
A8: REL-001 | B8: MTBF | C8: h | D8: Month | E8: Run hours ÷ Breakdowns | F8: IFERROR(run_hours/failures,0) | G8: run_hours, failures | H8: Original plant data (plant_base.csv, synthetic) | I8: Plant, Entity, Group | J8: Plant inputs → each plant's KPI; Plant inputs summed to each entity → entity KPI; entities summed to Group → Group KPI (recalculated from totals, never averaged) | K8: ='Plant KPIs'!K8 -> 166.13 | L8: ='Plant KPIs'!Q8 -> 104.05 | M8: ='Plant KPIs'!W8 -> 347.7 | N8: ='Plant KPIs'!AC8 -> 690.6 | O8: ='Plant KPIs'!AI8 -> 689.9 | P8: ='Plant KPIs'!AO8 -> 680.7 | Q8: ='Entity KPIs'!K8 -> 165.35 | R8: ='Entity KPIs'!Q8 -> 687.07 | S8: ='Group KPIs'!K8 -> 269.69 | T8: 212 h · Entity E-03; 205 h · Core Group G-05, Owner O-09 | U8: 0 same / 4 different
A9: REL-002 | B9: Mean Time to Repair | C9: h | D9: Month | E9: Repair hours ÷ Breakdowns | F9: IFERROR(repair_hours/failures,0) | G9: failures, repair_hours | H9: Original plant data (plant_base.csv, synthetic) | I9: Plant, Entity, Group | J9: Plant inputs → each plant's KPI; Plant inputs summed to each entity → entity KPI; entities summed to Group → Group KPI (recalculated from totals, never averaged) | K9: ='Plant KPIs'!K9 -> 5.4 | L9: ='Plant KPIs'!Q9 -> 11.42 | M9: ='Plant KPIs'!W9 -> 4.4 | N9: ='Plant KPIs'!AC9 -> 6.8 | O9: ='Plant KPIs'!AI9 -> 5.2 | P9: ='Plant KPIs'!AO9 -> 6.5 | Q9: ='Entity KPIs'!K9 -> 8.24 | R9: ='Entity KPIs'!Q9 -> 6.17 | S9: ='Group KPIs'!K9 -> 7.83 | T9: 3.4 h · Entity E-03; 3.6 h · Core Group G-05, Owner O-09 | U9: 0 same / 3 different
A10: REL-003 | B10: Unplanned downtime | C10: h | D10: Month | E10: Unplanned downtime | F10: unplanned_downtime_hours | G10: unplanned_downtime_hours | H10: Original plant data (plant_base.csv, synthetic) | I10: Plant, Entity, Group | J10: Plant inputs → each plant's KPI; Plant inputs summed to each entity → entity KPI; entities summed to Group → Group KPI (recalculated from totals, never averaged) | K10: ='Plant KPIs'!K10 -> 30.2 | L10: ='Plant KPIs'!Q10 -> 78.2 | M10: ='Plant KPIs'!W10 -> 12.3 | N10: ='Plant KPIs'!AC10 -> 10.1 | O10: ='Plant KPIs'!AI10 -> 10.2 | P10: ='Plant KPIs'!AO10 -> 13.4 | Q10: ='Entity KPIs'!K10 -> 120.7 | R10: ='Entity KPIs'!Q10 -> 33.7 | S10: ='Group KPIs'!K10 -> 154.4 | T10: 2.8 % of hours · Entity E-03; 3.1 % of hours · Core Group G-05, Owner O-09 | U10: 0 same / 4 different
A11: REL-004 | B11: Production loss from downtime | C11: t | D11: Month | E11: Production lost to downtime | F11: prod_loss_downtime_t | G11: prod_loss_downtime_t | H11: Original plant data (plant_base.csv, synthetic) | I11: Plant, Entity, Group | J11: Plant inputs → each plant's KPI; Plant inputs summed to each entity → entity KPI; entities summed to Group → Group KPI (recalculated from totals, never averaged) | K11: ='Plant KPIs'!K11 -> 4140 | L11: ='Plant KPIs'!Q11 -> 14772 | M11: ='Plant KPIs'!W11 -> 2772 | N11: ='Plant KPIs'!AC11 -> 1281 | O11: ='Plant KPIs'!AI11 -> 2091 | P11: ='Plant KPIs'!AO11 -> 2120 | Q11: ='Entity KPIs'!K11 -> 21684 | R11: ='Entity KPIs'!Q11 -> 5492 | S11: ='Group KPIs'!K11 -> 27176 | T11: 1.6 kt MTD · Entity E-03; 93% · Core Group G-05 | U11: 0 same / 2 different
A12: REL-005 | B12: Preventive-maintenance compliance | C12: % | D12: Month | E12: Preventive maintenance completed ÷ Preventive maintenance scheduled × 100 | F12: IFERROR(100*pm_completed/pm_scheduled,0) | G12: pm_scheduled, pm_completed | H12: Original plant data (plant_base.csv, synthetic) | I12: Plant, Entity, Group | J12: Plant inputs → each plant's KPI; Plant inputs summed to each entity → entity KPI; entities summed to Group → Group KPI (recalculated from totals, never averaged) | K12: ='Plant KPIs'!K12 -> 93.48 | L12: ='Plant KPIs'!Q12 -> 81.82 | M12: ='Plant KPIs'!W12 -> 100 | N12: ='Plant KPIs'!AC12 -> 100 | O12: ='Plant KPIs'!AI12 -> 97.62 | P12: ='Plant KPIs'!AO12 -> 94.44 | Q12: ='Entity KPIs'!K12 -> 93.43 | R12: ='Entity KPIs'!Q12 -> 97.81 | S12: ='Group KPIs'!K12 -> 95.62 | T12: 93 % · Entity E-03; 93% · Owner O-09 | U12: 1 same / 1 different
A13: CST-001 | B13: Cost per tonne | C13: ₹/t | D13: Month | E13: (Variable cost + Fixed cost) × 1000 ÷ Good output | F13: IFERROR(1000*(variable_cost_k+fixed_cost_k)/good_output_t,0) | G13: good_output_t, variable_cost_k, fixed_cost_k | H13: Original plant data (plant_base.csv, synthetic) | I13: Plant, Entity, Group | J13: Plant inputs → each plant's KPI; Plant inputs summed to each entity → entity KPI; entities summed to Group → Group KPI (recalculated from totals, never averaged) | K13: ='Plant KPIs'!K13 -> 2779.02 | L13: ='Plant KPIs'!Q13 -> 3245.21 | M13: ='Plant KPIs'!W13 -> 2629.1 | N13: ='Plant KPIs'!AC13 -> 3275.49 | O13: ='Plant KPIs'!AI13 -> 3011.79 | P13: ='Plant KPIs'!AO13 -> 2798.98 | Q13: ='Entity KPIs'!K13 -> 2853.05 | R13: ='Entity KPIs'!Q13 -> 3016.5 | S13: ='Group KPIs'!K13 -> 2933.74 | T13: ₹425 /t · Entity E-02, Entity E-11; ₹412 /t · Core Group G-03, Owner O-09; 412 ₹ /t · Core Group G-05, Owner O-09 | U13: 0 same / 7 different
... A37: CST-004 | B37: Power cost per tonne | C37: ₹/t | D37: Month | E37: Power cost × 1000 ÷ Good output | F37: IF(good_output_t=0,0,1000*power_cost_k/good_output_t) | G37: good_output_t, power_cost_k | H37: Original plant data + synthetic inputs added for this model | I37: Plant, Entity, Group | J37: Plant inputs → each plant's KPI; Plant inputs summed to each entity → entity KPI; entities summed to Group → Group KPI (recalculated from totals, never averaged) | K37: ='Plant KPIs'!K37 -> 164.79 | L37: ='Plant KPIs'!Q37 -> 215.86 | M37: ='Plant KPIs'!W37 -> 156.32 | N37: ='Plant KPIs'!AC37 -> 198.06 | O37: ='Plant KPIs'!AI37 -> 168.17 | P37: ='Plant KPIs'!AO37 -> 155.24 | Q37: ='Entity KPIs'!K37 -> 176.41 | R37: ='Entity KPIs'!Q37 -> 172.12 | S37: ='Group KPIs'!K37 -> 174.29 | T37: 6.1 ₹/t · Owner O-09 | U37: 0 same / 1 different
A38: FIN-001 | B38: EBITDA YTD | C38: ₹ m | D38: Year to date | E38: Sum of monthly EBITDA since April ÷ 1000 | F38: SUM(ebitda_k@ytd)/1000 | G38: variable_cost_k, fixed_cost_k, revenue_k, overhead_k | H38: Original plant data + synthetic inputs added for this model | I38: Entity, Group | J38: Plant inputs summed to each entity + entity inputs → entity KPI; entities summed to Group → Group KPI (recalculated from totals, never averaged) | K38: — | L38: — | M38: — | N38: — | O38: — | P38: — | Q38: ='Entity KPIs'!K38 -> 890.55 | R38: ='Entity KPIs'!Q38 -> 869.54 | S38: ='Group KPIs'!K38 -> 1760.09 | T38: 96.2 ₹ m · Entity E-01, Entity E-11; 361.3 ₹ m · Core Group G-01, Core Group G-02, Core Group G-03, Owner O-01, Owner STATE GALLERY | U38: 0 same / 9 different
A39: FIN-002 | B39: EBIT YTD | C39: ₹ m | D39: Year to date | E39: Sum of monthly EBIT since April ÷ 1000 | F39: SUM(ebit_k@ytd)/1000 | G39: variable_cost_k, fixed_cost_k, revenue_k, depreciation_k, overhead_k | H39: Original plant data + synthetic inputs added for this model | I39: Entity, Group | J39: Plant inputs summed to each entity + entity inputs → entity KPI; entities summed to Group → Group KPI (recalculated from totals, never averaged) | K39: — | L39: — | M39: — | N39: — | O39: — | P39: — | Q39: ='Entity KPIs'!K39 -> 610.05 | R39: ='Entity KPIs'!Q39 -> 618.1 | S39: ='Group KPIs'!K39 -> 1228.14 | T39: 68.7 ₹ m · Entity E-01, Entity E-11; ₹68.7 m · Entity E-01; 238.4 ₹ m · Core Group G-01, Core Group G-03, Owner O-01, Owner STATE GALLERY | U39: 0 same / 10 different
A40: FIN-003 | B40: Revenue YTD | C40: ₹ m | D40: Year to date | E40: Sum of monthly Revenue since April ÷ 1000 | F40: SUM(revenue_k@ytd)/1000 | G40: revenue_k | H40: Synthetic inputs added for this model | I40: Plant, Entity, Group | J40: Plant inputs → each plant's KPI; Plant inputs summed to each entity → entity KPI; entities summed to Group → Group KPI (recalculated from totals, never averaged) | K40: ='Plant KPIs'!K38 -> 1892.75 | L40: ='Plant KPIs'!Q38 -> 2089.58 | M40: ='Plant KPIs'!W38 -> 2989.99 | N40: ='Plant KPIs'!AC38 -> 1749.63 | O40: ='Plant KPIs'!AI38 -> 2890.84 | P40: ='Plant KPIs'!AO38 -> 2198.51 | Q40: ='Entity KPIs'!K40 -> 6972.32 | R40: ='Entity KPIs'!Q40 -> 6838.98 | S40: ='Group KPIs'!K40 -> 13811.3 | T40: ₹404.6 m · Entity E-01; 404.6 ₹ m · Entity E-11; 2,410 ₹ m · Core Group G-01, Core Group G-02, Core Group G-03, Owner O-01, Owner STATE GALLERY | U40: 0 same / 11 different
A41: FIN-004 | B41: Free cash flow YTD | C41: ₹ m | D41: Year to date | E41: Sum of monthly Free cash flow since April ÷ 1000 | F41: SUM(fcf_k@ytd)/1000 | G41: variable_cost_k, fixed_cost_k, revenue_k, overhead_k, tax_paid_k, receivables_k, payables_k, inventory_k, capex_spend_k | H41: Original plant data + synthetic inputs added for this model | I41: Entity, Group | J41: Plant inputs summed to each entity + entity inputs → entity KPI; entities summed to Group → Group KPI (recalculated from totals, never averaged) | K41: — | L41: — | M41: — | N41: — | O41: — | P41: — | Q41: ='Entity KPIs'!K41 -> 337.63 | R41: ='Entity KPIs'!Q41 -> 268.55 | S41: ='Group KPIs'!K41 -> 606.18 | T41: ₹19.8 m · Entity E-01; 19.8 ₹ m · Entity E-11; 96.4 ₹ m · Core Group G-01, Core Group G-03, Owner O-01, Owner O-03, Owner STATE GALLERY | U41: 0 same / 9 different
A42: FIN-005 | B42: ROCE, annualised | C42: % | D42: Year to date | E42: EBIT since April × 12 ÷ months elapsed ÷ Capital employed × 100 | F42: IF(capital_employed_k=0,0,100*SUM(ebit_k@ytd)*12/ytd_months/capital_employed_k) | G42: variable_cost_k, fixed_cost_k, revenue_k, depreciation_k, overhead_k, capital_employed_k | H42: Original plant data + synthetic inputs added for this model | I42: Entity, Group | J42: Plant inputs summed to each entity + entity inputs → entity KPI; entities summed to Group → Group KPI (recalculated from totals, never averaged) | K42: — | L42: — | M42: — | N42: — | O42: — | P42: — | Q42: ='Entity KPIs'!K42 -> 11.08 | R42: ='Entity KPIs'!Q42 -> 12.12 | S42: ='Group KPIs'!K42 -> 11.58 | T42: 11.4 % · Entity E-01, Entity E-11; 11.4% · Entity E-01; 11.8% · Core Group G-01, Owner O-01, Owner STATE GALLERY; 11.8 % · Core Group G-03, Owner O-01 | U42: 0 same / 10 different
A43: FIN-006 | B43: Net debt | C43: ₹ m | D43: Month end | E43: (Gross debt − Cash) ÷ 1000 | F43: net_debt_k/1000 | G43: gross_debt_k, cash_k | H43: Synthetic inputs added for this model | I43: Entity, Group | J43: Entity inputs → entity KPI; entities summed to Group → Group KPI (recalculated from totals, never averaged) | K43: — | L43: — | M43: — | N43: — | O43: — | P43: — | Q43: ='Entity KPIs'!K43 -> 3610 | R43: ='Entity KPIs'!Q43 -> 3040 | S43: ='Group KPIs'!K43 -> 6650 | T43: 1,140 ₹ m · Core Group G-01, Core Group G-03, Owner O-01, Owner O-03, Owner STATE GALLERY | U43: 0 same / 7 different
A44: FIN-007 | B44: Shareholder-value indicator (economic profit YTD) | C44: ₹ m | D44: Year to date | E44: (EBIT since April × (1 − Tax rate) − Capital employed × Cost of capital × months elapsed ÷ 12) ÷ 1000 | F44: (SUM(ebit_k@ytd)*(1-TaxRate)-capital_employed_k*WACC*ytd_months/12)/1000 | G44: variable_cost_k, fixed_cost_k, revenue_k, depreciation_k, overhead_k, capital_employed_k | H44: Original plant data + synthetic inputs added for this model | I44: Entity, Group | J44: Plant inputs summed to each entity + entity inputs → entity KPI; entities summed to Group → Group KPI (recalculated from totals, never averaged) | K44: — | L44: — | M44: — | N44: — | O44: — | P44: — | Q44: ='Entity KPIs'!K44 -> -65.72 | R44: ='Entity KPIs'!Q44 -> -20.93 | S44: ='Group KPIs'!K44 -> -86.65 | T44: — · Core Group G-03; [PLACEHOLDER] · Owner O-01, Owner STATE GALLERY | U44: 0 same / 4 different
A45: FIN-008 | B45: FCF conversion (FCF ÷ EBITDA) | C45: % | D45: Year to date | E45: Free cash flow since April ÷ EBITDA since April × 100 | F45: IF(SUM(ebitda_k@ytd)=0,0,100*SUM(fcf_k@ytd)/SUM(ebitda_k@ytd)) | G45: variable_cost_k, fixed_cost_k, revenue_k, overhead_k, tax_paid_k, receivables_k, payables_k, inventory_k, capex_spend_k | H45: Original plant data + synthetic inputs added for this model | I45: Entity, Group | J45: Plant inputs summed to each entity + entity inputs → entity KPI; entities summed to Group → Group KPI (recalculated from totals, never averaged) | K45: — | L45: — | M45: — | N45: — | O45: — | P45: — | Q45: ='Entity KPIs'!K45 -> 37.91 | R45: ='Entity KPIs'!Q45 -> 30.88 | S45: ='Group KPIs'!K45 -> 34.44 | T45: 27% · Core Group G-03 | U45: 0 same / 1 different
A46: CSH-001 | B46: Cash position | C46: ₹ m | D46: Month end | E46: Cash ÷ 1000 | F46: cash_k/1000 | G46: cash_k | H46: Synthetic inputs added for this model | I46: Entity, Group | J46: Entity inputs → entity KPI; entities summed to Group → Group KPI (recalculated from totals, never averaged) | K46: — | L46: — | M46: — | N46: — | O46: — | P46: — | Q46: ='Entity KPIs'!K46 -> 967.08 | R46: ='Entity KPIs'!Q46 -> 1174.74 | S46: ='Group KPIs'!K46 -> 2141.82 | T46: ₹41 m · Entity E-05; 384 ₹ m · Core Group G-04, Owner O-03 | U46: 0 same / 3 different
A47: CSH-002 | B47: Cash released YTD | C47: ₹ m | D47: Year to date | E47: Sum of cash released since April ÷ 1000 | F47: SUM(cash_released_k@ytd)/1000 | G47: cash_released_k | H47: Synthetic inputs added for this model | I47: Entity, Group | J47: Entity inputs → entity KPI; entities summed to Group → Group KPI (recalculated from totals, never averaged) | K47: — | L47: — | M47: — | N47: — | O47: — | P47: — | Q47: ='Entity KPIs'!K47 -> 4.2 | R47: ='Entity KPIs'!Q47 -> 17.83 | S47: ='Group KPIs'!K47 -> 22.03 | T47: ₹4.2 m · Entity E-05; ₹21 m · Core Group G-04, Owner O-03 | U47: 1 same / 2 different
A48: CSH-003 | B48: Daily collections | C48: ₹ m per day | D48: Month | E48: Cash collected ÷ Days in month ÷ 1000 | F48: collections_k/days/1000 | G48: collections_k | H48: Synthetic inputs added for this model | I48: Entity, Group | J48: Entity inputs → entity KPI; entities summed to Group → Group KPI (recalculated from totals, never averaged) | K48: — | L48: — | M48: — | N48: — | O48: — | P48: — | Q48: ='Entity KPIs'!K48 -> 38.6 | R48: ='Entity KPIs'!Q48 -> 38.17 | S48: ='Group KPIs'!K48 -> 76.77 | T48: 4.1 ₹ m · Entity E-01, Entity E-05, Owner S-11; ₹18.6 m · Core Group G-04, Owner O-03 | U48: 0 same / 5 different
A49: CSH-004 | B49: Cash-conversion cycle | C49: days | D49: Month end | E49: DSO + Inventory days − DPO | F49: dso_d+dio_d-dpo_d | G49: variable_cost_k, revenue_k, receivables_k, payables_k, inventory_k | H49: Original plant data + synthetic inputs added for this model | I49: Entity, Group | J49: Plant inputs summed to each entity + entity inputs → entity KPI; entities summed to Group → Group KPI (recalculated from totals, never averaged) | K49: — | L49: — | M49: — | N49: — | O49: — | P49: — | Q49: ='Entity KPIs'!K49 -> 52.3 | R49: ='Entity KPIs'!Q49 -> 13.42 | S49: ='Group KPIs'!K49 -> 32.59 | T49: 55 d · Entity E-05; 33 days · Core Group G-04; 33 d · Owner O-03 | U49: 2 same / 1 different
A50: CSH-006 | B50: Cash-upstream exposure | C50: ₹ m | D50: Next 30 days | E50: (Cash due to be upstreamed − Amount covered by available cash) ÷ 1000 | F50: (upstream_due_k-upstream_covered_k)/1000 | G50: upstream_due_k, upstream_covered_k | H50: Synthetic inputs added for this model | I50: Entity, Group | J50: Entity inputs → entity KPI; entities summed to Group → Group KPI (recalculated from totals, never averaged) | K50: — | L50: — | M50: — | N50: — | O50: — | P50: — | Q50: ='Entity KPIs'!K50 -> 27.21 | R50: ='Entity KPIs'!Q50 -> 0 | S50: ='Group KPIs'!K50 -> 27.21 | T50: ₹26 m at risk (FCST) · Entity E-01; 26 ₹ m · Entity E-05, Core Group G-04, Owner O-03, Owner S-11 | U50: 0 same / 5 different
A51: WCP-001 | B51: DSO | C51: days | D51: Month end | E51: Trade receivables ÷ Revenue × Days in month | F51: dso_d | G51: revenue_k, receivables_k | H51: Synthetic inputs added for this model | I51: Entity, Group | J51: Plant inputs summed to each entity + entity inputs → entity KPI; entities summed to Group → Group KPI (recalculated from totals, never averaged) | K51: — | L51: — | M51: — | N51: — | O51: — | P51: — | Q51: ='Entity KPIs'!K51 -> 52 | R51: ='Entity KPIs'!Q51 -> 42.05 | S51: ='Group KPIs'!K51 -> 46.97 | T51: 52 d · Entity E-01, Entity E-05; 52 days · Entity E-05, Owner S-11; 47 days · Core Group G-02, Core Group G-04; 47 d · Owner O-03 | U51: 7 same / 0 different
A52: WCP-002 | B52: DPO | C52: days | D52: Month end | E52: Trade payables ÷ Variable cost × Days in month | F52: dpo_d | G52: variable_cost_k, payables_k | H52: Original plant data + synthetic inputs added for this model | I52: Entity, Group | J52: Plant inputs summed to each entity + entity inputs → entity KPI; entities summed to Group → Group KPI (recalculated from totals, never averaged) | K52: — | L52: — | M52: — | N52: — | O52: — | P52: — | Q52: ='Entity KPIs'!K52 -> 40.2 | R52: ='Entity KPIs'!Q52 -> 63.74 | S52: ='Group KPIs'!K52 -> 52.15 | T52: 38 d · Entity E-05; 52 days · Core Group G-04; 52 d · Owner O-03 | U52: 2 same / 1 different
... A80: VAL-003 | B80: Cost savings delivered YTD | C80: ₹ m | D80: Year to date | E80: Sum of cost savings since April ÷ 1000 | F80: SUM(cost_savings_k@ytd)/1000 | G80: cost_savings_k | H80: Synthetic inputs added for this model | I80: Entity, Group | J80: Entity inputs → entity KPI; entities summed to Group → Group KPI (recalculated from totals, never averaged) | K80: — | L80: — | M80: — | N80: — | O80: — | P80: — | Q80: ='Entity KPIs'!K80 -> 3.89 | R80: ='Entity KPIs'!Q80 -> 7.35 | S80: ='Group KPIs'!K80 -> 11.25 | T80: ₹3.9 m · Entity E-06; ₹11 m · Core Group G-06, Owner O-04 | U80: 4 same / 0 different
A81: SUP-001 | B81: Supplier on-time delivery | C81: % | D81: Month | E81: Purchase-order lines on time ÷ Lines due × 100 | F81: IF(po_lines_due=0,0,100*po_lines_on_time/po_lines_due) | G81: po_lines_due, po_lines_on_time | H81: Synthetic inputs added for this model | I81: Plant, Entity, Group | J81: Plant inputs → each plant's KPI; Plant inputs summed to each entity → entity KPI; entities summed to Group → Group KPI (recalculated from totals, never averaged) | K81: ='Plant KPIs'!K39 -> 92.72 | L81: ='Plant KPIs'!Q39 -> 84.97 | M81: ='Plant KPIs'!W39 -> 92.41 | N81: ='Plant KPIs'!AC39 -> 93.45 | O81: ='Plant KPIs'!AI39 -> 91.9 | P81: ='Plant KPIs'!AO39 -> 90.73 | Q81: ='Entity KPIs'!K81 -> 90.39 | R81: ='Entity KPIs'!Q81 -> 92.28 | S81: ='Group KPIs'!K81 -> 91.41 | T81: 88 % · Entity E-04; 91% · Core Group G-05, Owner O-09; 91 % · Owner O-09 | U81: 3 same / 1 different
A82: SUP-002 | B82: Supplier fill rate | C82: % | D82: Month | E82: Quantity received ÷ Quantity ordered × 100 | F82: IF(qty_ordered_t=0,0,100*qty_received_t/qty_ordered_t) | G82: qty_ordered_t, qty_received_t | H82: Synthetic inputs added for this model | I82: Plant, Entity, Group | J82: Plant inputs → each plant's KPI; Plant inputs summed to each entity → entity KPI; entities summed to Group → Group KPI (recalculated from totals, never averaged) | K82: ='Plant KPIs'!K40 -> 96.14 | L82: ='Plant KPIs'!Q40 -> 97.38 | M82: ='Plant KPIs'!W40 -> 97.28 | N82: ='Plant KPIs'!AC40 -> 94.71 | O82: ='Plant KPIs'!AI40 -> 98.98 | P82: ='Plant KPIs'!AO40 -> 95.06 | Q82: ='Entity KPIs'!K82 -> 97.01 | R82: ='Entity KPIs'!Q82 -> 96.61 | S82: ='Group KPIs'!K82 -> 96.82 | T82: 94 % · Entity E-04 | U82: 0 same / 1 different
A83: SUP-003 | B83: Supplier quality-rejection rate | C83: % | D83: Month | E83: Quantity rejected ÷ Quantity received × 100 | F83: IF(qty_received_t=0,0,100*qty_rejected_t/qty_received_t) | G83: qty_received_t, qty_rejected_t | H83: Synthetic inputs added for this model | I83: Plant, Entity, Group | J83: Plant inputs → each plant's KPI; Plant inputs summed to each entity → entity KPI; entities summed to Group → Group KPI (recalculated from totals, never averaged) | K83: ='Plant KPIs'!K41 -> 1.4 | L83: ='Plant KPIs'!Q41 -> 1.11 | M83: ='Plant KPIs'!W41 -> 0.62 | N83: ='Plant KPIs'!AC41 -> 1.61 | O83: ='Plant KPIs'!AI41 -> 1.01 | P83: ='Plant KPIs'!AO41 -> 1.37 | Q83: ='Entity KPIs'!K83 -> 0.97 | R83: ='Entity KPIs'!Q83 -> 1.28 | S83: ='Group KPIs'!K83 -> 1.12 | T83: 1.2 % · Entity E-04 | U83: 0 same / 1 different
A84: SUP-004 | B84: Supplier lead-time variance | C84: % | D84: Month | E84: (Actual lead time − Planned lead time) ÷ Planned lead time × 100 | F84: IF(lead_time_planned_days=0,0,100*(lead_time_actual_days-lead_time_planned_days)/lead_time_planned_days) | G84: lead_time_planned_days, lead_time_actual_days | H84: Synthetic inputs added for this model | I84: Plant, Entity, Group | J84: Plant inputs → each plant's KPI; Plant inputs summed to each entity → entity KPI; entities summed to Group → Group KPI (recalculated from totals, never averaged) | K84: ='Plant KPIs'!K42 -> 4.97 | L84: ='Plant KPIs'!Q42 -> 17.33 | M84: ='Plant KPIs'!W42 -> 2.35 | N84: ='Plant KPIs'!AC42 -> 3.92 | O84: ='Plant KPIs'!AI42 -> 6.68 | P84: ='Plant KPIs'!AO42 -> -1.14 | Q84: ='Entity KPIs'!K84 -> 6.91 | R84: ='Entity KPIs'!Q84 -> 3.65 | S84: ='Group KPIs'!K84 -> 5.25 | T84: +6 days · Entity E-04; 38% · Core Group G-05 | U84: 0 same / 2 different
A85: SUP-005 | B85: Critical supplier exposure | C85: count | D85: Month end | E85: Critical single-source suppliers | F85: single_source_suppliers | G85: single_source_suppliers | H85: Synthetic inputs added for this model | I85: Entity, Group | J85: Entity inputs → entity KPI; entities summed to Group → Group KPI (recalculated from totals, never averaged) | K85: — | L85: — | M85: — | N85: — | O85: — | P85: — | Q85: ='Entity KPIs'!K85 -> 2 | R85: ='Entity KPIs'!Q85 -> 1 | S85: ='Group KPIs'!K85 -> 3 | T85: 2 single-source suppliers · Entity E-04; 3 single-source (1 elevated: S-07) · Core Group G-05 | U85: 2 same / 0 different
A86: SUP-007 | B86: Single-source spend share | C86: % | D86: Month | E86: Spend with single-source suppliers ÷ Supplier spend × 100 | F86: IF(supplier_spend_k=0,0,100*single_source_spend_k/supplier_spend_k) | G86: supplier_spend_k, single_source_spend_k | H86: Synthetic inputs added for this model | I86: Plant, Entity, Group | J86: Plant inputs → each plant's KPI; Plant inputs summed to each entity → entity KPI; entities summed to Group → Group KPI (recalculated from totals, never averaged) | K86: ='Plant KPIs'!K43 -> 30.12 | L86: ='Plant KPIs'!Q43 -> 43.02 | M86: ='Plant KPIs'!W43 -> 30.7 | N86: ='Plant KPIs'!AC43 -> 31.2 | O86: ='Plant KPIs'!AI43 -> 35.54 | P86: ='Plant KPIs'!AO43 -> 39.87 | Q86: ='Entity KPIs'!K86 -> 34.81 | R86: ='Entity KPIs'!Q86 -> 35.55 | S86: ='Group KPIs'!K86 -> 35.19 | T86: 38% · Owner O-09 | U86: 0 same / 1 different
A87: SUP-008 | B87: Supplier EHS incidents YTD | C87: count | D87: Year to date | E87: Sum of supplier EHS incidents since April | F87: SUM(supplier_ehs_incidents@ytd) | G87: supplier_ehs_incidents | H87: Synthetic inputs added for this model | I87: Plant, Entity, Group | J87: Plant inputs → each plant's KPI; Plant inputs summed to each entity → entity KPI; entities summed to Group → Group KPI (recalculated from totals, never averaged) | K87: ='Plant KPIs'!K44 -> 2 | L87: ='Plant KPIs'!Q44 -> 0 | M87: ='Plant KPIs'!W44 -> 0 | N87: ='Plant KPIs'!AC44 -> 0 | O87: ='Plant KPIs'!AI44 -> 1 | P87: ='Plant KPIs'!AO44 -> 0 | Q87: ='Entity KPIs'!K87 -> 2 | R87: ='Entity KPIs'!Q87 -> 1 | S87: ='Group KPIs'!K87 -> 3 | T87: 0 · Owner O-09 | U87: 0 same / 1 different
A88: CON-001 | B88: Contracts expiring, next 90 days | C88: count | D88: Month end | E88: Contracts expiring in next 90 days | F88: contracts_expiring_90d | G88: contracts_expiring_90d | H88: Synthetic inputs added for this model | I88: Entity, Group | J88: Entity inputs → entity KPI; entities summed to Group → Group KPI (recalculated from totals, never averaged) | K88: — | L88: — | M88: — | N88: — | O88: — | P88: — | Q88: ='Entity KPIs'!K88 -> 2 | R88: ='Entity KPIs'!Q88 -> 2 | S88: ='Group KPIs'!K88 -> 4 | T88: 1 (S-07) · Entity E-04, Entity E-07; 4 · Core Group G-07, Owner O-05 | U88: 3 same / 2 different
A89: CON-002 | B89: Contract-compliance rate | C89: % | D89: Month end | E89: Contracts fully compliant ÷ Active contracts × 100 | F89: IF(contracts_total=0,0,100*contracts_compliant/contracts_total) | G89: contracts_total, contracts_compliant | H89: Synthetic inputs added for this model | I89: Entity, Group | J89: Entity inputs → entity KPI; entities summed to Group → Group KPI (recalculated from totals, never averaged) | K89: — | L89: — | M89: — | N89: — | O89: — | P89: — | Q89: ='Entity KPIs'!K89 -> 95.83 | R89: ='Entity KPIs'!Q89 -> 95.59 | S89: ='Group KPIs'!K89 -> 95.71 | T89: 95% · Entity E-04, Entity E-07; 96% · Core Group G-07, Owner O-05 | U89: 2 same / 2 different
A90: CON-003 | B90: Supplier EHS non-compliance | C90: count | D90: Month end | E90: Suppliers not meeting EHS requirements | F90: supplier_ehs_noncompliance | G90: supplier_ehs_noncompliance | H90: Synthetic inputs added for this model | I90: Entity, Group | J90: Entity inputs → entity KPI; entities summed to Group → Group KPI (recalculated from totals, never averaged) | K90: — | L90: — | M90: — | N90: — | O90: — | P90: — | Q90: ='Entity KPIs'!K90 -> 0 | R90: ='Entity KPIs'!Q90 -> 0 | S90: ='Group KPIs'!K90 -> 0 | T90: 0 · Entity E-04, Entity E-07; 1 · Core Group G-05, Core Group G-07, Owner O-05 | U90: 2 same / 3 different
A91: REG-001 | B91: Pending filings | C91: count | D91: Month end | E91: Regulatory filings pending | F91: pending_filings | G91: pending_filings | H91: Synthetic inputs added for this model | I91: Plant, Entity, Group | J91: Plant inputs → each plant's KPI; Plant inputs summed to each entity → entity KPI; entities summed to Group → Group KPI (recalculated from totals, never averaged) | K91: ='Plant KPIs'!K45 -> 0 | L91: ='Plant KPIs'!Q45 -> 0 | M91: ='Plant KPIs'!W45 -> 0 | N91: ='Plant KPIs'!AC45 -> 0 | O91: ='Plant KPIs'!AI45 -> 0 | P91: ='Plant KPIs'!AO45 -> 0 | Q91: ='Entity KPIs'!K91 -> 0 | R91: ='Entity KPIs'!Q91 -> 0 | S91: ='Group KPIs'!K91 -> 0 | T91: 1 · Entity E-07; 3 · Core Group G-07 | U91: 0 same / 2 different
A92: REG-002 | B92: Regulatory deadlines, next 30 days | C92: count | D92: Month end | E92: Regulatory deadlines in next 30 days | F92: reg_deadlines_30d | G92: reg_deadlines_30d | H92: Synthetic inputs added for this model | I92: Plant, Entity, Group | J92: Plant inputs → each plant's KPI; Plant inputs summed to each entity → entity KPI; entities summed to Group → Group KPI (recalculated from totals, never averaged) | K92: ='Plant KPIs'!K46 -> 1 | L92: ='Plant KPIs'!Q46 -> 0 | M92: ='Plant KPIs'!W46 -> 1 | N92: ='Plant KPIs'!AC46 -> 0 | O92: ='Plant KPIs'!AI46 -> 0 | P92: ='Plant KPIs'!AO46 -> 1 | Q92: ='Entity KPIs'!K92 -> 2 | R92: ='Entity KPIs'!Q92 -> 1 | S92: ='Group KPIs'!K92 -> 3 | T92: 3 · Entity E-07, Core Group G-07 | U92: 1 same / 1 different
A93: REG-003 | B93: Licence expirations, next 12 months | C93: count | D93: Month end | E93: Licences expiring in next 12 months | F93: licences_expiring_12m | G93: licences_expiring_12m | H93: Synthetic inputs added for this model | I93: Plant, Entity, Group | J93: Plant inputs → each plant's KPI; Plant inputs summed to each entity → entity KPI; entities summed to Group → Group KPI (recalculated from totals, never averaged) | K93: ='Plant KPIs'!K47 -> 0 | L93: ='Plant KPIs'!Q47 -> 1 | M93: ='Plant KPIs'!W47 -> 0 | N93: ='Plant KPIs'!AC47 -> 0 | O93: ='Plant KPIs'!AI47 -> 0 | P93: ='Plant KPIs'!AO47 -> 0 | Q93: ='Entity KPIs'!K93 -> 1 | R93: ='Entity KPIs'!Q93 -> 0 | S93: ='Group KPIs'!K93 -> 1 | T93: 1 · Entity E-07; 2 · Core Group G-07 | U93: 1 same / 1 different
A94: REG-004 | B94: Regulatory obligations due, next 30 days | C94: count | D94: Month end | E94: Regulatory obligations due in next 30 days | F94: reg_obligations_due_30d | G94: reg_obligations_due_30d | H94: Synthetic inputs added for this model | I94: Plant, Entity, Group | J94: Plant inputs → each plant's KPI; Plant inputs summed to each entity → entity KPI; entities summed to Group → Group KPI (recalculated from totals, never averaged) | K94: ='Plant KPIs'!K48 -> 0 | L94: ='Plant KPIs'!Q48 -> 1 | M94: ='Plant KPIs'!W48 -> 0 | N94: ='Plant KPIs'!AC48 -> 0 | O94: ='Plant KPIs'!AI48 -> 1 | P94: ='Plant KPIs'!AO48 -> 0 | Q94: ='Entity KPIs'!K94 -> 1 | R94: ='Entity KPIs'!Q94 -> 1 | S94: ='Group KPIs'!K94 -> 2 | T94: 3 · Entity E-07; 5 · Core Group G-07 | U94: 0 same / 2 different
A95: REG-005 | B95: Overdue regulatory obligations | C95: count | D95: Month end | E95: Regulatory obligations overdue | F95: reg_obligations_overdue | G95: reg_obligations_overdue | H95: Synthetic inputs added for this model | I95: Plant, Entity, Group | J95: Plant inputs → each plant's KPI; Plant inputs summed to each entity → entity KPI; entities summed to Group → Group KPI (recalculated from totals, never averaged) | K95: ='Plant KPIs'!K49 -> 0 | L95: ='Plant KPIs'!Q49 -> 0 | M95: ='Plant KPIs'!W49 -> 0 | N95: ='Plant KPIs'!AC49 -> 0 | O95: ='Plant KPIs'!AI49 -> 0 | P95: ='Plant KPIs'!AO49 -> 0 | Q95: ='Entity KPIs'!K95 -> 0 | R95: ='Entity KPIs'!Q95 -> 0 | S95: ='Group KPIs'!K95 -> 0 | T95: 0 · Entity E-07, Core Group G-07, Owner O-05 | U95: 3 same / 0 different
A96: REG-007 | B96: Open regulatory actions | C96: count | D96: Month end | E96: Open regulatory actions | F96: reg_actions_open | G96: reg_actions_open | H96: Synthetic inputs added for this model | I96: Plant, Entity, Group | J96: Plant inputs → each plant's KPI; Plant inputs summed to each entity → entity KPI; entities summed to Group → Group KPI (recalculated from totals, never averaged) | K96: ='Plant KPIs'!K50 -> 0 | L96: ='Plant KPIs'!Q50 -> 0 | M96: ='Plant KPIs'!W50 -> 0 | N96: ='Plant KPIs'!AC50 -> 0 | O96: ='Plant KPIs'!AI50 -> 0 | P96: ='Plant KPIs'!AO50 -> 0 | Q96: ='Entity KPIs'!K96 -> 0 | R96: ='Entity KPIs'!Q96 -> 0 | S96: ='Group KPIs'!K96 -> 0 | T96: 0 · Entity E-07; 2 · Core Group G-07 | U96: 1 same / 1 different
A97: REG-008 | B97: Overdue compliance actions | C97: count | D97: Month end | E97: Overdue compliance actions | F97: compliance_actions_overdue | G97: compliance_actions_overdue | H97: Synthetic inputs added for this model | I97: Plant, Entity, Group | J97: Plant inputs → each plant's KPI; Plant inputs summed to each entity → entity KPI; entities summed to Group → Group KPI (recalculated from totals, never averaged) | K97: ='Plant KPIs'!K51 -> 0 | L97: ='Plant KPIs'!Q51 -> 0 | M97: ='Plant KPIs'!W51 -> 0 | N97: ='Plant KPIs'!AC51 -> 0 | O97: ='Plant KPIs'!AI51 -> 0 | P97: ='Plant KPIs'!AO51 -> 0 | Q97: ='Entity KPIs'!K97 -> 0 | R97: ='Entity KPIs'!Q97 -> 0 | S97: ='Group KPIs'!K97 -> 0 | T97: 0 · Entity E-07, Core Group G-07 | U97: 2 same / 0 different
A98: REG-009 | B98: Disclosure-clock status | C98: text | D98: Month end | E98: Triggered if any event that needs disclosure is open, otherwise Not triggered | F98: IF(disclosure_events_open>0,"Triggered","Not triggered") | G98: disclosure_events_open | H98: Synthetic inputs added for this model | I98: Plant, Entity, Group | J98: Plant inputs → each plant's KPI; Plant inputs summed to each entity → entity KPI; entities summed to Group → Group KPI (recalculated from totals, never averaged) | K98: ='Plant KPIs'!K52 -> Not triggered | L98: ='Plant KPIs'!Q52 -> Not triggered | M98: ='Plant KPIs'!W52 -> Not triggered | N98: ='Plant KPIs'!AC52 -> Not triggered | O98: ='Plant KPIs'!AI52 -> Not triggered | P98: ='Plant KPIs'!AO52 -> Not triggered | Q98: ='Entity KPIs'!K98 -> Not triggered | R98: ='Entity KPIs'!Q98 -> Not triggered | S98: ='Group KPIs'!K98 -> Not triggered | T98: Not triggered · Owner O-05 | U98: 1 same / 0 different
A99: REG-010 | B99: Regulatory breaches YTD | C99: count | D99: Year to date | E99: Sum of regulatory breaches since April | F99: SUM(reg_breaches@ytd) | G99: reg_breaches | H99: Synthetic inputs added for this model | I99: Plant, Entity, Group | J99: Plant inputs → each plant's KPI; Plant inputs summed to each entity → entity KPI; entities summed to Group → Group KPI (recalculated from totals, never averaged) | K99: ='Plant KPIs'!K53 -> 0 | L99: ='Plant KPIs'!Q53 -> 0 | M99: ='Plant KPIs'!W53 -> 0 | N99: ='Plant KPIs'!AC53 -> 0 | O99: ='Plant KPIs'!AI53 -> 0 | P99: ='Plant KPIs'!AO53 -> 0 | Q99: ='Entity KPIs'!K99 -> 0 | R99: ='Entity KPIs'!Q99 -> 0 | S99: ='Group KPIs'!K99 -> 0 | T99: 0 · Entity E-07, Core Group G-01, Owner O-05 | U99: 4 same / 0 different
A100: RSK-003 | B100: Regulatory breaches YTD (same measure as REG-010) | C100: count | D100: Year to date | E100: Sum of regulatory breaches since April | F100: SUM(reg_breaches@ytd) | G100: reg_breaches | H100: Synthetic inputs added for this model | I100: Plant, Entity, Group | J100: Plant inputs → each plant's KPI; Plant inputs summed to each entity → entity KPI; entities summed to Group → Group KPI (recalculated from totals, never averaged) | K100: ='Plant KPIs'!K54 -> 0 | L100: ='Plant KPIs'!Q54 -> 0 | M100: ='Plant KPIs'!W54 -> 0 | N100: ='Plant KPIs'!AC54 -> 0 | O100: ='Plant KPIs'!AI54 -> 0 | P100: ='Plant KPIs'!AO54 -> 0 | Q100: ='Entity KPIs'!K100 -> 0 | R100: ='Entity KPIs'!Q100 -> 0 | S100: ='Group KPIs'!K100 -> 0 | T100: 0 · Owner O-01, Owner STATE GALLERY | U100: 3 same / 0 different
A101: CMP-005 | B101: Regulatory breaches YTD (same measure as REG-010) | C101: count | D101: Year to date | E101: Sum of regulatory breaches since April | F101: SUM(reg_breaches@ytd) | G101: reg_breaches | H101: Synthetic inputs added for this model | I101: Plant, Entity, Group | J101: Plant inputs → each plant's KPI; Plant inputs summed to each entity → entity KPI; entities summed to Group → Group KPI (recalculated from totals, never averaged) | K101: ='Plant KPIs'!K55 -> 0 | L101: ='Plant KPIs'!Q55 -> 0 | M101: ='Plant KPIs'!W55 -> 0 | N101: ='Plant KPIs'!AC55 -> 0 | O101: ='Plant KPIs'!AI55 -> 0 | P101: ='Plant KPIs'!AO55 -> 0 | Q101: ='Entity KPIs'!K101 -> 0 | R101: ='Entity KPIs'!Q101 -> 0 | S101: ='Group KPIs'!K101 -> 0 | T101: 0 · Entity E-01, Owner O-01 | U101: 2 same / 0 different
A102: EHS-008 | B102: EHS escalation clocks running | C102: count | D102: Month end | E102: EHS escalation clocks running | F102: ehs_escalation_clocks | G102: ehs_escalation_clocks | H102: Synthetic inputs added for this model | I102: Plant, Entity, Group | J102: Plant inputs → each plant's KPI; Plant inputs summed to each entity → entity KPI; entities summed to Group → Group KPI (recalculated from totals, never averaged) | K102: ='Plant KPIs'!K56 -> 0 | L102: ='Plant KPIs'!Q56 -> 0 | M102: ='Plant KPIs'!W56 -> 0 | N102: ='Plant KPIs'!AC56 -> 0 | O102: ='Plant KPIs'!AI56 -> 0 | P102: ='Plant KPIs'!AO56 -> 0 | Q102: ='Entity KPIs'!K102 -> 0 | R102: ='Entity KPIs'!Q102 -> 0 | S102: ='Group KPIs'!K102 -> 0 | T102: 0 running · Entity E-07, Core Group G-07, Owner O-05 | U102: 3 same / 0 different
A103: EHS-010 | B103: EHS investigation completion rate YTD | C103: % | D103: Year to date | E103: EHS investigations completed since April ÷ Investigations due since April × 100 (100 if none due) | F103: IF(SUM(investigations_due@ytd)=0,100,100*SUM(investigations_completed@ytd)/SUM(investigations_due@ytd)) | G103: investigations_due, investigations_completed | H103: Original plant data (plant_base.csv, synthetic) | I103: Plant, Entity, Group | J103: Plant inputs → each plant's KPI; Plant inputs summed to each entity → entity KPI; entities summed to Group → Group KPI (recalculated from totals, never averaged) | K103: ='Plant KPIs'!K57 -> 100 | L103: ='Plant KPIs'!Q57 -> 75 | M103: ='Plant KPIs'!W57 -> 60 | N103: ='Plant KPIs'!AC57 -> 85.71 | O103: ='Plant KPIs'!AI57 -> 83.33 | P103: ='Plant KPIs'!AO57 -> 92.31 | Q103: ='Entity KPIs'!K103 -> 81.82 | R103: ='Entity KPIs'!Q103 -> 88.46 | S103: ='Group KPIs'!K103 -> 85.42 | T103: 83% · Core Group G-07 | U103: 0 same / 1 different
A104: CTL-002 | B104: Control failures YTD | C104: count | D104: Year to date | E104: Sum of control failures since April | F104: SUM(control_failures@ytd) | G104: control_failures | H104: Synthetic inputs added for this model | I104: Entity, Group | J104: Entity inputs → entity KPI; entities summed to Group → Group KPI (recalculated from totals, never averaged) | K104: — | L104: — | M104: — | N104: — | O104: — | P104: — | Q104: ='Entity KPIs'!K104 -> 2 | R104: ='Entity KPIs'!Q104 -> 2 | S104: ='Group KPIs'!K104 -> 4 | T104: 1 · Entity E-07; 4 · Core Group G-07, Owner O-05 | U104: 2 same / 1 different
A105: CTL-004 | B105: High-severity control failures YTD | C105: count | D105: Year to date | E105: Sum of high-severity control failures since April | F105: SUM(control_failures_high@ytd) | G105: control_failures_high | H105: Synthetic inputs added for this model | I105: Entity, Group | J105: Entity inputs → entity KPI; entities summed to Group → Group KPI (recalculated from totals, never averaged) | K105: — | L105: — | M105: — | N105: — | O105: — | P105: — | Q105: ='Entity KPIs'!K105 -> 0 | R105: ='Entity KPIs'!Q105 -> 0 | S105: ='Group KPIs'!K105 -> 0 | T105: 0 · Core Group G-07, Owner O-05 | U105: 2 same / 0 different
A106: CTL-005 | B106: Policy exceptions YTD | C106: count | D106: Year to date | E106: Sum of policy exceptions since April | F106: SUM(policy_exceptions@ytd) | G106: policy_exceptions | H106: Synthetic inputs added for this model | I106: Entity, Group | J106: Entity inputs → entity KPI; entities summed to Group → Group KPI (recalculated from totals, never averaged) | K106: — | L106: — | M106: — | N106: — | O106: — | P106: — | Q106: ='Entity KPIs'!K106 -> 2 | R106: ='Entity KPIs'!Q106 -> 2 | S106: ='Group KPIs'!K106 -> 4 | T106: 1 · Entity E-07; 3 · Core Group G-07, Owner O-05 | U106: 0 same / 3 different
A107: CTL-006 | B107: Unauthorised-vendor usage YTD | C107: count | D107: Year to date | E107: Sum of unauthorised vendor uses since April | F107: SUM(unauthorized_vendor_uses@ytd) | G107: unauthorized_vendor_uses | H107: Synthetic inputs added for this model | I107: Entity, Group | J107: Entity inputs → entity KPI; entities summed to Group → Group KPI (recalculated from totals, never averaged) | K107: — | L107: — | M107: — | N107: — | O107: — | P107: — | Q107: ='Entity KPIs'!K107 -> 0 | R107: ='Entity KPIs'!Q107 -> 0 | S107: ='Group KPIs'!K107 -> 0 | T107: 0 · Entity E-04, Entity E-07, Core Group G-07, Owner O-05 | U107: 4 same / 0 different
A108: CTL-007 | B108: Segregation-of-duties exceptions YTD | C108: count | D108: Year to date | E108: Sum of segregation-of-duties exceptions since April | F108: SUM(sod_exceptions@ytd) | G108: sod_exceptions | H108: Synthetic inputs added for this model | I108: Entity, Group | J108: Entity inputs → entity KPI; entities summed to Group → Group KPI (recalculated from totals, never averaged) | K108: — | L108: — | M108: — | N108: — | O108: — | P108: — | Q108: ='Entity KPIs'!K108 -> 0 | R108: ='Entity KPIs'!Q108 -> 1 | S108: ='Group KPIs'!K108 -> 1 | T108: 0 · Entity E-07; 1 · Core Group G-07, Owner O-05 | U108: 3 same / 0 different
A109: CTL-008 | B109: Unauthorised-access events YTD | C109: count | D109: Year to date | E109: Sum of unauthorised access events since April | F109: SUM(unauthorized_access_events@ytd) | G109: unauthorized_access_events | H109: Synthetic inputs added for this model | I109: Entity, Group | J109: Entity inputs → entity KPI; entities summed to Group → Group KPI (recalculated from totals, never averaged) | K109: — | L109: — | M109: — | N109: — | O109: — | P109: — | Q109: ='Entity KPIs'!K109 -> 0 | R109: ='Entity KPIs'!Q109 -> 0 | S109: ='Group KPIs'!K109 -> 0 | T109: 0 · Entity E-07, Core Group G-07, Owner O-05 | U109: 3 same / 0 different
A110: CTL-009 | B110: Data-sharing exceptions YTD | C110: count | D110: Year to date | E110: Sum of data-sharing exceptions since April | F110: SUM(data_sharing_exceptions@ytd) | G110: data_sharing_exceptions | H110: Synthetic inputs added for this model | I110: Entity, Group | J110: Entity inputs → entity KPI; entities summed to Group → Group KPI (recalculated from totals, never averaged) | K110: — | L110: — | M110: — | N110: — | O110: — | P110: — | Q110: ='Entity KPIs'!K110 -> 0 | R110: ='Entity KPIs'!Q110 -> 0 | S110: ='Group KPIs'!K110 -> 0 | T110: 0 · Entity E-07, Core Group G-07, Owner O-05 | U110: 3 same / 0 different
A111: CTL-010 | B111: Manual overrides YTD | C111: count | D111: Year to date | E111: Sum of manual operational or system overrides since April | F111: SUM(manual_overrides@ytd) | G111: manual_overrides | H111: Synthetic inputs added for this model | I111: Entity, Group | J111: Entity inputs → entity KPI; entities summed to Group → Group KPI (recalculated from totals, never averaged) | K111: — | L111: — | M111: — | N111: — | O111: — | P111: — | Q111: ='Entity KPIs'!K111 -> 7 | R111: ='Entity KPIs'!Q111 -> 7 | S111: ='Group KPIs'!K111 -> 14 | T111: 5 · Entity E-07; 12 · Core Group G-07, Owner O-05 | U111: 0 same / 3 different
A112: CTL-003 | B112: Assurance reviews completed | C112: text | D112: Year to date | E112: Assurance reviews completed since April, of those planned since April | F112: SUM(assurance_reviews_done@ytd)&" of "&SUM(assurance_reviews_planned@ytd) | G112: assurance_reviews_planned, assurance_reviews_done | H112: Synthetic inputs added for this model | I112: Entity, Group | J112: Entity inputs → entity KPI; entities summed to Group → Group KPI (recalculated from totals, never averaged) | K112: — | L112: — | M112: — | N112: — | O112: — | P112: — | Q112: ='Entity KPIs'!K112 -> 2 of 4 | R112: ='Entity KPIs'!Q112 -> 4 of 4 | S112: ='Group KPIs'!K112 -> 6 of 8 | T112: 6 of 8 · Core Group G-07 | U112: 1 same / 0 different
A113: GOV-001 | B113: Ageing certification approvals | C113: count | D113: Month end | E113: Certification approvals past due date | F113: cert_approvals_ageing | G113: cert_approvals_ageing | H113: Synthetic inputs added for this model | I113: Entity, Group | J113: Entity inputs → entity KPI; entities summed to Group → Group KPI (recalculated from totals, never averaged) | K113: — | L113: — | M113: — | N113: — | O113: — | P113: — | Q113: ='Entity KPIs'!K113 -> 1 | R113: ='Entity KPIs'!Q113 -> 1 | S113: ='Group KPIs'!K113 -> 2 | T113: 1 · Entity E-08; 2 > [PH] d · Core Group G-08, Owner G-08 | U113: 3 same / 0 different
A114: GOV-002 | B114: KPI overrides | C114: count | D114: Month end | E114: KPI values overridden | F114: kpi_overrides | G114: kpi_overrides | H114: Synthetic inputs added for this model | I114: Entity, Group | J114: Entity inputs → entity KPI; entities summed to Group → Group KPI (recalculated from totals, never averaged) | K114: — | L114: — | M114: — | N114: — | O114: — | P114: — | Q114: ='Entity KPIs'!K114 -> 0 | R114: ='Entity KPIs'!Q114 -> 0 | S114: ='Group KPIs'!K114 -> 0 | T114: 0 · Entity E-08, Core Group G-08, Owner G-08 | U114: 4 same / 0 different
A115: GOV-003 | B115: Recurring data-quality issues | C115: count | D115: Month end | E115: Recurring data-quality issues | F115: dq_issues_recurring | G115: dq_issues_recurring | H115: Synthetic inputs added for this model | I115: Entity, Group | J115: Entity inputs → entity KPI; entities summed to Group → Group KPI (recalculated from totals, never averaged) | K115: — | L115: — | M115: — | N115: — | O115: — | P115: — | Q115: ='Entity KPIs'!K115 -> 1 | R115: ='Entity KPIs'!Q115 -> 0 | S115: ='Group KPIs'!K115 -> 1 | T115: 1 (L2 meter mapping) · Entity E-08; 1 · Core Group G-08, Owner G-08 | U115: 3 same / 0 different
... A142: SIG-006 | B142: Cash burn signal | C142: text | D142: Month | E142: Triggered if operating cash flow in the month is negative | F142: IF(op_cash_flow_k<0,"Triggered","Not triggered") | G142: variable_cost_k, fixed_cost_k, revenue_k, overhead_k, tax_paid_k, receivables_k, payables_k, inventory_k | H142: Original plant data + synthetic inputs added for this model | I142: Entity, Group | J142: Plant inputs summed to each entity + entity inputs → entity KPI; entities summed to Group → Group KPI (recalculated from totals, never averaged) | K142: — | L142: — | M142: — | N142: — | O142: — | P142: — | Q142: ='Entity KPIs'!K142 -> Not triggered | R142: ='Entity KPIs'!Q142 -> Not triggered | S142: ='Group KPIs'!K142 -> Not triggered | T142: Not triggered · Owner O-03 | U142: 1 same / 0 different
A143: SIG-013 | B143: Pricing pressure | C143: text | D143: Month | E143: Realised price vs plan: Low if above −1%, Medium down to −3%, High below −3% | F143: IF(price_vs_plan_pct>=-1,"Low",IF(price_vs_plan_pct>=-3,"Medium","High"))&" ("&ROUND(price_vs_plan_pct,1)&"% vs plan price)" | G143: sales_t, planned_sales_t, revenue_k, planned_revenue_k | H143: Synthetic inputs added for this model | I143: Plant, Entity, Group | J143: Plant inputs → each plant's KPI; Plant inputs summed to each entity → entity KPI; entities summed to Group → Group KPI (recalculated from totals, never averaged) | K143: ='Plant KPIs'!K58 -> Low (0.2% vs plan price) | L143: ='Plant KPIs'!Q58 -> Medium (-2.3% vs plan price) | M143: ='Plant KPIs'!W58 -> Low (-0.5% vs plan price) | N143: ='Plant KPIs'!AC58 -> Low (-0.7% vs plan price) | O143: ='Plant KPIs'!AI58 -> Low (0.2% vs plan price) | P143: ='Plant KPIs'!AO58 -> Low (0.5% vs plan price) | Q143: ='Entity KPIs'!K143 -> Low (-0.9% vs plan price) | R143: ='Entity KPIs'!Q143 -> Low (0% vs plan price) | S143: ='Group KPIs'!K143 -> Low (-0.4% vs plan price) | T143: Low · Core Group G-03 | U143: 1 same / 0 different
A144: PRD-001 | B144: Days to breach (earliest plant) | C144: days | D144: Forecast | E144: Lowest plant forecast of days until its production plan is breached (99 = not expected) | F144: days_to_breach | G144: days_to_breach | H144: Synthetic inputs added for this model | I144: Plant, Entity, Group | J144: Plant inputs → each plant's KPI; Plant inputs summed to each entity → entity KPI; entities summed to Group → Group KPI (recalculated from totals, never averaged) | K144: ='Plant KPIs'!K59 -> 99 | L144: ='Plant KPIs'!Q59 -> 4 | M144: ='Plant KPIs'!W59 -> 99 | N144: ='Plant KPIs'!AC59 -> 99 | O144: ='Plant KPIs'!AI59 -> 99 | P144: ='Plant KPIs'!AO59 -> 99 | Q144: ='Entity KPIs'!K144 -> 4 | R144: ='Entity KPIs'!Q144 -> 99 | S144: ='Group KPIs'!K144 -> 4 | T144: 4 days · Entity E-01, Entity E-04, Owner O-01, Owner O-02, Owner O-09, Owner S-10, Core Group S-12, Entity S-12, Owner STATE GALLERY | U144: 10 same / 0 different
A145: PRD-002 | B145: Probability of production plan miss, next month | C145: % | D145: Next month | E145: Chance that output falls below plan: normal distribution with mean = Forecast good output, spread = √(sum of plant forecast variances) | F145: 100*NORM.DIST(planned_production_next_t,forecast_good_next_t,SQRT(forecast_good_var_next),TRUE) | G145: planned_production_next_t, forecast_good_next_t, forecast_good_var_next | H145: Synthetic inputs added for this model | I145: Plant, Entity, Group | J145: Plant inputs → each plant's KPI; Plant inputs summed to each entity → entity KPI; entities summed to Group → Group KPI (recalculated from totals, never averaged) | K145: ='Plant KPIs'!K60 -> 38.81 | L145: ='Plant KPIs'!Q60 -> 98.27 | M145: ='Plant KPIs'!W60 -> 43.19 | N145: ='Plant KPIs'!AC60 -> 52.26 | O145: ='Plant KPIs'!AI60 -> 46.86 | P145: ='Plant KPIs'!AO60 -> 43.2 | Q145: ='Entity KPIs'!K145 -> 79.36 | R145: ='Entity KPIs'!Q145 -> 45.13 | S145: ='Group KPIs'!K145 -> 69.69 | T145: 64% · Core Group G-01, Core Group G-10, Owner O-01, Owner O-02, Owner STATE GALLERY; 64 % · Core Group S-12; 71 % · Entity S-12 | U145: 0 same / 9 different
A146: PRD-003 | B146: Projected EBITDA gap, rest of year | C146: ₹ m | D146: Forecast | E146: (Forecast EBITDA − Planned EBITDA, rest of year) ÷ 1000 | F146: (forecast_ebitda_rest_k-planned_ebitda_rest_k)/1000 | G146: forecast_ebitda_rest_k, planned_ebitda_rest_k | H146: Synthetic inputs added for this model | I146: Entity, Group | J146: Entity inputs → entity KPI; entities summed to Group → Group KPI (recalculated from totals, never averaged) | K146: — | L146: — | M146: — | N146: — | O146: — | P146: — | Q146: ='Entity KPIs'!K146 -> -48.53 | R146: ='Entity KPIs'!Q146 -> -7.65 | S146: ='Group KPIs'!K146 -> -56.18 | T146: −₹9.2 m · Core Group G-01, Core Group G-03, Core Group G-10, Owner O-01, Owner O-02, Owner STATE GALLERY; −9.2 ₹ m · Owner S-09, Core Group S-12; −7.6 ₹ m · Entity S-12 | U146: 0 same / 11 different
A147: PRD-004 | B147: Projected liquidity gap, next 90 days | C147: ₹ m or text | D147: Next 90 days | E147: Cash + Undrawn facilities + Forecast net cash flow (90 days); 'None' if not negative | F147: IF(cash_k+undrawn_facilities_k+forecast_net_cash_flow_90d_k>=0,"None within 90 d",ROUND((cash_k+undrawn_facilities_k+forecast_net_cash_flow_90d_k)/1000,1)) | G147: cash_k, undrawn_facilities_k, forecast_net_cash_flow_90d_k | H147: Synthetic inputs added for this model | I147: Entity, Group | J147: Entity inputs → entity KPI; entities summed to Group → Group KPI (recalculated from totals, never averaged) | K147: — | L147: — | M147: — | N147: — | O147: — | P147: — | Q147: ='Entity KPIs'!K147 -> None within 90 d | R147: ='Entity KPIs'!Q147 -> None within 90 d | S147: ='Group KPIs'!K147 -> None within 90 d | T147: None within 90 d · Core Group G-01, Core Group G-04, Owner O-03; None · Owner O-02, Entity S-12; None in 90 d · Core Group S-12 | U147: 7 same / 0 different
A148: PRD-005 | B148: Forecast covenant breach | C148: text | D148: Quarter end | E148: Breach forecast if Forecast net debt ÷ Forecast 12-month EBITDA exceeds the covenant limit | F148: IF(forecast_ebitda_ltm_k=0,"No forecast",IF(forecast_net_debt_k/forecast_ebitda_ltm_k>CovenantMax,"Breach forecast","Not forecast")) | G148: forecast_net_debt_k, forecast_ebitda_ltm_k | H148: Synthetic inputs added for this model | I148: Entity, Group | J148: Entity inputs → entity KPI; entities summed to Group → Group KPI (recalculated from totals, never averaged) | K148: — | L148: — | M148: — | N148: — | O148: — | P148: — | Q148: ='Entity KPIs'!K148 -> Not forecast | R148: ='Entity KPIs'!Q148 -> Not forecast | S148: ='Group KPIs'!K148 -> Not forecast | T148: Not forecast · Core Group G-04, Owner O-02, Owner O-03; None forecast · Core Group G-10; No · Core Group S-12; No breach · headroom 1.2× · Entity S-12 | U148: 5 same / 2 different
A149: PRD-006 | B149: Production loss from downtime, next month | C149: kt | D149: Next month | E149: Forecast production lost to downtime next month ÷ 1000 | F149: forecast_downtime_loss_next_t/1000 | G149: forecast_downtime_loss_next_t | H149: Synthetic inputs added for this model | I149: Plant, Entity, Group | J149: Plant inputs → each plant's KPI; Plant inputs summed to each entity → entity KPI; entities summed to Group → Group KPI (recalculated from totals, never averaged) | K149: ='Plant KPIs'!K61 -> 4.17 | L149: ='Plant KPIs'!Q61 -> 15.61 | M149: ='Plant KPIs'!W61 -> 2.51 | N149: ='Plant KPIs'!AC61 -> 1.42 | O149: ='Plant KPIs'!AI61 -> 2.27 | P149: ='Plant KPIs'!AO61 -> 2.02 | Q149: ='Entity KPIs'!K149 -> 22.3 | R149: ='Entity KPIs'!Q149 -> 5.71 | S149: ='Group KPIs'!K149 -> 28.01 | T149: 11.2 kt · Core Group G-05, Core Group G-10, Owner O-09 | U149: 0 same / 4 different
A150: PRD-007 | B150: Probability OEE below 78%, next month | C150: % | D150: Next month | E150: Chance that Forecast good output < 78% × Ideal output next month (same distribution as PRD-002) | F150: 100*NORM.DIST(0.78*ideal_output_next_t,forecast_good_next_t,SQRT(forecast_good_var_next),TRUE) | G150: forecast_good_next_t, forecast_good_var_next, ideal_output_next_t | H150: Synthetic inputs added for this model | I150: Plant, Entity, Group | J150: Plant inputs → each plant's KPI; Plant inputs summed to each entity → entity KPI; entities summed to Group → Group KPI (recalculated from totals, never averaged) | K150: ='Plant KPIs'!K62 -> 2.06 | L150: ='Plant KPIs'!Q62 -> 31.38 | M150: ='Plant KPIs'!W62 -> 3.14 | N150: ='Plant KPIs'!AC62 -> 2.77 | O150: ='Plant KPIs'!AI62 -> 0.63 | P150: ='Plant KPIs'!AO62 -> 1.51 | Q150: ='Entity KPIs'!K150 -> 0.59 | R150: ='Entity KPIs'!Q150 -> 0.01 | S150: ='Group KPIs'!K150 -> 0 | T150: 41% · Owner O-09 | U150: 0 same / 1 different
A151: CST-005 | B151: Fixed cost YTD | C151: ₹ m | D151: Year to date | E151: Sum of fixed cost since April ÷ 1000 | F151: SUM(fixed_cost_k@ytd)/1000 | G151: fixed_cost_k | H151: Original plant data (plant_base.csv, synthetic) | I151: Plant, Entity, Group | J151: Plant inputs → each plant's KPI; Plant inputs summed to each entity → entity KPI; entities summed to Group → Group KPI (recalculated from totals, never averaged) | K151: ='Plant KPIs'!K63 -> 7.25 | L151: ='Plant KPIs'!Q63 -> 7.2 | M151: ='Plant KPIs'!W63 -> 6.99 | N151: ='Plant KPIs'!AC63 -> 7.18 | O151: ='Plant KPIs'!AI63 -> 8.37 | P151: ='Plant KPIs'!AO63 -> 7.59 | Q151: ='Entity KPIs'!K151 -> 21.44 | R151: ='Entity KPIs'!Q151 -> 23.14 | S151: ='Group KPIs'!K151 -> 44.58 | T151: ₹61 m · Entity E-11 | U151: 0 same / 1 different
A152: PRD-008 | B152: Projected FCF gap, full year | C152: ₹ m | D152: Forecast | E152: (Forecast EBITDA − Planned EBITDA, rest of year) × (1 − Tax rate) ÷ 1000 | F152: (forecast_ebitda_rest_k-planned_ebitda_rest_k)*(1-TaxRate)/1000 | G152: forecast_ebitda_rest_k, planned_ebitda_rest_k | H152: Synthetic inputs added for this model | I152: Entity, Group | J152: Entity inputs → entity KPI; entities summed to Group → Group KPI (recalculated from totals, never averaged) | K152: — | L152: — | M152: — | N152: — | O152: — | P152: — | Q152: ='Entity KPIs'!K152 -> -36.4 | R152: ='Entity KPIs'!Q152 -> -5.74 | S152: ='Group KPIs'!K152 -> -42.14 | T152: −₹9 m · Entity E-11 | U152: 0 same / 1 different
A153: PRD-009 | B153: ROCE at P12 (forecast) | C153: % | D153: Forecast | E153: (EBIT since April + Forecast EBITDA rest of year − Depreciation × remaining months) ÷ Capital employed × 100 | F153: IF(capital_employed_k=0,0,100*(SUM(ebit_k@ytd)+forecast_ebitda_rest_k-depreciation_k*(12-ytd_months))/capital_employed_k) | G153: variable_cost_k, fixed_cost_k, revenue_k, depreciation_k, overhead_k, capital_employed_k, forecast_ebitda_rest_k | H153: Original plant data + synthetic inputs added for this model | I153: Entity, Group | J153: Plant inputs summed to each entity + entity inputs → entity KPI; entities summed to Group → Group KPI (recalculated from totals, never averaged) | K153: — | L153: — | M153: — | N153: — | O153: — | P153: — | Q153: ='Entity KPIs'!K153 -> 13.51 | R153: ='Entity KPIs'!Q153 -> 15.07 | S153: ='Group KPIs'!K153 -> 14.26 | T153: 11.0% · Entity E-11 | U153: 0 same / 1 different
A154: PRD-010 | B154: Revenue per FTE | C154: ₹ m | D154: Year to date | E154: Revenue since April ÷ 1000 ÷ FTEs, where FTEs = Hours worked since April ÷ (2,000 h a year × months elapsed ÷ 12) | F154: IF(SUM(hours_worked@ytd)=0,0,SUM(revenue_k@ytd)/1000/(SUM(hours_worked@ytd)/(HoursPerFTE*ytd_months/12))) | G154: hours_worked, revenue_k | H154: Original plant data + synthetic inputs added for this model | I154: Plant, Entity, Group | J154: Plant inputs → each plant's KPI; Plant inputs summed to each entity → entity KPI; entities summed to Group → Group KPI (recalculated from totals, never averaged) | K154: ='Plant KPIs'!K64 -> 4.47 | L154: ='Plant KPIs'!Q64 -> 4.93 | M154: ='Plant KPIs'!W64 -> 6.59 | N154: ='Plant KPIs'!AC64 -> 4.27 | O154: ='Plant KPIs'!AI64 -> 6.82 | P154: ='Plant KPIs'!AO64 -> 4.86 | Q154: ='Entity KPIs'!K154 -> 5.36 | R154: ='Entity KPIs'!Q154 -> 5.32 | S154: ='Group KPIs'!K154 -> 5.34 | T154: ₹0.41 m · Entity E-11 | U154: 0 same / 1 different
A155: PRD-011 | B155: Tonnes per FTE | C155: t | D155: Year to date | E155: Good output since April ÷ FTEs (FTEs as in PRD-010) | F155: IF(SUM(hours_worked@ytd)=0,0,SUM(good_output_t@ytd)/(SUM(hours_worked@ytd)/(HoursPerFTE*ytd_months/12))) | G155: good_output_t, hours_worked | H155: Original plant data (plant_base.csv, synthetic) | I155: Plant, Entity, Group | J155: Plant inputs → each plant's KPI; Plant inputs summed to each entity → entity KPI; entities summed to Group → Group KPI (recalculated from totals, never averaged) | K155: ='Plant KPIs'!K65 -> 1186.11 | L155: ='Plant KPIs'!Q65 -> 1336.62 | M155: ='Plant KPIs'!W65 -> 1779.21 | N155: ='Plant KPIs'!AC65 -> 1135.52 | O155: ='Plant KPIs'!AI65 -> 1810.4 | P155: ='Plant KPIs'!AO65 -> 1290.61 | Q155: ='Entity KPIs'!K155 -> 1442.13 | R155: ='Entity KPIs'!Q155 -> 1412.54 | S155: ='Group KPIs'!K155 -> 1427.42 | T155: 236 t · Entity E-11 | U155: 0 same / 1 different
A156: PRD-012 | B156: Probability of EBITDA plan miss, full year | C156: % | D156: Forecast | E156: Chance that EBITDA for the rest of the year falls below plan: normal distribution with mean = Forecast EBITDA, spread = Forecast error × Forecast EBITDA | F156: IF(forecast_ebitda_rest_k=0,0,100*NORM.DIST(planned_ebitda_rest_k,forecast_ebitda_rest_k,ForecastError*forecast_ebitda_rest_k,TRUE)) | G156: forecast_ebitda_rest_k, planned_ebitda_rest_k | H156: Synthetic inputs added for this model | I156: Entity, Group | J156: Entity inputs → entity KPI; entities summed to Group → Group KPI (recalculated from totals, never averaged) | K156: — | L156: — | M156: — | N156: — | O156: — | P156: — | Q156: ='Entity KPIs'!K156 -> 85.18 | R156: ='Entity KPIs'!Q156 -> 56.48 | S156: ='Group KPIs'!K156 -> 72.63 | T156: 58% · Entity E-11 | U156: 0 same / 1 different
A157: REG-011 | B157: Disclosure clock (open incident) | C157: text | D157: Month end | E157: Hours left on the earliest open disclosure clock (999 = none running) | F157: IF(disclosure_clock_hours>=999,"No clock running",disclosure_clock_hours&" h remaining") | G157: disclosure_clock_hours | H157: Synthetic inputs added for this model | I157: Entity, Group | J157: Entity inputs → entity KPI; entities summed to Group → Group KPI (recalculated from totals, never averaged) | K157: — | L157: — | M157: — | N157: — | O157: — | P157: — | Q157: ='Entity KPIs'!K157 -> 38 h remaining | R157: ='Entity KPIs'!Q157 -> No clock running | S157: ='Group KPIs'!K157 -> 38 h remaining | T157: 38 h remaining · Entity E-07 | U157: 2 same / 0 different
A158: SIG-002 | B158: Yield (leading signal) | C158: text | D158: Month | E158: Change in Yield (PLT-005) from last month: Stable if under 1 pt, otherwise Improving or Deteriorating | F158: IF(ABS(100*good_output_t/feed_input_t-100*good_output_t@prev/feed_input_t@prev)<1,"Stable",IF(100*good_output_t/feed_input_t>100*good_output_t@prev/feed_input_t@prev,"Improving","Deteriorating"))&" ("&ROUND(100*good_output_t/feed_input_t-100*good_output_t@prev/feed_input_t@prev,1)&" pts vs last month)" | G158: good_output_t, feed_input_t | H158: Original plant data (plant_base.csv, synthetic) | I158: Plant, Entity, Group | J158: Plant inputs → each plant's KPI; Plant inputs summed to each entity → entity KPI; entities summed to Group → Group KPI (recalculated from totals, never averaged) | K158: ='Plant KPIs'!K66 -> Stable (-1 pts vs last month) | L158: ='Plant KPIs'!Q66 -> Improving (4.5 pts vs last month) | M158: ='Plant KPIs'!W66 -> Deteriorating (-1.7 pts vs last month) | N158: ='Plant KPIs'!AC66 -> Stable (-1 pts vs last month) | O158: ='Plant KPIs'!AI66 -> Improving (3.9 pts vs last month) | P158: ='Plant KPIs'!AO66 -> Stable (0.2 pts vs last month) | Q158: ='Entity KPIs'!K158 -> Stable (0.3 pts vs last month) | R158: ='Entity KPIs'!Q158 -> Improving (1.4 pts vs last month) | S158: ='Group KPIs'!K158 -> Stable (0.8 pts vs last month) | T158: Stable · Entity E-02 | U158: 1 same / 0 different
A159: SIG-003 | B159: Recovery (leading signal) | C159: text | D159: Month | E159: Change in Recovery (PLT-004) from last month: Stable if under 1 pt, otherwise Improving or Deteriorating | F159: IF(ABS(100*recovered_contained_t/feed_contained_t-100*recovered_contained_t@prev/feed_contained_t@prev)<1,"Stable",IF(100*recovered_contained_t/feed_contained_t>100*recovered_contained_t@prev/feed_contained_t@prev,"Improving","Deteriorating"))&" ("&ROUND(100*recovered_contained_t/feed_contained_t-100*recovered_contained_t@prev/feed_contained_t@prev,1)&" pts vs last month)" | G159: feed_contained_t, recovered_contained_t | H159: Original plant data (plant_base.csv, synthetic) | I159: Plant, Entity, Group | J159: Plant inputs → each plant's KPI; Plant inputs summed to each entity → entity KPI; entities summed to Group → Group KPI (recalculated from totals, never averaged) | K159: ='Plant KPIs'!K67 -> Improving (3 pts vs last month) | L159: ='Plant KPIs'!Q67 -> Improving (4.4 pts vs last month) | M159: ='Plant KPIs'!W67 -> Deteriorating (-3.4 pts vs last month) | N159: ='Plant KPIs'!AC67 -> Stable (-0.8 pts vs last month) | O159: ='Plant KPIs'!AI67 -> Deteriorating (-2.1 pts vs last month) | P159: ='Plant KPIs'!AO67 -> Deteriorating (-5.8 pts vs last month) | Q159: ='Entity KPIs'!K159 -> Stable (0.5 pts vs last month) | R159: ='Entity KPIs'!Q159 -> Deteriorating (-2.9 pts vs last month) | S159: ='Group KPIs'!K159 -> Deteriorating (-1.2 pts vs last month) | T159: Stable · Entity E-02 | U159: 1 same / 0 different
A160: SIG-010 | B160: Single-source supply risk | C160: text | D160: Month end | E160: Elevated if there are critical single-source suppliers and any critical material is at risk, otherwise Normal | F160: IF(AND(single_source_suppliers>0,critical_material_risks>0),"Elevated","Normal")&" ("&single_source_suppliers&" single-source suppliers, "&critical_material_risks&" materials at risk)" | G160: critical_material_risks, single_source_suppliers | H160: Original plant data + synthetic inputs added for this model | I160: Entity, Group | J160: Plant inputs summed to each entity + entity inputs → entity KPI; entities summed to Group → Group KPI (recalculated from totals, never averaged) | K160: — | L160: — | M160: — | N160: — | O160: — | P160: — | Q160: ='Entity KPIs'!K160 -> Elevated (2 single-source suppliers, 4 materials at risk) | R160: ='Entity KPIs'!Q160 -> Elevated (1 single-source suppliers, 1 materials at risk) | S160: ='Group KPIs'!K160 -> Elevated (3 single-source suppliers, 5 materials at risk) | T160: S-07 · elevated · Entity E-01, Entity E-04; (no value) · Core Group S-12 | U160: 2 same / 0 different / 1 other
A161: SIG-016 | B161: Freight exposure | C161: text | D161: Month | E161: Freight cost vs plan: Normal up to 2% over plan, Watch up to 5%, Alert above 5% | F161: IF(planned_freight_cost_k=0,"No plan",IF(100*(freight_cost_k/planned_freight_cost_k-1)<=2,"Normal",IF(100*(freight_cost_k/planned_freight_cost_k-1)<=5,"Watch","Alert"))&" ("&ROUND(100*(freight_cost_k/planned_freight_cost_k-1),1)&"% vs plan)") | G161: freight_cost_k, planned_freight_cost_k | H161: Synthetic inputs added for this model | I161: Entity, Group | J161: Entity inputs → entity KPI; entities summed to Group → Group KPI (recalculated from totals, never averaged) | K161: — | L161: — | M161: — | N161: — | O161: — | P161: — | Q161: ='Entity KPIs'!K161 -> Watch (3.5% vs plan) | R161: ='Entity KPIs'!Q161 -> Normal (0.5% vs plan) | S161: ='Group KPIs'!K161 -> Normal (2% vs plan) | T161: (no value) · Core Group S-12 | U161: 0 same / 0 different / 1 other

Sheet Lineage (Sep 2026)
A1: KPI ID | B1: Step | C1: Item | D1: Field | E1: Used in the formula as | F1: Plant 01 | G1: Plant 02 | H1: Plant 03 | I1: Plant 04 | J1: Plant 05 | K1: Plant 06 | L1: Entity A1 | M1: Entity A2 | N1: Group | O1: How it rolls up
A2: OPS-001 Production vs plan (%) = Good output ÷ Planned production × 100
A3: OPS-001 | B3: Input | C3: Good output (t) | D3: good_output_t | E3: This month | F3: ='Plant Inputs'!P9 -> 81854 | G3: ='Plant Inputs'!P15 -> 95233 | H3: ='Plant Inputs'!P21 -> 139711 | I3: ='Plant Inputs'!P27 -> 81694 | J3: ='Plant Inputs'!P33 -> 132787 | K3: ='Plant Inputs'!P39 -> 94388 | L3: ='Entity Inputs'!N9 -> 316798 | M3: ='Entity Inputs'!N15 -> 308869 | N3: ='Group Inputs'!M9 -> 625667 | O3: Sum of 3 plants → sum of 2 entities
A4: OPS-001 | B4: Input | C4: Planned production (t) | D4: planned_production_t | E4: This month | F4: ='Plant Inputs'!N9 -> 85234 | G4: ='Plant Inputs'!N15 -> 121475 | H4: ='Plant Inputs'!N21 -> 140379 | I4: ='Plant Inputs'!N27 -> 79048 | J4: ='Plant Inputs'!N33 -> 130881 | K4: ='Plant Inputs'!N39 -> 98037 | L4: ='Entity Inputs'!L9 -> 347088 | M4: ='Entity Inputs'!L15 -> 307966 | N4: ='Group Inputs'!K9 -> 655054 | O4: Sum of 3 plants → sum of 2 entities
A5: OPS-001 | B5: KPI result | C5: Production vs plan | E5: Month | F5: ='Plant KPIs'!K2 -> 96.03 | G5: ='Plant KPIs'!Q2 -> 78.4 | H5: ='Plant KPIs'!W2 -> 99.52 | I5: ='Plant KPIs'!AC2 -> 103.35 | J5: ='Plant KPIs'!AI2 -> 101.46 | K5: ='Plant KPIs'!AO2 -> 96.28 | L5: ='Entity KPIs'!K2 -> 91.27 | M5: ='Entity KPIs'!Q2 -> 100.29 | N5: ='Group KPIs'!K2 -> 95.51 | O5: Same formula applied at each level to that level's inputs
A7: OPS-003 Capacity utilization (%) = Good output ÷ Installed capacity × 100
A8: OPS-003 | B8: Input | C8: Good output (t) | D8: good_output_t | E8: This month | F8: ='Plant Inputs'!P9 -> 81854 | G8: ='Plant Inputs'!P15 -> 95233 | H8: ='Plant Inputs'!P21 -> 139711 | I8: ='Plant Inputs'!P27 -> 81694 | J8: ='Plant Inputs'!P33 -> 132787 | K8: ='Plant Inputs'!P39 -> 94388 | L8: ='Entity Inputs'!N9 -> 316798 | M8: ='Entity Inputs'!N15 -> 308869 | N8: ='Group Inputs'!M9 -> 625667 | O8: Sum of 3 plants → sum of 2 entities
A9: OPS-003 | B9: Input | C9: Installed capacity (t) | D9: installed_capacity_t | E9: This month | F9: ='Plant Inputs'!M9 -> 98712 | G9: ='Plant Inputs'!M15 -> 136008 | H9: ='Plant Inputs'!M21 -> 162288 | I9: ='Plant Inputs'!M27 -> 91296 | J9: ='Plant Inputs'!M33 -> 147600 | K9: ='Plant Inputs'!M39 -> 113904 | L9: ='Entity Inputs'!K9 -> 397008 | M9: ='Entity Inputs'!K15 -> 352800 | N9: ='Group Inputs'!J9 -> 749808 | O9: Sum of 3 plants → sum of 2 entities
A10: OPS-003 | B10: KPI result | C10: Capacity utilization | E10: Month | F10: ='Plant KPIs'!K3 -> 82.92 | G10: ='Plant KPIs'!Q3 -> 70.02 | H10: ='Plant KPIs'!W3 -> 86.09 | I10: ='Plant KPIs'!AC3 -> 89.48 | J10: ='Plant KPIs'!AI3 -> 89.96 | K10: ='Plant KPIs'!AO3 -> 82.87 | L10: ='Entity KPIs'!K3 -> 79.8 | M10: ='Entity KPIs'!Q3 -> 87.55 | N10: ='Group KPIs'!K3 -> 83.44 | O10: Same formula applied at each level to that level's inputs
A12: PLT-001 Asset utilization (%) = Run hours ÷ Calendar hours × 100
A13: PLT-001 | B13: Input | C13: Run hours (h) | D13: run_hours | E13: This month | F13: ='Plant Inputs'!J9 -> 664.5 | G13: ='Plant Inputs'!J15 -> 624.3 | H13: ='Plant Inputs'!J21 -> 695.4 | I13: ='Plant Inputs'!J27 -> 690.6 | J13: ='Plant Inputs'!J33 -> 689.9 | K13: ='Plant Inputs'!J39 -> 680.7 | L13: ='Entity Inputs'!H9 -> 1984.2 | M13: ='Entity Inputs'!H15 -> 2061.2 | N13: ='Group Inputs'!G9 -> 4045.4 | O13: Sum of 3 plants → sum of 2 entities
A14: PLT-001 | B14: Input | C14: Calendar hours (h) | D14: calendar_hours | E14: This month | F14: ='Plant Inputs'!H9 -> 720 | G14: ='Plant Inputs'!H15 -> 720 | H14: ='Plant Inputs'!H21 -> 720 | I14: ='Plant Inputs'!H27 -> 720 | J14: ='Plant Inputs'!H33 -> 720 | K14: ='Plant Inputs'!H39 -> 720 | L14: ='Entity Inputs'!F9 -> 2160 | M14: ='Entity Inputs'!F15 -> 2160 | N14: ='Group Inputs'!E9 -> 4320 | O14: Sum of 3 plants → sum of 2 entities
A15: PLT-001 | B15: KPI result | C15: Asset utilization | E15: Month | F15: ='Plant KPIs'!K4 -> 92.29 | G15: ='Plant KPIs'!Q4 -> 86.71 | H15: ='Plant KPIs'!W4 -> 96.58 | I15: ='Plant KPIs'!AC4 -> 95.92 | J15: ='Plant KPIs'!AI4 -> 95.82 | K15: ='Plant KPIs'!AO4 -> 94.54 | L15: ='Entity KPIs'!K4 -> 91.86 | M15: ='Entity KPIs'!Q4 -> 95.43 | N15: ='Group KPIs'!K4 -> 93.64 | O15: Same formula applied at each level to that level's inputs
A17: PLT-002 OEE (%) = Availability × Performance × Quality = Good output ÷ Ideal output × 100
A18: PLT-002 | B18: Input | C18: Good output (t) | D18: good_output_t | E18: This month | F18: ='Plant Inputs'!P9 -> 81854 | G18: ='Plant Inputs'!P15 -> 95233 | H18: ='Plant Inputs'!P21 -> 139711 | I18: ='Plant Inputs'!P27 -> 81694 | J18: ='Plant Inputs'!P33 -> 132787 | K18: ='Plant Inputs'!P39 -> 94388 | L18: ='Entity Inputs'!N9 -> 316798 | M18: ='Entity Inputs'!N15 -> 308869 | N18: ='Group Inputs'!M9 -> 625667 | O18: Sum of 3 plants → sum of 2 entities
A19: PLT-002 | B19: Input | C19: Ideal output (t) | D19: ideal_output_t | E19: This month | F19: ='Plant Inputs'!L9 -> 97478 | G19: ='Plant Inputs'!L15 -> 135441 | H19: ='Plant Inputs'!L21 -> 162063 | I19: ='Plant Inputs'!L27 -> 91042 | J19: ='Plant Inputs'!L33 -> 145550 | K19: ='Plant Inputs'!L39 -> 112638 | L19: ='Entity Inputs'!J9 -> 394982 | M19: ='Entity Inputs'!J15 -> 349230 | N19: ='Group Inputs'!I9 -> 744212 | O19: Sum of 3 plants → sum of 2 entities
A20: PLT-002 | B20: KPI result | C20: OEE | E20: Month | F20: ='Plant KPIs'!K5 -> 83.97 | G20: ='Plant KPIs'!Q5 -> 70.31 | H20: ='Plant KPIs'!W5 -> 86.21 | I20: ='Plant KPIs'!AC5 -> 89.73 | J20: ='Plant KPIs'!AI5 -> 91.23 | K20: ='Plant KPIs'!AO5 -> 83.8 | L20: ='Entity KPIs'!K5 -> 80.21 | M20: ='Entity KPIs'!Q5 -> 88.44 | N20: ='Group KPIs'!K5 -> 84.07 | O20: Same formula applied at each level to that level's inputs
A22: PLT-004 Recovery percentage (%) = Valuable content recovered ÷ Valuable content in feed × 100
A23: PLT-004 | B23: Input | C23: Valuable content recovered (t) | D23: recovered_contained_t | E23: This month | F23: ='Plant Inputs'!S9 -> 18334 | G23: ='Plant Inputs'!S15 -> 17994 | H23: ='Plant Inputs'!S21 -> 31527 | I23: ='Plant Inputs'!S27 -> 18005 | J23: ='Plant Inputs'!S33 -> 25111 | K23: ='Plant Inputs'!S39 -> 17410 | L23: ='Entity Inputs'!Q9 -> 67855 | M23: ='Entity Inputs'!Q15 -> 60526 | N23: ='Group Inputs'!P9 -> 128381 | O23: Sum of 3 plants → sum of 2 entities
A24: PLT-004 | B24: Input | C24: Valuable content in feed (t) | D24: feed_contained_t | E24: This month | F24: ='Plant Inputs'!R9 -> 19996 | G24: ='Plant Inputs'!R15 -> 20791 | H24: ='Plant Inputs'!R21 -> 36789 | I24: ='Plant Inputs'!R27 -> 20374 | J24: ='Plant Inputs'!R33 -> 28428 | K24: ='Plant Inputs'!R39 -> 20587 | L24: ='Entity Inputs'!P9 -> 77576 | M24: ='Entity Inputs'!P15 -> 69389 | N24: ='Group Inputs'!O9 -> 146965 | O24: Sum of 3 plants → sum of 2 entities
A25: PLT-004 | B25: KPI result | C25: Recovery percentage | E25: Month | F25: ='Plant KPIs'!K6 -> 91.69 | G25: ='Plant KPIs'!Q6 -> 86.55 | H25: ='Plant KPIs'!W6 -> 85.7 | I25: ='Plant KPIs'!AC6 -> 88.37 | J25: ='Plant KPIs'!AI6 -> 88.33 | K25: ='Plant KPIs'!AO6 -> 84.57 | L25: ='Entity KPIs'!K6 -> 87.47 | M25: ='Entity KPIs'!Q6 -> 87.23 | N25: ='Group KPIs'!K6 -> 87.35 | O25: Same formula applied at each level to that level's inputs
A27: PLT-005 Yield (%) = Good output ÷ Feed input × 100
A28: PLT-005 | B28: Input | C28: Good output (t) | D28: good_output_t | E28: This month | F28: ='Plant Inputs'!P9 -> 81854 | G28: ='Plant Inputs'!P15 -> 95233 | H28: ='Plant Inputs'!P21 -> 139711 | I28: ='Plant Inputs'!P27 -> 81694 | J28: ='Plant Inputs'!P33 -> 132787 | K28: ='Plant Inputs'!P39 -> 94388 | L28: ='Entity Inputs'!N9 -> 316798 | M28: ='Entity Inputs'!N15 -> 308869 | N28: ='Group Inputs'!M9 -> 625667 | O28: Sum of 3 plants → sum of 2 entities
A29: PLT-005 | B29: Input | C29: Feed input (t) | D29: feed_input_t | E29: This month | F29: ='Plant Inputs'!Q9 -> 89479 | G29: ='Plant Inputs'!Q15 -> 102279 | H29: ='Plant Inputs'!Q21 -> 154604 | I29: ='Plant Inputs'!Q27 -> 90180 | J29: ='Plant Inputs'!Q33 -> 142400 | K29: ='Plant Inputs'!Q39 -> 101633 | L29: ='Entity Inputs'!O9 -> 346362 | M29: ='Entity Inputs'!O15 -> 334213 | N29: ='Group Inputs'!N9 -> 680575 | O29: Sum of 3 plants → sum of 2 entities
A30: PLT-005 | B30: KPI result | C30: Yield | E30: Month | F30: ='Plant KPIs'!K7 -> 91.48 | G30: ='Plant KPIs'!Q7 -> 93.11 | H30: ='Plant KPIs'!W7 -> 90.37 | I30: ='Plant KPIs'!AC7 -> 90.59 | J30: ='Plant KPIs'!AI7 -> 93.25 | K30: ='Plant KPIs'!AO7 -> 92.87 | L30: ='Entity KPIs'!K7 -> 91.46 | M30: ='Entity KPIs'!Q7 -> 92.42 | N30: ='Group KPIs'!K7 -> 91.93 | O30: Same formula applied at each level to that level's inputs
A32: REL-001 MTBF (h) = Run hours ÷ Breakdowns
A33: REL-001 | B33: Input | C33: Run hours (h) | D33: run_hours | E33: This month | F33: ='Plant Inputs'!J9 -> 664.5 | G33: ='Plant Inputs'!J15 -> 624.3 | H33: ='Plant Inputs'!J21 -> 695.4 | I33: ='Plant Inputs'!J27 -> 690.6 | J33: ='Plant Inputs'!J33 -> 689.9 | K33: ='Plant Inputs'!J39 -> 680.7 | L33: ='Entity Inputs'!H9 -> 1984.2 | M33: ='Entity Inputs'!H15 -> 2061.2 | N33: ='Group Inputs'!G9 -> 4045.4 | O33: Sum of 3 plants → sum of 2 entities
A34: REL-001 | B34: Input | C34: Breakdowns (count) | D34: failures | E34: This month | F34: ='Plant Inputs'!U9 -> 4 | G34: ='Plant Inputs'!U15 -> 6 | H34: ='Plant Inputs'!U21 -> 2 | I34: ='Plant Inputs'!U27 -> 1 | J34: ='Plant Inputs'!U33 -> 1 | K34: ='Plant Inputs'!U39 -> 1 | L34: ='Entity Inputs'!S9 -> 12 | M34: ='Entity Inputs'!S15 -> 3 | N34: ='Group Inputs'!R9 -> 15 | O34: Sum of 3 plants → sum of 2 entities
A35: REL-001 | B35: KPI result | C35: MTBF | E35: Month | F35: ='Plant KPIs'!K8 -> 166.13 | G35: ='Plant KPIs'!Q8 -> 104.05 | H35: ='Plant KPIs'!W8 -> 347.7 | I35: ='Plant KPIs'!AC8 -> 690.6 | J35: ='Plant KPIs'!AI8 -> 689.9 | K35: ='Plant KPIs'!AO8 -> 680.7 | L35: ='Entity KPIs'!K8 -> 165.35 | M35: ='Entity KPIs'!Q8 -> 687.07 | N35: ='Group KPIs'!K8 -> 269.69 | O35: Same formula applied at each level to that level's inputs
A37: REL-002 Mean Time to Repair (h) = Repair hours ÷ Breakdowns
A38: REL-002 | B38: Input | C38: Repair hours (h) | D38: repair_hours | E38: This month | F38: ='Plant Inputs'!V9 -> 21.6 | G38: ='Plant Inputs'!V15 -> 68.5 | H38: ='Plant Inputs'!V21 -> 8.8 | I38: ='Plant Inputs'!V27 -> 6.8 | J38: ='Plant Inputs'!V33 -> 5.2 | K38: ='Plant Inputs'!V39 -> 6.5 | L38: ='Entity Inputs'!T9 -> 98.9 | M38: ='Entity Inputs'!T15 -> 18.5 | N38: ='Group Inputs'!S9 -> 117.4 | O38: Sum of 3 plants → sum of 2 entities
A39: REL-002 | B39: Input | C39: Breakdowns (count) | D39: failures | E39: This month | F39: ='Plant Inputs'!U9 -> 4 | G39: ='Plant Inputs'!U15 -> 6 | H39: ='Plant Inputs'!U21 -> 2 | I39: ='Plant Inputs'!U27 -> 1 | J39: ='Plant Inputs'!U33 -> 1 | K39: ='Plant Inputs'!U39 -> 1 | L39: ='Entity Inputs'!S9 -> 12 | M39: ='Entity Inputs'!S15 -> 3 | N39: ='Group Inputs'!R9 -> 15 | O39: Sum of 3 plants → sum of 2 entities
A40: REL-002 | B40: KPI result | C40: Mean Time to Repair | E40: Month | F40: ='Plant KPIs'!K9 -> 5.4 | G40: ='Plant KPIs'!Q9 -> 11.42 | H40: ='Plant KPIs'!W9 -> 4.4 | I40: ='Plant KPIs'!AC9 -> 6.8 | J40: ='Plant KPIs'!AI9 -> 5.2 | K40: ='Plant KPIs'!AO9 -> 6.5 | L40: ='Entity KPIs'!K9 -> 8.24 | M40: ='Entity KPIs'!Q9 -> 6.17 | N40: ='Group KPIs'!K9 -> 7.83 | O40: Same formula applied at each level to that level's inputs
A42: REL-003 Unplanned downtime (h) = Unplanned downtime
A43: REL-003 | B43: Input | C43: Unplanned downtime (h) | D43: unplanned_downtime_hours | E43: This month | F43: ='Plant Inputs'!K9 -> 30.2 | G43: ='Plant Inputs'!K15 -> 78.2 | H43: ='Plant Inputs'!K21 -> 12.3 | I43: ='Plant Inputs'!K27 -> 10.1 | J43: ='Plant Inputs'!K33 -> 10.2 | K43: ='Plant Inputs'!K39 -> 13.4 | L43: ='Entity Inputs'!I9 -> 120.7 | M43: ='Entity Inputs'!I15 -> 33.7 | N43: ='Group Inputs'!H9 -> 154.4 | O43: Sum of 3 plants → sum of 2 entities
A44: REL-003 | B44: KPI result | C44: Unplanned downtime | E44: Month | F44: ='Plant KPIs'!K10 -> 30.2 | G44: ='Plant KPIs'!Q10 -> 78.2 | H44: ='Plant KPIs'!W10 -> 12.3 | I44: ='Plant KPIs'!AC10 -> 10.1 | J44: ='Plant KPIs'!AI10 -> 10.2 | K44: ='Plant KPIs'!AO10 -> 13.4 | L44: ='Entity KPIs'!K10 -> 120.7 | M44: ='Entity KPIs'!Q10 -> 33.7 | N44: ='Group KPIs'!K10 -> 154.4 | O44: Same formula applied at each level to that level's inputs
A46: REL-004 Production loss from downtime (t) = Production lost to downtime
A47: REL-004 | B47: Input | C47: Production lost to downtime (t) | D47: prod_loss_downtime_t | E47: This month | F47: ='Plant Inputs'!T9 -> 4140 | G47: ='Plant Inputs'!T15 -> 14772 | H47: ='Plant Inputs'!T21 -> 2772 | I47: ='Plant Inputs'!T27 -> 1281 | J47: ='Plant Inputs'!T33 -> 2091 | K47: ='Plant Inputs'!T39 -> 2120 | L47: ='Entity Inputs'!R9 -> 21684 | M47: ='Entity Inputs'!R15 -> 5492 | N47: ='Group Inputs'!Q9 -> 27176 | O47: Sum of 3 plants → sum of 2 entities
A48: REL-004 | B48: KPI result | C48: Production loss from downtime | E48: Month | F48: ='Plant KPIs'!K11 -> 4140 | G48: ='Plant KPIs'!Q11 -> 14772 | H48: ='Plant KPIs'!W11 -> 2772 | I48: ='Plant KPIs'!AC11 -> 1281 | J48: ='Plant KPIs'!AI11 -> 2091 | K48: ='Plant KPIs'!AO11 -> 2120 | L48: ='Entity KPIs'!K11 -> 21684 | M48: ='Entity KPIs'!Q11 -> 5492 | N48: ='Group KPIs'!K11 -> 27176 | O48: Same formula applied at each level to that level's inputs
A50: REL-005 Preventive-maintenance compliance (%) = Preventive maintenance completed ÷ Preventive maintenance scheduled × 100
A51: REL-005 | B51: Input | C51: Preventive maintenance completed (count) | D51: pm_completed | E51: This month | F51: ='Plant Inputs'!X9 -> 43 | G51: ='Plant Inputs'!X15 -> 27 | H51: ='Plant Inputs'!X21 -> 58 | I51: ='Plant Inputs'!X27 -> 59 | J51: ='Plant Inputs'!X33 -> 41 | K51: ='Plant Inputs'!X39 -> 34 | L51: ='Entity Inputs'!V9 -> 128 | M51: ='Entity Inputs'!V15 -> 134 | N51: ='Group Inputs'!U9 -> 262 | O51: Sum of 3 plants → sum of 2 entities
A52: REL-005 | B52: Input | C52: Preventive maintenance scheduled (count) | D52: pm_scheduled | E52: This month | F52: ='Plant Inputs'!W9 -> 46 | G52: ='Plant Inputs'!W15 -> 33 | H52: ='Plant Inputs'!W21 -> 58 | I52: ='Plant Inputs'!W27 -> 59 | J52: ='Plant Inputs'!W33 -> 42 | K52: ='Plant Inputs'!W39 -> 36 | L52: ='Entity Inputs'!U9 -> 137 | M52: ='Entity Inputs'!U15 -> 137 | N52: ='Group Inputs'!T9 -> 274 | O52: Sum of 3 plants → sum of 2 entities
A53: REL-005 | B53: KPI result | C53: Preventive-maintenance compliance | E53: Month | F53: ='Plant KPIs'!K12 -> 93.48 | G53: ='Plant KPIs'!Q12 -> 81.82 | H53: ='Plant KPIs'!W12 -> 100 | I53: ='Plant KPIs'!AC12 -> 100 | J53: ='Plant KPIs'!AI12 -> 97.62 | K53: ='Plant KPIs'!AO12 -> 94.44 | L53: ='Entity KPIs'!K12 -> 93.43 | M53: ='Entity KPIs'!Q12 -> 97.81 | N53: ='Group KPIs'!K12 -> 95.62 | O53: Same formula applied at each level to that level's inputs
A55: CST-001 Cost per tonne (₹/t) = (Variable cost + Fixed cost) × 1000 ÷ Good output
A56: CST-001 | B56: Input | C56: Variable cost (₹ thousand) | D56: variable_cost_k | E56: This month | F56: ='Plant Inputs'!Y9 -> 226098.2 | G56: ='Plant Inputs'!Y15 -> 308111 | H56: ='Plant Inputs'!Y21 -> 365860.2 | I56: ='Plant Inputs'!Y27 -> 266460.1 | J56: ='Plant Inputs'!Y33 -> 398678.1 | K56: ='Plant Inputs'!Y39 -> 262617.2 | L56: ='Entity Inputs'!W9 -> 900069.4 | M56: ='Entity Inputs'!W15 -> 927755.4 | N56: ='Group Inputs'!V9 -> 1827824.8 | O56: Sum of 3 plants → sum of 2 entities
A57: CST-001 | B57: Input | C57: Fixed cost (₹ thousand) | D57: fixed_cost_k | E57: This month | F57: ='Plant Inputs'!AA9 -> 1375.5 | G57: ='Plant Inputs'!AA15 -> 940.2 | H57: ='Plant Inputs'!AA21 -> 1454.1 | I57: ='Plant Inputs'!AA27 -> 1127.6 | J57: ='Plant Inputs'!AA33 -> 1248.5 | K57: ='Plant Inputs'!AA39 -> 1573 | L57: ='Entity Inputs'!Y9 -> 3769.8 | M57: ='Entity Inputs'!Y15 -> 3949.1 | N57: ='Group Inputs'!X9 -> 7718.9 | O57: Sum of 3 plants → sum of 2 entities
A58: CST-001 | B58: Input | C58: Good output (t) | D58: good_output_t | E58: This month | F58: ='Plant Inputs'!P9 -> 81854 | G58: ='Plant Inputs'!P15 -> 95233 | H58: ='Plant Inputs'!P21 -> 139711 | I58: ='Plant Inputs'!P27 -> 81694 | J58: ='Plant Inputs'!P33 -> 132787 | K58: ='Plant Inputs'!P39 -> 94388 | L58: ='Entity Inputs'!N9 -> 316798 | M58: ='Entity Inputs'!N15 -> 308869 | N58: ='Group Inputs'!M9 -> 625667 | O58: Sum of 3 plants → sum of 2 entities
A59: CST-001 | B59: KPI result | C59: Cost per tonne | E59: Month | F59: ='Plant KPIs'!K13 -> 2779.02 | G59: ='Plant KPIs'!Q13 -> 3245.21 | H59: ='Plant KPIs'!W13 -> 2629.1 | I59: ='Plant KPIs'!AC13 -> 3275.49 | J59: ='Plant KPIs'!AI13 -> 3011.79 | K59: ='Plant KPIs'!AO13 -> 2798.98 | L59: ='Entity KPIs'!K13 -> 2853.05 | M59: ='Entity KPIs'!Q13 -> 3016.5 | N59: ='Group KPIs'!K13 -> 2933.74 | O59: Same formula applied at each level to that level's inputs
A61: CST-002 Variable cost (₹ thousand) = Variable cost
A62: CST-002 | B62: Input | C62: Variable cost (₹ thousand) | D62: variable_cost_k | E62: This month | F62: ='Plant Inputs'!Y9 -> 226098.2 | G62: ='Plant Inputs'!Y15 -> 308111 | H62: ='Plant Inputs'!Y21 -> 365860.2 | I62: ='Plant Inputs'!Y27 -> 266460.1 | J62: ='Plant Inputs'!Y33 -> 398678.1 | K62: ='Plant Inputs'!Y39 -> 262617.2 | L62: ='Entity Inputs'!W9 -> 900069.4 | M62: ='Entity Inputs'!W15 -> 927755.4 | N62: ='Group Inputs'!V9 -> 1827824.8 | O62: Sum of 3 plants → sum of 2 entities
A63: CST-002 | B63: KPI result | C63: Variable cost | E63: Month | F63: ='Plant KPIs'!K14 -> 226098.2 | G63: ='Plant KPIs'!Q14 -> 308111 | H63: ='Plant KPIs'!W14 -> 365860.2 | I63: ='Plant KPIs'!AC14 -> 266460.1 | J63: ='Plant KPIs'!AI14 -> 398678.1 | K63: ='Plant KPIs'!AO14 -> 262617.2 | L63: ='Entity KPIs'!K14 -> 900069.4 | M63: ='Entity KPIs'!Q14 -> 927755.4 | N63: ='Group KPIs'!K14 -> 1827824.8 | O63: Same formula applied at each level to that level's inputs
A65: CST-003 Fuel cost (₹ thousand) = Fuel cost
A66: CST-003 | B66: Input | C66: Fuel cost (₹ thousand) | D66: fuel_cost_k | E66: This month | F66: ='Plant Inputs'!Z9 -> 50616 | G66: ='Plant Inputs'!Z15 -> 70784.4 | H66: ='Plant Inputs'!Z21 -> 97272 | I66: ='Plant Inputs'!Z27 -> 82640.2 | J66: ='Plant Inputs'!Z33 -> 92193.9 | K66: ='Plant Inputs'!Z39 -> 65862.8 | L66: ='Entity Inputs'!X9 -> 218672.4 | M66: ='Entity Inputs'!X15 -> 240696.9 | N66: ='Group Inputs'!W9 -> 459369.3 | O66: Sum of 3 plants → sum of 2 entities
A67: CST-003 | B67: KPI result | C67: Fuel cost | E67: Month | F67: ='Plant KPIs'!K15 -> 50616 | G67: ='Plant KPIs'!Q15 -> 70784.4 | H67: ='Plant KPIs'!W15 -> 97272 | I67: ='Plant KPIs'!AC15 -> 82640.2 | J67: ='Plant KPIs'!AI15 -> 92193.9 | K67: ='Plant KPIs'!AO15 -> 65862.8 | L67: ='Entity KPIs'!K15 -> 218672.4 | M67: ='Entity KPIs'!Q15 -> 240696.9 | N67: ='Group KPIs'!K15 -> 459369.3 | O67: Same formula applied at each level to that level's inputs
A69: SUS-001 Water usage (m3) = Water used
A70: SUS-001 | B70: Input | C70: Water used (m³) | D70: water_m3 | E70: This month | F70: ='Plant Inputs'!AB9 -> 148807 | G70: ='Plant Inputs'!AB15 -> 245659 | H70: ='Plant Inputs'!AB21 -> 346844 | I70: ='Plant Inputs'!AB27 -> 178267 | J70: ='Plant Inputs'!AB33 -> 299945 | K70: ='Plant Inputs'!AB39 -> 230619 | L70: ='Entity Inputs'!Z9 -> 741310 | M70: ='Entity Inputs'!Z15 -> 708831 | N70: ='Group Inputs'!Y9 -> 1450141 | O70: Sum of 3 plants → sum of 2 entities
A71: SUS-001 | B71: KPI result | C71: Water usage | E71: Month | F71: ='Plant KPIs'!K16 -> 148807 | G71: ='Plant KPIs'!Q16 -> 245659 | H71: ='Plant KPIs'!W16 -> 346844 | I71: ='Plant KPIs'!AC16 -> 178267 | J71: ='Plant KPIs'!AI16 -> 299945 | K71: ='Plant KPIs'!AO16 -> 230619 | L71: ='Entity KPIs'!K16 -> 741310 | M71: ='Entity KPIs'!Q16 -> 708831 | N71: ='Group KPIs'!K16 -> 1450141 | O71: Same formula applied at each level to that level's inputs
A73: SUS-002 Emissions (tCO2e) = Emissions
A74: SUS-002 | B74: Input | C74: Emissions (t CO2e) | D74: emissions_tco2e | E74: This month | F74: ='Plant Inputs'!AC9 -> 59115 | G74: ='Plant Inputs'!AC15 -> 68824 | H74: ='Plant Inputs'!AC21 -> 91566 | I74: ='Plant Inputs'!AC27 -> 58385 | J74: ='Plant Inputs'!AC33 -> 86535 | K74: ='Plant Inputs'!AC39 -> 63239 | L74: ='Entity Inputs'!AA9 -> 219505 | M74: ='Entity Inputs'!AA15 -> 208159 | N74: ='Group Inputs'!Z9 -> 427664 | O74: Sum of 3 plants → sum of 2 entities
A75: SUS-002 | B75: KPI result | C75: Emissions | E75: Month | F75: ='Plant KPIs'!K17 -> 59115 | G75: ='Plant KPIs'!Q17 -> 68824 | H75: ='Plant KPIs'!W17 -> 91566 | I75: ='Plant KPIs'!AC17 -> 58385 | J75: ='Plant KPIs'!AI17 -> 86535 | K75: ='Plant KPIs'!AO17 -> 63239 | L75: ='Entity KPIs'!K17 -> 219505 | M75: ='Entity KPIs'!Q17 -> 208159 | N75: ='Group KPIs'!K17 -> 427664 | O75: Same formula applied at each level to that level's inputs
A77: SUS-003 Energy intensity (GJ/t) = Energy used ÷ Good output
A78: SUS-003 | B78: Input | C78: Energy used (GJ) | D78: energy_gj | E78: This month | F78: ='Plant Inputs'!AD9 -> 289576 | G78: ='Plant Inputs'!AD15 -> 358135 | H78: ='Plant Inputs'!AD21 -> 496742 | I78: ='Plant Inputs'!AD27 -> 283879 | J78: ='Plant Inputs'!AD33 -> 425107 | K78: ='Plant Inputs'!AD39 -> 287280 | L78: ='Entity Inputs'!AB9 -> 1144453 | M78: ='Entity Inputs'!AB15 -> 996266 | N78: ='Group Inputs'!AA9 -> 2140719 | O78: Sum of 3 plants → sum of 2 entities
A79: SUS-003 | B79: Input | C79: Good output (t) | D79: good_output_t | E79: This month | F79: ='Plant Inputs'!P9 -> 81854 | G79: ='Plant Inputs'!P15 -> 95233 | H79: ='Plant Inputs'!P21 -> 139711 | I79: ='Plant Inputs'!P27 -> 81694 | J79: ='Plant Inputs'!P33 -> 132787 | K79: ='Plant Inputs'!P39 -> 94388 | L79: ='Entity Inputs'!N9 -> 316798 | M79: ='Entity Inputs'!N15 -> 308869 | N79: ='Group Inputs'!M9 -> 625667 | O79: Sum of 3 plants → sum of 2 entities
A80: SUS-003 | B80: KPI result | C80: Energy intensity | E80: Month | F80: ='Plant KPIs'!K18 -> 3.54 | G80: ='Plant KPIs'!Q18 -> 3.76 | H80: ='Plant KPIs'!W18 -> 3.56 | I80: ='Plant KPIs'!AC18 -> 3.47 | J80: ='Plant KPIs'!AI18 -> 3.2 | K80: ='Plant KPIs'!AO18 -> 3.04 | L80: ='Entity KPIs'!K18 -> 3.61 | M80: ='Entity KPIs'!Q18 -> 3.23 | N80: ='Group KPIs'!K18 -> 3.42 | O80: Same formula applied at each level to that level's inputs
A82: SIG-007 Production at risk (t) = Production at risk
A83: SIG-007 | B83: Input | C83: Production at risk (t) | D83: production_at_risk_t | E83: This month | F83: ='Plant Inputs'!AE9 -> 3669 | G83: ='Plant Inputs'!AE15 -> 24322 | H83: ='Plant Inputs'!AE21 -> 2939 | I83: ='Plant Inputs'!AE27 -> 0 | J83: ='Plant Inputs'!AE33 -> 0 | K83: ='Plant Inputs'!AE39 -> 5880 | L83: ='Entity Inputs'!AC9 -> 30930 | M83: ='Entity Inputs'!AC15 -> 5880 | N83: ='Group Inputs'!AB9 -> 36810 | O83: Sum of 3 plants → sum of 2 entities
A84: SIG-007 | B84: KPI result | C84: Production at risk | E84: Month | F84: ='Plant KPIs'!K19 -> 3669 | G84: ='Plant KPIs'!Q19 -> 24322 | H84: ='Plant KPIs'!W19 -> 2939 | I84: ='Plant KPIs'!AC19 -> 0 | J84: ='Plant KPIs'!AI19 -> 0 | K84: ='Plant KPIs'!AO19 -> 5880 | L84: ='Entity KPIs'!K19 -> 30930 | M84: ='Entity KPIs'!Q19 -> 5880 | N84: ='Group KPIs'!K19 -> 36810 | O84: Same formula applied at each level to that level's inputs
A86: SIG-008 Critical plant-state alerts (count) = Critical plant alerts
A87: SIG-008 | B87: Input | C87: Critical plant alerts (count) | D87: critical_plant_alerts | E87: This month | F87: ='Plant Inputs'!AF9 -> 0 | G87: ='Plant Inputs'!AF15 -> 4 | H87: ='Plant Inputs'!AF21 -> 1 | I87: ='Plant Inputs'!AF27 -> 0 | J87: ='Plant Inputs'!AF33 -> 1 | K87: ='Plant Inputs'!AF39 -> 1 | L87: ='Entity Inputs'!AD9 -> 5 | M87: ='Entity Inputs'!AD15 -> 2 | N87: ='Group Inputs'!AC9 -> 7 | O87: Sum of 3 plants → sum of 2 entities
A88: SIG-008 | B88: KPI result | C88: Critical plant-state alerts | E88: Month | F88: ='Plant KPIs'!K20 -> 0 | G88: ='Plant KPIs'!Q20 -> 4 | H88: ='Plant KPIs'!W20 -> 1 | I88: ='Plant KPIs'!AC20 -> 0 | J88: ='Plant KPIs'!AI20 -> 1 | K88: ='Plant KPIs'!AO20 -> 1 | L88: ='Entity KPIs'!K20 -> 5 | M88: ='Entity KPIs'!Q20 -> 2 | N88: ='Group KPIs'!K20 -> 7 | O88: Same formula applied at each level to that level's inputs
A90: SIG-009 Critical-material shortage risk (count) = Critical materials at risk
A91: SIG-009 | B91: Input | C91: Critical materials at risk (count) | D91: critical_material_risks | E91: This month | F91: ='Plant Inputs'!AR9 -> 2 | G91: ='Plant Inputs'!AR15 -> 1 | H91: ='Plant Inputs'!AR21 -> 1 | I91: ='Plant Inputs'!AR27 -> 0 | J91: ='Plant Inputs'!AR33 -> 0 | K91: ='Plant Inputs'!AR39 -> 1 | L91: ='Entity Inputs'!AP9 -> 4 | M91: ='Entity Inputs'!AP15 -> 1 | N91: ='Group Inputs'!AO9 -> 5 | O91: Sum of 3 plants → sum of 2 entities
A92: SIG-009 | B92: KPI result | C92: Critical-material shortage risk | E92: Month | F92: ='Plant KPIs'!K21 -> 2 | G92: ='Plant KPIs'!Q21 -> 1 | H92: ='Plant KPIs'!W21 -> 1 | I92: ='Plant KPIs'!AC21 -> 0 | J92: ='Plant KPIs'!AI21 -> 0 | K92: ='Plant KPIs'!AO21 -> 1 | L92: ='Entity KPIs'!K21 -> 4 | M92: ='Entity KPIs'!Q21 -> 1 | N92: ='Group KPIs'!K21 -> 5 | O92: Same formula applied at each level to that level's inputs
A94: SIG-012 Dispatch delays (%) = Delayed dispatches ÷ Dispatches × 100
A95: SIG-012 | B95: Input | C95: Delayed dispatches (count) | D95: dispatches_delayed | E95: This month | F95: ='Plant Inputs'!AT9 -> 9 | G95: ='Plant Inputs'!AT15 -> 36 | H95: ='Plant Inputs'!AT21 -> 16 | I95: ='Plant Inputs'!AT27 -> 12 | J95: ='Plant Inputs'!AT33 -> 15 | K95: ='Plant Inputs'!AT39 -> 3 | L95: ='Entity Inputs'!AR9 -> 61 | M95: ='Entity Inputs'!AR15 -> 30 | N95: ='Group Inputs'!AQ9 -> 91 | O95: Sum of 3 plants → sum of 2 entities
A96: SIG-012 | B96: Input | C96: Dispatches (count) | D96: dispatches_total | E96: This month | F96: ='Plant Inputs'!AS9 -> 120 | G96: ='Plant Inputs'!AS15 -> 225 | H96: ='Plant Inputs'!AS21 -> 214 | I96: ='Plant Inputs'!AS27 -> 169 | J96: ='Plant Inputs'!AS33 -> 198 | K96: ='Plant Inputs'!AS39 -> 125 | L96: ='Entity Inputs'!AQ9 -> 559 | M96: ='Entity Inputs'!AQ15 -> 492 | N96: ='Group Inputs'!AP9 -> 1051 | O96: Sum of 3 plants → sum of 2 entities
A97: SIG-012 | B97: KPI result | C97: Dispatch delays | E97: Month | F97: ='Plant KPIs'!K22 -> 7.5 | G97: ='Plant KPIs'!Q22 -> 16 | H97: ='Plant KPIs'!W22 -> 7.48 | I97: ='Plant KPIs'!AC22 -> 7.1 | J97: ='Plant KPIs'!AI22 -> 7.58 | K97: ='Plant KPIs'!AO22 -> 2.4 | L97: ='Entity KPIs'!K22 -> 10.91 | M97: ='Entity KPIs'!Q22 -> 6.1 | N97: ='Group KPIs'!K22 -> 8.66 | O97: Same formula applied at each level to that level's inputs
A99: SIG-021 Environmental violations (count) = Environmental violations
A100: SIG-021 | B100: Input | C100: Environmental violations (count) | D100: env_violations | E100: This month | F100: ='Plant Inputs'!AM9 -> 0 | G100: ='Plant Inputs'!AM15 -> 0 | H100: ='Plant Inputs'!AM21 -> 0 | I100: ='Plant Inputs'!AM27 -> 0 | J100: ='Plant Inputs'!AM33 -> 0 | K100: ='Plant Inputs'!AM39 -> 0 | L100: ='Entity Inputs'!AK9 -> 0 | M100: ='Entity Inputs'!AK15 -> 0 | N100: ='Group Inputs'!AJ9 -> 0 | O100: Sum of 3 plants → sum of 2 entities
A101: SIG-021 | B101: KPI result | C101: Environmental violations | E101: Month | F101: ='Plant KPIs'!K23 -> 0 | G101: ='Plant KPIs'!Q23 -> 0 | H101: ='Plant KPIs'!W23 -> 0 | I101: ='Plant KPIs'!AC23 -> 0 | J101: ='Plant KPIs'!AI23 -> 0 | K101: ='Plant KPIs'!AO23 -> 0 | L101: ='Entity KPIs'!K23 -> 0 | M101: ='Entity KPIs'!Q23 -> 0 | N101: ='Group KPIs'!K23 -> 0 | O101: Same formula applied at each level to that level's inputs
A103: EHS-001 TRIR (per 200,000 h) = Recordable injuries × 200,000 ÷ Hours worked
A104: EHS-001 | B104: Input | C104: Recordable injuries (count) | D104: recordable_injuries | E104: This month | F104: ='Plant Inputs'!AH9 -> 0 | G104: ='Plant Inputs'!AH15 -> 0 | H104: ='Plant Inputs'!AH21 -> 1 | I104: ='Plant Inputs'!AH27 -> 0 | J104: ='Plant Inputs'!AH33 -> 0 | K104: ='Plant Inputs'!AH39 -> 0 | L104: ='Entity Inputs'!AF9 -> 1 | M104: ='Entity Inputs'!AF15 -> 0 | N104: ='Group Inputs'!AE9 -> 1 | O104: Sum of 3 plants → sum of 2 entities
A105: EHS-001 | B105: Input | C105: Hours worked (h) | D105: hours_worked | E105: This month | F105: ='Plant Inputs'!AG9 -> 55000 | G105: ='Plant Inputs'!AG15 -> 95000 | H105: ='Plant Inputs'!AG21 -> 69000 | I105: ='Plant Inputs'!AG27 -> 57000 | J105: ='Plant Inputs'!AG33 -> 60000 | K105: ='Plant Inputs'!AG39 -> 89000 | L105: ='Entity Inputs'!AE9 -> 219000 | M105: ='Entity Inputs'!AE15 -> 206000 | N105: ='Group Inputs'!AD9 -> 425000 | O105: Sum of 3 plants → sum of 2 entities
A106: EHS-001 | B106: KPI result | C106: TRIR | E106: Month | F106: ='Plant KPIs'!K24 -> 0 | G106: ='Plant KPIs'!Q24 -> 0 | H106: ='Plant KPIs'!W24 -> 2.9 | I106: ='Plant KPIs'!AC24 -> 0 | J106: ='Plant KPIs'!AI24 -> 0 | K106: ='Plant KPIs'!AO24 -> 0 | L106: ='Entity KPIs'!K24 -> 0.91 | M106: ='Entity KPIs'!Q24 -> 0 | N106: ='Group KPIs'!K24 -> 0.47 | O106: Same formula applied at each level to that level's inputs
A108: EHS-002 Severity incidents (count) = Severity incidents
A109: EHS-002 | B109: Input | C109: Severity incidents (count) | D109: severity_incidents | E109: This month | F109: ='Plant Inputs'!AI9 -> 1 | G109: ='Plant Inputs'!AI15 -> 0 | H109: ='Plant Inputs'!AI21 -> 0 | I109: ='Plant Inputs'!AI27 -> 0 | J109: ='Plant Inputs'!AI33 -> 1 | K109: ='Plant Inputs'!AI39 -> 1 | L109: ='Entity Inputs'!AG9 -> 1 | M109: ='Entity Inputs'!AG15 -> 2 | N109: ='Group Inputs'!AF9 -> 3 | O109: Sum of 3 plants → sum of 2 entities
A110: EHS-002 | B110: KPI result | C110: Severity incidents | E110: Month | F110: ='Plant KPIs'!K25 -> 1 | G110: ='Plant KPIs'!Q25 -> 0 | H110: ='Plant KPIs'!W25 -> 0 | I110: ='Plant KPIs'!AC25 -> 0 | J110: ='Plant KPIs'!AI25 -> 1 | K110: ='Plant KPIs'!AO25 -> 1 | L110: ='Entity KPIs'!K25 -> 1 | M110: ='Entity KPIs'!Q25 -> 2 | N110: ='Group KPIs'!K25 -> 3 | O110: Same formula applied at each level to that level's inputs
A112: EHS-003 Near misses (count) = Near misses
A113: EHS-003 | B113: Input | C113: Near misses (count) | D113: near_misses | E113: This month | F113: ='Plant Inputs'!AJ9 -> 9 | G113: ='Plant Inputs'!AJ15 -> 2 | H113: ='Plant Inputs'!AJ21 -> 9 | I113: ='Plant Inputs'!AJ27 -> 3 | J113: ='Plant Inputs'!AJ33 -> 9 | K113: ='Plant Inputs'!AJ39 -> 9 | L113: ='Entity Inputs'!AH9 -> 20 | M113: ='Entity Inputs'!AH15 -> 21 | N113: ='Group Inputs'!AG9 -> 41 | O113: Sum of 3 plants → sum of 2 entities
A114: EHS-003 | B114: KPI result | C114: Near misses | E114: Month | F114: ='Plant KPIs'!K26 -> 9 | G114: ='Plant KPIs'!Q26 -> 2 | H114: ='Plant KPIs'!W26 -> 9 | I114: ='Plant KPIs'!AC26 -> 3 | J114: ='Plant KPIs'!AI26 -> 9 | K114: ='Plant KPIs'!AO26 -> 9 | L114: ='Entity KPIs'!K26 -> 20 | M114: ='Entity KPIs'!Q26 -> 21 | N114: ='Group KPIs'!K26 -> 41 | O114: Same formula applied at each level to that level's inputs
A116: EHS-004 Critical safety incidents (count) = Critical safety incidents
A117: EHS-004 | B117: Input | C117: Critical safety incidents (count) | D117: critical_safety_incidents | E117: This month | F117: ='Plant Inputs'!AK9 -> 0 | G117: ='Plant Inputs'!AK15 -> 0 | H117: ='Plant Inputs'!AK21 -> 0 | I117: ='Plant Inputs'!AK27 -> 0 | J117: ='Plant Inputs'!AK33 -> 0 | K117: ='Plant Inputs'!AK39 -> 0 | L117: ='Entity Inputs'!AI9 -> 0 | M117: ='Entity Inputs'!AI15 -> 0 | N117: ='Group Inputs'!AH9 -> 0 | O117: Sum of 3 plants → sum of 2 entities
A118: EHS-004 | B118: KPI result | C118: Critical safety incidents | E118: Month | F118: ='Plant KPIs'!K27 -> 0 | G118: ='Plant KPIs'!Q27 -> 0 | H118: ='Plant KPIs'!W27 -> 0 | I118: ='Plant KPIs'!AC27 -> 0 | J118: ='Plant KPIs'!AI27 -> 0 | K118: ='Plant KPIs'!AO27 -> 0 | L118: ='Entity KPIs'!K27 -> 0 | M118: ='Entity KPIs'!Q27 -> 0 | N118: ='Group KPIs'!K27 -> 0 | O118: Same formula applied at each level to that level's inputs
A120: EHS-005 Environmental excursions (count) = Environmental excursions
A121: EHS-005 | B121: Input | C121: Environmental excursions (count) | D121: env_excursions | E121: This month | F121: ='Plant Inputs'!AL9 -> 0 | G121: ='Plant Inputs'!AL15 -> 1 | H121: ='Plant Inputs'!AL21 -> 0 | I121: ='Plant Inputs'!AL27 -> 1 | J121: ='Plant Inputs'!AL33 -> 0 | K121: ='Plant Inputs'!AL39 -> 0 | L121: ='Entity Inputs'!AJ9 -> 1 | M121: ='Entity Inputs'!AJ15 -> 1 | N121: ='Group Inputs'!AI9 -> 2 | O121: Sum of 3 plants → sum of 2 entities
A122: EHS-005 | B122: KPI result | C122: Environmental excursions | E122: Month | F122: ='Plant KPIs'!K28 -> 0 | G122: ='Plant KPIs'!Q28 -> 1 | H122: ='Plant KPIs'!W28 -> 0 | I122: ='Plant KPIs'!AC28 -> 1 | J122: ='Plant KPIs'!AI28 -> 0 | K122: ='Plant KPIs'!AO28 -> 0 | L122: ='Entity KPIs'!K28 -> 1 | M122: ='Entity KPIs'!Q28 -> 1 | N122: ='Group KPIs'!K28 -> 2 | O122: Same formula applied at each level to that level's inputs
A124: EHS-006 Open EHS corrective actions (count) = Open EHS corrective actions
A125: EHS-006 | B125: Input | C125: Open EHS corrective actions (count) | D125: ehs_ca_open | E125: This month | F125: ='Plant Inputs'!AN9 -> 14 | G125: ='Plant Inputs'!AN15 -> 6 | H125: ='Plant Inputs'!AN21 -> 8 | I125: ='Plant Inputs'!AN27 -> 6 | J125: ='Plant Inputs'!AN33 -> 6 | K125: ='Plant Inputs'!AN39 -> 5 | L125: ='Entity Inputs'!AL9 -> 28 | M125: ='Entity Inputs'!AL15 -> 17 | N125: ='Group Inputs'!AK9 -> 45 | O125: Sum of 3 plants → sum of 2 entities
A126: EHS-006 | B126: KPI result | C126: Open EHS corrective actions | E126: Month | F126: ='Plant KPIs'!K29 -> 14 | G126: ='Plant KPIs'!Q29 -> 6 | H126: ='Plant KPIs'!W29 -> 8 | I126: ='Plant KPIs'!AC29 -> 6 | J126: ='Plant KPIs'!AI29 -> 6 | K126: ='Plant KPIs'!AO29 -> 5 | L126: ='Entity KPIs'!K29 -> 28 | M126: ='Entity KPIs'!Q29 -> 17 | N126: ='Group KPIs'!K29 -> 45 | O126: Same formula applied at each level to that level's inputs
A128: EHS-007 Overdue EHS actions (count) = Overdue EHS corrective actions
...

Sheet Screen Values
A1: Lens | B1: Screen | C1: Screen title | D1: Element | E1: Label on the screen | F1: KPI ID | G1: Scope | H1: Shown on the screen | I1: Calculated, Sep 2026 (P06) | J1: Same or different
A2: Owner | B2: G-08 · Owner depth | C2: Trust Summary (Owner depth) | D2: Card | E2: Leadership KPIs affected by findings | F2: GOV-007 | G2: Group | H2: 1 | I2: ='Group KPIs'!K119 -> 1 | J2: Same
A3: Owner | B3: G-08 · Owner depth | C3: Trust Summary (Owner depth) | D3: Card | E3: Certified KPI percentage | F3: TRU-001 | G3: Group | H3: 84 % of leadership KPIs | I3: ='Group KPIs'!K125 -> 83.93 | J3: Same
A4: Owner | B4: G-08 · Owner depth | C4: Trust Summary (Owner depth) | D4: Card | E4: Uncertified KPI count | F4: TRU-002 | G4: Group | H4: 9 | I4: ='Group KPIs'!K126 -> 9 | J4: Same
A5: Owner | B5: G-08 · Owner depth | C5: Trust Summary (Owner depth) | D5: Card | E5: Material reconciliation breaks | F5: TRU-007 | G5: Group | H5: 1 | I5: ='Group KPIs'!K122 -> 1 | J5: Same
A6: Owner | B6: G-08 · Owner depth | C6: Trust Summary (Owner depth) | D6: Card | E6: Flash-to-Close variance (P06) | F6: TRU-010 | G6: Group | H6: 0.6 % | I6: ='Group KPIs'!K130 -> 0.38 | J6: Different
A7: Owner | B7: G-08 · Owner depth | C7: Trust Summary (Owner depth) | D7: Card | E7: Variance against Board numbers | F7: TRU-011 | G7: Group | H7: 0.3 % (max abs) | I7: ='Group KPIs'!K132 -> 0.27 | J7: Same
A8: Owner | B8: G-08 · Owner depth | C8: Trust Summary (Owner depth) | D8: Table | E8: Ageing certification approvals | F8: GOV-001 | G8: Group | H8: 2 > [PH] d | I8: ='Group KPIs'!K113 -> 2 | J8: Same
A9: Owner | B9: G-08 · Owner depth | C9: Trust Summary (Owner depth) | D9: Table | E9: Override count (KPI) | F9: GOV-002 | G9: Group | H9: 0 | I9: ='Group KPIs'!K114 -> 0 | J9: Same
A10: Owner | B10: G-08 · Owner depth | C10: Trust Summary (Owner depth) | D10: Table | E10: Recurring data-quality issues | F10: GOV-003 | G10: Group | H10: 1 | I10: ='Group KPIs'!K115 -> 1 | J10: Same
A11: Owner | B11: G-08 · Owner depth | C11: Trust Summary (Owner depth) | D11: Table | E11: Open audit findings | F11: GOV-004 | G11: Group | H11: 7 | I11: ='Group KPIs'!K116 -> 7 | J11: Same
A12: Owner | B12: G-08 · Owner depth | C12: Trust Summary (Owner depth) | D12: Table | E12: Overdue assurance actions | F12: GOV-005 | G12: Group | H12: 0 | I12: ='Group KPIs'!K117 -> 0 | J12: Same
A13: Owner | B13: G-08 · Owner depth | C13: Trust Summary (Owner depth) | D13: Table | E13: Repeat findings | F13: GOV-006 | G13: Group | H13: 1 | I13: ='Group KPIs'!K118 -> 1 | J13: Same
A14: Owner | B14: G-08 · Owner depth | C14: Trust Summary (Owner depth) | D14: Table | E14: Leadership KPIs affected by findings | F14: GOV-007 | G14: Group | H14: 1 | I14: ='Group KPIs'!K119 -> 1 | J14: Same
A15: Owner | B15: G-08 · Owner depth | C15: Trust Summary (Owner depth) | D15: Table | E15: Evidence completeness rate | F15: GOV-008 | G15: Group | H15: 88% | I15: ='Group KPIs'!K123 -> 87.96 | J15: Same
A16: Owner | B16: G-08 · Owner depth | C16: Trust Summary (Owner depth) | D16: Table | E16: Average finding-closure time | F16: GOV-009 | G16: Group | H16: 34 d | I16: ='Group KPIs'!K124 -> 32.81 | J16: Different
A17: Owner | B17: G-08 · Owner depth | C17: Trust Summary (Owner depth) | D17: Table | E17: KPI certification coverage | F17: TRU-001 | G17: Group | H17: 84 % of leadership KPIs | I17: ='Group KPIs'!K125 -> 83.93 | J17: Same
A18: Owner | B18: G-08 · Owner depth | C18: Trust Summary (Owner depth) | D18: Table | E18: Source-to-Lake reconciliation rate | F18: TRU-008 | G18: Group | H18: 99.2% | I18: ='Group KPIs'!K128 -> 99.02 | J18: Different
A19: Owner | B19: G-08 · Owner depth | C19: Trust Summary (Owner depth) | D19: Table | E19: Flash-to-MIS reconciliation rate | F19: TRU-009 | G19: Group | H19: 96.8% | I19: ='Group KPIs'!K129 -> 95.98 | J19: Different
A20: Owner | B20: G-08 · Owner depth | C20: Trust Summary (Owner depth) | D20: Table | E20: Flash-to-Close variance (P06) | F20: TRU-010 | G20: Group | H20: 0.6 % | I20: ='Group KPIs'!K130 -> 0.38 | J20: Different
A21: Owner | B21: G-08 · Owner depth | C21: Trust Summary (Owner depth) | D21: Table | E21: Variance against Board numbers | F21: TRU-011 | G21: Group | H21: 0.3% max abs · Entity B2 | I21: ='Group KPIs'!K132 -> 0.27 | J21: Same
A22: Owner | B22: O-01 | C22: Enterprise Health | D22: Card | E22: Capex physical progress | F22: CPX-004 | G22: Group | H22: 61 % weighted | I22: ='Group KPIs'!K69 -> 60.85 | J22: Same
A23: Owner | B23: O-01 | C23: Enterprise Health | D23: Card | E23: Open critical alerts | F23: EFF-002 | G23: Group | H23: 1 alert | I23: ='Group KPIs'!K133 -> 1 | J23: Same
A24: Owner | B24: O-01 | C24: Enterprise Health | D24: Card | E24: EBITDA YTD (to P06) | F24: FIN-001 | G24: Group | H24: 361.3 ₹ m | I24: ='Group KPIs'!K38 -> 1760.09 | J24: Different
A25: Owner | B25: O-01 | C25: Enterprise Health | D25: Card | E25: EBIT YTD (to P06) | F25: FIN-002 | G25: Group | H25: 238.4 ₹ m | I25: ='Group KPIs'!K39 -> 1228.14 | J25: Different
A26: Owner | B26: O-01 | C26: Enterprise Health | D26: Card | E26: Free Cash Flow YTD | F26: FIN-004 | G26: Group | H26: 96.4 ₹ m | I26: ='Group KPIs'!K41 -> 606.18 | J26: Different
A27: Owner | B27: O-01 | C27: Enterprise Health | D27: Card | E27: ROCE · rolling 12 m | F27: FIN-005 | G27: Group | H27: 11.8 % | I27: ='Group KPIs'!K42 -> 11.58 | J27: Different
A28: Owner | B28: O-01 | C28: Enterprise Health | D28: Card | E28: Net Debt | F28: FIN-006 | G28: Group | H28: 1,140 ₹ m | I28: ='Group KPIs'!K43 -> 6650 | J28: Different
A29: Owner | B29: O-01 | C29: Enterprise Health | D29: Card | E29: Production vs plan · Group MTD | F29: OPS-001 | G29: Group | H29: 98.1 % of plan | I29: ='Group KPIs'!K2 -> 95.51 | J29: Different
A30: Owner | B30: O-01 | C30: Enterprise Health | D30: Tile | E30: Days to breach · Plant 02 plan | F30: PRD-001 | G30: Plant 02 | H30: 4 days | I30: ='Plant KPIs'!Q59 -> 4 | J30: Same
A31: Owner | B31: O-01 | C31: Enterprise Health | D31: Tile | E31: Probability of plan miss · P07 | F31: PRD-002 | G31: Group | H31: 64% | I31: ='Group KPIs'!K145 -> 69.69 | J31: Different
A32: Owner | B32: O-01 | C32: Enterprise Health | D32: Tile | E32: Projected EBITDA gap · P07–P12 | F32: PRD-003 | G32: Group | H32: −₹9.2 m | I32: ='Group KPIs'!K146 -> -56.18 | J32: Different
A33: Owner | B33: O-01 | C33: Enterprise Health | D33: Table | E33: Regulatory breaches · YTD | F33: CMP-005 | G33: Group | H33: 0 | I33: ='Group KPIs'!K101 -> 0 | J33: Same
A34: Owner | B34: O-01 | C34: Enterprise Health | D34: Table | E34: EBIT YTD | F34: FIN-002 | G34: Group | H34: 238.4 ₹ m | I34: ='Group KPIs'!K39 -> 1228.14 | J34: Different
A35: Owner | B35: O-01 | C35: Enterprise Health | D35: Table | E35: Revenue YTD | F35: FIN-003 | G35: Group | H35: 2,410 ₹ m | I35: ='Group KPIs'!K40 -> 13811.3 | J35: Different
A36: Owner | B36: O-01 | C36: Enterprise Health | D36: Table | E36: ROCE (rolling 12 m) | F36: FIN-005 | G36: Group | H36: 11.8% | I36: ='Group KPIs'!K42 -> 11.58 | J36: Different
A37: Owner | B37: O-01 | C37: Enterprise Health | D37: Table | E37: Shareholder-value indicator | F37: FIN-007 | G37: Group | H37: [PLACEHOLDER] | I37: ='Group KPIs'!K44 -> -86.65 | J37: Different
A38: Owner | B38: O-01 | C38: Enterprise Health | D38: Table | E38: Sales vs plan · MTD | F38: OPS-002 | G38: Group | H38: 97.6% | I38: ='Group KPIs'!K35 -> 95.23 | J38: Different
A39: Owner | B39: O-01 | C39: Enterprise Health | D39: Table | E39: Capacity utilization | F39: OPS-003 | G39: Group | H39: 86% | I39: ='Group KPIs'!K3 -> 83.44 | J39: Different
A40: Owner | B40: O-01 | C40: Enterprise Health | D40: Table | E40: Sales vs plan · Group MTD | F40: OPS-004 | G40: Group | H40: 97.6% | I40: ='Group KPIs'!K36 -> 95.23 | J40: Different
A41: Owner | B41: O-01 | C41: Enterprise Health | D41: Table | E41: Capacity utilisation | F41: OPS-005 | G41: Group | H41: 86% | I41: ='Group KPIs'!K33 -> 83.44 | J41: Different
A42: Owner | B42: O-01 | C42: Enterprise Health | D42: Table | E42: Transformation progress (weighted) | F42: PRG-004 | G42: Group | H42: 54% | I42: ='Group KPIs'!K74 -> 54.03 | J42: Same
A43: Owner | B43: O-01 | C43: Enterprise Health | D43: Table | E43: Regulatory breaches · YTD | F43: RSK-003 | G43: Group | H43: 0 | I43: ='Group KPIs'!K100 -> 0 | J43: Same
A44: Owner | B44: O-01 | C44: Enterprise Health | D44: Table | E44: Transformation progress | F44: STR-002 | G44: Group | H44: 54% | I44: ='Group KPIs'!K75 -> 54.03 | J44: Same
A45: Owner | B45: O-01 · large display ≥ 1600 | C45: Enterprise Health | D45: Card | E45: Capex physical progress | F45: CPX-004 | G45: Group | H45: 61 % weighted | I45: ='Group KPIs'!K69 -> 60.85 | J45: Same
A46: Owner | B46: O-01 · large display ≥ 1600 | C46: Enterprise Health | D46: Card | E46: Open critical alerts | F46: EFF-002 | G46: Group | H46: 1 alert | I46: ='Group KPIs'!K133 -> 1 | J46: Same
A47: Owner | B47: O-01 · large display ≥ 1600 | C47: Enterprise Health | D47: Card | E47: EBITDA YTD (to P06) | F47: FIN-001 | G47: Group | H47: 361.3 ₹ m | I47: ='Group KPIs'!K38 -> 1760.09 | J47: Different
A48: Owner | B48: O-01 · large display ≥ 1600 | C48: Enterprise Health | D48: Card | E48: Free Cash Flow YTD | F48: FIN-004 | G48: Group | H48: 96.4 ₹ m | I48: ='Group KPIs'!K41 -> 606.18 | J48: Different
A49: Owner | B49: O-01 · large display ≥ 1600 | C49: Enterprise Health | D49: Card | E49: Net Debt | F49: FIN-006 | G49: Group | H49: 1,140 ₹ m | I49: ='Group KPIs'!K43 -> 6650 | J49: Different
A50: Owner | B50: O-01 · large display ≥ 1600 | C50: Enterprise Health | D50: Card | E50: Production vs plan · Group MTD | F50: OPS-001 | G50: Group | H50: 98.1 % of plan | I50: ='Group KPIs'!K2 -> 95.51 | J50: Different
A51: Owner | B51: O-01 · large display ≥ 1600 | C51: Enterprise Health | D51: Tile | E51: Days to breach · Plant 02 plan | F51: PRD-001 | G51: Plant 02 | H51: 4 days | I51: ='Plant KPIs'!Q59 -> 4 | J51: Same
A52: Owner | B52: O-01 · large display ≥ 1600 | C52: Enterprise Health | D52: Tile | E52: Probability of plan miss · P07 | F52: PRD-002 | G52: Group | H52: 64% | I52: ='Group KPIs'!K145 -> 69.69 | J52: Different
A53: Owner | B53: O-01 · large display ≥ 1600 | C53: Enterprise Health | D53: Tile | E53: Projected EBITDA gap · P07–P12 | F53: PRD-003 | G53: Group | H53: −₹9.2 m | I53: ='Group KPIs'!K146 -> -56.18 | J53: Different
A54: Owner | B54: O-01 · large display ≥ 1600 | C54: Enterprise Health | D54: Table | E54: EBIT YTD | F54: FIN-002 | G54: Group | H54: 238.4 ₹ m | I54: ='Group KPIs'!K39 -> 1228.14 | J54: Different
A55: Owner | B55: O-01 · large display ≥ 1600 | C55: Enterprise Health | D55: Table | E55: Revenue YTD | F55: FIN-003 | G55: Group | H55: 2,410 ₹ m | I55: ='Group KPIs'!K40 -> 13811.3 | J55: Different
A56: Owner | B56: O-01 · large display ≥ 1600 | C56: Enterprise Health | D56: Table | E56: ROCE (rolling 12 m) | F56: FIN-005 | G56: Group | H56: 11.8% | I56: ='Group KPIs'!K42 -> 11.58 | J56: Different
A57: Owner | B57: O-01 · large display ≥ 1600 | C57: Enterprise Health | D57: Table | E57: Shareholder-value indicator | F57: FIN-007 | G57: Group | H57: [PLACEHOLDER] | I57: ='Group KPIs'!K44 -> -86.65 | J57: Different
A58: Owner | B58: O-01 · large display ≥ 1600 | C58: Enterprise Health | D58: Table | E58: Sales vs plan · MTD | F58: OPS-002 | G58: Group | H58: 97.6% | I58: ='Group KPIs'!K35 -> 95.23 | J58: Different
A59: Owner | B59: O-01 · large display ≥ 1600 | C59: Enterprise Health | D59: Table | E59: Capacity utilization | F59: OPS-003 | G59: Group | H59: 86% | I59: ='Group KPIs'!K3 -> 83.44 | J59: Different
A60: Owner | B60: O-01 · large display ≥ 1600 | C60: Enterprise Health | D60: Table | E60: Regulatory breaches · YTD | F60: RSK-003 | G60: Group | H60: 0 | I60: ='Group KPIs'!K100 -> 0 | J60: Same
A61: Owner | B61: O-01 · large display ≥ 1600 | C61: Enterprise Health | D61: Table | E61: Transformation progress | F61: STR-002 | G61: Group | H61: 54% | I61: ='Group KPIs'!K75 -> 54.03 | J61: Same
A62: Owner | B62: O-02 | C62: 24-Hour Executive Change Report | D62: Tile | E62: Days to breach · Plant 02 plan | F62: PRD-001 | G62: Plant 02 | H62: 4 days | I62: ='Plant KPIs'!Q59 -> 4 | J62: Same
A63: Owner | B63: O-02 | C63: 24-Hour Executive Change Report | D63: Tile | E63: Probability of plan miss · P07 | F63: PRD-002 | G63: Group | H63: 64% | I63: ='Group KPIs'!K145 -> 69.69 | J63: Different
A64: Owner | B64: O-02 | C64: 24-Hour Executive Change Report | D64: Tile | E64: Projected EBITDA gap P07–P12 | F64: PRD-003 | G64: Group | H64: −₹9.2 m | I64: ='Group KPIs'!K146 -> -56.18 | J64: Different
A65: Owner | B65: O-02 | C65: 24-Hour Executive Change Report | D65: Tile | E65: Projected liquidity gap | F65: PRD-004 | G65: Group | H65: None | I65: ='Group KPIs'!K147 -> None within 90 d | J65: Same
A66: Owner | B66: O-02 | C66: 24-Hour Executive Change Report | D66: Tile | E66: Forecast covenant breach | F66: PRD-005 | G66: Group | H66: Not forecast | I66: ='Group KPIs'!K148 -> Not forecast | J66: Same
A67: Owner | B67: O-03 | C67: Cash and Liquidity Summary | D67: Card | E67: Cash position | F67: CSH-001 | G67: Group | H67: 384 ₹ m | I67: ='Group KPIs'!K46 -> 2141.82 | J67: Different
A68: Owner | B68: O-03 | C68: Cash and Liquidity Summary | D68: Card | E68: Cash-upstream exposure | F68: CSH-006 | G68: Group | H68: 26 ₹ m | I68: ='Group KPIs'!K50 -> 27.21 | J68: Different
A69: Owner | B69: O-03 | C69: Cash and Liquidity Summary | D69: Card | E69: Free Cash Flow YTD | F69: FIN-004 | G69: Group | H69: 96.4 ₹ m | I69: ='Group KPIs'!K41 -> 606.18 | J69: Different
A70: Owner | B70: O-03 | C70: Cash and Liquidity Summary | D70: Card | E70: Liquidity runway | F70: LIQ-001 | G70: Group | H70: 14.2 months | I70: ='Group KPIs'!K57 -> 16.71 | J70: Different
A71: Owner | B71: O-03 | C71: Cash and Liquidity Summary | D71: Card | E71: Covenant headroom | F71: LIQ-002 | G71: Group | H71: 22 % [TERMS — PH] | I71: ='Group KPIs'!K58 -> 24.44 | J71: Different
A72: Owner | B72: O-03 | C72: Cash and Liquidity Summary | D72: Card | E72: Net working capital | F72: WCP-004 | G72: Group | H72: 512 ₹ m | I72: ='Group KPIs'!K54 -> 2780.99 | J72: Different
A73: Owner | B73: O-03 | C73: Cash and Liquidity Summary | D73: Tile | E73: Projected liquidity gap | F73: PRD-004 | G73: Group | H73: None within 90 d | I73: ='Group KPIs'!K147 -> None within 90 d | J73: Same
A74: Owner | B74: O-03 | C74: Cash and Liquidity Summary | D74: Tile | E74: Forecast covenant breach | F74: PRD-005 | G74: Group | H74: Not forecast | I74: ='Group KPIs'!K148 -> Not forecast | J74: Same
A75: Owner | B75: O-03 | C75: Cash and Liquidity Summary | D75: Tile | E75: Collections slippage | F75: SIG-004 | G75: Group | H75: +2 d (A1) | I75: ='Group KPIs'!K140 -> 1.12 | J75: Different
A76: Owner | B76: O-03 | C76: Cash and Liquidity Summary | D76: Table | E76: Cash released · YTD | F76: CSH-002 | G76: Group | H76: ₹21 m | I76: ='Group KPIs'!K47 -> 22.03 | J76: Different
A77: Owner | B77: O-03 | C77: Cash and Liquidity Summary | D77: Table | E77: Daily collections (Group) | F77: CSH-003 | G77: Group | H77: ₹18.6 m | I77: ='Group KPIs'!K48 -> 76.77 | J77: Different
A78: Owner | B78: O-03 | C78: Cash and Liquidity Summary | D78: Table | E78: Cash-conversion cycle | F78: CSH-004 | G78: Group | H78: 33 d | I78: ='Group KPIs'!K49 -> 32.59 | J78: Same
A79: Owner | B79: O-03 | C79: Cash and Liquidity Summary | D79: Table | E79: Net Debt | F79: FIN-006 | G79: Group | H79: 1,140 ₹ m | I79: ='Group KPIs'!K43 -> 6650 | J79: Different
A80: Owner | B80: O-03 | C80: Cash and Liquidity Summary | D80: Table | E80: Debt-maturity exposure · next 12 m | F80: LIQ-003 | G80: Group | H80: ₹120 m | I80: ='Group KPIs'!K59 -> 891.41 | J80: Different
A81: Owner | B81: O-03 | C81: Cash and Liquidity Summary | D81: Table | E81: Financing exposure | F81: LIQ-004 | G81: Group | H81: ₹310 m | I81: ='Group KPIs'!K60 -> 2720.83 | J81: Different
A82: Owner | B82: O-03 | C82: Cash and Liquidity Summary | D82: Table | E82: Cash burn (leading) | F82: SIG-006 | G82: Group | H82: Not triggered | I82: ='Group KPIs'!K142 -> Not triggered | J82: Same
A83: Owner | B83: O-03 | C83: Cash and Liquidity Summary | D83: Table | E83: FX exposure (unhedged) | F83: TRS-001 | G83: Group | H83: ₹64 m | I83: ='Group KPIs'!K61 -> 221.72 | J83: Different
A84: Owner | B84: O-03 | C84: Cash and Liquidity Summary | D84: Table | E84: Hedging effectiveness | F84: TRS-002 | G84: Group | H84: 91% | I84: ='Group KPIs'!K62 -> 91.7 | J84: Different
A85: Owner | B85: O-03 | C85: Cash and Liquidity Summary | D85: Table | E85: FX exposure by currency (USD share) | F85: TRS-003 | G85: Group | H85: 72% of unhedged | I85: ='Group KPIs'!K63 -> 75.83 | J85: Different
A86: Owner | B86: O-03 | C86: Cash and Liquidity Summary | D86: Table | E86: Hedge cover · next 6 m | F86: TRS-004 | G86: Group | H86: 68% | I86: ='Group KPIs'!K64 -> 70.65 | J86: Different
A87: Owner | B87: O-03 | C87: Cash and Liquidity Summary | D87: Table | E87: FX sensitivity · 5% USD move | F87: TRS-005 | G87: Group | H87: ₹3.2 m EBITDA | I87: ='Group KPIs'!K65 -> 8.41 | J87: Different
A88: Owner | B88: O-03 | C88: Cash and Liquidity Summary | D88: Table | E88: DSO | F88: WCP-001 | G88: Group | H88: 47 d | I88: ='Group KPIs'!K51 -> 46.97 | J88: Same
A89: Owner | B89: O-03 | C89: Cash and Liquidity Summary | D89: Table | E89: DPO | F89: WCP-002 | G89: Group | H89: 52 d | I89: ='Group KPIs'!K52 -> 52.15 | J89: Same
A90: Owner | B90: O-03 | C90: Cash and Liquidity Summary | D90: Table | E90: Inventory days | F90: WCP-003 | G90: Group | H90: 38 d | I90: ='Group KPIs'!K53 -> 37.76 | J90: Same
A91: Owner | B91: O-03 | C91: Cash and Liquidity Summary | D91: Table | E91: Working-capital movement P07 | F91: WCP-005 | G91: Group | H91: +₹14 m | I91: ='Group KPIs'!K55 -> 17.26 | J91: Different
A92: Owner | B92: O-03 | C92: Cash and Liquidity Summary | D92: Table | E92: Working-capital days | F92: WCP-006 | G92: Group | H92: 33 | I92: ='Group KPIs'!K56 -> 35.72 | J92: Different
A93: Owner | B93: O-04 | C93: Major Capex and Strategic Initiatives | D93: Card | E93: Approved budget | F93: CPX-001 | G93: Group | H93: 850 ₹ m | I93: ='Group KPIs'!K66 -> 1860 | J93: Different
A94: Owner | B94: O-04 | C94: Major Capex and Strategic Initiatives | D94: Card | E94: Committed Capex | F94: CPX-002 | G94: Group | H94: 610 ₹ m · 72% | I94: ='Group KPIs'!K67 -> 1347.73 | J94: Different
A95: Owner | B95: O-04 | C95: Major Capex and Strategic Initiatives | D95: Card | E95: Actual spend | F95: CPX-003 | G95: Group | H95: 402 ₹ m · 47% | I95: ='Group KPIs'!K68 -> 879.71 | J95: Different
A96: Owner | B96: O-04 | C96: Major Capex and Strategic Initiatives | D96: Card | E96: Capex physical progress | F96: CPX-004 | G96: Group | H96: 61 % weighted | I96: ='Group KPIs'!K69 -> 60.85 | J96: Same
A97: Owner | B97: O-04 | C97: Major Capex and Strategic Initiatives | D97: Card | E97: Benefits realization | F97: PRG-002 | G97: Group | H97: 48 % of plan | I97: ='Group KPIs'!K72 -> 47.96 | J97: Same
A98: Owner | B98: O-04 | C98: Major Capex and Strategic Initiatives | D98: Card | E98: Capex value at risk | F98: SIG-011 | G98: Group | H98: 34 ₹ m | I98: ='Group KPIs'!K70 -> 148.03 | J98: Different
A99: Owner | B99: O-04 | C99: Major Capex and Strategic Initiatives | D99: Card | E99: EBITDA benefit delivered YTD | F99: VAL-001 | G99: Group | H99: ₹14 m | I99: ='Group KPIs'!K78 -> 14.21 | J99: Same
A100: Owner | B100: O-04 | C100: Major Capex and Strategic Initiatives | D100: Card | E100: Cash benefit delivered YTD | F100: VAL-002 | G100: Group | H100: ₹9 m | I100: ='Group KPIs'!K79 -> 8.71 | J100: Same
...

Sheet Group KPIs
A1: KPI ID | B1: Measure | C1: Unit | D1: Time basis | E1: How it is calculated | F1: 2026-04 (P01) | G1: 2026-05 (P02) | H1: 2026-06 (P03) | I1: 2026-07 (P04) | J1: 2026-08 (P05) | K1: 2026-09 (P06)
A2: OPS-001 | B2: Production vs plan | C2: % | D2: Month | E2: Good output ÷ Planned production × 100 | F2: =ROUND(IFERROR(100*'Group Inputs'!M4/'Group Inputs'!K4,0),2) -> 96.24 | G2: =ROUND(IFERROR(100*'Group Inputs'!M5/'Group Inputs'!K5,0),2) -> 91.56 | H2: =ROUND(IFERROR(100*'Group Inputs'!M6/'Group Inputs'!K6,0),2) -> 89.93 | I2: =ROUND(IFERROR(100*'Group Inputs'!M7/'Group Inputs'!K7,0),2) -> 94.02 | J2: =ROUND(IFERROR(100*'Group Inputs'!M8/'Group Inputs'!K8,0),2) -> 92.36 | K2: =ROUND(IFERROR(100*'Group Inputs'!M9/'Group Inputs'!K9,0),2) -> 95.51
A3: OPS-003 | B3: Capacity utilization | C3: % | D3: Month | E3: Good output ÷ Installed capacity × 100 | F3: =ROUND(IFERROR(100*'Group Inputs'!M4/'Group Inputs'!J4,0),2) -> 83.98 | G3: =ROUND(IFERROR(100*'Group Inputs'!M5/'Group Inputs'!J5,0),2) -> 76.21 | H3: =ROUND(IFERROR(100*'Group Inputs'!M6/'Group Inputs'!J6,0),2) -> 79.77 | I3: =ROUND(IFERROR(100*'Group Inputs'!M7/'Group Inputs'!J7,0),2) -> 82.31 | J3: =ROUND(IFERROR(100*'Group Inputs'!M8/'Group Inputs'!J8,0),2) -> 78.87 | K3: =ROUND(IFERROR(100*'Group Inputs'!M9/'Group Inputs'!J9,0),2) -> 83.44
A4: PLT-001 | B4: Asset utilization | C4: % | D4: Month | E4: Run hours ÷ Calendar hours × 100 | F4: =ROUND(IFERROR(100*'Group Inputs'!G4/'Group Inputs'!E4,0),2) -> 95.22 | G4: =ROUND(IFERROR(100*'Group Inputs'!G5/'Group Inputs'!E5,0),2) -> 88.71 | H4: =ROUND(IFERROR(100*'Group Inputs'!G6/'Group Inputs'!E6,0),2) -> 94.06 | I4: =ROUND(IFERROR(100*'Group Inputs'!G7/'Group Inputs'!E7,0),2) -> 93.6 | J4: =ROUND(IFERROR(100*'Group Inputs'!G8/'Group Inputs'!E8,0),2) -> 90.1 | K4: =ROUND(IFERROR(100*'Group Inputs'!G9/'Group Inputs'!E9,0),2) -> 93.64
A5: PLT-002 | B5: OEE | C5: % | D5: Month | E5: Availability × Performance × Quality = Good output ÷ Ideal output × 100 | F5: =ROUND(IFERROR(100*'Group Inputs'!M4/'Group Inputs'!I4,0),2) -> 84.74 | G5: =ROUND(IFERROR(100*'Group Inputs'!M5/'Group Inputs'!I5,0),2) -> 81.53 | H5: =ROUND(IFERROR(100*'Group Inputs'!M6/'Group Inputs'!I6,0),2) -> 80.23 | I5: =ROUND(IFERROR(100*'Group Inputs'!M7/'Group Inputs'!I7,0),2) -> 82.78 | J5: =ROUND(IFERROR(100*'Group Inputs'!M8/'Group Inputs'!I8,0),2) -> 82.21 | K5: =ROUND(IFERROR(100*'Group Inputs'!M9/'Group Inputs'!I9,0),2) -> 84.07
A6: PLT-004 | B6: Recovery percentage | C6: % | D6: Month | E6: Valuable content recovered ÷ Valuable content in feed × 100 | F6: =ROUND(IFERROR(100*'Group Inputs'!P4/'Group Inputs'!O4,0),2) -> 86.99 | G6: =ROUND(IFERROR(100*'Group Inputs'!P5/'Group Inputs'!O5,0),2) -> 86.1 | H6: =ROUND(IFERROR(100*'Group Inputs'!P6/'Group Inputs'!O6,0),2) -> 88.15 | I6: =ROUND(IFERROR(100*'Group Inputs'!P7/'Group Inputs'!O7,0),2) -> 87.16 | J6: =ROUND(IFERROR(100*'Group Inputs'!P8/'Group Inputs'!O8,0),2) -> 88.51 | K6: =ROUND(IFERROR(100*'Group Inputs'!P9/'Group Inputs'!O9,0),2) -> 87.35
A7: PLT-005 | B7: Yield | C7: % | D7: Month | E7: Good output ÷ Feed input × 100 | F7: =ROUND(IFERROR(100*'Group Inputs'!M4/'Group Inputs'!N4,0),2) -> 90.5 | G7: =ROUND(IFERROR(100*'Group Inputs'!M5/'Group Inputs'!N5,0),2) -> 92.35 | H7: =ROUND(IFERROR(100*'Group Inputs'!M6/'Group Inputs'!N6,0),2) -> 91.47 | I7: =ROUND(IFERROR(100*'Group Inputs'!M7/'Group Inputs'!N7,0),2) -> 91.45 | J7: =ROUND(IFERROR(100*'Group Inputs'!M8/'Group Inputs'!N8,0),2) -> 91.09 | K7: =ROUND(IFERROR(100*'Group Inputs'!M9/'Group Inputs'!N9,0),2) -> 91.93
A8: REL-001 | B8: MTBF | C8: h | D8: Month | E8: Run hours ÷ Breakdowns | F8: =ROUND(IFERROR('Group Inputs'!G4/'Group Inputs'!R4,0),2) -> 293.82 | G8: =ROUND(IFERROR('Group Inputs'!G5/'Group Inputs'!R5,0),2) -> 188.58 | H8: =ROUND(IFERROR('Group Inputs'!G6/'Group Inputs'!R6,0),2) -> 239.02 | I8: =ROUND(IFERROR('Group Inputs'!G7/'Group Inputs'!R7,0),2) -> 189.91 | J8: =ROUND(IFERROR('Group Inputs'!G8/'Group Inputs'!R8,0),2) -> 211.68 | K8: =ROUND(IFERROR('Group Inputs'!G9/'Group Inputs'!R9,0),2) -> 269.69
A9: REL-002 | B9: Mean Time to Repair | C9: h | D9: Month | E9: Repair hours ÷ Breakdowns | F9: =ROUND(IFERROR('Group Inputs'!S4/'Group Inputs'!R4,0),2) -> 5.08 | G9: =ROUND(IFERROR('Group Inputs'!S5/'Group Inputs'!R5,0),2) -> 6.16 | H9: =ROUND(IFERROR('Group Inputs'!S6/'Group Inputs'!R6,0),2) -> 6.58 | I9: =ROUND(IFERROR('Group Inputs'!S7/'Group Inputs'!R7,0),2) -> 6.69 | J9: =ROUND(IFERROR('Group Inputs'!S8/'Group Inputs'!R8,0),2) -> 6.91 | K9: =ROUND(IFERROR('Group Inputs'!S9/'Group Inputs'!R9,0),2) -> 7.83
A10: REL-003 | B10: Unplanned downtime | C10: h | D10: Month | E10: Unplanned downtime | F10: =ROUND('Group Inputs'!H4,2) -> 103.9 | G10: =ROUND('Group Inputs'!H5,2) -> 167.9 | H10: =ROUND('Group Inputs'!H6,2) -> 142 | I10: =ROUND('Group Inputs'!H7,2) -> 185.3 | J10: =ROUND('Group Inputs'!H8,2) -> 164 | K10: =ROUND('Group Inputs'!H9,2) -> 154.4
A11: REL-004 | B11: Production loss from downtime | C11: t | D11: Month | E11: Production lost to downtime | F11: =ROUND('Group Inputs'!Q4,2) -> 18729 | G11: =ROUND('Group Inputs'!Q5,2) -> 28641 | H11: =ROUND('Group Inputs'!Q6,2) -> 24878 | I11: =ROUND('Group Inputs'!Q7,2) -> 32847 | J11: =ROUND('Group Inputs'!Q8,2) -> 30108 | K11: =ROUND('Group Inputs'!Q9,2) -> 27176
A12: REL-005 | B12: Preventive-maintenance compliance | C12: % | D12: Month | E12: Preventive maintenance completed ÷ Preventive maintenance scheduled × 100 | F12: =ROUND(IFERROR(100*'Group Inputs'!U4/'Group Inputs'!T4,0),2) -> 93.46 | G12: =ROUND(IFERROR(100*'Group Inputs'!U5/'Group Inputs'!T5,0),2) -> 92.73 | H12: =ROUND(IFERROR(100*'Group Inputs'!U6/'Group Inputs'!T6,0),2) -> 94.68 | I12: =ROUND(IFERROR(100*'Group Inputs'!U7/'Group Inputs'!T7,0),2) -> 92.55 | J12: =ROUND(IFERROR(100*'Group Inputs'!U8/'Group Inputs'!T8,0),2) -> 98.28 | K12: =ROUND(IFERROR(100*'Group Inputs'!U9/'Group Inputs'!T9,0),2) -> 95.62
A13: CST-001 | B13: Cost per tonne | C13: ₹/t | D13: Month | E13: (Variable cost + Fixed cost) × 1000 ÷ Good output | F13: =ROUND(IFERROR(1000*('Group Inputs'!V4+'Group Inputs'!X4)/'Group Inputs'!M4,0),2) -> 3046.73 | G13: =ROUND(IFERROR(1000*('Group Inputs'!V5+'Group Inputs'!X5)/'Group Inputs'!M5,0),2) -> 3159.42 | H13: =ROUND(IFERROR(1000*('Group Inputs'!V6+'Group Inputs'!X6)/'Group Inputs'!M6,0),2) -> 3165.25 | I13: =ROUND(IFERROR(1000*('Group Inputs'!V7+'Group Inputs'!X7)/'Group Inputs'!M7,0),2) -> 3100.89 | J13: =ROUND(IFERROR(1000*('Group Inputs'!V8+'Group Inputs'!X8)/'Group Inputs'!M8,0),2) -> 3164.76 | K13: =ROUND(IFERROR(1000*('Group Inputs'!V9+'Group Inputs'!X9)/'Group Inputs'!M9,0),2) -> 2933.74
A14: CST-002 | B14: Variable cost | C14: ₹ thousand | D14: Month | E14: Variable cost | F14: =ROUND('Group Inputs'!V4,2) -> 1911388.7 | G14: =ROUND('Group Inputs'!V5,2) -> 1857317.9 | H14: =ROUND('Group Inputs'!V6,2) -> 1886763.2 | I14: =ROUND('Group Inputs'!V7,2) -> 1970228.4 | J14: =ROUND('Group Inputs'!V8,2) -> 1926079.2 | K14: =ROUND('Group Inputs'!V9,2) -> 1827824.8
A15: CST-003 | B15: Fuel cost | C15: ₹ thousand | D15: Month | E15: Fuel cost | F15: =ROUND('Group Inputs'!W4,2) -> 490330.5 | G15: =ROUND('Group Inputs'!W5,2) -> 492350.2 | H15: =ROUND('Group Inputs'!W6,2) -> 514853.4 | I15: =ROUND('Group Inputs'!W7,2) -> 564124.2 | J15: =ROUND('Group Inputs'!W8,2) -> 544908.7 | K15: =ROUND('Group Inputs'!W9,2) -> 459369.3
A16: SUS-001 | B16: Water usage | C16: m3 | D16: Month | E16: Water used | F16: =ROUND('Group Inputs'!Y4,2) -> 1352732 | G16: =ROUND('Group Inputs'!Y5,2) -> 1282066 | H16: =ROUND('Group Inputs'!Y6,2) -> 1245659 | I16: =ROUND('Group Inputs'!Y7,2) -> 1399278 | J16: =ROUND('Group Inputs'!Y8,2) -> 1363699 | K16: =ROUND('Group Inputs'!Y9,2) -> 1450141
A17: SUS-002 | B17: Emissions | C17: tCO2e | D17: Month | E17: Emissions | F17: =ROUND('Group Inputs'!Z4,2) -> 425627 | G17: =ROUND('Group Inputs'!Z5,2) -> 382393 | H17: =ROUND('Group Inputs'!Z6,2) -> 374121 | I17: =ROUND('Group Inputs'!Z7,2) -> 397386 | J17: =ROUND('Group Inputs'!Z8,2) -> 410412 | K17: =ROUND('Group Inputs'!Z9,2) -> 427664
A18: SUS-003 | B18: Energy intensity | C18: GJ/t | D18: Month | E18: Energy used ÷ Good output | F18: =ROUND(IFERROR('Group Inputs'!AA4/'Group Inputs'!M4,0),2) -> 3.37 | G18: =ROUND(IFERROR('Group Inputs'!AA5/'Group Inputs'!M5,0),2) -> 3.18 | H18: =ROUND(IFERROR('Group Inputs'!AA6/'Group Inputs'!M6,0),2) -> 3.26 | I18: =ROUND(IFERROR('Group Inputs'!AA7/'Group Inputs'!M7,0),2) -> 3.25 | J18: =ROUND(IFERROR('Group Inputs'!AA8/'Group Inputs'!M8,0),2) -> 3.52 | K18: =ROUND(IFERROR('Group Inputs'!AA9/'Group Inputs'!M9,0),2) -> 3.42
A19: SIG-007 | B19: Production at risk | C19: t | D19: Month | E19: Production at risk | F19: =ROUND('Group Inputs'!AB4,2) -> 28497 | G19: =ROUND('Group Inputs'!AB5,2) -> 55870 | H19: =ROUND('Group Inputs'!AB6,2) -> 72181 | I19: =ROUND('Group Inputs'!AB7,2) -> 38527 | J19: =ROUND('Group Inputs'!AB8,2) -> 44820 | K19: =ROUND('Group Inputs'!AB9,2) -> 36810
A20: SIG-008 | B20: Critical plant-state alerts | C20: count | D20: Month | E20: Critical plant alerts | F20: =ROUND('Group Inputs'!AC4,2) -> 8 | G20: =ROUND('Group Inputs'!AC5,2) -> 6 | H20: =ROUND('Group Inputs'!AC6,2) -> 9 | I20: =ROUND('Group Inputs'!AC7,2) -> 3 | J20: =ROUND('Group Inputs'!AC8,2) -> 11 | K20: =ROUND('Group Inputs'!AC9,2) -> 7
A21: SIG-009 | B21: Critical-material shortage risk | C21: count | D21: Month | E21: Critical materials at risk | F21: =ROUND('Group Inputs'!AO4,2) -> 3 | G21: =ROUND('Group Inputs'!AO5,2) -> 3 | H21: =ROUND('Group Inputs'!AO6,2) -> 1 | I21: =ROUND('Group Inputs'!AO7,2) -> 6 | J21: =ROUND('Group Inputs'!AO8,2) -> 6 | K21: =ROUND('Group Inputs'!AO9,2) -> 5
A22: SIG-012 | B22: Dispatch delays | C22: % | D22: Month | E22: Delayed dispatches ÷ Dispatches × 100 | F22: =ROUND(IFERROR(100*'Group Inputs'!AQ4/'Group Inputs'!AP4,0),2) -> 5.98 | G22: =ROUND(IFERROR(100*'Group Inputs'!AQ5/'Group Inputs'!AP5,0),2) -> 7.08 | H22: =ROUND(IFERROR(100*'Group Inputs'!AQ6/'Group Inputs'!AP6,0),2) -> 7.48 | I22: =ROUND(IFERROR(100*'Group Inputs'!AQ7/'Group Inputs'!AP7,0),2) -> 7.98 | J22: =ROUND(IFERROR(100*'Group Inputs'!AQ8/'Group Inputs'!AP8,0),2) -> 7.63 | K22: =ROUND(IFERROR(100*'Group Inputs'!AQ9/'Group Inputs'!AP9,0),2) -> 8.66
A23: SIG-021 | B23: Environmental violations | C23: count | D23: Month | E23: Environmental violations | F23: =ROUND('Group Inputs'!AJ4,2) -> 1 | G23: =ROUND('Group Inputs'!AJ5,2) -> 0 | H23: =ROUND('Group Inputs'!AJ6,2) -> 1 | I23: =ROUND('Group Inputs'!AJ7,2) -> 0 | J23: =ROUND('Group Inputs'!AJ8,2) -> 0 | K23: =ROUND('Group Inputs'!AJ9,2) -> 0
A24: EHS-001 | B24: TRIR | C24: per 200,000 h | D24: Month | E24: Recordable injuries × 200,000 ÷ Hours worked | F24: =ROUND(IFERROR(200000*'Group Inputs'!AE4/'Group Inputs'!AD4,0),2) -> 0.87 | G24: =ROUND(IFERROR(200000*'Group Inputs'!AE5/'Group Inputs'!AD5,0),2) -> 1.87 | H24: =ROUND(IFERROR(200000*'Group Inputs'!AE6/'Group Inputs'!AD6,0),2) -> 2.26 | I24: =ROUND(IFERROR(200000*'Group Inputs'!AE7/'Group Inputs'!AD7,0),2) -> 1.35 | J24: =ROUND(IFERROR(200000*'Group Inputs'!AE8/'Group Inputs'!AD8,0),2) -> 1.55 | K24: =ROUND(IFERROR(200000*'Group Inputs'!AE9/'Group Inputs'!AD9,0),2) -> 0.47
A25: EHS-002 | B25: Severity incidents | C25: count | D25: Month | E25: Severity incidents | F25: =ROUND('Group Inputs'!AF4,2) -> 1 | G25: =ROUND('Group Inputs'!AF5,2) -> 1 | H25: =ROUND('Group Inputs'!AF6,2) -> 0 | I25: =ROUND('Group Inputs'!AF7,2) -> 2 | J25: =ROUND('Group Inputs'!AF8,2) -> 1 | K25: =ROUND('Group Inputs'!AF9,2) -> 3
A26: EHS-003 | B26: Near misses | C26: count | D26: Month | E26: Near misses | F26: =ROUND('Group Inputs'!AG4,2) -> 39 | G26: =ROUND('Group Inputs'!AG5,2) -> 46 | H26: =ROUND('Group Inputs'!AG6,2) -> 44 | I26: =ROUND('Group Inputs'!AG7,2) -> 32 | J26: =ROUND('Group Inputs'!AG8,2) -> 42 | K26: =ROUND('Group Inputs'!AG9,2) -> 41
A27: EHS-004 | B27: Critical safety incidents | C27: count | D27: Month | E27: Critical safety incidents | F27: =ROUND('Group Inputs'!AH4,2) -> 0 | G27: =ROUND('Group Inputs'!AH5,2) -> 1 | H27: =ROUND('Group Inputs'!AH6,2) -> 0 | I27: =ROUND('Group Inputs'!AH7,2) -> 0 | J27: =ROUND('Group Inputs'!AH8,2) -> 1 | K27: =ROUND('Group Inputs'!AH9,2) -> 0
A28: EHS-005 | B28: Environmental excursions | C28: count | D28: Month | E28: Environmental excursions | F28: =ROUND('Group Inputs'!AI4,2) -> 2 | G28: =ROUND('Group Inputs'!AI5,2) -> 1 | H28: =ROUND('Group Inputs'!AI6,2) -> 1 | I28: =ROUND('Group Inputs'!AI7,2) -> 3 | J28: =ROUND('Group Inputs'!AI8,2) -> 1 | K28: =ROUND('Group Inputs'!AI9,2) -> 2
A29: EHS-006 | B29: Open EHS corrective actions | C29: count | D29: Month | E29: Open EHS corrective actions | F29: =ROUND('Group Inputs'!AK4,2) -> 60 | G29: =ROUND('Group Inputs'!AK5,2) -> 58 | H29: =ROUND('Group Inputs'!AK6,2) -> 45 | I29: =ROUND('Group Inputs'!AK7,2) -> 60 | J29: =ROUND('Group Inputs'!AK8,2) -> 44 | K29: =ROUND('Group Inputs'!AK9,2) -> 45
A30: EHS-007 | B30: Overdue EHS actions | C30: count | D30: Month | E30: Overdue EHS corrective actions | F30: =ROUND('Group Inputs'!AL4,2) -> 12 | G30: =ROUND('Group Inputs'!AL5,2) -> 14 | H30: =ROUND('Group Inputs'!AL6,2) -> 8 | I30: =ROUND('Group Inputs'!AL7,2) -> 12 | J30: =ROUND('Group Inputs'!AL8,2) -> 3 | K30: =ROUND('Group Inputs'!AL9,2) -> 9
A31: EHS-009 | B31: EHS investigation completion | C31: % | D31: Month | E31: EHS investigations completed ÷ EHS investigations due × 100 (100 if none due) | F31: =ROUND(IF('Group Inputs'!AM4=0,100,100*'Group Inputs'!AN4/'Group Inputs'!AM4),2) -> 66.67 | G31: =ROUND(IF('Group Inputs'!AM5=0,100,100*'Group Inputs'!AN5/'Group Inputs'!AM5),2) -> 100 | H31: =ROUND(IF('Group Inputs'!AM6=0,100,100*'Group Inputs'!AN6/'Group Inputs'!AM6),2) -> 88.89 | I31: =ROUND(IF('Group Inputs'!AM7=0,100,100*'Group Inputs'!AN7/'Group Inputs'!AM7),2) -> 85.71 | J31: =ROUND(IF('Group Inputs'!AM8=0,100,100*'Group Inputs'!AN8/'Group Inputs'!AM8),2) -> 90.91 | K31: =ROUND(IF('Group Inputs'!AM9=0,100,100*'Group Inputs'!AN9/'Group Inputs'!AM9),2) -> 75
A32: REG-006 | B32: Licence or permit expiry clock | C32: days | D32: Month | E32: Days to permit expiry (lowest plant) | F32: =ROUND('Group Inputs'!AR4,2) -> 215 | G32: =ROUND('Group Inputs'!AR5,2) -> 185 | H32: =ROUND('Group Inputs'!AR6,2) -> 155 | I32: =ROUND('Group Inputs'!AR7,2) -> 125 | J32: =ROUND('Group Inputs'!AR8,2) -> 95 | K32: =ROUND('Group Inputs'!AR9,2) -> 65
A33: OPS-005 | B33: Capacity utilisation (same measure as OPS-003) | C33: % | D33: Month | E33: Good output ÷ Installed capacity × 100 | F33: =ROUND(IFERROR(100*'Group Inputs'!M4/'Group Inputs'!J4,0),2) -> 83.98 | G33: =ROUND(IFERROR(100*'Group Inputs'!M5/'Group Inputs'!J5,0),2) -> 76.21 | H33: =ROUND(IFERROR(100*'Group Inputs'!M6/'Group Inputs'!J6,0),2) -> 79.77 | I33: =ROUND(IFERROR(100*'Group Inputs'!M7/'Group Inputs'!J7,0),2) -> 82.31 | J33: =ROUND(IFERROR(100*'Group Inputs'!M8/'Group Inputs'!J8,0),2) -> 78.87 | K33: =ROUND(IFERROR(100*'Group Inputs'!M9/'Group Inputs'!J9,0),2) -> 83.44
A34: OPS-006 | B34: OEE · Group weighted (same measure as PLT-002) | C34: % | D34: Month | E34: Good output ÷ Ideal output × 100 (weighted by output, not an average of plants) | F34: =ROUND(IFERROR(100*'Group Inputs'!M4/'Group Inputs'!I4,0),2) -> 84.74 | G34: =ROUND(IFERROR(100*'Group Inputs'!M5/'Group Inputs'!I5,0),2) -> 81.53 | H34: =ROUND(IFERROR(100*'Group Inputs'!M6/'Group Inputs'!I6,0),2) -> 80.23 | I34: =ROUND(IFERROR(100*'Group Inputs'!M7/'Group Inputs'!I7,0),2) -> 82.78 | J34: =ROUND(IFERROR(100*'Group Inputs'!M8/'Group Inputs'!I8,0),2) -> 82.21 | K34: =ROUND(IFERROR(100*'Group Inputs'!M9/'Group Inputs'!I9,0),2) -> 84.07
A35: OPS-002 | B35: Sales vs plan | C35: % | D35: Month | E35: Sales volume ÷ Planned sales volume × 100 | F35: =ROUND(IF('Group Inputs'!AT4=0,0,100*'Group Inputs'!AS4/'Group Inputs'!AT4),2) -> 95.35 | G35: =ROUND(IF('Group Inputs'!AT5=0,0,100*'Group Inputs'!AS5/'Group Inputs'!AT5),2) -> 91.65 | H35: =ROUND(IF('Group Inputs'!AT6=0,0,100*'Group Inputs'!AS6/'Group Inputs'!AT6),2) -> 88.97 | I35: =ROUND(IF('Group Inputs'!AT7=0,0,100*'Group Inputs'!AS7/'Group Inputs'!AT7),2) -> 93.98 | J35: =ROUND(IF('Group Inputs'!AT8=0,0,100*'Group Inputs'!AS8/'Group Inputs'!AT8),2) -> 92.4 | K35: =ROUND(IF('Group Inputs'!AT9=0,0,100*'Group Inputs'!AS9/'Group Inputs'!AT9),2) -> 95.23
A36: OPS-004 | B36: Sales vs plan · Group (same measure as OPS-002) | C36: % | D36: Month | E36: Sales volume ÷ Planned sales volume × 100 | F36: =ROUND(IF('Group Inputs'!AT4=0,0,100*'Group Inputs'!AS4/'Group Inputs'!AT4),2) -> 95.35 | G36: =ROUND(IF('Group Inputs'!AT5=0,0,100*'Group Inputs'!AS5/'Group Inputs'!AT5),2) -> 91.65 | H36: =ROUND(IF('Group Inputs'!AT6=0,0,100*'Group Inputs'!AS6/'Group Inputs'!AT6),2) -> 88.97 | I36: =ROUND(IF('Group Inputs'!AT7=0,0,100*'Group Inputs'!AS7/'Group Inputs'!AT7),2) -> 93.98 | J36: =ROUND(IF('Group Inputs'!AT8=0,0,100*'Group Inputs'!AS8/'Group Inputs'!AT8),2) -> 92.4 | K36: =ROUND(IF('Group Inputs'!AT9=0,0,100*'Group Inputs'!AS9/'Group Inputs'!AT9),2) -> 95.23
A37: CST-004 | B37: Power cost per tonne | C37: ₹/t | D37: Month | E37: Power cost × 1000 ÷ Good output | F37: =ROUND(IF('Group Inputs'!M4=0,0,1000*'Group Inputs'!AW4/'Group Inputs'!M4),2) -> 186.81 | G37: =ROUND(IF('Group Inputs'!M5=0,0,1000*'Group Inputs'!AW5/'Group Inputs'!M5),2) -> 185.82 | H37: =ROUND(IF('Group Inputs'!M6=0,0,1000*'Group Inputs'!AW6/'Group Inputs'!M6),2) -> 191.62 | I37: =ROUND(IF('Group Inputs'!M7=0,0,1000*'Group Inputs'!AW7/'Group Inputs'!M7),2) -> 171.72 | J37: =ROUND(IF('Group Inputs'!M8=0,0,1000*'Group Inputs'!AW8/'Group Inputs'!M8),2) -> 187.69 | K37: =ROUND(IF('Group Inputs'!M9=0,0,1000*'Group Inputs'!AW9/'Group Inputs'!M9),2) -> 174.29
A38: FIN-001 | B38: EBITDA YTD | C38: ₹ m | D38: Year to date | E38: Sum of monthly EBITDA since April ÷ 1000 | F38: =ROUND(SUM('Group Inputs'!FY$4:FY4)/1000,2) -> 321.96 | G38: =ROUND(SUM('Group Inputs'!FY$4:FY5)/1000,2) -> 574.52 | H38: =ROUND(SUM('Group Inputs'!FY$4:FY6)/1000,2) -> 816.46 | I38: =ROUND(SUM('Group Inputs'!FY$4:FY7)/1000,2) -> 1114.42 | J38: =ROUND(SUM('Group Inputs'!FY$4:FY8)/1000,2) -> 1363.11 | K38: =ROUND(SUM('Group Inputs'!FY$4:FY9)/1000,2) -> 1760.09
A39: FIN-002 | B39: EBIT YTD | C39: ₹ m | D39: Year to date | E39: Sum of monthly EBIT since April ÷ 1000 | F39: =ROUND(SUM('Group Inputs'!FZ$4:FZ4)/1000,2) -> 232.68 | G39: =ROUND(SUM('Group Inputs'!FZ$4:FZ5)/1000,2) -> 397.26 | H39: =ROUND(SUM('Group Inputs'!FZ$4:FZ6)/1000,2) -> 550.73 | I39: =ROUND(SUM('Group Inputs'!FZ$4:FZ7)/1000,2) -> 760.11 | J39: =ROUND(SUM('Group Inputs'!FZ$4:FZ8)/1000,2) -> 920.64 | K39: =ROUND(SUM('Group Inputs'!FZ$4:FZ9)/1000,2) -> 1228.14
A40: FIN-003 | B40: Revenue YTD | C40: ₹ m | D40: Year to date | E40: Sum of monthly Revenue since April ÷ 1000 | F40: =ROUND(SUM('Group Inputs'!AU$4:AU4)/1000,2) -> 2349.26 | G40: =ROUND(SUM('Group Inputs'!AU$4:AU5)/1000,2) -> 4568.1 | H40: =ROUND(SUM('Group Inputs'!AU$4:AU6)/1000,2) -> 6803.75 | I40: =ROUND(SUM('Group Inputs'!AU$4:AU7)/1000,2) -> 9188.45 | J40: =ROUND(SUM('Group Inputs'!AU$4:AU8)/1000,2) -> 11475.48 | K40: =ROUND(SUM('Group Inputs'!AU$4:AU9)/1000,2) -> 13811.3
A41: FIN-004 | B41: Free cash flow YTD | C41: ₹ m | D41: Year to date | E41: Sum of monthly Free cash flow since April ÷ 1000 | F41: =ROUND(SUM('Group Inputs'!GD$4:GD4)/1000,2) -> 65.96 | G41: =ROUND(SUM('Group Inputs'!GD$4:GD5)/1000,2) -> 311.68 | H41: =ROUND(SUM('Group Inputs'!GD$4:GD6)/1000,2) -> 327.88 | I41: =ROUND(SUM('Group Inputs'!GD$4:GD7)/1000,2) -> 372.88 | J41: =ROUND(SUM('Group Inputs'!GD$4:GD8)/1000,2) -> 448.76 | K41: =ROUND(SUM('Group Inputs'!GD$4:GD9)/1000,2) -> 606.18
A42: FIN-005 | B42: ROCE, annualised | C42: % | D42: Year to date | E42: EBIT since April × 12 ÷ months elapsed ÷ Capital employed × 100 | F42: =ROUND(IF('Group Inputs'!CA4=0,0,100*SUM('Group Inputs'!FZ$4:FZ4)*12/'Group Inputs'!D4/'Group Inputs'!CA4),2) -> 13.42 | G42: =ROUND(IF('Group Inputs'!CA5=0,0,100*SUM('Group Inputs'!FZ$4:FZ5)*12/'Group Inputs'!D5/'Group Inputs'!CA5),2) -> 11.41 | H42: =ROUND(IF('Group Inputs'!CA6=0,0,100*SUM('Group Inputs'!FZ$4:FZ6)*12/'Group Inputs'!D6/'Group Inputs'!CA6),2) -> 10.51 | I42: =ROUND(IF('Group Inputs'!CA7=0,0,100*SUM('Group Inputs'!FZ$4:FZ7)*12/'Group Inputs'!D7/'Group Inputs'!CA7),2) -> 10.83 | J42: =ROUND(IF('Group Inputs'!CA8=0,0,100*SUM('Group Inputs'!FZ$4:FZ8)*12/'Group Inputs'!D8/'Group Inputs'!CA8),2) -> 10.46 | K42: =ROUND(IF('Group Inputs'!CA9=0,0,100*SUM('Group Inputs'!FZ$4:FZ9)*12/'Group Inputs'!D9/'Group Inputs'!CA9),2) -> 11.58
A43: FIN-006 | B43: Net debt | C43: ₹ m | D43: Month end | E43: (Gross debt − Cash) ÷ 1000 | F43: =ROUND('Group Inputs'!GE4/1000,2) -> 7000 | G43: =ROUND('Group Inputs'!GE5/1000,2) -> 6930 | H43: =ROUND('Group Inputs'!GE6/1000,2) -> 6860 | I43: =ROUND('Group Inputs'!GE7/1000,2) -> 6790 | J43: =ROUND('Group Inputs'!GE8/1000,2) -> 6720 | K43: =ROUND('Group Inputs'!GE9/1000,2) -> 6650
A44: FIN-007 | B44: Shareholder-value indicator (economic profit YTD) | C44: ₹ m | D44: Year to date | E44: (EBIT since April × (1 − Tax rate) − Capital employed × Cost of capital × months elapsed ÷ 12) ÷ 1000 | F44: =ROUND((SUM('Group Inputs'!FZ$4:FZ4)*(1-Parameters!$B$2)-'Group Inputs'!CA4*Parameters!$B$3*'Group Inputs'!D4/12)/1000,2) -> 9.85 | G44: =ROUND((SUM('Group Inputs'!FZ$4:FZ5)*(1-Parameters!$B$2)-'Group Inputs'!CA5*Parameters!$B$3*'Group Inputs'!D5/12)/1000,2) -> -32.71 | H44: =ROUND((SUM('Group Inputs'!FZ$4:FZ6)*(1-Parameters!$B$2)-'Group Inputs'!CA6*Parameters!$B$3*'Group Inputs'!D6/12)/1000,2) -> -84.91 | I44: =ROUND((SUM('Group Inputs'!FZ$4:FZ7)*(1-Parameters!$B$2)-'Group Inputs'!CA7*Parameters!$B$3*'Group Inputs'!D7/12)/1000,2) -> -96.49 | J44: =ROUND((SUM('Group Inputs'!FZ$4:FZ8)*(1-Parameters!$B$2)-'Group Inputs'!CA8*Parameters!$B$3*'Group Inputs'!D8/12)/1000,2) -> -146.03 | K44: =ROUND((SUM('Group Inputs'!FZ$4:FZ9)*(1-Parameters!$B$2)-'Group Inputs'!CA9*Parameters!$B$3*'Group Inputs'!D9/12)/1000,2) -> -86.65
A45: FIN-008 | B45: FCF conversion (FCF ÷ EBITDA) | C45: % | D45: Year to date | E45: Free cash flow since April ÷ EBITDA since April × 100 | F45: =ROUND(IF(SUM('Group Inputs'!FY$4:FY4)=0,0,100*SUM('Group Inputs'!GD$4:GD4)/SUM('Group Inputs'!FY$4:FY4)),2) -> 20.49 | G45: =ROUND(IF(SUM('Group Inputs'!FY$4:FY5)=0,0,100*SUM('Group Inputs'!GD$4:GD5)/SUM('Group Inputs'!FY$4:FY5)),2) -> 54.25 | H45: =ROUND(IF(SUM('Group Inputs'!FY$4:FY6)=0,0,100*SUM('Group Inputs'!GD$4:GD6)/SUM('Group Inputs'!FY$4:FY6)),2) -> 40.16 | I45: =ROUND(IF(SUM('Group Inputs'!FY$4:FY7)=0,0,100*SUM('Group Inputs'!GD$4:GD7)/SUM('Group Inputs'!FY$4:FY7)),2) -> 33.46 | J45: =ROUND(IF(SUM('Group Inputs'!FY$4:FY8)=0,0,100*SUM('Group Inputs'!GD$4:GD8)/SUM('Group Inputs'!FY$4:FY8)),2) -> 32.92 | K45: =ROUND(IF(SUM('Group Inputs'!FY$4:FY9)=0,0,100*SUM('Group Inputs'!GD$4:GD9)/SUM('Group Inputs'!FY$4:FY9)),2) -> 34.44
A46: CSH-001 | B46: Cash position | C46: ₹ m | D46: Month end | E46: Cash ÷ 1000 | F46: =ROUND('Group Inputs'!CC4/1000,2) -> 2099.11 | G46: =ROUND('Group Inputs'!CC5/1000,2) -> 2017.66 | H46: =ROUND('Group Inputs'!CC6/1000,2) -> 1986.19 | I46: =ROUND('Group Inputs'!CC7/1000,2) -> 2142.07 | J46: =ROUND('Group Inputs'!CC8/1000,2) -> 2027.31 | K46: =ROUND('Group Inputs'!CC9/1000,2) -> 2141.82
A47: CSH-002 | B47: Cash released YTD | C47: ₹ m | D47: Year to date | E47: Sum of cash released since April ÷ 1000 | F47: =ROUND(SUM('Group Inputs'!CN$4:CN4)/1000,2) -> 3.83 | G47: =ROUND(SUM('Group Inputs'!CN$4:CN5)/1000,2) -> 7.49 | H47: =ROUND(SUM('Group Inputs'!CN$4:CN6)/1000,2) -> 11.28 | I47: =ROUND(SUM('Group Inputs'!CN$4:CN7)/1000,2) -> 14.88 | J47: =ROUND(SUM('Group Inputs'!CN$4:CN8)/1000,2) -> 18.62 | K47: =ROUND(SUM('Group Inputs'!CN$4:CN9)/1000,2) -> 22.03
A48: CSH-003 | B48: Daily collections | C48: ₹ m per day | D48: Month | E48: Cash collected ÷ Days in month ÷ 1000 | F48: =ROUND('Group Inputs'!CM4/'Group Inputs'!C4/1000,2) -> 77.02 | G48: =ROUND('Group Inputs'!CM5/'Group Inputs'!C5/1000,2) -> 70.67 | H48: =ROUND('Group Inputs'!CM6/'Group Inputs'!C6/1000,2) -> 73.45 | I48: =ROUND('Group Inputs'!CM7/'Group Inputs'!C7/1000,2) -> 75.79 | J48: =ROUND('Group Inputs'!CM8/'Group Inputs'!C8/1000,2) -> 73.61 | K48: =ROUND('Group Inputs'!CM9/'Group Inputs'!C9/1000,2) -> 76.77
A49: CSH-004 | B49: Cash-conversion cycle | C49: days | D49: Month end | E49: DSO + Inventory days − DPO | F49: =ROUND('Group Inputs'!GG4+'Group Inputs'!GI4-'Group Inputs'!GH4,2) -> 34.91 | G49: =ROUND('Group Inputs'!GG5+'Group Inputs'!GI5-'Group Inputs'!GH5,2) -> 35.93 | H49: =ROUND('Group Inputs'!GG6+'Group Inputs'!GI6-'Group Inputs'!GH6,2) -> 34.78 | I49: =ROUND('Group Inputs'!GG7+'Group Inputs'!GI7-'Group Inputs'!GH7,2) -> 33.84 | J49: =ROUND('Group Inputs'!GG8+'Group Inputs'!GI8-'Group Inputs'!GH8,2) -> 35.58 | K49: =ROUND('Group Inputs'!GG9+'Group Inputs'!GI9-'Group Inputs'!GH9,2) -> 32.59
A50: CSH-006 | B50: Cash-upstream exposure | C50: ₹ m | D50: Next 30 days | E50: (Cash due to be upstreamed − Amount covered by available cash) ÷ 1000 | F50: =ROUND(('Group Inputs'!CO4-'Group Inputs'!CP4)/1000,2) -> 0 | G50: =ROUND(('Group Inputs'!CO5-'Group Inputs'!CP5)/1000,2) -> 0 | H50: =ROUND(('Group Inputs'!CO6-'Group Inputs'!CP6)/1000,2) -> 0 | I50: =ROUND(('Group Inputs'!CO7-'Group Inputs'!CP7)/1000,2) -> 0 | J50: =ROUND(('Group Inputs'!CO8-'Group Inputs'!CP8)/1000,2) -> 25.62 | K50: =ROUND(('Group Inputs'!CO9-'Group Inputs'!CP9)/1000,2) -> 27.21
A51: WCP-001 | B51: DSO | C51: days | D51: Month end | E51: Trade receivables ÷ Revenue × Days in month | F51: =ROUND('Group Inputs'!GG4,2) -> 47.16 | G51: =ROUND('Group Inputs'!GG5,2) -> 48.66 | H51: =ROUND('Group Inputs'!GG6,2) -> 48.42 | I51: =ROUND('Group Inputs'!GG7,2) -> 48.03 | J51: =ROUND('Group Inputs'!GG8,2) -> 47.51 | K51: =ROUND('Group Inputs'!GG9,2) -> 46.97
A52: WCP-002 | B52: DPO | C52: days | D52: Month end | E52: Trade payables ÷ Variable cost × Days in month | F52: =ROUND('Group Inputs'!GH4,2) -> 50.37 | G52: =ROUND('Group Inputs'!GH5,2) -> 51.11 | H52: =ROUND('Group Inputs'!GH6,2) -> 52.39 | I52: =ROUND('Group Inputs'!GH7,2) -> 51.26 | J52: =ROUND('Group Inputs'!GH8,2) -> 50.37 | K52: =ROUND('Group Inputs'!GH9,2) -> 52.15
A53: WCP-003 | B53: Inventory days | C53: days | D53: Month end | E53: Inventory ÷ Variable cost × Days in month | F53: =ROUND('Group Inputs'!GI4,2) -> 38.13 | G53: =ROUND('Group Inputs'!GI5,2) -> 38.38 | H53: =ROUND('Group Inputs'!GI6,2) -> 38.75 | I53: =ROUND('Group Inputs'!GI7,2) -> 37.06 | J53: =ROUND('Group Inputs'!GI8,2) -> 38.44 | K53: =ROUND('Group Inputs'!GI9,2) -> 37.76
A54: WCP-004 | B54: Net working capital | C54: ₹ m | D54: Month end | E54: (Trade receivables + Inventory − Trade payables) ÷ 1000 | F54: =ROUND('Group Inputs'!GA4/1000,2) -> 2912.58 | G54: =ROUND('Group Inputs'!GA5/1000,2) -> 2720 | H54: =ROUND('Group Inputs'!GA6/1000,2) -> 2750.36 | I54: =ROUND('Group Inputs'!GA7/1000,2) -> 2792.72 | J54: =ROUND('Group Inputs'!GA8/1000,2) -> 2763.73 | K54: =ROUND('Group Inputs'!GA9/1000,2) -> 2780.99
A55: WCP-005 | B55: Working-capital movement | C55: ₹ m | D55: Month | E55: (Net working capital − last month's net working capital) ÷ 1000; positive = cash tied up | F55: =ROUND('Group Inputs'!GB4/1000,2) -> 43.69 | G55: =ROUND('Group Inputs'!GB5/1000,2) -> -192.58 | H55: =ROUND('Group Inputs'!GB6/1000,2) -> 30.36 | I55: =ROUND('Group Inputs'!GB7/1000,2) -> 42.36 | J55: =ROUND('Group Inputs'!GB8/1000,2) -> -29 | K55: =ROUND('Group Inputs'!GB9/1000,2) -> 17.26
A56: WCP-006 | B56: Working-capital days | C56: days | D56: Month end | E56: Net working capital ÷ Revenue × Days in month | F56: =ROUND(IF('Group Inputs'!AU4=0,0,'Group Inputs'!GA4/'Group Inputs'!AU4*'Group Inputs'!C4),2) -> 37.19 | G56: =ROUND(IF('Group Inputs'!AU5=0,0,'Group Inputs'!GA5/'Group Inputs'!AU5*'Group Inputs'!C5),2) -> 38 | H56: =ROUND(IF('Group Inputs'!AU6=0,0,'Group Inputs'!GA6/'Group Inputs'!AU6*'Group Inputs'!C6),2) -> 36.91 | I56: =ROUND(IF('Group Inputs'!AU7=0,0,'Group Inputs'!GA7/'Group Inputs'!AU7*'Group Inputs'!C7),2) -> 36.3 | J56: =ROUND(IF('Group Inputs'!AU8=0,0,'Group Inputs'!GA8/'Group Inputs'!AU8*'Group Inputs'!C8),2) -> 37.46 | K56: =ROUND(IF('Group Inputs'!AU9=0,0,'Group Inputs'!GA9/'Group Inputs'!AU9*'Group Inputs'!C9),2) -> 35.72
A57: LIQ-001 | B57: Liquidity runway | C57: months | D57: Month end | E57: (Cash + Undrawn facilities) ÷ (Fixed cost + Overheads + Debt service) per month | F57: =ROUND(IF(('Group Inputs'!X4+'Group Inputs'!BY4+'Group Inputs'!CE4)=0,0,('Group Inputs'!CC4+'Group Inputs'!CD4)/('Group Inputs'!X4+'Group Inputs'!BY4+'Group Inputs'!CE4)),2) -> 15.85 | G57: =ROUND(IF(('Group Inputs'!X5+'Group Inputs'!BY5+'Group Inputs'!CE5)=0,0,('Group Inputs'!CC5+'Group Inputs'!CD5)/('Group Inputs'!X5+'Group Inputs'!BY5+'Group Inputs'!CE5)),2) -> 15.91 | H57: =ROUND(IF(('Group Inputs'!X6+'Group Inputs'!BY6+'Group Inputs'!CE6)=0,0,('Group Inputs'!CC6+'Group Inputs'!CD6)/('Group Inputs'!X6+'Group Inputs'!BY6+'Group Inputs'!CE6)),2) -> 16.11 | I57: =ROUND(IF(('Group Inputs'!X7+'Group Inputs'!BY7+'Group Inputs'!CE7)=0,0,('Group Inputs'!CC7+'Group Inputs'!CD7)/('Group Inputs'!X7+'Group Inputs'!BY7+'Group Inputs'!CE7)),2) -> 16.2 | J57: =ROUND(IF(('Group Inputs'!X8+'Group Inputs'!BY8+'Group Inputs'!CE8)=0,0,('Group Inputs'!CC8+'Group Inputs'!CD8)/('Group Inputs'!X8+'Group Inputs'!BY8+'Group Inputs'!CE8)),2) -> 15.88 | K57: =ROUND(IF(('Group Inputs'!X9+'Group Inputs'!BY9+'Group Inputs'!CE9)=0,0,('Group Inputs'!CC9+'Group Inputs'!CD9)/('Group Inputs'!X9+'Group Inputs'!BY9+'Group Inputs'!CE9)),2) -> 16.71
A58: LIQ-002 | B58: Covenant headroom | C58: % | D58: Month end | E58: (Covenant limit − Net debt ÷ Annualised EBITDA) ÷ Covenant limit × 100 | F58: =ROUND(IF('Group Inputs'!GF4=0,0,100*(Parameters!$B$4-'Group Inputs'!GE4/'Group Inputs'!GF4)/Parameters!$B$4),2) -> 27.53 | G58: =ROUND(IF('Group Inputs'!GF5=0,0,100*(Parameters!$B$4-'Group Inputs'!GE5/'Group Inputs'!GF5)/Parameters!$B$4),2) -> 19.59 | H58: =ROUND(IF('Group Inputs'!GF6=0,0,100*(Parameters!$B$4-'Group Inputs'!GE6/'Group Inputs'!GF6)/Parameters!$B$4),2) -> 15.98 | I58: =ROUND(IF('Group Inputs'!GF7=0,0,100*(Parameters!$B$4-'Group Inputs'!GE7/'Group Inputs'!GF7)/Parameters!$B$4),2) -> 18.76 | J58: =ROUND(IF('Group Inputs'!GF8=0,0,100*(Parameters!$B$4-'Group Inputs'!GE8/'Group Inputs'!GF8)/Parameters!$B$4),2) -> 17.84 | K58: =ROUND(IF('Group Inputs'!GF9=0,0,100*(Parameters!$B$4-'Group Inputs'!GE9/'Group Inputs'!GF9)/Parameters!$B$4),2) -> 24.44
A59: LIQ-003 | B59: Debt-maturity exposure, next 12 months | C59: ₹ m | D59: Month end | E59: Debt maturing in next 12 months ÷ 1000 | F59: =ROUND('Group Inputs'!CF4/1000,2) -> 844.3 | G59: =ROUND('Group Inputs'!CF5/1000,2) -> 922.92 | H59: =ROUND('Group Inputs'!CF6/1000,2) -> 881.23 | I59: =ROUND('Group Inputs'!CF7/1000,2) -> 910.31 | J59: =ROUND('Group Inputs'!CF8/1000,2) -> 866.12 | K59: =ROUND('Group Inputs'!CF9/1000,2) -> 891.41
A60: LIQ-004 | B60: Financing exposure (floating-rate debt) | C60: ₹ m | D60: Month end | E60: Floating-rate debt ÷ 1000 | F60: =ROUND('Group Inputs'!CG4/1000,2) -> 2721.45 | G60: =ROUND('Group Inputs'!CG5/1000,2) -> 2519.26 | H60: =ROUND('Group Inputs'!CG6/1000,2) -> 2568.18 | I60: =ROUND('Group Inputs'!CG7/1000,2) -> 2622.48 | J60: =ROUND('Group Inputs'!CG8/1000,2) -> 2627.52 | K60: =ROUND('Group Inputs'!CG9/1000,2) -> 2720.83
A61: TRS-001 | B61: FX exposure, unhedged | C61: ₹ m | D61: Month end | E61: (Foreign-currency exposure − Amount hedged) ÷ 1000 | F61: =ROUND(('Group Inputs'!CZ4-'Group Inputs'!DA4)/1000,2) -> 190.79 | G61: =ROUND(('Group Inputs'!CZ5-'Group Inputs'!DA5)/1000,2) -> 207.5 | H61: =ROUND(('Group Inputs'!CZ6-'Group Inputs'!DA6)/1000,2) -> 188.28 | I61: =ROUND(('Group Inputs'!CZ7-'Group Inputs'!DA7)/1000,2) -> 227.78 | J61: =ROUND(('Group Inputs'!CZ8-'Group Inputs'!DA8)/1000,2) -> 225.53 | K61: =ROUND(('Group Inputs'!CZ9-'Group Inputs'!DA9)/1000,2) -> 221.72
A62: TRS-002 | B62: Hedging effectiveness | C62: % | D62: Month | E62: Change in value of hedges ÷ Change in value of hedged items × 100 | F62: =ROUND(IF('Group Inputs'!DE4=0,0,100*'Group Inputs'!DD4/'Group Inputs'!DE4),2) -> 89.09 | G62: =ROUND(IF('Group Inputs'!DE5=0,0,100*'Group Inputs'!DD5/'Group Inputs'!DE5),2) -> 92.53 | H62: =ROUND(IF('Group Inputs'!DE6=0,0,100*'Group Inputs'!DD6/'Group Inputs'!DE6),2) -> 92.84 | I62: =ROUND(IF('Group Inputs'!DE7=0,0,100*'Group Inputs'!DD7/'Group Inputs'!DE7),2) -> 90.54 | J62: =ROUND(IF('Group Inputs'!DE8=0,0,100*'Group Inputs'!DD8/'Group Inputs'!DE8),2) -> 92.99 | K62: =ROUND(IF('Group Inputs'!DE9=0,0,100*'Group Inputs'!DD9/'Group Inputs'!DE9),2) -> 91.7
A63: TRS-003 | B63: USD share of unhedged FX exposure | C63: % | D63: Month end | E63: (USD exposure − USD hedged) ÷ (FX exposure − FX hedged) × 100 | F63: =ROUND(IF(('Group Inputs'!CZ4-'Group Inputs'!DA4)=0,0,100*('Group Inputs'!DB4-'Group Inputs'!DC4)/('Group Inputs'!CZ4-'Group Inputs'!DA4)),2) -> 80.23 | G63: =ROUND(IF(('Group Inputs'!CZ5-'Group Inputs'!DA5)=0,0,100*('Group Inputs'!DB5-'Group Inputs'!DC5)/('Group Inputs'!CZ5-'Group Inputs'!DA5)),2) -> 82.15 | H63: =ROUND(IF(('Group Inputs'!CZ6-'Group Inputs'!DA6)=0,0,100*('Group Inputs'!DB6-'Group Inputs'!DC6)/('Group Inputs'!CZ6-'Group Inputs'!DA6)),2) -> 78.55 | I63: =ROUND(IF(('Group Inputs'!CZ7-'Group Inputs'!DA7)=0,0,100*('Group Inputs'!DB7-'Group Inputs'!DC7)/('Group Inputs'!CZ7-'Group Inputs'!DA7)),2) -> 80.32 | J63: =ROUND(IF(('Group Inputs'!CZ8-'Group Inputs'!DA8)=0,0,100*('Group Inputs'!DB8-'Group Inputs'!DC8)/('Group Inputs'!CZ8-'Group Inputs'!DA8)),2) -> 71.35 | K63: =ROUND(IF(('Group Inputs'!CZ9-'Group Inputs'!DA9)=0,0,100*('Group Inputs'!DB9-'Group Inputs'!DC9)/('Group Inputs'!CZ9-'Group Inputs'!DA9)),2) -> 75.83
A64: TRS-004 | B64: Hedge cover, next 6 months | C64: % | D64: Next 6 months | E64: Foreign-currency flows hedged ÷ Forecast foreign-currency flows, next 6 months × 100 | F64: =ROUND(IF('Group Inputs'!DF4=0,0,100*'Group Inputs'!DG4/'Group Inputs'!DF4),2) -> 70.22 | G64: =ROUND(IF('Group Inputs'!DF5=0,0,100*'Group Inputs'!DG5/'Group Inputs'!DF5),2) -> 71.1 | H64: =ROUND(IF('Group Inputs'!DF6=0,0,100*'Group Inputs'!DG6/'Group Inputs'!DF6),2) -> 69.89 | I64: =ROUND(IF('Group Inputs'!DF7=0,0,100*'Group Inputs'!DG7/'Group Inputs'!DF7),2) -> 68.44 | J64: =ROUND(IF('Group Inputs'!DF8=0,0,100*'Group Inputs'!DG8/'Group Inputs'!DF8),2) -> 69.67 | K64: =ROUND(IF('Group Inputs'!DF9=0,0,100*'Group Inputs'!DG9/'Group Inputs'!DF9),2) -> 70.65
A65: TRS-005 | B65: FX sensitivity, 5% USD move | C65: ₹ m | D65: Month end | E65: 5% × (USD exposure − USD hedged) ÷ 1000 | F65: =ROUND(0.05*('Group Inputs'!DB4-'Group Inputs'!DC4)/1000,2) -> 7.65 | G65: =ROUND(0.05*('Group Inputs'!DB5-'Group Inputs'!DC5)/1000,2) -> 8.52 | H65: =ROUND(0.05*('Group Inputs'!DB6-'Group Inputs'!DC6)/1000,2) -> 7.39 | I65: =ROUND(0.05*('Group Inputs'!DB7-'Group Inputs'!DC7)/1000,2) -> 9.15 | J65: =ROUND(0.05*('Group Inputs'!DB8-'Group Inputs'!DC8)/1000,2) -> 8.05 | K65: =ROUND(0.05*('Group Inputs'!DB9-'Group Inputs'!DC9)/1000,2) -> 8.41
A66: CPX-001 | B66: Approved capex budget | C66: ₹ m | D66: Full year | E66: Approved capex budget ÷ 1000 | F66: =ROUND('Group Inputs'!DH4/1000,2) -> 1860 | G66: =ROUND('Group Inputs'!DH5/1000,2) -> 1860 | H66: =ROUND('Group Inputs'!DH6/1000,2) -> 1860 | I66: =ROUND('Group Inputs'!DH7/1000,2) -> 1860 | J66: =ROUND('Group Inputs'!DH8/1000,2) -> 1860 | K66: =ROUND('Group Inputs'!DH9/1000,2) -> 1860
A67: CPX-002 | B67: Committed capex | C67: ₹ m | D67: To date | E67: Capex committed to date ÷ 1000 | F67: =ROUND('Group Inputs'!DI4/1000,2) -> 838.53 | G67: =ROUND('Group Inputs'!DI5/1000,2) -> 933.32 | H67: =ROUND('Group Inputs'!DI6/1000,2) -> 1037.26 | I67: =ROUND('Group Inputs'!DI7/1000,2) -> 1134.85 | J67: =ROUND('Group Inputs'!DI8/1000,2) -> 1238.53 | K67: =ROUND('Group Inputs'!DI9/1000,2) -> 1347.73
A68: CPX-003 | B68: Capex actual spend YTD | C68: ₹ m | D68: Year to date | E68: Sum of capex spent since April ÷ 1000 | F68: =ROUND(SUM('Group Inputs'!DJ$4:DJ4)/1000,2) -> 146.56 | G68: =ROUND(SUM('Group Inputs'!DJ$4:DJ5)/1000,2) -> 291.62 | H68: =ROUND(SUM('Group Inputs'!DJ$4:DJ6)/1000,2) -> 435.28 | I68: =ROUND(SUM('Group Inputs'!DJ$4:DJ7)/1000,2) -> 582.9 | J68: =ROUND(SUM('Group Inputs'!DJ$4:DJ8)/1000,2) -> 734.84 | K68: =ROUND(SUM('Group Inputs'!DJ$4:DJ9)/1000,2) -> 879.71
A69: CPX-004 | B69: Capex physical progress, weighted | C69: % | D69: To date | E69: Work completed valued at budget ÷ Approved budget × 100 (weights each project by its budget) | F69: =ROUND(IF('Group Inputs'!DH4=0,0,100*'Group Inputs'!DK4/'Group Inputs'!DH4),2) -> 38 | G69: =ROUND(IF('Group Inputs'!DH5=0,0,100*'Group Inputs'!DK5/'Group Inputs'!DH5),2) -> 42.57 | H69: =ROUND(IF('Group Inputs'!DH6=0,0,100*'Group Inputs'!DK6/'Group Inputs'!DH6),2) -> 47.14 | I69: =ROUND(IF('Group Inputs'!DH7=0,0,100*'Group Inputs'!DK7/'Group Inputs'!DH7),2) -> 51.71 | J69: =ROUND(IF('Group Inputs'!DH8=0,0,100*'Group Inputs'!DK8/'Group Inputs'!DH8),2) -> 56.28 | K69: =ROUND(IF('Group Inputs'!DH9=0,0,100*'Group Inputs'!DK9/'Group Inputs'!DH9),2) -> 60.85
A70: SIG-011 | B70: Capex value at risk | C70: ₹ m | D70: Month end | E70: Budget of projects at risk ÷ 1000 | F70: =ROUND('Group Inputs'!DL4/1000,2) -> 139.24 | G70: =ROUND('Group Inputs'!DL5/1000,2) -> 161.83 | H70: =ROUND('Group Inputs'!DL6/1000,2) -> 152.29 | I70: =ROUND('Group Inputs'!DL7/1000,2) -> 153.97 | J70: =ROUND('Group Inputs'!DL8/1000,2) -> 153.09 | K70: =ROUND('Group Inputs'!DL9/1000,2) -> 148.03
A71: PRG-001 | B71: Capex project status | C71: text | D71: Month end | E71: Count of projects by status | F71: ='Group Inputs'!DM4&" on track · "&'Group Inputs'!DN4&" at risk · "&'Group Inputs'!DO4&" off track" -> 9 on track · 2 at risk · 0 off track | G71: ='Group Inputs'!DM5&" on track · "&'Group Inputs'!DN5&" at risk · "&'Group Inputs'!DO5&" off track" -> 9 on track · 2 at risk · 0 off track | H71: ='Group Inputs'!DM6&" on track · "&'Group Inputs'!DN6&" at risk · "&'Group Inputs'!DO6&" off track" -> 9 on track · 2 at risk · 0 off track | I71: ='Group Inputs'!DM7&" on track · "&'Group Inputs'!DN7&" at risk · "&'Group Inputs'!DO7&" off track" -> 9 on track · 2 at risk · 0 off track | J71: ='Group Inputs'!DM8&" on track · "&'Group Inputs'!DN8&" at risk · "&'Group Inputs'!DO8&" off track" -> 9 on track · 2 at risk · 0 off track | K71: ='Group Inputs'!DM9&" on track · "&'Group Inputs'!DN9&" at risk · "&'Group Inputs'!DO9&" off track" -> 9 on track · 2 at risk · 0 off track
A72: PRG-002 | B72: Benefits realisation | C72: % | D72: Year to date | E72: Benefits delivered since April ÷ Benefits planned since April × 100 | F72: =ROUND(IF(SUM('Group Inputs'!DX$4:DX4)=0,0,100*SUM('Group Inputs'!DY$4:DY4)/SUM('Group Inputs'!DX$4:DX4)),2) -> 46.69 | G72: =ROUND(IF(SUM('Group Inputs'!DX$4:DX5)=0,0,100*SUM('Group Inputs'!DY$4:DY5)/SUM('Group Inputs'!DX$4:DX5)),2) -> 47.85 | H72: =ROUND(IF(SUM('Group Inputs'!DX$4:DX6)=0,0,100*SUM('Group Inputs'!DY$4:DY6)/SUM('Group Inputs'!DX$4:DX6)),2) -> 47.74 | I72: =ROUND(IF(SUM('Group Inputs'!DX$4:DX7)=0,0,100*SUM('Group Inputs'!DY$4:DY7)/SUM('Group Inputs'!DX$4:DX7)),2) -> 48.04 | J72: =ROUND(IF(SUM('Group Inputs'!DX$4:DX8)=0,0,100*SUM('Group Inputs'!DY$4:DY8)/SUM('Group Inputs'!DX$4:DX8)),2) -> 48.1 | K72: =ROUND(IF(SUM('Group Inputs'!DX$4:DX9)=0,0,100*SUM('Group Inputs'!DY$4:DY9)/SUM('Group Inputs'!DX$4:DX9)),2) -> 47.96
A73: PRG-003 | B73: Delayed projects | C73: count | D73: Month end | E73: Capex projects delayed | F73: =ROUND('Group Inputs'!DP4,2) -> 0 | G73: =ROUND('Group Inputs'!DP5,2) -> 0 | H73: =ROUND('Group Inputs'!DP6,2) -> 0 | I73: =ROUND('Group Inputs'!DP7,2) -> 1 | J73: =ROUND('Group Inputs'!DP8,2) -> 1 | K73: =ROUND('Group Inputs'!DP9,2) -> 1
A74: PRG-004 | B74: Capex / transformation progress (same measure as STR-002) | C74: % | D74: To date | E74: Transformation milestones completed ÷ Milestones in plan × 100 | F74: =ROUND(IF('Group Inputs'!DV4=0,0,100*'Group Inputs'!DW4/'Group Inputs'!DV4),2) -> 29.84 | G74: =ROUND(IF('Group Inputs'!DV5=0,0,100*'Group Inputs'!DW5/'Group Inputs'!DV5),2) -> 34.68 | H74: =ROUND(IF('Group Inputs'!DV6=0,0,100*'Group Inputs'!DW6/'Group Inputs'!DV6),2) -> 39.52 | I74: =ROUND(IF('Group Inputs'!DV7=0,0,100*'Group Inputs'!DW7/'Group Inputs'!DV7),2) -> 44.35 | J74: =ROUND(IF('Group Inputs'!DV8=0,0,100*'Group Inputs'!DW8/'Group Inputs'!DV8),2) -> 49.19 | K74: =ROUND(IF('Group Inputs'!DV9=0,0,100*'Group Inputs'!DW9/'Group Inputs'!DV9),2) -> 54.03
A75: STR-002 | B75: Transformation progress | C75: % | D75: To date | E75: Transformation milestones completed ÷ Milestones in plan × 100 | F75: =ROUND(IF('Group Inputs'!DV4=0,0,100*'Group Inputs'!DW4/'Group Inputs'!DV4),2) -> 29.84 | G75: =ROUND(IF('Group Inputs'!DV5=0,0,100*'Group Inputs'!DW5/'Group Inputs'!DV5),2) -> 34.68 | H75: =ROUND(IF('Group Inputs'!DV6=0,0,100*'Group Inputs'!DW6/'Group Inputs'!DV6),2) -> 39.52 | I75: =ROUND(IF('Group Inputs'!DV7=0,0,100*'Group Inputs'!DW7/'Group Inputs'!DV7),2) -> 44.35 | J75: =ROUND(IF('Group Inputs'!DV8=0,0,100*'Group Inputs'!DW8/'Group Inputs'!DV8),2) -> 49.19 | K75: =ROUND(IF('Group Inputs'!DV9=0,0,100*'Group Inputs'!DW9/'Group Inputs'!DV9),2) -> 54.03
A76: PRG-005 | B76: Transformation initiative status | C76: text | D76: Month end | E76: Count of transformation initiatives by status | F76: ='Group Inputs'!DS4&" on track · "&'Group Inputs'!DT4&" at risk · "&'Group Inputs'!DU4&" delayed" -> 15 on track · 6 at risk · 3 delayed | G76: ='Group Inputs'!DS5&" on track · "&'Group Inputs'!DT5&" at risk · "&'Group Inputs'!DU5&" delayed" -> 15 on track · 6 at risk · 3 delayed | H76: ='Group Inputs'!DS6&" on track · "&'Group Inputs'!DT6&" at risk · "&'Group Inputs'!DU6&" delayed" -> 15 on track · 6 at risk · 3 delayed | I76: ='Group Inputs'!DS7&" on track · "&'Group Inputs'!DT7&" at risk · "&'Group Inputs'!DU7&" delayed" -> 15 on track · 6 at risk · 3 delayed | J76: ='Group Inputs'!DS8&" on track · "&'Group Inputs'!DT8&" at risk · "&'Group Inputs'!DU8&" delayed" -> 15 on track · 6 at risk · 3 delayed | K76: ='Group Inputs'!DS9&" on track · "&'Group Inputs'!DT9&" at risk · "&'Group Inputs'!DU9&" delayed" -> 15 on track · 6 at risk · 3 delayed
A77: SUP-006 | B77: Contractor slippage | C77: days | D77: Month | E77: Contractor days late ÷ Contractor milestones due (average days late per milestone) | F77: =ROUND(IF('Group Inputs'!DQ4=0,0,'Group Inputs'!DR4/'Group Inputs'!DQ4),2) -> 2.36 | G77: =ROUND(IF('Group Inputs'!DQ5=0,0,'Group Inputs'!DR5/'Group Inputs'!DQ5),2) -> 2.2 | H77: =ROUND(IF('Group Inputs'!DQ6=0,0,'Group Inputs'!DR6/'Group Inputs'!DQ6),2) -> 2.18 | I77: =ROUND(IF('Group Inputs'!DQ7=0,0,'Group Inputs'!DR7/'Group Inputs'!DQ7),2) -> 2.1 | J77: =ROUND(IF('Group Inputs'!DQ8=0,0,'Group Inputs'!DR8/'Group Inputs'!DQ8),2) -> 2.15 | K77: =ROUND(IF('Group Inputs'!DQ9=0,0,'Group Inputs'!DR9/'Group Inputs'!DQ9),2) -> 1.73
A78: VAL-001 | B78: EBITDA benefit YTD | C78: ₹ m | D78: Year to date | E78: Sum of EBITDA benefit since April ÷ 1000 | F78: =ROUND(SUM('Group Inputs'!DZ$4:DZ4)/1000,2) -> 2.36 | G78: =ROUND(SUM('Group Inputs'!DZ$4:DZ5)/1000,2) -> 4.7 | H78: =ROUND(SUM('Group Inputs'!DZ$4:DZ6)/1000,2) -> 7.09 | I78: =ROUND(SUM('Group Inputs'!DZ$4:DZ7)/1000,2) -> 9.47 | J78: =ROUND(SUM('Group Inputs'!DZ$4:DZ8)/1000,2) -> 11.86 | K78: =ROUND(SUM('Group Inputs'!DZ$4:DZ9)/1000,2) -> 14.21
A79: VAL-002 | B79: Cash benefit YTD | C79: ₹ m | D79: Year to date | E79: Sum of cash benefit since April ÷ 1000 | F79: =ROUND(SUM('Group Inputs'!EA$4:EA4)/1000,2) -> 1.44 | G79: =ROUND(SUM('Group Inputs'!EA$4:EA5)/1000,2) -> 2.94 | H79: =ROUND(SUM('Group Inputs'!EA$4:EA6)/1000,2) -> 4.37 | I79: =ROUND(SUM('Group Inputs'!EA$4:EA7)/1000,2) -> 5.86 | J79: =ROUND(SUM('Group Inputs'!EA$4:EA8)/1000,2) -> 7.28 | K79: =ROUND(SUM('Group Inputs'!EA$4:EA9)/1000,2) -> 8.71
A80: VAL-003 | B80: Cost savings delivered YTD | C80: ₹ m | D80: Year to date | E80: Sum of cost savings since April ÷ 1000 | F80: =ROUND(SUM('Group Inputs'!EB$4:EB4)/1000,2) -> 1.77 | G80: =ROUND(SUM('Group Inputs'!EB$4:EB5)/1000,2) -> 3.67 | H80: =ROUND(SUM('Group Inputs'!EB$4:EB6)/1000,2) -> 5.56 | I80: =ROUND(SUM('Group Inputs'!EB$4:EB7)/1000,2) -> 7.47 | J80: =ROUND(SUM('Group Inputs'!EB$4:EB8)/1000,2) -> 9.36 | K80: =ROUND(SUM('Group Inputs'!EB$4:EB9)/1000,2) -> 11.25
A81: SUP-001 | B81: Supplier on-time delivery | C81: % | D81: Month | E81: Purchase-order lines on time ÷ Lines due × 100 | F81: =ROUND(IF('Group Inputs'!AY4=0,0,100*'Group Inputs'!AZ4/'Group Inputs'!AY4),2) -> 91.11 | G81: =ROUND(IF('Group Inputs'!AY5=0,0,100*'Group Inputs'!AZ5/'Group Inputs'!AY5),2) -> 91.39 | H81: =ROUND(IF('Group Inputs'!AY6=0,0,100*'Group Inputs'!AZ6/'Group Inputs'!AY6),2) -> 92.06 | I81: =ROUND(IF('Group Inputs'!AY7=0,0,100*'Group Inputs'!AZ7/'Group Inputs'!AY7),2) -> 91.89 | J81: =ROUND(IF('Group Inputs'!AY8=0,0,100*'Group Inputs'!AZ8/'Group Inputs'!AY8),2) -> 91.17 | K81: =ROUND(IF('Group Inputs'!AY9=0,0,100*'Group Inputs'!AZ9/'Group Inputs'!AY9),2) -> 91.41
A82: SUP-002 | B82: Supplier fill rate | C82: % | D82: Month | E82: Quantity received ÷ Quantity ordered × 100 | F82: =ROUND(IF('Group Inputs'!BA4=0,0,100*'Group Inputs'!BB4/'Group Inputs'!BA4),2) -> 95.96 | G82: =ROUND(IF('Group Inputs'!BA5=0,0,100*'Group Inputs'!BB5/'Group Inputs'!BA5),2) -> 95.52 | H82: =ROUND(IF('Group Inputs'!BA6=0,0,100*'Group Inputs'!BB6/'Group Inputs'!BA6),2) -> 96.93 | I82: =ROUND(IF('Group Inputs'!BA7=0,0,100*'Group Inputs'!BB7/'Group Inputs'!BA7),2) -> 95.87 | J82: =ROUND(IF('Group Inputs'!BA8=0,0,100*'Group Inputs'!BB8/'Group Inputs'!BA8),2) -> 96.93 | K82: =ROUND(IF('Group Inputs'!BA9=0,0,100*'Group Inputs'!BB9/'Group Inputs'!BA9),2) -> 96.82
A83: SUP-003 | B83: Supplier quality-rejection rate | C83: % | D83: Month | E83: Quantity rejected ÷ Quantity received × 100 | F83: =ROUND(IF('Group Inputs'!BB4=0,0,100*'Group Inputs'!BC4/'Group Inputs'!BB4),2) -> 1.19 | G83: =ROUND(IF('Group Inputs'!BB5=0,0,100*'Group Inputs'!BC5/'Group Inputs'!BB5),2) -> 0.93 | H83: =ROUND(IF('Group Inputs'!BB6=0,0,100*'Group Inputs'!BC6/'Group Inputs'!BB6),2) -> 0.87 | I83: =ROUND(IF('Group Inputs'!BB7=0,0,100*'Group Inputs'!BC7/'Group Inputs'!BB7),2) -> 0.9 | J83: =ROUND(IF('Group Inputs'!BB8=0,0,100*'Group Inputs'!BC8/'Group Inputs'!BB8),2) -> 1.33 | K83: =ROUND(IF('Group Inputs'!BB9=0,0,100*'Group Inputs'!BC9/'Group Inputs'!BB9),2) -> 1.12
A84: SUP-004 | B84: Supplier lead-time variance | C84: % | D84: Month | E84: (Actual lead time − Planned lead time) ÷ Planned lead time × 100 | F84: =ROUND(IF('Group Inputs'!BD4=0,0,100*('Group Inputs'!BE4-'Group Inputs'!BD4)/'Group Inputs'!BD4),2) -> 5.29 | G84: =ROUND(IF('Group Inputs'!BD5=0,0,100*('Group Inputs'!BE5-'Group Inputs'!BD5)/'Group Inputs'!BD5),2) -> 2.93 | H84: =ROUND(IF('Group Inputs'!BD6=0,0,100*('Group Inputs'!BE6-'Group Inputs'!BD6)/'Group Inputs'!BD6),2) -> 3.18 | I84: =ROUND(IF('Group Inputs'!BD7=0,0,100*('Group Inputs'!BE7-'Group Inputs'!BD7)/'Group Inputs'!BD7),2) -> 2.48 | J84: =ROUND(IF('Group Inputs'!BD8=0,0,100*('Group Inputs'!BE8-'Group Inputs'!BD8)/'Group Inputs'!BD8),2) -> 2.53 | K84: =ROUND(IF('Group Inputs'!BD9=0,0,100*('Group Inputs'!BE9-'Group Inputs'!BD9)/'Group Inputs'!BD9),2) -> 5.25
A85: SUP-005 | B85: Critical supplier exposure | C85: count | D85: Month end | E85: Critical single-source suppliers | F85: =ROUND('Group Inputs'!EG4,2) -> 3 | G85: =ROUND('Group Inputs'!EG5,2) -> 3 | H85: =ROUND('Group Inputs'!EG6,2) -> 3 | I85: =ROUND('Group Inputs'!EG7,2) -> 3 | J85: =ROUND('Group Inputs'!EG8,2) -> 3 | K85: =ROUND('Group Inputs'!EG9,2) -> 3
A86: SUP-007 | B86: Single-source spend share | C86: % | D86: Month | E86: Spend with single-source suppliers ÷ Supplier spend × 100 | F86: =ROUND(IF('Group Inputs'!BF4=0,0,100*'Group Inputs'!BG4/'Group Inputs'!BF4),2) -> 34.56 | G86: =ROUND(IF('Group Inputs'!BF5=0,0,100*'Group Inputs'!BG5/'Group Inputs'!BF5),2) -> 36.53 | H86: =ROUND(IF('Group Inputs'!BF6=0,0,100*'Group Inputs'!BG6/'Group Inputs'!BF6),2) -> 37.4 | I86: =ROUND(IF('Group Inputs'!BF7=0,0,100*'Group Inputs'!BG7/'Group Inputs'!BF7),2) -> 36.17 | J86: =ROUND(IF('Group Inputs'!BF8=0,0,100*'Group Inputs'!BG8/'Group Inputs'!BF8),2) -> 36.78 | K86: =ROUND(IF('Group Inputs'!BF9=0,0,100*'Group Inputs'!BG9/'Group Inputs'!BF9),2) -> 35.19
A87: SUP-008 | B87: Supplier EHS incidents YTD | C87: count | D87: Year to date | E87: Sum of supplier EHS incidents since April | F87: =ROUND(SUM('Group Inputs'!BH$4:BH4),2) -> 0 | G87: =ROUND(SUM('Group Inputs'!BH$4:BH5),2) -> 0 | H87: =ROUND(SUM('Group Inputs'!BH$4:BH6),2) -> 1 | I87: =ROUND(SUM('Group Inputs'!BH$4:BH7),2) -> 1 | J87: =ROUND(SUM('Group Inputs'!BH$4:BH8),2) -> 1 | K87: =ROUND(SUM('Group Inputs'!BH$4:BH9),2) -> 3
A88: CON-001 | B88: Contracts expiring, next 90 days | C88: count | D88: Month end | E88: Contracts expiring in next 90 days | F88: =ROUND('Group Inputs'!EE4,2) -> 3 | G88: =ROUND('Group Inputs'!EE5,2) -> 5 | H88: =ROUND('Group Inputs'!EE6,2) -> 4 | I88: =ROUND('Group Inputs'!EE7,2) -> 5 | J88: =ROUND('Group Inputs'!EE8,2) -> 4 | K88: =ROUND('Group Inputs'!EE9,2) -> 4
A89: CON-002 | B89: Contract-compliance rate | C89: % | D89: Month end | E89: Contracts fully compliant ÷ Active contracts × 100 | F89: =ROUND(IF('Group Inputs'!EC4=0,0,100*'Group Inputs'!ED4/'Group Inputs'!EC4),2) -> 96.43 | G89: =ROUND(IF('Group Inputs'!EC5=0,0,100*'Group Inputs'!ED5/'Group Inputs'!EC5),2) -> 95 | H89: =ROUND(IF('Group Inputs'!EC6=0,0,100*'Group Inputs'!ED6/'Group Inputs'!EC6),2) -> 96.43 | I89: =ROUND(IF('Group Inputs'!EC7=0,0,100*'Group Inputs'!ED7/'Group Inputs'!EC7),2) -> 95 | J89: =ROUND(IF('Group Inputs'!EC8=0,0,100*'Group Inputs'!ED8/'Group Inputs'!EC8),2) -> 95 | K89: =ROUND(IF('Group Inputs'!EC9=0,0,100*'Group Inputs'!ED9/'Group Inputs'!EC9),2) -> 95.71
A90: CON-003 | B90: Supplier EHS non-compliance | C90: count | D90: Month end | E90: Suppliers not meeting EHS requirements | F90: =ROUND('Group Inputs'!EF4,2) -> 1 | G90: =ROUND('Group Inputs'!EF5,2) -> 1 | H90: =ROUND('Group Inputs'!EF6,2) -> 0 | I90: =ROUND('Group Inputs'!EF7,2) -> 1 | J90: =ROUND('Group Inputs'!EF8,2) -> 0 | K90: =ROUND('Group Inputs'!EF9,2) -> 0
A91: REG-001 | B91: Pending filings | C91: count | D91: Month end | E91: Regulatory filings pending | F91: =ROUND('Group Inputs'!BI4,2) -> 3 | G91: =ROUND('Group Inputs'!BI5,2) -> 3 | H91: =ROUND('Group Inputs'!BI6,2) -> 1 | I91: =ROUND('Group Inputs'!BI7,2) -> 1 | J91: =ROUND('Group Inputs'!BI8,2) -> 0 | K91: =ROUND('Group Inputs'!BI9,2) -> 0
A92: REG-002 | B92: Regulatory deadlines, next 30 days | C92: count | D92: Month end | E92: Regulatory deadlines in next 30 days | F92: =ROUND('Group Inputs'!BJ4,2) -> 2 | G92: =ROUND('Group Inputs'!BJ5,2) -> 1 | H92: =ROUND('Group Inputs'!BJ6,2) -> 2 | I92: =ROUND('Group Inputs'!BJ7,2) -> 2 | J92: =ROUND('Group Inputs'!BJ8,2) -> 0 | K92: =ROUND('Group Inputs'!BJ9,2) -> 3
A93: REG-003 | B93: Licence expirations, next 12 months | C93: count | D93: Month end | E93: Licences expiring in next 12 months | F93: =ROUND('Group Inputs'!BK4,2) -> 3 | G93: =ROUND('Group Inputs'!BK5,2) -> 1 | H93: =ROUND('Group Inputs'!BK6,2) -> 3 | I93: =ROUND('Group Inputs'!BK7,2) -> 2 | J93: =ROUND('Group Inputs'!BK8,2) -> 2 | K93: =ROUND('Group Inputs'!BK9,2) -> 1
A94: REG-004 | B94: Regulatory obligations due, next 30 days | C94: count | D94: Month end | E94: Regulatory obligations due in next 30 days | F94: =ROUND('Group Inputs'!BL4,2) -> 4 | G94: =ROUND('Group Inputs'!BL5,2) -> 2 | H94: =ROUND('Group Inputs'!BL6,2) -> 4 | I94: =ROUND('Group Inputs'!BL7,2) -> 4 | J94: =ROUND('Group Inputs'!BL8,2) -> 4 | K94: =ROUND('Group Inputs'!BL9,2) -> 2
A95: REG-005 | B95: Overdue regulatory obligations | C95: count | D95: Month end | E95: Regulatory obligations overdue | F95: =ROUND('Group Inputs'!BM4,2) -> 0 | G95: =ROUND('Group Inputs'!BM5,2) -> 0 | H95: =ROUND('Group Inputs'!BM6,2) -> 0 | I95: =ROUND('Group Inputs'!BM7,2) -> 0 | J95: =ROUND('Group Inputs'!BM8,2) -> 0 | K95: =ROUND('Group Inputs'!BM9,2) -> 0
A96: REG-007 | B96: Open regulatory actions | C96: count | D96: Month end | E96: Open regulatory actions | F96: =ROUND('Group Inputs'!BN4,2) -> 0 | G96: =ROUND('Group Inputs'!BN5,2) -> 1 | H96: =ROUND('Group Inputs'!BN6,2) -> 0 | I96: =ROUND('Group Inputs'!BN7,2) -> 1 | J96: =ROUND('Group Inputs'!BN8,2) -> 1 | K96: =ROUND('Group Inputs'!BN9,2) -> 0
A97: REG-008 | B97: Overdue compliance actions | C97: count | D97: Month end | E97: Overdue compliance actions | F97: =ROUND('Group Inputs'!BO4,2) -> 0 | G97: =ROUND('Group Inputs'!BO5,2) -> 0 | H97: =ROUND('Group Inputs'!BO6,2) -> 0 | I97: =ROUND('Group Inputs'!BO7,2) -> 0 | J97: =ROUND('Group Inputs'!BO8,2) -> 0 | K97: =ROUND('Group Inputs'!BO9,2) -> 0
A98: REG-009 | B98: Disclosure-clock status | C98: text | D98: Month end | E98: Triggered if any event that needs disclosure is open, otherwise Not triggered | F98: =IF('Group Inputs'!BQ4>0,"Triggered","Not triggered") -> Not triggered | G98: =IF('Group Inputs'!BQ5>0,"Triggered","Not triggered") -> Not triggered | H98: =IF('Group Inputs'!BQ6>0,"Triggered","Not triggered") -> Not triggered | I98: =IF('Group Inputs'!BQ7>0,"Triggered","Not triggered") -> Not triggered | J98: =IF('Group Inputs'!BQ8>0,"Triggered","Not triggered") -> Not triggered | K98: =IF('Group Inputs'!BQ9>0,"Triggered","Not triggered") -> Not triggered
A99: REG-010 | B99: Regulatory breaches YTD | C99: count | D99: Year to date | E99: Sum of regulatory breaches since April | F99: =ROUND(SUM('Group Inputs'!BP$4:BP4),2) -> 0 | G99: =ROUND(SUM('Group Inputs'!BP$4:BP5),2) -> 0 | H99: =ROUND(SUM('Group Inputs'!BP$4:BP6),2) -> 0 | I99: =ROUND(SUM('Group Inputs'!BP$4:BP7),2) -> 0 | J99: =ROUND(SUM('Group Inputs'!BP$4:BP8),2) -> 0 | K99: =ROUND(SUM('Group Inputs'!BP$4:BP9),2) -> 0
A100: RSK-003 | B100: Regulatory breaches YTD (same measure as REG-010) | C100: count | D100: Year to date | E100: Sum of regulatory breaches since April | F100: =ROUND(SUM('Group Inputs'!BP$4:BP4),2) -> 0 | G100: =ROUND(SUM('Group Inputs'!BP$4:BP5),2) -> 0 | H100: =ROUND(SUM('Group Inputs'!BP$4:BP6),2) -> 0 | I100: =ROUND(SUM('Group Inputs'!BP$4:BP7),2) -> 0 | J100: =ROUND(SUM('Group Inputs'!BP$4:BP8),2) -> 0 | K100: =ROUND(SUM('Group Inputs'!BP$4:BP9),2) -> 0
...

Sheet Entity KPIs
A1: KPI ID | B1: Measure | C1: Unit | D1: Time basis | E1: How it is calculated | F1: Entity A1 · 2026-04 (P01) | G1: Entity A1 · 2026-05 (P02) | H1: Entity A1 · 2026-06 (P03) | I1: Entity A1 · 2026-07 (P04) | J1: Entity A1 · 2026-08 (P05) | K1: Entity A1 · 2026-09 (P06) | L1: Entity A2 · 2026-04 (P01) | M1: Entity A2 · 2026-05 (P02) | N1: Entity A2 · 2026-06 (P03) | O1: Entity A2 · 2026-07 (P04) | P1: Entity A2 · 2026-08 (P05) | Q1: Entity A2 · 2026-09 (P06)
A2: OPS-001 | B2: Production vs plan | C2: % | D2: Month | E2: Good output ÷ Planned production × 100 | F2: =ROUND(IFERROR(100*'Entity Inputs'!N4/'Entity Inputs'!L4,0),2) -> 92.81 | G2: =ROUND(IFERROR(100*'Entity Inputs'!N5/'Entity Inputs'!L5,0),2) -> 87.09 | H2: =ROUND(IFERROR(100*'Entity Inputs'!N6/'Entity Inputs'!L6,0),2) -> 86.25 | I2: =ROUND(IFERROR(100*'Entity Inputs'!N7/'Entity Inputs'!L7,0),2) -> 91.02 | J2: =ROUND(IFERROR(100*'Entity Inputs'!N8/'Entity Inputs'!L8,0),2) -> 88.58 | K2: =ROUND(IFERROR(100*'Entity Inputs'!N9/'Entity Inputs'!L9,0),2) -> 91.27 | L2: =ROUND(IFERROR(100*'Entity Inputs'!N10/'Entity Inputs'!L10,0),2) -> 100.1 | M2: =ROUND(IFERROR(100*'Entity Inputs'!N11/'Entity Inputs'!L11,0),2) -> 96.75 | N2: =ROUND(IFERROR(100*'Entity Inputs'!N12/'Entity Inputs'!L12,0),2) -> 94.03 | O2: =ROUND(IFERROR(100*'Entity Inputs'!N13/'Entity Inputs'!L13,0),2) -> 97.3 | P2: =ROUND(IFERROR(100*'Entity Inputs'!N14/'Entity Inputs'!L14,0),2) -> 96.69 | Q2: =ROUND(IFERROR(100*'Entity Inputs'!N15/'Entity Inputs'!L15,0),2) -> 100.29
A3: OPS-003 | B3: Capacity utilization | C3: % | D3: Month | E3: Good output ÷ Installed capacity × 100 | F3: =ROUND(IFERROR(100*'Entity Inputs'!N4/'Entity Inputs'!K4,0),2) -> 80.9 | G3: =ROUND(IFERROR(100*'Entity Inputs'!N5/'Entity Inputs'!K5,0),2) -> 73.48 | H3: =ROUND(IFERROR(100*'Entity Inputs'!N6/'Entity Inputs'!K6,0),2) -> 76.11 | I3: =ROUND(IFERROR(100*'Entity Inputs'!N7/'Entity Inputs'!K7,0),2) -> 78.51 | J3: =ROUND(IFERROR(100*'Entity Inputs'!N8/'Entity Inputs'!K8,0),2) -> 76.19 | K3: =ROUND(IFERROR(100*'Entity Inputs'!N9/'Entity Inputs'!K9,0),2) -> 79.8 | L3: =ROUND(IFERROR(100*'Entity Inputs'!N10/'Entity Inputs'!K10,0),2) -> 87.44 | M3: =ROUND(IFERROR(100*'Entity Inputs'!N11/'Entity Inputs'!K11,0),2) -> 79.28 | N3: =ROUND(IFERROR(100*'Entity Inputs'!N12/'Entity Inputs'!K12,0),2) -> 83.9 | O3: =ROUND(IFERROR(100*'Entity Inputs'!N13/'Entity Inputs'!K13,0),2) -> 86.58 | P3: =ROUND(IFERROR(100*'Entity Inputs'!N14/'Entity Inputs'!K14,0),2) -> 81.88 | Q3: =ROUND(IFERROR(100*'Entity Inputs'!N15/'Entity Inputs'!K15,0),2) -> 87.55
A4: PLT-001 | B4: Asset utilization | C4: % | D4: Month | E4: Run hours ÷ Calendar hours × 100 | F4: =ROUND(IFERROR(100*'Entity Inputs'!H4/'Entity Inputs'!F4,0),2) -> 94.75 | G4: =ROUND(IFERROR(100*'Entity Inputs'!H5/'Entity Inputs'!F5,0),2) -> 88.59 | H4: =ROUND(IFERROR(100*'Entity Inputs'!H6/'Entity Inputs'!F6,0),2) -> 93.69 | I4: =ROUND(IFERROR(100*'Entity Inputs'!H7/'Entity Inputs'!F7,0),2) -> 92.06 | J4: =ROUND(IFERROR(100*'Entity Inputs'!H8/'Entity Inputs'!F8,0),2) -> 90.77 | K4: =ROUND(IFERROR(100*'Entity Inputs'!H9/'Entity Inputs'!F9,0),2) -> 91.86 | L4: =ROUND(IFERROR(100*'Entity Inputs'!H10/'Entity Inputs'!F10,0),2) -> 95.69 | M4: =ROUND(IFERROR(100*'Entity Inputs'!H11/'Entity Inputs'!F11,0),2) -> 88.83 | N4: =ROUND(IFERROR(100*'Entity Inputs'!H12/'Entity Inputs'!F12,0),2) -> 94.43 | O4: =ROUND(IFERROR(100*'Entity Inputs'!H13/'Entity Inputs'!F13,0),2) -> 95.13 | P4: =ROUND(IFERROR(100*'Entity Inputs'!H14/'Entity Inputs'!F14,0),2) -> 89.43 | Q4: =ROUND(IFERROR(100*'Entity Inputs'!H15/'Entity Inputs'!F15,0),2) -> 95.43
A5: PLT-002 | B5: OEE | C5: % | D5: Month | E5: Availability × Performance × Quality = Good output ÷ Ideal output × 100 | F5: =ROUND(IFERROR(100*'Entity Inputs'!N4/'Entity Inputs'!J4,0),2) -> 81.65 | G5: =ROUND(IFERROR(100*'Entity Inputs'!N5/'Entity Inputs'!J5,0),2) -> 78.4 | H5: =ROUND(IFERROR(100*'Entity Inputs'!N6/'Entity Inputs'!J6,0),2) -> 76.22 | I5: =ROUND(IFERROR(100*'Entity Inputs'!N7/'Entity Inputs'!J7,0),2) -> 79.11 | J5: =ROUND(IFERROR(100*'Entity Inputs'!N8/'Entity Inputs'!J8,0),2) -> 78.73 | K5: =ROUND(IFERROR(100*'Entity Inputs'!N9/'Entity Inputs'!J9,0),2) -> 80.21 | L5: =ROUND(IFERROR(100*'Entity Inputs'!N10/'Entity Inputs'!J10,0),2) -> 88.21 | M5: =ROUND(IFERROR(100*'Entity Inputs'!N11/'Entity Inputs'!J11,0),2) -> 85.07 | N5: =ROUND(IFERROR(100*'Entity Inputs'!N12/'Entity Inputs'!J12,0),2) -> 84.77 | O5: =ROUND(IFERROR(100*'Entity Inputs'!N13/'Entity Inputs'!J13,0),2) -> 86.9 | P5: =ROUND(IFERROR(100*'Entity Inputs'!N14/'Entity Inputs'!J14,0),2) -> 86.21 | Q5: =ROUND(IFERROR(100*'Entity Inputs'!N15/'Entity Inputs'!J15,0),2) -> 88.44
A6: PLT-004 | B6: Recovery percentage | C6: % | D6: Month | E6: Valuable content recovered ÷ Valuable content in feed × 100 | F6: =ROUND(IFERROR(100*'Entity Inputs'!Q4/'Entity Inputs'!P4,0),2) -> 86.95 | G6: =ROUND(IFERROR(100*'Entity Inputs'!Q5/'Entity Inputs'!P5,0),2) -> 85.7 | H6: =ROUND(IFERROR(100*'Entity Inputs'!Q6/'Entity Inputs'!P6,0),2) -> 87.19 | I6: =ROUND(IFERROR(100*'Entity Inputs'!Q7/'Entity Inputs'!P7,0),2) -> 87.53 | J6: =ROUND(IFERROR(100*'Entity Inputs'!Q8/'Entity Inputs'!P8,0),2) -> 86.96 | K6: =ROUND(IFERROR(100*'Entity Inputs'!Q9/'Entity Inputs'!P9,0),2) -> 87.47 | L6: =ROUND(IFERROR(100*'Entity Inputs'!Q10/'Entity Inputs'!P10,0),2) -> 87.03 | M6: =ROUND(IFERROR(100*'Entity Inputs'!Q11/'Entity Inputs'!P11,0),2) -> 86.53 | N6: =ROUND(IFERROR(100*'Entity Inputs'!Q12/'Entity Inputs'!P12,0),2) -> 89.22 | O6: =ROUND(IFERROR(100*'Entity Inputs'!Q13/'Entity Inputs'!P13,0),2) -> 86.73 | P6: =ROUND(IFERROR(100*'Entity Inputs'!Q14/'Entity Inputs'!P14,0),2) -> 90.09 | Q6: =ROUND(IFERROR(100*'Entity Inputs'!Q15/'Entity Inputs'!P15,0),2) -> 87.23
A7: PLT-005 | B7: Yield | C7: % | D7: Month | E7: Good output ÷ Feed input × 100 | F7: =ROUND(IFERROR(100*'Entity Inputs'!N4/'Entity Inputs'!O4,0),2) -> 89.68 | G7: =ROUND(IFERROR(100*'Entity Inputs'!N5/'Entity Inputs'!O5,0),2) -> 91.9 | H7: =ROUND(IFERROR(100*'Entity Inputs'!N6/'Entity Inputs'!O6,0),2) -> 93.25 | I7: =ROUND(IFERROR(100*'Entity Inputs'!N7/'Entity Inputs'!O7,0),2) -> 89.98 | J7: =ROUND(IFERROR(100*'Entity Inputs'!N8/'Entity Inputs'!O8,0),2) -> 91.19 | K7: =ROUND(IFERROR(100*'Entity Inputs'!N9/'Entity Inputs'!O9,0),2) -> 91.46 | L7: =ROUND(IFERROR(100*'Entity Inputs'!N10/'Entity Inputs'!O10,0),2) -> 91.38 | M7: =ROUND(IFERROR(100*'Entity Inputs'!N11/'Entity Inputs'!O11,0),2) -> 92.82 | N7: =ROUND(IFERROR(100*'Entity Inputs'!N12/'Entity Inputs'!O12,0),2) -> 89.73 | O7: =ROUND(IFERROR(100*'Entity Inputs'!N13/'Entity Inputs'!O13,0),2) -> 93 | P7: =ROUND(IFERROR(100*'Entity Inputs'!N14/'Entity Inputs'!O14,0),2) -> 91 | Q7: =ROUND(IFERROR(100*'Entity Inputs'!N15/'Entity Inputs'!O15,0),2) -> 92.42
